Workbook
Name \a: #REF!
Name \a: #REF!
Name \p: #REF!
Name \p: #REF!
Name _______xlnm.Print_Titles: #REF!
Name _______xlnm_Print_Titles: NA()
Name ______xlnm._FilterDatabase: "#ref!"
Name ______xlnm.Print_Titles: #REF!
Name ______xlnm__FilterDatabase: "#ref!"
Name ______xlnm_Print_Titles: NA()
Name _____xlfn_BAHTTEXT: NA()
Name _____xlfn_SUMIFS: NA()
Name _____xlnm._FilterDatabase: "#ref!"
Name _____xlnm.Print_Titles: #REF!
Name _____xlnm__FilterDatabase: "#ref!"
Name _____xlnm_Print_Titles: NA()
Name ____xlfn_BAHTTEXT: NA()
Name ____xlfn_SUMIFS: NA()
Name ____xlnm._FilterDatabase: "#ref!"
Name ____xlnm.Print_Titles: #REF!
Name ____xlnm__FilterDatabase: "#ref!"
Name ____xlnm_Print_Titles: NA()
Name ___xlfn_BAHTTEXT: NA()
Name ___xlfn_SUMIFS: NA()
Name ___xlnm._FilterDatabase: "#ref!"
Name ___xlnm.Print_Titles: #REF!
Name ___xlnm__FilterDatabase: "#ref!"
Name ___xlnm_Print_Titles: NA()
Name __TAB3688: #REF!
Name __xlfn_BAHTTEXT: NA()
Name __xlfn_SUMIFS: NA()
Name __xlnm._FilterDatabase: "#ref!"
Name __xlnm.Print_Titles: #REF!
Name __xlnm__FilterDatabase: "#ref!"
Name __xlnm_Print_Titles: NA()
Name _TAB3688: #REF!
Name _TAB3688: #REF!
Name a: #REF!
Name abr: #REF!
Name abr: #REF!
Name abril: #REF!
Name ACRESCENTAR: #REF!
Name ADAPTADO: '[1]APONTAMENTO CREDENCIAMENTO'!#REF!
Name ADAPTADO: 'APONTAMENTO CREDENCIAMENTO'!$FF$7:$GJ$7
Name AGOSTO: #REF!
Name AI: #REF!
Name AI: #REF!
Name AII: #REF!
Name AII: #REF!
Name AK: #REF!
Name AK: #REF!
Name AL: #REF!
Name AL: #REF!
Name AMPLIAR: #REF!
Name AMPLIAR: #REF!
Name ApagaAtesteFis: 'ATESTE-LIQ-FIS'!$A$4:$K$3878
Name ApagaBaseC: 'BASE C'!$A$11:$N$4950
Name ApagaDadosA: 'APONTAMENTO CREDENCIAMENTO'!$Q$6:$EL$3029
Name ApagaDadosC: CONTINUA!$L$6:$BU$3047
Name ApagarDadosDigitados: #REF!

Sheet Planilha2
A1: Freguesia / Brasilândia | G1: ABRIL | I1: APONTAMENTO CREDENCIAMENTO | EL1: ATENÇÃO | FE1: =(552.16*30) -> 16564.8
G2: 01/06 a 30/06/2025
A3: 1 | B3: 2 | C3: 3 | D3: 1 | E3: 2 | F3: 3 | G3: 4 | H3: 5 | I3: 6 | J3: 7 | K3: 8 | L3: 9 | M3: 10 | N3: 10 | O3: 11 | P3: 13 | Q3: 14 | R3: 15 | S3: 16 | T3: 17 | U3: 18 | V3: 19 | W3: 20 | X3: 21 | Y3: 22 | Z3: 23 | AA3: 24 | AB3: 25 | AC3: 26 | AD3: 27 | AE3: 28 | AF3: 29 | AG3: 30 | AH3: 31 | AI3: 32 | AJ3: 33 | AK3: 34 | AL3: 35 | AM3: 36 | AN3: 37 | AO3: 38 | AP3: 39 | AQ3: 40 | AR3: 41 | AS3: 42 | AT3: 43 | AU3: 44 | AV3: 45 | AW3: 46 | AX3: 47 | AY3: 48 | AZ3: 49 | BA3: 50 | BB3: 51 | BC3: 52 | BD3: 53 | BE3: 54 | BF3: 55 | BG3: 56 | BH3: 57 | BI3: 58 | BJ3: 59 | BK3: 60 | BL3: 61 | BM3: 62 | BN3: 63 | BO3: 64 | BP3: 65 | BQ3: 66 | BR3: 67 | BS3: 68 | BT3: 69 | BU3: 70 | BV3: 71 | BW3: 72 | BX3: 73 | BY3: 74 | BZ3: 75 | CA3: 76 | CB3: 77 | CC3: 78 | CD3: 79 | CE3: 80 | CF3: 81 | CG3: 82 | CH3: 83 | CI3: 84 | CJ3: 85 | CK3: 86 | CL3: 87 | CM3: 88 | CN3: 89 | CO3: 90 | CP3: 91 | CQ3: 92 | CR3: 93 | CS3: 94 | CT3: 95 | CU3: 96 | CV3: 97 | CW3: 98 | CX3: 99 | CY3: 100 | CZ3: 101 | DA3: 102 | DB3: 103 | DC3: 104 | DD3: 105 | DE3: 106 | DF3: 107 | DG3: 108 | DH3: 109 | DI3: 110 | DJ3: 111 | DK3: 112 | DL3: 113 | DM3: 114 | DN3: 115 | DO3: 116 | DP3: 117 | DQ3: 118 | DR3: 119 | DS3: 120 | DT3: 121 | DU3: 122 | DV3: 123 | DW3: 124 | DX3: 125 | DY3: 126 | DZ3: 127 | EA3: 128 | EB3: 129 | EC3: 130 | ED3: 131 | EE3: 132 | EF3: 133 | EG3: 134 | EH3: 135 | EI3: 136 | EJ3: 137 | EK3: 138 | EL3: 139 | EM3: 140 | EN3: 141 | EO3: 142 | EP3: 143 | EQ3: 144 | ER3: 145 | ES3: 146 | ET3: 147 | EU3: 148 | EV3: 149 | EW3: 150 | EX3: 151 | EY3: 152 | EZ3: 153 | FA3: 154 | FB3: 155 | FC3: 156 | FD3: 157 | FE3: 158 | FF3: 159 | FG3: 160 | FH3: 161 | FI3: 162 | FJ3: 163 | FK3: 164 | FL3: 165 | FM3: 166 | FN3: 167 | FO3: 168 | FP3: 169 | FQ3: 170 | FR3: 171 | FS3: 172 | FT3: 173 | FU3: 174 | FV3: 175 | FW3: 176 | FX3: 177 | FY3: 178 | FZ3: 179 | GA3: 180 | GB3: 181 | GC3: 182 | GD3: 183 | GE3: 184 | GF3: 185 | GG3: 186 | GH3: 187 | GI3: 188 | GJ3: 189 | GK3: 190 | GL3: 191 | GM3: 192 | GN3: 193 | GO3: 194 | GP3: 195 | GQ3: 196 | GR3: 197 | GS3: 198 | GT3: 199 | GU3: 200 | GV3: 201 | GW3: 202 | GX3: 203 | GY3: 204 | GZ3: 205 | HA3: 206 | HB3: 207 | HC3: 208 | HD3: 209 | HE3: 210 | HF3: 211 | HG3: 212 | HH3: 213 | HI3: 214 | HJ3: 215 | HK3: 216 | HL3: 217 | HM3: 218 | HN3: 219 | HO3: 220 | HP3: 221 | HQ3: 222 | HR3: 223 | HS3: 224 | HT3: 225 | HU3: 226 | HV3: 227 | HW3: 228 | HX3: 229 | HY3: 230 | HZ3: 231 | IA3: 232
A4: CRMC | B4: OS | C4: DRE | D4: CONTRATO | E4: PLACA | F4: PERÍODO | H4: EMPRESA | I4: NOME CONDUTOR | J4: TIPO DE VEÍCULO (NORMAL, ADAPTADO) | K4: TIPO DE ATENDIMENTO | L4: TOTAL CONT REG | M4: TOTAL CONT CAD | N4: KM ADICIONAL | O4: SEI | P4: Tipo Optante | Q4: 01/04/2026 | U4: 46114 | Y4: 46115 | AC4: 46116 | AG4: 46117 | AK4: 46118 | AO4: 46119 | AS4: 46120 | AW4: 46121 | BA4: 46122 | BE4: 46123 | BI4: 46124 | BM4: 46125 | BQ4: 46126 | BU4: 46127 | BY4: 46128 | CC4: 46129 | CG4: 46130 | CK4: 46131 | CO4: 46132 | CS4: 46133 | CW4: 46134 | DA4: 46135 | DE4: 46136 | DI4: 46137 | DM4: 46138 | DQ4: 46139 | DU4: 46140 | DY4: 46141 | EC4: 46142 | EK4: FALTAS - APONTAR AS DATAS | EL4: OBSERVAÇÕES ALUNO PRESENCIAL COLUNAS FINAIS | EM4: Ajuste positivo | EN4: Ajuste negativo | EO4: Desconto faltas | EP4: TOTAL ALUNOS N CAD(30 DIAS) | EQ4: TOTAL ALUNOS N CAD(MENOS DE 30 DIAS) | ER4: TOTAL ALUNOS ATIV.COMPL. N CAD | ES4: TOTAL ALUNOS CAD (30 DIAS) | ET4: TOTAL ALUNOS CAD (MENOS DE 30 DIAS) | EU4: TOTAL ALUNOS ATIV.COMPL. CAD | EV4: TOTAL GERAL | EW4: Contratos Especiais (Valor fixo) | EX4: Valor total alunos presenciais (30 dias) | EY4: Ativ.Complementar Continuada | EZ4: Valor alunos presenciais (menos de 30 dias) | FA4: Saida de alunos ao longo do mês | FB4: CCA | FC4: Valor km adicional | FD4: Outros apontamentos | FE4: VALOR ATESTE | FF4: 30 | FG4: 29 | FH4: 28 | FI4: 27 | FJ4: 26 | FK4: 25 | FL4: 24 | FM4: 23 | FN4: 22 | FO4: 21 | FP4: 20 | FQ4: 19 | FR4: 18 | FS4: 17 | FT4: 16 | FU4: 15 | FV4: 14 | FW4: 13 | FX4: 12 | FY4: 11 | FZ4: 10 | GA4: 9 | GB4: 8 | GC4: 7 | GD4: 6 | GE4: 5 | GF4: 4 | GG4: 3 | GH4: 2 | GI4: 1 | GJ4: 1 | GK4: Multa Contratual | GL4: CÁLCULO | GM4: DIAS | GN4: 29 | GO4: 28 | GP4: 27 | GQ4: 26 | GR4: 25 | GS4: 24 | GT4: 23 | GU4: 22 | GV4: 21 | GW4: 20 | GX4: 19 | GY4: 18 | GZ4: 17 | HA4: 16 | HB4: 15 | HC4: 14 | HD4: 13 | HE4: 12 | HF4: 11 | HG4: 10 | HH4: 9 | HI4: 8 | HJ4: 7 | HK4: 6 | HL4: 5 | HM4: 4 | HN4: 3 | HO4: 2 | HP4: 1 | HW4: VALOR ATESTE | HY4: Ajuste positivo | HZ4: Ajuste negativo | IA4: Desconto faltas
F5: 01/04/2026 | G5: 30/04/2026 | Q5: N CAD presencial | R5: CAD | S5: AT. COMPL. N CAD | T5: AT. COMPL. CAD | U5: N CAD presencial | V5: CAD | W5: AT. COMPL. N CAD | X5: AT. COMPL. CAD | Y5: N CAD presencial | Z5: CAD | AA5: AT. COMPL. N CAD | AB5: AT. COMPL. CAD | AC5: N CAD presencial | AD5: CAD | AE5: AT. COMPL. N CAD | AF5: AT. COMPL. CAD | AG5: N CAD presencial | AH5: CAD | AI5: AT. COMPL. N CAD | AJ5: AT. COMPL. CAD | AK5: N CAD presencial | AL5: CAD | AM5: AT. COMPL. N CAD | AN5: AT. COMPL. CAD | AO5: N CAD presencial | AP5: CAD | AQ5: AT. COMPL. N CAD | AR5: AT. COMPL. CAD | AS5: N CAD presencial | AT5: CAD | AU5: AT. COMPL. N CAD | AV5: AT. COMPL. CAD | AW5: N CAD presencial | AX5: CAD | AY5: AT. COMPL. N CAD | AZ5: AT. COMPL. CAD | BA5: N CAD presencial | BB5: CAD | BC5: AT. COMPL. N CAD | BD5: AT. COMPL. CAD | BE5: N CAD presencial | BF5: CAD | BG5: AT. COMPL. N CAD | BH5: AT. COMPL. CAD | BI5: N CAD presencial | BJ5: CAD | BK5: AT. COMPL. N CAD | BL5: AT. COMPL. CAD | BM5: N CAD presencial | BN5: CAD | BO5: AT. COMPL. N CAD | BP5: AT. COMPL. CAD | BQ5: N CAD presencial | BR5: CAD | BS5: AT. COMPL. N CAD | BT5: AT. COMPL. CAD | BU5: N CAD presencial | BV5: CAD | BW5: AT. COMPL. N CAD | BX5: AT. COMPL. CAD | BY5: N CAD presencial | BZ5: CAD | CA5: AT. COMPL. N CAD | CB5: AT. COMPL. CAD | CC5: N CAD presencial | CD5: CAD | CE5: AT. COMPL. N CAD | CF5: AT. COMPL. CAD | CG5: N CAD presencial | CH5: CAD | CI5: AT. COMPL. N CAD | CJ5: AT. COMPL. CAD | CK5: N CAD presencial | CL5: CAD | CM5: AT. COMPL. N CAD | CN5: AT. COMPL. CAD | CO5: N CAD presencial | CP5: CAD | CQ5: AT. COMPL. N CAD | CR5: AT. COMPL. CAD | CS5: N CAD presencial | CT5: CAD | CU5: AT. COMPL. N CAD | CV5: AT. COMPL. CAD | CW5: N CAD presencial | CX5: CAD | CY5: AT. COMPL. N CAD | CZ5: AT. COMPL. CAD | DA5: N CAD presencial | DB5: CAD | DC5: AT. COMPL. N CAD | DD5: AT. COMPL. CAD | DE5: N CAD presencial | DF5: CAD | DG5: AT. COMPL. N CAD | DH5: AT. COMPL. CAD | DI5: N CAD presencial | DJ5: CAD | DK5: AT. COMPL. N CAD | DL5: AT. COMPL. CAD | DM5: N CAD presencial | DN5: CAD | DO5: AT. COMPL. N CAD | DP5: AT. COMPL. CAD | DQ5: N CAD presencial | DR5: CAD | DS5: AT. COMPL. N CAD | DT5: AT. COMPL. CAD | DU5: N CAD presencial | DV5: CAD | DW5: AT. COMPL. N CAD | DX5: AT. COMPL. CAD | DY5: N CAD presencial | DZ5: CAD | EA5: AT. COMPL. N CAD | EB5: AT. COMPL. CAD | EC5: N CAD presencial | ED5: CAD | EE5: AT. COMPL. N CAD | EF5: AT. COMPL. CAD | EG5: N CAD presencial | EH5: CAD | EI5: AT. COMPL. N CAD | EJ5: AT. COMPL. CAD
A6: 020.708-00 | B6: 2022/0026670-001 | C6: 1 | D6: 2022/0026670 | E6: DJE9491 | F6: 01/04/2026 | G6: 30/04/2026 | H6: ADILSON TOLEDO | I6: ADILSON TOLEDO | J6: NORMAL | K6: EMEI | L6: 0 | M6: 0 | O6: 6020.2022/0026670-0 | P6: 0 | U6: =Q6+'APONTAMENTO CREDENCIAMENTO'!U6 -> 0 | V6: =R6+'APONTAMENTO CREDENCIAMENTO'!V6 -> 0 | W6: =S6+'APONTAMENTO CREDENCIAMENTO'!W6 -> 0 | X6: =T6+'APONTAMENTO CREDENCIAMENTO'!X6 -> 0 | Y6: =U6+'APONTAMENTO CREDENCIAMENTO'!Y6 -> 0 | Z6: =V6+'APONTAMENTO CREDENCIAMENTO'!Z6 -> 0 | AA6: =W6+'APONTAMENTO CREDENCIAMENTO'!AA6 -> 0 | AB6: =X6+'APONTAMENTO CREDENCIAMENTO'!AB6 -> 0 | ... EF6: =EB6+'APONTAMENTO CREDENCIAMENTO'!EF6 -> 0 | EP6: 0 | EQ6: 0 | ER6: 0 | ES6: 0 | ET6: 0 | EU6: 0 | EV6: 0 | EW6: 0 | EX6: 24057.41 | EY6: 0 | EZ6: 0 | FA6: 0 | FB6: 0 | FC6: 0 | FD6: 0 | FE6: 24057.41 | FF6: 24057.41 | FG6: 0 | FH6: 0 | FI6: 0 | FJ6: 0 | FK6: 0 | FL6: 0 | FM6: 0 | FN6: 0 | FO6: 0 | FP6: 0 | FQ6: 0 | FR6: 0 | FS6: 0 | FT6: 0 | FU6: 0 | FV6: 0 | FW6: 0 | FX6: 0 | FY6: 0 | FZ6: 0 | GA6: 0 | GB6: 0 | GC6: 0 | GD6: 0 | GE6: 0 | GF6: 0 | GG6: 0 | GH6: 0 | GI6: 0 | GJ6: 0 | GL6: 0 | GN6: 0 | GO6: 0 | GP6: 0 | GQ6: 0 | GR6: 0 | GS6: 0 | GT6: 0 | GU6: 0 | GV6: 0 | GW6: 0 | GX6: 0 | GY6: 0 | GZ6: 0 | HA6: 0 | HB6: 0 | HC6: 0 | HD6: 0 | HE6: 0 | HF6: 0 | HG6: 0 | HH6: 0 | HI6: 0 | HJ6: 0 | HK6: 0 | HL6: 0 | HM6: 0 | HN6: 0 | HO6: 0 | HP6: 0 | HW6: 17629.31 | HY6: 0 | HZ6: 0 | IA6: 0 | IB6: FALSE
A7: 020.708-00 | B7: 2022/0026670-001 | C7: FB | D7: 2022/0026670 | E7: DJE9491 | F7: 01/04/2026 | G7: 30/04/2026 | H7: ADILSON TOLEDO | I7: ADILSON TOLEDO | J7: NORMAL | K7: EMEF | L7: 0 | M7: 0 | O7: 6020.2022/0026670-0 | P7: 0 | Q7: 59 | U7: =Q7+'APONTAMENTO CREDENCIAMENTO'!U7 -> 59 | V7: =R7+'APONTAMENTO CREDENCIAMENTO'!V7 -> 0 | W7: =S7+'APONTAMENTO CREDENCIAMENTO'!W7 -> 0 | X7: =T7+'APONTAMENTO CREDENCIAMENTO'!X7 -> 0 | Y7: =U7+'APONTAMENTO CREDENCIAMENTO'!Y7 -> 59 | Z7: =V7+'APONTAMENTO CREDENCIAMENTO'!Z7 -> 0 | AA7: =W7+'APONTAMENTO CREDENCIAMENTO'!AA7 -> 0 | AB7: =X7+'APONTAMENTO CREDENCIAMENTO'!AB7 -> 0 | ... EF7: =EB7+'APONTAMENTO CREDENCIAMENTO'!EF7 -> 0 | EP7: 59 | EQ7: 0 | ER7: 0 | ES7: 0 | ET7: 0 | EU7: 0 | EV7: 59 | EX7: 0 | EY7: 0 | EZ7: 0 | FA7: 0 | FB7: 0 | FC7: 0 | FD7: 0 | GL7: 0 | HY7: 0 | HZ7: 0 | IA7: 0
A8: 020.708-00 | B8: 2022/0026670-001 | C8: FB | D8: 2022/0026670 | E8: DJE9491 | F8: 01/04/2026 | G8: 30/04/2026 | H8: ADILSON TOLEDO | I8: ADILSON TOLEDO | J8: NORMAL | K8: EMEE | L8: 0 | M8: 0 | O8: 6020.2022/0026670-0 | P8: 0 | U8: =Q8+'APONTAMENTO CREDENCIAMENTO'!U8 -> 0 | V8: =R8+'APONTAMENTO CREDENCIAMENTO'!V8 -> 0 | W8: =S8+'APONTAMENTO CREDENCIAMENTO'!W8 -> 0 | X8: =T8+'APONTAMENTO CREDENCIAMENTO'!X8 -> 0 | Y8: =U8+'APONTAMENTO CREDENCIAMENTO'!Y8 -> 0 | Z8: =V8+'APONTAMENTO CREDENCIAMENTO'!Z8 -> 0 | AA8: =W8+'APONTAMENTO CREDENCIAMENTO'!AA8 -> 0 | AB8: =X8+'APONTAMENTO CREDENCIAMENTO'!AB8 -> 0 | ... EF8: =EB8+'APONTAMENTO CREDENCIAMENTO'!EF8 -> 0 | EP8: 0 | EQ8: 0 | ER8: 0 | ES8: 0 | ET8: 0 | EU8: 0 | EV8: 0 | EX8: 0 | EY8: 0 | EZ8: 0 | FA8: 0 | FB8: 0 | FC8: 0 | FD8: 0 | GL8: 0 | HY8: 0 | HZ8: 0 | IA8: 0
A9: 020.708-00 | B9: 2022/0026670-001 | C9: FB | D9: 2022/0026670 | E9: DJE9491 | F9: 01/04/2026 | G9: 30/04/2026 | H9: ADILSON TOLEDO | I9: ADILSON TOLEDO | J9: NORMAL | K9: CEI | L9: 0 | M9: 0 | O9: 6020.2022/0026670-0 | P9: 0 | U9: =Q9+'APONTAMENTO CREDENCIAMENTO'!U9 -> 0 | V9: =R9+'APONTAMENTO CREDENCIAMENTO'!V9 -> 0 | W9: =S9+'APONTAMENTO CREDENCIAMENTO'!W9 -> 0 | X9: =T9+'APONTAMENTO CREDENCIAMENTO'!X9 -> 0 | Y9: =U9+'APONTAMENTO CREDENCIAMENTO'!Y9 -> 0 | Z9: =V9+'APONTAMENTO CREDENCIAMENTO'!Z9 -> 0 | AA9: =W9+'APONTAMENTO CREDENCIAMENTO'!AA9 -> 0 | AB9: =X9+'APONTAMENTO CREDENCIAMENTO'!AB9 -> 0 | ... EF9: =EB9+'APONTAMENTO CREDENCIAMENTO'!EF9 -> 0 | EP9: 0 | EQ9: 0 | ER9: 0 | ES9: 0 | ET9: 0 | EU9: 0 | EV9: 0 | EX9: 0 | EY9: 0 | EZ9: 0 | FA9: 0 | FB9: 0 | FC9: 0 | FD9: 0 | GL9: 0 | HY9: 0 | HZ9: 0 | IA9: 0
A10: 020.708-00 | B10: 2022/0026670-001 | C10: FB | D10: 2022/0026670 | E10: DJE9491 | F10: 01/04/2026 | G10: 30/04/2026 | H10: ADILSON TOLEDO | I10: ADILSON TOLEDO | J10: NORMAL | K10: CCA | L10: 0 | M10: 0 | O10: 6020.2022/0026670-0 | P10: 0 | U10: =Q10+'APONTAMENTO CREDENCIAMENTO'!U10 -> 0 | V10: =R10+'APONTAMENTO CREDENCIAMENTO'!V10 -> 0 | W10: =S10+'APONTAMENTO CREDENCIAMENTO'!W10 -> 0 | X10: =T10+'APONTAMENTO CREDENCIAMENTO'!X10 -> 0 | Y10: =U10+'APONTAMENTO CREDENCIAMENTO'!Y10 -> 0 | Z10: =V10+'APONTAMENTO CREDENCIAMENTO'!Z10 -> 0 | AA10: =W10+'APONTAMENTO CREDENCIAMENTO'!AA10 -> 0 | AB10: =X10+'APONTAMENTO CREDENCIAMENTO'!AB10 -> 0 | ... EF10: =EB10+'APONTAMENTO CREDENCIAMENTO'!EF10 -> 0 | EP10: 0 | EQ10: 0 | ER10: 0 | ES10: 0 | ET10: 0 | EU10: 0 | EV10: 0 | EX10: 0 | EY10: 0 | EZ10: 0 | FA10: 0 | FB10: 0 | FC10: 0 | FD10: 0 | FF10: 0 | FG10: 0 | FH10: 0 | FI10: 0 | FJ10: 0 | FK10: 0 | FL10: 0 | FM10: 0 | FN10: 0 | FO10: 0 | FP10: 0 | FQ10: 0 | FR10: 0 | FS10: 0 | FT10: 0 | FU10: 0 | FV10: 0 | FW10: 0 | FX10: 0 | FY10: 0 | FZ10: 0 | GA10: 0 | GB10: 0 | GC10: 0 | GD10: 0 | GE10: 0 | GF10: 0 | GG10: 0 | GH10: 0 | GI10: 0 | GJ10: 0 | GL10: 0 | HY10: 0 | HZ10: 0 | IA10: 0
A11: 015.733-00 | B11: 2022/0027713-001B | C11: 4 | D11: 2022/0027713 | E11: ECM4497 | F11: 01/04/2026 | G11: 30/04/2026 | H11: ALEXANDRO CIRINO VIEIRA | I11: ALEXANDRO CIRINO VIEIRA | J11: NORMAL | K11: EMEI | L11: 0 | M11: 0 | O11: 6020.2022/0027713-2 | P11: 0 | U11: =Q11+'APONTAMENTO CREDENCIAMENTO'!U11 -> 0 | V11: =R11+'APONTAMENTO CREDENCIAMENTO'!V11 -> 0 | W11: =S11+'APONTAMENTO CREDENCIAMENTO'!W11 -> 0 | X11: =T11+'APONTAMENTO CREDENCIAMENTO'!X11 -> 0 | Y11: =U11+'APONTAMENTO CREDENCIAMENTO'!Y11 -> 0 | Z11: =V11+'APONTAMENTO CREDENCIAMENTO'!Z11 -> 0 | AA11: =W11+'APONTAMENTO CREDENCIAMENTO'!AA11 -> 0 | AB11: =X11+'APONTAMENTO CREDENCIAMENTO'!AB11 -> 0 | ... EF11: =EB11+'APONTAMENTO CREDENCIAMENTO'!EF11 -> 0 | EP11: 0 | EQ11: 0 | ER11: 0 | ES11: 0 | ET11: 0 | EU11: 0 | EV11: 0 | EW11: 11465.63 | EX11: 1155.69 | EY11: 0 | EZ11: 0 | FA11: 0 | FB11: 0 | FC11: 0 | FD11: 0 | FE11: 12852.68 | FF11: 1155.69 | FG11: 0 | FH11: 0 | FI11: 0 | FJ11: 0 | FK11: 0 | FL11: 0 | FM11: 0 | FN11: 0 | FO11: 0 | FP11: 0 | FQ11: 0 | FR11: 0 | FS11: 0 | FT11: 0 | FU11: 0 | FV11: 0 | FW11: 0 | FX11: 0 | FY11: 0 | FZ11: 0 | GA11: 0 | GB11: 0 | GC11: 0 | GD11: 0 | GE11: 0 | GF11: 0 | GG11: 0 | GH11: 0 | GI11: 0 | GJ11: 0 | GL11: 0 | GN11: 0 | GO11: 0 | GP11: 0 | GQ11: 0 | GR11: 0 | GS11: 0 | GT11: 0 | GU11: 0 | GV11: 0 | GW11: 0 | GX11: 0 | GY11: 0 | GZ11: 0 | HA11: 0 | HB11: 0 | HC11: 0 | HD11: 0 | HE11: 0 | HF11: 0 | HG11: 0 | HH11: 0 | HI11: 0 | HJ11: 0 | HK11: 0 | HL11: 0 | HM11: 0 | HN11: 0 | HO11: 0 | HP11: 0 | HW11: 17629.31 | HY11: 0 | HZ11: 0 | IA11: 0 | IB11: FALSE
A12: 015.733-00 | B12: 2022/0027713-001B | C12: FBE | D12: 2022/0027713 | E12: ECM4497 | F12: 01/04/2026 | G12: 30/04/2026 | H12: ALEXANDRO CIRINO VIEIRA | I12: ALEXANDRO CIRINO VIEIRA | J12: NORMAL | K12: EMEF | L12: 0 | M12: 0 | O12: 6020.2022/0027713-2 | P12: 0 | U12: =Q12+'APONTAMENTO CREDENCIAMENTO'!U12 -> 0 | V12: =R12+'APONTAMENTO CREDENCIAMENTO'!V12 -> 0 | W12: =S12+'APONTAMENTO CREDENCIAMENTO'!W12 -> 0 | X12: =T12+'APONTAMENTO CREDENCIAMENTO'!X12 -> 0 | Y12: =U12+'APONTAMENTO CREDENCIAMENTO'!Y12 -> 0 | Z12: =V12+'APONTAMENTO CREDENCIAMENTO'!Z12 -> 0 | AA12: =W12+'APONTAMENTO CREDENCIAMENTO'!AA12 -> 0 | AB12: =X12+'APONTAMENTO CREDENCIAMENTO'!AB12 -> 0 | ... EF12: =EB12+'APONTAMENTO CREDENCIAMENTO'!EF12 -> 0 | EP12: 0 | EQ12: 0 | ER12: 0 | ES12: 0 | ET12: 0 | EU12: 0 | EV12: 0 | EX12: 0 | EY12: 0 | EZ12: 0 | FA12: 0 | FB12: 0 | FC12: 0 | FD12: 0 | GL12: 0 | HY12: 0 | HZ12: 0 | IA12: 0
A13: 015.733-00 | B13: 2022/0027713-001B | C13: FBE | D13: 2022/0027713 | E13: ECM4497 | F13: 01/04/2026 | G13: 30/04/2026 | H13: ALEXANDRO CIRINO VIEIRA | I13: ALEXANDRO CIRINO VIEIRA | J13: NORMAL | K13: EMEE | L13: 24 | M13: 0 | O13: 6020.2022/0027713-2 | P13: 0 | Q13: 3 | U13: =Q13+'APONTAMENTO CREDENCIAMENTO'!U13 -> 3 | V13: =R13+'APONTAMENTO CREDENCIAMENTO'!V13 -> 0 | W13: =S13+'APONTAMENTO CREDENCIAMENTO'!W13 -> 0 | X13: =T13+'APONTAMENTO CREDENCIAMENTO'!X13 -> 0 | Y13: =U13+'APONTAMENTO CREDENCIAMENTO'!Y13 -> 3 | Z13: =V13+'APONTAMENTO CREDENCIAMENTO'!Z13 -> 0 | AA13: =W13+'APONTAMENTO CREDENCIAMENTO'!AA13 -> 0 | AB13: =X13+'APONTAMENTO CREDENCIAMENTO'!AB13 -> 0 | ... EF13: =EB13+'APONTAMENTO CREDENCIAMENTO'!EF13 -> 0 | EP13: 3 | EQ13: 0 | ER13: 0 | ES13: 0 | ET13: 0 | EU13: 0 | EV13: 3 | EX13: 0 | EY13: 231.36 | EZ13: 0 | FA13: 0 | FB13: 0 | FC13: 0 | FD13: 0 | GL13: 0 | HY13: 0 | HZ13: 0 | IA13: 0
A14: 015.733-00 | B14: 2022/0027713-001B | C14: FBE | D14: 2022/0027713 | E14: ECM4497 | F14: 01/04/2026 | G14: 30/04/2026 | H14: ALEXANDRO CIRINO VIEIRA | I14: ALEXANDRO CIRINO VIEIRA | J14: NORMAL | K14: CEI | L14: 0 | M14: 0 | O14: 6020.2022/0027713-2 | P14: 0 | U14: =Q14+'APONTAMENTO CREDENCIAMENTO'!U14 -> 0 | V14: =R14+'APONTAMENTO CREDENCIAMENTO'!V14 -> 0 | W14: =S14+'APONTAMENTO CREDENCIAMENTO'!W14 -> 0 | X14: =T14+'APONTAMENTO CREDENCIAMENTO'!X14 -> 0 | Y14: =U14+'APONTAMENTO CREDENCIAMENTO'!Y14 -> 0 | Z14: =V14+'APONTAMENTO CREDENCIAMENTO'!Z14 -> 0 | AA14: =W14+'APONTAMENTO CREDENCIAMENTO'!AA14 -> 0 | AB14: =X14+'APONTAMENTO CREDENCIAMENTO'!AB14 -> 0 | ... EF14: =EB14+'APONTAMENTO CREDENCIAMENTO'!EF14 -> 0 | EP14: 0 | EQ14: 0 | ER14: 0 | ES14: 0 | ET14: 0 | EU14: 0 | EV14: 0 | EX14: 0 | EY14: 0 | EZ14: 0 | FA14: 0 | FB14: 0 | FC14: 0 | FD14: 0 | GL14: 0 | HY14: 0 | HZ14: 0 | IA14: 0
A15: 015.733-00 | B15: 2022/0027713-001B | C15: FBE | D15: 2022/0027713 | E15: ECM4497 | F15: 01/04/2026 | G15: 30/04/2026 | H15: ALEXANDRO CIRINO VIEIRA | I15: ALEXANDRO CIRINO VIEIRA | J15: NORMAL | K15: CCA | L15: 0 | M15: 0 | O15: 6020.2022/0027713-2 | P15: 0 | U15: =Q15+'APONTAMENTO CREDENCIAMENTO'!U15 -> 0 | V15: =R15+'APONTAMENTO CREDENCIAMENTO'!V15 -> 0 | W15: =S15+'APONTAMENTO CREDENCIAMENTO'!W15 -> 0 | X15: =T15+'APONTAMENTO CREDENCIAMENTO'!X15 -> 0 | Y15: =U15+'APONTAMENTO CREDENCIAMENTO'!Y15 -> 0 | Z15: =V15+'APONTAMENTO CREDENCIAMENTO'!Z15 -> 0 | AA15: =W15+'APONTAMENTO CREDENCIAMENTO'!AA15 -> 0 | AB15: =X15+'APONTAMENTO CREDENCIAMENTO'!AB15 -> 0 | ... EF15: =EB15+'APONTAMENTO CREDENCIAMENTO'!EF15 -> 0 | EP15: 0 | EQ15: 0 | ER15: 0 | ES15: 0 | ET15: 0 | EU15: 0 | EV15: 0 | EX15: 0 | EY15: 0 | EZ15: 0 | FA15: 0 | FB15: 0 | FC15: 0 | FD15: 0 | FF15: 0 | FG15: 0 | FH15: 0 | FI15: 0 | FJ15: 0 | FK15: 0 | FL15: 0 | FM15: 0 | FN15: 0 | FO15: 0 | FP15: 0 | FQ15: 0 | FR15: 0 | FS15: 0 | FT15: 0 | FU15: 0 | FV15: 0 | FW15: 0 | FX15: 0 | FY15: 0 | FZ15: 0 | GA15: 0 | GB15: 0 | GC15: 0 | GD15: 0 | GE15: 0 | GF15: 0 | GG15: 0 | GH15: 0 | GI15: 0 | GJ15: 0 | GL15: 0 | HY15: 0 | HZ15: 0 | IA15: 0
A16: 015.812-00 | B16: 2022/0033780-001D | C16: 1 | D16: 2022/0033780 | E16: CLU1093 | F16: 01/04/2026 | G16: 30/04/2026 | H16: ANA CRISTINA FABRI DE LIMA | I16: ANA CRISTINA FABRI DE LIMA | J16: NORMAL | K16: EMEI | L16: 0 | M16: 0 | O16: 6020.2022/0033780-1 | P16: 0 | U16: =Q16+'APONTAMENTO CREDENCIAMENTO'!U16 -> 0 | V16: =R16+'APONTAMENTO CREDENCIAMENTO'!V16 -> 0 | W16: =S16+'APONTAMENTO CREDENCIAMENTO'!W16 -> 0 | X16: =T16+'APONTAMENTO CREDENCIAMENTO'!X16 -> 0 | Y16: =U16+'APONTAMENTO CREDENCIAMENTO'!Y16 -> 0 | Z16: =V16+'APONTAMENTO CREDENCIAMENTO'!Z16 -> 0 | AA16: =W16+'APONTAMENTO CREDENCIAMENTO'!AA16 -> 0 | AB16: =X16+'APONTAMENTO CREDENCIAMENTO'!AB16 -> 0 | ... EF16: =EB16+'APONTAMENTO CREDENCIAMENTO'!EF16 -> 0 | EP16: 0 | EQ16: 0 | ER16: 0 | ES16: 0 | ET16: 0 | EU16: 0 | EV16: 0 | EW16: 0 | EX16: 17123.27 | EY16: 0 | EZ16: 308.184 | FA16: 0 | FB16: 0 | FC16: 0 | FD16: 0 | FE16: 17518.214 | FF16: 17123.27 | FG16: 0 | FH16: 0 | FI16: 0 | FJ16: 0 | FK16: 0 | FL16: 308.184 | FM16: 0 | FN16: 0 | FO16: 0 | FP16: 0 | FQ16: 0 | FR16: 0 | FS16: 0 | FT16: 0 | FU16: 0 | FV16: 0 | FW16: 0 | FX16: 0 | FY16: 0 | FZ16: 0 | GA16: 0 | GB16: 0 | GC16: 0 | GD16: 0 | GE16: 0 | GF16: 0 | GG16: 0 | GH16: 0 | GI16: 0 | GJ16: 0 | GL16: 0 | GN16: 0 | GO16: 0 | GP16: 0 | GQ16: 0 | GR16: 0 | GS16: 0 | GT16: 0 | GU16: 0 | GV16: 0 | GW16: 0 | GX16: 0 | GY16: 0 | GZ16: 0 | HA16: 0 | HB16: 0 | HC16: 0 | HD16: 0 | HE16: 0 | HF16: 0 | HG16: 0 | HH16: 0 | HI16: 0 | HJ16: 0 | HK16: 0 | HL16: 0 | HM16: 0 | HN16: 0 | HO16: 0 | HP16: 0 | HW16: 17629.31 | HY16: 0 | HZ16: 0 | IA16: 0 | IB16: FALSE
A17: 015.812-00 | B17: 2022/0033780-001D | C17: FB | D17: 2022/0033780 | E17: CLU1093 | F17: 01/04/2026 | G17: 30/04/2026 | H17: ANA CRISTINA FABRI DE LIMA | I17: ANA CRISTINA FABRI DE LIMA | J17: NORMAL | K17: EMEF | L17: 9 | M17: 0 | O17: 6020.2022/0033780-1 | P17: 0 | Q17: 36 | S17: 5 | U17: =Q17+'APONTAMENTO CREDENCIAMENTO'!U17 -> 36 | V17: =R17+'APONTAMENTO CREDENCIAMENTO'!V17 -> 0 | W17: =S17+'APONTAMENTO CREDENCIAMENTO'!W17 -> 5 | X17: =T17+'APONTAMENTO CREDENCIAMENTO'!X17 -> 0 | Y17: =U17+'APONTAMENTO CREDENCIAMENTO'!Y17 -> 36 | Z17: =V17+'APONTAMENTO CREDENCIAMENTO'!Z17 -> 0 | AA17: =W17+'APONTAMENTO CREDENCIAMENTO'!AA17 -> 5 | AB17: =X17+'APONTAMENTO CREDENCIAMENTO'!AB17 -> 0 | ... EF17: =EB17+'APONTAMENTO CREDENCIAMENTO'!EF17 -> 0 | EP17: 36 | EQ17: 1 | ER17: 5 | ES17: 0 | ET17: 0 | EU17: 0 | EV17: 42 | EX17: 0 | EY17: 86.76 | EZ17: 0 | FA17: 0 | FB17: 0 | FC17: 0 | FD17: 0 | GL17: 0 | HY17: 0 | HZ17: 0 | IA17: 0
A18: 015.812-00 | B18: 2022/0033780-001D | C18: FB | D18: 2022/0033780 | E18: CLU1093 | F18: 01/04/2026 | G18: 30/04/2026 | H18: ANA CRISTINA FABRI DE LIMA | I18: ANA CRISTINA FABRI DE LIMA | J18: NORMAL | K18: EMEE | L18: 0 | M18: 0 | O18: 6020.2022/0033780-1 | P18: 0 | U18: =Q18+'APONTAMENTO CREDENCIAMENTO'!U18 -> 0 | V18: =R18+'APONTAMENTO CREDENCIAMENTO'!V18 -> 0 | W18: =S18+'APONTAMENTO CREDENCIAMENTO'!W18 -> 0 | X18: =T18+'APONTAMENTO CREDENCIAMENTO'!X18 -> 0 | Y18: =U18+'APONTAMENTO CREDENCIAMENTO'!Y18 -> 0 | Z18: =V18+'APONTAMENTO CREDENCIAMENTO'!Z18 -> 0 | AA18: =W18+'APONTAMENTO CREDENCIAMENTO'!AA18 -> 0 | AB18: =X18+'APONTAMENTO CREDENCIAMENTO'!AB18 -> 0 | ... EF18: =EB18+'APONTAMENTO CREDENCIAMENTO'!EF18 -> 0 | EP18: 0 | EQ18: 0 | ER18: 0 | ES18: 0 | ET18: 0 | EU18: 0 | EV18: 0 | EX18: 0 | EY18: 0 | EZ18: 0 | FA18: 0 | FB18: 0 | FC18: 0 | FD18: 0 | GL18: 0 | HY18: 0 | HZ18: 0 | IA18: 0
A19: 015.812-00 | B19: 2022/0033780-001D | C19: FB | D19: 2022/0033780 | E19: CLU1093 | F19: 01/04/2026 | G19: 30/04/2026 | H19: ANA CRISTINA FABRI DE LIMA | I19: ANA CRISTINA FABRI DE LIMA | J19: NORMAL | K19: CEI | L19: 0 | M19: 0 | O19: 6020.2022/0033780-1 | P19: 0 | U19: =Q19+'APONTAMENTO CREDENCIAMENTO'!U19 -> 0 | V19: =R19+'APONTAMENTO CREDENCIAMENTO'!V19 -> 0 | W19: =S19+'APONTAMENTO CREDENCIAMENTO'!W19 -> 0 | X19: =T19+'APONTAMENTO CREDENCIAMENTO'!X19 -> 0 | Y19: =U19+'APONTAMENTO CREDENCIAMENTO'!Y19 -> 0 | Z19: =V19+'APONTAMENTO CREDENCIAMENTO'!Z19 -> 0 | AA19: =W19+'APONTAMENTO CREDENCIAMENTO'!AA19 -> 0 | AB19: =X19+'APONTAMENTO CREDENCIAMENTO'!AB19 -> 0 | ... EF19: =EB19+'APONTAMENTO CREDENCIAMENTO'!EF19 -> 0 | EP19: 0 | EQ19: 0 | ER19: 0 | ES19: 0 | ET19: 0 | EU19: 0 | EV19: 0 | EX19: 0 | EY19: 0 | EZ19: 0 | FA19: 0 | FB19: 0 | FC19: 0 | FD19: 0 | GL19: 0 | HY19: 0 | HZ19: 0 | IA19: 0
A20: 015.812-00 | B20: 2022/0033780-001D | C20: FB | D20: 2022/0033780 | E20: CLU1093 | F20: 01/04/2026 | G20: 30/04/2026 | H20: ANA CRISTINA FABRI DE LIMA | I20: ANA CRISTINA FABRI DE LIMA | J20: NORMAL | K20: CCA | L20: 0 | M20: 0 | O20: 6020.2022/0033780-1 | P20: 0 | U20: =Q20+'APONTAMENTO CREDENCIAMENTO'!U20 -> 0 | V20: =R20+'APONTAMENTO CREDENCIAMENTO'!V20 -> 0 | W20: =S20+'APONTAMENTO CREDENCIAMENTO'!W20 -> 0 | X20: =T20+'APONTAMENTO CREDENCIAMENTO'!X20 -> 0 | Y20: =U20+'APONTAMENTO CREDENCIAMENTO'!Y20 -> 0 | Z20: =V20+'APONTAMENTO CREDENCIAMENTO'!Z20 -> 0 | AA20: =W20+'APONTAMENTO CREDENCIAMENTO'!AA20 -> 0 | AB20: =X20+'APONTAMENTO CREDENCIAMENTO'!AB20 -> 0 | ... EF20: =EB20+'APONTAMENTO CREDENCIAMENTO'!EF20 -> 0 | EP20: 0 | EQ20: 0 | ER20: 0 | ES20: 0 | ET20: 0 | EU20: 0 | EV20: 0 | EX20: 0 | EY20: 0 | EZ20: 0 | FA20: 0 | FB20: 0 | FC20: 0 | FD20: 0 | FF20: 0 | FG20: 0 | FH20: 0 | FI20: 0 | FJ20: 0 | FK20: 0 | FL20: 0 | FM20: 0 | FN20: 0 | FO20: 0 | FP20: 0 | FQ20: 0 | FR20: 0 | FS20: 0 | FT20: 0 | FU20: 0 | FV20: 0 | FW20: 0 | FX20: 0 | FY20: 0 | FZ20: 0 | GA20: 0 | GB20: 0 | GC20: 0 | GD20: 0 | GE20: 0 | GF20: 0 | GG20: 0 | GH20: 0 | GI20: 0 | GJ20: 0 | GL20: 0 | HY20: 0 | HZ20: 0 | IA20: 0
A21: 025.892-00 | B21: 2022/0027355-001 | C21: 4 | D21: 2022/0027355 | E21: EFU6103 | F21: 01/04/2026 | G21: 30/04/2026 | H21: ANDREIA NOEMIA PEREIRA | I21: ANDREIA NOEMIA PEREIRA | J21: NORMAL | K21: EMEI | L21: 0 | M21: 0 | O21: 6020.2022/0027355-2 | P21: 0 | U21: =Q21+'APONTAMENTO CREDENCIAMENTO'!U21 -> 0 | V21: =R21+'APONTAMENTO CREDENCIAMENTO'!V21 -> 0 | W21: =S21+'APONTAMENTO CREDENCIAMENTO'!W21 -> 0 | X21: =T21+'APONTAMENTO CREDENCIAMENTO'!X21 -> 0 | Y21: =U21+'APONTAMENTO CREDENCIAMENTO'!Y21 -> 0 | Z21: =V21+'APONTAMENTO CREDENCIAMENTO'!Z21 -> 0 | AA21: =W21+'APONTAMENTO CREDENCIAMENTO'!AA21 -> 0 | AB21: =X21+'APONTAMENTO CREDENCIAMENTO'!AB21 -> 0 | ... EF21: =EB21+'APONTAMENTO CREDENCIAMENTO'!EF21 -> 0 | EP21: 0 | EQ21: 0 | ER21: 0 | ES21: 0 | ET21: 0 | EU21: 0 | EV21: 0 | EW21: 11465.63 | EX21: 385.23 | EY21: 0 | EZ21: 0 | FA21: 0 | FB21: 0 | FC21: 0 | FD21: 0 | FE21: 11850.86 | FF21: 385.23 | FG21: 0 | FH21: 0 | FI21: 0 | FJ21: 0 | FK21: 0 | FL21: 0 | FM21: 0 | FN21: 0 | FO21: 0 | FP21: 0 | FQ21: 0 | FR21: 0 | FS21: 0 | FT21: 0 | FU21: 0 | FV21: 0 | FW21: 0 | FX21: 0 | FY21: 0 | FZ21: 0 | GA21: 0 | GB21: 0 | GC21: 0 | GD21: 0 | GE21: 0 | GF21: 0 | GG21: 0 | GH21: 0 | GI21: 0 | GJ21: 0 | GL21: 0 | GN21: 0 | GO21: 0 | GP21: 0 | GQ21: 0 | GR21: 0 | GS21: 0 | GT21: 0 | GU21: 0 | GV21: 0 | GW21: 0 | GX21: 0 | GY21: 0 | GZ21: 0 | HA21: 0 | HB21: 0 | HC21: 0 | HD21: 0 | HE21: 0 | HF21: 0 | HG21: 0 | HH21: 0 | HI21: 0 | HJ21: 0 | HK21: 0 | HL21: 0 | HM21: 0 | HN21: 0 | HO21: 0 | HP21: 0 | HW21: 17629.31 | HY21: 0 | HZ21: 0 | IA21: 0 | IB21: FALSE
A22: 025.892-00 | B22: 2022/0027355-001 | C22: FBE | D22: 2022/0027355 | E22: EFU6103 | F22: 01/04/2026 | G22: 30/04/2026 | H22: ANDREIA NOEMIA PEREIRA | I22: ANDREIA NOEMIA PEREIRA | J22: NORMAL | K22: EMEF | L22: 0 | M22: 0 | O22: 6020.2022/0027355-2 | P22: 0 | U22: =Q22+'APONTAMENTO CREDENCIAMENTO'!U22 -> 0 | V22: =R22+'APONTAMENTO CREDENCIAMENTO'!V22 -> 0 | W22: =S22+'APONTAMENTO CREDENCIAMENTO'!W22 -> 0 | X22: =T22+'APONTAMENTO CREDENCIAMENTO'!X22 -> 0 | Y22: =U22+'APONTAMENTO CREDENCIAMENTO'!Y22 -> 0 | Z22: =V22+'APONTAMENTO CREDENCIAMENTO'!Z22 -> 0 | AA22: =W22+'APONTAMENTO CREDENCIAMENTO'!AA22 -> 0 | AB22: =X22+'APONTAMENTO CREDENCIAMENTO'!AB22 -> 0 | ... EF22: =EB22+'APONTAMENTO CREDENCIAMENTO'!EF22 -> 0 | EP22: 0 | EQ22: 0 | ER22: 0 | ES22: 0 | ET22: 0 | EU22: 0 | EV22: 0 | EX22: 0 | EY22: 0 | EZ22: 0 | FA22: 0 | FB22: 0 | FC22: 0 | FD22: 0 | GL22: 0 | HY22: 0 | HZ22: 0 | IA22: 0
A23: 025.892-00 | B23: 2022/0027355-001 | C23: FBE | D23: 2022/0027355 | E23: EFU6103 | F23: 01/04/2026 | G23: 30/04/2026 | H23: ANDREIA NOEMIA PEREIRA | I23: ANDREIA NOEMIA PEREIRA | J23: NORMAL | K23: EMEE | L23: 0 | M23: 0 | O23: 6020.2022/0027355-2 | P23: 0 | Q23: 1 | U23: =Q23+'APONTAMENTO CREDENCIAMENTO'!U23 -> 1 | V23: =R23+'APONTAMENTO CREDENCIAMENTO'!V23 -> 0 | W23: =S23+'APONTAMENTO CREDENCIAMENTO'!W23 -> 0 | X23: =T23+'APONTAMENTO CREDENCIAMENTO'!X23 -> 0 | Y23: =U23+'APONTAMENTO CREDENCIAMENTO'!Y23 -> 1 | Z23: =V23+'APONTAMENTO CREDENCIAMENTO'!Z23 -> 0 | AA23: =W23+'APONTAMENTO CREDENCIAMENTO'!AA23 -> 0 | AB23: =X23+'APONTAMENTO CREDENCIAMENTO'!AB23 -> 0 | ... EF23: =EB23+'APONTAMENTO CREDENCIAMENTO'!EF23 -> 0 | EP23: 1 | EQ23: 0 | ER23: 0 | ES23: 0 | ET23: 0 | EU23: 0 | EV23: 1 | EX23: 0 | EY23: 0 | EZ23: 0 | FA23: 0 | FB23: 0 | FC23: 0 | FD23: 0 | GL23: 0 | HY23: 0 | HZ23: 0 | IA23: 0
A24: 025.892-00 | B24: 2022/0027355-001 | C24: FBE | D24: 2022/0027355 | E24: EFU6103 | F24: 01/04/2026 | G24: 30/04/2026 | H24: ANDREIA NOEMIA PEREIRA | I24: ANDREIA NOEMIA PEREIRA | J24: NORMAL | K24: CEI | L24: 0 | M24: 0 | O24: 6020.2022/0027355-2 | P24: 0 | U24: =Q24+'APONTAMENTO CREDENCIAMENTO'!U24 -> 0 | V24: =R24+'APONTAMENTO CREDENCIAMENTO'!V24 -> 0 | W24: =S24+'APONTAMENTO CREDENCIAMENTO'!W24 -> 0 | X24: =T24+'APONTAMENTO CREDENCIAMENTO'!X24 -> 0 | Y24: =U24+'APONTAMENTO CREDENCIAMENTO'!Y24 -> 0 | Z24: =V24+'APONTAMENTO CREDENCIAMENTO'!Z24 -> 0 | AA24: =W24+'APONTAMENTO CREDENCIAMENTO'!AA24 -> 0 | AB24: =X24+'APONTAMENTO CREDENCIAMENTO'!AB24 -> 0 | ... EF24: =EB24+'APONTAMENTO CREDENCIAMENTO'!EF24 -> 0 | EP24: 0 | EQ24: 0 | ER24: 0 | ES24: 0 | ET24: 0 | EU24: 0 | EV24: 0 | EX24: 0 | EY24: 0 | EZ24: 0 | FA24: 0 | FB24: 0 | FC24: 0 | FD24: 0 | GL24: 0 | HY24: 0 | HZ24: 0 | IA24: 0
A25: 025.892-00 | B25: 2022/0027355-001 | C25: FBE | D25: 2022/0027355 | E25: EFU6103 | F25: 01/04/2026 | G25: 30/04/2026 | H25: ANDREIA NOEMIA PEREIRA | I25: ANDREIA NOEMIA PEREIRA | J25: NORMAL | K25: CCA | L25: 0 | M25: 0 | O25: 6020.2022/0027355-2 | P25: 0 | U25: =Q25+'APONTAMENTO CREDENCIAMENTO'!U25 -> 0 | V25: =R25+'APONTAMENTO CREDENCIAMENTO'!V25 -> 0 | W25: =S25+'APONTAMENTO CREDENCIAMENTO'!W25 -> 0 | X25: =T25+'APONTAMENTO CREDENCIAMENTO'!X25 -> 0 | Y25: =U25+'APONTAMENTO CREDENCIAMENTO'!Y25 -> 0 | Z25: =V25+'APONTAMENTO CREDENCIAMENTO'!Z25 -> 0 | AA25: =W25+'APONTAMENTO CREDENCIAMENTO'!AA25 -> 0 | AB25: =X25+'APONTAMENTO CREDENCIAMENTO'!AB25 -> 0 | ... EF25: =EB25+'APONTAMENTO CREDENCIAMENTO'!EF25 -> 0 | EP25: 0 | EQ25: 0 | ER25: 0 | ES25: 0 | ET25: 0 | EU25: 0 | EV25: 0 | EX25: 0 | EY25: 0 | EZ25: 0 | FA25: 0 | FB25: 0 | FC25: 0 | FD25: 0 | FF25: 0 | FG25: 0 | FH25: 0 | FI25: 0 | FJ25: 0 | FK25: 0 | FL25: 0 | FM25: 0 | FN25: 0 | FO25: 0 | FP25: 0 | FQ25: 0 | FR25: 0 | FS25: 0 | FT25: 0 | FU25: 0 | FV25: 0 | FW25: 0 | FX25: 0 | FY25: 0 | FZ25: 0 | GA25: 0 | GB25: 0 | GC25: 0 | GD25: 0 | GE25: 0 | GF25: 0 | GG25: 0 | GH25: 0 | GI25: 0 | GJ25: 0 | GL25: 0 | HY25: 0 | HZ25: 0 | IA25: 0
A26: 022.524-00 | B26: 2022/0026000-001 | C26: 1 | D26: 2022/0026000 | E26: DTD7389 | F26: 01/04/2026 | G26: 30/04/2026 | H26: ANTONIO CARLOS GOMES | I26: ANTONIO CARLOS GOMES | J26: NORMAL | K26: EMEI | L26: 0 | M26: 0 | O26: 6020.2022/0026000-0 | P26: 0 | U26: =Q26+'APONTAMENTO CREDENCIAMENTO'!U26 -> 0 | V26: =R26+'APONTAMENTO CREDENCIAMENTO'!V26 -> 0 | W26: =S26+'APONTAMENTO CREDENCIAMENTO'!W26 -> 0 | X26: =T26+'APONTAMENTO CREDENCIAMENTO'!X26 -> 0 | Y26: =U26+'APONTAMENTO CREDENCIAMENTO'!Y26 -> 0 | Z26: =V26+'APONTAMENTO CREDENCIAMENTO'!Z26 -> 0 | AA26: =W26+'APONTAMENTO CREDENCIAMENTO'!AA26 -> 0 | AB26: =X26+'APONTAMENTO CREDENCIAMENTO'!AB26 -> 0 | ... EF26: =EB26+'APONTAMENTO CREDENCIAMENTO'!EF26 -> 0 | EP26: 0 | EQ26: 0 | ER26: 0 | ES26: 0 | ET26: 0 | EU26: 0 | EV26: 0 | EW26: 0 | EX26: 14811.89 | EY26: 0 | EZ26: 1181.372 | FA26: -295.343 | FB26: 0 | FC26: 0 | FD26: 0 | FE26: 16257.039 | FF26: 14811.89 | FG26: 0 | FH26: 0 | FI26: 0 | FJ26: 0 | FK26: 0 | FL26: 0 | FM26: 1181.372 | FN26: 0 | FO26: 0 | FP26: 0 | FQ26: 0 | FR26: 0 | FS26: 0 | FT26: 0 | FU26: 0 | FV26: -179.774 | FW26: 0 | FX26: 0 | FY26: 0 | FZ26: 0 | GA26: -115.569 | GB26: 0 | GC26: 0 | GD26: 0 | GE26: 0 | GF26: 0 | GG26: 0 | GH26: 0 | GI26: 0 | GJ26: 0 | GL26: 0 | GN26: 0 | GO26: 0 | GP26: 0 | GQ26: 0 | GR26: 0 | GS26: 0 | GT26: 0 | GU26: 0 | GV26: 0 | GW26: 0 | GX26: 0 | GY26: 0 | GZ26: 0 | HA26: 0 | HB26: 0 | HC26: 0 | HD26: 0 | HE26: 0 | HF26: 0 | HG26: 0 | HH26: 0 | HI26: 0 | HJ26: 0 | HK26: 0 | HL26: 0 | HM26: 0 | HN26: 0 | HO26: 0 | HP26: 0 | HW26: 17629.31 | HY26: 0 | HZ26: 0 | IA26: 0 | IB26: FALSE
A27: 022.524-00 | B27: 2022/0026000-001 | C27: FB | D27: 2022/0026000 | E27: DTD7389 | F27: 01/04/2026 | G27: 30/04/2026 | H27: ANTONIO CARLOS GOMES | I27: ANTONIO CARLOS GOMES | J27: NORMAL | K27: EMEF | L27: 58 | M27: 0 | O27: 6020.2022/0026000-0 | P27: 0 | Q27: 35 | U27: =Q27+'APONTAMENTO CREDENCIAMENTO'!U27 -> 35 | V27: =R27+'APONTAMENTO CREDENCIAMENTO'!V27 -> 0 | W27: =S27+'APONTAMENTO CREDENCIAMENTO'!W27 -> 0 | X27: =T27+'APONTAMENTO CREDENCIAMENTO'!X27 -> 0 | Y27: =U27+'APONTAMENTO CREDENCIAMENTO'!Y27 -> 35 | Z27: =V27+'APONTAMENTO CREDENCIAMENTO'!Z27 -> 0 | AA27: =W27+'APONTAMENTO CREDENCIAMENTO'!AA27 -> 0 | AB27: =X27+'APONTAMENTO CREDENCIAMENTO'!AB27 -> 0 | ... EF27: =EB27+'APONTAMENTO CREDENCIAMENTO'!EF27 -> 0 | EP27: 35 | EQ27: -1 | ER27: 3 | ES27: 0 | ET27: 0 | EU27: 0 | EV27: 37 | EX27: 0 | EY27: 559.12 | EZ27: 0 | FA27: 0 | FB27: 0 | FC27: 0 | FD27: 0 | GL27: 0 | HY27: 0 | HZ27: 0 | IA27: 0
A28: 022.524-00 | B28: 2022/0026000-001 | C28: FB | D28: 2022/0026000 | E28: DTD7389 | F28: 01/04/2026 | G28: 30/04/2026 | H28: ANTONIO CARLOS GOMES | I28: ANTONIO CARLOS GOMES | J28: NORMAL | K28: EMEE | L28: 0 | M28: 0 | O28: 6020.2022/0026000-0 | P28: 0 | U28: =Q28+'APONTAMENTO CREDENCIAMENTO'!U28 -> 0 | V28: =R28+'APONTAMENTO CREDENCIAMENTO'!V28 -> 0 | W28: =S28+'APONTAMENTO CREDENCIAMENTO'!W28 -> 0 | X28: =T28+'APONTAMENTO CREDENCIAMENTO'!X28 -> 0 | Y28: =U28+'APONTAMENTO CREDENCIAMENTO'!Y28 -> 0 | Z28: =V28+'APONTAMENTO CREDENCIAMENTO'!Z28 -> 0 | AA28: =W28+'APONTAMENTO CREDENCIAMENTO'!AA28 -> 0 | AB28: =X28+'APONTAMENTO CREDENCIAMENTO'!AB28 -> 0 | ... EF28: =EB28+'APONTAMENTO CREDENCIAMENTO'!EF28 -> 0 | EP28: 0 | EQ28: 0 | ER28: 0 | ES28: 0 | ET28: 0 | EU28: 0 | EV28: 0 | EX28: 0 | EY28: 0 | EZ28: 0 | FA28: 0 | FB28: 0 | FC28: 0 | FD28: 0 | GL28: 0 | HY28: 0 | HZ28: 0 | IA28: 0
A29: 022.524-00 | B29: 2022/0026000-001 | C29: FB | D29: 2022/0026000 | E29: DTD7389 | F29: 01/04/2026 | G29: 30/04/2026 | H29: ANTONIO CARLOS GOMES | I29: ANTONIO CARLOS GOMES | J29: NORMAL | K29: CEI | L29: 0 | M29: 0 | O29: 6020.2022/0026000-0 | P29: 0 | U29: =Q29+'APONTAMENTO CREDENCIAMENTO'!U29 -> 0 | V29: =R29+'APONTAMENTO CREDENCIAMENTO'!V29 -> 0 | W29: =S29+'APONTAMENTO CREDENCIAMENTO'!W29 -> 0 | X29: =T29+'APONTAMENTO CREDENCIAMENTO'!X29 -> 0 | Y29: =U29+'APONTAMENTO CREDENCIAMENTO'!Y29 -> 0 | Z29: =V29+'APONTAMENTO CREDENCIAMENTO'!Z29 -> 0 | AA29: =W29+'APONTAMENTO CREDENCIAMENTO'!AA29 -> 0 | AB29: =X29+'APONTAMENTO CREDENCIAMENTO'!AB29 -> 0 | ... EF29: =EB29+'APONTAMENTO CREDENCIAMENTO'!EF29 -> 0 | EP29: 0 | EQ29: 0 | ER29: 0 | ES29: 0 | ET29: 0 | EU29: 0 | EV29: 0 | EX29: 0 | EY29: 0 | EZ29: 0 | FA29: 0 | FB29: 0 | FC29: 0 | FD29: 0 | GL29: 0 | HY29: 0 | HZ29: 0 | IA29: 0
A30: 022.524-00 | B30: 2022/0026000-001 | C30: FB | D30: 2022/0026000 | E30: DTD7389 | F30: 01/04/2026 | G30: 30/04/2026 | H30: ANTONIO CARLOS GOMES | I30: ANTONIO CARLOS GOMES | J30: NORMAL | K30: CCA | L30: 0 | M30: 0 | O30: 6020.2022/0026000-0 | P30: 0 | U30: =Q30+'APONTAMENTO CREDENCIAMENTO'!U30 -> 0 | V30: =R30+'APONTAMENTO CREDENCIAMENTO'!V30 -> 0 | W30: =S30+'APONTAMENTO CREDENCIAMENTO'!W30 -> 0 | X30: =T30+'APONTAMENTO CREDENCIAMENTO'!X30 -> 0 | Y30: =U30+'APONTAMENTO CREDENCIAMENTO'!Y30 -> 0 | Z30: =V30+'APONTAMENTO CREDENCIAMENTO'!Z30 -> 0 | AA30: =W30+'APONTAMENTO CREDENCIAMENTO'!AA30 -> 0 | AB30: =X30+'APONTAMENTO CREDENCIAMENTO'!AB30 -> 0 | ... EF30: =EB30+'APONTAMENTO CREDENCIAMENTO'!EF30 -> 0 | EP30: 0 | EQ30: 0 | ER30: 0 | ES30: 0 | ET30: 0 | EU30: 0 | EV30: 0 | EX30: 0 | EY30: 0 | EZ30: 0 | FA30: 0 | FB30: 0 | FC30: 0 | FD30: 0 | FF30: 0 | FG30: 0 | FH30: 0 | FI30: 0 | FJ30: 0 | FK30: 0 | FL30: 0 | FM30: 0 | FN30: 0 | FO30: 0 | FP30: 0 | FQ30: 0 | FR30: 0 | FS30: 0 | FT30: 0 | FU30: 0 | FV30: 0 | FW30: 0 | FX30: 0 | FY30: 0 | FZ30: 0 | GA30: 0 | GB30: 0 | GC30: 0 | GD30: 0 | GE30: 0 | GF30: 0 | GG30: 0 | GH30: 0 | GI30: 0 | GJ30: 0 | GL30: 0 | HY30: 0 | HZ30: 0 | IA30: 0
A31: 005.388-00 | B31: 2022/0028814-001 | C31: 2 | D31: 2022/0028814 | E31: DTC6900 | F31: 01/04/2026 | G31: 30/04/2026 | H31: CARLOS OMAR ALVES | I31: CARLOS OMAR ALVES | J31: ADAPTADO | K31: EMEI | L31: 0 | M31: 0 | O31: 6020.2022/0028814-2 | P31: 0 | R31: 1 | U31: =Q31+'APONTAMENTO CREDENCIAMENTO'!U31 -> 0 | V31: =R31+'APONTAMENTO CREDENCIAMENTO'!V31 -> 1 | W31: =S31+'APONTAMENTO CREDENCIAMENTO'!W31 -> 0 | X31: =T31+'APONTAMENTO CREDENCIAMENTO'!X31 -> 0 | Y31: =U31+'APONTAMENTO CREDENCIAMENTO'!Y31 -> 0 | Z31: =V31+'APONTAMENTO CREDENCIAMENTO'!Z31 -> 1 | AA31: =W31+'APONTAMENTO CREDENCIAMENTO'!AA31 -> 0 | AB31: =X31+'APONTAMENTO CREDENCIAMENTO'!AB31 -> 0 | ... EF31: =EB31+'APONTAMENTO CREDENCIAMENTO'!EF31 -> 0 | EP31: 0 | EQ31: 0 | ER31: 0 | ES31: 1 | ET31: 0 | EU31: 0 | EV31: 1 | EW31: 0 | EX31: 14393.93 | EY31: 0 | EZ31: 0 | FA31: 0 | FB31: 0 | FC31: 0 | FD31: 0 | FE31: 14393.93 | FF31: 14393.93 | FG31: 0 | FH31: 0 | FI31: 0 | FJ31: 0 | FK31: 0 | FL31: 0 | FM31: 0 | FN31: 0 | FO31: 0 | FP31: 0 | FQ31: 0 | FR31: 0 | FS31: 0 | FT31: 0 | FU31: 0 | FV31: 0 | FW31: 0 | FX31: 0 | FY31: 0 | FZ31: 0 | GA31: 0 | GB31: 0 | GC31: 0 | GD31: 0 | GE31: 0 | GF31: 0 | GG31: 0 | GH31: 0 | GI31: 0 | GJ31: 0 | GL31: 0 | GN31: 0 | GO31: 0 | GP31: 0 | GQ31: 0 | GR31: 0 | GS31: 0 | GT31: 0 | GU31: 0 | GV31: 0 | GW31: 0 | GX31: 0 | GY31: 0 | GZ31: 0 | HA31: 0 | HB31: 0 | HC31: 0 | HD31: 0 | HE31: 0 | HF31: 0 | HG31: 0 | HH31: 0 | HI31: 0 | HJ31: 0 | HK31: 0 | HL31: 0 | HM31: 0 | HN31: 0 | HO31: 0 | HP31: 0 | HW31: 17629.31 | HY31: 0 | HZ31: 0 | IA31: 0 | IB31: FALSE
A32: 005.388-00 | B32: 2022/0028814-001 | C32: FB | D32: 2022/0028814 | E32: DTC6900 | F32: 01/04/2026 | G32: 30/04/2026 | H32: CARLOS OMAR ALVES | I32: CARLOS OMAR ALVES | J32: ADAPTADO | K32: EMEF | L32: 0 | M32: 0 | O32: 6020.2022/0028814-2 | P32: 0 | Q32: 1 | R32: 4 | S32: 1 | U32: =Q32+'APONTAMENTO CREDENCIAMENTO'!U32 -> 1 | V32: =R32+'APONTAMENTO CREDENCIAMENTO'!V32 -> 4 | W32: =S32+'APONTAMENTO CREDENCIAMENTO'!W32 -> 1 | X32: =T32+'APONTAMENTO CREDENCIAMENTO'!X32 -> 0 | Y32: =U32+'APONTAMENTO CREDENCIAMENTO'!Y32 -> 1 | Z32: =V32+'APONTAMENTO CREDENCIAMENTO'!Z32 -> 4 | AA32: =W32+'APONTAMENTO CREDENCIAMENTO'!AA32 -> 1 | AB32: =X32+'APONTAMENTO CREDENCIAMENTO'!AB32 -> 0 | ... EF32: =EB32+'APONTAMENTO CREDENCIAMENTO'!EF32 -> 0 | EP32: 1 | EQ32: 0 | ER32: 1 | ES32: 4 | ET32: 0 | EU32: 0 | EV32: 6 | EX32: 0 | EY32: 0 | EZ32: 0 | FA32: 0 | FB32: 0 | FC32: 0 | FD32: 0 | GL32: 0 | HY32: 0 | HZ32: 0 | IA32: 0
A33: 005.388-00 | B33: 2022/0028814-001 | C33: FB | D33: 2022/0028814 | E33: DTC6900 | F33: 01/04/2026 | G33: 30/04/2026 | H33: CARLOS OMAR ALVES | I33: CARLOS OMAR ALVES | J33: ADAPTADO | K33: EMEE | L33: 0 | M33: 0 | O33: 6020.2022/0028814-2 | P33: 0 | U33: =Q33+'APONTAMENTO CREDENCIAMENTO'!U33 -> 0 | V33: =R33+'APONTAMENTO CREDENCIAMENTO'!V33 -> 0 | W33: =S33+'APONTAMENTO CREDENCIAMENTO'!W33 -> 0 | X33: =T33+'APONTAMENTO CREDENCIAMENTO'!X33 -> 0 | Y33: =U33+'APONTAMENTO CREDENCIAMENTO'!Y33 -> 0 | Z33: =V33+'APONTAMENTO CREDENCIAMENTO'!Z33 -> 0 | AA33: =W33+'APONTAMENTO CREDENCIAMENTO'!AA33 -> 0 | AB33: =X33+'APONTAMENTO CREDENCIAMENTO'!AB33 -> 0 | ... EF33: =EB33+'APONTAMENTO CREDENCIAMENTO'!EF33 -> 0 | EP33: 0 | EQ33: 0 | ER33: 0 | ES33: 0 | ET33: 0 | EU33: 0 | EV33: 0 | EX33: 0 | EY33: 0 | EZ33: 0 | FA33: 0 | FB33: 0 | FC33: 0 | FD33: 0 | GL33: 0 | HY33: 0 | HZ33: 0 | IA33: 0
A34: 005.388-00 | B34: 2022/0028814-001 | C34: FB | D34: 2022/0028814 | E34: DTC6900 | F34: 01/04/2026 | G34: 30/04/2026 | H34: CARLOS OMAR ALVES | I34: CARLOS OMAR ALVES | J34: ADAPTADO | K34: CEI | L34: 0 | M34: 0 | O34: 6020.2022/0028814-2 | P34: 0 | U34: =Q34+'APONTAMENTO CREDENCIAMENTO'!U34 -> 0 | V34: =R34+'APONTAMENTO CREDENCIAMENTO'!V34 -> 0 | W34: =S34+'APONTAMENTO CREDENCIAMENTO'!W34 -> 0 | X34: =T34+'APONTAMENTO CREDENCIAMENTO'!X34 -> 0 | Y34: =U34+'APONTAMENTO CREDENCIAMENTO'!Y34 -> 0 | Z34: =V34+'APONTAMENTO CREDENCIAMENTO'!Z34 -> 0 | AA34: =W34+'APONTAMENTO CREDENCIAMENTO'!AA34 -> 0 | AB34: =X34+'APONTAMENTO CREDENCIAMENTO'!AB34 -> 0 | ... EF34: =EB34+'APONTAMENTO CREDENCIAMENTO'!EF34 -> 0 | EP34: 0 | EQ34: 0 | ER34: 0 | ES34: 0 | ET34: 0 | EU34: 0 | EV34: 0 | EX34: 0 | EY34: 0 | EZ34: 0 | FA34: 0 | FB34: 0 | FC34: 0 | FD34: 0 | GL34: 0 | HY34: 0 | HZ34: 0 | IA34: 0
A35: 005.388-00 | B35: 2022/0028814-001 | C35: FB | D35: 2022/0028814 | E35: DTC6900 | F35: 01/04/2026 | G35: 30/04/2026 | H35: CARLOS OMAR ALVES | I35: CARLOS OMAR ALVES | J35: ADAPTADO | K35: CCA | L35: 0 | M35: 0 | O35: 6020.2022/0028814-2 | P35: 0 | U35: =Q35+'APONTAMENTO CREDENCIAMENTO'!U35 -> 0 | V35: =R35+'APONTAMENTO CREDENCIAMENTO'!V35 -> 0 | W35: =S35+'APONTAMENTO CREDENCIAMENTO'!W35 -> 0 | X35: =T35+'APONTAMENTO CREDENCIAMENTO'!X35 -> 0 | Y35: =U35+'APONTAMENTO CREDENCIAMENTO'!Y35 -> 0 | Z35: =V35+'APONTAMENTO CREDENCIAMENTO'!Z35 -> 0 | AA35: =W35+'APONTAMENTO CREDENCIAMENTO'!AA35 -> 0 | AB35: =X35+'APONTAMENTO CREDENCIAMENTO'!AB35 -> 0 | ... EF35: =EB35+'APONTAMENTO CREDENCIAMENTO'!EF35 -> 0 | EP35: 0 | EQ35: 0 | ER35: 0 | ES35: 0 | ET35: 0 | EU35: 0 | EV35: 0 | EX35: 0 | EY35: 0 | EZ35: 0 | FA35: 0 | FB35: 0 | FC35: 0 | FD35: 0 | FF35: 0 | FG35: 0 | FH35: 0 | FI35: 0 | FJ35: 0 | FK35: 0 | FL35: 0 | FM35: 0 | FN35: 0 | FO35: 0 | FP35: 0 | FQ35: 0 | FR35: 0 | FS35: 0 | FT35: 0 | FU35: 0 | FV35: 0 | FW35: 0 | FX35: 0 | FY35: 0 | FZ35: 0 | GA35: 0 | GB35: 0 | GC35: 0 | GD35: 0 | GE35: 0 | GF35: 0 | GG35: 0 | GH35: 0 | GI35: 0 | GJ35: 0 | GL35: 0 | HY35: 0 | HZ35: 0 | IA35: 0
A36: 019.284-00 | B36: 2022/0031991-001 | C36: 1 | D36: 2022/0031991 | E36: DTA8459 | F36: 01/04/2026 | G36: 30/04/2026 | H36: CRISTIANE ROSIMEIRE DIAS | I36: CRISTIANE ROSIMEIRE DIAS | J36: NORMAL | K36: EMEI | L36: 0 | M36: 0 | O36: 6020.2022/0031991-9 | P36: 0 | Q36: 3 | U36: =Q36+'APONTAMENTO CREDENCIAMENTO'!U36 -> 3 | V36: =R36+'APONTAMENTO CREDENCIAMENTO'!V36 -> 0 | W36: =S36+'APONTAMENTO CREDENCIAMENTO'!W36 -> 0 | X36: =T36+'APONTAMENTO CREDENCIAMENTO'!X36 -> 0 | Y36: =U36+'APONTAMENTO CREDENCIAMENTO'!Y36 -> 3 | Z36: =V36+'APONTAMENTO CREDENCIAMENTO'!Z36 -> 0 | AA36: =W36+'APONTAMENTO CREDENCIAMENTO'!AA36 -> 0 | AB36: =X36+'APONTAMENTO CREDENCIAMENTO'!AB36 -> 0 | ... EF36: =EB36+'APONTAMENTO CREDENCIAMENTO'!EF36 -> 0 | EP36: 3 | EQ36: 0 | ER36: 0 | ES36: 0 | ET36: 0 | EU36: 0 | EV36: 3 | EW36: 0 | EX36: 12115.28 | EY36: 0 | EZ36: 0 | FA36: -372.389 | FB36: 0 | FC36: 0 | FD36: 0 | FE36: 11742.891 | FF36: 12115.28 | FG36: -372.389 | FH36: 0 | FI36: 0 | FJ36: 0 | FK36: 0 | FL36: 0 | FM36: 0 | FN36: 0 | FO36: 0 | FP36: 0 | FQ36: 0 | FR36: 0 | FS36: 0 | FT36: 0 | FU36: 0 | FV36: 0 | FW36: 0 | FX36: 0 | FY36: 0 | FZ36: 0 | GA36: 0 | GB36: 0 | GC36: 0 | GD36: 0 | GE36: 0 | GF36: 0 | GG36: 0 | GH36: 0 | GI36: 0 | GJ36: 0 | GL36: 0 | GN36: 0 | GO36: 0 | GP36: 0 | GQ36: 0 | GR36: 0 | GS36: 0 | GT36: 0 | GU36: 0 | GV36: 0 | GW36: 0 | GX36: 0 | GY36: 0 | GZ36: 0 | HA36: 0 | HB36: 0 | HC36: 0 | HD36: 0 | HE36: 0 | HF36: 0 | HG36: 0 | HH36: 0 | HI36: 0 | HJ36: 0 | HK36: 0 | HL36: 0 | HM36: 0 | HN36: 0 | HO36: 0 | HP36: 0 | HW36: 17629.31 | HY36: 0 | HZ36: 0 | IA36: 0 | IB36: FALSE
A37: 019.284-00 | B37: 2022/0031991-001 | C37: FB | D37: 2022/0031991 | E37: DTA8459 | F37: 01/04/2026 | G37: 30/04/2026 | H37: CRISTIANE ROSIMEIRE DIAS | I37: CRISTIANE ROSIMEIRE DIAS | J37: NORMAL | K37: EMEF | L37: 0 | M37: 0 | O37: 6020.2022/0031991-9 | P37: 0 | Q37: 25 | U37: =Q37+'APONTAMENTO CREDENCIAMENTO'!U37 -> 24 | V37: =R37+'APONTAMENTO CREDENCIAMENTO'!V37 -> 0 | W37: =S37+'APONTAMENTO CREDENCIAMENTO'!W37 -> 0 | X37: =T37+'APONTAMENTO CREDENCIAMENTO'!X37 -> 0 | Y37: =U37+'APONTAMENTO CREDENCIAMENTO'!Y37 -> 24 | Z37: =V37+'APONTAMENTO CREDENCIAMENTO'!Z37 -> 0 | AA37: =W37+'APONTAMENTO CREDENCIAMENTO'!AA37 -> 0 | AB37: =X37+'APONTAMENTO CREDENCIAMENTO'!AB37 -> 0 | ... EF37: =EB37+'APONTAMENTO CREDENCIAMENTO'!EF37 -> 0 | EP37: 25 | EQ37: -1 | ER37: 0 | ES37: 0 | ET37: 0 | EU37: 0 | EV37: 24 | EX37: 0 | EY37: 0 | EZ37: 0 | FA37: 0 | FB37: 0 | FC37: 0 | FD37: 0 | GL37: 0 | HY37: 0 | HZ37: 0 | IA37: 0
A38: 019.284-00 | B38: 2022/0031991-001 | C38: FB | D38: 2022/0031991 | E38: DTA8459 | F38: 01/04/2026 | G38: 30/04/2026 | H38: CRISTIANE ROSIMEIRE DIAS | I38: CRISTIANE ROSIMEIRE DIAS | J38: NORMAL | K38: EMEE | L38: 0 | M38: 0 | O38: 6020.2022/0031991-9 | P38: 0 | U38: =Q38+'APONTAMENTO CREDENCIAMENTO'!U38 -> 0 | V38: =R38+'APONTAMENTO CREDENCIAMENTO'!V38 -> 0 | W38: =S38+'APONTAMENTO CREDENCIAMENTO'!W38 -> 0 | X38: =T38+'APONTAMENTO CREDENCIAMENTO'!X38 -> 0 | Y38: =U38+'APONTAMENTO CREDENCIAMENTO'!Y38 -> 0 | Z38: =V38+'APONTAMENTO CREDENCIAMENTO'!Z38 -> 0 | AA38: =W38+'APONTAMENTO CREDENCIAMENTO'!AA38 -> 0 | AB38: =X38+'APONTAMENTO CREDENCIAMENTO'!AB38 -> 0 | ... EF38: =EB38+'APONTAMENTO CREDENCIAMENTO'!EF38 -> 0 | EP38: 0 | EQ38: 0 | ER38: 0 | ES38: 0 | ET38: 0 | EU38: 0 | EV38: 0 | EX38: 0 | EY38: 0 | EZ38: 0 | FA38: 0 | FB38: 0 | FC38: 0 | FD38: 0 | GL38: 0 | HY38: 0 | HZ38: 0 | IA38: 0
A39: 019.284-00 | B39: 2022/0031991-001 | C39: FB | D39: 2022/0031991 | E39: DTA8459 | F39: 01/04/2026 | G39: 30/04/2026 | H39: CRISTIANE ROSIMEIRE DIAS | I39: CRISTIANE ROSIMEIRE DIAS | J39: NORMAL | K39: CEI | L39: 0 | M39: 0 | O39: 6020.2022/0031991-9 | P39: 0 | U39: =Q39+'APONTAMENTO CREDENCIAMENTO'!U39 -> 0 | V39: =R39+'APONTAMENTO CREDENCIAMENTO'!V39 -> 0 | W39: =S39+'APONTAMENTO CREDENCIAMENTO'!W39 -> 0 | X39: =T39+'APONTAMENTO CREDENCIAMENTO'!X39 -> 0 | Y39: =U39+'APONTAMENTO CREDENCIAMENTO'!Y39 -> 0 | Z39: =V39+'APONTAMENTO CREDENCIAMENTO'!Z39 -> 0 | AA39: =W39+'APONTAMENTO CREDENCIAMENTO'!AA39 -> 0 | AB39: =X39+'APONTAMENTO CREDENCIAMENTO'!AB39 -> 0 | ... EF39: =EB39+'APONTAMENTO CREDENCIAMENTO'!EF39 -> 0 | EP39: 0 | EQ39: 0 | ER39: 0 | ES39: 0 | ET39: 0 | EU39: 0 | EV39: 0 | EX39: 0 | EY39: 0 | EZ39: 0 | FA39: 0 | FB39: 0 | FC39: 0 | FD39: 0 | GL39: 0 | HY39: 0 | HZ39: 0 | IA39: 0
A40: 019.284-00 | B40: 2022/0031991-001 | C40: FB | D40: 2022/0031991 | E40: DTA8459 | F40: 01/04/2026 | G40: 30/04/2026 | H40: CRISTIANE ROSIMEIRE DIAS | I40: CRISTIANE ROSIMEIRE DIAS | J40: NORMAL | K40: CCA | L40: 0 | M40: 0 | O40: 6020.2022/0031991-9 | P40: 0 | U40: =Q40+'APONTAMENTO CREDENCIAMENTO'!U40 -> 0 | V40: =R40+'APONTAMENTO CREDENCIAMENTO'!V40 -> 0 | W40: =S40+'APONTAMENTO CREDENCIAMENTO'!W40 -> 0 | X40: =T40+'APONTAMENTO CREDENCIAMENTO'!X40 -> 0 | Y40: =U40+'APONTAMENTO CREDENCIAMENTO'!Y40 -> 0 | Z40: =V40+'APONTAMENTO CREDENCIAMENTO'!Z40 -> 0 | AA40: =W40+'APONTAMENTO CREDENCIAMENTO'!AA40 -> 0 | AB40: =X40+'APONTAMENTO CREDENCIAMENTO'!AB40 -> 0 | ... EF40: =EB40+'APONTAMENTO CREDENCIAMENTO'!EF40 -> 0 | EP40: 0 | EQ40: 0 | ER40: 0 | ES40: 0 | ET40: 0 | EU40: 0 | EV40: 0 | EX40: 0 | EY40: 0 | EZ40: 0 | FA40: 0 | FB40: 0 | FC40: 0 | FD40: 0 | FF40: 0 | FG40: 0 | FH40: 0 | FI40: 0 | FJ40: 0 | FK40: 0 | FL40: 0 | FM40: 0 | FN40: 0 | FO40: 0 | FP40: 0 | FQ40: 0 | FR40: 0 | FS40: 0 | FT40: 0 | FU40: 0 | FV40: 0 | FW40: 0 | FX40: 0 | FY40: 0 | FZ40: 0 | GA40: 0 | GB40: 0 | GC40: 0 | GD40: 0 | GE40: 0 | GF40: 0 | GG40: 0 | GH40: 0 | GI40: 0 | GJ40: 0 | GL40: 0 | HY40: 0 | HZ40: 0 | IA40: 0
A41: 016.845-00 | B41: 2022/0026174-001 | C41: 1 | D41: 2022/0026174 | E41: CXA5755 | F41: 01/04/2026 | G41: 30/04/2026 | H41: DIONISIO SCARPONE | I41: DIONISIO SCARPONE | J41: NORMAL | K41: EMEI | L41: 0 | M41: 0 | O41: 6020.2022/0026174-0 | P41: 0 | Q41: 1 | U41: =Q41+'APONTAMENTO CREDENCIAMENTO'!U41 -> 1 | V41: =R41+'APONTAMENTO CREDENCIAMENTO'!V41 -> 0 | W41: =S41+'APONTAMENTO CREDENCIAMENTO'!W41 -> 0 | X41: =T41+'APONTAMENTO CREDENCIAMENTO'!X41 -> 0 | Y41: =U41+'APONTAMENTO CREDENCIAMENTO'!Y41 -> 1 | Z41: =V41+'APONTAMENTO CREDENCIAMENTO'!Z41 -> 0 | AA41: =W41+'APONTAMENTO CREDENCIAMENTO'!AA41 -> 0 | AB41: =X41+'APONTAMENTO CREDENCIAMENTO'!AB41 -> 0 | ... EF41: =EB41+'APONTAMENTO CREDENCIAMENTO'!EF41 -> 0 | EP41: 1 | EQ41: 0 | ER41: 0 | ES41: 0 | ET41: 0 | EU41: 0 | EV41: 1 | EW41: 0 | EX41: 17123.27 | EY41: 0 | EZ41: 192.615 | FA41: 0 | FB41: 0 | FC41: 0 | FD41: 0 | FE41: 17460.485 | FF41: 17123.27 | FG41: 0 | FH41: 0 | FI41: 0 | FJ41: 0 | FK41: 0 | FL41: 0 | FM41: 0 | FN41: 0 | FO41: 0 | FP41: 0 | FQ41: 0 | FR41: 0 | FS41: 0 | FT41: 0 | FU41: 192.615 | FV41: 0 | FW41: 0 | FX41: 0 | FY41: 0 | FZ41: 0 | GA41: 0 | GB41: 0 | GC41: 0 | GD41: 0 | GE41: 0 | GF41: 0 | GG41: 0 | GH41: 0 | GI41: 0 | GJ41: 0 | GL41: 0 | GN41: 0 | GO41: 0 | GP41: 0 | GQ41: 0 | GR41: 0 | GS41: 0 | GT41: 0 | GU41: 0 | GV41: 0 | GW41: 0 | GX41: 0 | GY41: 0 | GZ41: 0 | HA41: 0 | HB41: 0 | HC41: 0 | HD41: 0 | HE41: 0 | HF41: 0 | HG41: 0 | HH41: 0 | HI41: 0 | HJ41: 0 | HK41: 0 | HL41: 0 | HM41: 0 | HN41: 0 | HO41: 0 | HP41: 0 | HW41: 17629.31 | HY41: 0 | HZ41: 0 | IA41: 0 | IB41: FALSE
A42: 016.845-00 | B42: 2022/0026174-001 | C42: FB | D42: 2022/0026174 | E42: CXA5755 | F42: 01/04/2026 | G42: 30/04/2026 | H42: DIONISIO SCARPONE | I42: DIONISIO SCARPONE | J42: NORMAL | K42: EMEF | L42: 15 | M42: 0 | O42: 6020.2022/0026174-0 | P42: 0 | Q42: 35 | S42: 5 | U42: =Q42+'APONTAMENTO CREDENCIAMENTO'!U42 -> 35 | V42: =R42+'APONTAMENTO CREDENCIAMENTO'!V42 -> 0 | W42: =S42+'APONTAMENTO CREDENCIAMENTO'!W42 -> 5 | X42: =T42+'APONTAMENTO CREDENCIAMENTO'!X42 -> 0 | Y42: =U42+'APONTAMENTO CREDENCIAMENTO'!Y42 -> 35 | Z42: =V42+'APONTAMENTO CREDENCIAMENTO'!Z42 -> 0 | AA42: =W42+'APONTAMENTO CREDENCIAMENTO'!AA42 -> 5 | AB42: =X42+'APONTAMENTO CREDENCIAMENTO'!AB42 -> 0 | ... EF42: =EB42+'APONTAMENTO CREDENCIAMENTO'!EF42 -> 0 | EP42: 35 | EQ42: 1 | ER42: 5 | ES42: 0 | ET42: 0 | EU42: 0 | EV42: 41 | EX42: 0 | EY42: 144.6 | EZ42: 0 | FA42: 0 | FB42: 0 | FC42: 0 | FD42: 0 | GL42: 0 | HY42: 0 | HZ42: 0 | IA42: 0
A43: 016.845-00 | B43: 2022/0026174-001 | C43: FB | D43: 2022/0026174 | E43: CXA5755 | F43: 01/04/2026 | G43: 30/04/2026 | H43: DIONISIO SCARPONE | I43: DIONISIO SCARPONE | J43: NORMAL | K43: EMEE | L43: 0 | M43: 0 | O43: 6020.2022/0026174-0 | P43: 0 | U43: =Q43+'APONTAMENTO CREDENCIAMENTO'!U43 -> 0 | V43: =R43+'APONTAMENTO CREDENCIAMENTO'!V43 -> 0 | W43: =S43+'APONTAMENTO CREDENCIAMENTO'!W43 -> 0 | X43: =T43+'APONTAMENTO CREDENCIAMENTO'!X43 -> 0 | Y43: =U43+'APONTAMENTO CREDENCIAMENTO'!Y43 -> 0 | Z43: =V43+'APONTAMENTO CREDENCIAMENTO'!Z43 -> 0 | AA43: =W43+'APONTAMENTO CREDENCIAMENTO'!AA43 -> 0 | AB43: =X43+'APONTAMENTO CREDENCIAMENTO'!AB43 -> 0 | ... EF43: =EB43+'APONTAMENTO CREDENCIAMENTO'!EF43 -> 0 | EP43: 0 | EQ43: 0 | ER43: 0 | ES43: 0 | ET43: 0 | EU43: 0 | EV43: 0 | EX43: 0 | EY43: 0 | EZ43: 0 | FA43: 0 | FB43: 0 | FC43: 0 | FD43: 0 | GL43: 0 | HY43: 0 | HZ43: 0 | IA43: 0
A44: 016.845-00 | B44: 2022/0026174-001 | C44: FB | D44: 2022/0026174 | E44: CXA5755 | F44: 01/04/2026 | G44: 30/04/2026 | H44: DIONISIO SCARPONE | I44: DIONISIO SCARPONE | J44: NORMAL | K44: CEI | L44: 0 | M44: 0 | O44: 6020.2022/0026174-0 | P44: 0 | U44: =Q44+'APONTAMENTO CREDENCIAMENTO'!U44 -> 0 | V44: =R44+'APONTAMENTO CREDENCIAMENTO'!V44 -> 0 | W44: =S44+'APONTAMENTO CREDENCIAMENTO'!W44 -> 0 | X44: =T44+'APONTAMENTO CREDENCIAMENTO'!X44 -> 0 | Y44: =U44+'APONTAMENTO CREDENCIAMENTO'!Y44 -> 0 | Z44: =V44+'APONTAMENTO CREDENCIAMENTO'!Z44 -> 0 | AA44: =W44+'APONTAMENTO CREDENCIAMENTO'!AA44 -> 0 | AB44: =X44+'APONTAMENTO CREDENCIAMENTO'!AB44 -> 0 | ... EF44: =EB44+'APONTAMENTO CREDENCIAMENTO'!EF44 -> 0 | EP44: 0 | EQ44: 0 | ER44: 0 | ES44: 0 | ET44: 0 | EU44: 0 | EV44: 0 | EX44: 0 | EY44: 0 | EZ44: 0 | FA44: 0 | FB44: 0 | FC44: 0 | FD44: 0 | GL44: 0 | HY44: 0 | HZ44: 0 | IA44: 0
A45: 016.845-00 | B45: 2022/0026174-001 | C45: FB | D45: 2022/0026174 | E45: CXA5755 | F45: 01/04/2026 | G45: 30/04/2026 | H45: DIONISIO SCARPONE | I45: DIONISIO SCARPONE | J45: NORMAL | K45: CCA | L45: 0 | M45: 0 | O45: 6020.2022/0026174-0 | P45: 0 | U45: =Q45+'APONTAMENTO CREDENCIAMENTO'!U45 -> 0 | V45: =R45+'APONTAMENTO CREDENCIAMENTO'!V45 -> 0 | W45: =S45+'APONTAMENTO CREDENCIAMENTO'!W45 -> 0 | X45: =T45+'APONTAMENTO CREDENCIAMENTO'!X45 -> 0 | Y45: =U45+'APONTAMENTO CREDENCIAMENTO'!Y45 -> 0 | Z45: =V45+'APONTAMENTO CREDENCIAMENTO'!Z45 -> 0 | AA45: =W45+'APONTAMENTO CREDENCIAMENTO'!AA45 -> 0 | AB45: =X45+'APONTAMENTO CREDENCIAMENTO'!AB45 -> 0 | ... EF45: =EB45+'APONTAMENTO CREDENCIAMENTO'!EF45 -> 0 | EP45: 0 | EQ45: 0 | ER45: 0 | ES45: 0 | ET45: 0 | EU45: 0 | EV45: 0 | EX45: 0 | EY45: 0 | EZ45: 0 | FA45: 0 | FB45: 0 | FC45: 0 | FD45: 0 | FF45: 0 | FG45: 0 | FH45: 0 | FI45: 0 | FJ45: 0 | FK45: 0 | FL45: 0 | FM45: 0 | FN45: 0 | FO45: 0 | FP45: 0 | FQ45: 0 | FR45: 0 | FS45: 0 | FT45: 0 | FU45: 0 | FV45: 0 | FW45: 0 | FX45: 0 | FY45: 0 | FZ45: 0 | GA45: 0 | GB45: 0 | GC45: 0 | GD45: 0 | GE45: 0 | GF45: 0 | GG45: 0 | GH45: 0 | GI45: 0 | GJ45: 0 | GL45: 0 | HY45: 0 | HZ45: 0 | IA45: 0
A46: 011.460-00 | B46: 2022/0031239-001D | C46: 1 | D46: 2022/0031239 | E46: EGK6C37 | F46: 01/04/2026 | G46: 30/04/2026 | H46: EDILAINE APARECIDA DOS SANTOS PIMENTEL | I46: EDILAINE APARECIDA DOS SANTOS PIMENTEL | J46: NORMAL | K46: EMEI | L46: 0 | M46: 0 | O46: 6020.2022/0031239-6 | P46: 0 | Q46: 59 | U46: =Q46+'APONTAMENTO CREDENCIAMENTO'!U46 -> 59 | V46: =R46+'APONTAMENTO CREDENCIAMENTO'!V46 -> 0 | W46: =S46+'APONTAMENTO CREDENCIAMENTO'!W46 -> 0 | X46: =T46+'APONTAMENTO CREDENCIAMENTO'!X46 -> 0 | Y46: =U46+'APONTAMENTO CREDENCIAMENTO'!Y46 -> 59 | Z46: =V46+'APONTAMENTO CREDENCIAMENTO'!Z46 -> 0 | AA46: =W46+'APONTAMENTO CREDENCIAMENTO'!AA46 -> 0 | AB46: =X46+'APONTAMENTO CREDENCIAMENTO'!AB46 -> 0 | ... EF46: =EB46+'APONTAMENTO CREDENCIAMENTO'!EF46 -> 0 | EP46: 59 | EQ46: -1 | ER46: 0 | ES46: 0 | ET46: 0 | EU46: 0 | EV46: 58 | EW46: 0 | EX46: 24057.41 | EY46: 0 | EZ46: 89.887 | FA46: -475.117 | FB46: 0 | FC46: 0 | FD46: 0 | FE46: 23672.18 | FF46: 24057.41 | FG46: 0 | FH46: 0 | FI46: 0 | FJ46: 0 | FK46: 0 | FL46: 0 | FM46: -295.343 | FN46: 0 | FO46: 0 | FP46: 0 | FQ46: 0 | FR46: 0 | FS46: 0 | FT46: 0 | FU46: 0 | FV46: -179.774 | FW46: 0 | FX46: 0 | FY46: 0 | FZ46: 0 | GA46: 0 | GB46: 0 | GC46: 89.887 | GD46: 0 | GE46: 0 | GF46: 0 | GG46: 0 | GH46: 0 | GI46: 0 | GJ46: 0 | GL46: 0 | GN46: 0 | GO46: 0 | GP46: 0 | GQ46: 0 | GR46: 0 | GS46: 0 | GT46: 0 | GU46: 0 | GV46: 0 | GW46: 0 | GX46: 0 | GY46: 0 | GZ46: 0 | HA46: 0 | HB46: 0 | HC46: 0 | HD46: 0 | HE46: 0 | HF46: 0 | HG46: 0 | HH46: 0 | HI46: 0 | HJ46: 0 | HK46: 0 | HL46: 0 | HM46: 0 | HN46: 0 | HO46: 0 | HP46: 0 | HW46: 17629.31 | HY46: 0 | HZ46: 0 | IA46: 0 | IB46: FALSE
A47: 011.460-00 | B47: 2022/0031239-001D | C47: FB | D47: 2022/0031239 | E47: EGK6C37 | F47: 01/04/2026 | G47: 30/04/2026 | H47: EDILAINE APARECIDA DOS SANTOS PIMENTEL | I47: EDILAINE APARECIDA DOS SANTOS PIMENTEL | J47: NORMAL | K47: EMEF | L47: 0 | M47: 0 | O47: 6020.2022/0031239-6 | P47: 0 | U47: =Q47+'APONTAMENTO CREDENCIAMENTO'!U47 -> 0 | V47: =R47+'APONTAMENTO CREDENCIAMENTO'!V47 -> 0 | W47: =S47+'APONTAMENTO CREDENCIAMENTO'!W47 -> 0 | X47: =T47+'APONTAMENTO CREDENCIAMENTO'!X47 -> 0 | Y47: =U47+'APONTAMENTO CREDENCIAMENTO'!Y47 -> 0 | Z47: =V47+'APONTAMENTO CREDENCIAMENTO'!Z47 -> 0 | AA47: =W47+'APONTAMENTO CREDENCIAMENTO'!AA47 -> 0 | AB47: =X47+'APONTAMENTO CREDENCIAMENTO'!AB47 -> 0 | ... EF47: =EB47+'APONTAMENTO CREDENCIAMENTO'!EF47 -> 0 | EP47: 0 | EQ47: 0 | ER47: 0 | ES47: 0 | ET47: 0 | EU47: 0 | EV47: 0 | EX47: 0 | EY47: 0 | EZ47: 0 | FA47: 0 | FB47: 0 | FC47: 0 | FD47: 0 | GL47: 0 | HY47: 0 | HZ47: 0 | IA47: 0
A48: 011.460-00 | B48: 2022/0031239-001D | C48: FB | D48: 2022/0031239 | E48: EGK6C37 | F48: 01/04/2026 | G48: 30/04/2026 | H48: EDILAINE APARECIDA DOS SANTOS PIMENTEL | I48: EDILAINE APARECIDA DOS SANTOS PIMENTEL | J48: NORMAL | K48: EMEE | L48: 0 | M48: 0 | O48: 6020.2022/0031239-6 | P48: 0 | U48: =Q48+'APONTAMENTO CREDENCIAMENTO'!U48 -> 0 | V48: =R48+'APONTAMENTO CREDENCIAMENTO'!V48 -> 0 | W48: =S48+'APONTAMENTO CREDENCIAMENTO'!W48 -> 0 | X48: =T48+'APONTAMENTO CREDENCIAMENTO'!X48 -> 0 | Y48: =U48+'APONTAMENTO CREDENCIAMENTO'!Y48 -> 0 | Z48: =V48+'APONTAMENTO CREDENCIAMENTO'!Z48 -> 0 | AA48: =W48+'APONTAMENTO CREDENCIAMENTO'!AA48 -> 0 | AB48: =X48+'APONTAMENTO CREDENCIAMENTO'!AB48 -> 0 | ... EF48: =EB48+'APONTAMENTO CREDENCIAMENTO'!EF48 -> 0 | EP48: 0 | EQ48: 0 | ER48: 0 | ES48: 0 | ET48: 0 | EU48: 0 | EV48: 0 | EX48: 0 | EY48: 0 | EZ48: 0 | FA48: 0 | FB48: 0 | FC48: 0 | FD48: 0 | GL48: 0 | HY48: 0 | HZ48: 0 | IA48: 0
A49: 011.460-00 | B49: 2022/0031239-001D | C49: FB | D49: 2022/0031239 | E49: EGK6C37 | F49: 01/04/2026 | G49: 30/04/2026 | H49: EDILAINE APARECIDA DOS SANTOS PIMENTEL | I49: EDILAINE APARECIDA DOS SANTOS PIMENTEL | J49: NORMAL | K49: CEI | L49: 0 | M49: 0 | O49: 6020.2022/0031239-6 | P49: 0 | U49: =Q49+'APONTAMENTO CREDENCIAMENTO'!U49 -> 0 | V49: =R49+'APONTAMENTO CREDENCIAMENTO'!V49 -> 0 | W49: =S49+'APONTAMENTO CREDENCIAMENTO'!W49 -> 0 | X49: =T49+'APONTAMENTO CREDENCIAMENTO'!X49 -> 0 | Y49: =U49+'APONTAMENTO CREDENCIAMENTO'!Y49 -> 0 | Z49: =V49+'APONTAMENTO CREDENCIAMENTO'!Z49 -> 0 | AA49: =W49+'APONTAMENTO CREDENCIAMENTO'!AA49 -> 0 | AB49: =X49+'APONTAMENTO CREDENCIAMENTO'!AB49 -> 0 | ... EF49: =EB49+'APONTAMENTO CREDENCIAMENTO'!EF49 -> 0 | EP49: 0 | EQ49: 0 | ER49: 0 | ES49: 0 | ET49: 0 | EU49: 0 | EV49: 0 | EX49: 0 | EY49: 0 | EZ49: 0 | FA49: 0 | FB49: 0 | FC49: 0 | FD49: 0 | GL49: 0 | HY49: 0 | HZ49: 0 | IA49: 0
A50: 011.460-00 | B50: 2022/0031239-001D | C50: FB | D50: 2022/0031239 | E50: EGK6C37 | F50: 01/04/2026 | G50: 30/04/2026 | H50: EDILAINE APARECIDA DOS SANTOS PIMENTEL | I50: EDILAINE APARECIDA DOS SANTOS PIMENTEL | J50: NORMAL | K50: CCA | L50: 0 | M50: 0 | O50: 6020.2022/0031239-6 | P50: 0 | U50: =Q50+'APONTAMENTO CREDENCIAMENTO'!U50 -> 0 | V50: =R50+'APONTAMENTO CREDENCIAMENTO'!V50 -> 0 | W50: =S50+'APONTAMENTO CREDENCIAMENTO'!W50 -> 0 | X50: =T50+'APONTAMENTO CREDENCIAMENTO'!X50 -> 0 | Y50: =U50+'APONTAMENTO CREDENCIAMENTO'!Y50 -> 0 | Z50: =V50+'APONTAMENTO CREDENCIAMENTO'!Z50 -> 0 | AA50: =W50+'APONTAMENTO CREDENCIAMENTO'!AA50 -> 0 | AB50: =X50+'APONTAMENTO CREDENCIAMENTO'!AB50 -> 0 | ... EF50: =EB50+'APONTAMENTO CREDENCIAMENTO'!EF50 -> 0 | EP50: 0 | EQ50: 0 | ER50: 0 | ES50: 0 | ET50: 0 | EU50: 0 | EV50: 0 | EX50: 0 | EY50: 0 | EZ50: 0 | FA50: 0 | FB50: 0 | FC50: 0 | FD50: 0 | FF50: 0 | FG50: 0 | FH50: 0 | FI50: 0 | FJ50: 0 | FK50: 0 | FL50: 0 | FM50: 0 | FN50: 0 | FO50: 0 | FP50: 0 | FQ50: 0 | FR50: 0 | FS50: 0 | FT50: 0 | FU50: 0 | FV50: 0 | FW50: 0 | FX50: 0 | FY50: 0 | FZ50: 0 | GA50: 0 | GB50: 0 | GC50: 0 | GD50: 0 | GE50: 0 | GF50: 0 | GG50: 0 | GH50: 0 | GI50: 0 | GJ50: 0 | GL50: 0 | HY50: 0 | HZ50: 0 | IA50: 0
A51: 031.558-00 | B51: 2022/0033816-001B | C51: 2 | D51: 2022/0033816 | E51: FXO4860 | F51: 01/04/2026 | G51: 30/04/2026 | H51: GABRIEL ANTONIO ALMEIDA SOUZA | I51: GABRIEL ANTONIO ALMEIDA SOUZA | J51: ADAPTADO | K51: EMEI | L51: 0 | M51: 0 | O51: 6020.2022/0033816-6 | P51: 0 | U51: =Q51+'APONTAMENTO CREDENCIAMENTO'!U51 -> 0 | V51: =R51+'APONTAMENTO CREDENCIAMENTO'!V51 -> 0 | W51: =S51+'APONTAMENTO CREDENCIAMENTO'!W51 -> 0 | X51: =T51+'APONTAMENTO CREDENCIAMENTO'!X51 -> 0 | Y51: =U51+'APONTAMENTO CREDENCIAMENTO'!Y51 -> 0 | Z51: =V51+'APONTAMENTO CREDENCIAMENTO'!Z51 -> 0 | AA51: =W51+'APONTAMENTO CREDENCIAMENTO'!AA51 -> 0 | AB51: =X51+'APONTAMENTO CREDENCIAMENTO'!AB51 -> 0 | ... EF51: =EB51+'APONTAMENTO CREDENCIAMENTO'!EF51 -> 0 | EP51: 0 | EQ51: 1 | ER51: 0 | ES51: 0 | ET51: 0 | EU51: 0 | EV51: 1 | EW51: 0 | EX51: 20022.15 | EY51: 0 | EZ51: 205.456 | FA51: -744.778 | FB51: 0 | FC51: 0 | FD51: 0 | FE51: 19482.828 | FF51: 20022.15 | FG51: -744.778 | FH51: 0 | FI51: 0 | FJ51: 0 | FK51: 0 | FL51: 0 | FM51: 0 | FN51: 0 | FO51: 0 | FP51: 0 | FQ51: 0 | FR51: 0 | FS51: 0 | FT51: 205.456 | FU51: 0 | FV51: 0 | FW51: 0 | FX51: 0 | FY51: 0 | FZ51: 0 | GA51: 0 | GB51: 0 | GC51: 0 | GD51: 0 | GE51: 0 | GF51: 0 | GG51: 0 | GH51: 0 | GI51: 0 | GJ51: 0 | GL51: 0 | GN51: 0 | GO51: 0 | GP51: 0 | GQ51: 0 | GR51: 0 | GS51: 0 | GT51: 0 | GU51: 0 | GV51: 0 | GW51: 0 | GX51: 0 | GY51: 0 | GZ51: 0 | HA51: 0 | HB51: 0 | HC51: 0 | HD51: 0 | HE51: 0 | HF51: 0 | HG51: 0 | HH51: 0 | HI51: 0 | HJ51: 0 | HK51: 0 | HL51: 0 | HM51: 0 | HN51: 0 | HO51: 0 | HP51: 0 | HW51: 17629.31 | HY51: 0 | HZ51: 0 | IA51: 0 | IB51: FALSE
A52: 031.558-00 | B52: 2022/0033816-001B | C52: FB | D52: 2022/0033816 | E52: FXO4860 | F52: 01/04/2026 | G52: 30/04/2026 | H52: GABRIEL ANTONIO ALMEIDA SOUZA | I52: GABRIEL ANTONIO ALMEIDA SOUZA | J52: ADAPTADO | K52: EMEF | L52: 0 | M52: 0 | O52: 6020.2022/0033816-6 | P52: 0 | Q52: 6 | R52: 6 | T52: 1 | U52: =Q52+'APONTAMENTO CREDENCIAMENTO'!U52 -> 4 | V52: =R52+'APONTAMENTO CREDENCIAMENTO'!V52 -> 6 | W52: =S52+'APONTAMENTO CREDENCIAMENTO'!W52 -> 0 | X52: =T52+'APONTAMENTO CREDENCIAMENTO'!X52 -> 1 | Y52: =U52+'APONTAMENTO CREDENCIAMENTO'!Y52 -> 4 | Z52: =V52+'APONTAMENTO CREDENCIAMENTO'!Z52 -> 6 | AA52: =W52+'APONTAMENTO CREDENCIAMENTO'!AA52 -> 0 | AB52: =X52+'APONTAMENTO CREDENCIAMENTO'!AB52 -> 1 | ... EF52: =EB52+'APONTAMENTO CREDENCIAMENTO'!EF52 -> 1 | EP52: 6 | EQ52: -2 | ER52: 0 | ES52: 6 | ET52: 0 | EU52: 1 | EV52: 11 | EX52: 0 | EY52: 0 | EZ52: 0 | FA52: 0 | FB52: 0 | FC52: 0 | FD52: 0 | GL52: 0 | HY52: 0 | HZ52: 0 | IA52: 0
A53: 031.558-00 | B53: 2022/0033816-001B | C53: FB | D53: 2022/0033816 | E53: FXO4860 | F53: 01/04/2026 | G53: 30/04/2026 | H53: GABRIEL ANTONIO ALMEIDA SOUZA | I53: GABRIEL ANTONIO ALMEIDA SOUZA | J53: ADAPTADO | K53: EMEE | L53: 0 | M53: 0 | O53: 6020.2022/0033816-6 | P53: 0 | U53: =Q53+'APONTAMENTO CREDENCIAMENTO'!U53 -> 0 | V53: =R53+'APONTAMENTO CREDENCIAMENTO'!V53 -> 0 | W53: =S53+'APONTAMENTO CREDENCIAMENTO'!W53 -> 0 | X53: =T53+'APONTAMENTO CREDENCIAMENTO'!X53 -> 0 | Y53: =U53+'APONTAMENTO CREDENCIAMENTO'!Y53 -> 0 | Z53: =V53+'APONTAMENTO CREDENCIAMENTO'!Z53 -> 0 | AA53: =W53+'APONTAMENTO CREDENCIAMENTO'!AA53 -> 0 | AB53: =X53+'APONTAMENTO CREDENCIAMENTO'!AB53 -> 0 | ... EF53: =EB53+'APONTAMENTO CREDENCIAMENTO'!EF53 -> 0 | EP53: 0 | EQ53: 0 | ER53: 0 | ES53: 0 | ET53: 0 | EU53: 0 | EV53: 0 | EX53: 0 | EY53: 0 | EZ53: 0 | FA53: 0 | FB53: 0 | FC53: 0 | FD53: 0 | GL53: 0 | HY53: 0 | HZ53: 0 | IA53: 0
A54: 031.558-00 | B54: 2022/0033816-001B | C54: FB | D54: 2022/0033816 | E54: FXO4860 | F54: 01/04/2026 | G54: 30/04/2026 | H54: GABRIEL ANTONIO ALMEIDA SOUZA | I54: GABRIEL ANTONIO ALMEIDA SOUZA | J54: ADAPTADO | K54: CEI | L54: 0 | M54: 0 | O54: 6020.2022/0033816-6 | P54: 0 | U54: =Q54+'APONTAMENTO CREDENCIAMENTO'!U54 -> 0 | V54: =R54+'APONTAMENTO CREDENCIAMENTO'!V54 -> 0 | W54: =S54+'APONTAMENTO CREDENCIAMENTO'!W54 -> 0 | X54: =T54+'APONTAMENTO CREDENCIAMENTO'!X54 -> 0 | Y54: =U54+'APONTAMENTO CREDENCIAMENTO'!Y54 -> 0 | Z54: =V54+'APONTAMENTO CREDENCIAMENTO'!Z54 -> 0 | AA54: =W54+'APONTAMENTO CREDENCIAMENTO'!AA54 -> 0 | AB54: =X54+'APONTAMENTO CREDENCIAMENTO'!AB54 -> 0 | ... EF54: =EB54+'APONTAMENTO CREDENCIAMENTO'!EF54 -> 0 | EP54: 0 | EQ54: 0 | ER54: 0 | ES54: 0 | ET54: 0 | EU54: 0 | EV54: 0 | EX54: 0 | EY54: 0 | EZ54: 0 | FA54: 0 | FB54: 0 | FC54: 0 | FD54: 0 | GL54: 0 | HY54: 0 | HZ54: 0 | IA54: 0
A55: 031.558-00 | B55: 2022/0033816-001B | C55: FB | D55: 2022/0033816 | E55: FXO4860 | F55: 01/04/2026 | G55: 30/04/2026 | H55: GABRIEL ANTONIO ALMEIDA SOUZA | I55: GABRIEL ANTONIO ALMEIDA SOUZA | J55: ADAPTADO | K55: CCA | L55: 0 | M55: 0 | O55: 6020.2022/0033816-6 | P55: 0 | U55: =Q55+'APONTAMENTO CREDENCIAMENTO'!U55 -> 0 | V55: =R55+'APONTAMENTO CREDENCIAMENTO'!V55 -> 0 | W55: =S55+'APONTAMENTO CREDENCIAMENTO'!W55 -> 0 | X55: =T55+'APONTAMENTO CREDENCIAMENTO'!X55 -> 0 | Y55: =U55+'APONTAMENTO CREDENCIAMENTO'!Y55 -> 0 | Z55: =V55+'APONTAMENTO CREDENCIAMENTO'!Z55 -> 0 | AA55: =W55+'APONTAMENTO CREDENCIAMENTO'!AA55 -> 0 | AB55: =X55+'APONTAMENTO CREDENCIAMENTO'!AB55 -> 0 | ... EF55: =EB55+'APONTAMENTO CREDENCIAMENTO'!EF55 -> 0 | EP55: 0 | EQ55: 0 | ER55: 0 | ES55: 0 | ET55: 0 | EU55: 0 | EV55: 0 | EX55: 0 | EY55: 0 | EZ55: 0 | FA55: 0 | FB55: 0 | FC55: 0 | FD55: 0 | FF55: 0 | FG55: 0 | FH55: 0 | FI55: 0 | FJ55: 0 | FK55: 0 | FL55: 0 | FM55: 0 | FN55: 0 | FO55: 0 | FP55: 0 | FQ55: 0 | FR55: 0 | FS55: 0 | FT55: 0 | FU55: 0 | FV55: 0 | FW55: 0 | FX55: 0 | FY55: 0 | FZ55: 0 | GA55: 0 | GB55: 0 | GC55: 0 | GD55: 0 | GE55: 0 | GF55: 0 | GG55: 0 | GH55: 0 | GI55: 0 | GJ55: 0 | GL55: 0 | HY55: 0 | HZ55: 0 | IA55: 0
A56: 022.771-00 | B56: 2023/0039607-001 | C56: 1 | D56: 2023/0039607 | E56: ELW1444 | F56: 01/04/2026 | G56: 30/04/2026 | H56: JACO FELISARDO DE SOUZA FILHO | I56: JACO FELISARDO DE SOUZA FILHO | J56: NORMAL | K56: EMEI | L56: 0 | M56: 0 | O56: 6020.2023/0039607-9 | P56: 0 | U56: =Q56+'APONTAMENTO CREDENCIAMENTO'!U56 -> 0 | V56: =R56+'APONTAMENTO CREDENCIAMENTO'!V56 -> 0 | W56: =S56+'APONTAMENTO CREDENCIAMENTO'!W56 -> 0 | X56: =T56+'APONTAMENTO CREDENCIAMENTO'!X56 -> 0 | Y56: =U56+'APONTAMENTO CREDENCIAMENTO'!Y56 -> 0 | Z56: =V56+'APONTAMENTO CREDENCIAMENTO'!Z56 -> 0 | AA56: =W56+'APONTAMENTO CREDENCIAMENTO'!AA56 -> 0 | AB56: =X56+'APONTAMENTO CREDENCIAMENTO'!AB56 -> 0 | ... EF56: =EB56+'APONTAMENTO CREDENCIAMENTO'!EF56 -> 0 | EP56: 0 | EQ56: 0 | ER56: 0 | ES56: 0 | ET56: 0 | EU56: 0 | EV56: 0 | EW56: 0 | EX56: 14426.66 | EY56: 0 | EZ56: 487.958 | FA56: 0 | FB56: 0 | FC56: 0 | FD56: 0 | FE56: 14982.098 | FF56: 14426.66 | FG56: 0 | FH56: 0 | FI56: 0 | FJ56: 0 | FK56: 0 | FL56: 308.184 | FM56: 0 | FN56: 0 | FO56: 0 | FP56: 0 | FQ56: 0 | FR56: 0 | FS56: 0 | FT56: 0 | FU56: 0 | FV56: 179.774 | FW56: 0 | FX56: 0 | FY56: 0 | FZ56: 0 | GA56: 0 | GB56: 0 | GC56: 0 | GD56: 0 | GE56: 0 | GF56: 0 | GG56: 0 | GH56: 0 | GI56: 0 | GJ56: 0 | GL56: 0 | GN56: 0 | GO56: 0 | GP56: 0 | GQ56: 0 | GR56: 0 | GS56: 0 | GT56: 0 | GU56: 0 | GV56: 0 | GW56: 0 | GX56: 0 | GY56: 0 | GZ56: 0 | HA56: 0 | HB56: 0 | HC56: 0 | HD56: 0 | HE56: 0 | HF56: 0 | HG56: 0 | HH56: 0 | HI56: 0 | HJ56: 0 | HK56: 0 | HL56: 0 | HM56: 0 | HN56: 0 | HO56: 0 | HP56: 0 | HW56: 17629.31 | HY56: 0 | HZ56: 0 | IA56: 0 | IB56: FALSE
A57: 022.771-00 | B57: 2023/0039607-001 | C57: FB | D57: 2023/0039607 | E57: ELW1444 | F57: 01/04/2026 | G57: 30/04/2026 | H57: JACO FELISARDO DE SOUZA FILHO | I57: JACO FELISARDO DE SOUZA FILHO | J57: NORMAL | K57: EMEF | L57: 7 | M57: 0 | O57: 6020.2023/0039607-9 | P57: 0 | Q57: 34 | U57: =Q57+'APONTAMENTO CREDENCIAMENTO'!U57 -> 34 | V57: =R57+'APONTAMENTO CREDENCIAMENTO'!V57 -> 0 | W57: =S57+'APONTAMENTO CREDENCIAMENTO'!W57 -> 0 | X57: =T57+'APONTAMENTO CREDENCIAMENTO'!X57 -> 0 | Y57: =U57+'APONTAMENTO CREDENCIAMENTO'!Y57 -> 34 | Z57: =V57+'APONTAMENTO CREDENCIAMENTO'!Z57 -> 0 | AA57: =W57+'APONTAMENTO CREDENCIAMENTO'!AA57 -> 0 | AB57: =X57+'APONTAMENTO CREDENCIAMENTO'!AB57 -> 0 | ... EF57: =EB57+'APONTAMENTO CREDENCIAMENTO'!EF57 -> 0 | EP57: 34 | EQ57: 2 | ER57: 0 | ES57: 0 | ET57: 0 | EU57: 0 | EV57: 36 | EX57: 0 | EY57: 67.48 | EZ57: 0 | FA57: 0 | FB57: 0 | FC57: 0 | FD57: 0 | GL57: 0 | HY57: 0 | HZ57: 0 | IA57: 0
A58: 022.771-00 | B58: 2023/0039607-001 | C58: FB | D58: 2023/0039607 | E58: ELW1444 | F58: 01/04/2026 | G58: 30/04/2026 | H58: JACO FELISARDO DE SOUZA FILHO | I58: JACO FELISARDO DE SOUZA FILHO | J58: NORMAL | K58: EMEE | L58: 0 | M58: 0 | O58: 6020.2023/0039607-9 | P58: 0 | U58: =Q58+'APONTAMENTO CREDENCIAMENTO'!U58 -> 0 | V58: =R58+'APONTAMENTO CREDENCIAMENTO'!V58 -> 0 | W58: =S58+'APONTAMENTO CREDENCIAMENTO'!W58 -> 0 | X58: =T58+'APONTAMENTO CREDENCIAMENTO'!X58 -> 0 | Y58: =U58+'APONTAMENTO CREDENCIAMENTO'!Y58 -> 0 | Z58: =V58+'APONTAMENTO CREDENCIAMENTO'!Z58 -> 0 | AA58: =W58+'APONTAMENTO CREDENCIAMENTO'!AA58 -> 0 | AB58: =X58+'APONTAMENTO CREDENCIAMENTO'!AB58 -> 0 | ... EF58: =EB58+'APONTAMENTO CREDENCIAMENTO'!EF58 -> 0 | EP58: 0 | EQ58: 0 | ER58: 0 | ES58: 0 | ET58: 0 | EU58: 0 | EV58: 0 | EX58: 0 | EY58: 0 | EZ58: 0 | FA58: 0 | FB58: 0 | FC58: 0 | FD58: 0 | GL58: 0 | HY58: 0 | HZ58: 0 | IA58: 0
A59: 022.771-00 | B59: 2023/0039607-001 | C59: FB | D59: 2023/0039607 | E59: ELW1444 | F59: 01/04/2026 | G59: 30/04/2026 | H59: JACO FELISARDO DE SOUZA FILHO | I59: JACO FELISARDO DE SOUZA FILHO | J59: NORMAL | K59: CEI | L59: 0 | M59: 0 | O59: 6020.2023/0039607-9 | P59: 0 | U59: =Q59+'APONTAMENTO CREDENCIAMENTO'!U59 -> 0 | V59: =R59+'APONTAMENTO CREDENCIAMENTO'!V59 -> 0 | W59: =S59+'APONTAMENTO CREDENCIAMENTO'!W59 -> 0 | X59: =T59+'APONTAMENTO CREDENCIAMENTO'!X59 -> 0 | Y59: =U59+'APONTAMENTO CREDENCIAMENTO'!Y59 -> 0 | Z59: =V59+'APONTAMENTO CREDENCIAMENTO'!Z59 -> 0 | AA59: =W59+'APONTAMENTO CREDENCIAMENTO'!AA59 -> 0 | AB59: =X59+'APONTAMENTO CREDENCIAMENTO'!AB59 -> 0 | ... EF59: =EB59+'APONTAMENTO CREDENCIAMENTO'!EF59 -> 0 | EP59: 0 | EQ59: 0 | ER59: 0 | ES59: 0 | ET59: 0 | EU59: 0 | EV59: 0 | EX59: 0 | EY59: 0 | EZ59: 0 | FA59: 0 | FB59: 0 | FC59: 0 | FD59: 0 | GL59: 0 | HY59: 0 | HZ59: 0 | IA59: 0
A60: 022.771-00 | B60: 2023/0039607-001 | C60: FB | D60: 2023/0039607 | E60: ELW1444 | F60: 01/04/2026 | G60: 30/04/2026 | H60: JACO FELISARDO DE SOUZA FILHO | I60: JACO FELISARDO DE SOUZA FILHO | J60: NORMAL | K60: CCA | L60: 0 | M60: 0 | O60: 6020.2023/0039607-9 | P60: 0 | U60: =Q60+'APONTAMENTO CREDENCIAMENTO'!U60 -> 0 | V60: =R60+'APONTAMENTO CREDENCIAMENTO'!V60 -> 0 | W60: =S60+'APONTAMENTO CREDENCIAMENTO'!W60 -> 0 | X60: =T60+'APONTAMENTO CREDENCIAMENTO'!X60 -> 0 | Y60: =U60+'APONTAMENTO CREDENCIAMENTO'!Y60 -> 0 | Z60: =V60+'APONTAMENTO CREDENCIAMENTO'!Z60 -> 0 | AA60: =W60+'APONTAMENTO CREDENCIAMENTO'!AA60 -> 0 | AB60: =X60+'APONTAMENTO CREDENCIAMENTO'!AB60 -> 0 | ... EF60: =EB60+'APONTAMENTO CREDENCIAMENTO'!EF60 -> 0 | EP60: 0 | EQ60: 0 | ER60: 0 | ES60: 0 | ET60: 0 | EU60: 0 | EV60: 0 | EX60: 0 | EY60: 0 | EZ60: 0 | FA60: 0 | FB60: 0 | FC60: 0 | FD60: 0 | FF60: 0 | FG60: 0 | FH60: 0 | FI60: 0 | FJ60: 0 | FK60: 0 | FL60: 0 | FM60: 0 | FN60: 0 | FO60: 0 | FP60: 0 | FQ60: 0 | FR60: 0 | FS60: 0 | FT60: 0 | FU60: 0 | FV60: 0 | FW60: 0 | FX60: 0 | FY60: 0 | FZ60: 0 | GA60: 0 | GB60: 0 | GC60: 0 | GD60: 0 | GE60: 0 | GF60: 0 | GG60: 0 | GH60: 0 | GI60: 0 | GJ60: 0 | GL60: 0 | HY60: 0 | HZ60: 0 | IA60: 0
A61: 014.409-00 | B61: 2022/0032145-001B | C61: 1 | D61: 2022/0032145 | E61: DTC4582 | F61: 01/04/2026 | G61: 30/04/2026 | H61: JOSE ANTONIO DA SILVA | I61: JOSE ANTONIO DA SILVA | J61: NORMAL | K61: EMEI | L61: 0 | M61: 0 | O61: 6020.2022/0032145-0 | P61: 0 | U61: =Q61+'APONTAMENTO CREDENCIAMENTO'!U61 -> 0 | V61: =R61+'APONTAMENTO CREDENCIAMENTO'!V61 -> 0 | W61: =S61+'APONTAMENTO CREDENCIAMENTO'!W61 -> 0 | X61: =T61+'APONTAMENTO CREDENCIAMENTO'!X61 -> 0 | Y61: =U61+'APONTAMENTO CREDENCIAMENTO'!Y61 -> 0 | Z61: =V61+'APONTAMENTO CREDENCIAMENTO'!Z61 -> 0 | AA61: =W61+'APONTAMENTO CREDENCIAMENTO'!AA61 -> 0 | AB61: =X61+'APONTAMENTO CREDENCIAMENTO'!AB61 -> 0 | ... EF61: =EB61+'APONTAMENTO CREDENCIAMENTO'!EF61 -> 0 | EP61: 0 | EQ61: 0 | ER61: 0 | ES61: 0 | ET61: 0 | EU61: 0 | EV61: 0 | EW61: 0 | EX61: 19434.65 | EY61: 0 | EZ61: 642.05 | FA61: 0 | FB61: 0 | FC61: 0 | FD61: 0 | FE61: 20076.7 | FF61: 19434.65 | FG61: 0 | FH61: 0 | FI61: 0 | FJ61: 0 | FK61: 642.05 | FL61: 0 | FM61: 0 | FN61: 0 | FO61: 0 | FP61: 0 | FQ61: 0 | FR61: 0 | FS61: 0 | FT61: 0 | FU61: 0 | FV61: 0 | FW61: 0 | FX61: 0 | FY61: 0 | FZ61: 0 | GA61: 0 | GB61: 0 | GC61: 0 | GD61: 0 | GE61: 0 | GF61: 0 | GG61: 0 | GH61: 0 | GI61: 0 | GJ61: 0 | GL61: 0 | GN61: 0 | GO61: 0 | GP61: 0 | GQ61: 0 | GR61: 0 | GS61: 0 | GT61: 0 | GU61: 0 | GV61: 0 | GW61: 0 | GX61: 0 | GY61: 0 | GZ61: 0 | HA61: 0 | HB61: 0 | HC61: 0 | HD61: 0 | HE61: 0 | HF61: 0 | HG61: 0 | HH61: 0 | HI61: 0 | HJ61: 0 | HK61: 0 | HL61: 0 | HM61: 0 | HN61: 0 | HO61: 0 | HP61: 0 | HW61: 17629.31 | HY61: 0 | HZ61: 0 | IA61: 0 | IB61: FALSE
A62: 014.409-00 | B62: 2022/0032145-001B | C62: FB | D62: 2022/0032145 | E62: DTC4582 | F62: 01/04/2026 | G62: 30/04/2026 | H62: JOSE ANTONIO DA SILVA | I62: JOSE ANTONIO DA SILVA | J62: NORMAL | K62: EMEF | L62: 0 | M62: 0 | O62: 6020.2022/0032145-0 | P62: 0 | Q62: 47 | U62: =Q62+'APONTAMENTO CREDENCIAMENTO'!U62 -> 47 | V62: =R62+'APONTAMENTO CREDENCIAMENTO'!V62 -> 0 | W62: =S62+'APONTAMENTO CREDENCIAMENTO'!W62 -> 0 | X62: =T62+'APONTAMENTO CREDENCIAMENTO'!X62 -> 0 | Y62: =U62+'APONTAMENTO CREDENCIAMENTO'!Y62 -> 47 | Z62: =V62+'APONTAMENTO CREDENCIAMENTO'!Z62 -> 0 | AA62: =W62+'APONTAMENTO CREDENCIAMENTO'!AA62 -> 0 | AB62: =X62+'APONTAMENTO CREDENCIAMENTO'!AB62 -> 0 | ... EF62: =EB62+'APONTAMENTO CREDENCIAMENTO'!EF62 -> 0 | EP62: 47 | EQ62: 2 | ER62: 0 | ES62: 0 | ET62: 0 | EU62: 0 | EV62: 49 | EX62: 0 | EY62: 0 | EZ62: 0 | FA62: 0 | FB62: 0 | FC62: 0 | FD62: 0 | GL62: 0 | HY62: 0 | HZ62: 0 | IA62: 0
A63: 014.409-00 | B63: 2022/0032145-001B | C63: FB | D63: 2022/0032145 | E63: DTC4582 | F63: 01/04/2026 | G63: 30/04/2026 | H63: JOSE ANTONIO DA SILVA | I63: JOSE ANTONIO DA SILVA | J63: NORMAL | K63: EMEE | L63: 0 | M63: 0 | O63: 6020.2022/0032145-0 | P63: 0 | U63: =Q63+'APONTAMENTO CREDENCIAMENTO'!U63 -> 0 | V63: =R63+'APONTAMENTO CREDENCIAMENTO'!V63 -> 0 | W63: =S63+'APONTAMENTO CREDENCIAMENTO'!W63 -> 0 | X63: =T63+'APONTAMENTO CREDENCIAMENTO'!X63 -> 0 | Y63: =U63+'APONTAMENTO CREDENCIAMENTO'!Y63 -> 0 | Z63: =V63+'APONTAMENTO CREDENCIAMENTO'!Z63 -> 0 | AA63: =W63+'APONTAMENTO CREDENCIAMENTO'!AA63 -> 0 | AB63: =X63+'APONTAMENTO CREDENCIAMENTO'!AB63 -> 0 | ... EF63: =EB63+'APONTAMENTO CREDENCIAMENTO'!EF63 -> 0 | EP63: 0 | EQ63: 0 | ER63: 0 | ES63: 0 | ET63: 0 | EU63: 0 | EV63: 0 | EX63: 0 | EY63: 0 | EZ63: 0 | FA63: 0 | FB63: 0 | FC63: 0 | FD63: 0 | GL63: 0 | HY63: 0 | HZ63: 0 | IA63: 0
A64: 014.409-00 | B64: 2022/0032145-001B | C64: FB | D64: 2022/0032145 | E64: DTC4582 | F64: 01/04/2026 | G64: 30/04/2026 | H64: JOSE ANTONIO DA SILVA | I64: JOSE ANTONIO DA SILVA | J64: NORMAL | K64: CEI | L64: 0 | M64: 0 | O64: 6020.2022/0032145-0 | P64: 0 | U64: =Q64+'APONTAMENTO CREDENCIAMENTO'!U64 -> 0 | V64: =R64+'APONTAMENTO CREDENCIAMENTO'!V64 -> 0 | W64: =S64+'APONTAMENTO CREDENCIAMENTO'!W64 -> 0 | X64: =T64+'APONTAMENTO CREDENCIAMENTO'!X64 -> 0 | Y64: =U64+'APONTAMENTO CREDENCIAMENTO'!Y64 -> 0 | Z64: =V64+'APONTAMENTO CREDENCIAMENTO'!Z64 -> 0 | AA64: =W64+'APONTAMENTO CREDENCIAMENTO'!AA64 -> 0 | AB64: =X64+'APONTAMENTO CREDENCIAMENTO'!AB64 -> 0 | ... EF64: =EB64+'APONTAMENTO CREDENCIAMENTO'!EF64 -> 0 | EP64: 0 | EQ64: 0 | ER64: 0 | ES64: 0 | ET64: 0 | EU64: 0 | EV64: 0 | EX64: 0 | EY64: 0 | EZ64: 0 | FA64: 0 | FB64: 0 | FC64: 0 | FD64: 0 | GL64: 0 | HY64: 0 | HZ64: 0 | IA64: 0
A65: 014.409-00 | B65: 2022/0032145-001B | C65: FB | D65: 2022/0032145 | E65: DTC4582 | F65: 01/04/2026 | G65: 30/04/2026 | H65: JOSE ANTONIO DA SILVA | I65: JOSE ANTONIO DA SILVA | J65: NORMAL | K65: CCA | L65: 0 | M65: 0 | O65: 6020.2022/0032145-0 | P65: 0 | U65: =Q65+'APONTAMENTO CREDENCIAMENTO'!U65 -> 0 | V65: =R65+'APONTAMENTO CREDENCIAMENTO'!V65 -> 0 | W65: =S65+'APONTAMENTO CREDENCIAMENTO'!W65 -> 0 | X65: =T65+'APONTAMENTO CREDENCIAMENTO'!X65 -> 0 | Y65: =U65+'APONTAMENTO CREDENCIAMENTO'!Y65 -> 0 | Z65: =V65+'APONTAMENTO CREDENCIAMENTO'!Z65 -> 0 | AA65: =W65+'APONTAMENTO CREDENCIAMENTO'!AA65 -> 0 | AB65: =X65+'APONTAMENTO CREDENCIAMENTO'!AB65 -> 0 | ... EF65: =EB65+'APONTAMENTO CREDENCIAMENTO'!EF65 -> 0 | EP65: 0 | EQ65: 0 | ER65: 0 | ES65: 0 | ET65: 0 | EU65: 0 | EV65: 0 | EX65: 0 | EY65: 0 | EZ65: 0 | FA65: 0 | FB65: 0 | FC65: 0 | FD65: 0 | FF65: 0 | FG65: 0 | FH65: 0 | FI65: 0 | FJ65: 0 | FK65: 0 | FL65: 0 | FM65: 0 | FN65: 0 | FO65: 0 | FP65: 0 | FQ65: 0 | FR65: 0 | FS65: 0 | FT65: 0 | FU65: 0 | FV65: 0 | FW65: 0 | FX65: 0 | FY65: 0 | FZ65: 0 | GA65: 0 | GB65: 0 | GC65: 0 | GD65: 0 | GE65: 0 | GF65: 0 | GG65: 0 | GH65: 0 | GI65: 0 | GJ65: 0 | GL65: 0 | HY65: 0 | HZ65: 0 | IA65: 0
A66: 022.608-00 | B66: 2022/0030845-001A | C66: 4 | D66: 2022/0030845 | E66: ELQ8250 | F66: 01/04/2026 | G66: 30/04/2026 | H66: JOSE FIRMINO BATISTA | I66: JOSE FIRMINO BATISTA | J66: NORMAL | K66: EMEI | L66: 0 | M66: 0 | O66: 6020.2022/0030845-3 | P66: 0 | U66: =Q66+'APONTAMENTO CREDENCIAMENTO'!U66 -> 0 | V66: =R66+'APONTAMENTO CREDENCIAMENTO'!V66 -> 0 | W66: =S66+'APONTAMENTO CREDENCIAMENTO'!W66 -> 0 | X66: =T66+'APONTAMENTO CREDENCIAMENTO'!X66 -> 0 | Y66: =U66+'APONTAMENTO CREDENCIAMENTO'!Y66 -> 0 | Z66: =V66+'APONTAMENTO CREDENCIAMENTO'!Z66 -> 0 | AA66: =W66+'APONTAMENTO CREDENCIAMENTO'!AA66 -> 0 | AB66: =X66+'APONTAMENTO CREDENCIAMENTO'!AB66 -> 0 | ... EF66: =EB66+'APONTAMENTO CREDENCIAMENTO'!EF66 -> 0 | EP66: 0 | EQ66: 0 | ER66: 0 | ES66: 0 | ET66: 0 | EU66: 0 | EV66: 0 | EW66: 11465.63 | EX66: 3467.07 | EY66: 0 | EZ66: 0 | FA66: 0 | FB66: 0 | FC66: 0 | FD66: 0 | FE66: 14932.7 | FF66: 3467.07 | FG66: 0 | FH66: 0 | FI66: 0 | FJ66: 0 | FK66: 0 | FL66: 0 | FM66: 0 | FN66: 0 | FO66: 0 | FP66: 0 | FQ66: 0 | FR66: 0 | FS66: 0 | FT66: 0 | FU66: 0 | FV66: 0 | FW66: 0 | FX66: 0 | FY66: 0 | FZ66: 0 | GA66: 0 | GB66: 0 | GC66: 0 | GD66: 0 | GE66: 0 | GF66: 0 | GG66: 0 | GH66: 0 | GI66: 0 | GJ66: 0 | GL66: 0 | GN66: 0 | GO66: 0 | GP66: 0 | GQ66: 0 | GR66: 0 | GS66: 0 | GT66: 0 | GU66: 0 | GV66: 0 | GW66: 0 | GX66: 0 | GY66: 0 | GZ66: 0 | HA66: 0 | HB66: 0 | HC66: 0 | HD66: 0 | HE66: 0 | HF66: 0 | HG66: 0 | HH66: 0 | HI66: 0 | HJ66: 0 | HK66: 0 | HL66: 0 | HM66: 0 | HN66: 0 | HO66: 0 | HP66: 0 | HW66: 17629.31 | HY66: 0 | HZ66: 0 | IA66: 0 | IB66: FALSE
A67: 022.608-00 | B67: 2022/0030845-001A | C67: FBE | D67: 2022/0030845 | E67: ELQ8250 | F67: 01/04/2026 | G67: 30/04/2026 | H67: JOSE FIRMINO BATISTA | I67: JOSE FIRMINO BATISTA | J67: NORMAL | K67: EMEF | L67: 0 | M67: 0 | O67: 6020.2022/0030845-3 | P67: 0 | U67: =Q67+'APONTAMENTO CREDENCIAMENTO'!U67 -> 0 | V67: =R67+'APONTAMENTO CREDENCIAMENTO'!V67 -> 0 | W67: =S67+'APONTAMENTO CREDENCIAMENTO'!W67 -> 0 | X67: =T67+'APONTAMENTO CREDENCIAMENTO'!X67 -> 0 | Y67: =U67+'APONTAMENTO CREDENCIAMENTO'!Y67 -> 0 | Z67: =V67+'APONTAMENTO CREDENCIAMENTO'!Z67 -> 0 | AA67: =W67+'APONTAMENTO CREDENCIAMENTO'!AA67 -> 0 | AB67: =X67+'APONTAMENTO CREDENCIAMENTO'!AB67 -> 0 | ... EF67: =EB67+'APONTAMENTO CREDENCIAMENTO'!EF67 -> 0 | EP67: 0 | EQ67: 0 | ER67: 0 | ES67: 0 | ET67: 0 | EU67: 0 | EV67: 0 | EX67: 0 | EY67: 0 | EZ67: 0 | FA67: 0 | FB67: 0 | FC67: 0 | FD67: 0 | GL67: 0 | HY67: 0 | HZ67: 0 | IA67: 0
A68: 022.608-00 | B68: 2022/0030845-001A | C68: FBE | D68: 2022/0030845 | E68: ELQ8250 | F68: 01/04/2026 | G68: 30/04/2026 | H68: JOSE FIRMINO BATISTA | I68: JOSE FIRMINO BATISTA | J68: NORMAL | K68: EMEE | L68: 0 | M68: 0 | O68: 6020.2022/0030845-3 | P68: 0 | Q68: 9 | U68: =Q68+'APONTAMENTO CREDENCIAMENTO'!U68 -> 9 | V68: =R68+'APONTAMENTO CREDENCIAMENTO'!V68 -> 0 | W68: =S68+'APONTAMENTO CREDENCIAMENTO'!W68 -> 0 | X68: =T68+'APONTAMENTO CREDENCIAMENTO'!X68 -> 0 | Y68: =U68+'APONTAMENTO CREDENCIAMENTO'!Y68 -> 9 | Z68: =V68+'APONTAMENTO CREDENCIAMENTO'!Z68 -> 0 | AA68: =W68+'APONTAMENTO CREDENCIAMENTO'!AA68 -> 0 | AB68: =X68+'APONTAMENTO CREDENCIAMENTO'!AB68 -> 0 | ... EF68: =EB68+'APONTAMENTO CREDENCIAMENTO'!EF68 -> 0 | EP68: 9 | EQ68: 0 | ER68: 0 | ES68: 0 | ET68: 0 | EU68: 0 | EV68: 9 | EX68: 0 | EY68: 0 | EZ68: 0 | FA68: 0 | FB68: 0 | FC68: 0 | FD68: 0 | GL68: 0 | HY68: 0 | HZ68: 0 | IA68: 0
A69: 022.608-00 | B69: 2022/0030845-001A | C69: FBE | D69: 2022/0030845 | E69: ELQ8250 | F69: 01/04/2026 | G69: 30/04/2026 | H69: JOSE FIRMINO BATISTA | I69: JOSE FIRMINO BATISTA | J69: NORMAL | K69: CEI | L69: 0 | M69: 0 | O69: 6020.2022/0030845-3 | P69: 0 | U69: =Q69+'APONTAMENTO CREDENCIAMENTO'!U69 -> 0 | V69: =R69+'APONTAMENTO CREDENCIAMENTO'!V69 -> 0 | W69: =S69+'APONTAMENTO CREDENCIAMENTO'!W69 -> 0 | X69: =T69+'APONTAMENTO CREDENCIAMENTO'!X69 -> 0 | Y69: =U69+'APONTAMENTO CREDENCIAMENTO'!Y69 -> 0 | Z69: =V69+'APONTAMENTO CREDENCIAMENTO'!Z69 -> 0 | AA69: =W69+'APONTAMENTO CREDENCIAMENTO'!AA69 -> 0 | AB69: =X69+'APONTAMENTO CREDENCIAMENTO'!AB69 -> 0 | ... EF69: =EB69+'APONTAMENTO CREDENCIAMENTO'!EF69 -> 0 | EP69: 0 | EQ69: 0 | ER69: 0 | ES69: 0 | ET69: 0 | EU69: 0 | EV69: 0 | EX69: 0 | EY69: 0 | EZ69: 0 | FA69: 0 | FB69: 0 | FC69: 0 | FD69: 0 | GL69: 0 | HY69: 0 | HZ69: 0 | IA69: 0
A70: 022.608-00 | B70: 2022/0030845-001A | C70: FBE | D70: 2022/0030845 | E70: ELQ8250 | F70: 01/04/2026 | G70: 30/04/2026 | H70: JOSE FIRMINO BATISTA | I70: JOSE FIRMINO BATISTA | J70: NORMAL | K70: CCA | L70: 0 | M70: 0 | O70: 6020.2022/0030845-3 | P70: 0 | U70: =Q70+'APONTAMENTO CREDENCIAMENTO'!U70 -> 0 | V70: =R70+'APONTAMENTO CREDENCIAMENTO'!V70 -> 0 | W70: =S70+'APONTAMENTO CREDENCIAMENTO'!W70 -> 0 | X70: =T70+'APONTAMENTO CREDENCIAMENTO'!X70 -> 0 | Y70: =U70+'APONTAMENTO CREDENCIAMENTO'!Y70 -> 0 | Z70: =V70+'APONTAMENTO CREDENCIAMENTO'!Z70 -> 0 | AA70: =W70+'APONTAMENTO CREDENCIAMENTO'!AA70 -> 0 | AB70: =X70+'APONTAMENTO CREDENCIAMENTO'!AB70 -> 0 | ... EF70: =EB70+'APONTAMENTO CREDENCIAMENTO'!EF70 -> 0 | EP70: 0 | EQ70: 0 | ER70: 0 | ES70: 0 | ET70: 0 | EU70: 0 | EV70: 0 | EX70: 0 | EY70: 0 | EZ70: 0 | FA70: 0 | FB70: 0 | FC70: 0 | FD70: 0 | FF70: 0 | FG70: 0 | FH70: 0 | FI70: 0 | FJ70: 0 | FK70: 0 | FL70: 0 | FM70: 0 | FN70: 0 | FO70: 0 | FP70: 0 | FQ70: 0 | FR70: 0 | FS70: 0 | FT70: 0 | FU70: 0 | FV70: 0 | FW70: 0 | FX70: 0 | FY70: 0 | FZ70: 0 | GA70: 0 | GB70: 0 | GC70: 0 | GD70: 0 | GE70: 0 | GF70: 0 | GG70: 0 | GH70: 0 | GI70: 0 | GJ70: 0 | GL70: 0 | HY70: 0 | HZ70: 0 | IA70: 0
A71: 029.004-00 | B71: 2022/0027707-001 | C71: 1 | D71: 2022/0027707 | E71: FFN2680 | F71: 01/04/2026 | G71: 30/04/2026 | H71: JOSE RICARDO FERREIRA DOS SANTOS | I71: JOSE RICARDO FERREIRA DOS SANTOS | J71: NORMAL | K71: EMEI | L71: 0 | M71: 0 | O71: 6020.2022/0027707-8 | P71: 0 | U71: =Q71+'APONTAMENTO CREDENCIAMENTO'!U71 -> 0 | V71: =R71+'APONTAMENTO CREDENCIAMENTO'!V71 -> 0 | W71: =S71+'APONTAMENTO CREDENCIAMENTO'!W71 -> 0 | X71: =T71+'APONTAMENTO CREDENCIAMENTO'!X71 -> 0 | Y71: =U71+'APONTAMENTO CREDENCIAMENTO'!Y71 -> 0 | Z71: =V71+'APONTAMENTO CREDENCIAMENTO'!Z71 -> 0 | AA71: =W71+'APONTAMENTO CREDENCIAMENTO'!AA71 -> 0 | AB71: =X71+'APONTAMENTO CREDENCIAMENTO'!AB71 -> 0 | ... EF71: =EB71+'APONTAMENTO CREDENCIAMENTO'!EF71 -> 0 | EP71: 0 | EQ71: 0 | ER71: 0 | ES71: 0 | ET71: 0 | EU71: 0 | EV71: 0 | EW71: 0 | EX71: 17893.73 | EY71: 0 | EZ71: 0 | FA71: 0 | FB71: 0 | FC71: 0 | FD71: 0 | FE71: 17941.93 | FF71: 17893.73 | FG71: 0 | FH71: 0 | FI71: 0 | FJ71: 0 | FK71: 0 | FL71: 0 | FM71: 0 | FN71: 0 | FO71: 0 | FP71: 0 | FQ71: 0 | FR71: 0 | FS71: 0 | FT71: 0 | FU71: 0 | FV71: 0 | FW71: 0 | FX71: 0 | FY71: 0 | FZ71: 0 | GA71: 0 | GB71: 0 | GC71: 0 | GD71: 0 | GE71: 0 | GF71: 0 | GG71: 0 | GH71: 0 | GI71: 0 | GJ71: 0 | GL71: 0 | GN71: 0 | GO71: 0 | GP71: 0 | GQ71: 0 | GR71: 0 | GS71: 0 | GT71: 0 | GU71: 0 | GV71: 0 | GW71: 0 | GX71: 0 | GY71: 0 | GZ71: 0 | HA71: 0 | HB71: 0 | HC71: 0 | HD71: 0 | HE71: 0 | HF71: 0 | HG71: 0 | HH71: 0 | HI71: 0 | HJ71: 0 | HK71: 0 | HL71: 0 | HM71: 0 | HN71: 0 | HO71: 0 | HP71: 0 | HW71: 17629.31 | HY71: 0 | HZ71: 0 | IA71: 0 | IB71: FALSE
A72: 029.004-00 | B72: 2022/0027707-001 | C72: FB | D72: 2022/0027707 | E72: FFN2680 | F72: 01/04/2026 | G72: 30/04/2026 | H72: JOSE RICARDO FERREIRA DOS SANTOS | I72: JOSE RICARDO FERREIRA DOS SANTOS | J72: NORMAL | K72: EMEF | L72: 5 | M72: 0 | O72: 6020.2022/0027707-8 | P72: 0 | Q72: 37 | S72: 6 | U72: =Q72+'APONTAMENTO CREDENCIAMENTO'!U72 -> 37 | V72: =R72+'APONTAMENTO CREDENCIAMENTO'!V72 -> 0 | W72: =S72+'APONTAMENTO CREDENCIAMENTO'!W72 -> 6 | X72: =T72+'APONTAMENTO CREDENCIAMENTO'!X72 -> 0 | Y72: =U72+'APONTAMENTO CREDENCIAMENTO'!Y72 -> 37 | Z72: =V72+'APONTAMENTO CREDENCIAMENTO'!Z72 -> 0 | AA72: =W72+'APONTAMENTO CREDENCIAMENTO'!AA72 -> 6 | AB72: =X72+'APONTAMENTO CREDENCIAMENTO'!AB72 -> 0 | ... EF72: =EB72+'APONTAMENTO CREDENCIAMENTO'!EF72 -> 0 | EP72: 37 | EQ72: 0 | ER72: 6 | ES72: 0 | ET72: 0 | EU72: 0 | EV72: 43 | EX72: 0 | EY72: 48.2 | EZ72: 0 | FA72: 0 | FB72: 0 | FC72: 0 | FD72: 0 | GL72: 0 | HY72: 0 | HZ72: 0 | IA72: 0
A73: 029.004-00 | B73: 2022/0027707-001 | C73: FB | D73: 2022/0027707 | E73: FFN2680 | F73: 01/04/2026 | G73: 30/04/2026 | H73: JOSE RICARDO FERREIRA DOS SANTOS | I73: JOSE RICARDO FERREIRA DOS SANTOS | J73: NORMAL | K73: EMEE | L73: 0 | M73: 0 | O73: 6020.2022/0027707-8 | P73: 0 | U73: =Q73+'APONTAMENTO CREDENCIAMENTO'!U73 -> 0 | V73: =R73+'APONTAMENTO CREDENCIAMENTO'!V73 -> 0 | W73: =S73+'APONTAMENTO CREDENCIAMENTO'!W73 -> 0 | X73: =T73+'APONTAMENTO CREDENCIAMENTO'!X73 -> 0 | Y73: =U73+'APONTAMENTO CREDENCIAMENTO'!Y73 -> 0 | Z73: =V73+'APONTAMENTO CREDENCIAMENTO'!Z73 -> 0 | AA73: =W73+'APONTAMENTO CREDENCIAMENTO'!AA73 -> 0 | AB73: =X73+'APONTAMENTO CREDENCIAMENTO'!AB73 -> 0 | ... EF73: =EB73+'APONTAMENTO CREDENCIAMENTO'!EF73 -> 0 | EP73: 0 | EQ73: 0 | ER73: 0 | ES73: 0 | ET73: 0 | EU73: 0 | EV73: 0 | EX73: 0 | EY73: 0 | EZ73: 0 | FA73: 0 | FB73: 0 | FC73: 0 | FD73: 0 | GL73: 0 | HY73: 0 | HZ73: 0 | IA73: 0
A74: 029.004-00 | B74: 2022/0027707-001 | C74: FB | D74: 2022/0027707 | E74: FFN2680 | F74: 01/04/2026 | G74: 30/04/2026 | H74: JOSE RICARDO FERREIRA DOS SANTOS | I74: JOSE RICARDO FERREIRA DOS SANTOS | J74: NORMAL | K74: CEI | L74: 0 | M74: 0 | O74: 6020.2022/0027707-8 | P74: 0 | U74: =Q74+'APONTAMENTO CREDENCIAMENTO'!U74 -> 0 | V74: =R74+'APONTAMENTO CREDENCIAMENTO'!V74 -> 0 | W74: =S74+'APONTAMENTO CREDENCIAMENTO'!W74 -> 0 | X74: =T74+'APONTAMENTO CREDENCIAMENTO'!X74 -> 0 | Y74: =U74+'APONTAMENTO CREDENCIAMENTO'!Y74 -> 0 | Z74: =V74+'APONTAMENTO CREDENCIAMENTO'!Z74 -> 0 | AA74: =W74+'APONTAMENTO CREDENCIAMENTO'!AA74 -> 0 | AB74: =X74+'APONTAMENTO CREDENCIAMENTO'!AB74 -> 0 | ... EF74: =EB74+'APONTAMENTO CREDENCIAMENTO'!EF74 -> 0 | EP74: 0 | EQ74: 0 | ER74: 0 | ES74: 0 | ET74: 0 | EU74: 0 | EV74: 0 | EX74: 0 | EY74: 0 | EZ74: 0 | FA74: 0 | FB74: 0 | FC74: 0 | FD74: 0 | GL74: 0 | HY74: 0 | HZ74: 0 | IA74: 0
A75: 029.004-00 | B75: 2022/0027707-001 | C75: FB | D75: 2022/0027707 | E75: FFN2680 | F75: 01/04/2026 | G75: 30/04/2026 | H75: JOSE RICARDO FERREIRA DOS SANTOS | I75: JOSE RICARDO FERREIRA DOS SANTOS | J75: NORMAL | K75: CCA | L75: 0 | M75: 0 | O75: 6020.2022/0027707-8 | P75: 0 | U75: =Q75+'APONTAMENTO CREDENCIAMENTO'!U75 -> 0 | V75: =R75+'APONTAMENTO CREDENCIAMENTO'!V75 -> 0 | W75: =S75+'APONTAMENTO CREDENCIAMENTO'!W75 -> 0 | X75: =T75+'APONTAMENTO CREDENCIAMENTO'!X75 -> 0 | Y75: =U75+'APONTAMENTO CREDENCIAMENTO'!Y75 -> 0 | Z75: =V75+'APONTAMENTO CREDENCIAMENTO'!Z75 -> 0 | AA75: =W75+'APONTAMENTO CREDENCIAMENTO'!AA75 -> 0 | AB75: =X75+'APONTAMENTO CREDENCIAMENTO'!AB75 -> 0 | ... EF75: =EB75+'APONTAMENTO CREDENCIAMENTO'!EF75 -> 0 | EP75: 0 | EQ75: 0 | ER75: 0 | ES75: 0 | ET75: 0 | EU75: 0 | EV75: 0 | EX75: 0 | EY75: 0 | EZ75: 0 | FA75: 0 | FB75: 0 | FC75: 0 | FD75: 0 | FF75: 0 | FG75: 0 | FH75: 0 | FI75: 0 | FJ75: 0 | FK75: 0 | FL75: 0 | FM75: 0 | FN75: 0 | FO75: 0 | FP75: 0 | FQ75: 0 | FR75: 0 | FS75: 0 | FT75: 0 | FU75: 0 | FV75: 0 | FW75: 0 | FX75: 0 | FY75: 0 | FZ75: 0 | GA75: 0 | GB75: 0 | GC75: 0 | GD75: 0 | GE75: 0 | GF75: 0 | GG75: 0 | GH75: 0 | GI75: 0 | GJ75: 0 | GL75: 0 | HY75: 0 | HZ75: 0 | IA75: 0
A76: 017.058-00 | B76: 2022/0034092-001 | C76: 4 | D76: 2022/0034092 | E76: GIB7756 | F76: 01/04/2026 | G76: 30/04/2026 | H76: JUCINEIDE MOSSIN | I76: JUCINEIDE MOSSIN | J76: NORMAL | K76: EMEI | L76: 0 | M76: 0 | O76: 6020.2022/0034092-6 | P76: 0 | U76: =Q76+'APONTAMENTO CREDENCIAMENTO'!U76 -> 0 | V76: =R76+'APONTAMENTO CREDENCIAMENTO'!V76 -> 0 | W76: =S76+'APONTAMENTO CREDENCIAMENTO'!W76 -> 0 | X76: =T76+'APONTAMENTO CREDENCIAMENTO'!X76 -> 0 | Y76: =U76+'APONTAMENTO CREDENCIAMENTO'!Y76 -> 0 | Z76: =V76+'APONTAMENTO CREDENCIAMENTO'!Z76 -> 0 | AA76: =W76+'APONTAMENTO CREDENCIAMENTO'!AA76 -> 0 | AB76: =X76+'APONTAMENTO CREDENCIAMENTO'!AB76 -> 0 | ... EF76: =EB76+'APONTAMENTO CREDENCIAMENTO'!EF76 -> 0 | EP76: 0 | EQ76: 0 | ER76: 0 | ES76: 0 | ET76: 0 | EU76: 0 | EV76: 0 | EW76: 11465.63 | EX76: 2311.38 | EY76: 0 | EZ76: 218.297 | FA76: 0 | FB76: 0 | FC76: 0 | FD76: 0 | FE76: 13995.307 | FF76: 2311.38 | FG76: 0 | FH76: 0 | FI76: 0 | FJ76: 0 | FK76: 0 | FL76: 0 | FM76: 0 | FN76: 0 | FO76: 0 | FP76: 0 | FQ76: 0 | FR76: 0 | FS76: 0 | FT76: 0 | FU76: 0 | FV76: 0 | FW76: 0 | FX76: 0 | FY76: 0 | FZ76: 0 | GA76: 115.569 | GB76: 102.728 | GC76: 0 | GD76: 0 | GE76: 0 | GF76: 0 | GG76: 0 | GH76: 0 | GI76: 0 | GJ76: 0 | GL76: 0 | GN76: 0 | GO76: 0 | GP76: 0 | GQ76: 0 | GR76: 0 | GS76: 0 | GT76: 0 | GU76: 0 | GV76: 0 | GW76: 0 | GX76: 0 | GY76: 0 | GZ76: 0 | HA76: 0 | HB76: 0 | HC76: 0 | HD76: 0 | HE76: 0 | HF76: 0 | HG76: 0 | HH76: 0 | HI76: 0 | HJ76: 0 | HK76: 0 | HL76: 0 | HM76: 0 | HN76: 0 | HO76: 0 | HP76: 0 | HW76: 17629.31 | HY76: 0 | HZ76: 0 | IA76: 0 | IB76: FALSE
A77: 017.058-00 | B77: 2022/0034092-001 | C77: FBE | D77: 2022/0034092 | E77: GIB7756 | F77: 01/04/2026 | G77: 30/04/2026 | H77: JUCINEIDE MOSSIN | I77: JUCINEIDE MOSSIN | J77: NORMAL | K77: EMEF | L77: 0 | M77: 0 | O77: 6020.2022/0034092-6 | P77: 0 | U77: =Q77+'APONTAMENTO CREDENCIAMENTO'!U77 -> 0 | V77: =R77+'APONTAMENTO CREDENCIAMENTO'!V77 -> 0 | W77: =S77+'APONTAMENTO CREDENCIAMENTO'!W77 -> 0 | X77: =T77+'APONTAMENTO CREDENCIAMENTO'!X77 -> 0 | Y77: =U77+'APONTAMENTO CREDENCIAMENTO'!Y77 -> 0 | Z77: =V77+'APONTAMENTO CREDENCIAMENTO'!Z77 -> 0 | AA77: =W77+'APONTAMENTO CREDENCIAMENTO'!AA77 -> 0 | AB77: =X77+'APONTAMENTO CREDENCIAMENTO'!AB77 -> 0 | ... EF77: =EB77+'APONTAMENTO CREDENCIAMENTO'!EF77 -> 0 | EP77: 0 | EQ77: 0 | ER77: 0 | ES77: 0 | ET77: 0 | EU77: 0 | EV77: 0 | EX77: 0 | EY77: 0 | EZ77: 0 | FA77: 0 | FB77: 0 | FC77: 0 | FD77: 0 | GL77: 0 | HY77: 0 | HZ77: 0 | IA77: 0
A78: 017.058-00 | B78: 2022/0034092-001 | C78: FBE | D78: 2022/0034092 | E78: GIB7756 | F78: 01/04/2026 | G78: 30/04/2026 | H78: JUCINEIDE MOSSIN | I78: JUCINEIDE MOSSIN | J78: NORMAL | K78: EMEE | L78: 0 | M78: 0 | O78: 6020.2022/0034092-6 | P78: 0 | Q78: 6 | U78: =Q78+'APONTAMENTO CREDENCIAMENTO'!U78 -> 6 | V78: =R78+'APONTAMENTO CREDENCIAMENTO'!V78 -> 0 | W78: =S78+'APONTAMENTO CREDENCIAMENTO'!W78 -> 0 | X78: =T78+'APONTAMENTO CREDENCIAMENTO'!X78 -> 0 | Y78: =U78+'APONTAMENTO CREDENCIAMENTO'!Y78 -> 6 | Z78: =V78+'APONTAMENTO CREDENCIAMENTO'!Z78 -> 0 | AA78: =W78+'APONTAMENTO CREDENCIAMENTO'!AA78 -> 0 | AB78: =X78+'APONTAMENTO CREDENCIAMENTO'!AB78 -> 0 | ... EF78: =EB78+'APONTAMENTO CREDENCIAMENTO'!EF78 -> 0 | EP78: 6 | EQ78: 2 | ER78: 0 | ES78: 0 | ET78: 0 | EU78: 0 | EV78: 8 | EX78: 0 | EY78: 0 | EZ78: 0 | FA78: 0 | FB78: 0 | FC78: 0 | FD78: 0 | GL78: 0 | HY78: 0 | HZ78: 0 | IA78: 0
A79: 017.058-00 | B79: 2022/0034092-001 | C79: FBE | D79: 2022/0034092 | E79: GIB7756 | F79: 01/04/2026 | G79: 30/04/2026 | H79: JUCINEIDE MOSSIN | I79: JUCINEIDE MOSSIN | J79: NORMAL | K79: CEI | L79: 0 | M79: 0 | O79: 6020.2022/0034092-6 | P79: 0 | U79: =Q79+'APONTAMENTO CREDENCIAMENTO'!U79 -> 0 | V79: =R79+'APONTAMENTO CREDENCIAMENTO'!V79 -> 0 | W79: =S79+'APONTAMENTO CREDENCIAMENTO'!W79 -> 0 | X79: =T79+'APONTAMENTO CREDENCIAMENTO'!X79 -> 0 | Y79: =U79+'APONTAMENTO CREDENCIAMENTO'!Y79 -> 0 | Z79: =V79+'APONTAMENTO CREDENCIAMENTO'!Z79 -> 0 | AA79: =W79+'APONTAMENTO CREDENCIAMENTO'!AA79 -> 0 | AB79: =X79+'APONTAMENTO CREDENCIAMENTO'!AB79 -> 0 | ... EF79: =EB79+'APONTAMENTO CREDENCIAMENTO'!EF79 -> 0 | EP79: 0 | EQ79: 0 | ER79: 0 | ES79: 0 | ET79: 0 | EU79: 0 | EV79: 0 | EX79: 0 | EY79: 0 | EZ79: 0 | FA79: 0 | FB79: 0 | FC79: 0 | FD79: 0 | GL79: 0 | HY79: 0 | HZ79: 0 | IA79: 0
A80: 017.058-00 | B80: 2022/0034092-001 | C80: FBE | D80: 2022/0034092 | E80: GIB7756 | F80: 01/04/2026 | G80: 30/04/2026 | H80: JUCINEIDE MOSSIN | I80: JUCINEIDE MOSSIN | J80: NORMAL | K80: CCA | L80: 0 | M80: 0 | O80: 6020.2022/0034092-6 | P80: 0 | U80: =Q80+'APONTAMENTO CREDENCIAMENTO'!U80 -> 0 | V80: =R80+'APONTAMENTO CREDENCIAMENTO'!V80 -> 0 | W80: =S80+'APONTAMENTO CREDENCIAMENTO'!W80 -> 0 | X80: =T80+'APONTAMENTO CREDENCIAMENTO'!X80 -> 0 | Y80: =U80+'APONTAMENTO CREDENCIAMENTO'!Y80 -> 0 | Z80: =V80+'APONTAMENTO CREDENCIAMENTO'!Z80 -> 0 | AA80: =W80+'APONTAMENTO CREDENCIAMENTO'!AA80 -> 0 | AB80: =X80+'APONTAMENTO CREDENCIAMENTO'!AB80 -> 0 | ... EF80: =EB80+'APONTAMENTO CREDENCIAMENTO'!EF80 -> 0 | EP80: 0 | EQ80: 0 | ER80: 0 | ES80: 0 | ET80: 0 | EU80: 0 | EV80: 0 | EX80: 0 | EY80: 0 | EZ80: 0 | FA80: 0 | FB80: 0 | FC80: 0 | FD80: 0 | FF80: 0 | FG80: 0 | FH80: 0 | FI80: 0 | FJ80: 0 | FK80: 0 | FL80: 0 | FM80: 0 | FN80: 0 | FO80: 0 | FP80: 0 | FQ80: 0 | FR80: 0 | FS80: 0 | FT80: 0 | FU80: 0 | FV80: 0 | FW80: 0 | FX80: 0 | FY80: 0 | FZ80: 0 | GA80: 0 | GB80: 0 | GC80: 0 | GD80: 0 | GE80: 0 | GF80: 0 | GG80: 0 | GH80: 0 | GI80: 0 | GJ80: 0 | GL80: 0 | HY80: 0 | HZ80: 0 | IA80: 0
A81: 021.878-00 | B81: 2022/0025123-001C | C81: 1 | D81: 2022/0025123 | E81: DTA8749 | F81: 01/04/2026 | G81: 30/04/2026 | H81: LENILDO MANOEL DO NASCIMENTO | I81: LENILDO MANOEL DO NASCIMENTO | J81: NORMAL | K81: EMEI | L81: 0 | M81: 0 | O81: 6020.2022/0025123-0 | P81: 0 | Q81: 27 | U81: =Q81+'APONTAMENTO CREDENCIAMENTO'!U81 -> 27 | V81: =R81+'APONTAMENTO CREDENCIAMENTO'!V81 -> 0 | W81: =S81+'APONTAMENTO CREDENCIAMENTO'!W81 -> 0 | X81: =T81+'APONTAMENTO CREDENCIAMENTO'!X81 -> 0 | Y81: =U81+'APONTAMENTO CREDENCIAMENTO'!Y81 -> 27 | Z81: =V81+'APONTAMENTO CREDENCIAMENTO'!Z81 -> 0 | AA81: =W81+'APONTAMENTO CREDENCIAMENTO'!AA81 -> 0 | AB81: =X81+'APONTAMENTO CREDENCIAMENTO'!AB81 -> 0 | ... EF81: =EB81+'APONTAMENTO CREDENCIAMENTO'!EF81 -> 0 | EP81: 27 | EQ81: 1 | ER81: 0 | ES81: 0 | ET81: 0 | EU81: 0 | EV81: 28 | EW81: 0 | EX81: 19049.42 | EY81: 0 | EZ81: 102.728 | FA81: 0 | FB81: 0 | FC81: 0 | FD81: 0 | FE81: 19152.148 | FF81: 19049.42 | FG81: 0 | FH81: 0 | FI81: 0 | FJ81: 0 | FK81: 0 | FL81: 0 | FM81: 0 | FN81: 0 | FO81: 0 | FP81: 0 | FQ81: 0 | FR81: 0 | FS81: 0 | FT81: 0 | FU81: 0 | FV81: 0 | FW81: 0 | FX81: 0 | FY81: 0 | FZ81: 0 | GA81: 0 | GB81: 102.728 | GC81: 0 | GD81: 0 | GE81: 0 | GF81: 0 | GG81: 0 | GH81: 0 | GI81: 0 | GJ81: 0 | GL81: 0 | GN81: 0 | GO81: 0 | GP81: 0 | GQ81: 0 | GR81: 0 | GS81: 0 | GT81: 0 | GU81: 0 | GV81: 0 | GW81: 0 | GX81: 0 | GY81: 0 | GZ81: 0 | HA81: 0 | HB81: 0 | HC81: 0 | HD81: 0 | HE81: 0 | HF81: 0 | HG81: 0 | HH81: 0 | HI81: 0 | HJ81: 0 | HK81: 0 | HL81: 0 | HM81: 0 | HN81: 0 | HO81: 0 | HP81: 0 | HW81: 17629.31 | HY81: 0 | HZ81: 0 | IA81: 0 | IB81: FALSE
A82: 021.878-00 | B82: 2022/0025123-001C | C82: FB | D82: 2022/0025123 | E82: DTA8749 | F82: 01/04/2026 | G82: 30/04/2026 | H82: LENILDO MANOEL DO NASCIMENTO | I82: LENILDO MANOEL DO NASCIMENTO | J82: NORMAL | K82: EMEF | L82: 0 | M82: 0 | O82: 6020.2022/0025123-0 | P82: 0 | Q82: 19 | U82: =Q82+'APONTAMENTO CREDENCIAMENTO'!U82 -> 19 | V82: =R82+'APONTAMENTO CREDENCIAMENTO'!V82 -> 0 | W82: =S82+'APONTAMENTO CREDENCIAMENTO'!W82 -> 0 | X82: =T82+'APONTAMENTO CREDENCIAMENTO'!X82 -> 0 | Y82: =U82+'APONTAMENTO CREDENCIAMENTO'!Y82 -> 19 | Z82: =V82+'APONTAMENTO CREDENCIAMENTO'!Z82 -> 0 | AA82: =W82+'APONTAMENTO CREDENCIAMENTO'!AA82 -> 0 | AB82: =X82+'APONTAMENTO CREDENCIAMENTO'!AB82 -> 0 | ... EF82: =EB82+'APONTAMENTO CREDENCIAMENTO'!EF82 -> 0 | EP82: 19 | EQ82: 0 | ER82: 0 | ES82: 0 | ET82: 0 | EU82: 0 | EV82: 19 | EX82: 0 | EY82: 0 | EZ82: 0 | FA82: 0 | FB82: 0 | FC82: 0 | FD82: 0 | GL82: 0 | HY82: 0 | HZ82: 0 | IA82: 0
A83: 021.878-00 | B83: 2022/0025123-001C | C83: FB | D83: 2022/0025123 | E83: DTA8749 | F83: 01/04/2026 | G83: 30/04/2026 | H83: LENILDO MANOEL DO NASCIMENTO | I83: LENILDO MANOEL DO NASCIMENTO | J83: NORMAL | K83: EMEE | L83: 0 | M83: 0 | O83: 6020.2022/0025123-0 | P83: 0 | U83: =Q83+'APONTAMENTO CREDENCIAMENTO'!U83 -> 0 | V83: =R83+'APONTAMENTO CREDENCIAMENTO'!V83 -> 0 | W83: =S83+'APONTAMENTO CREDENCIAMENTO'!W83 -> 0 | X83: =T83+'APONTAMENTO CREDENCIAMENTO'!X83 -> 0 | Y83: =U83+'APONTAMENTO CREDENCIAMENTO'!Y83 -> 0 | Z83: =V83+'APONTAMENTO CREDENCIAMENTO'!Z83 -> 0 | AA83: =W83+'APONTAMENTO CREDENCIAMENTO'!AA83 -> 0 | AB83: =X83+'APONTAMENTO CREDENCIAMENTO'!AB83 -> 0 | ... EF83: =EB83+'APONTAMENTO CREDENCIAMENTO'!EF83 -> 0 | EP83: 0 | EQ83: 0 | ER83: 0 | ES83: 0 | ET83: 0 | EU83: 0 | EV83: 0 | EX83: 0 | EY83: 0 | EZ83: 0 | FA83: 0 | FB83: 0 | FC83: 0 | FD83: 0 | GL83: 0 | HY83: 0 | HZ83: 0 | IA83: 0
A84: 021.878-00 | B84: 2022/0025123-001C | C84: FB | D84: 2022/0025123 | E84: DTA8749 | F84: 01/04/2026 | G84: 30/04/2026 | H84: LENILDO MANOEL DO NASCIMENTO | I84: LENILDO MANOEL DO NASCIMENTO | J84: NORMAL | K84: CEI | L84: 0 | M84: 0 | O84: 6020.2022/0025123-0 | P84: 0 | U84: =Q84+'APONTAMENTO CREDENCIAMENTO'!U84 -> 0 | V84: =R84+'APONTAMENTO CREDENCIAMENTO'!V84 -> 0 | W84: =S84+'APONTAMENTO CREDENCIAMENTO'!W84 -> 0 | X84: =T84+'APONTAMENTO CREDENCIAMENTO'!X84 -> 0 | Y84: =U84+'APONTAMENTO CREDENCIAMENTO'!Y84 -> 0 | Z84: =V84+'APONTAMENTO CREDENCIAMENTO'!Z84 -> 0 | AA84: =W84+'APONTAMENTO CREDENCIAMENTO'!AA84 -> 0 | AB84: =X84+'APONTAMENTO CREDENCIAMENTO'!AB84 -> 0 | ... EF84: =EB84+'APONTAMENTO CREDENCIAMENTO'!EF84 -> 0 | EP84: 0 | EQ84: 0 | ER84: 0 | ES84: 0 | ET84: 0 | EU84: 0 | EV84: 0 | EX84: 0 | EY84: 0 | EZ84: 0 | FA84: 0 | FB84: 0 | FC84: 0 | FD84: 0 | GL84: 0 | HY84: 0 | HZ84: 0 | IA84: 0
A85: 021.878-00 | B85: 2022/0025123-001C | C85: FB | D85: 2022/0025123 | E85: DTA8749 | F85: 01/04/2026 | G85: 30/04/2026 | H85: LENILDO MANOEL DO NASCIMENTO | I85: LENILDO MANOEL DO NASCIMENTO | J85: NORMAL | K85: CCA | L85: 0 | M85: 0 | O85: 6020.2022/0025123-0 | P85: 0 | U85: =Q85+'APONTAMENTO CREDENCIAMENTO'!U85 -> 0 | V85: =R85+'APONTAMENTO CREDENCIAMENTO'!V85 -> 0 | W85: =S85+'APONTAMENTO CREDENCIAMENTO'!W85 -> 0 | X85: =T85+'APONTAMENTO CREDENCIAMENTO'!X85 -> 0 | Y85: =U85+'APONTAMENTO CREDENCIAMENTO'!Y85 -> 0 | Z85: =V85+'APONTAMENTO CREDENCIAMENTO'!Z85 -> 0 | AA85: =W85+'APONTAMENTO CREDENCIAMENTO'!AA85 -> 0 | AB85: =X85+'APONTAMENTO CREDENCIAMENTO'!AB85 -> 0 | ... EF85: =EB85+'APONTAMENTO CREDENCIAMENTO'!EF85 -> 0 | EP85: 0 | EQ85: 0 | ER85: 0 | ES85: 0 | ET85: 0 | EU85: 0 | EV85: 0 | EX85: 0 | EY85: 0 | EZ85: 0 | FA85: 0 | FB85: 0 | FC85: 0 | FD85: 0 | FF85: 0 | FG85: 0 | FH85: 0 | FI85: 0 | FJ85: 0 | FK85: 0 | FL85: 0 | FM85: 0 | FN85: 0 | FO85: 0 | FP85: 0 | FQ85: 0 | FR85: 0 | FS85: 0 | FT85: 0 | FU85: 0 | FV85: 0 | FW85: 0 | FX85: 0 | FY85: 0 | FZ85: 0 | GA85: 0 | GB85: 0 | GC85: 0 | GD85: 0 | GE85: 0 | GF85: 0 | GG85: 0 | GH85: 0 | GI85: 0 | GJ85: 0 | GL85: 0 | HY85: 0 | HZ85: 0 | IA85: 0
A86: 023.311-00 | B86: 2022/0028906-001C | C86: 1 | D86: 2022/0028906 | E86: UDX3C07 | F86: 01/04/2026 | G86: 30/04/2026 | H86: LUCIA MARIZ RAMOS CONTELI | I86: LUCIA MARIZ RAMOS CONTELI | J86: NORMAL | K86: EMEI | L86: 0 | M86: 0 | O86: 6020.2022/0028906-8 | P86: 0 | Q86: 4 | U86: =Q86+'APONTAMENTO CREDENCIAMENTO'!U86 -> 4 | V86: =R86+'APONTAMENTO CREDENCIAMENTO'!V86 -> 0 | W86: =S86+'APONTAMENTO CREDENCIAMENTO'!W86 -> 0 | X86: =T86+'APONTAMENTO CREDENCIAMENTO'!X86 -> 0 | Y86: =U86+'APONTAMENTO CREDENCIAMENTO'!Y86 -> 4 | Z86: =V86+'APONTAMENTO CREDENCIAMENTO'!Z86 -> 0 | AA86: =W86+'APONTAMENTO CREDENCIAMENTO'!AA86 -> 0 | AB86: =X86+'APONTAMENTO CREDENCIAMENTO'!AB86 -> 0 | ... EF86: =EB86+'APONTAMENTO CREDENCIAMENTO'!EF86 -> 0 | EP86: 4 | EQ86: 2 | ER86: 0 | ES86: 0 | ET86: 0 | EU86: 0 | EV86: 6 | EW86: 0 | EX86: 18664.19 | EY86: 0 | EZ86: 1284.1 | FA86: 0 | FB86: 0 | FC86: 0 | FD86: 0 | FE86: 19948.29 | FF86: 18664.19 | FG86: 0 | FH86: 0 | FI86: 0 | FJ86: 0 | FK86: 321.025 | FL86: 308.184 | FM86: 0 | FN86: 0 | FO86: 0 | FP86: 0 | FQ86: 0 | FR86: 231.138 | FS86: 218.297 | FT86: 0 | FU86: 0 | FV86: 0 | FW86: 0 | FX86: 0 | FY86: 0 | FZ86: 0 | GA86: 0 | GB86: 205.456 | GC86: 0 | GD86: 0 | GE86: 0 | GF86: 0 | GG86: 0 | GH86: 0 | GI86: 0 | GJ86: 0 | GL86: 0 | GN86: 0 | GO86: 0 | GP86: 0 | GQ86: 0 | GR86: 0 | GS86: 0 | GT86: 0 | GU86: 0 | GV86: 0 | GW86: 0 | GX86: 0 | GY86: 0 | GZ86: 0 | HA86: 0 | HB86: 0 | HC86: 0 | HD86: 0 | HE86: 0 | HF86: 0 | HG86: 0 | HH86: 0 | HI86: 0 | HJ86: 0 | HK86: 0 | HL86: 0 | HM86: 0 | HN86: 0 | HO86: 0 | HP86: 0 | HW86: 17629.31 | HY86: 0 | HZ86: 0 | IA86: 0 | IB86: FALSE
A87: 023.311-00 | B87: 2022/0028906-001C | C87: FB | D87: 2022/0028906 | E87: UDX3C07 | F87: 01/04/2026 | G87: 30/04/2026 | H87: LUCIA MARIZ RAMOS CONTELI | I87: LUCIA MARIZ RAMOS CONTELI | J87: NORMAL | K87: EMEF | L87: 0 | M87: 0 | O87: 6020.2022/0028906-8 | P87: 0 | Q87: 41 | U87: =Q87+'APONTAMENTO CREDENCIAMENTO'!U87 -> 41 | V87: =R87+'APONTAMENTO CREDENCIAMENTO'!V87 -> 0 | W87: =S87+'APONTAMENTO CREDENCIAMENTO'!W87 -> 0 | X87: =T87+'APONTAMENTO CREDENCIAMENTO'!X87 -> 0 | Y87: =U87+'APONTAMENTO CREDENCIAMENTO'!Y87 -> 41 | Z87: =V87+'APONTAMENTO CREDENCIAMENTO'!Z87 -> 0 | AA87: =W87+'APONTAMENTO CREDENCIAMENTO'!AA87 -> 0 | AB87: =X87+'APONTAMENTO CREDENCIAMENTO'!AB87 -> 0 | ... EF87: =EB87+'APONTAMENTO CREDENCIAMENTO'!EF87 -> 0 | EP87: 41 | EQ87: 4 | ER87: 0 | ES87: 0 | ET87: 0 | EU87: 0 | EV87: 45 | EX87: 0 | EY87: 0 | EZ87: 0 | FA87: 0 | FB87: 0 | FC87: 0 | FD87: 0 | GL87: 0 | HY87: 0 | HZ87: 0 | IA87: 0
A88: 023.311-00 | B88: 2022/0028906-001C | C88: FB | D88: 2022/0028906 | E88: UDX3C07 | F88: 01/04/2026 | G88: 30/04/2026 | H88: LUCIA MARIZ RAMOS CONTELI | I88: LUCIA MARIZ RAMOS CONTELI | J88: NORMAL | K88: EMEE | L88: 0 | M88: 0 | O88: 6020.2022/0028906-8 | P88: 0 | U88: =Q88+'APONTAMENTO CREDENCIAMENTO'!U88 -> 0 | V88: =R88+'APONTAMENTO CREDENCIAMENTO'!V88 -> 0 | W88: =S88+'APONTAMENTO CREDENCIAMENTO'!W88 -> 0 | X88: =T88+'APONTAMENTO CREDENCIAMENTO'!X88 -> 0 | Y88: =U88+'APONTAMENTO CREDENCIAMENTO'!Y88 -> 0 | Z88: =V88+'APONTAMENTO CREDENCIAMENTO'!Z88 -> 0 | AA88: =W88+'APONTAMENTO CREDENCIAMENTO'!AA88 -> 0 | AB88: =X88+'APONTAMENTO CREDENCIAMENTO'!AB88 -> 0 | ... EF88: =EB88+'APONTAMENTO CREDENCIAMENTO'!EF88 -> 0 | EP88: 0 | EQ88: 0 | ER88: 0 | ES88: 0 | ET88: 0 | EU88: 0 | EV88: 0 | EX88: 0 | EY88: 0 | EZ88: 0 | FA88: 0 | FB88: 0 | FC88: 0 | FD88: 0 | GL88: 0 | HY88: 0 | HZ88: 0 | IA88: 0
A89: 023.311-00 | B89: 2022/0028906-001C | C89: FB | D89: 2022/0028906 | E89: UDX3C07 | F89: 01/04/2026 | G89: 30/04/2026 | H89: LUCIA MARIZ RAMOS CONTELI | I89: LUCIA MARIZ RAMOS CONTELI | J89: NORMAL | K89: CEI | L89: 0 | M89: 0 | O89: 6020.2022/0028906-8 | P89: 0 | U89: =Q89+'APONTAMENTO CREDENCIAMENTO'!U89 -> 0 | V89: =R89+'APONTAMENTO CREDENCIAMENTO'!V89 -> 0 | W89: =S89+'APONTAMENTO CREDENCIAMENTO'!W89 -> 0 | X89: =T89+'APONTAMENTO CREDENCIAMENTO'!X89 -> 0 | Y89: =U89+'APONTAMENTO CREDENCIAMENTO'!Y89 -> 0 | Z89: =V89+'APONTAMENTO CREDENCIAMENTO'!Z89 -> 0 | AA89: =W89+'APONTAMENTO CREDENCIAMENTO'!AA89 -> 0 | AB89: =X89+'APONTAMENTO CREDENCIAMENTO'!AB89 -> 0 | ... EF89: =EB89+'APONTAMENTO CREDENCIAMENTO'!EF89 -> 0 | EP89: 0 | EQ89: 0 | ER89: 0 | ES89: 0 | ET89: 0 | EU89: 0 | EV89: 0 | EX89: 0 | EY89: 0 | EZ89: 0 | FA89: 0 | FB89: 0 | FC89: 0 | FD89: 0 | GL89: 0 | HY89: 0 | HZ89: 0 | IA89: 0
A90: 023.311-00 | B90: 2022/0028906-001C | C90: FB | D90: 2022/0028906 | E90: UDX3C07 | F90: 01/04/2026 | G90: 30/04/2026 | H90: LUCIA MARIZ RAMOS CONTELI | I90: LUCIA MARIZ RAMOS CONTELI | J90: NORMAL | K90: CCA | L90: 0 | M90: 0 | O90: 6020.2022/0028906-8 | P90: 0 | U90: =Q90+'APONTAMENTO CREDENCIAMENTO'!U90 -> 0 | V90: =R90+'APONTAMENTO CREDENCIAMENTO'!V90 -> 0 | W90: =S90+'APONTAMENTO CREDENCIAMENTO'!W90 -> 0 | X90: =T90+'APONTAMENTO CREDENCIAMENTO'!X90 -> 0 | Y90: =U90+'APONTAMENTO CREDENCIAMENTO'!Y90 -> 0 | Z90: =V90+'APONTAMENTO CREDENCIAMENTO'!Z90 -> 0 | AA90: =W90+'APONTAMENTO CREDENCIAMENTO'!AA90 -> 0 | AB90: =X90+'APONTAMENTO CREDENCIAMENTO'!AB90 -> 0 | ... EF90: =EB90+'APONTAMENTO CREDENCIAMENTO'!EF90 -> 0 | EP90: 0 | EQ90: 0 | ER90: 0 | ES90: 0 | ET90: 0 | EU90: 0 | EV90: 0 | EX90: 0 | EY90: 0 | EZ90: 0 | FA90: 0 | FB90: 0 | FC90: 0 | FD90: 0 | FF90: 0 | FG90: 0 | FH90: 0 | FI90: 0 | FJ90: 0 | FK90: 0 | FL90: 0 | FM90: 0 | FN90: 0 | FO90: 0 | FP90: 0 | FQ90: 0 | FR90: 0 | FS90: 0 | FT90: 0 | FU90: 0 | FV90: 0 | FW90: 0 | FX90: 0 | FY90: 0 | FZ90: 0 | GA90: 0 | GB90: 0 | GC90: 0 | GD90: 0 | GE90: 0 | GF90: 0 | GG90: 0 | GH90: 0 | GI90: 0 | GJ90: 0 | GL90: 0 | HY90: 0 | HZ90: 0 | IA90: 0
A91: 046.270-00 | B91: 2024/0016319-001A | C91: 1 | D91: 2024/0016319 | E91: TJK7J20 | F91: 01/04/2026 | G91: 30/04/2026 | H91: LUCIANA ALINE SILVEIRA PAIVA | I91: LUCIANA ALINE SILVEIRA PAIVA | J91: NORMAL | K91: EMEI | L91: 0 | M91: 0 | O91: 6020.2024/0016319-0 | P91: 0 | U91: =Q91+'APONTAMENTO CREDENCIAMENTO'!U91 -> 0 | V91: =R91+'APONTAMENTO CREDENCIAMENTO'!V91 -> 0 | W91: =S91+'APONTAMENTO CREDENCIAMENTO'!W91 -> 0 | X91: =T91+'APONTAMENTO CREDENCIAMENTO'!X91 -> 0 | Y91: =U91+'APONTAMENTO CREDENCIAMENTO'!Y91 -> 0 | Z91: =V91+'APONTAMENTO CREDENCIAMENTO'!Z91 -> 0 | AA91: =W91+'APONTAMENTO CREDENCIAMENTO'!AA91 -> 0 | AB91: =X91+'APONTAMENTO CREDENCIAMENTO'!AB91 -> 0 | ... EF91: =EB91+'APONTAMENTO CREDENCIAMENTO'!EF91 -> 0 | EP91: 0 | EQ91: 0 | ER91: 0 | ES91: 0 | ET91: 0 | EU91: 0 | EV91: 0 | EW91: 0 | EX91: 25983.56 | EY91: 0 | EZ91: 0 | FA91: 0 | FB91: 0 | FC91: 0 | FD91: 0 | FE91: 26157.08 | FF91: 25983.56 | FG91: 0 | FH91: 0 | FI91: 0 | FJ91: 0 | FK91: 0 | FL91: 0 | FM91: 0 | FN91: 0 | FO91: 0 | FP91: 0 | FQ91: 0 | FR91: 0 | FS91: 0 | FT91: 0 | FU91: 0 | FV91: 0 | FW91: 0 | FX91: 0 | FY91: 0 | FZ91: 0 | GA91: 0 | GB91: 0 | GC91: 0 | GD91: 0 | GE91: 0 | GF91: 0 | GG91: 0 | GH91: 0 | GI91: 0 | GJ91: 0 | GL91: 0 | GN91: 0 | GO91: 0 | GP91: 0 | GQ91: 0 | GR91: 0 | GS91: 0 | GT91: 0 | GU91: 0 | GV91: 0 | GW91: 0 | GX91: 0 | GY91: 0 | GZ91: 0 | HA91: 0 | HB91: 0 | HC91: 0 | HD91: 0 | HE91: 0 | HF91: 0 | HG91: 0 | HH91: 0 | HI91: 0 | HJ91: 0 | HK91: 0 | HL91: 0 | HM91: 0 | HN91: 0 | HO91: 0 | HP91: 0 | HW91: 17629.31 | HY91: 0 | HZ91: 0 | IA91: 0 | IB91: FALSE
A92: 046.270-00 | B92: 2024/0016319-001A | C92: FB | D92: 2024/0016319 | E92: TJK7J20 | F92: 01/04/2026 | G92: 30/04/2026 | H92: LUCIANA ALINE SILVEIRA PAIVA | I92: LUCIANA ALINE SILVEIRA PAIVA | J92: NORMAL | K92: EMEF | L92: 18 | M92: 0 | O92: 6020.2024/0016319-0 | P92: 0 | Q92: 55 | S92: 9 | U92: =Q92+'APONTAMENTO CREDENCIAMENTO'!U92 -> 55 | V92: =R92+'APONTAMENTO CREDENCIAMENTO'!V92 -> 0 | W92: =S92+'APONTAMENTO CREDENCIAMENTO'!W92 -> 9 | X92: =T92+'APONTAMENTO CREDENCIAMENTO'!X92 -> 0 | Y92: =U92+'APONTAMENTO CREDENCIAMENTO'!Y92 -> 55 | Z92: =V92+'APONTAMENTO CREDENCIAMENTO'!Z92 -> 0 | AA92: =W92+'APONTAMENTO CREDENCIAMENTO'!AA92 -> 9 | AB92: =X92+'APONTAMENTO CREDENCIAMENTO'!AB92 -> 0 | ... EF92: =EB92+'APONTAMENTO CREDENCIAMENTO'!EF92 -> 0 | EP92: 55 | EQ92: 0 | ER92: 9 | ES92: 0 | ET92: 0 | EU92: 0 | EV92: 64 | EX92: 0 | EY92: 173.52 | EZ92: 0 | FA92: 0 | FB92: 0 | FC92: 0 | FD92: 0 | GL92: 0 | HY92: 0 | HZ92: 0 | IA92: 0
A93: 046.270-00 | B93: 2024/0016319-001A | C93: FB | D93: 2024/0016319 | E93: TJK7J20 | F93: 01/04/2026 | G93: 30/04/2026 | H93: LUCIANA ALINE SILVEIRA PAIVA | I93: LUCIANA ALINE SILVEIRA PAIVA | J93: NORMAL | K93: EMEE | L93: 0 | M93: 0 | O93: 6020.2024/0016319-0 | P93: 0 | U93: =Q93+'APONTAMENTO CREDENCIAMENTO'!U93 -> 0 | V93: =R93+'APONTAMENTO CREDENCIAMENTO'!V93 -> 0 | W93: =S93+'APONTAMENTO CREDENCIAMENTO'!W93 -> 0 | X93: =T93+'APONTAMENTO CREDENCIAMENTO'!X93 -> 0 | Y93: =U93+'APONTAMENTO CREDENCIAMENTO'!Y93 -> 0 | Z93: =V93+'APONTAMENTO CREDENCIAMENTO'!Z93 -> 0 | AA93: =W93+'APONTAMENTO CREDENCIAMENTO'!AA93 -> 0 | AB93: =X93+'APONTAMENTO CREDENCIAMENTO'!AB93 -> 0 | ... EF93: =EB93+'APONTAMENTO CREDENCIAMENTO'!EF93 -> 0 | EP93: 0 | EQ93: 0 | ER93: 0 | ES93: 0 | ET93: 0 | EU93: 0 | EV93: 0 | EX93: 0 | EY93: 0 | EZ93: 0 | FA93: 0 | FB93: 0 | FC93: 0 | FD93: 0 | GL93: 0 | HY93: 0 | HZ93: 0 | IA93: 0
A94: 046.270-00 | B94: 2024/0016319-001A | C94: FB | D94: 2024/0016319 | E94: TJK7J20 | F94: 01/04/2026 | G94: 30/04/2026 | H94: LUCIANA ALINE SILVEIRA PAIVA | I94: LUCIANA ALINE SILVEIRA PAIVA | J94: NORMAL | K94: CEI | L94: 0 | M94: 0 | O94: 6020.2024/0016319-0 | P94: 0 | U94: =Q94+'APONTAMENTO CREDENCIAMENTO'!U94 -> 0 | V94: =R94+'APONTAMENTO CREDENCIAMENTO'!V94 -> 0 | W94: =S94+'APONTAMENTO CREDENCIAMENTO'!W94 -> 0 | X94: =T94+'APONTAMENTO CREDENCIAMENTO'!X94 -> 0 | Y94: =U94+'APONTAMENTO CREDENCIAMENTO'!Y94 -> 0 | Z94: =V94+'APONTAMENTO CREDENCIAMENTO'!Z94 -> 0 | AA94: =W94+'APONTAMENTO CREDENCIAMENTO'!AA94 -> 0 | AB94: =X94+'APONTAMENTO CREDENCIAMENTO'!AB94 -> 0 | ... EF94: =EB94+'APONTAMENTO CREDENCIAMENTO'!EF94 -> 0 | EP94: 0 | EQ94: 0 | ER94: 0 | ES94: 0 | ET94: 0 | EU94: 0 | EV94: 0 | EX94: 0 | EY94: 0 | EZ94: 0 | FA94: 0 | FB94: 0 | FC94: 0 | FD94: 0 | GL94: 0 | HY94: 0 | HZ94: 0 | IA94: 0
A95: 046.270-00 | B95: 2024/0016319-001A | C95: FB | D95: 2024/0016319 | E95: TJK7J20 | F95: 01/04/2026 | G95: 30/04/2026 | H95: LUCIANA ALINE SILVEIRA PAIVA | I95: LUCIANA ALINE SILVEIRA PAIVA | J95: NORMAL | K95: CCA | L95: 0 | M95: 0 | O95: 6020.2024/0016319-0 | P95: 0 | U95: =Q95+'APONTAMENTO CREDENCIAMENTO'!U95 -> 0 | V95: =R95+'APONTAMENTO CREDENCIAMENTO'!V95 -> 0 | W95: =S95+'APONTAMENTO CREDENCIAMENTO'!W95 -> 0 | X95: =T95+'APONTAMENTO CREDENCIAMENTO'!X95 -> 0 | Y95: =U95+'APONTAMENTO CREDENCIAMENTO'!Y95 -> 0 | Z95: =V95+'APONTAMENTO CREDENCIAMENTO'!Z95 -> 0 | AA95: =W95+'APONTAMENTO CREDENCIAMENTO'!AA95 -> 0 | AB95: =X95+'APONTAMENTO CREDENCIAMENTO'!AB95 -> 0 | ... EF95: =EB95+'APONTAMENTO CREDENCIAMENTO'!EF95 -> 0 | EP95: 0 | EQ95: 0 | ER95: 0 | ES95: 0 | ET95: 0 | EU95: 0 | EV95: 0 | EX95: 0 | EY95: 0 | EZ95: 0 | FA95: 0 | FB95: 0 | FC95: 0 | FD95: 0 | FF95: 0 | FG95: 0 | FH95: 0 | FI95: 0 | FJ95: 0 | FK95: 0 | FL95: 0 | FM95: 0 | FN95: 0 | FO95: 0 | FP95: 0 | FQ95: 0 | FR95: 0 | FS95: 0 | FT95: 0 | FU95: 0 | FV95: 0 | FW95: 0 | FX95: 0 | FY95: 0 | FZ95: 0 | GA95: 0 | GB95: 0 | GC95: 0 | GD95: 0 | GE95: 0 | GF95: 0 | GG95: 0 | GH95: 0 | GI95: 0 | GJ95: 0 | GL95: 0 | HY95: 0 | HZ95: 0 | IA95: 0
A96: 014.199-00 | B96: 2022/0029312-001 | C96: 1 | D96: 2022/0029312 | E96: CZZ1758 | F96: 01/04/2026 | G96: 30/04/2026 | H96: MARIO MORENO | I96: MARIO MORENO | J96: NORMAL | K96: EMEI | L96: 0 | M96: 0 | O96: 6020.2022/0029312-0 | P96: 0 | Q96: 28 | U96: =Q96+'APONTAMENTO CREDENCIAMENTO'!U96 -> 28 | V96: =R96+'APONTAMENTO CREDENCIAMENTO'!V96 -> 0 | W96: =S96+'APONTAMENTO CREDENCIAMENTO'!W96 -> 0 | X96: =T96+'APONTAMENTO CREDENCIAMENTO'!X96 -> 0 | Y96: =U96+'APONTAMENTO CREDENCIAMENTO'!Y96 -> 28 | Z96: =V96+'APONTAMENTO CREDENCIAMENTO'!Z96 -> 0 | AA96: =W96+'APONTAMENTO CREDENCIAMENTO'!AA96 -> 0 | AB96: =X96+'APONTAMENTO CREDENCIAMENTO'!AB96 -> 0 | ... EF96: =EB96+'APONTAMENTO CREDENCIAMENTO'!EF96 -> 0 | EP96: 28 | EQ96: 0 | ER96: 0 | ES96: 0 | ET96: 0 | EU96: 0 | EV96: 28 | EW96: 0 | EX96: 12115.28 | EY96: 0 | EZ96: 205.456 | FA96: -269.661 | FB96: 0 | FC96: 0 | FD96: 0 | FE96: 12051.075 | FF96: 12115.28 | FG96: 0 | FH96: 0 | FI96: 0 | FJ96: 0 | FK96: 0 | FL96: 0 | FM96: 0 | FN96: 0 | FO96: -269.661 | FP96: 0 | FQ96: 0 | FR96: 0 | FS96: 0 | FT96: 205.456 | FU96: 0 | FV96: 0 | FW96: 0 | FX96: 0 | FY96: 0 | FZ96: 0 | GA96: 0 | GB96: 0 | GC96: 0 | GD96: 0 | GE96: 0 | GF96: 0 | GG96: 0 | GH96: 0 | GI96: 0 | GJ96: 0 | GL96: 0 | GN96: 0 | GO96: 0 | GP96: 0 | GQ96: 0 | GR96: 0 | GS96: 0 | GT96: 0 | GU96: 0 | GV96: 0 | GW96: 0 | GX96: 0 | GY96: 0 | GZ96: 0 | HA96: 0 | HB96: 0 | HC96: 0 | HD96: 0 | HE96: 0 | HF96: 0 | HG96: 0 | HH96: 0 | HI96: 0 | HJ96: 0 | HK96: 0 | HL96: 0 | HM96: 0 | HN96: 0 | HO96: 0 | HP96: 0 | HW96: 17629.31 | HY96: 0 | HZ96: 0 | IA96: 0 | IB96: FALSE
A97: 014.199-00 | B97: 2022/0029312-001 | C97: FB | D97: 2022/0029312 | E97: CZZ1758 | F97: 01/04/2026 | G97: 30/04/2026 | H97: MARIO MORENO | I97: MARIO MORENO | J97: NORMAL | K97: EMEF | L97: 0 | M97: 0 | O97: 6020.2022/0029312-0 | P97: 0 | U97: =Q97+'APONTAMENTO CREDENCIAMENTO'!U97 -> 0 | V97: =R97+'APONTAMENTO CREDENCIAMENTO'!V97 -> 0 | W97: =S97+'APONTAMENTO CREDENCIAMENTO'!W97 -> 0 | X97: =T97+'APONTAMENTO CREDENCIAMENTO'!X97 -> 0 | Y97: =U97+'APONTAMENTO CREDENCIAMENTO'!Y97 -> 0 | Z97: =V97+'APONTAMENTO CREDENCIAMENTO'!Z97 -> 0 | AA97: =W97+'APONTAMENTO CREDENCIAMENTO'!AA97 -> 0 | AB97: =X97+'APONTAMENTO CREDENCIAMENTO'!AB97 -> 0 | ... EF97: =EB97+'APONTAMENTO CREDENCIAMENTO'!EF97 -> 0 | EP97: 0 | EQ97: 0 | ER97: 0 | ES97: 0 | ET97: 0 | EU97: 0 | EV97: 0 | EX97: 0 | EY97: 0 | EZ97: 0 | FA97: 0 | FB97: 0 | FC97: 0 | FD97: 0 | GL97: 0 | HY97: 0 | HZ97: 0 | IA97: 0
A98: 014.199-00 | B98: 2022/0029312-001 | C98: FB | D98: 2022/0029312 | E98: CZZ1758 | F98: 01/04/2026 | G98: 30/04/2026 | H98: MARIO MORENO | I98: MARIO MORENO | J98: NORMAL | K98: EMEE | L98: 0 | M98: 0 | O98: 6020.2022/0029312-0 | P98: 0 | U98: =Q98+'APONTAMENTO CREDENCIAMENTO'!U98 -> 0 | V98: =R98+'APONTAMENTO CREDENCIAMENTO'!V98 -> 0 | W98: =S98+'APONTAMENTO CREDENCIAMENTO'!W98 -> 0 | X98: =T98+'APONTAMENTO CREDENCIAMENTO'!X98 -> 0 | Y98: =U98+'APONTAMENTO CREDENCIAMENTO'!Y98 -> 0 | Z98: =V98+'APONTAMENTO CREDENCIAMENTO'!Z98 -> 0 | AA98: =W98+'APONTAMENTO CREDENCIAMENTO'!AA98 -> 0 | AB98: =X98+'APONTAMENTO CREDENCIAMENTO'!AB98 -> 0 | ... EF98: =EB98+'APONTAMENTO CREDENCIAMENTO'!EF98 -> 0 | EP98: 0 | EQ98: 0 | ER98: 0 | ES98: 0 | ET98: 0 | EU98: 0 | EV98: 0 | EX98: 0 | EY98: 0 | EZ98: 0 | FA98: 0 | FB98: 0 | FC98: 0 | FD98: 0 | GL98: 0 | HY98: 0 | HZ98: 0 | IA98: 0
A99: 014.199-00 | B99: 2022/0029312-001 | C99: FB | D99: 2022/0029312 | E99: CZZ1758 | F99: 01/04/2026 | G99: 30/04/2026 | H99: MARIO MORENO | I99: MARIO MORENO | J99: NORMAL | K99: CEI | L99: 0 | M99: 0 | O99: 6020.2022/0029312-0 | P99: 0 | U99: =Q99+'APONTAMENTO CREDENCIAMENTO'!U99 -> 0 | V99: =R99+'APONTAMENTO CREDENCIAMENTO'!V99 -> 0 | W99: =S99+'APONTAMENTO CREDENCIAMENTO'!W99 -> 0 | X99: =T99+'APONTAMENTO CREDENCIAMENTO'!X99 -> 0 | Y99: =U99+'APONTAMENTO CREDENCIAMENTO'!Y99 -> 0 | Z99: =V99+'APONTAMENTO CREDENCIAMENTO'!Z99 -> 0 | AA99: =W99+'APONTAMENTO CREDENCIAMENTO'!AA99 -> 0 | AB99: =X99+'APONTAMENTO CREDENCIAMENTO'!AB99 -> 0 | ... EF99: =EB99+'APONTAMENTO CREDENCIAMENTO'!EF99 -> 0 | EP99: 0 | EQ99: 0 | ER99: 0 | ES99: 0 | ET99: 0 | EU99: 0 | EV99: 0 | EX99: 0 | EY99: 0 | EZ99: 0 | FA99: 0 | FB99: 0 | FC99: 0 | FD99: 0 | GL99: 0 | HY99: 0 | HZ99: 0 | IA99: 0
A100: 014.199-00 | B100: 2022/0029312-001 | C100: FB | D100: 2022/0029312 | E100: CZZ1758 | F100: 01/04/2026 | G100: 30/04/2026 | H100: MARIO MORENO | I100: MARIO MORENO | J100: NORMAL | K100: CCA | L100: 0 | M100: 0 | O100: 6020.2022/0029312-0 | P100: 0 | U100: =Q100+'APONTAMENTO CREDENCIAMENTO'!U100 -> 0 | V100: =R100+'APONTAMENTO CREDENCIAMENTO'!V100 -> 0 | W100: =S100+'APONTAMENTO CREDENCIAMENTO'!W100 -> 0 | X100: =T100+'APONTAMENTO CREDENCIAMENTO'!X100 -> 0 | Y100: =U100+'APONTAMENTO CREDENCIAMENTO'!Y100 -> 0 | Z100: =V100+'APONTAMENTO CREDENCIAMENTO'!Z100 -> 0 | AA100: =W100+'APONTAMENTO CREDENCIAMENTO'!AA100 -> 0 | AB100: =X100+'APONTAMENTO CREDENCIAMENTO'!AB100 -> 0 | ... EF100: =EB100+'APONTAMENTO CREDENCIAMENTO'!EF100 -> 0 | EP100: 0 | EQ100: 0 | ER100: 0 | ES100: 0 | ET100: 0 | EU100: 0 | EV100: 0 | EX100: 0 | EY100: 0 | EZ100: 0 | FA100: 0 | FB100: 0 | FC100: 0 | FD100: 0 | FF100: 0 | FG100: 0 | FH100: 0 | FI100: 0 | FJ100: 0 | FK100: 0 | FL100: 0 | FM100: 0 | FN100: 0 | FO100: 0 | FP100: 0 | FQ100: 0 | FR100: 0 | FS100: 0 | FT100: 0 | FU100: 0 | FV100: 0 | FW100: 0 | FX100: 0 | FY100: 0 | FZ100: 0 | GA100: 0 | GB100: 0 | GC100: 0 | GD100: 0 | GE100: 0 | GF100: 0 | GG100: 0 | GH100: 0 | GI100: 0 | GJ100: 0 | GL100: 0 | HY100: 0 | HZ100: 0 | IA100: 0
...

Sheet APONTAMENTO CREDENCIAMENTO
A1: Freguesia / Brasilândia | G1: ='BASE C'!E4 -> ABRIL | I1: APONTAMENTO CREDENCIAMENTO | EL1: ATENÇÃO
G2: 01/06 a 30/06/2025
A3: 1 | B3: =A3+1 -> 2 | C3: =B3+1 -> 3 | D3: 1 | E3: =D3+1 -> 2 | F3: =E3+1 -> 3 | G3: =F3+1 -> 4 | H3: =G3+1 -> 5 | I3: =H3+1 -> 6 | J3: =I3+1 -> 7 | K3: =J3+1 -> 8 | L3: =K3+1 -> 9 | M3: =L3+1 -> 10 | N3: 10 | O3: =N3+1 -> 11 | P3: 13 | Q3: =P3+1 -> 14 | R3: =Q3+1 -> 15 | S3: =R3+1 -> 16 | T3: =S3+1 -> 17 | U3: =T3+1 -> 18 | V3: =U3+1 -> 19 | W3: =V3+1 -> 20 | X3: =W3+1 -> 21 | ... EL3: =EK3+1 -> 139 | EM3: 140 | EN3: =EM3+1 -> 141 | EO3: =EN3+1 -> 142 | EP3: =EO3+1 -> 143 | EQ3: =EP3+1 -> 144 | ER3: =EQ3+1 -> 145 | ES3: =ER3+1 -> 146 | ET3: =ES3+1 -> 147 | EU3: =ET3+1 -> 148 | ... IA3: =HZ3+1 -> 232
A4: CRMC | B4: OS | C4: DRE | D4: CONTRATO | E4: PLACA | F4: PERÍODO | H4: EMPRESA | I4: NOME CONDUTOR | J4: TIPO DE VEÍCULO (NORMAL, ADAPTADO) | K4: TIPO DE ATENDIMENTO | L4: TOTAL CONT REG | M4: TOTAL CONT CAD | N4: KM ADICIONAL | O4: SEI | P4: Tipo Optante | Q4: =F5 -> 01/04/2026 | U4: =Q4+1 -> 46114 | Y4: =U4+1 -> 46115 | AC4: =Y4+1 -> 46116 | AG4: =AC4+1 -> 46117 | AK4: =AG4+1 -> 46118 | AO4: =AK4+1 -> 46119 | AS4: =AO4+1 -> 46120 | AW4: =AS4+1 -> 46121 | BA4: =AW4+1 -> 46122 | BE4: =BA4+1 -> 46123 | BI4: =BE4+1 -> 46124 | BM4: =BI4+1 -> 46125 | BQ4: =BM4+1 -> 46126 | BU4: =BQ4+1 -> 46127 | BY4: =BU4+1 -> 46128 | CC4: =BY4+1 -> 46129 | CG4: =CC4+1 -> 46130 | CK4: =CG4+1 -> 46131 | CO4: =CK4+1 -> 46132 | CS4: =CO4+1 -> 46133 | CW4: =CS4+1 -> 46134 | DA4: =CW4+1 -> 46135 | DE4: =DA4+1 -> 46136 | DI4: =DE4+1 -> 46137 | DM4: =DI4+1 -> 46138 | DQ4: =DM4+1 -> 46139 | DU4: =DQ4+1 -> 46140 | DY4: =DU4+1 -> 46141 | EC4: =DY4+1 -> 46142 | EK4: FALTAS - APONTAR AS DATAS | EL4: OBSERVAÇÕES ALUNO PRESENCIAL COLUNAS FINAIS | EM4: Ajuste positivo | EN4: Ajuste negativo | EO4: Desconto faltas | EP4: TOTAL ALUNOS N CAD(30 DIAS) | EQ4: TOTAL ALUNOS N CAD(MENOS DE 30 DIAS) | ER4: TOTAL ALUNOS ATIV.COMPL. N CAD | ES4: TOTAL ALUNOS CAD (30 DIAS) | ET4: TOTAL ALUNOS CAD (MENOS DE 30 DIAS) | EU4: TOTAL ALUNOS ATIV.COMPL. CAD | EV4: TOTAL GERAL | EW4: Contratos Especiais (Valor fixo) | EX4: Valor total alunos presenciais (30 dias) | EY4: Ativ.Complementar Continuada | EZ4: Valor alunos presenciais (menos de 30 dias) | FA4: Saida de alunos ao longo do mês | FB4: CCA | FC4: Valor km adicional | FD4: Outros apontamentos | FE4: VALOR ATESTE | FF4: 30 | FG4: =FF4-1 -> 29 | FH4: =FG4-1 -> 28 | FI4: =FH4-1 -> 27 | FJ4: =FI4-1 -> 26 | FK4: =FJ4-1 -> 25 | FL4: =FK4-1 -> 24 | FM4: =FL4-1 -> 23 | FN4: =FM4-1 -> 22 | ... GI4: =GH4-1 -> 1 | GJ4: 1 | GK4: Multa Contratual | GL4: CÁLCULO | GM4: DIAS | GN4: 29 | GO4: =GN4-1 -> 28 | GP4: =GO4-1 -> 27 | GQ4: =GP4-1 -> 26 | GR4: =GQ4-1 -> 25 | GS4: =GR4-1 -> 24 | GT4: =GS4-1 -> 23 | GU4: =GT4-1 -> 22 | GV4: =GU4-1 -> 21 | ... HP4: =HO4-1 -> 1 | HW4: VALOR ATESTE | HY4: Ajuste positivo | HZ4: Ajuste negativo | IA4: Desconto faltas
F5: 01/04/2026 | G5: 30/04/2026 | Q5: N CAD presencial | R5: CAD | S5: AT. COMPL. N CAD | T5: AT. COMPL. CAD | U5: N CAD presencial | V5: CAD | W5: AT. COMPL. N CAD | X5: AT. COMPL. CAD | Y5: N CAD presencial | Z5: CAD | AA5: AT. COMPL. N CAD | AB5: AT. COMPL. CAD | AC5: N CAD presencial | AD5: CAD | AE5: AT. COMPL. N CAD | AF5: AT. COMPL. CAD | AG5: N CAD presencial | AH5: CAD | AI5: AT. COMPL. N CAD | AJ5: AT. COMPL. CAD | AK5: N CAD presencial | AL5: CAD | AM5: AT. COMPL. N CAD | AN5: AT. COMPL. CAD | AO5: N CAD presencial | AP5: CAD | AQ5: AT. COMPL. N CAD | AR5: AT. COMPL. CAD | AS5: N CAD presencial | AT5: CAD | AU5: AT. COMPL. N CAD | AV5: AT. COMPL. CAD | AW5: N CAD presencial | AX5: CAD | AY5: AT. COMPL. N CAD | AZ5: AT. COMPL. CAD | BA5: N CAD presencial | BB5: CAD | BC5: AT. COMPL. N CAD | BD5: AT. COMPL. CAD | BE5: N CAD presencial | BF5: CAD | BG5: AT. COMPL. N CAD | BH5: AT. COMPL. CAD | BI5: N CAD presencial | BJ5: CAD | BK5: AT. COMPL. N CAD | BL5: AT. COMPL. CAD | BM5: N CAD presencial | BN5: CAD | BO5: AT. COMPL. N CAD | BP5: AT. COMPL. CAD | BQ5: N CAD presencial | BR5: CAD | BS5: AT. COMPL. N CAD | BT5: AT. COMPL. CAD | BU5: N CAD presencial | BV5: CAD | BW5: AT. COMPL. N CAD | BX5: AT. COMPL. CAD | BY5: N CAD presencial | BZ5: CAD | CA5: AT. COMPL. N CAD | CB5: AT. COMPL. CAD | CC5: N CAD presencial | CD5: CAD | CE5: AT. COMPL. N CAD | CF5: AT. COMPL. CAD | CG5: N CAD presencial | CH5: CAD | CI5: AT. COMPL. N CAD | CJ5: AT. COMPL. CAD | CK5: N CAD presencial | CL5: CAD | CM5: AT. COMPL. N CAD | CN5: AT. COMPL. CAD | CO5: N CAD presencial | CP5: CAD | CQ5: AT. COMPL. N CAD | CR5: AT. COMPL. CAD | CS5: N CAD presencial | CT5: CAD | CU5: AT. COMPL. N CAD | CV5: AT. COMPL. CAD | CW5: N CAD presencial | CX5: CAD | CY5: AT. COMPL. N CAD | CZ5: AT. COMPL. CAD | DA5: N CAD presencial | DB5: CAD | DC5: AT. COMPL. N CAD | DD5: AT. COMPL. CAD | DE5: N CAD presencial | DF5: CAD | DG5: AT. COMPL. N CAD | DH5: AT. COMPL. CAD | DI5: N CAD presencial | DJ5: CAD | DK5: AT. COMPL. N CAD | DL5: AT. COMPL. CAD | DM5: N CAD presencial | DN5: CAD | DO5: AT. COMPL. N CAD | DP5: AT. COMPL. CAD | DQ5: N CAD presencial | DR5: CAD | DS5: AT. COMPL. N CAD | DT5: AT. COMPL. CAD | DU5: N CAD presencial | DV5: CAD | DW5: AT. COMPL. N CAD | DX5: AT. COMPL. CAD | DY5: N CAD presencial | DZ5: CAD | EA5: AT. COMPL. N CAD | EB5: AT. COMPL. CAD | EC5: N CAD presencial | ED5: CAD | EE5: AT. COMPL. N CAD | EF5: AT. COMPL. CAD | EG5: N CAD presencial | EH5: CAD | EI5: AT. COMPL. N CAD | EJ5: AT. COMPL. CAD
A6: 020.708-00 | B6: 2022/0026670-001 | C6: 1 | D6: 2022/0026670 | E6: DJE9491 | F6: 01/04/2026 | G6: 30/04/2026 | H6: ADILSON TOLEDO | I6: ADILSON TOLEDO | J6: NORMAL | K6: EMEI | L6: =CONTINUA!BV6 -> 0 | M6: =CONTINUA!BW6 -> 0 | O6: 6020.2022/0026670-0 | P6: 0 | EP6: =Q6 -> 0 | EQ6: =U6+Y6+AC6+AG6+AK6+AO6+AS6+AW6+BA6+BE6+BI6+BM6+BQ6+BU6+BY6+CC6+CG6+CK6+CO6+CS6+CW6+DA6+DE6+DI6+DM6+DQ6+DU6+DY6+EC6+EG6 -> 0 | ER6: =S6+W6+AA6+AE6+AI6+AM6+AQ6+AU6+AY6+BC6+BG6+BK6+BO6+BS6+BW6+CA6+CE6+CI6+CM6+CQ6+CU6+CY6+DC6+DG6+DK6+DO6+DS6+DW6+EA6+EE6+EI6 -> 0 | ES6: =R6 -> 0 | ET6: =V6+Z6+AD6+AH6+AL6+AP6+AT6+AX6+BB6+BF6+BJ6+BN6+BR6+BV6+BZ6+CD6+CH6+CL6+CP6+CT6+CX6+DB6+DF6+DJ6+DN6+DR6+DV6+DZ6+ED6+EH6 -> 0 | EU6: =T6+X6+AB6+AF6+AJ6+AN6+AR6+AV6+AZ6+BD6+BH6+BL6+BP6+BT6+BX6+CB6+CF6+CJ6+CN6+CR6+CV6+CZ6+DD6+DH6+DL6+DP6+DT6+DX6+EB6+EF6+EJ6 -> 0 | EV6: =EP6+EQ6+ES6+ET6+ER6+EU6 -> 0 | EW6: =IF(C6=4,IF(MAX(Q6:EJ8)>0,(Especiall/30*(IF(($G6-$F6)=($G$5-$F$5),30,IF(DAY($G6)=31,($G6-$F6),($G6-$F6)+1)))),0),0) -> 0 | EX6: =FF6 -> 24057.41 | EY6: =(L6*regular)+(M6*Cadeirantee) -> 0 | EZ6: =SUMIF(FG6:GJ6,">0") -> 0 | FA6: =SUMIF(FG6:GJ6,"<0")+SUMIF(GN6:HP6,"<0") -> 0 | FB6: 0 | FC6: =N6*km*'VALORES TABELA'!$B$13 -> 0 | FD6: =GL6 -> 0 | FE6: =(EW6+EW7+EW8+EW9+EX6+EX7+EX8+EX9+EY6+EY7+EY8+EY9+EY10+EZ6+EZ7+EZ8+EZ9+FA6+FA7+FA8+FA9+FC6+FC7+FC8+FC9+HY6-HZ6-IA6+FD6+FD7+FD8+FD9+FB10) -> 24057.41 | FF6: =IF(C6=4,SUM(Q6+Q7+Q8+S6+S7+S8)*Percapita/30*FF$4+(R6+R7+R8+T6+T7+T8)*Cadeirante/30*FF$4,IF(C6=3,IF(Q9+S9=10,Fixo/30*FF$4+(Q6+Q7+Q8+S6+S7+S8)*Percapita/30*FF$4+(R9+T9)*Cadeirante/30*FF$4,IF(Q9+S9<=9,(Q9+S9)*Crechee/30*FF$4)+(R9+T9)*Cadeirante/30*FF$4+(Q6+Q7+Q8+S6+S7+S8)*Percapita/30*FF$4)+IF(Q9+S9>=11,Fixo/30*FF$4+(Q9+S9-10)*Crechee/30*FF$4,0),IF(C6=2,IF(R6+R7+R8+R9+T6+T7+T8+T9=1,Cadeirante/30*FF$4,IF(R6+R7+R8+R9+T6+T7+T8+T9=2,Fixo/30*FF$4,IF(R6+R7+R8+R9+T6+T7+T8+T9>2,Fixo/30*FF$4+(R6+R7+R8+R9+T6+T7+T8+T9-2)*Cadeirante/30*FF$4)))+(Q6+Q7+Q8+S6+S7+S8)*Percapita/30*FF$4+(Q9+S9)*Crechee/30*FF$4,IF(C6=1,IF(Q6+Q7+Q8+R6+R7+R8+S6+S7+S8+T6+T7+T8<=15,(Q6+Q7+Q8+S6+S7+S8)*Percapita/30*FF$4,IF(Q6+Q7+Q8+R6+R7+R8+S6+S7+S8+T6+T7+T8>=16,Fixo/30*FF$4+(Q6+Q7+Q8+R6+R7+R8+S6+S7+S8+T6+T7-16)*Percapita/30*FF$4)))))) -> 24057.41 | FG6: =IF(C6=4,SUM(U6+U7+U8+W6+W7+W8)*Percapita/30*FG$4+(V6+V7+V8+X6+X7+X8)*Cadeirante/30*FG$4,IF(C6=3,IF(U9+W9=10,Fixo/30*FG$4+(U6+U7+U8+W6+W7+W8)*Percapita/30*FG$4+(V9+X9)*Cadeirante/30*FG$4,IF(U9+W9<=9,(U9+W9)*Crechee/30*FG$4)+(V9+X9)*Cadeirante/30*FG$4+(U6+U7+U8+W6+W7+W8)*Percapita/30*FG$4)+IF(U9+W9>=11,Fixo/30*FG$4+(U9+W9-10)*Crechee/30*FG$4,0),IF(C6=2,IF(V6+V7+V8+V9+X6+X7+X8+X9=1,Cadeirante/30*FG$4,IF(V6+V7+V8+V9+X6+X7+X8+X9=2,Fixo/30*FG$4,IF(V6+V7+V8+V9+X6+X7+X8+X9>2,Fixo/30*FG$4+(V6+V7+V8+V9+X6+X7+X8+X9-2)*Cadeirante/30*FG$4)))+(U6+U7+U8+W6+W7+W8)*Percapita/30*FG$4+(U9+W9)*Crechee/30*FG$4,IF(C6=1,IF(U6+U7+U8+V6+V7+V8+W6+W7+W8+X6+X7+X8<=15,(U6+U7+U8+W6+W7+W8)*Percapita/30*FG$4,IF(U6+U7+U8+V6+V7+V8+W6+W7+W8+X6+X7+X8>=16,Fixo/30*FG$4+(U6+U7+U8+V6+V7+V8+W6+W7+W8+X6+X7-16)*Percapita/30*FG$4)))))) -> 0 | FH6: =IF(C6=4,SUM(Y6+Y7+Y8+AA6+AA7+AA8)*Percapita/30*FH$4+(Z6+Z7+Z8+AB6+AB7+AB8)*Cadeirante/30*FH$4,IF(C6=3,IF(Y9+AA9=10,Fixo/30*FH$4+(Y6+Y7+Y8+AA6+AA7+AA8)*Percapita/30*FH$4+(Z9+AB9)*Cadeirante/30*FH$4,IF(Y9+AA9<=9,(Y9+AA9)*Crechee/30*FH$4)+(Z9+AB9)*Cadeirante/30*FH$4+(Y6+Y7+Y8+AA6+AA7+AA8)*Percapita/30*FH$4)+IF(Y9+AA9>=11,Fixo/30*FH$4+(Y9+AA9-10)*Crechee/30*FH$4,0),IF(C6=2,IF(Z6+Z7+Z8+Z9+AB6+AB7+AB8+AB9=1,Cadeirante/30*FH$4,IF(Z6+Z7+Z8+Z9+AB6+AB7+AB8+AB9=2,Fixo/30*FH$4,IF(Z6+Z7+Z8+Z9+AB6+AB7+AB8+AB9>2,Fixo/30*FH$4+(Z6+Z7+Z8+Z9+AB6+AB7+AB8+AB9-2)*Cadeirante/30*FH$4)))+(Y6+Y7+Y8+AA6+AA7+AA8)*Percapita/30*FH$4+(Y9+AA9)*Crechee/30*FH$4,IF(C6=1,IF(Y6+Y7+Y8+Z6+Z7+Z8+AA6+AA7+AA8+AB6+AB7+AB8<=15,(Y6+Y7+Y8+AA6+AA7+AA8)*Percapita/30*FH$4,IF(Y6+Y7+Y8+Z6+Z7+Z8+AA6+AA7+AA8+AB6+AB7+AB8>=16,Fixo/30*FH$4+(Y6+Y7+Y8+Z6+Z7+Z8+AA6+AA7+AA8+AB6+AB7-16)*Percapita/30*FH$4)))))) -> 0 | FI6: =IF(C6=4,SUM(AC6+AC7+AC8+AE6+AE7+AE8)*Percapita/30*FI$4+(AD6+AD7+AD8+AF6+AF7+AF8)*Cadeirante/30*FI$4,IF(C6=3,IF(AC9+AE9=10,Fixo/30*FI$4+(AC6+AC7+AC8+AE6+AE7+AE8)*Percapita/30*FI$4+(AD9+AF9)*Cadeirante/30*FI$4,IF(AC9+AE9<=9,(AC9+AE9)*Crechee/30*FI$4)+(AD9+AF9)*Cadeirante/30*FI$4+(AC6+AC7+AC8+AE6+AE7+AE8)*Percapita/30*FI$4)+IF(AC9+AE9>=11,Fixo/30*FI$4+(AC9+AE9-10)*Crechee/30*FI$4,0),IF(C6=2,IF(AD6+AD7+AD8+AD9+AF6+AF7+AF8+AF9=1,Cadeirante/30*FI$4,IF(AD6+AD7+AD8+AD9+AF6+AF7+AF8+AF9=2,Fixo/30*FI$4,IF(AD6+AD7+AD8+AD9+AF6+AF7+AF8+AF9>2,Fixo/30*FI$4+(AD6+AD7+AD8+AD9+AF6+AF7+AF8+AF9-2)*Cadeirante/30*FI$4)))+(AC6+AC7+AC8+AE6+AE7+AE8)*Percapita/30*FI$4+(AC9+AE9)*Crechee/30*FI$4,IF(C6=1,IF(AC6+AC7+AC8+AD6+AD7+AD8+AE6+AE7+AE8+AF6+AF7+AF8<=15,(AC6+AC7+AC8+AE6+AE7+AE8)*Percapita/30*FI$4,IF(AC6+AC7+AC8+AD6+AD7+AD8+AE6+AE7+AE8+AF6+AF7+AF8>=16,Fixo/30*FI$4+(AC6+AC7+AC8+AD6+AD7+AD8+AE6+AE7+AE8+AF6+AF7-16)*Percapita/30*FI$4)))))) -> 0 | FJ6: =IF(C6=4,SUM(AG6+AG7+AG8+AI6+AI7+AI8)*Percapita/30*FJ$4+(AH6+AH7+AH8+AJ6+AJ7+AJ8)*Cadeirante/30*FJ$4,IF(C6=3,IF(AG9+AI9=10,Fixo/30*FJ$4+(AG6+AG7+AG8+AI6+AI7+AI8)*Percapita/30*FJ$4+(AH9+AJ9)*Cadeirante/30*FJ$4,IF(AG9+AI9<=9,(AG9+AI9)*Crechee/30*FJ$4)+(AH9+AJ9)*Cadeirante/30*FJ$4+(AG6+AG7+AG8+AI6+AI7+AI8)*Percapita/30*FJ$4)+IF(AG9+AI9>=11,Fixo/30*FJ$4+(AG9+AI9-10)*Crechee/30*FJ$4,0),IF(C6=2,IF(AH6+AH7+AH8+AH9+AJ6+AJ7+AJ8+AJ9=1,Cadeirante/30*FJ$4,IF(AH6+AH7+AH8+AH9+AJ6+AJ7+AJ8+AJ9=2,Fixo/30*FJ$4,IF(AH6+AH7+AH8+AH9+AJ6+AJ7+AJ8+AJ9>2,Fixo/30*FJ$4+(AH6+AH7+AH8+AH9+AJ6+AJ7+AJ8+AJ9-2)*Cadeirante/30*FJ$4)))+(AG6+AG7+AG8+AI6+AI7+AI8)*Percapita/30*FJ$4+(AG9+AI9)*Crechee/30*FJ$4,IF(C6=1,IF(AG6+AG7+AG8+AH6+AH7+AH8+AI6+AI7+AI8+AJ6+AJ7+AJ8<=15,(AG6+AG7+AG8+AI6+AI7+AI8)*Percapita/30*FJ$4,IF(AG6+AG7+AG8+AH6+AH7+AH8+AI6+AI7+AI8+AJ6+AJ7+AJ8>=16,Fixo/30*FJ$4+(AG6+AG7+AG8+AH6+AH7+AH8+AI6+AI7+AI8+AJ6+AJ7-16)*Percapita/30*FJ$4)))))) -> 0 | FK6: =IF(C6=4,SUM(AK6+AK7+AK8+AM6+AM7+AM8)*Percapita/30*FK$4+(AL6+AL7+AL8+AN6+AN7+AN8)*Cadeirante/30*FK$4,IF(C6=3,IF(AK9+AM9=10,Fixo/30*FK$4+(AK6+AK7+AK8+AM6+AM7+AM8)*Percapita/30*FK$4+(AL9+AN9)*Cadeirante/30*FK$4,IF(AK9+AM9<=9,(AK9+AM9)*Crechee/30*FK$4)+(AL9+AN9)*Cadeirante/30*FK$4+(AK6+AK7+AK8+AM6+AM7+AM8)*Percapita/30*FK$4)+IF(AK9+AM9>=11,Fixo/30*FK$4+(AK9+AM9-10)*Crechee/30*FK$4,0),IF(C6=2,IF(AL6+AL7+AL8+AL9+AN6+AN7+AN8+AN9=1,Cadeirante/30*FK$4,IF(AL6+AL7+AL8+AL9+AN6+AN7+AN8+AN9=2,Fixo/30*FK$4,IF(AL6+AL7+AL8+AL9+AN6+AN7+AN8+AN9>2,Fixo/30*FK$4+(AL6+AL7+AL8+AL9+AN6+AN7+AN8+AN9-2)*Cadeirante/30*FK$4)))+(AK6+AK7+AK8+AM6+AM7+AM8)*Percapita/30*FK$4+(AK9+AM9)*Crechee/30*FK$4,IF(C6=1,IF(AK6+AK7+AK8+AL6+AL7+AL8+AM6+AM7+AM8+AN6+AN7+AN8<=15,(AK6+AK7+AK8+AM6+AM7+AM8)*Percapita/30*FK$4,IF(AK6+AK7+AK8+AL6+AL7+AL8+AM6+AM7+AM8+AN6+AN7+AN8>=16,Fixo/30*FK$4+(AK6+AK7+AK8+AL6+AL7+AL8+AM6+AM7+AM8+AN6+AN7-16)*Percapita/30*FK$4)))))) -> 0 | FL6: =IF(C6=4,SUM(AO6+AO7+AO8+AQ6+AQ7+AQ8)*Percapita/30*FL$4+(AP6+AP7+AP8+AR6+AR7+AR8)*Cadeirante/30*FL$4,IF(C6=3,IF(AO9+AQ9=10,Fixo/30*FL$4+(AO6+AO7+AO8+AQ6+AQ7+AQ8)*Percapita/30*FL$4+(AP9+AR9)*Cadeirante/30*FL$4,IF(AO9+AQ9<=9,(AO9+AQ9)*Crechee/30*FL$4)+(AP9+AR9)*Cadeirante/30*FL$4+(AO6+AO7+AO8+AQ6+AQ7+AQ8)*Percapita/30*FL$4)+IF(AO9+AQ9>=11,Fixo/30*FL$4+(AO9+AQ9-10)*Crechee/30*FL$4,0),IF(C6=2,IF(AP6+AP7+AP8+AP9+AR6+AR7+AR8+AR9=1,Cadeirante/30*FL$4,IF(AP6+AP7+AP8+AP9+AR6+AR7+AR8+AR9=2,Fixo/30*FL$4,IF(AP6+AP7+AP8+AP9+AR6+AR7+AR8+AR9>2,Fixo/30*FL$4+(AP6+AP7+AP8+AP9+AR6+AR7+AR8+AR9-2)*Cadeirante/30*FL$4)))+(AO6+AO7+AO8+AQ6+AQ7+AQ8)*Percapita/30*FL$4+(AO9+AQ9)*Crechee/30*FL$4,IF(C6=1,IF(AO6+AO7+AO8+AP6+AP7+AP8+AQ6+AQ7+AQ8+AR6+AR7+AR8<=15,(AO6+AO7+AO8+AQ6+AQ7+AQ8)*Percapita/30*FL$4,IF(AO6+AO7+AO8+AP6+AP7+AP8+AQ6+AQ7+AQ8+AR6+AR7+AR8>=16,Fixo/30*FL$4+(AO6+AO7+AO8+AP6+AP7+AP8+AQ6+AQ7+AQ8+AR6+AR7-16)*Percapita/30*FL$4)))))) -> 0 | FM6: =IF(C6=4,SUM(AS6+AS7+AS8+AU6+AU7+AU8)*Percapita/30*FM$4+(AT6+AT7+AT8+AV6+AV7+AV8)*Cadeirante/30*FM$4,IF(C6=3,IF(AS9+AU9=10,Fixo/30*FM$4+(AS6+AS7+AS8+AU6+AU7+AU8)*Percapita/30*FM$4+(AT9+AV9)*Cadeirante/30*FM$4,IF(AS9+AU9<=9,(AS9+AU9)*Crechee/30*FM$4)+(AT9+AV9)*Cadeirante/30*FM$4+(AS6+AS7+AS8+AU6+AU7+AU8)*Percapita/30*FM$4)+IF(AS9+AU9>=11,Fixo/30*FM$4+(AS9+AU9-10)*Crechee/30*FM$4,0),IF(C6=2,IF(AT6+AT7+AT8+AT9+AV6+AV7+AV8+AV9=1,Cadeirante/30*FM$4,IF(AT6+AT7+AT8+AT9+AV6+AV7+AV8+AV9=2,Fixo/30*FM$4,IF(AT6+AT7+AT8+AT9+AV6+AV7+AV8+AV9>2,Fixo/30*FM$4+(AT6+AT7+AT8+AT9+AV6+AV7+AV8+AV9-2)*Cadeirante/30*FM$4)))+(AS6+AS7+AS8+AU6+AU7+AU8)*Percapita/30*FM$4+(AS9+AU9)*Crechee/30*FM$4,IF(C6=1,IF(AS6+AS7+AS8+AT6+AT7+AT8+AU6+AU7+AU8+AV6+AV7+AV8<=15,(AS6+AS7+AS8+AU6+AU7+AU8)*Percapita/30*FM$4,IF(AS6+AS7+AS8+AT6+AT7+AT8+AU6+AU7+AU8+AV6+AV7+AV8>=16,Fixo/30*FM$4+(AS6+AS7+AS8+AT6+AT7+AT8+AU6+AU7+AU8+AV6+AV7-16)*Percapita/30*FM$4)))))) -> 0 | FN6: =IF(C6=4,SUM(AW6+AW7+AW8+AY6+AY7+AY8)*Percapita/30*FN$4+(AX6+AX7+AX8+AZ6+AZ7+AZ8)*Cadeirante/30*FN$4,IF(C6=3,IF(AW9+AY9=10,Fixo/30*FN$4+(AW6+AW7+AW8+AY6+AY7+AY8)*Percapita/30*FN$4+(AX9+AZ9)*Cadeirante/30*FN$4,IF(AW9+AY9<=9,(AW9+AY9)*Crechee/30*FN$4)+(AX9+AZ9)*Cadeirante/30*FN$4+(AW6+AW7+AW8+AY6+AY7+AY8)*Percapita/30*FN$4)+IF(AW9+AY9>=11,Fixo/30*FN$4+(AW9+AY9-10)*Crechee/30*FN$4,0),IF(C6=2,IF(AX6+AX7+AX8+AX9+AZ6+AZ7+AZ8+AZ9=1,Cadeirante/30*FN$4,IF(AX6+AX7+AX8+AX9+AZ6+AZ7+AZ8+AZ9=2,Fixo/30*FN$4,IF(AX6+AX7+AX8+AX9+AZ6+AZ7+AZ8+AZ9>2,Fixo/30*FN$4+(AX6+AX7+AX8+AX9+AZ6+AZ7+AZ8+AZ9-2)*Cadeirante/30*FN$4)))+(AW6+AW7+AW8+AY6+AY7+AY8)*Percapita/30*FN$4+(AW9+AY9)*Crechee/30*FN$4,IF(C6=1,IF(AW6+AW7+AW8+AX6+AX7+AX8+AY6+AY7+AY8+AZ6+AZ7+AZ8<=15,(AW6+AW7+AW8+AY6+AY7+AY8)*Percapita/30*FN$4,IF(AW6+AW7+AW8+AX6+AX7+AX8+AY6+AY7+AY8+AZ6+AZ7+AZ8>=16,Fixo/30*FN$4+(AW6+AW7+AW8+AX6+AX7+AX8+AY6+AY7+AY8+AZ6+AZ7-16)*Percapita/30*FN$4)))))) -> 0 | FO6: =IF(C6=4,SUM(BA6+BA7+BA8+BC6+BC7+BC8)*Percapita/30*FO$4+(BB6+BB7+BB8+BD6+BD7+BD8)*Cadeirante/30*FO$4,IF(C6=3,IF(BA9+BC9=10,Fixo/30*FO$4+(BA6+BA7+BA8+BC6+BC7+BC8)*Percapita/30*FO$4+(BB9+BD9)*Cadeirante/30*FO$4,IF(BA9+BC9<=9,(BA9+BC9)*Crechee/30*FO$4)+(BB9+BD9)*Cadeirante/30*FO$4+(BA6+BA7+BA8+BC6+BC7+BC8)*Percapita/30*FO$4)+IF(BA9+BC9>=11,Fixo/30*FO$4+(BA9+BC9-10)*Crechee/30*FO$4,0),IF(C6=2,IF(BB6+BB7+BB8+BB9+BD6+BD7+BD8+BD9=1,Cadeirante/30*FO$4,IF(BB6+BB7+BB8+BB9+BD6+BD7+BD8+BD9=2,Fixo/30*FO$4,IF(BB6+BB7+BB8+BB9+BD6+BD7+BD8+BD9>2,Fixo/30*FO$4+(BB6+BB7+BB8+BB9+BD6+BD7+BD8+BD9-2)*Cadeirante/30*FO$4)))+(BA6+BA7+BA8+BC6+BC7+BC8)*Percapita/30*FO$4+(BA9+BC9)*Crechee/30*FO$4,IF(C6=1,IF(BA6+BA7+BA8+BB6+BB7+BB8+BC6+BC7+BC8+BD6+BD7+BD8<=15,(BA6+BA7+BA8+BC6+BC7+BC8)*Percapita/30*FO$4,IF(BA6+BA7+BA8+BB6+BB7+BB8+BC6+BC7+BC8+BD6+BD7+BD8>=16,Fixo/30*FO$4+(BA6+BA7+BA8+BB6+BB7+BB8+BC6+BC7+BC8+BD6+BD7-16)*Percapita/30*FO$4)))))) -> 0 | FP6: =IF(C6=4,SUM(BE6+BE7+BE8+BG6+BG7+BG8)*Percapita/30*FP$4+(BF6+BF7+BF8+BH6+BH7+BH8)*Cadeirante/30*FP$4,IF(C6=3,IF(BE9+BG9=10,Fixo/30*FP$4+(BE6+BE7+BE8+BG6+BG7+BG8)*Percapita/30*FP$4+(BF9+BH9)*Cadeirante/30*FP$4,IF(BE9+BG9<=9,(BE9+BG9)*Crechee/30*FP$4)+(BF9+BH9)*Cadeirante/30*FP$4+(BE6+BE7+BE8+BG6+BG7+BG8)*Percapita/30*FP$4)+IF(BE9+BG9>=11,Fixo/30*FP$4+(BE9+BG9-10)*Crechee/30*FP$4,0),IF(C6=2,IF(BF6+BF7+BF8+BF9+BH6+BH7+BH8+BH9=1,Cadeirante/30*FP$4,IF(BF6+BF7+BF8+BF9+BH6+BH7+BH8+BH9=2,Fixo/30*FP$4,IF(BF6+BF7+BF8+BF9+BH6+BH7+BH8+BH9>2,Fixo/30*FP$4+(BF6+BF7+BF8+BF9+BH6+BH7+BH8+BH9-2)*Cadeirante/30*FP$4)))+(BE6+BE7+BE8+BG6+BG7+BG8)*Percapita/30*FP$4+(BE9+BG9)*Crechee/30*FP$4,IF(C6=1,IF(BE6+BE7+BE8+BF6+BF7+BF8+BG6+BG7+BG8+BH6+BH7+BH8<=15,(BE6+BE7+BE8+BG6+BG7+BG8)*Percapita/30*FP$4,IF(BE6+BE7+BE8+BF6+BF7+BF8+BG6+BG7+BG8+BH6+BH7+BH8>=16,Fixo/30*FP$4+(BE6+BE7+BE8+BF6+BF7+BF8+BG6+BG7+BG8+BH6+BH7-16)*Percapita/30*FP$4)))))) -> 0 | FQ6: =IF(C6=4,SUM(BI6+BI7+BI8+BK6+BK7+BK8)*Percapita/30*FQ$4+(BJ6+BJ7+BJ8+BL6+BL7+BL8)*Cadeirante/30*FQ$4,IF(C6=3,IF(BI9+BK9=10,Fixo/30*FQ$4+(BI6+BI7+BI8+BK6+BK7+BK8)*Percapita/30*FQ$4+(BJ9+BL9)*Cadeirante/30*FQ$4,IF(BI9+BK9<=9,(BI9+BK9)*Crechee/30*FQ$4)+(BJ9+BL9)*Cadeirante/30*FQ$4+(BI6+BI7+BI8+BK6+BK7+BK8)*Percapita/30*FQ$4)+IF(BI9+BK9>=11,Fixo/30*FQ$4+(BI9+BK9-10)*Crechee/30*FQ$4,0),IF(C6=2,IF(BJ6+BJ7+BJ8+BJ9+BL6+BL7+BL8+BL9=1,Cadeirante/30*FQ$4,IF(BJ6+BJ7+BJ8+BJ9+BL6+BL7+BL8+BL9=2,Fixo/30*FQ$4,IF(BJ6+BJ7+BJ8+BJ9+BL6+BL7+BL8+BL9>2,Fixo/30*FQ$4+(BJ6+BJ7+BJ8+BJ9+BL6+BL7+BL8+BL9-2)*Cadeirante/30*FQ$4)))+(BI6+BI7+BI8+BK6+BK7+BK8)*Percapita/30*FQ$4+(BI9+BK9)*Crechee/30*FQ$4,IF(C6=1,IF(BI6+BI7+BI8+BJ6+BJ7+BJ8+BK6+BK7+BK8+BL6+BL7+BL8<=15,(BI6+BI7+BI8+BK6+BK7+BK8)*Percapita/30*FQ$4,IF(BI6+BI7+BI8+BJ6+BJ7+BJ8+BK6+BK7+BK8+BL6+BL7+BL8>=16,Fixo/30*FQ$4+(BI6+BI7+BI8+BJ6+BJ7+BJ8+BK6+BK7+BK8+BL6+BL7-16)*Percapita/30*FQ$4)))))) -> 0 | FR6: =IF(C6=4,SUM(BM6+BM7+BM8+BO6+BO7+BO8)*Percapita/30*FR$4+(BN6+BN7+BN8+BP6+BP7+BP8)*Cadeirante/30*FR$4,IF(C6=3,IF(BM9+BO9=10,Fixo/30*FR$4+(BM6+BM7+BM8+BO6+BO7+BO8)*Percapita/30*FR$4+(BN9+BP9)*Cadeirante/30*FR$4,IF(BM9+BO9<=9,(BM9+BO9)*Crechee/30*FR$4)+(BN9+BP9)*Cadeirante/30*FR$4+(BM6+BM7+BM8+BO6+BO7+BO8)*Percapita/30*FR$4)+IF(BM9+BO9>=11,Fixo/30*FR$4+(BM9+BO9-10)*Crechee/30*FR$4,0),IF(C6=2,IF(BN6+BN7+BN8+BN9+BP6+BP7+BP8+BP9=1,Cadeirante/30*FR$4,IF(BN6+BN7+BN8+BN9+BP6+BP7+BP8+BP9=2,Fixo/30*FR$4,IF(BN6+BN7+BN8+BN9+BP6+BP7+BP8+BP9>2,Fixo/30*FR$4+(BN6+BN7+BN8+BN9+BP6+BP7+BP8+BP9-2)*Cadeirante/30*FR$4)))+(BM6+BM7+BM8+BO6+BO7+BO8)*Percapita/30*FR$4+(BM9+BO9)*Crechee/30*FR$4,IF(C6=1,IF(BM6+BM7+BM8+BN6+BN7+BN8+BO6+BO7+BO8+BP6+BP7+BP8<=15,(BM6+BM7+BM8+BO6+BO7+BO8)*Percapita/30*FR$4,IF(BM6+BM7+BM8+BN6+BN7+BN8+BO6+BO7+BO8+BP6+BP7+BP8>=16,Fixo/30*FR$4+(BM6+BM7+BM8+BN6+BN7+BN8+BO6+BO7+BO8+BP6+BP7-16)*Percapita/30*FR$4)))))) -> 0 | FS6: =IF(C6=4,SUM(BQ6+BQ7+BQ8+BS6+BS7+BS8)*Percapita/30*FS$4+(BR6+BR7+BR8+BT6+BT7+BT8)*Cadeirante/30*FS$4,IF(C6=3,IF(BQ9+BS9=10,Fixo/30*FS$4+(BQ6+BQ7+BQ8+BS6+BS7+BS8)*Percapita/30*FS$4+(BR9+BT9)*Cadeirante/30*FS$4,IF(BQ9+BS9<=9,(BQ9+BS9)*Crechee/30*FS$4)+(BR9+BT9)*Cadeirante/30*FS$4+(BQ6+BQ7+BQ8+BS6+BS7+BS8)*Percapita/30*FS$4)+IF(BQ9+BS9>=11,Fixo/30*FS$4+(BQ9+BS9-10)*Crechee/30*FS$4,0),IF(C6=2,IF(BR6+BR7+BR8+BR9+BT6+BT7+BT8+BT9=1,Cadeirante/30*FS$4,IF(BR6+BR7+BR8+BR9+BT6+BT7+BT8+BT9=2,Fixo/30*FS$4,IF(BR6+BR7+BR8+BR9+BT6+BT7+BT8+BT9>2,Fixo/30*FS$4+(BR6+BR7+BR8+BR9+BT6+BT7+BT8+BT9-2)*Cadeirante/30*FS$4)))+(BQ6+BQ7+BQ8+BS6+BS7+BS8)*Percapita/30*FS$4+(BQ9+BS9)*Crechee/30*FS$4,IF(C6=1,IF(BQ6+BQ7+BQ8+BR6+BR7+BR8+BS6+BS7+BS8+BT6+BT7+BT8<=15,(BQ6+BQ7+BQ8+BS6+BS7+BS8)*Percapita/30*FS$4,IF(BQ6+BQ7+BQ8+BR6+BR7+BR8+BS6+BS7+BS8+BT6+BT7+BT8>=16,Fixo/30*FS$4+(BQ6+BQ7+BQ8+BR6+BR7+BR8+BS6+BS7+BS8+BT6+BT7-16)*Percapita/30*FS$4)))))) -> 0 | FT6: =IF(C6=4,SUM(BU6+BU7+BU8+BW6+BW7+BW8)*Percapita/30*FT$4+(BV6+BV7+BV8+BX6+BX7+BX8)*Cadeirante/30*FT$4,IF(C6=3,IF(BU9+BW9=10,Fixo/30*FT$4+(BU6+BU7+BU8+BW6+BW7+BW8)*Percapita/30*FT$4+(BV9+BX9)*Cadeirante/30*FT$4,IF(BU9+BW9<=9,(BU9+BW9)*Crechee/30*FT$4)+(BV9+BX9)*Cadeirante/30*FT$4+(BU6+BU7+BU8+BW6+BW7+BW8)*Percapita/30*FT$4)+IF(BU9+BW9>=11,Fixo/30*FT$4+(BU9+BW9-10)*Crechee/30*FT$4,0),IF(C6=2,IF(BV6+BV7+BV8+BV9+BX6+BX7+BX8+BX9=1,Cadeirante/30*FT$4,IF(BV6+BV7+BV8+BV9+BX6+BX7+BX8+BX9=2,Fixo/30*FT$4,IF(BV6+BV7+BV8+BV9+BX6+BX7+BX8+BX9>2,Fixo/30*FT$4+(BV6+BV7+BV8+BV9+BX6+BX7+BX8+BX9-2)*Cadeirante/30*FT$4)))+(BU6+BU7+BU8+BW6+BW7+BW8)*Percapita/30*FT$4+(BU9+BW9)*Crechee/30*FT$4,IF(C6=1,IF(BU6+BU7+BU8+BV6+BV7+BV8+BW6+BW7+BW8+BX6+BX7+BX8<=15,(BU6+BU7+BU8+BW6+BW7+BW8)*Percapita/30*FT$4,IF(BU6+BU7+BU8+BV6+BV7+BV8+BW6+BW7+BW8+BX6+BX7+BX8>=16,Fixo/30*FT$4+(BU6+BU7+BU8+BV6+BV7+BV8+BW6+BW7+BW8+BX6+BX7-16)*Percapita/30*FT$4)))))) -> 0 | FU6: =IF(C6=4,SUM(BY6+BY7+BY8+CA6+CA7+CA8)*Percapita/30*FU$4+(BZ6+BZ7+BZ8+CB6+CB7+CB8)*Cadeirante/30*FU$4,IF(C6=3,IF(BY9+CA9=10,Fixo/30*FU$4+(BY6+BY7+BY8+CA6+CA7+CA8)*Percapita/30*FU$4+(BZ9+CB9)*Cadeirante/30*FU$4,IF(BY9+CA9<=9,(BY9+CA9)*Crechee/30*FU$4)+(BZ9+CB9)*Cadeirante/30*FU$4+(BY6+BY7+BY8+CA6+CA7+CA8)*Percapita/30*FU$4)+IF(BY9+CA9>=11,Fixo/30*FU$4+(BY9+CA9-10)*Crechee/30*FU$4,0),IF(C6=2,IF(BZ6+BZ7+BZ8+BZ9+CB6+CB7+CB8+CB9=1,Cadeirante/30*FU$4,IF(BZ6+BZ7+BZ8+BZ9+CB6+CB7+CB8+CB9=2,Fixo/30*FU$4,IF(BZ6+BZ7+BZ8+BZ9+CB6+CB7+CB8+CB9>2,Fixo/30*FU$4+(BZ6+BZ7+BZ8+BZ9+CB6+CB7+CB8+CB9-2)*Cadeirante/30*FU$4)))+(BY6+BY7+BY8+CA6+CA7+CA8)*Percapita/30*FU$4+(BY9+CA9)*Crechee/30*FU$4,IF(C6=1,IF(BY6+BY7+BY8+BZ6+BZ7+BZ8+CA6+CA7+CA8+CB6+CB7+CB8<=15,(BY6+BY7+BY8+CA6+CA7+CA8)*Percapita/30*FU$4,IF(BY6+BY7+BY8+BZ6+BZ7+BZ8+CA6+CA7+CA8+CB6+CB7+CB8>=16,Fixo/30*FU$4+(BY6+BY7+BY8+BZ6+BZ7+BZ8+CA6+CA7+CA8+CB6+CB7-16)*Percapita/30*FU$4)))))) -> 0 | FV6: =IF(C6=4,SUM(CC6+CC7+CC8+CE6+CE7+CE8)*Percapita/30*FV$4+(CD6+CD7+CD8+CF6+CF7+CF8)*Cadeirante/30*FV$4,IF(C6=3,IF(CC9+CE9=10,Fixo/30*FV$4+(CC6+CC7+CC8+CE6+CE7+CE8)*Percapita/30*FV$4+(CD9+CF9)*Cadeirante/30*FV$4,IF(CC9+CE9<=9,(CC9+CE9)*Crechee/30*FV$4)+(CD9+CF9)*Cadeirante/30*FV$4+(CC6+CC7+CC8+CE6+CE7+CE8)*Percapita/30*FV$4)+IF(CC9+CE9>=11,Fixo/30*FV$4+(CC9+CE9-10)*Crechee/30*FV$4,0),IF(C6=2,IF(CD6+CD7+CD8+CD9+CF6+CF7+CF8+CF9=1,Cadeirante/30*FV$4,IF(CD6+CD7+CD8+CD9+CF6+CF7+CF8+CF9=2,Fixo/30*FV$4,IF(CD6+CD7+CD8+CD9+CF6+CF7+CF8+CF9>2,Fixo/30*FV$4+(CD6+CD7+CD8+CD9+CF6+CF7+CF8+CF9-2)*Cadeirante/30*FV$4)))+(CC6+CC7+CC8+CE6+CE7+CE8)*Percapita/30*FV$4+(CC9+CE9)*Crechee/30*FV$4,IF(C6=1,IF(CC6+CC7+CC8+CD6+CD7+CD8+CE6+CE7+CE8+CF6+CF7+CF8<=15,(CC6+CC7+CC8+CE6+CE7+CE8)*Percapita/30*FV$4,IF(CC6+CC7+CC8+CD6+CD7+CD8+CE6+CE7+CE8+CF6+CF7+CF8>=16,Fixo/30*FV$4+(CC6+CC7+CC8+CD6+CD7+CD8+CE6+CE7+CE8+CF6+CF7-16)*Percapita/30*FV$4)))))) -> 0 | FW6: =IF(C6=4,SUM(CG6+CG7+CG8+CI6+CI7+CI8)*Percapita/30*FW$4+(CH6+CH7+CH8+CJ6+CJ7+CJ8)*Cadeirante/30*FW$4,IF(C6=3,IF(CG9+CI9=10,Fixo/30*FW$4+(CG6+CG7+CG8+CI6+CI7+CI8)*Percapita/30*FW$4+(CH9+CJ9)*Cadeirante/30*FW$4,IF(CG9+CI9<=9,(CG9+CI9)*Crechee/30*FW$4)+(CH9+CJ9)*Cadeirante/30*FW$4+(CG6+CG7+CG8+CI6+CI7+CI8)*Percapita/30*FW$4)+IF(CG9+CI9>=11,Fixo/30*FW$4+(CG9+CI9-10)*Crechee/30*FW$4,0),IF(C6=2,IF(CH6+CH7+CH8+CH9+CJ6+CJ7+CJ8+CJ9=1,Cadeirante/30*FW$4,IF(CH6+CH7+CH8+CH9+CJ6+CJ7+CJ8+CJ9=2,Fixo/30*FW$4,IF(CH6+CH7+CH8+CH9+CJ6+CJ7+CJ8+CJ9>2,Fixo/30*FW$4+(CH6+CH7+CH8+CH9+CJ6+CJ7+CJ8+CJ9-2)*Cadeirante/30*FW$4)))+(CG6+CG7+CG8+CI6+CI7+CI8)*Percapita/30*FW$4+(CG9+CI9)*Crechee/30*FW$4,IF(C6=1,IF(CG6+CG7+CG8+CH6+CH7+CH8+CI6+CI7+CI8+CJ6+CJ7+CJ8<=15,(CG6+CG7+CG8+CI6+CI7+CI8)*Percapita/30*FW$4,IF(CG6+CG7+CG8+CH6+CH7+CH8+CI6+CI7+CI8+CJ6+CJ7+CJ8>=16,Fixo/30*FW$4+(CG6+CG7+CG8+CH6+CH7+CH8+CI6+CI7+CI8+CJ6+CJ7-16)*Percapita/30*FW$4)))))) -> 0 | FX6: =IF(C6=4,SUM(CK6+CK7+CK8+CM6+CM7+CM8)*Percapita/30*FX$4+(CL6+CL7+CL8+CN6+CN7+CN8)*Cadeirante/30*FX$4,IF(C6=3,IF(CK9+CM9=10,Fixo/30*FX$4+(CK6+CK7+CK8+CM6+CM7+CM8)*Percapita/30*FX$4+(CL9+CN9)*Cadeirante/30*FX$4,IF(CK9+CM9<=9,(CK9+CM9)*Crechee/30*FX$4)+(CL9+CN9)*Cadeirante/30*FX$4+(CK6+CK7+CK8+CM6+CM7+CM8)*Percapita/30*FX$4)+IF(CK9+CM9>=11,Fixo/30*FX$4+(CK9+CM9-10)*Crechee/30*FX$4,0),IF(C6=2,IF(CL6+CL7+CL8+CL9+CN6+CN7+CN8+CN9=1,Cadeirante/30*FX$4,IF(CL6+CL7+CL8+CL9+CN6+CN7+CN8+CN9=2,Fixo/30*FX$4,IF(CL6+CL7+CL8+CL9+CN6+CN7+CN8+CN9>2,Fixo/30*FX$4+(CL6+CL7+CL8+CL9+CN6+CN7+CN8+CN9-2)*Cadeirante/30*FX$4)))+(CK6+CK7+CK8+CM6+CM7+CM8)*Percapita/30*FX$4+(CK9+CM9)*Crechee/30*FX$4,IF(C6=1,IF(CK6+CK7+CK8+CL6+CL7+CL8+CM6+CM7+CM8+CN6+CN7+CN8<=15,(CK6+CK7+CK8+CM6+CM7+CM8)*Percapita/30*FX$4,IF(CK6+CK7+CK8+CL6+CL7+CL8+CM6+CM7+CM8+CN6+CN7+CN8>=16,Fixo/30*FX$4+(CK6+CK7+CK8+CL6+CL7+CL8+CM6+CM7+CM8+CN6+CN7-16)*Percapita/30*FX$4)))))) -> 0 | FY6: =IF(C6=4,SUM(CO6+CO7+CO8+CQ6+CQ7+CQ8)*Percapita/30*FY$4+(CP6+CP7+CP8+CR6+CR7+CR8)*Cadeirante/30*FY$4,IF(C6=3,IF(CO9+CQ9=10,Fixo/30*FY$4+(CO6+CO7+CO8+CQ6+CQ7+CQ8)*Percapita/30*FY$4+(CP9+CR9)*Cadeirante/30*FY$4,IF(CO9+CQ9<=9,(CO9+CQ9)*Crechee/30*FY$4)+(CP9+CR9)*Cadeirante/30*FY$4+(CO6+CO7+CO8+CQ6+CQ7+CQ8)*Percapita/30*FY$4)+IF(CO9+CQ9>=11,Fixo/30*FY$4+(CO9+CQ9-10)*Crechee/30*FY$4,0),IF(C6=2,IF(CP6+CP7+CP8+CP9+CR6+CR7+CR8+CR9=1,Cadeirante/30*FY$4,IF(CP6+CP7+CP8+CP9+CR6+CR7+CR8+CR9=2,Fixo/30*FY$4,IF(CP6+CP7+CP8+CP9+CR6+CR7+CR8+CR9>2,Fixo/30*FY$4+(CP6+CP7+CP8+CP9+CR6+CR7+CR8+CR9-2)*Cadeirante/30*FY$4)))+(CO6+CO7+CO8+CQ6+CQ7+CQ8)*Percapita/30*FY$4+(CO9+CQ9)*Crechee/30*FY$4,IF(C6=1,IF(CO6+CO7+CO8+CP6+CP7+CP8+CQ6+CQ7+CQ8+CR6+CR7+CR8<=15,(CO6+CO7+CO8+CQ6+CQ7+CQ8)*Percapita/30*FY$4,IF(CO6+CO7+CO8+CP6+CP7+CP8+CQ6+CQ7+CQ8+CR6+CR7+CR8>=16,Fixo/30*FY$4+(CO6+CO7+CO8+CP6+CP7+CP8+CQ6+CQ7+CQ8+CR6+CR7-16)*Percapita/30*FY$4)))))) -> 0 | FZ6: =IF(C6=4,SUM(CS6+CS7+CS8+CU6+CU7+CU8)*Percapita/30*FZ$4+(CT6+CT7+CT8+CV6+CV7+CV8)*Cadeirante/30*FZ$4,IF(C6=3,IF(CS9+CU9=10,Fixo/30*FZ$4+(CS6+CS7+CS8+CU6+CU7+CU8)*Percapita/30*FZ$4+(CT9+CV9)*Cadeirante/30*FZ$4,IF(CS9+CU9<=9,(CS9+CU9)*Crechee/30*FZ$4)+(CT9+CV9)*Cadeirante/30*FZ$4+(CS6+CS7+CS8+CU6+CU7+CU8)*Percapita/30*FZ$4)+IF(CS9+CU9>=11,Fixo/30*FZ$4+(CS9+CU9-10)*Crechee/30*FZ$4,0),IF(C6=2,IF(CT6+CT7+CT8+CT9+CV6+CV7+CV8+CV9=1,Cadeirante/30*FZ$4,IF(CT6+CT7+CT8+CT9+CV6+CV7+CV8+CV9=2,Fixo/30*FZ$4,IF(CT6+CT7+CT8+CT9+CV6+CV7+CV8+CV9>2,Fixo/30*FZ$4+(CT6+CT7+CT8+CT9+CV6+CV7+CV8+CV9-2)*Cadeirante/30*FZ$4)))+(CS6+CS7+CS8+CU6+CU7+CU8)*Percapita/30*FZ$4+(CS9+CU9)*Crechee/30*FZ$4,IF(C6=1,IF(CS6+CS7+CS8+CT6+CT7+CT8+CU6+CU7+CU8+CV6+CV7+CV8<=15,(CS6+CS7+CS8+CU6+CU7+CU8)*Percapita/30*FZ$4,IF(CS6+CS7+CS8+CT6+CT7+CT8+CU6+CU7+CU8+CV6+CV7+CV8>=16,Fixo/30*FZ$4+(CS6+CS7+CS8+CT6+CT7+CT8+CU6+CU7+CU8+CV6+CV7-16)*Percapita/30*FZ$4)))))) -> 0 | GA6: =IF(C6=4,SUM(CW6+CW7+CW8+CY6+CY7+CY8)*Percapita/30*GA$4+(CX6+CX7+CX8+CZ6+CZ7+CZ8)*Cadeirante/30*GA$4,IF(C6=3,IF(CW9+CY9=10,Fixo/30*GA$4+(CW6+CW7+CW8+CY6+CY7+CY8)*Percapita/30*GA$4+(CX9+CZ9)*Cadeirante/30*GA$4,IF(CW9+CY9<=9,(CW9+CY9)*Crechee/30*GA$4)+(CX9+CZ9)*Cadeirante/30*GA$4+(CW6+CW7+CW8+CY6+CY7+CY8)*Percapita/30*GA$4)+IF(CW9+CY9>=11,Fixo/30*GA$4+(CW9+CY9-10)*Crechee/30*GA$4,0),IF(C6=2,IF(CX6+CX7+CX8+CX9+CZ6+CZ7+CZ8+CZ9=1,Cadeirante/30*GA$4,IF(CX6+CX7+CX8+CX9+CZ6+CZ7+CZ8+CZ9=2,Fixo/30*GA$4,IF(CX6+CX7+CX8+CX9+CZ6+CZ7+CZ8+CZ9>2,Fixo/30*GA$4+(CX6+CX7+CX8+CX9+CZ6+CZ7+CZ8+CZ9-2)*Cadeirante/30*GA$4)))+(CW6+CW7+CW8+CY6+CY7+CY8)*Percapita/30*GA$4+(CW9+CY9)*Crechee/30*GA$4,IF(C6=1,IF(CW6+CW7+CW8+CX6+CX7+CX8+CY6+CY7+CY8+CZ6+CZ7+CZ8<=15,(CW6+CW7+CW8+CY6+CY7+CY8)*Percapita/30*GA$4,IF(CW6+CW7+CW8+CX6+CX7+CX8+CY6+CY7+CY8+CZ6+CZ7+CZ8>=16,Fixo/30*GA$4+(CW6+CW7+CW8+CX6+CX7+CX8+CY6+CY7+CY8+CZ6+CZ7-16)*Percapita/30*GA$4)))))) -> 0 | GB6: =IF(C6=4,SUM(DA6+DA7+DA8+DC6+DC7+DC8)*Percapita/30*GB$4+(DB6+DB7+DB8+DD6+DD7+DD8)*Cadeirante/30*GB$4,IF(C6=3,IF(DA9+DC9=10,Fixo/30*GB$4+(DA6+DA7+DA8+DC6+DC7+DC8)*Percapita/30*GB$4+(DB9+DD9)*Cadeirante/30*GB$4,IF(DA9+DC9<=9,(DA9+DC9)*Crechee/30*GB$4)+(DB9+DD9)*Cadeirante/30*GB$4+(DA6+DA7+DA8+DC6+DC7+DC8)*Percapita/30*GB$4)+IF(DA9+DC9>=11,Fixo/30*GB$4+(DA9+DC9-10)*Crechee/30*GB$4,0),IF(C6=2,IF(DB6+DB7+DB8+DB9+DD6+DD7+DD8+DD9=1,Cadeirante/30*GB$4,IF(DB6+DB7+DB8+DB9+DD6+DD7+DD8+DD9=2,Fixo/30*GB$4,IF(DB6+DB7+DB8+DB9+DD6+DD7+DD8+DD9>2,Fixo/30*GB$4+(DB6+DB7+DB8+DB9+DD6+DD7+DD8+DD9-2)*Cadeirante/30*GB$4)))+(DA6+DA7+DA8+DC6+DC7+DC8)*Percapita/30*GB$4+(DA9+DC9)*Crechee/30*GB$4,IF(C6=1,IF(DA6+DA7+DA8+DB6+DB7+DB8+DC6+DC7+DC8+DD6+DD7+DD8<=15,(DA6+DA7+DA8+DC6+DC7+DC8)*Percapita/30*GB$4,IF(DA6+DA7+DA8+DB6+DB7+DB8+DC6+DC7+DC8+DD6+DD7+DD8>=16,Fixo/30*GB$4+(DA6+DA7+DA8+DB6+DB7+DB8+DC6+DC7+DC8+DD6+DD7-16)*Percapita/30*GB$4)))))) -> 0 | GC6: =IF(C6=4,SUM(DE6+DE7+DE8+DG6+DG7+DG8)*Percapita/30*GC$4+(DF6+DF7+DF8+DH6+DH7+DH8)*Cadeirante/30*GC$4,IF(C6=3,IF(DE9+DG9=10,Fixo/30*GC$4+(DE6+DE7+DE8+DG6+DG7+DG8)*Percapita/30*GC$4+(DF9+DH9)*Cadeirante/30*GC$4,IF(DE9+DG9<=9,(DE9+DG9)*Crechee/30*GC$4)+(DF9+DH9)*Cadeirante/30*GC$4+(DE6+DE7+DE8+DG6+DG7+DG8)*Percapita/30*GC$4)+IF(DE9+DG9>=11,Fixo/30*GC$4+(DE9+DG9-10)*Crechee/30*GC$4,0),IF(C6=2,IF(DF6+DF7+DF8+DF9+DH6+DH7+DH8+DH9=1,Cadeirante/30*GC$4,IF(DF6+DF7+DF8+DF9+DH6+DH7+DH8+DH9=2,Fixo/30*GC$4,IF(DF6+DF7+DF8+DF9+DH6+DH7+DH8+DH9>2,Fixo/30*GC$4+(DF6+DF7+DF8+DF9+DH6+DH7+DH8+DH9-2)*Cadeirante/30*GC$4)))+(DE6+DE7+DE8+DG6+DG7+DG8)*Percapita/30*GC$4+(DE9+DG9)*Crechee/30*GC$4,IF(C6=1,IF(DE6+DE7+DE8+DF6+DF7+DF8+DG6+DG7+DG8+DH6+DH7+DH8<=15,(DE6+DE7+DE8+DG6+DG7+DG8)*Percapita/30*GC$4,IF(DE6+DE7+DE8+DF6+DF7+DF8+DG6+DG7+DG8+DH6+DH7+DH8>=16,Fixo/30*GC$4+(DE6+DE7+DE8+DF6+DF7+DF8+DG6+DG7+DG8+DH6+DH7-16)*Percapita/30*GC$4)))))) -> 0 | GD6: =IF(C6=4,SUM(DI6+DI7+DI8+DK6+DK7+DK8)*Percapita/30*GD$4+(DJ6+DJ7+DJ8+DL6+DL7+DL8)*Cadeirante/30*GD$4,IF(C6=3,IF(DI9+DK9=10,Fixo/30*GD$4+(DI6+DI7+DI8+DK6+DK7+DK8)*Percapita/30*GD$4+(DJ9+DL9)*Cadeirante/30*GD$4,IF(DI9+DK9<=9,(DI9+DK9)*Crechee/30*GD$4)+(DJ9+DL9)*Cadeirante/30*GD$4+(DI6+DI7+DI8+DK6+DK7+DK8)*Percapita/30*GD$4)+IF(DI9+DK9>=11,Fixo/30*GD$4+(DI9+DK9-10)*Crechee/30*GD$4,0),IF(C6=2,IF(DJ6+DJ7+DJ8+DJ9+DL6+DL7+DL8+DL9=1,Cadeirante/30*GD$4,IF(DJ6+DJ7+DJ8+DJ9+DL6+DL7+DL8+DL9=2,Fixo/30*GD$4,IF(DJ6+DJ7+DJ8+DJ9+DL6+DL7+DL8+DL9>2,Fixo/30*GD$4+(DJ6+DJ7+DJ8+DJ9+DL6+DL7+DL8+DL9-2)*Cadeirante/30*GD$4)))+(DI6+DI7+DI8+DK6+DK7+DK8)*Percapita/30*GD$4+(DI9+DK9)*Crechee/30*GD$4,IF(C6=1,IF(DI6+DI7+DI8+DJ6+DJ7+DJ8+DK6+DK7+DK8+DL6+DL7+DL8<=15,(DI6+DI7+DI8+DK6+DK7+DK8)*Percapita/30*GD$4,IF(DI6+DI7+DI8+DJ6+DJ7+DJ8+DK6+DK7+DK8+DL6+DL7+DL8>=16,Fixo/30*GD$4+(DI6+DI7+DI8+DJ6+DJ7+DJ8+DK6+DK7+DK8+DL6+DL7-16)*Percapita/30*GD$4)))))) -> 0 | GE6: =IF(C6=4,SUM(DM6+DM7+DM8+DO6+DO7+DO8)*Percapita/30*GE$4+(DN6+DN7+DN8+DP6+DP7+DP8)*Cadeirante/30*GE$4,IF(C6=3,IF(DM9+DO9=10,Fixo/30*GE$4+(DM6+DM7+DM8+DO6+DO7+DO8)*Percapita/30*GE$4+(DN9+DP9)*Cadeirante/30*GE$4,IF(DM9+DO9<=9,(DM9+DO9)*Crechee/30*GE$4)+(DN9+DP9)*Cadeirante/30*GE$4+(DM6+DM7+DM8+DO6+DO7+DO8)*Percapita/30*GE$4)+IF(DM9+DO9>=11,Fixo/30*GE$4+(DM9+DO9-10)*Crechee/30*GE$4,0),IF(C6=2,IF(DN6+DN7+DN8+DN9+DP6+DP7+DP8+DP9=1,Cadeirante/30*GE$4,IF(DN6+DN7+DN8+DN9+DP6+DP7+DP8+DP9=2,Fixo/30*GE$4,IF(DN6+DN7+DN8+DN9+DP6+DP7+DP8+DP9>2,Fixo/30*GE$4+(DN6+DN7+DN8+DN9+DP6+DP7+DP8+DP9-2)*Cadeirante/30*GE$4)))+(DM6+DM7+DM8+DO6+DO7+DO8)*Percapita/30*GE$4+(DM9+DO9)*Crechee/30*GE$4,IF(C6=1,IF(DM6+DM7+DM8+DN6+DN7+DN8+DO6+DO7+DO8+DP6+DP7+DP8<=15,(DM6+DM7+DM8+DO6+DO7+DO8)*Percapita/30*GE$4,IF(DM6+DM7+DM8+DN6+DN7+DN8+DO6+DO7+DO8+DP6+DP7+DP8>=16,Fixo/30*GE$4+(DM6+DM7+DM8+DN6+DN7+DN8+DO6+DO7+DO8+DP6+DP7-16)*Percapita/30*GE$4)))))) -> 0 | GF6: =IF(C6=4,SUM(DQ6+DQ7+DQ8+DS6+DS7+DS8)*Percapita/30*GF$4+(DR6+DR7+DR8+DT6+DT7+DT8)*Cadeirante/30*GF$4,IF(C6=3,IF(DQ9+DS9=10,Fixo/30*GF$4+(DQ6+DQ7+DQ8+DS6+DS7+DS8)*Percapita/30*GF$4+(DR9+DT9)*Cadeirante/30*GF$4,IF(DQ9+DS9<=9,(DQ9+DS9)*Crechee/30*GF$4)+(DR9+DT9)*Cadeirante/30*GF$4+(DQ6+DQ7+DQ8+DS6+DS7+DS8)*Percapita/30*GF$4)+IF(DQ9+DS9>=11,Fixo/30*GF$4+(DQ9+DS9-10)*Crechee/30*GF$4,0),IF(C6=2,IF(DR6+DR7+DR8+DR9+DT6+DT7+DT8+DT9=1,Cadeirante/30*GF$4,IF(DR6+DR7+DR8+DR9+DT6+DT7+DT8+DT9=2,Fixo/30*GF$4,IF(DR6+DR7+DR8+DR9+DT6+DT7+DT8+DT9>2,Fixo/30*GF$4+(DR6+DR7+DR8+DR9+DT6+DT7+DT8+DT9-2)*Cadeirante/30*GF$4)))+(DQ6+DQ7+DQ8+DS6+DS7+DS8)*Percapita/30*GF$4+(DQ9+DS9)*Crechee/30*GF$4,IF(C6=1,IF(DQ6+DQ7+DQ8+DR6+DR7+DR8+DS6+DS7+DS8+DT6+DT7+DT8<=15,(DQ6+DQ7+DQ8+DS6+DS7+DS8)*Percapita/30*GF$4,IF(DQ6+DQ7+DQ8+DR6+DR7+DR8+DS6+DS7+DS8+DT6+DT7+DT8>=16,Fixo/30*GF$4+(DQ6+DQ7+DQ8+DR6+DR7+DR8+DS6+DS7+DS8+DT6+DT7-16)*Percapita/30*GF$4)))))) -> 0 | GG6: =IF(C6=4,SUM(DU6+DU7+DU8+DW6+DW7+DW8)*Percapita/30*GG$4+(DV6+DV7+DV8+DX6+DX7+DX8)*Cadeirante/30*GG$4,IF(C6=3,IF(DU9+DW9=10,Fixo/30*GG$4+(DU6+DU7+DU8+DW6+DW7+DW8)*Percapita/30*GG$4+(DV9+DX9)*Cadeirante/30*GG$4,IF(DU9+DW9<=9,(DU9+DW9)*Crechee/30*GG$4)+(DV9+DX9)*Cadeirante/30*GG$4+(DU6+DU7+DU8+DW6+DW7+DW8)*Percapita/30*GG$4)+IF(DU9+DW9>=11,Fixo/30*GG$4+(DU9+DW9-10)*Crechee/30*GG$4,0),IF(C6=2,IF(DV6+DV7+DV8+DV9+DX6+DX7+DX8+DX9=1,Cadeirante/30*GG$4,IF(DV6+DV7+DV8+DV9+DX6+DX7+DX8+DX9=2,Fixo/30*GG$4,IF(DV6+DV7+DV8+DV9+DX6+DX7+DX8+DX9>2,Fixo/30*GG$4+(DV6+DV7+DV8+DV9+DX6+DX7+DX8+DX9-2)*Cadeirante/30*GG$4)))+(DU6+DU7+DU8+DW6+DW7+DW8)*Percapita/30*GG$4+(DU9+DW9)*Crechee/30*GG$4,IF(C6=1,IF(DU6+DU7+DU8+DV6+DV7+DV8+DW6+DW7+DW8+DX6+DX7+DX8<=15,(DU6+DU7+DU8+DW6+DW7+DW8)*Percapita/30*GG$4,IF(DU6+DU7+DU8+DV6+DV7+DV8+DW6+DW7+DW8+DX6+DX7+DX8>=16,Fixo/30*GG$4+(DU6+DU7+DU8+DV6+DV7+DV8+DW6+DW7+DW8+DX6+DX7-16)*Percapita/30*GG$4)))))) -> 0 | GH6: =IF(C6=4,SUM(DY6+DY7+DY8+EA6+EA7+EA8)*Percapita/30*GH$4+(DZ6+DZ7+DZ8+EB6+EB7+EB8)*Cadeirante/30*GH$4,IF(C6=3,IF(DY9+EA9=10,Fixo/30*GH$4+(DY6+DY7+DY8+EA6+EA7+EA8)*Percapita/30*GH$4+(DZ9+EB9)*Cadeirante/30*GH$4,IF(DY9+EA9<=9,(DY9+EA9)*Crechee/30*GH$4)+(DZ9+EB9)*Cadeirante/30*GH$4+(DY6+DY7+DY8+EA6+EA7+EA8)*Percapita/30*GH$4)+IF(DY9+EA9>=11,Fixo/30*GH$4+(DY9+EA9-10)*Crechee/30*GH$4,0),IF(C6=2,IF(DZ6+DZ7+DZ8+DZ9+EB6+EB7+EB8+EB9=1,Cadeirante/30*GH$4,IF(DZ6+DZ7+DZ8+DZ9+EB6+EB7+EB8+EB9=2,Fixo/30*GH$4,IF(DZ6+DZ7+DZ8+DZ9+EB6+EB7+EB8+EB9>2,Fixo/30*GH$4+(DZ6+DZ7+DZ8+DZ9+EB6+EB7+EB8+EB9-2)*Cadeirante/30*GH$4)))+(DY6+DY7+DY8+EA6+EA7+EA8)*Percapita/30*GH$4+(DY9+EA9)*Crechee/30*GH$4,IF(C6=1,IF(DY6+DY7+DY8+DZ6+DZ7+DZ8+EA6+EA7+EA8+EB6+EB7+EB8<=15,(DY6+DY7+DY8+EA6+EA7+EA8)*Percapita/30*GH$4,IF(DY6+DY7+DY8+DZ6+DZ7+DZ8+EA6+EA7+EA8+EB6+EB7+EB8>=16,Fixo/30*GH$4+(DY6+DY7+DY8+DZ6+DZ7+DZ8+EA6+EA7+EA8+EB6+EB7-16)*Percapita/30*GH$4)))))) -> 0 | GI6: =IF(C6=4,SUM(EC6+EC7+EC8+EE6+EE7+EE8)*Percapita/30*GI$4+(ED6+ED7+ED8+EF6+EF7+EF8)*Cadeirante/30*GI$4,IF(C6=3,IF(EC9+EE9=10,Fixo/30*GI$4+(EC6+EC7+EC8+EE6+EE7+EE8)*Percapita/30*GI$4+(ED9+EF9)*Cadeirante/30*GI$4,IF(EC9+EE9<=9,(EC9+EE9)*Crechee/30*GI$4)+(ED9+EF9)*Cadeirante/30*GI$4+(EC6+EC7+EC8+EE6+EE7+EE8)*Percapita/30*GI$4)+IF(EC9+EE9>=11,Fixo/30*GI$4+(EC9+EE9-10)*Crechee/30*GI$4,0),IF(C6=2,IF(ED6+ED7+ED8+ED9+EF6+EF7+EF8+EF9=1,Cadeirante/30*GI$4,IF(ED6+ED7+ED8+ED9+EF6+EF7+EF8+EF9=2,Fixo/30*GI$4,IF(ED6+ED7+ED8+ED9+EF6+EF7+EF8+EF9>2,Fixo/30*GI$4+(ED6+ED7+ED8+ED9+EF6+EF7+EF8+EF9-2)*Cadeirante/30*GI$4)))+(EC6+EC7+EC8+EE6+EE7+EE8)*Percapita/30*GI$4+(EC9+EE9)*Crechee/30*GI$4,IF(C6=1,IF(EC6+EC7+EC8+ED6+ED7+ED8+EE6+EE7+EE8+EF6+EF7+EF8<=15,(EC6+EC7+EC8+EE6+EE7+EE8)*Percapita/30*GI$4,IF(EC6+EC7+EC8+ED6+ED7+ED8+EE6+EE7+EE8+EF6+EF7+EF8>=16,Fixo/30*GI$4+(EC6+EC7+EC8+ED6+ED7+ED8+EE6+EE7+EE8+EF6+EF7-16)*Percapita/30*GI$4)))))) -> 0 | GJ6: =IF(C6=4,SUM(EG6+EG7+EG8+EI6+EI7+EI8)*Percapita/30*GJ$4+(EH6+EH7+EH8+EJ6+EJ7+EJ8)*Cadeirante/30*GJ$4,IF(C6=3,IF(EG9+EI9=10,Fixo/30*GJ$4+(EG6+EG7+EG8+EI6+EI7+EI8)*Percapita/30*GJ$4+(EH9+EJ9)*Cadeirante/30*GJ$4,IF(EG9+EI9<=9,(EG9+EI9)*Crechee/30*GJ$4)+(EH9+EJ9)*Cadeirante/30*GJ$4+(EG6+EG7+EG8+EI6+EI7+EI8)*Percapita/30*GJ$4)+IF(EG9+EI9>=11,Fixo/30*GJ$4+(EG9+EI9-10)*Crechee/30*GJ$4,0),IF(C6=2,IF(EH6+EH7+EH8+EH9+EJ6+EJ7+EJ8+EJ9=1,Cadeirante/30*GJ$4,IF(EH6+EH7+EH8+EH9+EJ6+EJ7+EJ8+EJ9=2,Fixo/30*GJ$4,IF(EH6+EH7+EH8+EH9+EJ6+EJ7+EJ8+EJ9>2,Fixo/30*GJ$4+(EH6+EH7+EH8+EH9+EJ6+EJ7+EJ8+EJ9-2)*Cadeirante/30*GJ$4)))+(EG6+EG7+EG8+EI6+EI7+EI8)*Percapita/30*GJ$4+(EG9+EI9)*Crechee/30*GJ$4,IF(C6=1,IF(EG6+EG7+EG8+EH6+EH7+EH8+EI6+EI7+EI8+EJ6+EJ7+EJ8<=15,(EG6+EG7+EG8+EI6+EI7+EI8)*Percapita/30*GJ$4,IF(EG6+EG7+EG8+EH6+EH7+EH8+EI6+EI7+EI8+EJ6+EJ7+EJ8>=16,Fixo/30*GJ$4+(EG6+EG7+EG8+EH6+EH7+EH8+EI6+EI7+EI8+EJ6+EJ7-16)*Percapita/30*GJ$4)))))) -> 0 | GL6: =IF(J6="ADAPTADO",T6*Cadeirante/30*GM6+S6*Percapita/30*GM6,IF(J6="NORMAL",(S6+T6)*Percapita/30*GM6,IF(J6="CRECHE",0)))*-1 -> 0 | GN6: =SUMIF(V6:V9,"<0")*Cadeirante/30*GN$4+SUMIF(X6:X9,"<0")*Cadeirante/30*GN$4 -> 0 | GO6: =SUMIF(Z6:Z9,"<0")*Cadeirante/30*GO$4+SUMIF(AB6:AB9,"<0")*Cadeirante/30*GO$4 -> 0 | GP6: =SUMIF(AD6:AD9,"<0")*Cadeirante/30*GP$4+SUMIF(AF6:AF9,"<0")*Cadeirante/30*GP$4 -> 0 | GQ6: =SUMIF(AH6:AH9,"<0")*Cadeirante/30*GQ$4+SUMIF(AJ6:AJ9,"<0")*Cadeirante/30*GQ$4 -> 0 | GR6: =SUMIF(AL6:AL9,"<0")*Cadeirante/30*GR$4+SUMIF(AN6:AN9,"<0")*Cadeirante/30*GR$4 -> 0 | GS6: =SUMIF(AP6:AP9,"<0")*Cadeirante/30*GS$4+SUMIF(AR6:AR9,"<0")*Cadeirante/30*GS$4 -> 0 | GT6: =SUMIF(AT6:AT9,"<0")*Cadeirante/30*GT$4+SUMIF(AV6:AV9,"<0")*Cadeirante/30*GT$4 -> 0 | GU6: =SUMIF(AX6:AX9,"<0")*Cadeirante/30*GU$4+SUMIF(AZ6:AZ9,"<0")*Cadeirante/30*GU$4 -> 0 | GV6: =SUMIF(BB6:BB9,"<0")*Cadeirante/30*GV$4+SUMIF(BD6:BD9,"<0")*Cadeirante/30*GV$4 -> 0 | GW6: =SUMIF(BF6:BF9,"<0")*Cadeirante/30*GW$4+SUMIF(BH6:BH9,"<0")*Cadeirante/30*GW$4 -> 0 | GX6: =SUMIF(BJ6:BJ9,"<0")*Cadeirante/30*GX$4+SUMIF(BL6:BL9,"<0")*Cadeirante/30*GX$4 -> 0 | GY6: =SUMIF(BN6:BN9,"<0")*Cadeirante/30*GY$4+SUMIF(BP6:BP9,"<0")*Cadeirante/30*GY$4 -> 0 | GZ6: =SUMIF(BR6:BR9,"<0")*Cadeirante/30*GZ$4+SUMIF(BT6:BT9,"<0")*Cadeirante/30*GZ$4 -> 0 | HA6: =SUMIF(BV6:BV9,"<0")*Cadeirante/30*HA$4+SUMIF(BX6:BX9,"<0")*Cadeirante/30*HA$4 -> 0 | HB6: =SUMIF(BZ6:BZ9,"<0")*Cadeirante/30*HB$4+SUMIF(CB6:CB9,"<0")*Cadeirante/30*HB$4 -> 0 | HC6: =SUMIF(CD6:CD9,"<0")*Cadeirante/30*HC$4+SUMIF(CF6:CF9,"<0")*Cadeirante/30*HC$4 -> 0 | HD6: =SUMIF(CH6:CH9,"<0")*Cadeirante/30*HD$4+SUMIF(CJ6:CJ9,"<0")*Cadeirante/30*HD$4 -> 0 | HE6: =SUMIF(CL6:CL9,"<0")*Cadeirante/30*HE$4+SUMIF(CN6:CN9,"<0")*Cadeirante/30*HE$4 -> 0 | HF6: =SUMIF(CP6:CP9,"<0")*Cadeirante/30*HF$4+SUMIF(CR6:CR9,"<0")*Cadeirante/30*HF$4 -> 0 | HG6: =SUMIF(CT6:CT9,"<0")*Cadeirante/30*HG$4+SUMIF(CV6:CV9,"<0")*Cadeirante/30*HG$4 -> 0 | HH6: =SUMIF(CX6:CX9,"<0")*Cadeirante/30*HH$4+SUMIF(CZ6:CZ9,"<0")*Cadeirante/30*HH$4 -> 0 | HI6: =SUMIF(DB6:DB9,"<0")*Cadeirante/30*HI$4+SUMIF(DD6:DD9,"<0")*Cadeirante/30*HI$4 -> 0 | HJ6: =SUMIF(DF6:DF9,"<0")*Cadeirante/30*HJ$4+SUMIF(DH6:DH9,"<0")*Cadeirante/30*HJ$4 -> 0 | HK6: =SUMIF(DJ6:DJ9,"<0")*Cadeirante/30*HK$4+SUMIF(DL6:DL9,"<0")*Cadeirante/30*HK$4 -> 0 | HL6: =SUMIF(DN6:DN9,"<0")*Cadeirante/30*HL$4+SUMIF(DP6:DP9,"<0")*Cadeirante/30*HL$4 -> 0 | HM6: =SUMIF(DR6:DR9,"<0")*Cadeirante/30*HM$4+SUMIF(DT6:DT9,"<0")*Cadeirante/30*HM$4 -> 0 | HN6: =SUMIF(DV6:DV9,"<0")*Cadeirante/30*HN$4+SUMIF(DX6:DX9,"<0")*Cadeirante/30*HN$4 -> 0 | HO6: =SUMIF(DZ6:DZ9,"<0")*Cadeirante/30*HO$4+SUMIF(EB6:EB9,"<0")*Cadeirante/30*HO$4 -> 0 | HP6: =SUMIF(ED6:ED9,"<0")*Cadeirante/30*HP$4+SUMIF(EF6:EF9,"<0")*Cadeirante/30*HP$4 -> 0 | HW6: 17629.31 | HY6: =IF(ISTEXT(EM6), VALUE(EM6), EM6) -> 0 | HZ6: =IF(ISTEXT(EN6), VALUE(EN6), EN6) -> 0 | IA6: =IF(ISTEXT(EO6), VALUE(EO6), EO6) -> 0 | IB6: =HW6=FE6 -> FALSE
A7: 020.708-00 | B7: 2022/0026670-001 | C7: FB | D7: 2022/0026670 | E7: DJE9491 | F7: 01/04/2026 | G7: 30/04/2026 | H7: ADILSON TOLEDO | I7: ADILSON TOLEDO | J7: NORMAL | K7: EMEF | L7: =CONTINUA!BV7 -> 0 | M7: =CONTINUA!BW7 -> 0 | O7: 6020.2022/0026670-0 | P7: 0 | Q7: 59 | EP7: =Q7 -> 59 | EQ7: =U7+Y7+AC7+AG7+AK7+AO7+AS7+AW7+BA7+BE7+BI7+BM7+BQ7+BU7+BY7+CC7+CG7+CK7+CO7+CS7+CW7+DA7+DE7+DI7+DM7+DQ7+DU7+DY7+EC7+EG7 -> 0 | ER7: =S7+W7+AA7+AE7+AI7+AM7+AQ7+AU7+AY7+BC7+BG7+BK7+BO7+BS7+BW7+CA7+CE7+CI7+CM7+CQ7+CU7+CY7+DC7+DG7+DK7+DO7+DS7+DW7+EA7+EE7+EI7 -> 0 | ES7: =R7 -> 0 | ET7: =V7+Z7+AD7+AH7+AL7+AP7+AT7+AX7+BB7+BF7+BJ7+BN7+BR7+BV7+BZ7+CD7+CH7+CL7+CP7+CT7+CX7+DB7+DF7+DJ7+DN7+DR7+DV7+DZ7+ED7+EH7 -> 0 | EU7: =T7+X7+AB7+AF7+AJ7+AN7+AR7+AV7+AZ7+BD7+BH7+BL7+BP7+BT7+BX7+CB7+CF7+CJ7+CN7+CR7+CV7+CZ7+DD7+DH7+DL7+DP7+DT7+DX7+EB7+EF7+EJ7 -> 0 | EV7: =EP7+EQ7+ES7+ET7+ER7+EU7 -> 59 | EX7: =FF7 -> 0 | EY7: =(L7*regular)+(M7*Cadeirantee) -> 0 | EZ7: =SUMIF(FG7:GJ7,">0") -> 0 | FA7: =SUMIF(FG7:GJ7,"<0")+SUMIF(GN7:HP7,"<0") -> 0 | FB7: 0 | FC7: =N7*km*'VALORES TABELA'!$B$13 -> 0 | FD7: =GL7 -> 0 | GL7: =IF(J7="ADAPTADO",T7*Cadeirante/30*GM7+S7*Percapita/30*GM7,IF(J7="NORMAL",(S7+T7)*Percapita/30*GM7,IF(J7="CRECHE",0)))*-1 -> 0 | HY7: =IF(ISTEXT(EM7), VALUE(EM7), EM7) -> 0 | HZ7: =IF(ISTEXT(EN7), VALUE(EN7), EN7) -> 0 | IA7: =IF(ISTEXT(EO7), VALUE(EO7), EO7) -> 0
A8: 020.708-00 | B8: 2022/0026670-001 | C8: FB | D8: 2022/0026670 | E8: DJE9491 | F8: 01/04/2026 | G8: 30/04/2026 | H8: ADILSON TOLEDO | I8: ADILSON TOLEDO | J8: NORMAL | K8: EMEE | L8: =CONTINUA!BV8 -> 0 | M8: =CONTINUA!BW8 -> 0 | O8: 6020.2022/0026670-0 | P8: 0 | EP8: =Q8 -> 0 | EQ8: =U8+Y8+AC8+AG8+AK8+AO8+AS8+AW8+BA8+BE8+BI8+BM8+BQ8+BU8+BY8+CC8+CG8+CK8+CO8+CS8+CW8+DA8+DE8+DI8+DM8+DQ8+DU8+DY8+EC8+EG8 -> 0 | ER8: =S8+W8+AA8+AE8+AI8+AM8+AQ8+AU8+AY8+BC8+BG8+BK8+BO8+BS8+BW8+CA8+CE8+CI8+CM8+CQ8+CU8+CY8+DC8+DG8+DK8+DO8+DS8+DW8+EA8+EE8+EI8 -> 0 | ES8: =R8 -> 0 | ET8: =V8+Z8+AD8+AH8+AL8+AP8+AT8+AX8+BB8+BF8+BJ8+BN8+BR8+BV8+BZ8+CD8+CH8+CL8+CP8+CT8+CX8+DB8+DF8+DJ8+DN8+DR8+DV8+DZ8+ED8+EH8 -> 0 | EU8: =T8+X8+AB8+AF8+AJ8+AN8+AR8+AV8+AZ8+BD8+BH8+BL8+BP8+BT8+BX8+CB8+CF8+CJ8+CN8+CR8+CV8+CZ8+DD8+DH8+DL8+DP8+DT8+DX8+EB8+EF8+EJ8 -> 0 | EV8: =EP8+EQ8+ES8+ET8+ER8+EU8 -> 0 | EX8: =FF8 -> 0 | EY8: =(L8*regular)+(M8*Cadeirantee) -> 0 | EZ8: =SUMIF(FG8:GJ8,">0") -> 0 | FA8: =SUMIF(FG8:GJ8,"<0")+SUMIF(GN8:HP8,"<0") -> 0 | FB8: 0 | FC8: =N8*km*'VALORES TABELA'!$B$13 -> 0 | FD8: =GL8 -> 0 | GL8: =IF(J8="ADAPTADO",T8*Cadeirante/30*GM8+S8*Percapita/30*GM8,IF(J8="NORMAL",(S8+T8)*Percapita/30*GM8,IF(J8="CRECHE",0)))*-1 -> 0 | HY8: =IF(ISTEXT(EM8), VALUE(EM8), EM8) -> 0 | HZ8: =IF(ISTEXT(EN8), VALUE(EN8), EN8) -> 0 | IA8: =IF(ISTEXT(EO8), VALUE(EO8), EO8) -> 0
A9: 020.708-00 | B9: 2022/0026670-001 | C9: FB | D9: 2022/0026670 | E9: DJE9491 | F9: 01/04/2026 | G9: 30/04/2026 | H9: ADILSON TOLEDO | I9: ADILSON TOLEDO | J9: NORMAL | K9: CEI | L9: =CONTINUA!BV9 -> 0 | M9: =CONTINUA!BW9 -> 0 | O9: 6020.2022/0026670-0 | P9: 0 | EP9: =Q9 -> 0 | EQ9: =U9+Y9+AC9+AG9+AK9+AO9+AS9+AW9+BA9+BE9+BI9+BM9+BQ9+BU9+BY9+CC9+CG9+CK9+CO9+CS9+CW9+DA9+DE9+DI9+DM9+DQ9+DU9+DY9+EC9+EG9 -> 0 | ER9: =S9+W9+AA9+AE9+AI9+AM9+AQ9+AU9+AY9+BC9+BG9+BK9+BO9+BS9+BW9+CA9+CE9+CI9+CM9+CQ9+CU9+CY9+DC9+DG9+DK9+DO9+DS9+DW9+EA9+EE9+EI9 -> 0 | ES9: =R9 -> 0 | ET9: =V9+Z9+AD9+AH9+AL9+AP9+AT9+AX9+BB9+BF9+BJ9+BN9+BR9+BV9+BZ9+CD9+CH9+CL9+CP9+CT9+CX9+DB9+DF9+DJ9+DN9+DR9+DV9+DZ9+ED9+EH9 -> 0 | EU9: =T9+X9+AB9+AF9+AJ9+AN9+AR9+AV9+AZ9+BD9+BH9+BL9+BP9+BT9+BX9+CB9+CF9+CJ9+CN9+CR9+CV9+CZ9+DD9+DH9+DL9+DP9+DT9+DX9+EB9+EF9+EJ9 -> 0 | EV9: =EP9+EQ9+ES9+ET9+ER9+EU9 -> 0 | EX9: =FF9 -> 0 | EY9: =(L9*regular)+(M9*Cadeirantee) -> 0 | EZ9: =SUMIF(FG9:GJ9,">0") -> 0 | FA9: =SUMIF(FG9:GJ9,"<0")+SUMIF(GN9:HP9,"<0") -> 0 | FB9: 0 | FC9: =N9*km*'VALORES TABELA'!$B$13 -> 0 | FD9: =GL9 -> 0 | GL9: =IF(J9="ADAPTADO",T9*Cadeirante/30*GM9+S9*Percapita/30*GM9,IF(J9="NORMAL",(S9+T9)*Percapita/30*GM9,IF(J9="CRECHE",0)))*-1 -> 0 | HY9: =IF(ISTEXT(EM9), VALUE(EM9), EM9) -> 0 | HZ9: =IF(ISTEXT(EN9), VALUE(EN9), EN9) -> 0 | IA9: =IF(ISTEXT(EO9), VALUE(EO9), EO9) -> 0
A10: 020.708-00 | B10: 2022/0026670-001 | C10: FB | D10: 2022/0026670 | E10: DJE9491 | F10: 01/04/2026 | G10: 30/04/2026 | H10: ADILSON TOLEDO | I10: ADILSON TOLEDO | J10: NORMAL | K10: CCA | L10: =CONTINUA!BV10 -> 0 | M10: =CONTINUA!BW10 -> 0 | O10: 6020.2022/0026670-0 | P10: 0 | EP10: =Q10 -> 0 | EQ10: =U10+Y10+AC10+AG10+AK10+AO10+AS10+AW10+BA10+BE10+BI10+BM10+BQ10+BU10+BY10+CC10+CG10+CK10+CO10+CS10+CW10+DA10+DE10+DI10+DM10+DQ10+DU10+DY10+EC10+EG10 -> 0 | ER10: =S10+W10+AA10+AE10+AI10+AM10+AQ10+AU10+AY10+BC10+BG10+BK10+BO10+BS10+BW10+CA10+CE10+CI10+CM10+CQ10+CU10+CY10+DC10+DG10+DK10+DO10+DS10+DW10+EA10+EE10+EI10 -> 0 | ES10: =R10 -> 0 | ET10: =V10+Z10+AD10+AH10+AL10+AP10+AT10+AX10+BB10+BF10+BJ10+BN10+BR10+BV10+BZ10+CD10+CH10+CL10+CP10+CT10+CX10+DB10+DF10+DJ10+DN10+DR10+DV10+DZ10+ED10+EH10 -> 0 | EU10: =T10+X10+AB10+AF10+AJ10+AN10+AR10+AV10+AZ10+BD10+BH10+BL10+BP10+BT10+BX10+CB10+CF10+CJ10+CN10+CR10+CV10+CZ10+DD10+DH10+DL10+DP10+DT10+DX10+EB10+EF10+EJ10 -> 0 | EV10: =EP10+EQ10+ES10+ET10+ER10+EU10 -> 0 | EX10: 0 | EY10: 0 | EZ10: 0 | FA10: 0 | FB10: =SUM(FF10:GI10)/2 -> 0 | FC10: =N10*km*'VALORES TABELA'!$B$13 -> 0 | FD10: =GL10 -> 0 | FF10: =((Q10+S10)*Percapita)+((R10+T10)*Cadeirante) -> 0 | FG10: =((U10+W10)*Percapita/30*FG$4)+((V10+X10)*Cadeirante/30*FG$4) -> 0 | FH10: =((Y10+AA10)*Percapita/30*FH$4)+((Z10+AB10)*Cadeirante/30*FH$4) -> 0 | FI10: =((AC10+AE10)*Percapita/30*FI$4)+((AD10+AF10)*Cadeirante/30*FI$4) -> 0 | FJ10: =((AG10+AI10)*Percapita/30*FJ$4)+((AH10+AJ10)*Cadeirante/30*FJ$4) -> 0 | FK10: =((AK10+AM10)*Percapita/30*FK$4)+((AL10+AN10)*Cadeirante/30*FK$4) -> 0 | FL10: =((AO10+AQ10)*Percapita/30*FL$4)+((AP10+AR10)*Cadeirante/30*FL$4) -> 0 | FM10: =((AS10+AU10)*Percapita/30*FM$4)+((AT10+AV10)*Cadeirante/30*FM$4) -> 0 | FN10: =((AW10+AY10)*Percapita/30*FN$4)+((AX10+AZ10)*Cadeirante/30*FN$4) -> 0 | FO10: =((BA10+BC10)*Percapita/30*FO$4)+((BB10+BD10)*Cadeirante/30*FO$4) -> 0 | FP10: =((BE10+BG10)*Percapita/30*FP$4)+((BF10+BH10)*Cadeirante/30*FP$4) -> 0 | FQ10: =((BI10+BK10)*Percapita/30*FQ$4)+((BJ10+BL10)*Cadeirante/30*FQ$4) -> 0 | FR10: =((BM10+BO10)*Percapita/30*FR$4)+((BN10+BP10)*Cadeirante/30*FR$4) -> 0 | FS10: =((BQ10+BS10)*Percapita/30*FS$4)+((BR10+BT10)*Cadeirante/30*FS$4) -> 0 | FT10: =((BU10+BW10)*Percapita/30*FT$4)+((BV10+BX10)*Cadeirante/30*FT$4) -> 0 | FU10: =((BY10+CA10)*Percapita/30*FU$4)+((BZ10+CB10)*Cadeirante/30*FU$4) -> 0 | FV10: =((CC10+CE10)*Percapita/30*FV$4)+((CD10+CF10)*Cadeirante/30*FV$4) -> 0 | FW10: =((CG10+CI10)*Percapita/30*FW$4)+((CI10+CK10)*Cadeirante/30*FW$4) -> 0 | FX10: =((CK10+CM10)*Percapita/30*FX$4)+((CL10+CN10)*Cadeirante/30*FX$4) -> 0 | FY10: =((CO10+CQ10)*Percapita/30*FY$4)+((CP10+CR10)*Cadeirante/30*FY$4) -> 0 | FZ10: =((CS10+CU10)*Percapita/30*FZ$4)+((CT10+CV10)*Cadeirante/30*FZ$4) -> 0 | GA10: =((CW10+CY10)*Percapita/30*GA$4)+((CX10+CZ10)*Cadeirante/30*GA$4) -> 0 | GB10: =((DA10+DC10)*Percapita/30*GB$4)+((DB10+DD10)*Cadeirante/30*GB$4) -> 0 | GC10: =((DE10+DG10)*Percapita/30*GC$4)+((DF10+DH10)*Cadeirante/30*GC$4) -> 0 | GD10: =((DI10+DK10)*Percapita/30*GD$4)+((DJ10+DL10)*Cadeirante/30*GD$4) -> 0 | GE10: =((DM10+DO10)*Percapita/30*GE$4)+((DN10+DP10)*Cadeirante/30*GE$4) -> 0 | GF10: =((DQ10+DS10)*Percapita/30*GF$4)+((DR10+DT10)*Cadeirante/30*GF$4) -> 0 | GG10: =((DU10+DW10)*Percapita/30*GG$4)+((DV10+DX10)*Cadeirante/30*GG$4) -> 0 | GH10: =((DY10+EA10)*Percapita/30*GH$4)+((DZ10+EB10)*Cadeirante/30*GH$4) -> 0 | GI10: =((EC10+EE10)*Percapita/30*GI$4)+((ED10+EF10)*Cadeirante/30*GI$4) -> 0 | GJ10: =((EG10+EI10)*Percapita)+((EH10+EJ10)*Cadeirante) -> 0 | GL10: =IF(J10="ADAPTADO",T10*Cadeirante/30*GM10+S10*Percapita/30*GM10,IF(J10="NORMAL",(S10+T10)*Percapita/30*GM10,IF(J10="CRECHE",0)))*-1 -> 0 | HY10: =IF(ISTEXT(EM10), VALUE(EM10), EM10) -> 0 | HZ10: =IF(ISTEXT(EN10), VALUE(EN10), EN10) -> 0 | IA10: =IF(ISTEXT(EO10), VALUE(EO10), EO10) -> 0
A11: 015.733-00 | B11: 2022/0027713-001B | C11: 4 | D11: 2022/0027713 | E11: ECM4497 | F11: 01/04/2026 | G11: 30/04/2026 | H11: ALEXANDRO CIRINO VIEIRA | I11: ALEXANDRO CIRINO VIEIRA | J11: NORMAL | K11: EMEI | L11: =CONTINUA!BV11 -> 0 | M11: =CONTINUA!BW11 -> 0 | O11: 6020.2022/0027713-2 | P11: 0 | EP11: =Q11 -> 0 | EQ11: =U11+Y11+AC11+AG11+AK11+AO11+AS11+AW11+BA11+BE11+BI11+BM11+BQ11+BU11+BY11+CC11+CG11+CK11+CO11+CS11+CW11+DA11+DE11+DI11+DM11+DQ11+DU11+DY11+EC11+EG11 -> 0 | ER11: =S11+W11+AA11+AE11+AI11+AM11+AQ11+AU11+AY11+BC11+BG11+BK11+BO11+BS11+BW11+CA11+CE11+CI11+CM11+CQ11+CU11+CY11+DC11+DG11+DK11+DO11+DS11+DW11+EA11+EE11+EI11 -> 0 | ES11: =R11 -> 0 | ET11: =V11+Z11+AD11+AH11+AL11+AP11+AT11+AX11+BB11+BF11+BJ11+BN11+BR11+BV11+BZ11+CD11+CH11+CL11+CP11+CT11+CX11+DB11+DF11+DJ11+DN11+DR11+DV11+DZ11+ED11+EH11 -> 0 | EU11: =T11+X11+AB11+AF11+AJ11+AN11+AR11+AV11+AZ11+BD11+BH11+BL11+BP11+BT11+BX11+CB11+CF11+CJ11+CN11+CR11+CV11+CZ11+DD11+DH11+DL11+DP11+DT11+DX11+EB11+EF11+EJ11 -> 0 | EV11: =EP11+EQ11+ES11+ET11+ER11+EU11 -> 0 | EW11: =IF(C11=4,IF(MAX(Q11:EJ13)>0,(Especiall/30*(IF(($G11-$F11)=($G$5-$F$5),30,IF(DAY($G11)=31,($G11-$F11),($G11-$F11)+1)))),0),0) -> 11465.63 | EX11: =FF11 -> 1155.69 | EY11: =(L11*regular)+(M11*Cadeirantee) -> 0 | EZ11: =SUMIF(FG11:GJ11,">0") -> 0 | FA11: =SUMIF(FG11:GJ11,"<0")+SUMIF(GN11:HP11,"<0") -> 0 | FB11: 0 | FC11: =N11*km*'VALORES TABELA'!$B$13 -> 0 | FD11: =GL11 -> 0 | FE11: =(EW11+EW12+EW13+EW14+EX11+EX12+EX13+EX14+EY11+EY12+EY13+EY14+EY15+EZ11+EZ12+EZ13+EZ14+FA11+FA12+FA13+FA14+FC11+FC12+FC13+FC14+HY11-HZ11-IA11+FD11+FD12+FD13+FD14+FB15) -> 12852.68 | FF11: =IF(C11=4,SUM(Q11+Q12+Q13+S11+S12+S13)*Percapita/30*FF$4+(R11+R12+R13+T11+T12+T13)*Cadeirante/30*FF$4,IF(C11=3,IF(Q14+S14=10,Fixo/30*FF$4+(Q11+Q12+Q13+S11+S12+S13)*Percapita/30*FF$4+(R14+T14)*Cadeirante/30*FF$4,IF(Q14+S14<=9,(Q14+S14)*Crechee/30*FF$4)+(R14+T14)*Cadeirante/30*FF$4+(Q11+Q12+Q13+S11+S12+S13)*Percapita/30*FF$4)+IF(Q14+S14>=11,Fixo/30*FF$4+(Q14+S14-10)*Crechee/30*FF$4,0),IF(C11=2,IF(R11+R12+R13+R14+T11+T12+T13+T14=1,Cadeirante/30*FF$4,IF(R11+R12+R13+R14+T11+T12+T13+T14=2,Fixo/30*FF$4,IF(R11+R12+R13+R14+T11+T12+T13+T14>2,Fixo/30*FF$4+(R11+R12+R13+R14+T11+T12+T13+T14-2)*Cadeirante/30*FF$4)))+(Q11+Q12+Q13+S11+S12+S13)*Percapita/30*FF$4+(Q14+S14)*Crechee/30*FF$4,IF(C11=1,IF(Q11+Q12+Q13+R11+R12+R13+S11+S12+S13+T11+T12+T13<=15,(Q11+Q12+Q13+S11+S12+S13)*Percapita/30*FF$4,IF(Q11+Q12+Q13+R11+R12+R13+S11+S12+S13+T11+T12+T13>=16,Fixo/30*FF$4+(Q11+Q12+Q13+R11+R12+R13+S11+S12+S13+T11+T12-16)*Percapita/30*FF$4)))))) -> 1155.69 | FG11: =IF(C11=4,SUM(U11+U12+U13+W11+W12+W13)*Percapita/30*FG$4+(V11+V12+V13+X11+X12+X13)*Cadeirante/30*FG$4,IF(C11=3,IF(U14+W14=10,Fixo/30*FG$4+(U11+U12+U13+W11+W12+W13)*Percapita/30*FG$4+(V14+X14)*Cadeirante/30*FG$4,IF(U14+W14<=9,(U14+W14)*Crechee/30*FG$4)+(V14+X14)*Cadeirante/30*FG$4+(U11+U12+U13+W11+W12+W13)*Percapita/30*FG$4)+IF(U14+W14>=11,Fixo/30*FG$4+(U14+W14-10)*Crechee/30*FG$4,0),IF(C11=2,IF(V11+V12+V13+V14+X11+X12+X13+X14=1,Cadeirante/30*FG$4,IF(V11+V12+V13+V14+X11+X12+X13+X14=2,Fixo/30*FG$4,IF(V11+V12+V13+V14+X11+X12+X13+X14>2,Fixo/30*FG$4+(V11+V12+V13+V14+X11+X12+X13+X14-2)*Cadeirante/30*FG$4)))+(U11+U12+U13+W11+W12+W13)*Percapita/30*FG$4+(U14+W14)*Crechee/30*FG$4,IF(C11=1,IF(U11+U12+U13+V11+V12+V13+W11+W12+W13+X11+X12+X13<=15,(U11+U12+U13+W11+W12+W13)*Percapita/30*FG$4,IF(U11+U12+U13+V11+V12+V13+W11+W12+W13+X11+X12+X13>=16,Fixo/30*FG$4+(U11+U12+U13+V11+V12+V13+W11+W12+W13+X11+X12-16)*Percapita/30*FG$4)))))) -> 0 | FH11: =IF(C11=4,SUM(Y11+Y12+Y13+AA11+AA12+AA13)*Percapita/30*FH$4+(Z11+Z12+Z13+AB11+AB12+AB13)*Cadeirante/30*FH$4,IF(C11=3,IF(Y14+AA14=10,Fixo/30*FH$4+(Y11+Y12+Y13+AA11+AA12+AA13)*Percapita/30*FH$4+(Z14+AB14)*Cadeirante/30*FH$4,IF(Y14+AA14<=9,(Y14+AA14)*Crechee/30*FH$4)+(Z14+AB14)*Cadeirante/30*FH$4+(Y11+Y12+Y13+AA11+AA12+AA13)*Percapita/30*FH$4)+IF(Y14+AA14>=11,Fixo/30*FH$4+(Y14+AA14-10)*Crechee/30*FH$4,0),IF(C11=2,IF(Z11+Z12+Z13+Z14+AB11+AB12+AB13+AB14=1,Cadeirante/30*FH$4,IF(Z11+Z12+Z13+Z14+AB11+AB12+AB13+AB14=2,Fixo/30*FH$4,IF(Z11+Z12+Z13+Z14+AB11+AB12+AB13+AB14>2,Fixo/30*FH$4+(Z11+Z12+Z13+Z14+AB11+AB12+AB13+AB14-2)*Cadeirante/30*FH$4)))+(Y11+Y12+Y13+AA11+AA12+AA13)*Percapita/30*FH$4+(Y14+AA14)*Crechee/30*FH$4,IF(C11=1,IF(Y11+Y12+Y13+Z11+Z12+Z13+AA11+AA12+AA13+AB11+AB12+AB13<=15,(Y11+Y12+Y13+AA11+AA12+AA13)*Percapita/30*FH$4,IF(Y11+Y12+Y13+Z11+Z12+Z13+AA11+AA12+AA13+AB11+AB12+AB13>=16,Fixo/30*FH$4+(Y11+Y12+Y13+Z11+Z12+Z13+AA11+AA12+AA13+AB11+AB12-16)*Percapita/30*FH$4)))))) -> 0 | FI11: =IF(C11=4,SUM(AC11+AC12+AC13+AE11+AE12+AE13)*Percapita/30*FI$4+(AD11+AD12+AD13+AF11+AF12+AF13)*Cadeirante/30*FI$4,IF(C11=3,IF(AC14+AE14=10,Fixo/30*FI$4+(AC11+AC12+AC13+AE11+AE12+AE13)*Percapita/30*FI$4+(AD14+AF14)*Cadeirante/30*FI$4,IF(AC14+AE14<=9,(AC14+AE14)*Crechee/30*FI$4)+(AD14+AF14)*Cadeirante/30*FI$4+(AC11+AC12+AC13+AE11+AE12+AE13)*Percapita/30*FI$4)+IF(AC14+AE14>=11,Fixo/30*FI$4+(AC14+AE14-10)*Crechee/30*FI$4,0),IF(C11=2,IF(AD11+AD12+AD13+AD14+AF11+AF12+AF13+AF14=1,Cadeirante/30*FI$4,IF(AD11+AD12+AD13+AD14+AF11+AF12+AF13+AF14=2,Fixo/30*FI$4,IF(AD11+AD12+AD13+AD14+AF11+AF12+AF13+AF14>2,Fixo/30*FI$4+(AD11+AD12+AD13+AD14+AF11+AF12+AF13+AF14-2)*Cadeirante/30*FI$4)))+(AC11+AC12+AC13+AE11+AE12+AE13)*Percapita/30*FI$4+(AC14+AE14)*Crechee/30*FI$4,IF(C11=1,IF(AC11+AC12+AC13+AD11+AD12+AD13+AE11+AE12+AE13+AF11+AF12+AF13<=15,(AC11+AC12+AC13+AE11+AE12+AE13)*Percapita/30*FI$4,IF(AC11+AC12+AC13+AD11+AD12+AD13+AE11+AE12+AE13+AF11+AF12+AF13>=16,Fixo/30*FI$4+(AC11+AC12+AC13+AD11+AD12+AD13+AE11+AE12+AE13+AF11+AF12-16)*Percapita/30*FI$4)))))) -> 0 | FJ11: =IF(C11=4,SUM(AG11+AG12+AG13+AI11+AI12+AI13)*Percapita/30*FJ$4+(AH11+AH12+AH13+AJ11+AJ12+AJ13)*Cadeirante/30*FJ$4,IF(C11=3,IF(AG14+AI14=10,Fixo/30*FJ$4+(AG11+AG12+AG13+AI11+AI12+AI13)*Percapita/30*FJ$4+(AH14+AJ14)*Cadeirante/30*FJ$4,IF(AG14+AI14<=9,(AG14+AI14)*Crechee/30*FJ$4)+(AH14+AJ14)*Cadeirante/30*FJ$4+(AG11+AG12+AG13+AI11+AI12+AI13)*Percapita/30*FJ$4)+IF(AG14+AI14>=11,Fixo/30*FJ$4+(AG14+AI14-10)*Crechee/30*FJ$4,0),IF(C11=2,IF(AH11+AH12+AH13+AH14+AJ11+AJ12+AJ13+AJ14=1,Cadeirante/30*FJ$4,IF(AH11+AH12+AH13+AH14+AJ11+AJ12+AJ13+AJ14=2,Fixo/30*FJ$4,IF(AH11+AH12+AH13+AH14+AJ11+AJ12+AJ13+AJ14>2,Fixo/30*FJ$4+(AH11+AH12+AH13+AH14+AJ11+AJ12+AJ13+AJ14-2)*Cadeirante/30*FJ$4)))+(AG11+AG12+AG13+AI11+AI12+AI13)*Percapita/30*FJ$4+(AG14+AI14)*Crechee/30*FJ$4,IF(C11=1,IF(AG11+AG12+AG13+AH11+AH12+AH13+AI11+AI12+AI13+AJ11+AJ12+AJ13<=15,(AG11+AG12+AG13+AI11+AI12+AI13)*Percapita/30*FJ$4,IF(AG11+AG12+AG13+AH11+AH12+AH13+AI11+AI12+AI13+AJ11+AJ12+AJ13>=16,Fixo/30*FJ$4+(AG11+AG12+AG13+AH11+AH12+AH13+AI11+AI12+AI13+AJ11+AJ12-16)*Percapita/30*FJ$4)))))) -> 0 | FK11: =IF(C11=4,SUM(AK11+AK12+AK13+AM11+AM12+AM13)*Percapita/30*FK$4+(AL11+AL12+AL13+AN11+AN12+AN13)*Cadeirante/30*FK$4,IF(C11=3,IF(AK14+AM14=10,Fixo/30*FK$4+(AK11+AK12+AK13+AM11+AM12+AM13)*Percapita/30*FK$4+(AL14+AN14)*Cadeirante/30*FK$4,IF(AK14+AM14<=9,(AK14+AM14)*Crechee/30*FK$4)+(AL14+AN14)*Cadeirante/30*FK$4+(AK11+AK12+AK13+AM11+AM12+AM13)*Percapita/30*FK$4)+IF(AK14+AM14>=11,Fixo/30*FK$4+(AK14+AM14-10)*Crechee/30*FK$4,0),IF(C11=2,IF(AL11+AL12+AL13+AL14+AN11+AN12+AN13+AN14=1,Cadeirante/30*FK$4,IF(AL11+AL12+AL13+AL14+AN11+AN12+AN13+AN14=2,Fixo/30*FK$4,IF(AL11+AL12+AL13+AL14+AN11+AN12+AN13+AN14>2,Fixo/30*FK$4+(AL11+AL12+AL13+AL14+AN11+AN12+AN13+AN14-2)*Cadeirante/30*FK$4)))+(AK11+AK12+AK13+AM11+AM12+AM13)*Percapita/30*FK$4+(AK14+AM14)*Crechee/30*FK$4,IF(C11=1,IF(AK11+AK12+AK13+AL11+AL12+AL13+AM11+AM12+AM13+AN11+AN12+AN13<=15,(AK11+AK12+AK13+AM11+AM12+AM13)*Percapita/30*FK$4,IF(AK11+AK12+AK13+AL11+AL12+AL13+AM11+AM12+AM13+AN11+AN12+AN13>=16,Fixo/30*FK$4+(AK11+AK12+AK13+AL11+AL12+AL13+AM11+AM12+AM13+AN11+AN12-16)*Percapita/30*FK$4)))))) -> 0 | FL11: =IF(C11=4,SUM(AO11+AO12+AO13+AQ11+AQ12+AQ13)*Percapita/30*FL$4+(AP11+AP12+AP13+AR11+AR12+AR13)*Cadeirante/30*FL$4,IF(C11=3,IF(AO14+AQ14=10,Fixo/30*FL$4+(AO11+AO12+AO13+AQ11+AQ12+AQ13)*Percapita/30*FL$4+(AP14+AR14)*Cadeirante/30*FL$4,IF(AO14+AQ14<=9,(AO14+AQ14)*Crechee/30*FL$4)+(AP14+AR14)*Cadeirante/30*FL$4+(AO11+AO12+AO13+AQ11+AQ12+AQ13)*Percapita/30*FL$4)+IF(AO14+AQ14>=11,Fixo/30*FL$4+(AO14+AQ14-10)*Crechee/30*FL$4,0),IF(C11=2,IF(AP11+AP12+AP13+AP14+AR11+AR12+AR13+AR14=1,Cadeirante/30*FL$4,IF(AP11+AP12+AP13+AP14+AR11+AR12+AR13+AR14=2,Fixo/30*FL$4,IF(AP11+AP12+AP13+AP14+AR11+AR12+AR13+AR14>2,Fixo/30*FL$4+(AP11+AP12+AP13+AP14+AR11+AR12+AR13+AR14-2)*Cadeirante/30*FL$4)))+(AO11+AO12+AO13+AQ11+AQ12+AQ13)*Percapita/30*FL$4+(AO14+AQ14)*Crechee/30*FL$4,IF(C11=1,IF(AO11+AO12+AO13+AP11+AP12+AP13+AQ11+AQ12+AQ13+AR11+AR12+AR13<=15,(AO11+AO12+AO13+AQ11+AQ12+AQ13)*Percapita/30*FL$4,IF(AO11+AO12+AO13+AP11+AP12+AP13+AQ11+AQ12+AQ13+AR11+AR12+AR13>=16,Fixo/30*FL$4+(AO11+AO12+AO13+AP11+AP12+AP13+AQ11+AQ12+AQ13+AR11+AR12-16)*Percapita/30*FL$4)))))) -> 0 | FM11: =IF(C11=4,SUM(AS11+AS12+AS13+AU11+AU12+AU13)*Percapita/30*FM$4+(AT11+AT12+AT13+AV11+AV12+AV13)*Cadeirante/30*FM$4,IF(C11=3,IF(AS14+AU14=10,Fixo/30*FM$4+(AS11+AS12+AS13+AU11+AU12+AU13)*Percapita/30*FM$4+(AT14+AV14)*Cadeirante/30*FM$4,IF(AS14+AU14<=9,(AS14+AU14)*Crechee/30*FM$4)+(AT14+AV14)*Cadeirante/30*FM$4+(AS11+AS12+AS13+AU11+AU12+AU13)*Percapita/30*FM$4)+IF(AS14+AU14>=11,Fixo/30*FM$4+(AS14+AU14-10)*Crechee/30*FM$4,0),IF(C11=2,IF(AT11+AT12+AT13+AT14+AV11+AV12+AV13+AV14=1,Cadeirante/30*FM$4,IF(AT11+AT12+AT13+AT14+AV11+AV12+AV13+AV14=2,Fixo/30*FM$4,IF(AT11+AT12+AT13+AT14+AV11+AV12+AV13+AV14>2,Fixo/30*FM$4+(AT11+AT12+AT13+AT14+AV11+AV12+AV13+AV14-2)*Cadeirante/30*FM$4)))+(AS11+AS12+AS13+AU11+AU12+AU13)*Percapita/30*FM$4+(AS14+AU14)*Crechee/30*FM$4,IF(C11=1,IF(AS11+AS12+AS13+AT11+AT12+AT13+AU11+AU12+AU13+AV11+AV12+AV13<=15,(AS11+AS12+AS13+AU11+AU12+AU13)*Percapita/30*FM$4,IF(AS11+AS12+AS13+AT11+AT12+AT13+AU11+AU12+AU13+AV11+AV12+AV13>=16,Fixo/30*FM$4+(AS11+AS12+AS13+AT11+AT12+AT13+AU11+AU12+AU13+AV11+AV12-16)*Percapita/30*FM$4)))))) -> 0 | FN11: =IF(C11=4,SUM(AW11+AW12+AW13+AY11+AY12+AY13)*Percapita/30*FN$4+(AX11+AX12+AX13+AZ11+AZ12+AZ13)*Cadeirante/30*FN$4,IF(C11=3,IF(AW14+AY14=10,Fixo/30*FN$4+(AW11+AW12+AW13+AY11+AY12+AY13)*Percapita/30*FN$4+(AX14+AZ14)*Cadeirante/30*FN$4,IF(AW14+AY14<=9,(AW14+AY14)*Crechee/30*FN$4)+(AX14+AZ14)*Cadeirante/30*FN$4+(AW11+AW12+AW13+AY11+AY12+AY13)*Percapita/30*FN$4)+IF(AW14+AY14>=11,Fixo/30*FN$4+(AW14+AY14-10)*Crechee/30*FN$4,0),IF(C11=2,IF(AX11+AX12+AX13+AX14+AZ11+AZ12+AZ13+AZ14=1,Cadeirante/30*FN$4,IF(AX11+AX12+AX13+AX14+AZ11+AZ12+AZ13+AZ14=2,Fixo/30*FN$4,IF(AX11+AX12+AX13+AX14+AZ11+AZ12+AZ13+AZ14>2,Fixo/30*FN$4+(AX11+AX12+AX13+AX14+AZ11+AZ12+AZ13+AZ14-2)*Cadeirante/30*FN$4)))+(AW11+AW12+AW13+AY11+AY12+AY13)*Percapita/30*FN$4+(AW14+AY14)*Crechee/30*FN$4,IF(C11=1,IF(AW11+AW12+AW13+AX11+AX12+AX13+AY11+AY12+AY13+AZ11+AZ12+AZ13<=15,(AW11+AW12+AW13+AY11+AY12+AY13)*Percapita/30*FN$4,IF(AW11+AW12+AW13+AX11+AX12+AX13+AY11+AY12+AY13+AZ11+AZ12+AZ13>=16,Fixo/30*FN$4+(AW11+AW12+AW13+AX11+AX12+AX13+AY11+AY12+AY13+AZ11+AZ12-16)*Percapita/30*FN$4)))))) -> 0 | FO11: =IF(C11=4,SUM(BA11+BA12+BA13+BC11+BC12+BC13)*Percapita/30*FO$4+(BB11+BB12+BB13+BD11+BD12+BD13)*Cadeirante/30*FO$4,IF(C11=3,IF(BA14+BC14=10,Fixo/30*FO$4+(BA11+BA12+BA13+BC11+BC12+BC13)*Percapita/30*FO$4+(BB14+BD14)*Cadeirante/30*FO$4,IF(BA14+BC14<=9,(BA14+BC14)*Crechee/30*FO$4)+(BB14+BD14)*Cadeirante/30*FO$4+(BA11+BA12+BA13+BC11+BC12+BC13)*Percapita/30*FO$4)+IF(BA14+BC14>=11,Fixo/30*FO$4+(BA14+BC14-10)*Crechee/30*FO$4,0),IF(C11=2,IF(BB11+BB12+BB13+BB14+BD11+BD12+BD13+BD14=1,Cadeirante/30*FO$4,IF(BB11+BB12+BB13+BB14+BD11+BD12+BD13+BD14=2,Fixo/30*FO$4,IF(BB11+BB12+BB13+BB14+BD11+BD12+BD13+BD14>2,Fixo/30*FO$4+(BB11+BB12+BB13+BB14+BD11+BD12+BD13+BD14-2)*Cadeirante/30*FO$4)))+(BA11+BA12+BA13+BC11+BC12+BC13)*Percapita/30*FO$4+(BA14+BC14)*Crechee/30*FO$4,IF(C11=1,IF(BA11+BA12+BA13+BB11+BB12+BB13+BC11+BC12+BC13+BD11+BD12+BD13<=15,(BA11+BA12+BA13+BC11+BC12+BC13)*Percapita/30*FO$4,IF(BA11+BA12+BA13+BB11+BB12+BB13+BC11+BC12+BC13+BD11+BD12+BD13>=16,Fixo/30*FO$4+(BA11+BA12+BA13+BB11+BB12+BB13+BC11+BC12+BC13+BD11+BD12-16)*Percapita/30*FO$4)))))) -> 0 | FP11: =IF(C11=4,SUM(BE11+BE12+BE13+BG11+BG12+BG13)*Percapita/30*FP$4+(BF11+BF12+BF13+BH11+BH12+BH13)*Cadeirante/30*FP$4,IF(C11=3,IF(BE14+BG14=10,Fixo/30*FP$4+(BE11+BE12+BE13+BG11+BG12+BG13)*Percapita/30*FP$4+(BF14+BH14)*Cadeirante/30*FP$4,IF(BE14+BG14<=9,(BE14+BG14)*Crechee/30*FP$4)+(BF14+BH14)*Cadeirante/30*FP$4+(BE11+BE12+BE13+BG11+BG12+BG13)*Percapita/30*FP$4)+IF(BE14+BG14>=11,Fixo/30*FP$4+(BE14+BG14-10)*Crechee/30*FP$4,0),IF(C11=2,IF(BF11+BF12+BF13+BF14+BH11+BH12+BH13+BH14=1,Cadeirante/30*FP$4,IF(BF11+BF12+BF13+BF14+BH11+BH12+BH13+BH14=2,Fixo/30*FP$4,IF(BF11+BF12+BF13+BF14+BH11+BH12+BH13+BH14>2,Fixo/30*FP$4+(BF11+BF12+BF13+BF14+BH11+BH12+BH13+BH14-2)*Cadeirante/30*FP$4)))+(BE11+BE12+BE13+BG11+BG12+BG13)*Percapita/30*FP$4+(BE14+BG14)*Crechee/30*FP$4,IF(C11=1,IF(BE11+BE12+BE13+BF11+BF12+BF13+BG11+BG12+BG13+BH11+BH12+BH13<=15,(BE11+BE12+BE13+BG11+BG12+BG13)*Percapita/30*FP$4,IF(BE11+BE12+BE13+BF11+BF12+BF13+BG11+BG12+BG13+BH11+BH12+BH13>=16,Fixo/30*FP$4+(BE11+BE12+BE13+BF11+BF12+BF13+BG11+BG12+BG13+BH11+BH12-16)*Percapita/30*FP$4)))))) -> 0 | FQ11: =IF(C11=4,SUM(BI11+BI12+BI13+BK11+BK12+BK13)*Percapita/30*FQ$4+(BJ11+BJ12+BJ13+BL11+BL12+BL13)*Cadeirante/30*FQ$4,IF(C11=3,IF(BI14+BK14=10,Fixo/30*FQ$4+(BI11+BI12+BI13+BK11+BK12+BK13)*Percapita/30*FQ$4+(BJ14+BL14)*Cadeirante/30*FQ$4,IF(BI14+BK14<=9,(BI14+BK14)*Crechee/30*FQ$4)+(BJ14+BL14)*Cadeirante/30*FQ$4+(BI11+BI12+BI13+BK11+BK12+BK13)*Percapita/30*FQ$4)+IF(BI14+BK14>=11,Fixo/30*FQ$4+(BI14+BK14-10)*Crechee/30*FQ$4,0),IF(C11=2,IF(BJ11+BJ12+BJ13+BJ14+BL11+BL12+BL13+BL14=1,Cadeirante/30*FQ$4,IF(BJ11+BJ12+BJ13+BJ14+BL11+BL12+BL13+BL14=2,Fixo/30*FQ$4,IF(BJ11+BJ12+BJ13+BJ14+BL11+BL12+BL13+BL14>2,Fixo/30*FQ$4+(BJ11+BJ12+BJ13+BJ14+BL11+BL12+BL13+BL14-2)*Cadeirante/30*FQ$4)))+(BI11+BI12+BI13+BK11+BK12+BK13)*Percapita/30*FQ$4+(BI14+BK14)*Crechee/30*FQ$4,IF(C11=1,IF(BI11+BI12+BI13+BJ11+BJ12+BJ13+BK11+BK12+BK13+BL11+BL12+BL13<=15,(BI11+BI12+BI13+BK11+BK12+BK13)*Percapita/30*FQ$4,IF(BI11+BI12+BI13+BJ11+BJ12+BJ13+BK11+BK12+BK13+BL11+BL12+BL13>=16,Fixo/30*FQ$4+(BI11+BI12+BI13+BJ11+BJ12+BJ13+BK11+BK12+BK13+BL11+BL12-16)*Percapita/30*FQ$4)))))) -> 0 | FR11: =IF(C11=4,SUM(BM11+BM12+BM13+BO11+BO12+BO13)*Percapita/30*FR$4+(BN11+BN12+BN13+BP11+BP12+BP13)*Cadeirante/30*FR$4,IF(C11=3,IF(BM14+BO14=10,Fixo/30*FR$4+(BM11+BM12+BM13+BO11+BO12+BO13)*Percapita/30*FR$4+(BN14+BP14)*Cadeirante/30*FR$4,IF(BM14+BO14<=9,(BM14+BO14)*Crechee/30*FR$4)+(BN14+BP14)*Cadeirante/30*FR$4+(BM11+BM12+BM13+BO11+BO12+BO13)*Percapita/30*FR$4)+IF(BM14+BO14>=11,Fixo/30*FR$4+(BM14+BO14-10)*Crechee/30*FR$4,0),IF(C11=2,IF(BN11+BN12+BN13+BN14+BP11+BP12+BP13+BP14=1,Cadeirante/30*FR$4,IF(BN11+BN12+BN13+BN14+BP11+BP12+BP13+BP14=2,Fixo/30*FR$4,IF(BN11+BN12+BN13+BN14+BP11+BP12+BP13+BP14>2,Fixo/30*FR$4+(BN11+BN12+BN13+BN14+BP11+BP12+BP13+BP14-2)*Cadeirante/30*FR$4)))+(BM11+BM12+BM13+BO11+BO12+BO13)*Percapita/30*FR$4+(BM14+BO14)*Crechee/30*FR$4,IF(C11=1,IF(BM11+BM12+BM13+BN11+BN12+BN13+BO11+BO12+BO13+BP11+BP12+BP13<=15,(BM11+BM12+BM13+BO11+BO12+BO13)*Percapita/30*FR$4,IF(BM11+BM12+BM13+BN11+BN12+BN13+BO11+BO12+BO13+BP11+BP12+BP13>=16,Fixo/30*FR$4+(BM11+BM12+BM13+BN11+BN12+BN13+BO11+BO12+BO13+BP11+BP12-16)*Percapita/30*FR$4)))))) -> 0 | FS11: =IF(C11=4,SUM(BQ11+BQ12+BQ13+BS11+BS12+BS13)*Percapita/30*FS$4+(BR11+BR12+BR13+BT11+BT12+BT13)*Cadeirante/30*FS$4,IF(C11=3,IF(BQ14+BS14=10,Fixo/30*FS$4+(BQ11+BQ12+BQ13+BS11+BS12+BS13)*Percapita/30*FS$4+(BR14+BT14)*Cadeirante/30*FS$4,IF(BQ14+BS14<=9,(BQ14+BS14)*Crechee/30*FS$4)+(BR14+BT14)*Cadeirante/30*FS$4+(BQ11+BQ12+BQ13+BS11+BS12+BS13)*Percapita/30*FS$4)+IF(BQ14+BS14>=11,Fixo/30*FS$4+(BQ14+BS14-10)*Crechee/30*FS$4,0),IF(C11=2,IF(BR11+BR12+BR13+BR14+BT11+BT12+BT13+BT14=1,Cadeirante/30*FS$4,IF(BR11+BR12+BR13+BR14+BT11+BT12+BT13+BT14=2,Fixo/30*FS$4,IF(BR11+BR12+BR13+BR14+BT11+BT12+BT13+BT14>2,Fixo/30*FS$4+(BR11+BR12+BR13+BR14+BT11+BT12+BT13+BT14-2)*Cadeirante/30*FS$4)))+(BQ11+BQ12+BQ13+BS11+BS12+BS13)*Percapita/30*FS$4+(BQ14+BS14)*Crechee/30*FS$4,IF(C11=1,IF(BQ11+BQ12+BQ13+BR11+BR12+BR13+BS11+BS12+BS13+BT11+BT12+BT13<=15,(BQ11+BQ12+BQ13+BS11+BS12+BS13)*Percapita/30*FS$4,IF(BQ11+BQ12+BQ13+BR11+BR12+BR13+BS11+BS12+BS13+BT11+BT12+BT13>=16,Fixo/30*FS$4+(BQ11+BQ12+BQ13+BR11+BR12+BR13+BS11+BS12+BS13+BT11+BT12-16)*Percapita/30*FS$4)))))) -> 0 | FT11: =IF(C11=4,SUM(BU11+BU12+BU13+BW11+BW12+BW13)*Percapita/30*FT$4+(BV11+BV12+BV13+BX11+BX12+BX13)*Cadeirante/30*FT$4,IF(C11=3,IF(BU14+BW14=10,Fixo/30*FT$4+(BU11+BU12+BU13+BW11+BW12+BW13)*Percapita/30*FT$4+(BV14+BX14)*Cadeirante/30*FT$4,IF(BU14+BW14<=9,(BU14+BW14)*Crechee/30*FT$4)+(BV14+BX14)*Cadeirante/30*FT$4+(BU11+BU12+BU13+BW11+BW12+BW13)*Percapita/30*FT$4)+IF(BU14+BW14>=11,Fixo/30*FT$4+(BU14+BW14-10)*Crechee/30*FT$4,0),IF(C11=2,IF(BV11+BV12+BV13+BV14+BX11+BX12+BX13+BX14=1,Cadeirante/30*FT$4,IF(BV11+BV12+BV13+BV14+BX11+BX12+BX13+BX14=2,Fixo/30*FT$4,IF(BV11+BV12+BV13+BV14+BX11+BX12+BX13+BX14>2,Fixo/30*FT$4+(BV11+BV12+BV13+BV14+BX11+BX12+BX13+BX14-2)*Cadeirante/30*FT$4)))+(BU11+BU12+BU13+BW11+BW12+BW13)*Percapita/30*FT$4+(BU14+BW14)*Crechee/30*FT$4,IF(C11=1,IF(BU11+BU12+BU13+BV11+BV12+BV13+BW11+BW12+BW13+BX11+BX12+BX13<=15,(BU11+BU12+BU13+BW11+BW12+BW13)*Percapita/30*FT$4,IF(BU11+BU12+BU13+BV11+BV12+BV13+BW11+BW12+BW13+BX11+BX12+BX13>=16,Fixo/30*FT$4+(BU11+BU12+BU13+BV11+BV12+BV13+BW11+BW12+BW13+BX11+BX12-16)*Percapita/30*FT$4)))))) -> 0 | FU11: =IF(C11=4,SUM(BY11+BY12+BY13+CA11+CA12+CA13)*Percapita/30*FU$4+(BZ11+BZ12+BZ13+CB11+CB12+CB13)*Cadeirante/30*FU$4,IF(C11=3,IF(BY14+CA14=10,Fixo/30*FU$4+(BY11+BY12+BY13+CA11+CA12+CA13)*Percapita/30*FU$4+(BZ14+CB14)*Cadeirante/30*FU$4,IF(BY14+CA14<=9,(BY14+CA14)*Crechee/30*FU$4)+(BZ14+CB14)*Cadeirante/30*FU$4+(BY11+BY12+BY13+CA11+CA12+CA13)*Percapita/30*FU$4)+IF(BY14+CA14>=11,Fixo/30*FU$4+(BY14+CA14-10)*Crechee/30*FU$4,0),IF(C11=2,IF(BZ11+BZ12+BZ13+BZ14+CB11+CB12+CB13+CB14=1,Cadeirante/30*FU$4,IF(BZ11+BZ12+BZ13+BZ14+CB11+CB12+CB13+CB14=2,Fixo/30*FU$4,IF(BZ11+BZ12+BZ13+BZ14+CB11+CB12+CB13+CB14>2,Fixo/30*FU$4+(BZ11+BZ12+BZ13+BZ14+CB11+CB12+CB13+CB14-2)*Cadeirante/30*FU$4)))+(BY11+BY12+BY13+CA11+CA12+CA13)*Percapita/30*FU$4+(BY14+CA14)*Crechee/30*FU$4,IF(C11=1,IF(BY11+BY12+BY13+BZ11+BZ12+BZ13+CA11+CA12+CA13+CB11+CB12+CB13<=15,(BY11+BY12+BY13+CA11+CA12+CA13)*Percapita/30*FU$4,IF(BY11+BY12+BY13+BZ11+BZ12+BZ13+CA11+CA12+CA13+CB11+CB12+CB13>=16,Fixo/30*FU$4+(BY11+BY12+BY13+BZ11+BZ12+BZ13+CA11+CA12+CA13+CB11+CB12-16)*Percapita/30*FU$4)))))) -> 0 | FV11: =IF(C11=4,SUM(CC11+CC12+CC13+CE11+CE12+CE13)*Percapita/30*FV$4+(CD11+CD12+CD13+CF11+CF12+CF13)*Cadeirante/30*FV$4,IF(C11=3,IF(CC14+CE14=10,Fixo/30*FV$4+(CC11+CC12+CC13+CE11+CE12+CE13)*Percapita/30*FV$4+(CD14+CF14)*Cadeirante/30*FV$4,IF(CC14+CE14<=9,(CC14+CE14)*Crechee/30*FV$4)+(CD14+CF14)*Cadeirante/30*FV$4+(CC11+CC12+CC13+CE11+CE12+CE13)*Percapita/30*FV$4)+IF(CC14+CE14>=11,Fixo/30*FV$4+(CC14+CE14-10)*Crechee/30*FV$4,0),IF(C11=2,IF(CD11+CD12+CD13+CD14+CF11+CF12+CF13+CF14=1,Cadeirante/30*FV$4,IF(CD11+CD12+CD13+CD14+CF11+CF12+CF13+CF14=2,Fixo/30*FV$4,IF(CD11+CD12+CD13+CD14+CF11+CF12+CF13+CF14>2,Fixo/30*FV$4+(CD11+CD12+CD13+CD14+CF11+CF12+CF13+CF14-2)*Cadeirante/30*FV$4)))+(CC11+CC12+CC13+CE11+CE12+CE13)*Percapita/30*FV$4+(CC14+CE14)*Crechee/30*FV$4,IF(C11=1,IF(CC11+CC12+CC13+CD11+CD12+CD13+CE11+CE12+CE13+CF11+CF12+CF13<=15,(CC11+CC12+CC13+CE11+CE12+CE13)*Percapita/30*FV$4,IF(CC11+CC12+CC13+CD11+CD12+CD13+CE11+CE12+CE13+CF11+CF12+CF13>=16,Fixo/30*FV$4+(CC11+CC12+CC13+CD11+CD12+CD13+CE11+CE12+CE13+CF11+CF12-16)*Percapita/30*FV$4)))))) -> 0 | FW11: =IF(C11=4,SUM(CG11+CG12+CG13+CI11+CI12+CI13)*Percapita/30*FW$4+(CH11+CH12+CH13+CJ11+CJ12+CJ13)*Cadeirante/30*FW$4,IF(C11=3,IF(CG14+CI14=10,Fixo/30*FW$4+(CG11+CG12+CG13+CI11+CI12+CI13)*Percapita/30*FW$4+(CH14+CJ14)*Cadeirante/30*FW$4,IF(CG14+CI14<=9,(CG14+CI14)*Crechee/30*FW$4)+(CH14+CJ14)*Cadeirante/30*FW$4+(CG11+CG12+CG13+CI11+CI12+CI13)*Percapita/30*FW$4)+IF(CG14+CI14>=11,Fixo/30*FW$4+(CG14+CI14-10)*Crechee/30*FW$4,0),IF(C11=2,IF(CH11+CH12+CH13+CH14+CJ11+CJ12+CJ13+CJ14=1,Cadeirante/30*FW$4,IF(CH11+CH12+CH13+CH14+CJ11+CJ12+CJ13+CJ14=2,Fixo/30*FW$4,IF(CH11+CH12+CH13+CH14+CJ11+CJ12+CJ13+CJ14>2,Fixo/30*FW$4+(CH11+CH12+CH13+CH14+CJ11+CJ12+CJ13+CJ14-2)*Cadeirante/30*FW$4)))+(CG11+CG12+CG13+CI11+CI12+CI13)*Percapita/30*FW$4+(CG14+CI14)*Crechee/30*FW$4,IF(C11=1,IF(CG11+CG12+CG13+CH11+CH12+CH13+CI11+CI12+CI13+CJ11+CJ12+CJ13<=15,(CG11+CG12+CG13+CI11+CI12+CI13)*Percapita/30*FW$4,IF(CG11+CG12+CG13+CH11+CH12+CH13+CI11+CI12+CI13+CJ11+CJ12+CJ13>=16,Fixo/30*FW$4+(CG11+CG12+CG13+CH11+CH12+CH13+CI11+CI12+CI13+CJ11+CJ12-16)*Percapita/30*FW$4)))))) -> 0 | FX11: =IF(C11=4,SUM(CK11+CK12+CK13+CM11+CM12+CM13)*Percapita/30*FX$4+(CL11+CL12+CL13+CN11+CN12+CN13)*Cadeirante/30*FX$4,IF(C11=3,IF(CK14+CM14=10,Fixo/30*FX$4+(CK11+CK12+CK13+CM11+CM12+CM13)*Percapita/30*FX$4+(CL14+CN14)*Cadeirante/30*FX$4,IF(CK14+CM14<=9,(CK14+CM14)*Crechee/30*FX$4)+(CL14+CN14)*Cadeirante/30*FX$4+(CK11+CK12+CK13+CM11+CM12+CM13)*Percapita/30*FX$4)+IF(CK14+CM14>=11,Fixo/30*FX$4+(CK14+CM14-10)*Crechee/30*FX$4,0),IF(C11=2,IF(CL11+CL12+CL13+CL14+CN11+CN12+CN13+CN14=1,Cadeirante/30*FX$4,IF(CL11+CL12+CL13+CL14+CN11+CN12+CN13+CN14=2,Fixo/30*FX$4,IF(CL11+CL12+CL13+CL14+CN11+CN12+CN13+CN14>2,Fixo/30*FX$4+(CL11+CL12+CL13+CL14+CN11+CN12+CN13+CN14-2)*Cadeirante/30*FX$4)))+(CK11+CK12+CK13+CM11+CM12+CM13)*Percapita/30*FX$4+(CK14+CM14)*Crechee/30*FX$4,IF(C11=1,IF(CK11+CK12+CK13+CL11+CL12+CL13+CM11+CM12+CM13+CN11+CN12+CN13<=15,(CK11+CK12+CK13+CM11+CM12+CM13)*Percapita/30*FX$4,IF(CK11+CK12+CK13+CL11+CL12+CL13+CM11+CM12+CM13+CN11+CN12+CN13>=16,Fixo/30*FX$4+(CK11+CK12+CK13+CL11+CL12+CL13+CM11+CM12+CM13+CN11+CN12-16)*Percapita/30*FX$4)))))) -> 0 | FY11: =IF(C11=4,SUM(CO11+CO12+CO13+CQ11+CQ12+CQ13)*Percapita/30*FY$4+(CP11+CP12+CP13+CR11+CR12+CR13)*Cadeirante/30*FY$4,IF(C11=3,IF(CO14+CQ14=10,Fixo/30*FY$4+(CO11+CO12+CO13+CQ11+CQ12+CQ13)*Percapita/30*FY$4+(CP14+CR14)*Cadeirante/30*FY$4,IF(CO14+CQ14<=9,(CO14+CQ14)*Crechee/30*FY$4)+(CP14+CR14)*Cadeirante/30*FY$4+(CO11+CO12+CO13+CQ11+CQ12+CQ13)*Percapita/30*FY$4)+IF(CO14+CQ14>=11,Fixo/30*FY$4+(CO14+CQ14-10)*Crechee/30*FY$4,0),IF(C11=2,IF(CP11+CP12+CP13+CP14+CR11+CR12+CR13+CR14=1,Cadeirante/30*FY$4,IF(CP11+CP12+CP13+CP14+CR11+CR12+CR13+CR14=2,Fixo/30*FY$4,IF(CP11+CP12+CP13+CP14+CR11+CR12+CR13+CR14>2,Fixo/30*FY$4+(CP11+CP12+CP13+CP14+CR11+CR12+CR13+CR14-2)*Cadeirante/30*FY$4)))+(CO11+CO12+CO13+CQ11+CQ12+CQ13)*Percapita/30*FY$4+(CO14+CQ14)*Crechee/30*FY$4,IF(C11=1,IF(CO11+CO12+CO13+CP11+CP12+CP13+CQ11+CQ12+CQ13+CR11+CR12+CR13<=15,(CO11+CO12+CO13+CQ11+CQ12+CQ13)*Percapita/30*FY$4,IF(CO11+CO12+CO13+CP11+CP12+CP13+CQ11+CQ12+CQ13+CR11+CR12+CR13>=16,Fixo/30*FY$4+(CO11+CO12+CO13+CP11+CP12+CP13+CQ11+CQ12+CQ13+CR11+CR12-16)*Percapita/30*FY$4)))))) -> 0 | FZ11: =IF(C11=4,SUM(CS11+CS12+CS13+CU11+CU12+CU13)*Percapita/30*FZ$4+(CT11+CT12+CT13+CV11+CV12+CV13)*Cadeirante/30*FZ$4,IF(C11=3,IF(CS14+CU14=10,Fixo/30*FZ$4+(CS11+CS12+CS13+CU11+CU12+CU13)*Percapita/30*FZ$4+(CT14+CV14)*Cadeirante/30*FZ$4,IF(CS14+CU14<=9,(CS14+CU14)*Crechee/30*FZ$4)+(CT14+CV14)*Cadeirante/30*FZ$4+(CS11+CS12+CS13+CU11+CU12+CU13)*Percapita/30*FZ$4)+IF(CS14+CU14>=11,Fixo/30*FZ$4+(CS14+CU14-10)*Crechee/30*FZ$4,0),IF(C11=2,IF(CT11+CT12+CT13+CT14+CV11+CV12+CV13+CV14=1,Cadeirante/30*FZ$4,IF(CT11+CT12+CT13+CT14+CV11+CV12+CV13+CV14=2,Fixo/30*FZ$4,IF(CT11+CT12+CT13+CT14+CV11+CV12+CV13+CV14>2,Fixo/30*FZ$4+(CT11+CT12+CT13+CT14+CV11+CV12+CV13+CV14-2)*Cadeirante/30*FZ$4)))+(CS11+CS12+CS13+CU11+CU12+CU13)*Percapita/30*FZ$4+(CS14+CU14)*Crechee/30*FZ$4,IF(C11=1,IF(CS11+CS12+CS13+CT11+CT12+CT13+CU11+CU12+CU13+CV11+CV12+CV13<=15,(CS11+CS12+CS13+CU11+CU12+CU13)*Percapita/30*FZ$4,IF(CS11+CS12+CS13+CT11+CT12+CT13+CU11+CU12+CU13+CV11+CV12+CV13>=16,Fixo/30*FZ$4+(CS11+CS12+CS13+CT11+CT12+CT13+CU11+CU12+CU13+CV11+CV12-16)*Percapita/30*FZ$4)))))) -> 0 | GA11: =IF(C11=4,SUM(CW11+CW12+CW13+CY11+CY12+CY13)*Percapita/30*GA$4+(CX11+CX12+CX13+CZ11+CZ12+CZ13)*Cadeirante/30*GA$4,IF(C11=3,IF(CW14+CY14=10,Fixo/30*GA$4+(CW11+CW12+CW13+CY11+CY12+CY13)*Percapita/30*GA$4+(CX14+CZ14)*Cadeirante/30*GA$4,IF(CW14+CY14<=9,(CW14+CY14)*Crechee/30*GA$4)+(CX14+CZ14)*Cadeirante/30*GA$4+(CW11+CW12+CW13+CY11+CY12+CY13)*Percapita/30*GA$4)+IF(CW14+CY14>=11,Fixo/30*GA$4+(CW14+CY14-10)*Crechee/30*GA$4,0),IF(C11=2,IF(CX11+CX12+CX13+CX14+CZ11+CZ12+CZ13+CZ14=1,Cadeirante/30*GA$4,IF(CX11+CX12+CX13+CX14+CZ11+CZ12+CZ13+CZ14=2,Fixo/30*GA$4,IF(CX11+CX12+CX13+CX14+CZ11+CZ12+CZ13+CZ14>2,Fixo/30*GA$4+(CX11+CX12+CX13+CX14+CZ11+CZ12+CZ13+CZ14-2)*Cadeirante/30*GA$4)))+(CW11+CW12+CW13+CY11+CY12+CY13)*Percapita/30*GA$4+(CW14+CY14)*Crechee/30*GA$4,IF(C11=1,IF(CW11+CW12+CW13+CX11+CX12+CX13+CY11+CY12+CY13+CZ11+CZ12+CZ13<=15,(CW11+CW12+CW13+CY11+CY12+CY13)*Percapita/30*GA$4,IF(CW11+CW12+CW13+CX11+CX12+CX13+CY11+CY12+CY13+CZ11+CZ12+CZ13>=16,Fixo/30*GA$4+(CW11+CW12+CW13+CX11+CX12+CX13+CY11+CY12+CY13+CZ11+CZ12-16)*Percapita/30*GA$4)))))) -> 0 | GB11: =IF(C11=4,SUM(DA11+DA12+DA13+DC11+DC12+DC13)*Percapita/30*GB$4+(DB11+DB12+DB13+DD11+DD12+DD13)*Cadeirante/30*GB$4,IF(C11=3,IF(DA14+DC14=10,Fixo/30*GB$4+(DA11+DA12+DA13+DC11+DC12+DC13)*Percapita/30*GB$4+(DB14+DD14)*Cadeirante/30*GB$4,IF(DA14+DC14<=9,(DA14+DC14)*Crechee/30*GB$4)+(DB14+DD14)*Cadeirante/30*GB$4+(DA11+DA12+DA13+DC11+DC12+DC13)*Percapita/30*GB$4)+IF(DA14+DC14>=11,Fixo/30*GB$4+(DA14+DC14-10)*Crechee/30*GB$4,0),IF(C11=2,IF(DB11+DB12+DB13+DB14+DD11+DD12+DD13+DD14=1,Cadeirante/30*GB$4,IF(DB11+DB12+DB13+DB14+DD11+DD12+DD13+DD14=2,Fixo/30*GB$4,IF(DB11+DB12+DB13+DB14+DD11+DD12+DD13+DD14>2,Fixo/30*GB$4+(DB11+DB12+DB13+DB14+DD11+DD12+DD13+DD14-2)*Cadeirante/30*GB$4)))+(DA11+DA12+DA13+DC11+DC12+DC13)*Percapita/30*GB$4+(DA14+DC14)*Crechee/30*GB$4,IF(C11=1,IF(DA11+DA12+DA13+DB11+DB12+DB13+DC11+DC12+DC13+DD11+DD12+DD13<=15,(DA11+DA12+DA13+DC11+DC12+DC13)*Percapita/30*GB$4,IF(DA11+DA12+DA13+DB11+DB12+DB13+DC11+DC12+DC13+DD11+DD12+DD13>=16,Fixo/30*GB$4+(DA11+DA12+DA13+DB11+DB12+DB13+DC11+DC12+DC13+DD11+DD12-16)*Percapita/30*GB$4)))))) -> 0 | GC11: =IF(C11=4,SUM(DE11+DE12+DE13+DG11+DG12+DG13)*Percapita/30*GC$4+(DF11+DF12+DF13+DH11+DH12+DH13)*Cadeirante/30*GC$4,IF(C11=3,IF(DE14+DG14=10,Fixo/30*GC$4+(DE11+DE12+DE13+DG11+DG12+DG13)*Percapita/30*GC$4+(DF14+DH14)*Cadeirante/30*GC$4,IF(DE14+DG14<=9,(DE14+DG14)*Crechee/30*GC$4)+(DF14+DH14)*Cadeirante/30*GC$4+(DE11+DE12+DE13+DG11+DG12+DG13)*Percapita/30*GC$4)+IF(DE14+DG14>=11,Fixo/30*GC$4+(DE14+DG14-10)*Crechee/30*GC$4,0),IF(C11=2,IF(DF11+DF12+DF13+DF14+DH11+DH12+DH13+DH14=1,Cadeirante/30*GC$4,IF(DF11+DF12+DF13+DF14+DH11+DH12+DH13+DH14=2,Fixo/30*GC$4,IF(DF11+DF12+DF13+DF14+DH11+DH12+DH13+DH14>2,Fixo/30*GC$4+(DF11+DF12+DF13+DF14+DH11+DH12+DH13+DH14-2)*Cadeirante/30*GC$4)))+(DE11+DE12+DE13+DG11+DG12+DG13)*Percapita/30*GC$4+(DE14+DG14)*Crechee/30*GC$4,IF(C11=1,IF(DE11+DE12+DE13+DF11+DF12+DF13+DG11+DG12+DG13+DH11+DH12+DH13<=15,(DE11+DE12+DE13+DG11+DG12+DG13)*Percapita/30*GC$4,IF(DE11+DE12+DE13+DF11+DF12+DF13+DG11+DG12+DG13+DH11+DH12+DH13>=16,Fixo/30*GC$4+(DE11+DE12+DE13+DF11+DF12+DF13+DG11+DG12+DG13+DH11+DH12-16)*Percapita/30*GC$4)))))) -> 0 | GD11: =IF(C11=4,SUM(DI11+DI12+DI13+DK11+DK12+DK13)*Percapita/30*GD$4+(DJ11+DJ12+DJ13+DL11+DL12+DL13)*Cadeirante/30*GD$4,IF(C11=3,IF(DI14+DK14=10,Fixo/30*GD$4+(DI11+DI12+DI13+DK11+DK12+DK13)*Percapita/30*GD$4+(DJ14+DL14)*Cadeirante/30*GD$4,IF(DI14+DK14<=9,(DI14+DK14)*Crechee/30*GD$4)+(DJ14+DL14)*Cadeirante/30*GD$4+(DI11+DI12+DI13+DK11+DK12+DK13)*Percapita/30*GD$4)+IF(DI14+DK14>=11,Fixo/30*GD$4+(DI14+DK14-10)*Crechee/30*GD$4,0),IF(C11=2,IF(DJ11+DJ12+DJ13+DJ14+DL11+DL12+DL13+DL14=1,Cadeirante/30*GD$4,IF(DJ11+DJ12+DJ13+DJ14+DL11+DL12+DL13+DL14=2,Fixo/30*GD$4,IF(DJ11+DJ12+DJ13+DJ14+DL11+DL12+DL13+DL14>2,Fixo/30*GD$4+(DJ11+DJ12+DJ13+DJ14+DL11+DL12+DL13+DL14-2)*Cadeirante/30*GD$4)))+(DI11+DI12+DI13+DK11+DK12+DK13)*Percapita/30*GD$4+(DI14+DK14)*Crechee/30*GD$4,IF(C11=1,IF(DI11+DI12+DI13+DJ11+DJ12+DJ13+DK11+DK12+DK13+DL11+DL12+DL13<=15,(DI11+DI12+DI13+DK11+DK12+DK13)*Percapita/30*GD$4,IF(DI11+DI12+DI13+DJ11+DJ12+DJ13+DK11+DK12+DK13+DL11+DL12+DL13>=16,Fixo/30*GD$4+(DI11+DI12+DI13+DJ11+DJ12+DJ13+DK11+DK12+DK13+DL11+DL12-16)*Percapita/30*GD$4)))))) -> 0 | GE11: =IF(C11=4,SUM(DM11+DM12+DM13+DO11+DO12+DO13)*Percapita/30*GE$4+(DN11+DN12+DN13+DP11+DP12+DP13)*Cadeirante/30*GE$4,IF(C11=3,IF(DM14+DO14=10,Fixo/30*GE$4+(DM11+DM12+DM13+DO11+DO12+DO13)*Percapita/30*GE$4+(DN14+DP14)*Cadeirante/30*GE$4,IF(DM14+DO14<=9,(DM14+DO14)*Crechee/30*GE$4)+(DN14+DP14)*Cadeirante/30*GE$4+(DM11+DM12+DM13+DO11+DO12+DO13)*Percapita/30*GE$4)+IF(DM14+DO14>=11,Fixo/30*GE$4+(DM14+DO14-10)*Crechee/30*GE$4,0),IF(C11=2,IF(DN11+DN12+DN13+DN14+DP11+DP12+DP13+DP14=1,Cadeirante/30*GE$4,IF(DN11+DN12+DN13+DN14+DP11+DP12+DP13+DP14=2,Fixo/30*GE$4,IF(DN11+DN12+DN13+DN14+DP11+DP12+DP13+DP14>2,Fixo/30*GE$4+(DN11+DN12+DN13+DN14+DP11+DP12+DP13+DP14-2)*Cadeirante/30*GE$4)))+(DM11+DM12+DM13+DO11+DO12+DO13)*Percapita/30*GE$4+(DM14+DO14)*Crechee/30*GE$4,IF(C11=1,IF(DM11+DM12+DM13+DN11+DN12+DN13+DO11+DO12+DO13+DP11+DP12+DP13<=15,(DM11+DM12+DM13+DO11+DO12+DO13)*Percapita/30*GE$4,IF(DM11+DM12+DM13+DN11+DN12+DN13+DO11+DO12+DO13+DP11+DP12+DP13>=16,Fixo/30*GE$4+(DM11+DM12+DM13+DN11+DN12+DN13+DO11+DO12+DO13+DP11+DP12-16)*Percapita/30*GE$4)))))) -> 0 | GF11: =IF(C11=4,SUM(DQ11+DQ12+DQ13+DS11+DS12+DS13)*Percapita/30*GF$4+(DR11+DR12+DR13+DT11+DT12+DT13)*Cadeirante/30*GF$4,IF(C11=3,IF(DQ14+DS14=10,Fixo/30*GF$4+(DQ11+DQ12+DQ13+DS11+DS12+DS13)*Percapita/30*GF$4+(DR14+DT14)*Cadeirante/30*GF$4,IF(DQ14+DS14<=9,(DQ14+DS14)*Crechee/30*GF$4)+(DR14+DT14)*Cadeirante/30*GF$4+(DQ11+DQ12+DQ13+DS11+DS12+DS13)*Percapita/30*GF$4)+IF(DQ14+DS14>=11,Fixo/30*GF$4+(DQ14+DS14-10)*Crechee/30*GF$4,0),IF(C11=2,IF(DR11+DR12+DR13+DR14+DT11+DT12+DT13+DT14=1,Cadeirante/30*GF$4,IF(DR11+DR12+DR13+DR14+DT11+DT12+DT13+DT14=2,Fixo/30*GF$4,IF(DR11+DR12+DR13+DR14+DT11+DT12+DT13+DT14>2,Fixo/30*GF$4+(DR11+DR12+DR13+DR14+DT11+DT12+DT13+DT14-2)*Cadeirante/30*GF$4)))+(DQ11+DQ12+DQ13+DS11+DS12+DS13)*Percapita/30*GF$4+(DQ14+DS14)*Crechee/30*GF$4,IF(C11=1,IF(DQ11+DQ12+DQ13+DR11+DR12+DR13+DS11+DS12+DS13+DT11+DT12+DT13<=15,(DQ11+DQ12+DQ13+DS11+DS12+DS13)*Percapita/30*GF$4,IF(DQ11+DQ12+DQ13+DR11+DR12+DR13+DS11+DS12+DS13+DT11+DT12+DT13>=16,Fixo/30*GF$4+(DQ11+DQ12+DQ13+DR11+DR12+DR13+DS11+DS12+DS13+DT11+DT12-16)*Percapita/30*GF$4)))))) -> 0 | GG11: =IF(C11=4,SUM(DU11+DU12+DU13+DW11+DW12+DW13)*Percapita/30*GG$4+(DV11+DV12+DV13+DX11+DX12+DX13)*Cadeirante/30*GG$4,IF(C11=3,IF(DU14+DW14=10,Fixo/30*GG$4+(DU11+DU12+DU13+DW11+DW12+DW13)*Percapita/30*GG$4+(DV14+DX14)*Cadeirante/30*GG$4,IF(DU14+DW14<=9,(DU14+DW14)*Crechee/30*GG$4)+(DV14+DX14)*Cadeirante/30*GG$4+(DU11+DU12+DU13+DW11+DW12+DW13)*Percapita/30*GG$4)+IF(DU14+DW14>=11,Fixo/30*GG$4+(DU14+DW14-10)*Crechee/30*GG$4,0),IF(C11=2,IF(DV11+DV12+DV13+DV14+DX11+DX12+DX13+DX14=1,Cadeirante/30*GG$4,IF(DV11+DV12+DV13+DV14+DX11+DX12+DX13+DX14=2,Fixo/30*GG$4,IF(DV11+DV12+DV13+DV14+DX11+DX12+DX13+DX14>2,Fixo/30*GG$4+(DV11+DV12+DV13+DV14+DX11+DX12+DX13+DX14-2)*Cadeirante/30*GG$4)))+(DU11+DU12+DU13+DW11+DW12+DW13)*Percapita/30*GG$4+(DU14+DW14)*Crechee/30*GG$4,IF(C11=1,IF(DU11+DU12+DU13+DV11+DV12+DV13+DW11+DW12+DW13+DX11+DX12+DX13<=15,(DU11+DU12+DU13+DW11+DW12+DW13)*Percapita/30*GG$4,IF(DU11+DU12+DU13+DV11+DV12+DV13+DW11+DW12+DW13+DX11+DX12+DX13>=16,Fixo/30*GG$4+(DU11+DU12+DU13+DV11+DV12+DV13+DW11+DW12+DW13+DX11+DX12-16)*Percapita/30*GG$4)))))) -> 0 | GH11: =IF(C11=4,SUM(DY11+DY12+DY13+EA11+EA12+EA13)*Percapita/30*GH$4+(DZ11+DZ12+DZ13+EB11+EB12+EB13)*Cadeirante/30*GH$4,IF(C11=3,IF(DY14+EA14=10,Fixo/30*GH$4+(DY11+DY12+DY13+EA11+EA12+EA13)*Percapita/30*GH$4+(DZ14+EB14)*Cadeirante/30*GH$4,IF(DY14+EA14<=9,(DY14+EA14)*Crechee/30*GH$4)+(DZ14+EB14)*Cadeirante/30*GH$4+(DY11+DY12+DY13+EA11+EA12+EA13)*Percapita/30*GH$4)+IF(DY14+EA14>=11,Fixo/30*GH$4+(DY14+EA14-10)*Crechee/30*GH$4,0),IF(C11=2,IF(DZ11+DZ12+DZ13+DZ14+EB11+EB12+EB13+EB14=1,Cadeirante/30*GH$4,IF(DZ11+DZ12+DZ13+DZ14+EB11+EB12+EB13+EB14=2,Fixo/30*GH$4,IF(DZ11+DZ12+DZ13+DZ14+EB11+EB12+EB13+EB14>2,Fixo/30*GH$4+(DZ11+DZ12+DZ13+DZ14+EB11+EB12+EB13+EB14-2)*Cadeirante/30*GH$4)))+(DY11+DY12+DY13+EA11+EA12+EA13)*Percapita/30*GH$4+(DY14+EA14)*Crechee/30*GH$4,IF(C11=1,IF(DY11+DY12+DY13+DZ11+DZ12+DZ13+EA11+EA12+EA13+EB11+EB12+EB13<=15,(DY11+DY12+DY13+EA11+EA12+EA13)*Percapita/30*GH$4,IF(DY11+DY12+DY13+DZ11+DZ12+DZ13+EA11+EA12+EA13+EB11+EB12+EB13>=16,Fixo/30*GH$4+(DY11+DY12+DY13+DZ11+DZ12+DZ13+EA11+EA12+EA13+EB11+EB12-16)*Percapita/30*GH$4)))))) -> 0 | GI11: =IF(C11=4,SUM(EC11+EC12+EC13+EE11+EE12+EE13)*Percapita/30*GI$4+(ED11+ED12+ED13+EF11+EF12+EF13)*Cadeirante/30*GI$4,IF(C11=3,IF(EC14+EE14=10,Fixo/30*GI$4+(EC11+EC12+EC13+EE11+EE12+EE13)*Percapita/30*GI$4+(ED14+EF14)*Cadeirante/30*GI$4,IF(EC14+EE14<=9,(EC14+EE14)*Crechee/30*GI$4)+(ED14+EF14)*Cadeirante/30*GI$4+(EC11+EC12+EC13+EE11+EE12+EE13)*Percapita/30*GI$4)+IF(EC14+EE14>=11,Fixo/30*GI$4+(EC14+EE14-10)*Crechee/30*GI$4,0),IF(C11=2,IF(ED11+ED12+ED13+ED14+EF11+EF12+EF13+EF14=1,Cadeirante/30*GI$4,IF(ED11+ED12+ED13+ED14+EF11+EF12+EF13+EF14=2,Fixo/30*GI$4,IF(ED11+ED12+ED13+ED14+EF11+EF12+EF13+EF14>2,Fixo/30*GI$4+(ED11+ED12+ED13+ED14+EF11+EF12+EF13+EF14-2)*Cadeirante/30*GI$4)))+(EC11+EC12+EC13+EE11+EE12+EE13)*Percapita/30*GI$4+(EC14+EE14)*Crechee/30*GI$4,IF(C11=1,IF(EC11+EC12+EC13+ED11+ED12+ED13+EE11+EE12+EE13+EF11+EF12+EF13<=15,(EC11+EC12+EC13+EE11+EE12+EE13)*Percapita/30*GI$4,IF(EC11+EC12+EC13+ED11+ED12+ED13+EE11+EE12+EE13+EF11+EF12+EF13>=16,Fixo/30*GI$4+(EC11+EC12+EC13+ED11+ED12+ED13+EE11+EE12+EE13+EF11+EF12-16)*Percapita/30*GI$4)))))) -> 0 | GJ11: =IF(C11=4,SUM(EG11+EG12+EG13+EI11+EI12+EI13)*Percapita/30*GJ$4+(EH11+EH12+EH13+EJ11+EJ12+EJ13)*Cadeirante/30*GJ$4,IF(C11=3,IF(EG14+EI14=10,Fixo/30*GJ$4+(EG11+EG12+EG13+EI11+EI12+EI13)*Percapita/30*GJ$4+(EH14+EJ14)*Cadeirante/30*GJ$4,IF(EG14+EI14<=9,(EG14+EI14)*Crechee/30*GJ$4)+(EH14+EJ14)*Cadeirante/30*GJ$4+(EG11+EG12+EG13+EI11+EI12+EI13)*Percapita/30*GJ$4)+IF(EG14+EI14>=11,Fixo/30*GJ$4+(EG14+EI14-10)*Crechee/30*GJ$4,0),IF(C11=2,IF(EH11+EH12+EH13+EH14+EJ11+EJ12+EJ13+EJ14=1,Cadeirante/30*GJ$4,IF(EH11+EH12+EH13+EH14+EJ11+EJ12+EJ13+EJ14=2,Fixo/30*GJ$4,IF(EH11+EH12+EH13+EH14+EJ11+EJ12+EJ13+EJ14>2,Fixo/30*GJ$4+(EH11+EH12+EH13+EH14+EJ11+EJ12+EJ13+EJ14-2)*Cadeirante/30*GJ$4)))+(EG11+EG12+EG13+EI11+EI12+EI13)*Percapita/30*GJ$4+(EG14+EI14)*Crechee/30*GJ$4,IF(C11=1,IF(EG11+EG12+EG13+EH11+EH12+EH13+EI11+EI12+EI13+EJ11+EJ12+EJ13<=15,(EG11+EG12+EG13+EI11+EI12+EI13)*Percapita/30*GJ$4,IF(EG11+EG12+EG13+EH11+EH12+EH13+EI11+EI12+EI13+EJ11+EJ12+EJ13>=16,Fixo/30*GJ$4+(EG11+EG12+EG13+EH11+EH12+EH13+EI11+EI12+EI13+EJ11+EJ12-16)*Percapita/30*GJ$4)))))) -> 0 | GL11: =IF(J11="ADAPTADO",T11*Cadeirante/30*GM11+S11*Percapita/30*GM11,IF(J11="NORMAL",(S11+T11)*Percapita/30*GM11,IF(J11="CRECHE",0)))*-1 -> 0 | GN11: =SUMIF(V11:V14,"<0")*Cadeirante/30*GN$4+SUMIF(X11:X14,"<0")*Cadeirante/30*GN$4 -> 0 | GO11: =SUMIF(Z11:Z14,"<0")*Cadeirante/30*GO$4+SUMIF(AB11:AB14,"<0")*Cadeirante/30*GO$4 -> 0 | GP11: =SUMIF(AD11:AD14,"<0")*Cadeirante/30*GP$4+SUMIF(AF11:AF14,"<0")*Cadeirante/30*GP$4 -> 0 | GQ11: =SUMIF(AH11:AH14,"<0")*Cadeirante/30*GQ$4+SUMIF(AJ11:AJ14,"<0")*Cadeirante/30*GQ$4 -> 0 | GR11: =SUMIF(AL11:AL14,"<0")*Cadeirante/30*GR$4+SUMIF(AN11:AN14,"<0")*Cadeirante/30*GR$4 -> 0 | GS11: =SUMIF(AP11:AP14,"<0")*Cadeirante/30*GS$4+SUMIF(AR11:AR14,"<0")*Cadeirante/30*GS$4 -> 0 | GT11: =SUMIF(AT11:AT14,"<0")*Cadeirante/30*GT$4+SUMIF(AV11:AV14,"<0")*Cadeirante/30*GT$4 -> 0 | GU11: =SUMIF(AX11:AX14,"<0")*Cadeirante/30*GU$4+SUMIF(AZ11:AZ14,"<0")*Cadeirante/30*GU$4 -> 0 | GV11: =SUMIF(BB11:BB14,"<0")*Cadeirante/30*GV$4+SUMIF(BD11:BD14,"<0")*Cadeirante/30*GV$4 -> 0 | GW11: =SUMIF(BF11:BF14,"<0")*Cadeirante/30*GW$4+SUMIF(BH11:BH14,"<0")*Cadeirante/30*GW$4 -> 0 | GX11: =SUMIF(BJ11:BJ14,"<0")*Cadeirante/30*GX$4+SUMIF(BL11:BL14,"<0")*Cadeirante/30*GX$4 -> 0 | GY11: =SUMIF(BN11:BN14,"<0")*Cadeirante/30*GY$4+SUMIF(BP11:BP14,"<0")*Cadeirante/30*GY$4 -> 0 | GZ11: =SUMIF(BR11:BR14,"<0")*Cadeirante/30*GZ$4+SUMIF(BT11:BT14,"<0")*Cadeirante/30*GZ$4 -> 0 | HA11: =SUMIF(BV11:BV14,"<0")*Cadeirante/30*HA$4+SUMIF(BX11:BX14,"<0")*Cadeirante/30*HA$4 -> 0 | HB11: =SUMIF(BZ11:BZ14,"<0")*Cadeirante/30*HB$4+SUMIF(CB11:CB14,"<0")*Cadeirante/30*HB$4 -> 0 | HC11: =SUMIF(CD11:CD14,"<0")*Cadeirante/30*HC$4+SUMIF(CF11:CF14,"<0")*Cadeirante/30*HC$4 -> 0 | HD11: =SUMIF(CH11:CH14,"<0")*Cadeirante/30*HD$4+SUMIF(CJ11:CJ14,"<0")*Cadeirante/30*HD$4 -> 0 | HE11: =SUMIF(CL11:CL14,"<0")*Cadeirante/30*HE$4+SUMIF(CN11:CN14,"<0")*Cadeirante/30*HE$4 -> 0 | HF11: =SUMIF(CP11:CP14,"<0")*Cadeirante/30*HF$4+SUMIF(CR11:CR14,"<0")*Cadeirante/30*HF$4 -> 0 | HG11: =SUMIF(CT11:CT14,"<0")*Cadeirante/30*HG$4+SUMIF(CV11:CV14,"<0")*Cadeirante/30*HG$4 -> 0 | HH11: =SUMIF(CX11:CX14,"<0")*Cadeirante/30*HH$4+SUMIF(CZ11:CZ14,"<0")*Cadeirante/30*HH$4 -> 0 | HI11: =SUMIF(DB11:DB14,"<0")*Cadeirante/30*HI$4+SUMIF(DD11:DD14,"<0")*Cadeirante/30*HI$4 -> 0 | HJ11: =SUMIF(DF11:DF14,"<0")*Cadeirante/30*HJ$4+SUMIF(DH11:DH14,"<0")*Cadeirante/30*HJ$4 -> 0 | HK11: =SUMIF(DJ11:DJ14,"<0")*Cadeirante/30*HK$4+SUMIF(DL11:DL14,"<0")*Cadeirante/30*HK$4 -> 0 | HL11: =SUMIF(DN11:DN14,"<0")*Cadeirante/30*HL$4+SUMIF(DP11:DP14,"<0")*Cadeirante/30*HL$4 -> 0 | HM11: =SUMIF(DR11:DR14,"<0")*Cadeirante/30*HM$4+SUMIF(DT11:DT14,"<0")*Cadeirante/30*HM$4 -> 0 | HN11: =SUMIF(DV11:DV14,"<0")*Cadeirante/30*HN$4+SUMIF(DX11:DX14,"<0")*Cadeirante/30*HN$4 -> 0 | HO11: =SUMIF(DZ11:DZ14,"<0")*Cadeirante/30*HO$4+SUMIF(EB11:EB14,"<0")*Cadeirante/30*HO$4 -> 0 | HP11: =SUMIF(ED11:ED14,"<0")*Cadeirante/30*HP$4+SUMIF(EF11:EF14,"<0")*Cadeirante/30*HP$4 -> 0 | HW11: 17629.31 | HY11: =IF(ISTEXT(EM11), VALUE(EM11), EM11) -> 0 | HZ11: =IF(ISTEXT(EN11), VALUE(EN11), EN11) -> 0 | IA11: =IF(ISTEXT(EO11), VALUE(EO11), EO11) -> 0 | IB11: =HW11=FE11 -> FALSE
A12: 015.733-00 | B12: 2022/0027713-001B | C12: FBE | D12: 2022/0027713 | E12: ECM4497 | F12: 01/04/2026 | G12: 30/04/2026 | H12: ALEXANDRO CIRINO VIEIRA | I12: ALEXANDRO CIRINO VIEIRA | J12: NORMAL | K12: EMEF | L12: =CONTINUA!BV12 -> 0 | M12: =CONTINUA!BW12 -> 0 | O12: 6020.2022/0027713-2 | P12: 0 | EP12: =Q12 -> 0 | EQ12: =U12+Y12+AC12+AG12+AK12+AO12+AS12+AW12+BA12+BE12+BI12+BM12+BQ12+BU12+BY12+CC12+CG12+CK12+CO12+CS12+CW12+DA12+DE12+DI12+DM12+DQ12+DU12+DY12+EC12+EG12 -> 0 | ER12: =S12+W12+AA12+AE12+AI12+AM12+AQ12+AU12+AY12+BC12+BG12+BK12+BO12+BS12+BW12+CA12+CE12+CI12+CM12+CQ12+CU12+CY12+DC12+DG12+DK12+DO12+DS12+DW12+EA12+EE12+EI12 -> 0 | ES12: =R12 -> 0 | ET12: =V12+Z12+AD12+AH12+AL12+AP12+AT12+AX12+BB12+BF12+BJ12+BN12+BR12+BV12+BZ12+CD12+CH12+CL12+CP12+CT12+CX12+DB12+DF12+DJ12+DN12+DR12+DV12+DZ12+ED12+EH12 -> 0 | EU12: =T12+X12+AB12+AF12+AJ12+AN12+AR12+AV12+AZ12+BD12+BH12+BL12+BP12+BT12+BX12+CB12+CF12+CJ12+CN12+CR12+CV12+CZ12+DD12+DH12+DL12+DP12+DT12+DX12+EB12+EF12+EJ12 -> 0 | EV12: =EP12+EQ12+ES12+ET12+ER12+EU12 -> 0 | EX12: =FF12 -> 0 | EY12: =(L12*regular)+(M12*Cadeirantee) -> 0 | EZ12: =SUMIF(FG12:GJ12,">0") -> 0 | FA12: =SUMIF(FG12:GJ12,"<0")+SUMIF(GN12:HP12,"<0") -> 0 | FB12: 0 | FC12: =N12*km*'VALORES TABELA'!$B$13 -> 0 | FD12: =GL12 -> 0 | FE12: 12621.3 | GL12: =IF(J12="ADAPTADO",T12*Cadeirante/30*GM12+S12*Percapita/30*GM12,IF(J12="NORMAL",(S12+T12)*Percapita/30*GM12,IF(J12="CRECHE",0)))*-1 -> 0 | HY12: =IF(ISTEXT(EM12), VALUE(EM12), EM12) -> 0 | HZ12: =IF(ISTEXT(EN12), VALUE(EN12), EN12) -> 0 | IA12: =IF(ISTEXT(EO12), VALUE(EO12), EO12) -> 0
