Workbook
Name \a: #REF!
Name \a: #REF!
Name \p: #REF!
Name \p: #REF!
Name _______xlnm.Print_Titles: #REF!
Name _______xlnm_Print_Titles: NA()
Name ______xlnm._FilterDatabase: "#ref!"
Name ______xlnm.Print_Titles: #REF!
Name ______xlnm__FilterDatabase: "#ref!"
Name ______xlnm_Print_Titles: NA()
Name _____xlfn_BAHTTEXT: NA()
Name _____xlfn_SUMIFS: NA()
Name _____xlnm._FilterDatabase: "#ref!"
Name _____xlnm.Print_Titles: #REF!
Name _____xlnm__FilterDatabase: "#ref!"
Name _____xlnm_Print_Titles: NA()
Name ____xlfn_BAHTTEXT: NA()
Name ____xlfn_SUMIFS: NA()
Name ____xlnm._FilterDatabase: "#ref!"
Name ____xlnm.Print_Titles: #REF!
Name ____xlnm__FilterDatabase: "#ref!"
Name ____xlnm_Print_Titles: NA()
Name ___xlfn_BAHTTEXT: NA()
Name ___xlfn_SUMIFS: NA()
Name ___xlnm._FilterDatabase: "#ref!"
Name ___xlnm.Print_Titles: #REF!
Name ___xlnm__FilterDatabase: "#ref!"
Name ___xlnm_Print_Titles: NA()
Name __TAB3688: #REF!
Name __xlfn_BAHTTEXT: NA()
Name __xlfn_SUMIFS: NA()
Name __xlnm._FilterDatabase: "#ref!"
Name __xlnm.Print_Titles: #REF!
Name __xlnm__FilterDatabase: "#ref!"
Name __xlnm_Print_Titles: NA()
Name _TAB3688: #REF!
Name _TAB3688: #REF!
Name a: #REF!
Name abr: #REF!
Name abr: #REF!
Name abril: #REF!
Name ACRESCENTAR: #REF!
Name ADAPTADO: '[1]APONTAMENTO CREDENCIAMENTO'!#REF!
Name ADAPTADO: 'APONTAMENTO CREDENCIAMENTO'!#REF!
Name AGOSTO: #REF!
Name AI: #REF!
Name AI: #REF!
Name AII: #REF!
Name AII: #REF!
Name AK: #REF!
Name AK: #REF!
Name AL: #REF!
Name AL: #REF!
Name AMPLIAR: #REF!
Name AMPLIAR: #REF!
Name ApagaAtesteFis: 'ATESTE-LIQ-FIS'!$A$4:$K$3898
Name ApagaBaseC: 'BASE C'!$A$11:$N$4950
Name ApagaDadosA: 'APONTAMENTO CREDENCIAMENTO'!$Q$6:$T$3059
Name ApagaDadosC: CONTINUA!$L$6:$BU$3077
Name ApagarDadosDigitados: #REF!

Sheet APONTAMENTO CREDENCIAMENTO
A1: Guaianases | G1: ='BASE C'!E4 -> ABRIL | I1: APONTAMENTO CREDENCIAMENTO
G2: 01/06 a 30/06/2025
A3: 1 | B3: =A3+1 -> 2 | C3: =B3+1 -> 3 | D3: 1 | E3: =D3+1 -> 2 | F3: =E3+1 -> 3 | G3: =F3+1 -> 4 | H3: =G3+1 -> 5 | I3: =H3+1 -> 6 | J3: =I3+1 -> 7 | K3: =J3+1 -> 8 | L3: =K3+1 -> 9 | M3: =L3+1 -> 10 | N3: 10 | O3: =N3+1 -> 11 | P3: 13 | Q3: =P3+1 -> 14 | R3: =Q3+1 -> 15 | S3: =R3+1 -> 16 | T3: =S3+1 -> 17
A4: CRMC | B4: OS | C4: DRE | D4: CONTRATO | E4: PLACA | F4: PERÍODO | H4: EMPRESA | I4: NOME CONDUTOR | J4: TIPO DE VEÍCULO (NORMAL, ADAPTADO) | K4: TIPO DE ATENDIMENTO | L4: TOTAL CONT REG | M4: TOTAL CONT CAD | N4: KM ADICIONAL | O4: SEI | P4: Tipo Optante | Q4: =F5 -> 01/04/2026 | W4: =Q4+1 -> 46114 | AC4: =W4+1 -> 46115 | AI4: =AC4+1 -> 46116 | AO4: =AI4+1 -> 46117 | AU4: =AO4+1 -> 46118 | BA4: =AU4+1 -> 46119 | BG4: =BA4+1 -> 46120 | BM4: =BG4+1 -> 46121 | BS4: =BM4+1 -> 46122 | BY4: =BS4+1 -> 46123 | CE4: =BY4+1 -> 46124 | CK4: =CE4+1 -> 46125 | CQ4: =CK4+1 -> 46126 | CW4: =CQ4+1 -> 46127 | DC4: =CW4+1 -> 46128 | DI4: =DC4 -> 46128 | DO4: =DI4+1 -> 46129 | DU4: =DO4+1 -> 46130 | EA4: =DU4+1 -> 46131 | EG4: =EA4+1 -> 46132 | EM4: =EG4+1 -> 46133 | ES4: =EM4+1 -> 46134 | EY4: =ES4+1 -> 46135 | FE4: =EY4+1 -> 46136 | FK4: =FE4+1 -> 46137 | FQ4: =FK4+1 -> 46138 | FW4: =FQ4+1 -> 46139 | GC4: =FW4+1 -> 46140 | GI4: =GC4+1 -> 46141 | GO4: =GI4+1 -> 46142 | GU4: =GO4+1 -> 46143
F5: 01/04/2026 | G5: 30/04/2026 | Q5: N CAD presencial | R5: CAD | S5: AT. COMPL. N CAD | T5: AT. COMPL. CAD | U5: Cont N CAD | V5: Cont CAD | W5: N CAD presencial | X5: CAD | Y5: AT. COMPL. N CAD | Z5: AT. COMPL. CAD | AA5: Cont N CAD | AB5: Cont CAD | AC5: N CAD presencial | AD5: CAD | AE5: AT. COMPL. N CAD | AF5: AT. COMPL. CAD | AG5: Cont N CAD | AH5: Cont CAD | AI5: N CAD presencial | AJ5: CAD | AK5: AT. COMPL. N CAD | AL5: AT. COMPL. CAD | AM5: Cont N CAD | AN5: Cont CAD | AO5: N CAD presencial | AP5: CAD | AQ5: AT. COMPL. N CAD | AR5: AT. COMPL. CAD | AS5: Cont N CAD | AT5: Cont CAD | AU5: N CAD presencial | AV5: CAD | AW5: AT. COMPL. N CAD | AX5: AT. COMPL. CAD | AY5: Cont N CAD | AZ5: Cont CAD | BA5: N CAD presencial | BB5: CAD | BC5: AT. COMPL. N CAD | BD5: AT. COMPL. CAD | BE5: Cont N CAD | BF5: Cont CAD | BG5: N CAD presencial | BH5: CAD | BI5: AT. COMPL. N CAD | BJ5: AT. COMPL. CAD | BK5: Cont N CAD | BL5: Cont CAD | BM5: N CAD presencial | BN5: CAD | BO5: AT. COMPL. N CAD | BP5: AT. COMPL. CAD | BQ5: Cont N CAD | BR5: Cont CAD | BS5: N CAD presencial | BT5: CAD | BU5: AT. COMPL. N CAD | BV5: AT. COMPL. CAD | BW5: Cont N CAD | BX5: Cont CAD | BY5: N CAD presencial | BZ5: CAD | CA5: AT. COMPL. N CAD | CB5: AT. COMPL. CAD | CC5: Cont N CAD | CD5: Cont CAD | CE5: N CAD presencial | CF5: CAD | CG5: AT. COMPL. N CAD | CH5: AT. COMPL. CAD | CI5: Cont N CAD | CJ5: Cont CAD | CK5: N CAD presencial | CL5: CAD | CM5: AT. COMPL. N CAD | CN5: AT. COMPL. CAD | CO5: Cont N CAD | CP5: Cont CAD | CQ5: N CAD presencial | CR5: CAD | CS5: AT. COMPL. N CAD | CT5: AT. COMPL. CAD | CU5: Cont N CAD | CV5: Cont CAD | CW5: N CAD presencial | CX5: CAD | CY5: AT. COMPL. N CAD | CZ5: AT. COMPL. CAD | DA5: Cont N CAD | DB5: Cont CAD | DC5: N CAD presencial | DD5: CAD | DE5: AT. COMPL. N CAD | DF5: AT. COMPL. CAD | DG5: Cont N CAD | DH5: Cont CAD | DI5: N CAD presencial | DJ5: CAD | DK5: AT. COMPL. N CAD | DL5: AT. COMPL. CAD | DM5: Cont N CAD | DN5: Cont CAD | DO5: N CAD presencial | DP5: CAD | DQ5: AT. COMPL. N CAD | DR5: AT. COMPL. CAD | DS5: Cont N CAD | DT5: Cont CAD | DU5: N CAD presencial | DV5: CAD | DW5: AT. COMPL. N CAD | DX5: AT. COMPL. CAD | DY5: Cont N CAD | DZ5: Cont CAD | EA5: N CAD presencial | EB5: CAD | EC5: AT. COMPL. N CAD | ED5: AT. COMPL. CAD | EE5: Cont N CAD | EF5: Cont CAD | EG5: N CAD presencial | EH5: CAD | EI5: AT. COMPL. N CAD | EJ5: AT. COMPL. CAD | EK5: Cont N CAD | EL5: Cont CAD | EM5: N CAD presencial | EN5: CAD | EO5: AT. COMPL. N CAD | EP5: AT. COMPL. CAD | EQ5: Cont N CAD | ER5: Cont CAD | ES5: N CAD presencial | ET5: CAD | EU5: AT. COMPL. N CAD | EV5: AT. COMPL. CAD | EW5: Cont N CAD | EX5: Cont CAD | EY5: N CAD presencial | EZ5: CAD | FA5: AT. COMPL. N CAD | FB5: AT. COMPL. CAD | FC5: Cont N CAD | FD5: Cont CAD | FE5: N CAD presencial | FF5: CAD | FG5: AT. COMPL. N CAD | FH5: AT. COMPL. CAD | FI5: Cont N CAD | FJ5: Cont CAD | FK5: N CAD presencial | FL5: CAD | FM5: AT. COMPL. N CAD | FN5: AT. COMPL. CAD | FO5: Cont N CAD | FP5: Cont CAD | FQ5: N CAD presencial | FR5: CAD | FS5: AT. COMPL. N CAD | FT5: AT. COMPL. CAD | FU5: Cont N CAD | FV5: Cont CAD | FW5: N CAD presencial | FX5: CAD | FY5: AT. COMPL. N CAD | FZ5: AT. COMPL. CAD | GA5: Cont N CAD | GB5: Cont CAD | GC5: N CAD presencial | GD5: CAD | GE5: AT. COMPL. N CAD | GF5: AT. COMPL. CAD | GG5: Cont N CAD | GH5: Cont CAD | GI5: N CAD presencial | GJ5: CAD | GK5: AT. COMPL. N CAD | GL5: AT. COMPL. CAD | GM5: Cont N CAD | GN5: Cont CAD | GO5: N CAD presencial | GP5: CAD | GQ5: AT. COMPL. N CAD | GR5: AT. COMPL. CAD | GS5: Cont N CAD | GT5: Cont CAD | GU5: N CAD presencial | GV5: CAD | GW5: AT. COMPL. N CAD | GX5: AT. COMPL. CAD | GY5: Cont N CAD | GZ5: Cont CAD
A6: 019.832-00 | B6: 2022/0031800-001 | C6: 1 | D6: 2022/0031800 | E6: DJB1584 | F6: 01/04/2026 | G6: 30/04/2026 | H6: AJENIAS PEREIRA | I6: AJENIAS PEREIRA | J6: NORMAL | K6: EMEI | L6: =CONTINUA!BV6 -> 0 | M6: =CONTINUA!BW6 -> 0 | O6: 6020.2022/0031800-9 | P6: 0 | Q6: 4 | S6: 0 | U6: 0 | V6: 0 | W6: 4 | Y6: 0 | AA6: 0 | AB6: 0 | AC6: 4 | AE6: 0 | AG6: 0 | AH6: 0 | AI6: 4 | AK6: 0 | AM6: 0 | AN6: 0 | AO6: 4 | AQ6: 0 | AS6: 0 | AT6: 0 | AU6: 4 | AW6: 0 | AY6: 0 | AZ6: 0 | BA6: 4 | BC6: 0 | BE6: 0 | BF6: 0 | BG6: 4 | BI6: 0 | BK6: 0 | BL6: 0 | BM6: 4 | BO6: 0 | BQ6: 0 | BR6: 0 | BS6: 4 | BU6: 0 | BW6: 0 | BX6: 0 | BY6: 4 | CA6: 0 | CC6: 0 | CD6: 0 | CE6: 4 | CG6: 0 | CI6: 0 | CJ6: 0 | CK6: 4 | CM6: 0 | CO6: 0 | CP6: 0 | CQ6: 4 | CS6: 0 | CU6: 0 | CV6: 0 | CW6: 4 | CY6: 0 | DA6: 0 | DB6: 0 | DC6: 4 | DE6: 0 | DG6: 0 | DH6: 0 | DI6: 4 | DK6: 0 | DM6: 0 | DN6: 0 | DO6: 4 | DQ6: 0 | DS6: 0 | DT6: 0 | DU6: 4 | DW6: 0 | DY6: 0 | DZ6: 0 | EA6: 4 | EC6: 0 | EE6: 0 | EF6: 0 | EG6: 4 | EI6: 0 | EK6: 0 | EL6: 0 | EM6: 4 | EO6: 0 | EQ6: 0 | ER6: 0 | ES6: 4 | EU6: 0 | EW6: 0 | EX6: 0 | EY6: 4 | FA6: 0 | FC6: 0 | FD6: 0 | FE6: 4 | FG6: 0 | FI6: 0 | FJ6: 0 | FK6: 4 | FM6: 0 | FO6: 0 | FP6: 0 | FQ6: 4 | FS6: 0 | FU6: 0 | FV6: 0 | FW6: 4 | FY6: 0 | GA6: 0 | GB6: 0 | GC6: 4 | GE6: 0 | GG6: 0 | GH6: 0 | GI6: 4 | GK6: 0 | GM6: 0 | GN6: 0 | GO6: 4 | GQ6: 0 | GS6: 0 | GT6: 0 | GU6: 4 | GW6: 0 | GY6: 0 | GZ6: 0
A7: 019.832-00 | B7: 2022/0031800-001 | C7: G | D7: 2022/0031800 | E7: DJB1584 | F7: 01/04/2026 | G7: 30/04/2026 | H7: AJENIAS PEREIRA | I7: AJENIAS PEREIRA | J7: NORMAL | K7: EMEF | L7: =CONTINUA!BV7 -> 0 | M7: =CONTINUA!BW7 -> 0 | O7: 6020.2022/0031800-9 | P7: 0 | Q7: 49 | S7: 0 | U7: 0 | V7: 0 | W7: 49 | Y7: 0 | AA7: 0 | AB7: 0 | AC7: 49 | AE7: 0 | AG7: 0 | AH7: 0 | AI7: 49 | AK7: 0 | AM7: 0 | AN7: 0 | AO7: 49 | AQ7: 0 | AS7: 0 | AT7: 0 | AU7: 49 | AW7: 0 | AY7: 0 | AZ7: 0 | BA7: 49 | BC7: 0 | BE7: 0 | BF7: 0 | BG7: 49 | BI7: 0 | BK7: 0 | BL7: 0 | BM7: 49 | BO7: 0 | BQ7: 0 | BR7: 0 | BS7: 49 | BU7: 0 | BW7: 0 | BX7: 0 | BY7: 49 | CA7: 0 | CC7: 0 | CD7: 0 | CE7: 49 | CG7: 0 | CI7: 0 | CJ7: 0 | CK7: 49 | CM7: 0 | CO7: 0 | CP7: 0 | CQ7: 49 | CS7: 0 | CU7: 0 | CV7: 0 | CW7: 49 | CY7: 0 | DA7: 0 | DB7: 0 | DC7: 49 | DE7: 0 | DG7: 0 | DH7: 0 | DI7: 49 | DK7: 0 | DM7: 0 | DN7: 0 | DO7: 49 | DQ7: 0 | DS7: 0 | DT7: 0 | DU7: 49 | DW7: 0 | DY7: 0 | DZ7: 0 | EA7: 49 | EC7: 0 | EE7: 0 | EF7: 0 | EG7: 49 | EI7: 0 | EK7: 0 | EL7: 0 | EM7: 49 | EO7: 0 | EQ7: 0 | ER7: 0 | ES7: 49 | EU7: 0 | EW7: 0 | EX7: 0 | EY7: 49 | FA7: 0 | FC7: 0 | FD7: 0 | FE7: 49 | FG7: 0 | FI7: 0 | FJ7: 0 | FK7: 49 | FM7: 0 | FO7: 0 | FP7: 0 | FQ7: 49 | FS7: 0 | FU7: 0 | FV7: 0 | FW7: 49 | FY7: 0 | GA7: 0 | GB7: 0 | GC7: 49 | GE7: 0 | GG7: 0 | GH7: 0 | GI7: 49 | GK7: 0 | GM7: 0 | GN7: 0 | GO7: 49 | GQ7: 0 | GS7: 0 | GT7: 0 | GU7: 49 | GW7: 0 | GY7: 0 | GZ7: 0
A8: 019.832-00 | B8: 2022/0031800-001 | C8: G | D8: 2022/0031800 | E8: DJB1584 | F8: 01/04/2026 | G8: 30/04/2026 | H8: AJENIAS PEREIRA | I8: AJENIAS PEREIRA | J8: NORMAL | K8: EMEE | L8: =CONTINUA!BV8 -> 0 | M8: =CONTINUA!BW8 -> 0 | O8: 6020.2022/0031800-9 | P8: 0 | Q8: 0 | S8: 0 | U8: 0 | V8: 0 | W8: 0 | Y8: 0 | AA8: 0 | AB8: 0 | AC8: 0 | AE8: 0 | AG8: 0 | AH8: 0 | AI8: 0 | AK8: 0 | AM8: 0 | AN8: 0 | AO8: 0 | AQ8: 0 | AS8: 0 | AT8: 0 | AU8: 0 | AW8: 0 | AY8: 0 | AZ8: 0 | BA8: 0 | BC8: 0 | BE8: 0 | BF8: 0 | BG8: 0 | BI8: 0 | BK8: 0 | BL8: 0 | BM8: 0 | BO8: 0 | BQ8: 0 | BR8: 0 | BS8: 0 | BU8: 0 | BW8: 0 | BX8: 0 | BY8: 0 | CA8: 0 | CC8: 0 | CD8: 0 | CE8: 0 | CG8: 0 | CI8: 0 | CJ8: 0 | CK8: 0 | CM8: 0 | CO8: 0 | CP8: 0 | CQ8: 0 | CS8: 0 | CU8: 0 | CV8: 0 | CW8: 0 | CY8: 0 | DA8: 0 | DB8: 0 | DC8: 0 | DE8: 0 | DG8: 0 | DH8: 0 | DI8: 0 | DK8: 0 | DM8: 0 | DN8: 0 | DO8: 0 | DQ8: 0 | DS8: 0 | DT8: 0 | DU8: 0 | DW8: 0 | DY8: 0 | DZ8: 0 | EA8: 0 | EC8: 0 | EE8: 0 | EF8: 0 | EG8: 0 | EI8: 0 | EK8: 0 | EL8: 0 | EM8: 0 | EO8: 0 | EQ8: 0 | ER8: 0 | ES8: 0 | EU8: 0 | EW8: 0 | EX8: 0 | EY8: 0 | FA8: 0 | FC8: 0 | FD8: 0 | FE8: 0 | FG8: 0 | FI8: 0 | FJ8: 0 | FK8: 0 | FM8: 0 | FO8: 0 | FP8: 0 | FQ8: 0 | FS8: 0 | FU8: 0 | FV8: 0 | FW8: 0 | FY8: 0 | GA8: 0 | GB8: 0 | GC8: 0 | GE8: 0 | GG8: 0 | GH8: 0 | GI8: 0 | GK8: 0 | GM8: 0 | GN8: 0 | GO8: 0 | GQ8: 0 | GS8: 0 | GT8: 0 | GU8: 0 | GW8: 0 | GY8: 0 | GZ8: 0
A9: 019.832-00 | B9: 2022/0031800-001 | C9: G | D9: 2022/0031800 | E9: DJB1584 | F9: 01/04/2026 | G9: 30/04/2026 | H9: AJENIAS PEREIRA | I9: AJENIAS PEREIRA | J9: NORMAL | K9: CEI | L9: =CONTINUA!BV9 -> 0 | M9: =CONTINUA!BW9 -> 0 | O9: 6020.2022/0031800-9 | P9: 0 | Q9: 0 | S9: 0 | U9: 0 | V9: 0 | W9: 0 | Y9: 0 | AA9: 0 | AB9: 0 | AC9: 0 | AE9: 0 | AG9: 0 | AH9: 0 | AI9: 0 | AK9: 0 | AM9: 0 | AN9: 0 | AO9: 0 | AQ9: 0 | AS9: 0 | AT9: 0 | AU9: 0 | AW9: 0 | AY9: 0 | AZ9: 0 | BA9: 0 | BC9: 0 | BE9: 0 | BF9: 0 | BG9: 0 | BI9: 0 | BK9: 0 | BL9: 0 | BM9: 0 | BO9: 0 | BQ9: 0 | BR9: 0 | BS9: 0 | BU9: 0 | BW9: 0 | BX9: 0 | BY9: 0 | CA9: 0 | CC9: 0 | CD9: 0 | CE9: 0 | CG9: 0 | CI9: 0 | CJ9: 0 | CK9: 0 | CM9: 0 | CO9: 0 | CP9: 0 | CQ9: 0 | CS9: 0 | CU9: 0 | CV9: 0 | CW9: 0 | CY9: 0 | DA9: 0 | DB9: 0 | DC9: 0 | DE9: 0 | DG9: 0 | DH9: 0 | DI9: 0 | DK9: 0 | DM9: 0 | DN9: 0 | DO9: 0 | DQ9: 0 | DS9: 0 | DT9: 0 | DU9: 0 | DW9: 0 | DY9: 0 | DZ9: 0 | EA9: 0 | EC9: 0 | EE9: 0 | EF9: 0 | EG9: 0 | EI9: 0 | EK9: 0 | EL9: 0 | EM9: 0 | EO9: 0 | EQ9: 0 | ER9: 0 | ES9: 0 | EU9: 0 | EW9: 0 | EX9: 0 | EY9: 0 | FA9: 0 | FC9: 0 | FD9: 0 | FE9: 0 | FG9: 0 | FI9: 0 | FJ9: 0 | FK9: 0 | FM9: 0 | FO9: 0 | FP9: 0 | FQ9: 0 | FS9: 0 | FU9: 0 | FV9: 0 | FW9: 0 | FY9: 0 | GA9: 0 | GB9: 0 | GC9: 0 | GE9: 0 | GG9: 0 | GH9: 0 | GI9: 0 | GK9: 0 | GM9: 0 | GN9: 0 | GO9: 0 | GQ9: 0 | GS9: 0 | GT9: 0 | GU9: 0 | GW9: 0 | GY9: 0 | GZ9: 0
A10: 019.832-00 | B10: 2022/0031800-001 | C10: G | D10: 2022/0031800 | E10: DJB1584 | F10: 01/04/2026 | G10: 30/04/2026 | H10: AJENIAS PEREIRA | I10: AJENIAS PEREIRA | J10: NORMAL | K10: CCA | L10: =CONTINUA!BV10 -> 0 | M10: =CONTINUA!BW10 -> 0 | O10: 6020.2022/0031800-9 | P10: 0 | Q10: 0 | S10: 0 | U10: 0 | V10: 0 | W10: 0 | Y10: 0 | AA10: 0 | AB10: 0 | AC10: 0 | AE10: 0 | AG10: 0 | AH10: 0 | AI10: 0 | AK10: 0 | AM10: 0 | AN10: 0 | AO10: 0 | AQ10: 0 | AS10: 0 | AT10: 0 | AU10: 0 | AW10: 0 | AY10: 0 | AZ10: 0 | BA10: 0 | BC10: 0 | BE10: 0 | BF10: 0 | BG10: 0 | BI10: 0 | BK10: 0 | BL10: 0 | BM10: 0 | BO10: 0 | BQ10: 0 | BR10: 0 | BS10: 0 | BU10: 0 | BW10: 0 | BX10: 0 | BY10: 0 | CA10: 0 | CC10: 0 | CD10: 0 | CE10: 0 | CG10: 0 | CI10: 0 | CJ10: 0 | CK10: 0 | CM10: 0 | CO10: 0 | CP10: 0 | CQ10: 0 | CS10: 0 | CU10: 0 | CV10: 0 | CW10: 0 | CY10: 0 | DA10: 0 | DB10: 0 | DC10: 0 | DE10: 0 | DG10: 0 | DH10: 0 | DI10: 0 | DK10: 0 | DM10: 0 | DN10: 0 | DO10: 0 | DQ10: 0 | DS10: 0 | DT10: 0 | DU10: 0 | DW10: 0 | DY10: 0 | DZ10: 0 | EA10: 0 | EC10: 0 | EE10: 0 | EF10: 0 | EG10: 0 | EI10: 0 | EK10: 0 | EL10: 0 | EM10: 0 | EO10: 0 | EQ10: 0 | ER10: 0 | ES10: 0 | EU10: 0 | EW10: 0 | EX10: 0 | EY10: 0 | FA10: 0 | FC10: 0 | FD10: 0 | FE10: 0 | FG10: 0 | FI10: 0 | FJ10: 0 | FK10: 0 | FM10: 0 | FO10: 0 | FP10: 0 | FQ10: 0 | FS10: 0 | FU10: 0 | FV10: 0 | FW10: 0 | FY10: 0 | GA10: 0 | GB10: 0 | GC10: 0 | GE10: 0 | GG10: 0 | GH10: 0 | GI10: 0 | GK10: 0 | GM10: 0 | GN10: 0 | GO10: 0 | GQ10: 0 | GS10: 0 | GT10: 0 | GU10: 0 | GW10: 0 | GY10: 0 | GZ10: 0
A11: 017.554-00 | B11: 2022/0029218-001 | C11: 1 | D11: 2022/0029218 | E11: CZX5065 | F11: 01/04/2026 | G11: 30/04/2026 | H11: ALTAIR ELIAS CARNEIRO | I11: ALTAIR ELIAS CARNEIRO | J11: NORMAL | K11: EMEI | L11: =CONTINUA!BV11 -> 0 | M11: =CONTINUA!BW11 -> 0 | O11: 6020.2022/0029218-2 | P11: 0 | Q11: 19 | S11: 0 | U11: 0 | V11: 0 | W11: 19 | Y11: 0 | AA11: 0 | AB11: 0 | AC11: 19 | AE11: 0 | AG11: 0 | AH11: 0 | AI11: 19 | AK11: 0 | AM11: 0 | AN11: 0 | AO11: 19 | AQ11: 0 | AS11: 0 | AT11: 0 | AU11: 19 | AW11: 0 | AY11: 0 | AZ11: 0 | BA11: 19 | BC11: 0 | BE11: 0 | BF11: 0 | BG11: 19 | BI11: 0 | BK11: 0 | BL11: 0 | BM11: 19 | BO11: 0 | BQ11: 0 | BR11: 0 | BS11: 19 | BU11: 0 | BW11: 0 | BX11: 0 | BY11: 19 | CA11: 0 | CC11: 0 | CD11: 0 | CE11: 19 | CG11: 0 | CI11: 0 | CJ11: 0 | CK11: 19 | CM11: 0 | CO11: 0 | CP11: 0 | CQ11: 19 | CS11: 0 | CU11: 0 | CV11: 0 | CW11: 19 | CY11: 0 | DA11: 0 | DB11: 0 | DC11: 19 | DE11: 0 | DG11: 0 | DH11: 0 | DI11: 19 | DK11: 0 | DM11: 0 | DN11: 0 | DO11: 19 | DQ11: 0 | DS11: 0 | DT11: 0 | DU11: 19 | DW11: 0 | DY11: 0 | DZ11: 0 | EA11: 19 | EC11: 0 | EE11: 0 | EF11: 0 | EG11: 19 | EI11: 0 | EK11: 0 | EL11: 0 | EM11: 19 | EO11: 0 | EQ11: 0 | ER11: 0 | ES11: 19 | EU11: 0 | EW11: 0 | EX11: 0 | EY11: 19 | FA11: 0 | FC11: 0 | FD11: 0 | FE11: 19 | FG11: 0 | FI11: 0 | FJ11: 0 | FK11: 19 | FM11: 0 | FO11: 0 | FP11: 0 | FQ11: 19 | FS11: 0 | FU11: 0 | FV11: 0 | FW11: 19 | FY11: 0 | GA11: 0 | GB11: 0 | GC11: 19 | GE11: 0 | GG11: 0 | GH11: 0 | GI11: 19 | GK11: 0 | GM11: 0 | GN11: 0 | GO11: 19 | GQ11: 0 | GS11: 0 | GT11: 0 | GU11: 19 | GW11: 0 | GY11: 0 | GZ11: 0
A12: 017.554-00 | B12: 2022/0029218-001 | C12: G | D12: 2022/0029218 | E12: CZX5065 | F12: 01/04/2026 | G12: 30/04/2026 | H12: ALTAIR ELIAS CARNEIRO | I12: ALTAIR ELIAS CARNEIRO | J12: NORMAL | K12: EMEF | L12: =CONTINUA!BV12 -> 0 | M12: =CONTINUA!BW12 -> 0 | O12: 6020.2022/0029218-2 | P12: 0 | Q12: 6 | S12: 0 | U12: 0 | V12: 0 | W12: 6 | Y12: 0 | AA12: 0 | AB12: 0 | AC12: 6 | AE12: 0 | AG12: 0 | AH12: 0 | AI12: 6 | AK12: 0 | AM12: 0 | AN12: 0 | AO12: 6 | AQ12: 0 | AS12: 0 | AT12: 0 | AU12: 6 | AW12: 0 | AY12: 0 | AZ12: 0 | BA12: 6 | BC12: 0 | BE12: 0 | BF12: 0 | BG12: 6 | BI12: 0 | BK12: 0 | BL12: 0 | BM12: 6 | BO12: 0 | BQ12: 0 | BR12: 0 | BS12: 6 | BU12: 0 | BW12: 0 | BX12: 0 | BY12: 6 | CA12: 0 | CC12: 0 | CD12: 0 | CE12: 6 | CG12: 0 | CI12: 0 | CJ12: 0 | CK12: 6 | CM12: 0 | CO12: 0 | CP12: 0 | CQ12: 6 | CS12: 0 | CU12: 0 | CV12: 0 | CW12: 6 | CY12: 0 | DA12: 0 | DB12: 0 | DC12: 6 | DE12: 0 | DG12: 0 | DH12: 0 | DI12: 6 | DK12: 0 | DM12: 0 | DN12: 0 | DO12: 6 | DQ12: 0 | DS12: 0 | DT12: 0 | DU12: 6 | DW12: 0 | DY12: 0 | DZ12: 0 | EA12: 6 | EC12: 0 | EE12: 0 | EF12: 0 | EG12: 6 | EI12: 0 | EK12: 0 | EL12: 0 | EM12: 6 | EO12: 0 | EQ12: 0 | ER12: 0 | ES12: 6 | EU12: 0 | EW12: 0 | EX12: 0 | EY12: 6 | FA12: 0 | FC12: 0 | FD12: 0 | FE12: 6 | FG12: 0 | FI12: 0 | FJ12: 0 | FK12: 6 | FM12: 0 | FO12: 0 | FP12: 0 | FQ12: 6 | FS12: 0 | FU12: 0 | FV12: 0 | FW12: 6 | FY12: 0 | GA12: 0 | GB12: 0 | GC12: 6 | GE12: 0 | GG12: 0 | GH12: 0 | GI12: 6 | GK12: 0 | GM12: 0 | GN12: 0 | GO12: 6 | GQ12: 0 | GS12: 0 | GT12: 0 | GU12: 6 | GW12: 0 | GY12: 0 | GZ12: 0
A13: 017.554-00 | B13: 2022/0029218-001 | C13: G | D13: 2022/0029218 | E13: CZX5065 | F13: 01/04/2026 | G13: 30/04/2026 | H13: ALTAIR ELIAS CARNEIRO | I13: ALTAIR ELIAS CARNEIRO | J13: NORMAL | K13: EMEE | L13: =CONTINUA!BV13 -> 0 | M13: =CONTINUA!BW13 -> 0 | O13: 6020.2022/0029218-2 | P13: 0 | Q13: 0 | S13: 0 | U13: 0 | V13: 0 | W13: 0 | Y13: 0 | AA13: 0 | AB13: 0 | AC13: 0 | AE13: 0 | AG13: 0 | AH13: 0 | AI13: 0 | AK13: 0 | AM13: 0 | AN13: 0 | AO13: 0 | AQ13: 0 | AS13: 0 | AT13: 0 | AU13: 0 | AW13: 0 | AY13: 0 | AZ13: 0 | BA13: 0 | BC13: 0 | BE13: 0 | BF13: 0 | BG13: 0 | BI13: 0 | BK13: 0 | BL13: 0 | BM13: 0 | BO13: 0 | BQ13: 0 | BR13: 0 | BS13: 0 | BU13: 0 | BW13: 0 | BX13: 0 | BY13: 0 | CA13: 0 | CC13: 0 | CD13: 0 | CE13: 0 | CG13: 0 | CI13: 0 | CJ13: 0 | CK13: 0 | CM13: 0 | CO13: 0 | CP13: 0 | CQ13: 0 | CS13: 0 | CU13: 0 | CV13: 0 | CW13: 0 | CY13: 0 | DA13: 0 | DB13: 0 | DC13: 0 | DE13: 0 | DG13: 0 | DH13: 0 | DI13: 0 | DK13: 0 | DM13: 0 | DN13: 0 | DO13: 0 | DQ13: 0 | DS13: 0 | DT13: 0 | DU13: 0 | DW13: 0 | DY13: 0 | DZ13: 0 | EA13: 0 | EC13: 0 | EE13: 0 | EF13: 0 | EG13: 0 | EI13: 0 | EK13: 0 | EL13: 0 | EM13: 0 | EO13: 0 | EQ13: 0 | ER13: 0 | ES13: 0 | EU13: 0 | EW13: 0 | EX13: 0 | EY13: 0 | FA13: 0 | FC13: 0 | FD13: 0 | FE13: 0 | FG13: 0 | FI13: 0 | FJ13: 0 | FK13: 0 | FM13: 0 | FO13: 0 | FP13: 0 | FQ13: 0 | FS13: 0 | FU13: 0 | FV13: 0 | FW13: 0 | FY13: 0 | GA13: 0 | GB13: 0 | GC13: 0 | GE13: 0 | GG13: 0 | GH13: 0 | GI13: 0 | GK13: 0 | GM13: 0 | GN13: 0 | GO13: 0 | GQ13: 0 | GS13: 0 | GT13: 0 | GU13: 0 | GW13: 0 | GY13: 0 | GZ13: 0
A14: 017.554-00 | B14: 2022/0029218-001 | C14: G | D14: 2022/0029218 | E14: CZX5065 | F14: 01/04/2026 | G14: 30/04/2026 | H14: ALTAIR ELIAS CARNEIRO | I14: ALTAIR ELIAS CARNEIRO | J14: NORMAL | K14: CEI | L14: =CONTINUA!BV14 -> 0 | M14: =CONTINUA!BW14 -> 0 | O14: 6020.2022/0029218-2 | P14: 0 | Q14: 0 | S14: 0 | U14: 0 | V14: 0 | W14: 0 | Y14: 0 | AA14: 0 | AB14: 0 | AC14: 0 | AE14: 0 | AG14: 0 | AH14: 0 | AI14: 0 | AK14: 0 | AM14: 0 | AN14: 0 | AO14: 0 | AQ14: 0 | AS14: 0 | AT14: 0 | AU14: 0 | AW14: 0 | AY14: 0 | AZ14: 0 | BA14: 0 | BC14: 0 | BE14: 0 | BF14: 0 | BG14: 0 | BI14: 0 | BK14: 0 | BL14: 0 | BM14: 0 | BO14: 0 | BQ14: 0 | BR14: 0 | BS14: 0 | BU14: 0 | BW14: 0 | BX14: 0 | BY14: 0 | CA14: 0 | CC14: 0 | CD14: 0 | CE14: 0 | CG14: 0 | CI14: 0 | CJ14: 0 | CK14: 0 | CM14: 0 | CO14: 0 | CP14: 0 | CQ14: 0 | CS14: 0 | CU14: 0 | CV14: 0 | CW14: 0 | CY14: 0 | DA14: 0 | DB14: 0 | DC14: 0 | DE14: 0 | DG14: 0 | DH14: 0 | DI14: 0 | DK14: 0 | DM14: 0 | DN14: 0 | DO14: 0 | DQ14: 0 | DS14: 0 | DT14: 0 | DU14: 0 | DW14: 0 | DY14: 0 | DZ14: 0 | EA14: 0 | EC14: 0 | EE14: 0 | EF14: 0 | EG14: 0 | EI14: 0 | EK14: 0 | EL14: 0 | EM14: 0 | EO14: 0 | EQ14: 0 | ER14: 0 | ES14: 0 | EU14: 0 | EW14: 0 | EX14: 0 | EY14: 0 | FA14: 0 | FC14: 0 | FD14: 0 | FE14: 0 | FG14: 0 | FI14: 0 | FJ14: 0 | FK14: 0 | FM14: 0 | FO14: 0 | FP14: 0 | FQ14: 0 | FS14: 0 | FU14: 0 | FV14: 0 | FW14: 0 | FY14: 0 | GA14: 0 | GB14: 0 | GC14: 0 | GE14: 0 | GG14: 0 | GH14: 0 | GI14: 0 | GK14: 0 | GM14: 0 | GN14: 0 | GO14: 0 | GQ14: 0 | GS14: 0 | GT14: 0 | GU14: 0 | GW14: 0 | GY14: 0 | GZ14: 0
A15: 017.554-00 | B15: 2022/0029218-001 | C15: G | D15: 2022/0029218 | E15: CZX5065 | F15: 01/04/2026 | G15: 30/04/2026 | H15: ALTAIR ELIAS CARNEIRO | I15: ALTAIR ELIAS CARNEIRO | J15: NORMAL | K15: CCA | L15: =CONTINUA!BV15 -> 0 | M15: =CONTINUA!BW15 -> 0 | O15: 6020.2022/0029218-2 | P15: 0 | Q15: 0 | S15: 0 | U15: 0 | V15: 0 | W15: 0 | Y15: 0 | AA15: 0 | AB15: 0 | AC15: 0 | AE15: 0 | AG15: 0 | AH15: 0 | AI15: 0 | AK15: 0 | AM15: 0 | AN15: 0 | AO15: 0 | AQ15: 0 | AS15: 0 | AT15: 0 | AU15: 0 | AW15: 0 | AY15: 0 | AZ15: 0 | BA15: 0 | BC15: 0 | BE15: 0 | BF15: 0 | BG15: 0 | BI15: 0 | BK15: 0 | BL15: 0 | BM15: 0 | BO15: 0 | BQ15: 0 | BR15: 0 | BS15: 0 | BU15: 0 | BW15: 0 | BX15: 0 | BY15: 0 | CA15: 0 | CC15: 0 | CD15: 0 | CE15: 0 | CG15: 0 | CI15: 0 | CJ15: 0 | CK15: 0 | CM15: 0 | CO15: 0 | CP15: 0 | CQ15: 0 | CS15: 0 | CU15: 0 | CV15: 0 | CW15: 0 | CY15: 0 | DA15: 0 | DB15: 0 | DC15: 0 | DE15: 0 | DG15: 0 | DH15: 0 | DI15: 0 | DK15: 0 | DM15: 0 | DN15: 0 | DO15: 0 | DQ15: 0 | DS15: 0 | DT15: 0 | DU15: 0 | DW15: 0 | DY15: 0 | DZ15: 0 | EA15: 0 | EC15: 0 | EE15: 0 | EF15: 0 | EG15: 0 | EI15: 0 | EK15: 0 | EL15: 0 | EM15: 0 | EO15: 0 | EQ15: 0 | ER15: 0 | ES15: 0 | EU15: 0 | EW15: 0 | EX15: 0 | EY15: 0 | FA15: 0 | FC15: 0 | FD15: 0 | FE15: 0 | FG15: 0 | FI15: 0 | FJ15: 0 | FK15: 0 | FM15: 0 | FO15: 0 | FP15: 0 | FQ15: 0 | FS15: 0 | FU15: 0 | FV15: 0 | FW15: 0 | FY15: 0 | GA15: 0 | GB15: 0 | GC15: 0 | GE15: 0 | GG15: 0 | GH15: 0 | GI15: 0 | GK15: 0 | GM15: 0 | GN15: 0 | GO15: 0 | GQ15: 0 | GS15: 0 | GT15: 0 | GU15: 0 | GW15: 0 | GY15: 0 | GZ15: 0
A16: 001.119-00 | B16: 2023/0026116-001 | C16: 1 | D16: 2023/0026116 | E16: DTD4303 | F16: 01/04/2026 | G16: 30/04/2026 | H16: ANTONIO ROBERTO GOMES | I16: ANTONIO ROBERTO GOMES | J16: NORMAL | K16: EMEI | L16: =CONTINUA!BV16 -> 0 | M16: =CONTINUA!BW16 -> 0 | O16: 6020.2023/0026116-5 | P16: 0 | Q16: 0 | S16: 0 | U16: 0 | V16: 0 | W16: 0 | Y16: 0 | AA16: 0 | AB16: 0 | AC16: 0 | AE16: 0 | AG16: 0 | AH16: 0 | AI16: 0 | AK16: 0 | AM16: 0 | AN16: 0 | AO16: 0 | AQ16: 0 | AS16: 0 | AT16: 0 | AU16: 0 | AW16: 0 | AY16: 0 | AZ16: 0 | BA16: 0 | BC16: 0 | BE16: 0 | BF16: 0 | BG16: 0 | BI16: 0 | BK16: 0 | BL16: 0 | BM16: 0 | BO16: 0 | BQ16: 0 | BR16: 0 | BS16: 0 | BU16: 0 | BW16: 0 | BX16: 0 | BY16: 0 | CA16: 0 | CC16: 0 | CD16: 0 | CE16: 0 | CG16: 0 | CI16: 0 | CJ16: 0 | CK16: 0 | CM16: 0 | CO16: 0 | CP16: 0 | CQ16: 0 | CS16: 0 | CU16: 0 | CV16: 0 | CW16: 0 | CY16: 0 | DA16: 0 | DB16: 0 | DC16: 0 | DE16: 0 | DG16: 0 | DH16: 0 | DI16: 0 | DK16: 0 | DM16: 0 | DN16: 0 | DO16: 0 | DQ16: 0 | DS16: 0 | DT16: 0 | DU16: 0 | DW16: 0 | DY16: 0 | DZ16: 0 | EA16: 0 | EC16: 0 | EE16: 0 | EF16: 0 | EG16: 0 | EI16: 0 | EK16: 0 | EL16: 0 | EM16: 0 | EO16: 0 | EQ16: 0 | ER16: 0 | ES16: 0 | EU16: 0 | EW16: 0 | EX16: 0 | EY16: 0 | FA16: 0 | FC16: 0 | FD16: 0 | FE16: 0 | FG16: 0 | FI16: 0 | FJ16: 0 | FK16: 0 | FM16: 0 | FO16: 0 | FP16: 0 | FQ16: 0 | FS16: 0 | FU16: 0 | FV16: 0 | FW16: 0 | FY16: 0 | GA16: 0 | GB16: 0 | GC16: 0 | GE16: 0 | GG16: 0 | GH16: 0 | GI16: 0 | GK16: 0 | GM16: 0 | GN16: 0 | GO16: 0 | GQ16: 0 | GS16: 0 | GT16: 0 | GU16: 0 | GW16: 0 | GY16: 0 | GZ16: 0
A17: 001.119-00 | B17: 2023/0026116-001 | C17: G | D17: 2023/0026116 | E17: DTD4303 | F17: 01/04/2026 | G17: 30/04/2026 | H17: ANTONIO ROBERTO GOMES | I17: ANTONIO ROBERTO GOMES | J17: NORMAL | K17: EMEF | L17: =CONTINUA!BV17 -> 24 | M17: =CONTINUA!BW17 -> 0 | O17: 6020.2023/0026116-5 | P17: 0 | Q17: 48 | S17: 5 | U17: 0 | V17: 0 | W17: 48 | Y17: 5 | AA17: 0 | AB17: 0 | AC17: 48 | AE17: 5 | AG17: 0 | AH17: 0 | AI17: 48 | AK17: 5 | AM17: 0 | AN17: 0 | AO17: 48 | AQ17: 5 | AS17: 0 | AT17: 0 | AU17: 48 | AW17: 5 | AY17: 0 | AZ17: 0 | BA17: 48 | BC17: 5 | BE17: 0 | BF17: 0 | BG17: 48 | BI17: 5 | BK17: 0 | BL17: 0 | BM17: 48 | BO17: 5 | BQ17: 0 | BR17: 0 | BS17: 48 | BU17: 5 | BW17: 0 | BX17: 0 | BY17: 48 | CA17: 5 | CC17: 0 | CD17: 0 | CE17: 48 | CG17: 5 | CI17: 0 | CJ17: 0 | CK17: 48 | CM17: 5 | CO17: 0 | CP17: 0 | CQ17: 48 | CS17: 5 | CU17: 0 | CV17: 0 | CW17: 48 | CY17: 5 | DA17: 0 | DB17: 0 | DC17: 48 | DE17: 5 | DG17: 0 | DH17: 0 | DI17: 48 | DK17: 5 | DM17: 0 | DN17: 0 | DO17: 48 | DQ17: 5 | DS17: 0 | DT17: 0 | DU17: 48 | DW17: 5 | DY17: 0 | DZ17: 0 | EA17: 48 | EC17: 5 | EE17: 0 | EF17: 0 | EG17: 48 | EI17: 5 | EK17: 0 | EL17: 0 | EM17: 48 | EO17: 5 | EQ17: 0 | ER17: 0 | ES17: 48 | EU17: 5 | EW17: 0 | EX17: 0 | EY17: 48 | FA17: 5 | FC17: 0 | FD17: 0 | FE17: 48 | FG17: 5 | FI17: 0 | FJ17: 0 | FK17: 48 | FM17: 5 | FO17: 0 | FP17: 0 | FQ17: 48 | FS17: 5 | FU17: 0 | FV17: 0 | FW17: 48 | FY17: 5 | GA17: 0 | GB17: 0 | GC17: 48 | GE17: 5 | GG17: 0 | GH17: 0 | GI17: 48 | GK17: 5 | GM17: 0 | GN17: 0 | GO17: 48 | GQ17: 5 | GS17: 0 | GT17: 0 | GU17: 48 | GW17: 5 | GY17: 0 | GZ17: 0
A18: 001.119-00 | B18: 2023/0026116-001 | C18: G | D18: 2023/0026116 | E18: DTD4303 | F18: 01/04/2026 | G18: 30/04/2026 | H18: ANTONIO ROBERTO GOMES | I18: ANTONIO ROBERTO GOMES | J18: NORMAL | K18: EMEE | L18: =CONTINUA!BV18 -> 0 | M18: =CONTINUA!BW18 -> 0 | O18: 6020.2023/0026116-5 | P18: 0 | Q18: 0 | S18: 0 | U18: 0 | V18: 0 | W18: 0 | Y18: 0 | AA18: 0 | AB18: 0 | AC18: 0 | AE18: 0 | AG18: 0 | AH18: 0 | AI18: 0 | AK18: 0 | AM18: 0 | AN18: 0 | AO18: 0 | AQ18: 0 | AS18: 0 | AT18: 0 | AU18: 0 | AW18: 0 | AY18: 0 | AZ18: 0 | BA18: 0 | BC18: 0 | BE18: 0 | BF18: 0 | BG18: 0 | BI18: 0 | BK18: 0 | BL18: 0 | BM18: 0 | BO18: 0 | BQ18: 0 | BR18: 0 | BS18: 0 | BU18: 0 | BW18: 0 | BX18: 0 | BY18: 0 | CA18: 0 | CC18: 0 | CD18: 0 | CE18: 0 | CG18: 0 | CI18: 0 | CJ18: 0 | CK18: 0 | CM18: 0 | CO18: 0 | CP18: 0 | CQ18: 0 | CS18: 0 | CU18: 0 | CV18: 0 | CW18: 0 | CY18: 0 | DA18: 0 | DB18: 0 | DC18: 0 | DE18: 0 | DG18: 0 | DH18: 0 | DI18: 0 | DK18: 0 | DM18: 0 | DN18: 0 | DO18: 0 | DQ18: 0 | DS18: 0 | DT18: 0 | DU18: 0 | DW18: 0 | DY18: 0 | DZ18: 0 | EA18: 0 | EC18: 0 | EE18: 0 | EF18: 0 | EG18: 0 | EI18: 0 | EK18: 0 | EL18: 0 | EM18: 0 | EO18: 0 | EQ18: 0 | ER18: 0 | ES18: 0 | EU18: 0 | EW18: 0 | EX18: 0 | EY18: 0 | FA18: 0 | FC18: 0 | FD18: 0 | FE18: 0 | FG18: 0 | FI18: 0 | FJ18: 0 | FK18: 0 | FM18: 0 | FO18: 0 | FP18: 0 | FQ18: 0 | FS18: 0 | FU18: 0 | FV18: 0 | FW18: 0 | FY18: 0 | GA18: 0 | GB18: 0 | GC18: 0 | GE18: 0 | GG18: 0 | GH18: 0 | GI18: 0 | GK18: 0 | GM18: 0 | GN18: 0 | GO18: 0 | GQ18: 0 | GS18: 0 | GT18: 0 | GU18: 0 | GW18: 0 | GY18: 0 | GZ18: 0
A19: 001.119-00 | B19: 2023/0026116-001 | C19: G | D19: 2023/0026116 | E19: DTD4303 | F19: 01/04/2026 | G19: 30/04/2026 | H19: ANTONIO ROBERTO GOMES | I19: ANTONIO ROBERTO GOMES | J19: NORMAL | K19: CEI | L19: =CONTINUA!BV19 -> 0 | M19: =CONTINUA!BW19 -> 0 | O19: 6020.2023/0026116-5 | P19: 0 | Q19: 0 | S19: 0 | U19: 0 | V19: 0 | W19: 0 | Y19: 0 | AA19: 0 | AB19: 0 | AC19: 0 | AE19: 0 | AG19: 0 | AH19: 0 | AI19: 0 | AK19: 0 | AM19: 0 | AN19: 0 | AO19: 0 | AQ19: 0 | AS19: 0 | AT19: 0 | AU19: 0 | AW19: 0 | AY19: 0 | AZ19: 0 | BA19: 0 | BC19: 0 | BE19: 0 | BF19: 0 | BG19: 0 | BI19: 0 | BK19: 0 | BL19: 0 | BM19: 0 | BO19: 0 | BQ19: 0 | BR19: 0 | BS19: 0 | BU19: 0 | BW19: 0 | BX19: 0 | BY19: 0 | CA19: 0 | CC19: 0 | CD19: 0 | CE19: 0 | CG19: 0 | CI19: 0 | CJ19: 0 | CK19: 0 | CM19: 0 | CO19: 0 | CP19: 0 | CQ19: 0 | CS19: 0 | CU19: 0 | CV19: 0 | CW19: 0 | CY19: 0 | DA19: 0 | DB19: 0 | DC19: 0 | DE19: 0 | DG19: 0 | DH19: 0 | DI19: 0 | DK19: 0 | DM19: 0 | DN19: 0 | DO19: 0 | DQ19: 0 | DS19: 0 | DT19: 0 | DU19: 0 | DW19: 0 | DY19: 0 | DZ19: 0 | EA19: 0 | EC19: 0 | EE19: 0 | EF19: 0 | EG19: 0 | EI19: 0 | EK19: 0 | EL19: 0 | EM19: 0 | EO19: 0 | EQ19: 0 | ER19: 0 | ES19: 0 | EU19: 0 | EW19: 0 | EX19: 0 | EY19: 0 | FA19: 0 | FC19: 0 | FD19: 0 | FE19: 0 | FG19: 0 | FI19: 0 | FJ19: 0 | FK19: 0 | FM19: 0 | FO19: 0 | FP19: 0 | FQ19: 0 | FS19: 0 | FU19: 0 | FV19: 0 | FW19: 0 | FY19: 0 | GA19: 0 | GB19: 0 | GC19: 0 | GE19: 0 | GG19: 0 | GH19: 0 | GI19: 0 | GK19: 0 | GM19: 0 | GN19: 0 | GO19: 0 | GQ19: 0 | GS19: 0 | GT19: 0 | GU19: 0 | GW19: 0 | GY19: 0 | GZ19: 0
A20: 001.119-00 | B20: 2023/0026116-001 | C20: G | D20: 2023/0026116 | E20: DTD4303 | F20: 01/04/2026 | G20: 30/04/2026 | H20: ANTONIO ROBERTO GOMES | I20: ANTONIO ROBERTO GOMES | J20: NORMAL | K20: CCA | L20: =CONTINUA!BV20 -> 0 | M20: =CONTINUA!BW20 -> 0 | O20: 6020.2023/0026116-5 | P20: 0 | Q20: 0 | S20: 0 | U20: 0 | V20: 0 | W20: 0 | Y20: 0 | AA20: 0 | AB20: 0 | AC20: 0 | AE20: 0 | AG20: 0 | AH20: 0 | AI20: 0 | AK20: 0 | AM20: 0 | AN20: 0 | AO20: 0 | AQ20: 0 | AS20: 0 | AT20: 0 | AU20: 0 | AW20: 0 | AY20: 0 | AZ20: 0 | BA20: 0 | BC20: 0 | BE20: 0 | BF20: 0 | BG20: 0 | BI20: 0 | BK20: 0 | BL20: 0 | BM20: 0 | BO20: 0 | BQ20: 0 | BR20: 0 | BS20: 0 | BU20: 0 | BW20: 0 | BX20: 0 | BY20: 0 | CA20: 0 | CC20: 0 | CD20: 0 | CE20: 0 | CG20: 0 | CI20: 0 | CJ20: 0 | CK20: 0 | CM20: 0 | CO20: 0 | CP20: 0 | CQ20: 0 | CS20: 0 | CU20: 0 | CV20: 0 | CW20: 0 | CY20: 0 | DA20: 0 | DB20: 0 | DC20: 0 | DE20: 0 | DG20: 0 | DH20: 0 | DI20: 0 | DK20: 0 | DM20: 0 | DN20: 0 | DO20: 0 | DQ20: 0 | DS20: 0 | DT20: 0 | DU20: 0 | DW20: 0 | DY20: 0 | DZ20: 0 | EA20: 0 | EC20: 0 | EE20: 0 | EF20: 0 | EG20: 0 | EI20: 0 | EK20: 0 | EL20: 0 | EM20: 0 | EO20: 0 | EQ20: 0 | ER20: 0 | ES20: 0 | EU20: 0 | EW20: 0 | EX20: 0 | EY20: 0 | FA20: 0 | FC20: 0 | FD20: 0 | FE20: 0 | FG20: 0 | FI20: 0 | FJ20: 0 | FK20: 0 | FM20: 0 | FO20: 0 | FP20: 0 | FQ20: 0 | FS20: 0 | FU20: 0 | FV20: 0 | FW20: 0 | FY20: 0 | GA20: 0 | GB20: 0 | GC20: 0 | GE20: 0 | GG20: 0 | GH20: 0 | GI20: 0 | GK20: 0 | GM20: 0 | GN20: 0 | GO20: 0 | GQ20: 0 | GS20: 0 | GT20: 0 | GU20: 0 | GW20: 0 | GY20: 0 | GZ20: 0
A21: 034.861-00 | B21: 2022/0033315-001A | C21: 1 | D21: 2022/0033315 | E21: FQH5J83 | F21: 01/04/2026 | G21: 30/04/2026 | H21: BRUNO EDUARDO BARBOSA | I21: BRUNO EDUARDO BARBOSA | J21: NORMAL | K21: EMEI | L21: =CONTINUA!BV21 -> 0 | M21: =CONTINUA!BW21 -> 0 | O21: 6020.2022/0033315-6 | P21: 0 | Q21: 0 | S21: 0 | U21: 0 | V21: 0 | W21: 0 | Y21: 0 | AA21: 0 | AB21: 0 | AC21: 0 | AE21: 0 | AG21: 0 | AH21: 0 | AI21: 0 | AK21: 0 | AM21: 0 | AN21: 0 | AO21: 0 | AQ21: 0 | AS21: 0 | AT21: 0 | AU21: 0 | AW21: 0 | AY21: 0 | AZ21: 0 | BA21: 0 | BC21: 0 | BE21: 0 | BF21: 0 | BG21: 0 | BI21: 0 | BK21: 0 | BL21: 0 | BM21: 0 | BO21: 0 | BQ21: 0 | BR21: 0 | BS21: 0 | BU21: 0 | BW21: 0 | BX21: 0 | BY21: 0 | CA21: 0 | CC21: 0 | CD21: 0 | CE21: 0 | CG21: 0 | CI21: 0 | CJ21: 0 | CK21: 0 | CM21: 0 | CO21: 0 | CP21: 0 | CQ21: 0 | CS21: 0 | CU21: 0 | CV21: 0 | CW21: 0 | CY21: 0 | DA21: 0 | DB21: 0 | DC21: 0 | DE21: 0 | DG21: 0 | DH21: 0 | DI21: 0 | DK21: 0 | DM21: 0 | DN21: 0 | DO21: 0 | DQ21: 0 | DS21: 0 | DT21: 0 | DU21: 0 | DW21: 0 | DY21: 0 | DZ21: 0 | EA21: 0 | EC21: 0 | EE21: 0 | EF21: 0 | EG21: 0 | EI21: 0 | EK21: 0 | EL21: 0 | EM21: 0 | EO21: 0 | EQ21: 0 | ER21: 0 | ES21: 0 | EU21: 0 | EW21: 0 | EX21: 0 | EY21: 0 | FA21: 0 | FC21: 0 | FD21: 0 | FE21: 0 | FG21: 0 | FI21: 0 | FJ21: 0 | FK21: 0 | FM21: 0 | FO21: 0 | FP21: 0 | FQ21: 0 | FS21: 0 | FU21: 0 | FV21: 0 | FW21: 0 | FY21: 0 | GA21: 0 | GB21: 0 | GC21: 0 | GE21: 0 | GG21: 0 | GH21: 0 | GI21: 0 | GK21: 0 | GM21: 0 | GN21: 0 | GO21: 0 | GQ21: 0 | GS21: 0 | GT21: 0 | GU21: 0 | GW21: 0 | GY21: 0 | GZ21: 0
A22: 034.861-00 | B22: 2022/0033315-001A | C22: G | D22: 2022/0033315 | E22: FQH5J83 | F22: 01/04/2026 | G22: 30/04/2026 | H22: BRUNO EDUARDO BARBOSA | I22: BRUNO EDUARDO BARBOSA | J22: NORMAL | K22: EMEF | L22: =CONTINUA!BV22 -> 16 | M22: =CONTINUA!BW22 -> 0 | O22: 6020.2022/0033315-6 | P22: 0 | Q22: 45 | S22: 0 | U22: 0 | V22: 0 | W22: 45 | Y22: 0 | AA22: 0 | AB22: 0 | AC22: 45 | AE22: 0 | AG22: 0 | AH22: 0 | AI22: 45 | AK22: 0 | AM22: 0 | AN22: 0 | AO22: 45 | AQ22: 0 | AS22: 0 | AT22: 0 | AU22: 45 | AW22: 0 | AY22: 0 | AZ22: 0 | BA22: 45 | BC22: 0 | BE22: 0 | BF22: 0 | BG22: 45 | BI22: 0 | BK22: 0 | BL22: 0 | BM22: 45 | BO22: 0 | BQ22: 0 | BR22: 0 | BS22: 45 | BU22: 0 | BW22: 0 | BX22: 0 | BY22: 45 | CA22: 0 | CC22: 0 | CD22: 0 | CE22: 45 | CG22: 0 | CI22: 0 | CJ22: 0 | CK22: 45 | CM22: 0 | CO22: 0 | CP22: 0 | CQ22: 45 | CS22: 0 | CU22: 0 | CV22: 0 | CW22: 45 | CY22: 0 | DA22: 0 | DB22: 0 | DC22: 45 | DE22: 0 | DG22: 0 | DH22: 0 | DI22: 45 | DK22: 0 | DM22: 0 | DN22: 0 | DO22: 45 | DQ22: 0 | DS22: 0 | DT22: 0 | DU22: 45 | DW22: 0 | DY22: 0 | DZ22: 0 | EA22: 45 | EC22: 0 | EE22: 0 | EF22: 0 | EG22: 45 | EI22: 0 | EK22: 0 | EL22: 0 | EM22: 45 | EO22: 0 | EQ22: 0 | ER22: 0 | ES22: 45 | EU22: 0 | EW22: 0 | EX22: 0 | EY22: 45 | FA22: 0 | FC22: 0 | FD22: 0 | FE22: 45 | FG22: 0 | FI22: 0 | FJ22: 0 | FK22: 45 | FM22: 0 | FO22: 0 | FP22: 0 | FQ22: 45 | FS22: 0 | FU22: 0 | FV22: 0 | FW22: 45 | FY22: 0 | GA22: 0 | GB22: 0 | GC22: 45 | GE22: 0 | GG22: 0 | GH22: 0 | GI22: 45 | GK22: 0 | GM22: 0 | GN22: 0 | GO22: 45 | GQ22: 0 | GS22: 0 | GT22: 0 | GU22: 45 | GW22: 0 | GY22: 0 | GZ22: 0
A23: 034.861-00 | B23: 2022/0033315-001A | C23: G | D23: 2022/0033315 | E23: FQH5J83 | F23: 01/04/2026 | G23: 30/04/2026 | H23: BRUNO EDUARDO BARBOSA | I23: BRUNO EDUARDO BARBOSA | J23: NORMAL | K23: EMEE | L23: =CONTINUA!BV23 -> 0 | M23: =CONTINUA!BW23 -> 0 | O23: 6020.2022/0033315-6 | P23: 0 | Q23: 0 | S23: 0 | U23: 0 | V23: 0 | W23: 0 | Y23: 0 | AA23: 0 | AB23: 0 | AC23: 0 | AE23: 0 | AG23: 0 | AH23: 0 | AI23: 0 | AK23: 0 | AM23: 0 | AN23: 0 | AO23: 0 | AQ23: 0 | AS23: 0 | AT23: 0 | AU23: 0 | AW23: 0 | AY23: 0 | AZ23: 0 | BA23: 0 | BC23: 0 | BE23: 0 | BF23: 0 | BG23: 0 | BI23: 0 | BK23: 0 | BL23: 0 | BM23: 0 | BO23: 0 | BQ23: 0 | BR23: 0 | BS23: 0 | BU23: 0 | BW23: 0 | BX23: 0 | BY23: 0 | CA23: 0 | CC23: 0 | CD23: 0 | CE23: 0 | CG23: 0 | CI23: 0 | CJ23: 0 | CK23: 0 | CM23: 0 | CO23: 0 | CP23: 0 | CQ23: 0 | CS23: 0 | CU23: 0 | CV23: 0 | CW23: 0 | CY23: 0 | DA23: 0 | DB23: 0 | DC23: 0 | DE23: 0 | DG23: 0 | DH23: 0 | DI23: 0 | DK23: 0 | DM23: 0 | DN23: 0 | DO23: 0 | DQ23: 0 | DS23: 0 | DT23: 0 | DU23: 0 | DW23: 0 | DY23: 0 | DZ23: 0 | EA23: 0 | EC23: 0 | EE23: 0 | EF23: 0 | EG23: 0 | EI23: 0 | EK23: 0 | EL23: 0 | EM23: 0 | EO23: 0 | EQ23: 0 | ER23: 0 | ES23: 0 | EU23: 0 | EW23: 0 | EX23: 0 | EY23: 0 | FA23: 0 | FC23: 0 | FD23: 0 | FE23: 0 | FG23: 0 | FI23: 0 | FJ23: 0 | FK23: 0 | FM23: 0 | FO23: 0 | FP23: 0 | FQ23: 0 | FS23: 0 | FU23: 0 | FV23: 0 | FW23: 0 | FY23: 0 | GA23: 0 | GB23: 0 | GC23: 0 | GE23: 0 | GG23: 0 | GH23: 0 | GI23: 0 | GK23: 0 | GM23: 0 | GN23: 0 | GO23: 0 | GQ23: 0 | GS23: 0 | GT23: 0 | GU23: 0 | GW23: 0 | GY23: 0 | GZ23: 0
A24: 034.861-00 | B24: 2022/0033315-001A | C24: G | D24: 2022/0033315 | E24: FQH5J83 | F24: 01/04/2026 | G24: 30/04/2026 | H24: BRUNO EDUARDO BARBOSA | I24: BRUNO EDUARDO BARBOSA | J24: NORMAL | K24: CEI | L24: =CONTINUA!BV24 -> 0 | M24: =CONTINUA!BW24 -> 0 | O24: 6020.2022/0033315-6 | P24: 0 | Q24: 0 | S24: 0 | U24: 0 | V24: 0 | W24: 0 | Y24: 0 | AA24: 0 | AB24: 0 | AC24: 0 | AE24: 0 | AG24: 0 | AH24: 0 | AI24: 0 | AK24: 0 | AM24: 0 | AN24: 0 | AO24: 0 | AQ24: 0 | AS24: 0 | AT24: 0 | AU24: 0 | AW24: 0 | AY24: 0 | AZ24: 0 | BA24: 0 | BC24: 0 | BE24: 0 | BF24: 0 | BG24: 0 | BI24: 0 | BK24: 0 | BL24: 0 | BM24: 0 | BO24: 0 | BQ24: 0 | BR24: 0 | BS24: 0 | BU24: 0 | BW24: 0 | BX24: 0 | BY24: 0 | CA24: 0 | CC24: 0 | CD24: 0 | CE24: 0 | CG24: 0 | CI24: 0 | CJ24: 0 | CK24: 0 | CM24: 0 | CO24: 0 | CP24: 0 | CQ24: 0 | CS24: 0 | CU24: 0 | CV24: 0 | CW24: 0 | CY24: 0 | DA24: 0 | DB24: 0 | DC24: 0 | DE24: 0 | DG24: 0 | DH24: 0 | DI24: 0 | DK24: 0 | DM24: 0 | DN24: 0 | DO24: 0 | DQ24: 0 | DS24: 0 | DT24: 0 | DU24: 0 | DW24: 0 | DY24: 0 | DZ24: 0 | EA24: 0 | EC24: 0 | EE24: 0 | EF24: 0 | EG24: 0 | EI24: 0 | EK24: 0 | EL24: 0 | EM24: 0 | EO24: 0 | EQ24: 0 | ER24: 0 | ES24: 0 | EU24: 0 | EW24: 0 | EX24: 0 | EY24: 0 | FA24: 0 | FC24: 0 | FD24: 0 | FE24: 0 | FG24: 0 | FI24: 0 | FJ24: 0 | FK24: 0 | FM24: 0 | FO24: 0 | FP24: 0 | FQ24: 0 | FS24: 0 | FU24: 0 | FV24: 0 | FW24: 0 | FY24: 0 | GA24: 0 | GB24: 0 | GC24: 0 | GE24: 0 | GG24: 0 | GH24: 0 | GI24: 0 | GK24: 0 | GM24: 0 | GN24: 0 | GO24: 0 | GQ24: 0 | GS24: 0 | GT24: 0 | GU24: 0 | GW24: 0 | GY24: 0 | GZ24: 0
A25: 034.861-00 | B25: 2022/0033315-001A | C25: G | D25: 2022/0033315 | E25: FQH5J83 | F25: 01/04/2026 | G25: 30/04/2026 | H25: BRUNO EDUARDO BARBOSA | I25: BRUNO EDUARDO BARBOSA | J25: NORMAL | K25: CCA | L25: =CONTINUA!BV25 -> 0 | M25: =CONTINUA!BW25 -> 0 | O25: 6020.2022/0033315-6 | P25: 0 | Q25: 0 | S25: 0 | U25: 0 | V25: 0 | W25: 0 | Y25: 0 | AA25: 0 | AB25: 0 | AC25: 0 | AE25: 0 | AG25: 0 | AH25: 0 | AI25: 0 | AK25: 0 | AM25: 0 | AN25: 0 | AO25: 0 | AQ25: 0 | AS25: 0 | AT25: 0 | AU25: 0 | AW25: 0 | AY25: 0 | AZ25: 0 | BA25: 0 | BC25: 0 | BE25: 0 | BF25: 0 | BG25: 0 | BI25: 0 | BK25: 0 | BL25: 0 | BM25: 0 | BO25: 0 | BQ25: 0 | BR25: 0 | BS25: 0 | BU25: 0 | BW25: 0 | BX25: 0 | BY25: 0 | CA25: 0 | CC25: 0 | CD25: 0 | CE25: 0 | CG25: 0 | CI25: 0 | CJ25: 0 | CK25: 0 | CM25: 0 | CO25: 0 | CP25: 0 | CQ25: 0 | CS25: 0 | CU25: 0 | CV25: 0 | CW25: 0 | CY25: 0 | DA25: 0 | DB25: 0 | DC25: 0 | DE25: 0 | DG25: 0 | DH25: 0 | DI25: 0 | DK25: 0 | DM25: 0 | DN25: 0 | DO25: 0 | DQ25: 0 | DS25: 0 | DT25: 0 | DU25: 0 | DW25: 0 | DY25: 0 | DZ25: 0 | EA25: 0 | EC25: 0 | EE25: 0 | EF25: 0 | EG25: 0 | EI25: 0 | EK25: 0 | EL25: 0 | EM25: 0 | EO25: 0 | EQ25: 0 | ER25: 0 | ES25: 0 | EU25: 0 | EW25: 0 | EX25: 0 | EY25: 0 | FA25: 0 | FC25: 0 | FD25: 0 | FE25: 0 | FG25: 0 | FI25: 0 | FJ25: 0 | FK25: 0 | FM25: 0 | FO25: 0 | FP25: 0 | FQ25: 0 | FS25: 0 | FU25: 0 | FV25: 0 | FW25: 0 | FY25: 0 | GA25: 0 | GB25: 0 | GC25: 0 | GE25: 0 | GG25: 0 | GH25: 0 | GI25: 0 | GK25: 0 | GM25: 0 | GN25: 0 | GO25: 0 | GQ25: 0 | GS25: 0 | GT25: 0 | GU25: 0 | GW25: 0 | GY25: 0 | GZ25: 0
A26: 020.989-00 | B26: 2022/0034309-001B | C26: 2 | D26: 2022/0034309 | E26: FRC8739 | F26: 01/04/2026 | G26: 30/04/2026 | H26: CARLOS ALBERTO DE ARAUJO | I26: CARLOS ALBERTO DE ARAUJO | J26: ADAPTADO | K26: EMEI | L26: =CONTINUA!BV26 -> 0 | M26: =CONTINUA!BW26 -> 0 | O26: 6020.2022/0034309-7 | P26: 0 | Q26: 0 | R26: 2 | S26: 0 | T26: 0 | U26: 0 | V26: 0 | W26: 0 | X26: 2 | Y26: 0 | Z26: 0 | AA26: 0 | AB26: 0 | AC26: 0 | AD26: 2 | AE26: 0 | AF26: 0 | AG26: 0 | AH26: 0 | AI26: 0 | AJ26: 2 | AK26: 0 | AL26: 0 | AM26: 0 | AN26: 0 | AO26: 0 | AP26: 2 | AQ26: 0 | AR26: 0 | AS26: 0 | AT26: 0 | AU26: 0 | AV26: 2 | AW26: 0 | AX26: 0 | AY26: 0 | AZ26: 0 | BA26: 0 | BB26: 2 | BC26: 0 | BD26: 0 | BE26: 0 | BF26: 0 | BG26: 0 | BH26: 2 | BI26: 0 | BJ26: 0 | BK26: 0 | BL26: 0 | BM26: 0 | BN26: 2 | BO26: 0 | BP26: 0 | BQ26: 0 | BR26: 0 | BS26: 0 | BT26: 2 | BU26: 0 | BV26: 0 | BW26: 0 | BX26: 0 | BY26: 0 | BZ26: 2 | CA26: 0 | CB26: 0 | CC26: 0 | CD26: 0 | CE26: 0 | CF26: 2 | CG26: 0 | CH26: 0 | CI26: 0 | CJ26: 0 | CK26: 0 | CL26: 2 | CM26: 0 | CN26: 0 | CO26: 0 | CP26: 0 | CQ26: 0 | CR26: 2 | CS26: 0 | CT26: 0 | CU26: 0 | CV26: 0 | CW26: 0 | CX26: 2 | CY26: 0 | CZ26: 0 | DA26: 0 | DB26: 0 | DC26: 0 | DD26: 2 | DE26: 0 | DF26: 0 | DG26: 0 | DH26: 0 | DI26: 0 | DJ26: 2 | DK26: 0 | DL26: 0 | DM26: 0 | DN26: 0 | DO26: 0 | DP26: 2 | DQ26: 0 | DR26: 0 | DS26: 0 | DT26: 0 | DU26: 0 | DV26: 2 | DW26: 0 | DX26: 0 | DY26: 0 | DZ26: 0 | EA26: 0 | EB26: 2 | EC26: 0 | ED26: 0 | EE26: 0 | EF26: 0 | EG26: 0 | EH26: 2 | EI26: 0 | EJ26: 0 | EK26: 0 | EL26: 0 | EM26: 0 | EN26: 2 | EO26: 0 | EP26: 0 | EQ26: 0 | ER26: 0 | ES26: 0 | ET26: 2 | EU26: 0 | EV26: 0 | EW26: 0 | EX26: 0 | EY26: 0 | EZ26: 2 | FA26: 0 | FB26: 0 | FC26: 0 | FD26: 0 | FE26: 0 | FF26: 2 | FG26: 0 | FH26: 0 | FI26: 0 | FJ26: 0 | FK26: 0 | FL26: 2 | FM26: 0 | FN26: 0 | FO26: 0 | FP26: 0 | FQ26: 0 | FR26: 2 | FS26: 0 | FT26: 0 | FU26: 0 | FV26: 0 | FW26: 0 | FX26: 2 | FY26: 0 | FZ26: 0 | GA26: 0 | GB26: 0 | GC26: 0 | GD26: 2 | GE26: 0 | GF26: 0 | GG26: 0 | GH26: 0 | GI26: 0 | GJ26: 2 | GK26: 0 | GL26: 0 | GM26: 0 | GN26: 0 | GO26: 0 | GP26: 2 | GQ26: 0 | GR26: 0 | GS26: 0 | GT26: 0 | GU26: 0 | GV26: 2 | GW26: 0 | GX26: 0 | GY26: 0 | GZ26: 0
A27: 020.989-00 | B27: 2022/0034309-001B | C27: G | D27: 2022/0034309 | E27: FRC8739 | F27: 01/04/2026 | G27: 30/04/2026 | H27: CARLOS ALBERTO DE ARAUJO | I27: CARLOS ALBERTO DE ARAUJO | J27: ADAPTADO | K27: EMEF | L27: =CONTINUA!BV27 -> 0 | M27: =CONTINUA!BW27 -> 0 | O27: 6020.2022/0034309-7 | P27: 0 | Q27: 14 | R27: 2 | S27: 8 | T27: 0 | U27: 0 | V27: 0 | W27: 14 | X27: 2 | Y27: 8 | Z27: 0 | AA27: 0 | AB27: 0 | AC27: 14 | AD27: 2 | AE27: 8 | AF27: 0 | AG27: 0 | AH27: 0 | AI27: 14 | AJ27: 2 | AK27: 8 | AL27: 0 | AM27: 0 | AN27: 0 | AO27: 14 | AP27: 2 | AQ27: 8 | AR27: 0 | AS27: 0 | AT27: 0 | AU27: 14 | AV27: 2 | AW27: 8 | AX27: 0 | AY27: 0 | AZ27: 0 | BA27: 14 | BB27: 2 | BC27: 8 | BD27: 0 | BE27: 0 | BF27: 0 | BG27: 14 | BH27: 2 | BI27: 8 | BJ27: 0 | BK27: 0 | BL27: 0 | BM27: 14 | BN27: 2 | BO27: 8 | BP27: 0 | BQ27: 0 | BR27: 0 | BS27: 14 | BT27: 2 | BU27: 8 | BV27: 0 | BW27: 0 | BX27: 0 | BY27: 14 | BZ27: 2 | CA27: 8 | CB27: 0 | CC27: 0 | CD27: 0 | CE27: 14 | CF27: 2 | CG27: 8 | CH27: 0 | CI27: 0 | CJ27: 0 | CK27: 14 | CL27: 2 | CM27: 8 | CN27: 0 | CO27: 0 | CP27: 0 | CQ27: 14 | CR27: 2 | CS27: 8 | CT27: 0 | CU27: 0 | CV27: 0 | CW27: 14 | CX27: 2 | CY27: 8 | CZ27: 0 | DA27: 0 | DB27: 0 | DC27: 14 | DD27: 2 | DE27: 8 | DF27: 0 | DG27: 0 | DH27: 0 | DI27: 14 | DJ27: 2 | DK27: 8 | DL27: 0 | DM27: 0 | DN27: 0 | DO27: 14 | DP27: 2 | DQ27: 8 | DR27: 0 | DS27: 0 | DT27: 0 | DU27: 14 | DV27: 2 | DW27: 8 | DX27: 0 | DY27: 0 | DZ27: 0 | EA27: 14 | EB27: 2 | EC27: 8 | ED27: 0 | EE27: 0 | EF27: 0 | EG27: 14 | EH27: 2 | EI27: 8 | EJ27: 0 | EK27: 0 | EL27: 0 | EM27: 14 | EN27: 2 | EO27: 8 | EP27: 0 | EQ27: 0 | ER27: 0 | ES27: 14 | ET27: 2 | EU27: 8 | EV27: 0 | EW27: 0 | EX27: 0 | EY27: 14 | EZ27: 2 | FA27: 8 | FB27: 0 | FC27: 0 | FD27: 0 | FE27: 14 | FF27: 2 | FG27: 8 | FH27: 0 | FI27: 0 | FJ27: 0 | FK27: 14 | FL27: 2 | FM27: 8 | FN27: 0 | FO27: 0 | FP27: 0 | FQ27: 14 | FR27: 2 | FS27: 8 | FT27: 0 | FU27: 0 | FV27: 0 | FW27: 14 | FX27: 2 | FY27: 8 | FZ27: 0 | GA27: 0 | GB27: 0 | GC27: 14 | GD27: 2 | GE27: 8 | GF27: 0 | GG27: 0 | GH27: 0 | GI27: 14 | GJ27: 2 | GK27: 8 | GL27: 0 | GM27: 0 | GN27: 0 | GO27: 14 | GP27: 2 | GQ27: 8 | GR27: 0 | GS27: 0 | GT27: 0 | GU27: 14 | GV27: 2 | GW27: 8 | GX27: 0 | GY27: 0 | GZ27: 0
A28: 020.989-00 | B28: 2022/0034309-001B | C28: G | D28: 2022/0034309 | E28: FRC8739 | F28: 01/04/2026 | G28: 30/04/2026 | H28: CARLOS ALBERTO DE ARAUJO | I28: CARLOS ALBERTO DE ARAUJO | J28: ADAPTADO | K28: EMEE | L28: =CONTINUA!BV28 -> 0 | M28: =CONTINUA!BW28 -> 0 | O28: 6020.2022/0034309-7 | P28: 0 | Q28: 0 | R28: 0 | S28: 0 | T28: 0 | U28: 0 | V28: 0 | W28: 0 | X28: 0 | Y28: 0 | Z28: 0 | AA28: 0 | AB28: 0 | AC28: 0 | AD28: 0 | AE28: 0 | AF28: 0 | AG28: 0 | AH28: 0 | AI28: 0 | AJ28: 0 | AK28: 0 | AL28: 0 | AM28: 0 | AN28: 0 | AO28: 0 | AP28: 0 | AQ28: 0 | AR28: 0 | AS28: 0 | AT28: 0 | AU28: 0 | AV28: 0 | AW28: 0 | AX28: 0 | AY28: 0 | AZ28: 0 | BA28: 0 | BB28: 0 | BC28: 0 | BD28: 0 | BE28: 0 | BF28: 0 | BG28: 0 | BH28: 0 | BI28: 0 | BJ28: 0 | BK28: 0 | BL28: 0 | BM28: 0 | BN28: 0 | BO28: 0 | BP28: 0 | BQ28: 0 | BR28: 0 | BS28: 0 | BT28: 0 | BU28: 0 | BV28: 0 | BW28: 0 | BX28: 0 | BY28: 0 | BZ28: 0 | CA28: 0 | CB28: 0 | CC28: 0 | CD28: 0 | CE28: 0 | CF28: 0 | CG28: 0 | CH28: 0 | CI28: 0 | CJ28: 0 | CK28: 0 | CL28: 0 | CM28: 0 | CN28: 0 | CO28: 0 | CP28: 0 | CQ28: 0 | CR28: 0 | CS28: 0 | CT28: 0 | CU28: 0 | CV28: 0 | CW28: 0 | CX28: 0 | CY28: 0 | CZ28: 0 | DA28: 0 | DB28: 0 | DC28: 0 | DD28: 0 | DE28: 0 | DF28: 0 | DG28: 0 | DH28: 0 | DI28: 0 | DJ28: 0 | DK28: 0 | DL28: 0 | DM28: 0 | DN28: 0 | DO28: 0 | DP28: 0 | DQ28: 0 | DR28: 0 | DS28: 0 | DT28: 0 | DU28: 0 | DV28: 0 | DW28: 0 | DX28: 0 | DY28: 0 | DZ28: 0 | EA28: 0 | EB28: 0 | EC28: 0 | ED28: 0 | EE28: 0 | EF28: 0 | EG28: 0 | EH28: 0 | EI28: 0 | EJ28: 0 | EK28: 0 | EL28: 0 | EM28: 0 | EN28: 0 | EO28: 0 | EP28: 0 | EQ28: 0 | ER28: 0 | ES28: 0 | ET28: 0 | EU28: 0 | EV28: 0 | EW28: 0 | EX28: 0 | EY28: 0 | EZ28: 0 | FA28: 0 | FB28: 0 | FC28: 0 | FD28: 0 | FE28: 0 | FF28: 0 | FG28: 0 | FH28: 0 | FI28: 0 | FJ28: 0 | FK28: 0 | FL28: 0 | FM28: 0 | FN28: 0 | FO28: 0 | FP28: 0 | FQ28: 0 | FR28: 0 | FS28: 0 | FT28: 0 | FU28: 0 | FV28: 0 | FW28: 0 | FX28: 0 | FY28: 0 | FZ28: 0 | GA28: 0 | GB28: 0 | GC28: 0 | GD28: 0 | GE28: 0 | GF28: 0 | GG28: 0 | GH28: 0 | GI28: 0 | GJ28: 0 | GK28: 0 | GL28: 0 | GM28: 0 | GN28: 0 | GO28: 0 | GP28: 0 | GQ28: 0 | GR28: 0 | GS28: 0 | GT28: 0 | GU28: 0 | GV28: 0 | GW28: 0 | GX28: 0 | GY28: 0 | GZ28: 0
A29: 020.989-00 | B29: 2022/0034309-001B | C29: G | D29: 2022/0034309 | E29: FRC8739 | F29: 01/04/2026 | G29: 30/04/2026 | H29: CARLOS ALBERTO DE ARAUJO | I29: CARLOS ALBERTO DE ARAUJO | J29: ADAPTADO | K29: CEI | L29: =CONTINUA!BV29 -> 0 | M29: =CONTINUA!BW29 -> 0 | O29: 6020.2022/0034309-7 | P29: 0 | Q29: 0 | R29: 0 | S29: 0 | T29: 0 | U29: 0 | V29: 0 | W29: 0 | X29: 0 | Y29: 0 | Z29: 0 | AA29: 0 | AB29: 0 | AC29: 0 | AD29: 0 | AE29: 0 | AF29: 0 | AG29: 0 | AH29: 0 | AI29: 0 | AJ29: 0 | AK29: 0 | AL29: 0 | AM29: 0 | AN29: 0 | AO29: 0 | AP29: 0 | AQ29: 0 | AR29: 0 | AS29: 0 | AT29: 0 | AU29: 0 | AV29: 0 | AW29: 0 | AX29: 0 | AY29: 0 | AZ29: 0 | BA29: 0 | BB29: 0 | BC29: 0 | BD29: 0 | BE29: 0 | BF29: 0 | BG29: 0 | BH29: 0 | BI29: 0 | BJ29: 0 | BK29: 0 | BL29: 0 | BM29: 0 | BN29: 0 | BO29: 0 | BP29: 0 | BQ29: 0 | BR29: 0 | BS29: 0 | BT29: 0 | BU29: 0 | BV29: 0 | BW29: 0 | BX29: 0 | BY29: 0 | BZ29: 0 | CA29: 0 | CB29: 0 | CC29: 0 | CD29: 0 | CE29: 0 | CF29: 0 | CG29: 0 | CH29: 0 | CI29: 0 | CJ29: 0 | CK29: 0 | CL29: 0 | CM29: 0 | CN29: 0 | CO29: 0 | CP29: 0 | CQ29: 0 | CR29: 0 | CS29: 0 | CT29: 0 | CU29: 0 | CV29: 0 | CW29: 0 | CX29: 0 | CY29: 0 | CZ29: 0 | DA29: 0 | DB29: 0 | DC29: 0 | DD29: 0 | DE29: 0 | DF29: 0 | DG29: 0 | DH29: 0 | DI29: 0 | DJ29: 0 | DK29: 0 | DL29: 0 | DM29: 0 | DN29: 0 | DO29: 0 | DP29: 0 | DQ29: 0 | DR29: 0 | DS29: 0 | DT29: 0 | DU29: 0 | DV29: 0 | DW29: 0 | DX29: 0 | DY29: 0 | DZ29: 0 | EA29: 0 | EB29: 0 | EC29: 0 | ED29: 0 | EE29: 0 | EF29: 0 | EG29: 0 | EH29: 0 | EI29: 0 | EJ29: 0 | EK29: 0 | EL29: 0 | EM29: 0 | EN29: 0 | EO29: 0 | EP29: 0 | EQ29: 0 | ER29: 0 | ES29: 0 | ET29: 0 | EU29: 0 | EV29: 0 | EW29: 0 | EX29: 0 | EY29: 0 | EZ29: 0 | FA29: 0 | FB29: 0 | FC29: 0 | FD29: 0 | FE29: 0 | FF29: 0 | FG29: 0 | FH29: 0 | FI29: 0 | FJ29: 0 | FK29: 0 | FL29: 0 | FM29: 0 | FN29: 0 | FO29: 0 | FP29: 0 | FQ29: 0 | FR29: 0 | FS29: 0 | FT29: 0 | FU29: 0 | FV29: 0 | FW29: 0 | FX29: 0 | FY29: 0 | FZ29: 0 | GA29: 0 | GB29: 0 | GC29: 0 | GD29: 0 | GE29: 0 | GF29: 0 | GG29: 0 | GH29: 0 | GI29: 0 | GJ29: 0 | GK29: 0 | GL29: 0 | GM29: 0 | GN29: 0 | GO29: 0 | GP29: 0 | GQ29: 0 | GR29: 0 | GS29: 0 | GT29: 0 | GU29: 0 | GV29: 0 | GW29: 0 | GX29: 0 | GY29: 0 | GZ29: 0
A30: 020.989-00 | B30: 2022/0034309-001B | C30: G | D30: 2022/0034309 | E30: FRC8739 | F30: 01/04/2026 | G30: 30/04/2026 | H30: CARLOS ALBERTO DE ARAUJO | I30: CARLOS ALBERTO DE ARAUJO | J30: ADAPTADO | K30: CCA | L30: =CONTINUA!BV30 -> 0 | M30: =CONTINUA!BW30 -> 0 | O30: 6020.2022/0034309-7 | P30: 0 | Q30: 0 | R30: 0 | S30: 0 | T30: 0 | U30: 0 | V30: 0 | W30: 0 | X30: 0 | Y30: 0 | Z30: 0 | AA30: 0 | AB30: 0 | AC30: 0 | AD30: 0 | AE30: 0 | AF30: 0 | AG30: 0 | AH30: 0 | AI30: 0 | AJ30: 0 | AK30: 0 | AL30: 0 | AM30: 0 | AN30: 0 | AO30: 0 | AP30: 0 | AQ30: 0 | AR30: 0 | AS30: 0 | AT30: 0 | AU30: 0 | AV30: 0 | AW30: 0 | AX30: 0 | AY30: 0 | AZ30: 0 | BA30: 0 | BB30: 0 | BC30: 0 | BD30: 0 | BE30: 0 | BF30: 0 | BG30: 0 | BH30: 0 | BI30: 0 | BJ30: 0 | BK30: 0 | BL30: 0 | BM30: 0 | BN30: 0 | BO30: 0 | BP30: 0 | BQ30: 0 | BR30: 0 | BS30: 0 | BT30: 0 | BU30: 0 | BV30: 0 | BW30: 0 | BX30: 0 | BY30: 0 | BZ30: 0 | CA30: 0 | CB30: 0 | CC30: 0 | CD30: 0 | CE30: 0 | CF30: 0 | CG30: 0 | CH30: 0 | CI30: 0 | CJ30: 0 | CK30: 0 | CL30: 0 | CM30: 0 | CN30: 0 | CO30: 0 | CP30: 0 | CQ30: 0 | CR30: 0 | CS30: 0 | CT30: 0 | CU30: 0 | CV30: 0 | CW30: 0 | CX30: 0 | CY30: 0 | CZ30: 0 | DA30: 0 | DB30: 0 | DC30: 0 | DD30: 0 | DE30: 0 | DF30: 0 | DG30: 0 | DH30: 0 | DI30: 0 | DJ30: 0 | DK30: 0 | DL30: 0 | DM30: 0 | DN30: 0 | DO30: 0 | DP30: 0 | DQ30: 0 | DR30: 0 | DS30: 0 | DT30: 0 | DU30: 0 | DV30: 0 | DW30: 0 | DX30: 0 | DY30: 0 | DZ30: 0 | EA30: 0 | EB30: 0 | EC30: 0 | ED30: 0 | EE30: 0 | EF30: 0 | EG30: 0 | EH30: 0 | EI30: 0 | EJ30: 0 | EK30: 0 | EL30: 0 | EM30: 0 | EN30: 0 | EO30: 0 | EP30: 0 | EQ30: 0 | ER30: 0 | ES30: 0 | ET30: 0 | EU30: 0 | EV30: 0 | EW30: 0 | EX30: 0 | EY30: 0 | EZ30: 0 | FA30: 0 | FB30: 0 | FC30: 0 | FD30: 0 | FE30: 0 | FF30: 0 | FG30: 0 | FH30: 0 | FI30: 0 | FJ30: 0 | FK30: 0 | FL30: 0 | FM30: 0 | FN30: 0 | FO30: 0 | FP30: 0 | FQ30: 0 | FR30: 0 | FS30: 0 | FT30: 0 | FU30: 0 | FV30: 0 | FW30: 0 | FX30: 0 | FY30: 0 | FZ30: 0 | GA30: 0 | GB30: 0 | GC30: 0 | GD30: 0 | GE30: 0 | GF30: 0 | GG30: 0 | GH30: 0 | GI30: 0 | GJ30: 0 | GK30: 0 | GL30: 0 | GM30: 0 | GN30: 0 | GO30: 0 | GP30: 0 | GQ30: 0 | GR30: 0 | GS30: 0 | GT30: 0 | GU30: 0 | GV30: 0 | GW30: 0 | GX30: 0 | GY30: 0 | GZ30: 0
A31: 017.507-00 | B31: 2022/0032326-001 | C31: 2 | D31: 2022/0032326 | E31: ECT4953 | F31: 01/04/2026 | G31: 30/04/2026 | H31: CARLOS GONCALVES DOS SANTOS | I31: CARLOS GONCALVES DOS SANTOS | J31: ADAPTADO | K31: EMEI | L31: =CONTINUA!BV31 -> 0 | M31: =CONTINUA!BW31 -> 4 | O31: 6020.2022/0032326-6 | P31: 0 | Q31: 0 | R31: 2 | S31: 0 | T31: 1 | U31: 0 | V31: 0 | W31: 0 | X31: 2 | Y31: 0 | Z31: 1 | AA31: 0 | AB31: 0 | AC31: 0 | AD31: 2 | AE31: 0 | AF31: 1 | AG31: 0 | AH31: 0 | AI31: 0 | AJ31: 2 | AK31: 0 | AL31: 1 | AM31: 0 | AN31: 0 | AO31: 0 | AP31: 2 | AQ31: 0 | AR31: 1 | AS31: 0 | AT31: 0 | AU31: 0 | AV31: 2 | AW31: 0 | AX31: 1 | AY31: 0 | AZ31: 0 | BA31: 0 | BB31: 2 | BC31: 0 | BD31: 1 | BE31: 0 | BF31: 0 | BG31: 0 | BH31: 2 | BI31: 0 | BJ31: 1 | BK31: 0 | BL31: 0 | BM31: 0 | BN31: 2 | BO31: 0 | BP31: 1 | BQ31: 0 | BR31: 0 | BS31: 0 | BT31: 2 | BU31: 0 | BV31: 1 | BW31: 0 | BX31: 0 | BY31: 0 | BZ31: 2 | CA31: 0 | CB31: 1 | CC31: 0 | CD31: 0 | CE31: 0 | CF31: 2 | CG31: 0 | CH31: 1 | CI31: 0 | CJ31: 0 | CK31: 0 | CL31: 2 | CM31: 0 | CN31: 1 | CO31: 0 | CP31: 0 | CQ31: 0 | CR31: 2 | CS31: 0 | CT31: 1 | CU31: 0 | CV31: 0 | CW31: 0 | CX31: 2 | CY31: 0 | CZ31: 1 | DA31: 0 | DB31: 0 | DC31: 0 | DD31: 2 | DE31: 0 | DF31: 1 | DG31: 0 | DH31: 0 | DI31: 0 | DJ31: 2 | DK31: 0 | DL31: 1 | DM31: 0 | DN31: 0 | DO31: 0 | DP31: 2 | DQ31: 0 | DR31: 1 | DS31: 0 | DT31: 0 | DU31: 0 | DV31: 2 | DW31: 0 | DX31: 1 | DY31: 0 | DZ31: 0 | EA31: 0 | EB31: 2 | EC31: 0 | ED31: 1 | EE31: 0 | EF31: 0 | EG31: 0 | EH31: 2 | EI31: 0 | EJ31: 1 | EK31: 0 | EL31: 0 | EM31: 0 | EN31: 2 | EO31: 0 | EP31: 1 | EQ31: 0 | ER31: 0 | ES31: 0 | ET31: 2 | EU31: 0 | EV31: 1 | EW31: 0 | EX31: 0 | EY31: 0 | EZ31: 2 | FA31: 0 | FB31: 1 | FC31: 0 | FD31: 0 | FE31: 0 | FF31: 2 | FG31: 0 | FH31: 1 | FI31: 0 | FJ31: 0 | FK31: 0 | FL31: 2 | FM31: 0 | FN31: 1 | FO31: 0 | FP31: 0 | FQ31: 0 | FR31: 2 | FS31: 0 | FT31: 1 | FU31: 0 | FV31: 0 | FW31: 0 | FX31: 2 | FY31: 0 | FZ31: 1 | GA31: 0 | GB31: 0 | GC31: 0 | GD31: 2 | GE31: 0 | GF31: 1 | GG31: 0 | GH31: 0 | GI31: 0 | GJ31: 2 | GK31: 0 | GL31: 1 | GM31: 0 | GN31: 0 | GO31: 0 | GP31: 2 | GQ31: 0 | GR31: 1 | GS31: 0 | GT31: 0 | GU31: 0 | GV31: 2 | GW31: 0 | GX31: 1 | GY31: 0 | GZ31: 0
A32: 017.507-00 | B32: 2022/0032326-001 | C32: G | D32: 2022/0032326 | E32: ECT4953 | F32: 01/04/2026 | G32: 30/04/2026 | H32: CARLOS GONCALVES DOS SANTOS | I32: CARLOS GONCALVES DOS SANTOS | J32: ADAPTADO | K32: EMEF | L32: =CONTINUA!BV32 -> 12 | M32: =CONTINUA!BW32 -> 0 | O32: 6020.2022/0032326-6 | P32: 0 | Q32: 10 | R32: 2 | S32: 0 | T32: 0 | U32: 0 | V32: 0 | W32: 10 | X32: 2 | Y32: 0 | Z32: 0 | AA32: 0 | AB32: 0 | AC32: 10 | AD32: 2 | AE32: 0 | AF32: 0 | AG32: 0 | AH32: 0 | AI32: 10 | AJ32: 2 | AK32: 0 | AL32: 0 | AM32: 0 | AN32: 0 | AO32: 10 | AP32: 2 | AQ32: 0 | AR32: 0 | AS32: 0 | AT32: 0 | AU32: 10 | AV32: 2 | AW32: 0 | AX32: 0 | AY32: 0 | AZ32: 0 | BA32: 10 | BB32: 2 | BC32: 0 | BD32: 0 | BE32: 0 | BF32: 0 | BG32: 10 | BH32: 2 | BI32: 0 | BJ32: 0 | BK32: 0 | BL32: 0 | BM32: 10 | BN32: 2 | BO32: 0 | BP32: 0 | BQ32: 0 | BR32: 0 | BS32: 10 | BT32: 2 | BU32: 0 | BV32: 0 | BW32: 0 | BX32: 0 | BY32: 10 | BZ32: 2 | CA32: 0 | CB32: 0 | CC32: 0 | CD32: 0 | CE32: 10 | CF32: 2 | CG32: 0 | CH32: 0 | CI32: 0 | CJ32: 0 | CK32: 10 | CL32: 2 | CM32: 0 | CN32: 0 | CO32: 0 | CP32: 0 | CQ32: 10 | CR32: 2 | CS32: 0 | CT32: 0 | CU32: 0 | CV32: 0 | CW32: 10 | CX32: 2 | CY32: 0 | CZ32: 0 | DA32: 0 | DB32: 0 | DC32: 10 | DD32: 2 | DE32: 0 | DF32: 0 | DG32: 0 | DH32: 0 | DI32: 10 | DJ32: 2 | DK32: 0 | DL32: 0 | DM32: 0 | DN32: 0 | DO32: 10 | DP32: 2 | DQ32: 0 | DR32: 0 | DS32: 0 | DT32: 0 | DU32: 10 | DV32: 2 | DW32: 0 | DX32: 0 | DY32: 0 | DZ32: 0 | EA32: 10 | EB32: 2 | EC32: 0 | ED32: 0 | EE32: 0 | EF32: 0 | EG32: 10 | EH32: 2 | EI32: 0 | EJ32: 0 | EK32: 0 | EL32: 0 | EM32: 10 | EN32: 2 | EO32: 0 | EP32: 0 | EQ32: 0 | ER32: 0 | ES32: 10 | ET32: 2 | EU32: 0 | EV32: 0 | EW32: 0 | EX32: 0 | EY32: 10 | EZ32: 2 | FA32: 0 | FB32: 0 | FC32: 0 | FD32: 0 | FE32: 10 | FF32: 2 | FG32: 0 | FH32: 0 | FI32: 0 | FJ32: 0 | FK32: 10 | FL32: 2 | FM32: 0 | FN32: 0 | FO32: 0 | FP32: 0 | FQ32: 10 | FR32: 2 | FS32: 0 | FT32: 0 | FU32: 0 | FV32: 0 | FW32: 10 | FX32: 2 | FY32: 0 | FZ32: 0 | GA32: 0 | GB32: 0 | GC32: 10 | GD32: 2 | GE32: 0 | GF32: 0 | GG32: 0 | GH32: 0 | GI32: 10 | GJ32: 2 | GK32: 0 | GL32: 0 | GM32: 0 | GN32: 0 | GO32: 10 | GP32: 2 | GQ32: 0 | GR32: 0 | GS32: 0 | GT32: 0 | GU32: 10 | GV32: 2 | GW32: 0 | GX32: 0 | GY32: 0 | GZ32: 0
A33: 017.507-00 | B33: 2022/0032326-001 | C33: G | D33: 2022/0032326 | E33: ECT4953 | F33: 01/04/2026 | G33: 30/04/2026 | H33: CARLOS GONCALVES DOS SANTOS | I33: CARLOS GONCALVES DOS SANTOS | J33: ADAPTADO | K33: EMEE | L33: =CONTINUA!BV33 -> 0 | M33: =CONTINUA!BW33 -> 0 | O33: 6020.2022/0032326-6 | P33: 0 | Q33: 0 | R33: 0 | S33: 0 | T33: 0 | U33: 0 | V33: 0 | W33: 0 | X33: 0 | Y33: 0 | Z33: 0 | AA33: 0 | AB33: 0 | AC33: 0 | AD33: 0 | AE33: 0 | AF33: 0 | AG33: 0 | AH33: 0 | AI33: 0 | AJ33: 0 | AK33: 0 | AL33: 0 | AM33: 0 | AN33: 0 | AO33: 0 | AP33: 0 | AQ33: 0 | AR33: 0 | AS33: 0 | AT33: 0 | AU33: 0 | AV33: 0 | AW33: 0 | AX33: 0 | AY33: 0 | AZ33: 0 | BA33: 0 | BB33: 0 | BC33: 0 | BD33: 0 | BE33: 0 | BF33: 0 | BG33: 0 | BH33: 0 | BI33: 0 | BJ33: 0 | BK33: 0 | BL33: 0 | BM33: 0 | BN33: 0 | BO33: 0 | BP33: 0 | BQ33: 0 | BR33: 0 | BS33: 0 | BT33: 0 | BU33: 0 | BV33: 0 | BW33: 0 | BX33: 0 | BY33: 0 | BZ33: 0 | CA33: 0 | CB33: 0 | CC33: 0 | CD33: 0 | CE33: 0 | CF33: 0 | CG33: 0 | CH33: 0 | CI33: 0 | CJ33: 0 | CK33: 0 | CL33: 0 | CM33: 0 | CN33: 0 | CO33: 0 | CP33: 0 | CQ33: 0 | CR33: 0 | CS33: 0 | CT33: 0 | CU33: 0 | CV33: 0 | CW33: 0 | CX33: 0 | CY33: 0 | CZ33: 0 | DA33: 0 | DB33: 0 | DC33: 0 | DD33: 0 | DE33: 0 | DF33: 0 | DG33: 0 | DH33: 0 | DI33: 0 | DJ33: 0 | DK33: 0 | DL33: 0 | DM33: 0 | DN33: 0 | DO33: 0 | DP33: 0 | DQ33: 0 | DR33: 0 | DS33: 0 | DT33: 0 | DU33: 0 | DV33: 0 | DW33: 0 | DX33: 0 | DY33: 0 | DZ33: 0 | EA33: 0 | EB33: 0 | EC33: 0 | ED33: 0 | EE33: 0 | EF33: 0 | EG33: 0 | EH33: 0 | EI33: 0 | EJ33: 0 | EK33: 0 | EL33: 0 | EM33: 0 | EN33: 0 | EO33: 0 | EP33: 0 | EQ33: 0 | ER33: 0 | ES33: 0 | ET33: 0 | EU33: 0 | EV33: 0 | EW33: 0 | EX33: 0 | EY33: 0 | EZ33: 0 | FA33: 0 | FB33: 0 | FC33: 0 | FD33: 0 | FE33: 0 | FF33: 0 | FG33: 0 | FH33: 0 | FI33: 0 | FJ33: 0 | FK33: 0 | FL33: 0 | FM33: 0 | FN33: 0 | FO33: 0 | FP33: 0 | FQ33: 0 | FR33: 0 | FS33: 0 | FT33: 0 | FU33: 0 | FV33: 0 | FW33: 0 | FX33: 0 | FY33: 0 | FZ33: 0 | GA33: 0 | GB33: 0 | GC33: 0 | GD33: 0 | GE33: 0 | GF33: 0 | GG33: 0 | GH33: 0 | GI33: 0 | GJ33: 0 | GK33: 0 | GL33: 0 | GM33: 0 | GN33: 0 | GO33: 0 | GP33: 0 | GQ33: 0 | GR33: 0 | GS33: 0 | GT33: 0 | GU33: 0 | GV33: 0 | GW33: 0 | GX33: 0 | GY33: 0 | GZ33: 0
A34: 017.507-00 | B34: 2022/0032326-001 | C34: G | D34: 2022/0032326 | E34: ECT4953 | F34: 01/04/2026 | G34: 30/04/2026 | H34: CARLOS GONCALVES DOS SANTOS | I34: CARLOS GONCALVES DOS SANTOS | J34: ADAPTADO | K34: CEI | L34: =CONTINUA!BV34 -> 0 | M34: =CONTINUA!BW34 -> 0 | O34: 6020.2022/0032326-6 | P34: 0 | Q34: 0 | R34: 0 | S34: 0 | T34: 0 | U34: 0 | V34: 0 | W34: 0 | X34: 0 | Y34: 0 | Z34: 0 | AA34: 0 | AB34: 0 | AC34: 0 | AD34: 0 | AE34: 0 | AF34: 0 | AG34: 0 | AH34: 0 | AI34: 0 | AJ34: 0 | AK34: 0 | AL34: 0 | AM34: 0 | AN34: 0 | AO34: 0 | AP34: 0 | AQ34: 0 | AR34: 0 | AS34: 0 | AT34: 0 | AU34: 0 | AV34: 0 | AW34: 0 | AX34: 0 | AY34: 0 | AZ34: 0 | BA34: 0 | BB34: 0 | BC34: 0 | BD34: 0 | BE34: 0 | BF34: 0 | BG34: 0 | BH34: 0 | BI34: 0 | BJ34: 0 | BK34: 0 | BL34: 0 | BM34: 0 | BN34: 0 | BO34: 0 | BP34: 0 | BQ34: 0 | BR34: 0 | BS34: 0 | BT34: 0 | BU34: 0 | BV34: 0 | BW34: 0 | BX34: 0 | BY34: 0 | BZ34: 0 | CA34: 0 | CB34: 0 | CC34: 0 | CD34: 0 | CE34: 0 | CF34: 0 | CG34: 0 | CH34: 0 | CI34: 0 | CJ34: 0 | CK34: 0 | CL34: 0 | CM34: 0 | CN34: 0 | CO34: 0 | CP34: 0 | CQ34: 0 | CR34: 0 | CS34: 0 | CT34: 0 | CU34: 0 | CV34: 0 | CW34: 0 | CX34: 0 | CY34: 0 | CZ34: 0 | DA34: 0 | DB34: 0 | DC34: 0 | DD34: 0 | DE34: 0 | DF34: 0 | DG34: 0 | DH34: 0 | DI34: 0 | DJ34: 0 | DK34: 0 | DL34: 0 | DM34: 0 | DN34: 0 | DO34: 0 | DP34: 0 | DQ34: 0 | DR34: 0 | DS34: 0 | DT34: 0 | DU34: 0 | DV34: 0 | DW34: 0 | DX34: 0 | DY34: 0 | DZ34: 0 | EA34: 0 | EB34: 0 | EC34: 0 | ED34: 0 | EE34: 0 | EF34: 0 | EG34: 0 | EH34: 0 | EI34: 0 | EJ34: 0 | EK34: 0 | EL34: 0 | EM34: 0 | EN34: 0 | EO34: 0 | EP34: 0 | EQ34: 0 | ER34: 0 | ES34: 0 | ET34: 0 | EU34: 0 | EV34: 0 | EW34: 0 | EX34: 0 | EY34: 0 | EZ34: 0 | FA34: 0 | FB34: 0 | FC34: 0 | FD34: 0 | FE34: 0 | FF34: 0 | FG34: 0 | FH34: 0 | FI34: 0 | FJ34: 0 | FK34: 0 | FL34: 0 | FM34: 0 | FN34: 0 | FO34: 0 | FP34: 0 | FQ34: 0 | FR34: 0 | FS34: 0 | FT34: 0 | FU34: 0 | FV34: 0 | FW34: 0 | FX34: 0 | FY34: 0 | FZ34: 0 | GA34: 0 | GB34: 0 | GC34: 0 | GD34: 0 | GE34: 0 | GF34: 0 | GG34: 0 | GH34: 0 | GI34: 0 | GJ34: 0 | GK34: 0 | GL34: 0 | GM34: 0 | GN34: 0 | GO34: 0 | GP34: 0 | GQ34: 0 | GR34: 0 | GS34: 0 | GT34: 0 | GU34: 0 | GV34: 0 | GW34: 0 | GX34: 0 | GY34: 0 | GZ34: 0
A35: 017.507-00 | B35: 2022/0032326-001 | C35: G | D35: 2022/0032326 | E35: ECT4953 | F35: 01/04/2026 | G35: 30/04/2026 | H35: CARLOS GONCALVES DOS SANTOS | I35: CARLOS GONCALVES DOS SANTOS | J35: ADAPTADO | K35: CCA | L35: =CONTINUA!BV35 -> 0 | M35: =CONTINUA!BW35 -> 0 | O35: 6020.2022/0032326-6 | P35: 0 | Q35: 0 | R35: 0 | S35: 0 | T35: 0 | U35: 0 | V35: 0 | W35: 0 | X35: 0 | Y35: 0 | Z35: 0 | AA35: 0 | AB35: 0 | AC35: 0 | AD35: 0 | AE35: 0 | AF35: 0 | AG35: 0 | AH35: 0 | AI35: 0 | AJ35: 0 | AK35: 0 | AL35: 0 | AM35: 0 | AN35: 0 | AO35: 0 | AP35: 0 | AQ35: 0 | AR35: 0 | AS35: 0 | AT35: 0 | AU35: 0 | AV35: 0 | AW35: 0 | AX35: 0 | AY35: 0 | AZ35: 0 | BA35: 0 | BB35: 0 | BC35: 0 | BD35: 0 | BE35: 0 | BF35: 0 | BG35: 0 | BH35: 0 | BI35: 0 | BJ35: 0 | BK35: 0 | BL35: 0 | BM35: 0 | BN35: 0 | BO35: 0 | BP35: 0 | BQ35: 0 | BR35: 0 | BS35: 0 | BT35: 0 | BU35: 0 | BV35: 0 | BW35: 0 | BX35: 0 | BY35: 0 | BZ35: 0 | CA35: 0 | CB35: 0 | CC35: 0 | CD35: 0 | CE35: 0 | CF35: 0 | CG35: 0 | CH35: 0 | CI35: 0 | CJ35: 0 | CK35: 0 | CL35: 0 | CM35: 0 | CN35: 0 | CO35: 0 | CP35: 0 | CQ35: 0 | CR35: 0 | CS35: 0 | CT35: 0 | CU35: 0 | CV35: 0 | CW35: 0 | CX35: 0 | CY35: 0 | CZ35: 0 | DA35: 0 | DB35: 0 | DC35: 0 | DD35: 0 | DE35: 0 | DF35: 0 | DG35: 0 | DH35: 0 | DI35: 0 | DJ35: 0 | DK35: 0 | DL35: 0 | DM35: 0 | DN35: 0 | DO35: 0 | DP35: 0 | DQ35: 0 | DR35: 0 | DS35: 0 | DT35: 0 | DU35: 0 | DV35: 0 | DW35: 0 | DX35: 0 | DY35: 0 | DZ35: 0 | EA35: 0 | EB35: 0 | EC35: 0 | ED35: 0 | EE35: 0 | EF35: 0 | EG35: 0 | EH35: 0 | EI35: 0 | EJ35: 0 | EK35: 0 | EL35: 0 | EM35: 0 | EN35: 0 | EO35: 0 | EP35: 0 | EQ35: 0 | ER35: 0 | ES35: 0 | ET35: 0 | EU35: 0 | EV35: 0 | EW35: 0 | EX35: 0 | EY35: 0 | EZ35: 0 | FA35: 0 | FB35: 0 | FC35: 0 | FD35: 0 | FE35: 0 | FF35: 0 | FG35: 0 | FH35: 0 | FI35: 0 | FJ35: 0 | FK35: 0 | FL35: 0 | FM35: 0 | FN35: 0 | FO35: 0 | FP35: 0 | FQ35: 0 | FR35: 0 | FS35: 0 | FT35: 0 | FU35: 0 | FV35: 0 | FW35: 0 | FX35: 0 | FY35: 0 | FZ35: 0 | GA35: 0 | GB35: 0 | GC35: 0 | GD35: 0 | GE35: 0 | GF35: 0 | GG35: 0 | GH35: 0 | GI35: 0 | GJ35: 0 | GK35: 0 | GL35: 0 | GM35: 0 | GN35: 0 | GO35: 0 | GP35: 0 | GQ35: 0 | GR35: 0 | GS35: 0 | GT35: 0 | GU35: 0 | GV35: 0 | GW35: 0 | GX35: 0 | GY35: 0 | GZ35: 0
A36: 030.526-00 | B36: 2023/0024580-001 | C36: 2 | D36: 2023/0024580 | E36: DTE2230 | F36: 01/04/2026 | G36: 30/04/2026 | H36: CARLOS VITORINO FIGUEIREDO | I36: CARLOS VITORINO FIGUEIREDO | J36: ADAPTADO | K36: EMEI | L36: =CONTINUA!BV36 -> 0 | M36: =CONTINUA!BW36 -> 0 | O36: 6020.2023/0024580-1 | P36: 0 | Q36: 0 | R36: 1 | S36: 0 | T36: 0 | U36: 0 | V36: 0 | W36: 0 | X36: 1 | Y36: 0 | Z36: 0 | AA36: 0 | AB36: 0 | AC36: 0 | AD36: 1 | AE36: 0 | AF36: 0 | AG36: 0 | AH36: 0 | AI36: 0 | AJ36: 1 | AK36: 0 | AL36: 0 | AM36: 0 | AN36: 0 | AO36: 0 | AP36: 1 | AQ36: 0 | AR36: 0 | AS36: 0 | AT36: 0 | AU36: 0 | AV36: 1 | AW36: 0 | AX36: 0 | AY36: 0 | AZ36: 0 | BA36: 0 | BB36: 1 | BC36: 0 | BD36: 0 | BE36: 0 | BF36: 0 | BG36: 0 | BH36: 1 | BI36: 0 | BJ36: 0 | BK36: 0 | BL36: 0 | BM36: 0 | BN36: 1 | BO36: 0 | BP36: 0 | BQ36: 0 | BR36: 0 | BS36: 0 | BT36: 1 | BU36: 0 | BV36: 0 | BW36: 0 | BX36: 0 | BY36: 0 | BZ36: 1 | CA36: 0 | CB36: 0 | CC36: 0 | CD36: 0 | CE36: 0 | CF36: 1 | CG36: 0 | CH36: 0 | CI36: 0 | CJ36: 0 | CK36: 0 | CL36: 1 | CM36: 0 | CN36: 0 | CO36: 0 | CP36: 0 | CQ36: 0 | CR36: 1 | CS36: 0 | CT36: 0 | CU36: 0 | CV36: 0 | CW36: 0 | CX36: 1 | CY36: 0 | CZ36: 0 | DA36: 0 | DB36: 0 | DC36: 0 | DD36: 1 | DE36: 0 | DF36: 0 | DG36: 0 | DH36: 0 | DI36: 0 | DJ36: 1 | DK36: 0 | DL36: 0 | DM36: 0 | DN36: 0 | DO36: 0 | DP36: 1 | DQ36: 0 | DR36: 0 | DS36: 0 | DT36: 0 | DU36: 0 | DV36: 1 | DW36: 0 | DX36: 0 | DY36: 0 | DZ36: 0 | EA36: 0 | EB36: 1 | EC36: 0 | ED36: 0 | EE36: 0 | EF36: 0 | EG36: 0 | EH36: 1 | EI36: 0 | EJ36: 0 | EK36: 0 | EL36: 0 | EM36: 0 | EN36: 1 | EO36: 0 | EP36: 0 | EQ36: 0 | ER36: 0 | ES36: 0 | ET36: 1 | EU36: 0 | EV36: 0 | EW36: 0 | EX36: 0 | EY36: 0 | EZ36: 1 | FA36: 0 | FB36: 0 | FC36: 0 | FD36: 0 | FE36: 0 | FF36: 1 | FG36: 0 | FH36: 0 | FI36: 0 | FJ36: 0 | FK36: 0 | FL36: 1 | FM36: 0 | FN36: 0 | FO36: 0 | FP36: 0 | FQ36: 0 | FR36: 1 | FS36: 0 | FT36: 0 | FU36: 0 | FV36: 0 | FW36: 0 | FX36: 1 | FY36: 0 | FZ36: 0 | GA36: 0 | GB36: 0 | GC36: 0 | GD36: 1 | GE36: 0 | GF36: 0 | GG36: 0 | GH36: 0 | GI36: 0 | GJ36: 1 | GK36: 0 | GL36: 0 | GM36: 0 | GN36: 0 | GO36: 0 | GP36: 1 | GQ36: 0 | GR36: 0 | GS36: 0 | GT36: 0 | GU36: 0 | GV36: 1 | GW36: 0 | GX36: 0 | GY36: 0 | GZ36: 0
A37: 030.526-00 | B37: 2023/0024580-001 | C37: G | D37: 2023/0024580 | E37: DTE2230 | F37: 01/04/2026 | G37: 30/04/2026 | H37: CARLOS VITORINO FIGUEIREDO | I37: CARLOS VITORINO FIGUEIREDO | J37: ADAPTADO | K37: EMEF | L37: =CONTINUA!BV37 -> 20 | M37: =CONTINUA!BW37 -> 0 | O37: 6020.2023/0024580-1 | P37: 0 | Q37: 18 | R37: 1 | S37: 8 | T37: 1 | U37: 0 | V37: 0 | W37: 18 | X37: 1 | Y37: 8 | Z37: 1 | AA37: 0 | AB37: 0 | AC37: 18 | AD37: 1 | AE37: 8 | AF37: 1 | AG37: 0 | AH37: 0 | AI37: 18 | AJ37: 1 | AK37: 8 | AL37: 1 | AM37: 0 | AN37: 0 | AO37: 18 | AP37: 1 | AQ37: 8 | AR37: 1 | AS37: 0 | AT37: 0 | AU37: 18 | AV37: 1 | AW37: 8 | AX37: 1 | AY37: 0 | AZ37: 0 | BA37: 18 | BB37: 1 | BC37: 8 | BD37: 1 | BE37: 0 | BF37: 0 | BG37: 18 | BH37: 1 | BI37: 8 | BJ37: 1 | BK37: 0 | BL37: 0 | BM37: 18 | BN37: 1 | BO37: 8 | BP37: 1 | BQ37: 0 | BR37: 0 | BS37: 18 | BT37: 1 | BU37: 8 | BV37: 1 | BW37: 0 | BX37: 0 | BY37: 18 | BZ37: 1 | CA37: 8 | CB37: 1 | CC37: 0 | CD37: 0 | CE37: 18 | CF37: 1 | CG37: 8 | CH37: 1 | CI37: 0 | CJ37: 0 | CK37: 18 | CL37: 1 | CM37: 8 | CN37: 1 | CO37: 0 | CP37: 0 | CQ37: 18 | CR37: 1 | CS37: 8 | CT37: 1 | CU37: 0 | CV37: 0 | CW37: 18 | CX37: 1 | CY37: 8 | CZ37: 1 | DA37: 0 | DB37: 0 | DC37: 18 | DD37: 1 | DE37: 8 | DF37: 1 | DG37: 0 | DH37: 0 | DI37: 18 | DJ37: 1 | DK37: 8 | DL37: 1 | DM37: 0 | DN37: 0 | DO37: 18 | DP37: 1 | DQ37: 8 | DR37: 1 | DS37: 0 | DT37: 0 | DU37: 18 | DV37: 1 | DW37: 8 | DX37: 1 | DY37: 0 | DZ37: 0 | EA37: 18 | EB37: 1 | EC37: 8 | ED37: 1 | EE37: 0 | EF37: 0 | EG37: 18 | EH37: 1 | EI37: 8 | EJ37: 1 | EK37: 0 | EL37: 0 | EM37: 18 | EN37: 1 | EO37: 8 | EP37: 1 | EQ37: 0 | ER37: 0 | ES37: 18 | ET37: 1 | EU37: 8 | EV37: 1 | EW37: 0 | EX37: 0 | EY37: 18 | EZ37: 1 | FA37: 8 | FB37: 1 | FC37: 0 | FD37: 0 | FE37: 18 | FF37: 1 | FG37: 8 | FH37: 1 | FI37: 0 | FJ37: 0 | FK37: 18 | FL37: 1 | FM37: 8 | FN37: 1 | FO37: 0 | FP37: 0 | FQ37: 18 | FR37: 1 | FS37: 8 | FT37: 1 | FU37: 0 | FV37: 0 | FW37: 18 | FX37: 1 | FY37: 8 | FZ37: 1 | GA37: 0 | GB37: 0 | GC37: 18 | GD37: 1 | GE37: 8 | GF37: 1 | GG37: 0 | GH37: 0 | GI37: 18 | GJ37: 1 | GK37: 8 | GL37: 1 | GM37: 0 | GN37: 0 | GO37: 18 | GP37: 1 | GQ37: 8 | GR37: 1 | GS37: 0 | GT37: 0 | GU37: 18 | GV37: 1 | GW37: 8 | GX37: 1 | GY37: 0 | GZ37: 0
A38: 030.526-00 | B38: 2023/0024580-001 | C38: G | D38: 2023/0024580 | E38: DTE2230 | F38: 01/04/2026 | G38: 30/04/2026 | H38: CARLOS VITORINO FIGUEIREDO | I38: CARLOS VITORINO FIGUEIREDO | J38: ADAPTADO | K38: EMEE | L38: =CONTINUA!BV38 -> 0 | M38: =CONTINUA!BW38 -> 0 | O38: 6020.2023/0024580-1 | P38: 0 | Q38: 0 | R38: 0 | S38: 0 | T38: 0 | U38: 0 | V38: 0 | W38: 0 | X38: 0 | Y38: 0 | Z38: 0 | AA38: 0 | AB38: 0 | AC38: 0 | AD38: 0 | AE38: 0 | AF38: 0 | AG38: 0 | AH38: 0 | AI38: 0 | AJ38: 0 | AK38: 0 | AL38: 0 | AM38: 0 | AN38: 0 | AO38: 0 | AP38: 0 | AQ38: 0 | AR38: 0 | AS38: 0 | AT38: 0 | AU38: 0 | AV38: 0 | AW38: 0 | AX38: 0 | AY38: 0 | AZ38: 0 | BA38: 0 | BB38: 0 | BC38: 0 | BD38: 0 | BE38: 0 | BF38: 0 | BG38: 0 | BH38: 0 | BI38: 0 | BJ38: 0 | BK38: 0 | BL38: 0 | BM38: 0 | BN38: 0 | BO38: 0 | BP38: 0 | BQ38: 0 | BR38: 0 | BS38: 0 | BT38: 0 | BU38: 0 | BV38: 0 | BW38: 0 | BX38: 0 | BY38: 0 | BZ38: 0 | CA38: 0 | CB38: 0 | CC38: 0 | CD38: 0 | CE38: 0 | CF38: 0 | CG38: 0 | CH38: 0 | CI38: 0 | CJ38: 0 | CK38: 0 | CL38: 0 | CM38: 0 | CN38: 0 | CO38: 0 | CP38: 0 | CQ38: 0 | CR38: 0 | CS38: 0 | CT38: 0 | CU38: 0 | CV38: 0 | CW38: 0 | CX38: 0 | CY38: 0 | CZ38: 0 | DA38: 0 | DB38: 0 | DC38: 0 | DD38: 0 | DE38: 0 | DF38: 0 | DG38: 0 | DH38: 0 | DI38: 0 | DJ38: 0 | DK38: 0 | DL38: 0 | DM38: 0 | DN38: 0 | DO38: 0 | DP38: 0 | DQ38: 0 | DR38: 0 | DS38: 0 | DT38: 0 | DU38: 0 | DV38: 0 | DW38: 0 | DX38: 0 | DY38: 0 | DZ38: 0 | EA38: 0 | EB38: 0 | EC38: 0 | ED38: 0 | EE38: 0 | EF38: 0 | EG38: 0 | EH38: 0 | EI38: 0 | EJ38: 0 | EK38: 0 | EL38: 0 | EM38: 0 | EN38: 0 | EO38: 0 | EP38: 0 | EQ38: 0 | ER38: 0 | ES38: 0 | ET38: 0 | EU38: 0 | EV38: 0 | EW38: 0 | EX38: 0 | EY38: 0 | EZ38: 0 | FA38: 0 | FB38: 0 | FC38: 0 | FD38: 0 | FE38: 0 | FF38: 0 | FG38: 0 | FH38: 0 | FI38: 0 | FJ38: 0 | FK38: 0 | FL38: 0 | FM38: 0 | FN38: 0 | FO38: 0 | FP38: 0 | FQ38: 0 | FR38: 0 | FS38: 0 | FT38: 0 | FU38: 0 | FV38: 0 | FW38: 0 | FX38: 0 | FY38: 0 | FZ38: 0 | GA38: 0 | GB38: 0 | GC38: 0 | GD38: 0 | GE38: 0 | GF38: 0 | GG38: 0 | GH38: 0 | GI38: 0 | GJ38: 0 | GK38: 0 | GL38: 0 | GM38: 0 | GN38: 0 | GO38: 0 | GP38: 0 | GQ38: 0 | GR38: 0 | GS38: 0 | GT38: 0 | GU38: 0 | GV38: 0 | GW38: 0 | GX38: 0 | GY38: 0 | GZ38: 0
A39: 030.526-00 | B39: 2023/0024580-001 | C39: G | D39: 2023/0024580 | E39: DTE2230 | F39: 01/04/2026 | G39: 30/04/2026 | H39: CARLOS VITORINO FIGUEIREDO | I39: CARLOS VITORINO FIGUEIREDO | J39: ADAPTADO | K39: CEI | L39: =CONTINUA!BV39 -> 0 | M39: =CONTINUA!BW39 -> 0 | O39: 6020.2023/0024580-1 | P39: 0 | Q39: 0 | R39: 0 | S39: 0 | T39: 0 | U39: 0 | V39: 0 | W39: 0 | X39: 0 | Y39: 0 | Z39: 0 | AA39: 0 | AB39: 0 | AC39: 0 | AD39: 0 | AE39: 0 | AF39: 0 | AG39: 0 | AH39: 0 | AI39: 0 | AJ39: 0 | AK39: 0 | AL39: 0 | AM39: 0 | AN39: 0 | AO39: 0 | AP39: 0 | AQ39: 0 | AR39: 0 | AS39: 0 | AT39: 0 | AU39: 0 | AV39: 0 | AW39: 0 | AX39: 0 | AY39: 0 | AZ39: 0 | BA39: 0 | BB39: 0 | BC39: 0 | BD39: 0 | BE39: 0 | BF39: 0 | BG39: 0 | BH39: 0 | BI39: 0 | BJ39: 0 | BK39: 0 | BL39: 0 | BM39: 0 | BN39: 0 | BO39: 0 | BP39: 0 | BQ39: 0 | BR39: 0 | BS39: 0 | BT39: 0 | BU39: 0 | BV39: 0 | BW39: 0 | BX39: 0 | BY39: 0 | BZ39: 0 | CA39: 0 | CB39: 0 | CC39: 0 | CD39: 0 | CE39: 0 | CF39: 0 | CG39: 0 | CH39: 0 | CI39: 0 | CJ39: 0 | CK39: 0 | CL39: 0 | CM39: 0 | CN39: 0 | CO39: 0 | CP39: 0 | CQ39: 0 | CR39: 0 | CS39: 0 | CT39: 0 | CU39: 0 | CV39: 0 | CW39: 0 | CX39: 0 | CY39: 0 | CZ39: 0 | DA39: 0 | DB39: 0 | DC39: 0 | DD39: 0 | DE39: 0 | DF39: 0 | DG39: 0 | DH39: 0 | DI39: 0 | DJ39: 0 | DK39: 0 | DL39: 0 | DM39: 0 | DN39: 0 | DO39: 0 | DP39: 0 | DQ39: 0 | DR39: 0 | DS39: 0 | DT39: 0 | DU39: 0 | DV39: 0 | DW39: 0 | DX39: 0 | DY39: 0 | DZ39: 0 | EA39: 0 | EB39: 0 | EC39: 0 | ED39: 0 | EE39: 0 | EF39: 0 | EG39: 0 | EH39: 0 | EI39: 0 | EJ39: 0 | EK39: 0 | EL39: 0 | EM39: 0 | EN39: 0 | EO39: 0 | EP39: 0 | EQ39: 0 | ER39: 0 | ES39: 0 | ET39: 0 | EU39: 0 | EV39: 0 | EW39: 0 | EX39: 0 | EY39: 0 | EZ39: 0 | FA39: 0 | FB39: 0 | FC39: 0 | FD39: 0 | FE39: 0 | FF39: 0 | FG39: 0 | FH39: 0 | FI39: 0 | FJ39: 0 | FK39: 0 | FL39: 0 | FM39: 0 | FN39: 0 | FO39: 0 | FP39: 0 | FQ39: 0 | FR39: 0 | FS39: 0 | FT39: 0 | FU39: 0 | FV39: 0 | FW39: 0 | FX39: 0 | FY39: 0 | FZ39: 0 | GA39: 0 | GB39: 0 | GC39: 0 | GD39: 0 | GE39: 0 | GF39: 0 | GG39: 0 | GH39: 0 | GI39: 0 | GJ39: 0 | GK39: 0 | GL39: 0 | GM39: 0 | GN39: 0 | GO39: 0 | GP39: 0 | GQ39: 0 | GR39: 0 | GS39: 0 | GT39: 0 | GU39: 0 | GV39: 0 | GW39: 0 | GX39: 0 | GY39: 0 | GZ39: 0
A40: 030.526-00 | B40: 2023/0024580-001 | C40: G | D40: 2023/0024580 | E40: DTE2230 | F40: 01/04/2026 | G40: 30/04/2026 | H40: CARLOS VITORINO FIGUEIREDO | I40: CARLOS VITORINO FIGUEIREDO | J40: ADAPTADO | K40: CCA | L40: =CONTINUA!BV40 -> 0 | M40: =CONTINUA!BW40 -> 0 | O40: 6020.2023/0024580-1 | P40: 0 | Q40: 0 | R40: 0 | S40: 0 | T40: 0 | U40: 0 | V40: 0 | W40: 0 | X40: 0 | Y40: 0 | Z40: 0 | AA40: 0 | AB40: 0 | AC40: 0 | AD40: 0 | AE40: 0 | AF40: 0 | AG40: 0 | AH40: 0 | AI40: 0 | AJ40: 0 | AK40: 0 | AL40: 0 | AM40: 0 | AN40: 0 | AO40: 0 | AP40: 0 | AQ40: 0 | AR40: 0 | AS40: 0 | AT40: 0 | AU40: 0 | AV40: 0 | AW40: 0 | AX40: 0 | AY40: 0 | AZ40: 0 | BA40: 0 | BB40: 0 | BC40: 0 | BD40: 0 | BE40: 0 | BF40: 0 | BG40: 0 | BH40: 0 | BI40: 0 | BJ40: 0 | BK40: 0 | BL40: 0 | BM40: 0 | BN40: 0 | BO40: 0 | BP40: 0 | BQ40: 0 | BR40: 0 | BS40: 0 | BT40: 0 | BU40: 0 | BV40: 0 | BW40: 0 | BX40: 0 | BY40: 0 | BZ40: 0 | CA40: 0 | CB40: 0 | CC40: 0 | CD40: 0 | CE40: 0 | CF40: 0 | CG40: 0 | CH40: 0 | CI40: 0 | CJ40: 0 | CK40: 0 | CL40: 0 | CM40: 0 | CN40: 0 | CO40: 0 | CP40: 0 | CQ40: 0 | CR40: 0 | CS40: 0 | CT40: 0 | CU40: 0 | CV40: 0 | CW40: 0 | CX40: 0 | CY40: 0 | CZ40: 0 | DA40: 0 | DB40: 0 | DC40: 0 | DD40: 0 | DE40: 0 | DF40: 0 | DG40: 0 | DH40: 0 | DI40: 0 | DJ40: 0 | DK40: 0 | DL40: 0 | DM40: 0 | DN40: 0 | DO40: 0 | DP40: 0 | DQ40: 0 | DR40: 0 | DS40: 0 | DT40: 0 | DU40: 0 | DV40: 0 | DW40: 0 | DX40: 0 | DY40: 0 | DZ40: 0 | EA40: 0 | EB40: 0 | EC40: 0 | ED40: 0 | EE40: 0 | EF40: 0 | EG40: 0 | EH40: 0 | EI40: 0 | EJ40: 0 | EK40: 0 | EL40: 0 | EM40: 0 | EN40: 0 | EO40: 0 | EP40: 0 | EQ40: 0 | ER40: 0 | ES40: 0 | ET40: 0 | EU40: 0 | EV40: 0 | EW40: 0 | EX40: 0 | EY40: 0 | EZ40: 0 | FA40: 0 | FB40: 0 | FC40: 0 | FD40: 0 | FE40: 0 | FF40: 0 | FG40: 0 | FH40: 0 | FI40: 0 | FJ40: 0 | FK40: 0 | FL40: 0 | FM40: 0 | FN40: 0 | FO40: 0 | FP40: 0 | FQ40: 0 | FR40: 0 | FS40: 0 | FT40: 0 | FU40: 0 | FV40: 0 | FW40: 0 | FX40: 0 | FY40: 0 | FZ40: 0 | GA40: 0 | GB40: 0 | GC40: 0 | GD40: 0 | GE40: 0 | GF40: 0 | GG40: 0 | GH40: 0 | GI40: 0 | GJ40: 0 | GK40: 0 | GL40: 0 | GM40: 0 | GN40: 0 | GO40: 0 | GP40: 0 | GQ40: 0 | GR40: 0 | GS40: 0 | GT40: 0 | GU40: 0 | GV40: 0 | GW40: 0 | GX40: 0 | GY40: 0 | GZ40: 0
A41: 038.961-00 | B41: 2022/0029260-001A | C41: 1 | D41: 2022/0029260 | E41: FXE1C10 | F41: 01/04/2026 | G41: 30/04/2026 | H41: CLAUDEMIR CORREIA E SILVA | I41: CLAUDEMIR CORREIA E SILVA | J41: NORMAL | K41: EMEI | L41: =CONTINUA!BV41 -> 0 | M41: =CONTINUA!BW41 -> 0 | O41: 6020.2022/0029260-3 | P41: 0 | Q41: 26 | S41: 0 | U41: 0 | V41: 0 | W41: 26 | Y41: 0 | AA41: 0 | AB41: 0 | AC41: 26 | AE41: 0 | AG41: 0 | AH41: 0 | AI41: 26 | AK41: 0 | AM41: 0 | AN41: 0 | AO41: 26 | AQ41: 0 | AS41: 0 | AT41: 0 | AU41: 26 | AW41: 0 | AY41: 0 | AZ41: 0 | BA41: 26 | BC41: 0 | BE41: 0 | BF41: 0 | BG41: 26 | BI41: 0 | BK41: 0 | BL41: 0 | BM41: 26 | BO41: 0 | BQ41: 0 | BR41: 0 | BS41: 26 | BU41: 0 | BW41: 0 | BX41: 0 | BY41: 26 | CA41: 0 | CC41: 0 | CD41: 0 | CE41: 26 | CG41: 0 | CI41: 0 | CJ41: 0 | CK41: 26 | CM41: 0 | CO41: 0 | CP41: 0 | CQ41: 26 | CS41: 0 | CU41: 0 | CV41: 0 | CW41: 26 | CY41: 0 | DA41: 0 | DB41: 0 | DC41: 26 | DE41: 0 | DG41: 0 | DH41: 0 | DI41: 26 | DK41: 0 | DM41: 0 | DN41: 0 | DO41: 26 | DQ41: 0 | DS41: 0 | DT41: 0 | DU41: 26 | DW41: 0 | DY41: 0 | DZ41: 0 | EA41: 26 | EC41: 0 | EE41: 0 | EF41: 0 | EG41: 26 | EI41: 0 | EK41: 0 | EL41: 0 | EM41: 26 | EO41: 0 | EQ41: 0 | ER41: 0 | ES41: 26 | EU41: 0 | EW41: 0 | EX41: 0 | EY41: 26 | FA41: 0 | FC41: 0 | FD41: 0 | FE41: 26 | FG41: 0 | FI41: 0 | FJ41: 0 | FK41: 26 | FM41: 0 | FO41: 0 | FP41: 0 | FQ41: 26 | FS41: 0 | FU41: 0 | FV41: 0 | FW41: 26 | FY41: 0 | GA41: 0 | GB41: 0 | GC41: 26 | GE41: 0 | GG41: 0 | GH41: 0 | GI41: 26 | GK41: 0 | GM41: 0 | GN41: 0 | GO41: 26 | GQ41: 0 | GS41: 0 | GT41: 0 | GU41: 26 | GW41: 0 | GY41: 0 | GZ41: 0
A42: 038.961-00 | B42: 2022/0029260-001A | C42: G | D42: 2022/0029260 | E42: FXE1C10 | F42: 01/04/2026 | G42: 30/04/2026 | H42: CLAUDEMIR CORREIA E SILVA | I42: CLAUDEMIR CORREIA E SILVA | J42: NORMAL | K42: EMEF | L42: =CONTINUA!BV42 -> 0 | M42: =CONTINUA!BW42 -> 0 | O42: 6020.2022/0029260-3 | P42: 0 | Q42: 22 | S42: 0 | U42: 0 | V42: 0 | W42: 22 | Y42: 0 | AA42: 0 | AB42: 0 | AC42: 22 | AE42: 0 | AG42: 0 | AH42: 0 | AI42: 22 | AK42: 0 | AM42: 0 | AN42: 0 | AO42: 22 | AQ42: 0 | AS42: 0 | AT42: 0 | AU42: 22 | AW42: 0 | AY42: 0 | AZ42: 0 | BA42: 22 | BC42: 0 | BE42: 0 | BF42: 0 | BG42: 22 | BI42: 0 | BK42: 0 | BL42: 0 | BM42: 22 | BO42: 0 | BQ42: 0 | BR42: 0 | BS42: 22 | BU42: 0 | BW42: 0 | BX42: 0 | BY42: 22 | CA42: 0 | CC42: 0 | CD42: 0 | CE42: 22 | CG42: 0 | CI42: 0 | CJ42: 0 | CK42: 22 | CM42: 0 | CO42: 0 | CP42: 0 | CQ42: 22 | CS42: 0 | CU42: 0 | CV42: 0 | CW42: 22 | CY42: 0 | DA42: 0 | DB42: 0 | DC42: 22 | DE42: 0 | DG42: 0 | DH42: 0 | DI42: 22 | DK42: 0 | DM42: 0 | DN42: 0 | DO42: 22 | DQ42: 0 | DS42: 0 | DT42: 0 | DU42: 22 | DW42: 0 | DY42: 0 | DZ42: 0 | EA42: 22 | EC42: 0 | EE42: 0 | EF42: 0 | EG42: 22 | EI42: 0 | EK42: 0 | EL42: 0 | EM42: 22 | EO42: 0 | EQ42: 0 | ER42: 0 | ES42: 22 | EU42: 0 | EW42: 0 | EX42: 0 | EY42: 22 | FA42: 0 | FC42: 0 | FD42: 0 | FE42: 22 | FG42: 0 | FI42: 0 | FJ42: 0 | FK42: 22 | FM42: 0 | FO42: 0 | FP42: 0 | FQ42: 22 | FS42: 0 | FU42: 0 | FV42: 0 | FW42: 22 | FY42: 0 | GA42: 0 | GB42: 0 | GC42: 22 | GE42: 0 | GG42: 0 | GH42: 0 | GI42: 22 | GK42: 0 | GM42: 0 | GN42: 0 | GO42: 22 | GQ42: 0 | GS42: 0 | GT42: 0 | GU42: 22 | GW42: 0 | GY42: 0 | GZ42: 0
A43: 038.961-00 | B43: 2022/0029260-001A | C43: G | D43: 2022/0029260 | E43: FXE1C10 | F43: 01/04/2026 | G43: 30/04/2026 | H43: CLAUDEMIR CORREIA E SILVA | I43: CLAUDEMIR CORREIA E SILVA | J43: NORMAL | K43: EMEE | L43: =CONTINUA!BV43 -> 0 | M43: =CONTINUA!BW43 -> 0 | O43: 6020.2022/0029260-3 | P43: 0 | Q43: 0 | S43: 0 | U43: 0 | V43: 0 | W43: 0 | Y43: 0 | AA43: 0 | AB43: 0 | AC43: 0 | AE43: 0 | AG43: 0 | AH43: 0 | AI43: 0 | AK43: 0 | AM43: 0 | AN43: 0 | AO43: 0 | AQ43: 0 | AS43: 0 | AT43: 0 | AU43: 0 | AW43: 0 | AY43: 0 | AZ43: 0 | BA43: 0 | BC43: 0 | BE43: 0 | BF43: 0 | BG43: 0 | BI43: 0 | BK43: 0 | BL43: 0 | BM43: 0 | BO43: 0 | BQ43: 0 | BR43: 0 | BS43: 0 | BU43: 0 | BW43: 0 | BX43: 0 | BY43: 0 | CA43: 0 | CC43: 0 | CD43: 0 | CE43: 0 | CG43: 0 | CI43: 0 | CJ43: 0 | CK43: 0 | CM43: 0 | CO43: 0 | CP43: 0 | CQ43: 0 | CS43: 0 | CU43: 0 | CV43: 0 | CW43: 0 | CY43: 0 | DA43: 0 | DB43: 0 | DC43: 0 | DE43: 0 | DG43: 0 | DH43: 0 | DI43: 0 | DK43: 0 | DM43: 0 | DN43: 0 | DO43: 0 | DQ43: 0 | DS43: 0 | DT43: 0 | DU43: 0 | DW43: 0 | DY43: 0 | DZ43: 0 | EA43: 0 | EC43: 0 | EE43: 0 | EF43: 0 | EG43: 0 | EI43: 0 | EK43: 0 | EL43: 0 | EM43: 0 | EO43: 0 | EQ43: 0 | ER43: 0 | ES43: 0 | EU43: 0 | EW43: 0 | EX43: 0 | EY43: 0 | FA43: 0 | FC43: 0 | FD43: 0 | FE43: 0 | FG43: 0 | FI43: 0 | FJ43: 0 | FK43: 0 | FM43: 0 | FO43: 0 | FP43: 0 | FQ43: 0 | FS43: 0 | FU43: 0 | FV43: 0 | FW43: 0 | FY43: 0 | GA43: 0 | GB43: 0 | GC43: 0 | GE43: 0 | GG43: 0 | GH43: 0 | GI43: 0 | GK43: 0 | GM43: 0 | GN43: 0 | GO43: 0 | GQ43: 0 | GS43: 0 | GT43: 0 | GU43: 0 | GW43: 0 | GY43: 0 | GZ43: 0
A44: 038.961-00 | B44: 2022/0029260-001A | C44: G | D44: 2022/0029260 | E44: FXE1C10 | F44: 01/04/2026 | G44: 30/04/2026 | H44: CLAUDEMIR CORREIA E SILVA | I44: CLAUDEMIR CORREIA E SILVA | J44: NORMAL | K44: CEI | L44: =CONTINUA!BV44 -> 0 | M44: =CONTINUA!BW44 -> 0 | O44: 6020.2022/0029260-3 | P44: 0 | Q44: 0 | S44: 0 | U44: 0 | V44: 0 | W44: 0 | Y44: 0 | AA44: 0 | AB44: 0 | AC44: 0 | AE44: 0 | AG44: 0 | AH44: 0 | AI44: 0 | AK44: 0 | AM44: 0 | AN44: 0 | AO44: 0 | AQ44: 0 | AS44: 0 | AT44: 0 | AU44: 0 | AW44: 0 | AY44: 0 | AZ44: 0 | BA44: 0 | BC44: 0 | BE44: 0 | BF44: 0 | BG44: 0 | BI44: 0 | BK44: 0 | BL44: 0 | BM44: 0 | BO44: 0 | BQ44: 0 | BR44: 0 | BS44: 0 | BU44: 0 | BW44: 0 | BX44: 0 | BY44: 0 | CA44: 0 | CC44: 0 | CD44: 0 | CE44: 0 | CG44: 0 | CI44: 0 | CJ44: 0 | CK44: 0 | CM44: 0 | CO44: 0 | CP44: 0 | CQ44: 0 | CS44: 0 | CU44: 0 | CV44: 0 | CW44: 0 | CY44: 0 | DA44: 0 | DB44: 0 | DC44: 0 | DE44: 0 | DG44: 0 | DH44: 0 | DI44: 0 | DK44: 0 | DM44: 0 | DN44: 0 | DO44: 0 | DQ44: 0 | DS44: 0 | DT44: 0 | DU44: 0 | DW44: 0 | DY44: 0 | DZ44: 0 | EA44: 0 | EC44: 0 | EE44: 0 | EF44: 0 | EG44: 0 | EI44: 0 | EK44: 0 | EL44: 0 | EM44: 0 | EO44: 0 | EQ44: 0 | ER44: 0 | ES44: 0 | EU44: 0 | EW44: 0 | EX44: 0 | EY44: 0 | FA44: 0 | FC44: 0 | FD44: 0 | FE44: 0 | FG44: 0 | FI44: 0 | FJ44: 0 | FK44: 0 | FM44: 0 | FO44: 0 | FP44: 0 | FQ44: 0 | FS44: 0 | FU44: 0 | FV44: 0 | FW44: 0 | FY44: 0 | GA44: 0 | GB44: 0 | GC44: 0 | GE44: 0 | GG44: 0 | GH44: 0 | GI44: 0 | GK44: 0 | GM44: 0 | GN44: 0 | GO44: 0 | GQ44: 0 | GS44: 0 | GT44: 0 | GU44: 0 | GW44: 0 | GY44: 0 | GZ44: 0
A45: 038.961-00 | B45: 2022/0029260-001A | C45: G | D45: 2022/0029260 | E45: FXE1C10 | F45: 01/04/2026 | G45: 30/04/2026 | H45: CLAUDEMIR CORREIA E SILVA | I45: CLAUDEMIR CORREIA E SILVA | J45: NORMAL | K45: CCA | L45: =CONTINUA!BV45 -> 0 | M45: =CONTINUA!BW45 -> 0 | O45: 6020.2022/0029260-3 | P45: 0 | Q45: 0 | S45: 0 | U45: 0 | V45: 0 | W45: 0 | Y45: 0 | AA45: 0 | AB45: 0 | AC45: 0 | AE45: 0 | AG45: 0 | AH45: 0 | AI45: 0 | AK45: 0 | AM45: 0 | AN45: 0 | AO45: 0 | AQ45: 0 | AS45: 0 | AT45: 0 | AU45: 0 | AW45: 0 | AY45: 0 | AZ45: 0 | BA45: 0 | BC45: 0 | BE45: 0 | BF45: 0 | BG45: 0 | BI45: 0 | BK45: 0 | BL45: 0 | BM45: 0 | BO45: 0 | BQ45: 0 | BR45: 0 | BS45: 0 | BU45: 0 | BW45: 0 | BX45: 0 | BY45: 0 | CA45: 0 | CC45: 0 | CD45: 0 | CE45: 0 | CG45: 0 | CI45: 0 | CJ45: 0 | CK45: 0 | CM45: 0 | CO45: 0 | CP45: 0 | CQ45: 0 | CS45: 0 | CU45: 0 | CV45: 0 | CW45: 0 | CY45: 0 | DA45: 0 | DB45: 0 | DC45: 0 | DE45: 0 | DG45: 0 | DH45: 0 | DI45: 0 | DK45: 0 | DM45: 0 | DN45: 0 | DO45: 0 | DQ45: 0 | DS45: 0 | DT45: 0 | DU45: 0 | DW45: 0 | DY45: 0 | DZ45: 0 | EA45: 0 | EC45: 0 | EE45: 0 | EF45: 0 | EG45: 0 | EI45: 0 | EK45: 0 | EL45: 0 | EM45: 0 | EO45: 0 | EQ45: 0 | ER45: 0 | ES45: 0 | EU45: 0 | EW45: 0 | EX45: 0 | EY45: 0 | FA45: 0 | FC45: 0 | FD45: 0 | FE45: 0 | FG45: 0 | FI45: 0 | FJ45: 0 | FK45: 0 | FM45: 0 | FO45: 0 | FP45: 0 | FQ45: 0 | FS45: 0 | FU45: 0 | FV45: 0 | FW45: 0 | FY45: 0 | GA45: 0 | GB45: 0 | GC45: 0 | GE45: 0 | GG45: 0 | GH45: 0 | GI45: 0 | GK45: 0 | GM45: 0 | GN45: 0 | GO45: 0 | GQ45: 0 | GS45: 0 | GT45: 0 | GU45: 0 | GW45: 0 | GY45: 0 | GZ45: 0
A46: 015.661-00 | B46: 2023/0015338-001B | C46: 1 | D46: 2023/0015338 | E46: DMG7186 | F46: 01/04/2026 | G46: 30/04/2026 | H46: DAVID CAMINI | I46: DAVID CAMINI | J46: NORMAL | K46: EMEI | L46: =CONTINUA!BV46 -> 0 | M46: =CONTINUA!BW46 -> 0 | O46: 6020.2023/0015338-9 | P46: 0 | Q46: 6 | S46: 0 | U46: 0 | V46: 0 | W46: 6 | Y46: 0 | AA46: 0 | AB46: 0 | AC46: 6 | AE46: 0 | AG46: 0 | AH46: 0 | AI46: 6 | AK46: 0 | AM46: 0 | AN46: 0 | AO46: 6 | AQ46: 0 | AS46: 0 | AT46: 0 | AU46: 6 | AW46: 0 | AY46: 0 | AZ46: 0 | BA46: 6 | BC46: 0 | BE46: 0 | BF46: 0 | BG46: 6 | BI46: 0 | BK46: 0 | BL46: 0 | BM46: 6 | BO46: 0 | BQ46: 0 | BR46: 0 | BS46: 6 | BU46: 0 | BW46: 0 | BX46: 0 | BY46: 6 | CA46: 0 | CC46: 0 | CD46: 0 | CE46: 6 | CG46: 0 | CI46: 0 | CJ46: 0 | CK46: 6 | CM46: 0 | CO46: 0 | CP46: 0 | CQ46: 6 | CS46: 0 | CU46: 0 | CV46: 0 | CW46: 6 | CY46: 0 | DA46: 0 | DB46: 0 | DC46: 6 | DE46: 0 | DG46: 0 | DH46: 0 | DI46: 6 | DK46: 0 | DM46: 0 | DN46: 0 | DO46: 6 | DQ46: 0 | DS46: 0 | DT46: 0 | DU46: 6 | DW46: 0 | DY46: 0 | DZ46: 0 | EA46: 6 | EC46: 0 | EE46: 0 | EF46: 0 | EG46: 6 | EI46: 0 | EK46: 0 | EL46: 0 | EM46: 6 | EO46: 0 | EQ46: 0 | ER46: 0 | ES46: 6 | EU46: 0 | EW46: 0 | EX46: 0 | EY46: 6 | FA46: 0 | FC46: 0 | FD46: 0 | FE46: 6 | FG46: 0 | FI46: 0 | FJ46: 0 | FK46: 6 | FM46: 0 | FO46: 0 | FP46: 0 | FQ46: 6 | FS46: 0 | FU46: 0 | FV46: 0 | FW46: 6 | FY46: 0 | GA46: 0 | GB46: 0 | GC46: 6 | GE46: 0 | GG46: 0 | GH46: 0 | GI46: 6 | GK46: 0 | GM46: 0 | GN46: 0 | GO46: 6 | GQ46: 0 | GS46: 0 | GT46: 0 | GU46: 6 | GW46: 0 | GY46: 0 | GZ46: 0
A47: 015.661-00 | B47: 2023/0015338-001B | C47: G | D47: 2023/0015338 | E47: DMG7186 | F47: 01/04/2026 | G47: 30/04/2026 | H47: DAVID CAMINI | I47: DAVID CAMINI | J47: NORMAL | K47: EMEF | L47: =CONTINUA!BV47 -> 0 | M47: =CONTINUA!BW47 -> 0 | O47: 6020.2023/0015338-9 | P47: 0 | Q47: 35 | S47: 3 | U47: 0 | V47: 0 | W47: 35 | Y47: 3 | AA47: 0 | AB47: 0 | AC47: 35 | AE47: 3 | AG47: 0 | AH47: 0 | AI47: 35 | AK47: 3 | AM47: 0 | AN47: 0 | AO47: 35 | AQ47: 3 | AS47: 0 | AT47: 0 | AU47: 35 | AW47: 3 | AY47: 0 | AZ47: 0 | BA47: 35 | BC47: 3 | BE47: 0 | BF47: 0 | BG47: 35 | BI47: 3 | BK47: 0 | BL47: 0 | BM47: 35 | BO47: 3 | BQ47: 0 | BR47: 0 | BS47: 35 | BU47: 3 | BW47: 0 | BX47: 0 | BY47: 35 | CA47: 3 | CC47: 0 | CD47: 0 | CE47: 35 | CG47: 3 | CI47: 0 | CJ47: 0 | CK47: 35 | CM47: 3 | CO47: 0 | CP47: 0 | CQ47: 35 | CS47: 3 | CU47: 0 | CV47: 0 | CW47: 35 | CY47: 3 | DA47: 0 | DB47: 0 | DC47: 35 | DE47: 3 | DG47: 0 | DH47: 0 | DI47: 35 | DK47: 3 | DM47: 0 | DN47: 0 | DO47: 35 | DQ47: 3 | DS47: 0 | DT47: 0 | DU47: 35 | DW47: 3 | DY47: 0 | DZ47: 0 | EA47: 35 | EC47: 3 | EE47: 0 | EF47: 0 | EG47: 35 | EI47: 3 | EK47: 0 | EL47: 0 | EM47: 35 | EO47: 3 | EQ47: 0 | ER47: 0 | ES47: 35 | EU47: 3 | EW47: 0 | EX47: 0 | EY47: 35 | FA47: 3 | FC47: 0 | FD47: 0 | FE47: 35 | FG47: 3 | FI47: 0 | FJ47: 0 | FK47: 35 | FM47: 3 | FO47: 0 | FP47: 0 | FQ47: 35 | FS47: 3 | FU47: 0 | FV47: 0 | FW47: 35 | FY47: 3 | GA47: 0 | GB47: 0 | GC47: 35 | GE47: 3 | GG47: 0 | GH47: 0 | GI47: 35 | GK47: 3 | GM47: 0 | GN47: 0 | GO47: 35 | GQ47: 3 | GS47: 0 | GT47: 0 | GU47: 35 | GW47: 3 | GY47: 0 | GZ47: 0
A48: 015.661-00 | B48: 2023/0015338-001B | C48: G | D48: 2023/0015338 | E48: DMG7186 | F48: 01/04/2026 | G48: 30/04/2026 | H48: DAVID CAMINI | I48: DAVID CAMINI | J48: NORMAL | K48: EMEE | L48: =CONTINUA!BV48 -> 0 | M48: =CONTINUA!BW48 -> 0 | O48: 6020.2023/0015338-9 | P48: 0 | Q48: 0 | S48: 0 | U48: 0 | V48: 0 | W48: 0 | Y48: 0 | AA48: 0 | AB48: 0 | AC48: 0 | AE48: 0 | AG48: 0 | AH48: 0 | AI48: 0 | AK48: 0 | AM48: 0 | AN48: 0 | AO48: 0 | AQ48: 0 | AS48: 0 | AT48: 0 | AU48: 0 | AW48: 0 | AY48: 0 | AZ48: 0 | BA48: 0 | BC48: 0 | BE48: 0 | BF48: 0 | BG48: 0 | BI48: 0 | BK48: 0 | BL48: 0 | BM48: 0 | BO48: 0 | BQ48: 0 | BR48: 0 | BS48: 0 | BU48: 0 | BW48: 0 | BX48: 0 | BY48: 0 | CA48: 0 | CC48: 0 | CD48: 0 | CE48: 0 | CG48: 0 | CI48: 0 | CJ48: 0 | CK48: 0 | CM48: 0 | CO48: 0 | CP48: 0 | CQ48: 0 | CS48: 0 | CU48: 0 | CV48: 0 | CW48: 0 | CY48: 0 | DA48: 0 | DB48: 0 | DC48: 0 | DE48: 0 | DG48: 0 | DH48: 0 | DI48: 0 | DK48: 0 | DM48: 0 | DN48: 0 | DO48: 0 | DQ48: 0 | DS48: 0 | DT48: 0 | DU48: 0 | DW48: 0 | DY48: 0 | DZ48: 0 | EA48: 0 | EC48: 0 | EE48: 0 | EF48: 0 | EG48: 0 | EI48: 0 | EK48: 0 | EL48: 0 | EM48: 0 | EO48: 0 | EQ48: 0 | ER48: 0 | ES48: 0 | EU48: 0 | EW48: 0 | EX48: 0 | EY48: 0 | FA48: 0 | FC48: 0 | FD48: 0 | FE48: 0 | FG48: 0 | FI48: 0 | FJ48: 0 | FK48: 0 | FM48: 0 | FO48: 0 | FP48: 0 | FQ48: 0 | FS48: 0 | FU48: 0 | FV48: 0 | FW48: 0 | FY48: 0 | GA48: 0 | GB48: 0 | GC48: 0 | GE48: 0 | GG48: 0 | GH48: 0 | GI48: 0 | GK48: 0 | GM48: 0 | GN48: 0 | GO48: 0 | GQ48: 0 | GS48: 0 | GT48: 0 | GU48: 0 | GW48: 0 | GY48: 0 | GZ48: 0
A49: 015.661-00 | B49: 2023/0015338-001B | C49: G | D49: 2023/0015338 | E49: DMG7186 | F49: 01/04/2026 | G49: 30/04/2026 | H49: DAVID CAMINI | I49: DAVID CAMINI | J49: NORMAL | K49: CEI | L49: =CONTINUA!BV49 -> 0 | M49: =CONTINUA!BW49 -> 0 | O49: 6020.2023/0015338-9 | P49: 0 | Q49: 0 | S49: 0 | U49: 0 | V49: 0 | W49: 0 | Y49: 0 | AA49: 0 | AB49: 0 | AC49: 0 | AE49: 0 | AG49: 0 | AH49: 0 | AI49: 0 | AK49: 0 | AM49: 0 | AN49: 0 | AO49: 0 | AQ49: 0 | AS49: 0 | AT49: 0 | AU49: 0 | AW49: 0 | AY49: 0 | AZ49: 0 | BA49: 0 | BC49: 0 | BE49: 0 | BF49: 0 | BG49: 0 | BI49: 0 | BK49: 0 | BL49: 0 | BM49: 0 | BO49: 0 | BQ49: 0 | BR49: 0 | BS49: 0 | BU49: 0 | BW49: 0 | BX49: 0 | BY49: 0 | CA49: 0 | CC49: 0 | CD49: 0 | CE49: 0 | CG49: 0 | CI49: 0 | CJ49: 0 | CK49: 0 | CM49: 0 | CO49: 0 | CP49: 0 | CQ49: 0 | CS49: 0 | CU49: 0 | CV49: 0 | CW49: 0 | CY49: 0 | DA49: 0 | DB49: 0 | DC49: 0 | DE49: 0 | DG49: 0 | DH49: 0 | DI49: 0 | DK49: 0 | DM49: 0 | DN49: 0 | DO49: 0 | DQ49: 0 | DS49: 0 | DT49: 0 | DU49: 0 | DW49: 0 | DY49: 0 | DZ49: 0 | EA49: 0 | EC49: 0 | EE49: 0 | EF49: 0 | EG49: 0 | EI49: 0 | EK49: 0 | EL49: 0 | EM49: 0 | EO49: 0 | EQ49: 0 | ER49: 0 | ES49: 0 | EU49: 0 | EW49: 0 | EX49: 0 | EY49: 0 | FA49: 0 | FC49: 0 | FD49: 0 | FE49: 0 | FG49: 0 | FI49: 0 | FJ49: 0 | FK49: 0 | FM49: 0 | FO49: 0 | FP49: 0 | FQ49: 0 | FS49: 0 | FU49: 0 | FV49: 0 | FW49: 0 | FY49: 0 | GA49: 0 | GB49: 0 | GC49: 0 | GE49: 0 | GG49: 0 | GH49: 0 | GI49: 0 | GK49: 0 | GM49: 0 | GN49: 0 | GO49: 0 | GQ49: 0 | GS49: 0 | GT49: 0 | GU49: 0 | GW49: 0 | GY49: 0 | GZ49: 0
A50: 015.661-00 | B50: 2023/0015338-001B | C50: G | D50: 2023/0015338 | E50: DMG7186 | F50: 01/04/2026 | G50: 30/04/2026 | H50: DAVID CAMINI | I50: DAVID CAMINI | J50: NORMAL | K50: CCA | L50: =CONTINUA!BV50 -> 0 | M50: =CONTINUA!BW50 -> 0 | O50: 6020.2023/0015338-9 | P50: 0 | Q50: 0 | S50: 0 | U50: 0 | V50: 0 | W50: 0 | Y50: 0 | AA50: 0 | AB50: 0 | AC50: 0 | AE50: 0 | AG50: 0 | AH50: 0 | AI50: 0 | AK50: 0 | AM50: 0 | AN50: 0 | AO50: 0 | AQ50: 0 | AS50: 0 | AT50: 0 | AU50: 0 | AW50: 0 | AY50: 0 | AZ50: 0 | BA50: 0 | BC50: 0 | BE50: 0 | BF50: 0 | BG50: 0 | BI50: 0 | BK50: 0 | BL50: 0 | BM50: 0 | BO50: 0 | BQ50: 0 | BR50: 0 | BS50: 0 | BU50: 0 | BW50: 0 | BX50: 0 | BY50: 0 | CA50: 0 | CC50: 0 | CD50: 0 | CE50: 0 | CG50: 0 | CI50: 0 | CJ50: 0 | CK50: 0 | CM50: 0 | CO50: 0 | CP50: 0 | CQ50: 0 | CS50: 0 | CU50: 0 | CV50: 0 | CW50: 0 | CY50: 0 | DA50: 0 | DB50: 0 | DC50: 0 | DE50: 0 | DG50: 0 | DH50: 0 | DI50: 0 | DK50: 0 | DM50: 0 | DN50: 0 | DO50: 0 | DQ50: 0 | DS50: 0 | DT50: 0 | DU50: 0 | DW50: 0 | DY50: 0 | DZ50: 0 | EA50: 0 | EC50: 0 | EE50: 0 | EF50: 0 | EG50: 0 | EI50: 0 | EK50: 0 | EL50: 0 | EM50: 0 | EO50: 0 | EQ50: 0 | ER50: 0 | ES50: 0 | EU50: 0 | EW50: 0 | EX50: 0 | EY50: 0 | FA50: 0 | FC50: 0 | FD50: 0 | FE50: 0 | FG50: 0 | FI50: 0 | FJ50: 0 | FK50: 0 | FM50: 0 | FO50: 0 | FP50: 0 | FQ50: 0 | FS50: 0 | FU50: 0 | FV50: 0 | FW50: 0 | FY50: 0 | GA50: 0 | GB50: 0 | GC50: 0 | GE50: 0 | GG50: 0 | GH50: 0 | GI50: 0 | GK50: 0 | GM50: 0 | GN50: 0 | GO50: 0 | GQ50: 0 | GS50: 0 | GT50: 0 | GU50: 0 | GW50: 0 | GY50: 0 | GZ50: 0
A51: 014.300-00 | B51: 2023/0024108-001 | C51: 1 | D51: 2023/0024108 | E51: DTD3001 | F51: 01/04/2026 | G51: 30/04/2026 | H51: EDILENE SALES FEITOZA | I51: EDILENE SALES FEITOZA | J51: NORMAL | K51: EMEI | L51: =CONTINUA!BV51 -> 0 | M51: =CONTINUA!BW51 -> 0 | O51: 6020.2023/0024108-3 | P51: 0 | Q51: 45 | S51: 0 | U51: 0 | V51: 0 | W51: 45 | Y51: 0 | AA51: 0 | AB51: 0 | AC51: 45 | AE51: 0 | AG51: 0 | AH51: 0 | AI51: 45 | AK51: 0 | AM51: 0 | AN51: 0 | AO51: 45 | AQ51: 0 | AS51: 0 | AT51: 0 | AU51: 45 | AW51: 0 | AY51: 0 | AZ51: 0 | BA51: 45 | BC51: 0 | BE51: 0 | BF51: 0 | BG51: 45 | BI51: 0 | BK51: 0 | BL51: 0 | BM51: 45 | BO51: 0 | BQ51: 0 | BR51: 0 | BS51: 45 | BU51: 0 | BW51: 0 | BX51: 0 | BY51: 45 | CA51: 0 | CC51: 0 | CD51: 0 | CE51: 45 | CG51: 0 | CI51: 0 | CJ51: 0 | CK51: 45 | CM51: 0 | CO51: 0 | CP51: 0 | CQ51: 45 | CS51: 0 | CU51: 0 | CV51: 0 | CW51: 45 | CY51: 0 | DA51: 0 | DB51: 0 | DC51: 45 | DE51: 0 | DG51: 0 | DH51: 0 | DI51: 45 | DK51: 0 | DM51: 0 | DN51: 0 | DO51: 45 | DQ51: 0 | DS51: 0 | DT51: 0 | DU51: 45 | DW51: 0 | DY51: 0 | DZ51: 0 | EA51: 45 | EC51: 0 | EE51: 0 | EF51: 0 | EG51: 45 | EI51: 0 | EK51: 0 | EL51: 0 | EM51: 45 | EO51: 0 | EQ51: 0 | ER51: 0 | ES51: 45 | EU51: 0 | EW51: 0 | EX51: 0 | EY51: 45 | FA51: 0 | FC51: 0 | FD51: 0 | FE51: 45 | FG51: 0 | FI51: 0 | FJ51: 0 | FK51: 45 | FM51: 0 | FO51: 0 | FP51: 0 | FQ51: 45 | FS51: 0 | FU51: 0 | FV51: 0 | FW51: 45 | FY51: 0 | GA51: 0 | GB51: 0 | GC51: 45 | GE51: 0 | GG51: 0 | GH51: 0 | GI51: 45 | GK51: 0 | GM51: 0 | GN51: 0 | GO51: 45 | GQ51: 0 | GS51: 0 | GT51: 0 | GU51: 45 | GW51: 0 | GY51: 0 | GZ51: 0
A52: 014.300-00 | B52: 2023/0024108-001 | C52: G | D52: 2023/0024108 | E52: DTD3001 | F52: 01/04/2026 | G52: 30/04/2026 | H52: EDILENE SALES FEITOZA | I52: EDILENE SALES FEITOZA | J52: NORMAL | K52: EMEF | L52: =CONTINUA!BV52 -> 0 | M52: =CONTINUA!BW52 -> 0 | O52: 6020.2023/0024108-3 | P52: 0 | Q52: 0 | S52: 0 | U52: 0 | V52: 0 | W52: 0 | Y52: 0 | AA52: 0 | AB52: 0 | AC52: 0 | AE52: 0 | AG52: 0 | AH52: 0 | AI52: 0 | AK52: 0 | AM52: 0 | AN52: 0 | AO52: 0 | AQ52: 0 | AS52: 0 | AT52: 0 | AU52: 0 | AW52: 0 | AY52: 0 | AZ52: 0 | BA52: 0 | BC52: 0 | BE52: 0 | BF52: 0 | BG52: 0 | BI52: 0 | BK52: 0 | BL52: 0 | BM52: 0 | BO52: 0 | BQ52: 0 | BR52: 0 | BS52: 0 | BU52: 0 | BW52: 0 | BX52: 0 | BY52: 0 | CA52: 0 | CC52: 0 | CD52: 0 | CE52: 0 | CG52: 0 | CI52: 0 | CJ52: 0 | CK52: 0 | CM52: 0 | CO52: 0 | CP52: 0 | CQ52: 0 | CS52: 0 | CU52: 0 | CV52: 0 | CW52: 0 | CY52: 0 | DA52: 0 | DB52: 0 | DC52: 0 | DE52: 0 | DG52: 0 | DH52: 0 | DI52: 0 | DK52: 0 | DM52: 0 | DN52: 0 | DO52: 0 | DQ52: 0 | DS52: 0 | DT52: 0 | DU52: 0 | DW52: 0 | DY52: 0 | DZ52: 0 | EA52: 0 | EC52: 0 | EE52: 0 | EF52: 0 | EG52: 0 | EI52: 0 | EK52: 0 | EL52: 0 | EM52: 0 | EO52: 0 | EQ52: 0 | ER52: 0 | ES52: 0 | EU52: 0 | EW52: 0 | EX52: 0 | EY52: 0 | FA52: 0 | FC52: 0 | FD52: 0 | FE52: 0 | FG52: 0 | FI52: 0 | FJ52: 0 | FK52: 0 | FM52: 0 | FO52: 0 | FP52: 0 | FQ52: 0 | FS52: 0 | FU52: 0 | FV52: 0 | FW52: 0 | FY52: 0 | GA52: 0 | GB52: 0 | GC52: 0 | GE52: 0 | GG52: 0 | GH52: 0 | GI52: 0 | GK52: 0 | GM52: 0 | GN52: 0 | GO52: 0 | GQ52: 0 | GS52: 0 | GT52: 0 | GU52: 0 | GW52: 0 | GY52: 0 | GZ52: 0
A53: 014.300-00 | B53: 2023/0024108-001 | C53: G | D53: 2023/0024108 | E53: DTD3001 | F53: 01/04/2026 | G53: 30/04/2026 | H53: EDILENE SALES FEITOZA | I53: EDILENE SALES FEITOZA | J53: NORMAL | K53: EMEE | L53: =CONTINUA!BV53 -> 0 | M53: =CONTINUA!BW53 -> 0 | O53: 6020.2023/0024108-3 | P53: 0 | Q53: 0 | S53: 0 | U53: 0 | V53: 0 | W53: 0 | Y53: 0 | AA53: 0 | AB53: 0 | AC53: 0 | AE53: 0 | AG53: 0 | AH53: 0 | AI53: 0 | AK53: 0 | AM53: 0 | AN53: 0 | AO53: 0 | AQ53: 0 | AS53: 0 | AT53: 0 | AU53: 0 | AW53: 0 | AY53: 0 | AZ53: 0 | BA53: 0 | BC53: 0 | BE53: 0 | BF53: 0 | BG53: 0 | BI53: 0 | BK53: 0 | BL53: 0 | BM53: 0 | BO53: 0 | BQ53: 0 | BR53: 0 | BS53: 0 | BU53: 0 | BW53: 0 | BX53: 0 | BY53: 0 | CA53: 0 | CC53: 0 | CD53: 0 | CE53: 0 | CG53: 0 | CI53: 0 | CJ53: 0 | CK53: 0 | CM53: 0 | CO53: 0 | CP53: 0 | CQ53: 0 | CS53: 0 | CU53: 0 | CV53: 0 | CW53: 0 | CY53: 0 | DA53: 0 | DB53: 0 | DC53: 0 | DE53: 0 | DG53: 0 | DH53: 0 | DI53: 0 | DK53: 0 | DM53: 0 | DN53: 0 | DO53: 0 | DQ53: 0 | DS53: 0 | DT53: 0 | DU53: 0 | DW53: 0 | DY53: 0 | DZ53: 0 | EA53: 0 | EC53: 0 | EE53: 0 | EF53: 0 | EG53: 0 | EI53: 0 | EK53: 0 | EL53: 0 | EM53: 0 | EO53: 0 | EQ53: 0 | ER53: 0 | ES53: 0 | EU53: 0 | EW53: 0 | EX53: 0 | EY53: 0 | FA53: 0 | FC53: 0 | FD53: 0 | FE53: 0 | FG53: 0 | FI53: 0 | FJ53: 0 | FK53: 0 | FM53: 0 | FO53: 0 | FP53: 0 | FQ53: 0 | FS53: 0 | FU53: 0 | FV53: 0 | FW53: 0 | FY53: 0 | GA53: 0 | GB53: 0 | GC53: 0 | GE53: 0 | GG53: 0 | GH53: 0 | GI53: 0 | GK53: 0 | GM53: 0 | GN53: 0 | GO53: 0 | GQ53: 0 | GS53: 0 | GT53: 0 | GU53: 0 | GW53: 0 | GY53: 0 | GZ53: 0
A54: 014.300-00 | B54: 2023/0024108-001 | C54: G | D54: 2023/0024108 | E54: DTD3001 | F54: 01/04/2026 | G54: 30/04/2026 | H54: EDILENE SALES FEITOZA | I54: EDILENE SALES FEITOZA | J54: NORMAL | K54: CEI | L54: =CONTINUA!BV54 -> 0 | M54: =CONTINUA!BW54 -> 0 | O54: 6020.2023/0024108-3 | P54: 0 | Q54: 0 | S54: 0 | U54: 0 | V54: 0 | W54: 0 | Y54: 0 | AA54: 0 | AB54: 0 | AC54: 0 | AE54: 0 | AG54: 0 | AH54: 0 | AI54: 0 | AK54: 0 | AM54: 0 | AN54: 0 | AO54: 0 | AQ54: 0 | AS54: 0 | AT54: 0 | AU54: 0 | AW54: 0 | AY54: 0 | AZ54: 0 | BA54: 0 | BC54: 0 | BE54: 0 | BF54: 0 | BG54: 0 | BI54: 0 | BK54: 0 | BL54: 0 | BM54: 0 | BO54: 0 | BQ54: 0 | BR54: 0 | BS54: 0 | BU54: 0 | BW54: 0 | BX54: 0 | BY54: 0 | CA54: 0 | CC54: 0 | CD54: 0 | CE54: 0 | CG54: 0 | CI54: 0 | CJ54: 0 | CK54: 0 | CM54: 0 | CO54: 0 | CP54: 0 | CQ54: 0 | CS54: 0 | CU54: 0 | CV54: 0 | CW54: 0 | CY54: 0 | DA54: 0 | DB54: 0 | DC54: 0 | DE54: 0 | DG54: 0 | DH54: 0 | DI54: 0 | DK54: 0 | DM54: 0 | DN54: 0 | DO54: 0 | DQ54: 0 | DS54: 0 | DT54: 0 | DU54: 0 | DW54: 0 | DY54: 0 | DZ54: 0 | EA54: 0 | EC54: 0 | EE54: 0 | EF54: 0 | EG54: 0 | EI54: 0 | EK54: 0 | EL54: 0 | EM54: 0 | EO54: 0 | EQ54: 0 | ER54: 0 | ES54: 0 | EU54: 0 | EW54: 0 | EX54: 0 | EY54: 0 | FA54: 0 | FC54: 0 | FD54: 0 | FE54: 0 | FG54: 0 | FI54: 0 | FJ54: 0 | FK54: 0 | FM54: 0 | FO54: 0 | FP54: 0 | FQ54: 0 | FS54: 0 | FU54: 0 | FV54: 0 | FW54: 0 | FY54: 0 | GA54: 0 | GB54: 0 | GC54: 0 | GE54: 0 | GG54: 0 | GH54: 0 | GI54: 0 | GK54: 0 | GM54: 0 | GN54: 0 | GO54: 0 | GQ54: 0 | GS54: 0 | GT54: 0 | GU54: 0 | GW54: 0 | GY54: 0 | GZ54: 0
A55: 014.300-00 | B55: 2023/0024108-001 | C55: G | D55: 2023/0024108 | E55: DTD3001 | F55: 01/04/2026 | G55: 30/04/2026 | H55: EDILENE SALES FEITOZA | I55: EDILENE SALES FEITOZA | J55: NORMAL | K55: CCA | L55: =CONTINUA!BV55 -> 0 | M55: =CONTINUA!BW55 -> 0 | O55: 6020.2023/0024108-3 | P55: 0 | Q55: 0 | S55: 0 | U55: 0 | V55: 0 | W55: 0 | Y55: 0 | AA55: 0 | AB55: 0 | AC55: 0 | AE55: 0 | AG55: 0 | AH55: 0 | AI55: 0 | AK55: 0 | AM55: 0 | AN55: 0 | AO55: 0 | AQ55: 0 | AS55: 0 | AT55: 0 | AU55: 0 | AW55: 0 | AY55: 0 | AZ55: 0 | BA55: 0 | BC55: 0 | BE55: 0 | BF55: 0 | BG55: 0 | BI55: 0 | BK55: 0 | BL55: 0 | BM55: 0 | BO55: 0 | BQ55: 0 | BR55: 0 | BS55: 0 | BU55: 0 | BW55: 0 | BX55: 0 | BY55: 0 | CA55: 0 | CC55: 0 | CD55: 0 | CE55: 0 | CG55: 0 | CI55: 0 | CJ55: 0 | CK55: 0 | CM55: 0 | CO55: 0 | CP55: 0 | CQ55: 0 | CS55: 0 | CU55: 0 | CV55: 0 | CW55: 0 | CY55: 0 | DA55: 0 | DB55: 0 | DC55: 0 | DE55: 0 | DG55: 0 | DH55: 0 | DI55: 0 | DK55: 0 | DM55: 0 | DN55: 0 | DO55: 0 | DQ55: 0 | DS55: 0 | DT55: 0 | DU55: 0 | DW55: 0 | DY55: 0 | DZ55: 0 | EA55: 0 | EC55: 0 | EE55: 0 | EF55: 0 | EG55: 0 | EI55: 0 | EK55: 0 | EL55: 0 | EM55: 0 | EO55: 0 | EQ55: 0 | ER55: 0 | ES55: 0 | EU55: 0 | EW55: 0 | EX55: 0 | EY55: 0 | FA55: 0 | FC55: 0 | FD55: 0 | FE55: 0 | FG55: 0 | FI55: 0 | FJ55: 0 | FK55: 0 | FM55: 0 | FO55: 0 | FP55: 0 | FQ55: 0 | FS55: 0 | FU55: 0 | FV55: 0 | FW55: 0 | FY55: 0 | GA55: 0 | GB55: 0 | GC55: 0 | GE55: 0 | GG55: 0 | GH55: 0 | GI55: 0 | GK55: 0 | GM55: 0 | GN55: 0 | GO55: 0 | GQ55: 0 | GS55: 0 | GT55: 0 | GU55: 0 | GW55: 0 | GY55: 0 | GZ55: 0
A56: 014.386-00 | B56: 2022/0029282-001 | C56: 1 | D56: 2022/0029282 | E56: EUV7153 | F56: 01/04/2026 | G56: 30/04/2026 | H56: EDUARDO MARSURA DOS SANTOS | I56: EDUARDO MARSURA DOS SANTOS | J56: NORMAL | K56: EMEI | L56: =CONTINUA!BV56 -> 0 | M56: =CONTINUA!BW56 -> 0 | O56: 6020.2022/0029282-4 | P56: 0 | Q56: 0 | S56: 0 | U56: 0 | V56: 0 | W56: 0 | Y56: 0 | AA56: 0 | AB56: 0 | AC56: 0 | AE56: 0 | AG56: 0 | AH56: 0 | AI56: 0 | AK56: 0 | AM56: 0 | AN56: 0 | AO56: 0 | AQ56: 0 | AS56: 0 | AT56: 0 | AU56: 0 | AW56: 0 | AY56: 0 | AZ56: 0 | BA56: 0 | BC56: 0 | BE56: 0 | BF56: 0 | BG56: 0 | BI56: 0 | BK56: 0 | BL56: 0 | BM56: 0 | BO56: 0 | BQ56: 0 | BR56: 0 | BS56: 0 | BU56: 0 | BW56: 0 | BX56: 0 | BY56: 0 | CA56: 0 | CC56: 0 | CD56: 0 | CE56: 0 | CG56: 0 | CI56: 0 | CJ56: 0 | CK56: 0 | CM56: 0 | CO56: 0 | CP56: 0 | CQ56: 0 | CS56: 0 | CU56: 0 | CV56: 0 | CW56: 0 | CY56: 0 | DA56: 0 | DB56: 0 | DC56: 0 | DE56: 0 | DG56: 0 | DH56: 0 | DI56: 0 | DK56: 0 | DM56: 0 | DN56: 0 | DO56: 0 | DQ56: 0 | DS56: 0 | DT56: 0 | DU56: 0 | DW56: 0 | DY56: 0 | DZ56: 0 | EA56: 0 | EC56: 0 | EE56: 0 | EF56: 0 | EG56: 0 | EI56: 0 | EK56: 0 | EL56: 0 | EM56: 0 | EO56: 0 | EQ56: 0 | ER56: 0 | ES56: 0 | EU56: 0 | EW56: 0 | EX56: 0 | EY56: 0 | FA56: 0 | FC56: 0 | FD56: 0 | FE56: 0 | FG56: 0 | FI56: 0 | FJ56: 0 | FK56: 0 | FM56: 0 | FO56: 0 | FP56: 0 | FQ56: 0 | FS56: 0 | FU56: 0 | FV56: 0 | FW56: 0 | FY56: 0 | GA56: 0 | GB56: 0 | GC56: 0 | GE56: 0 | GG56: 0 | GH56: 0 | GI56: 0 | GK56: 0 | GM56: 0 | GN56: 0 | GO56: 0 | GQ56: 0 | GS56: 0 | GT56: 0 | GU56: 0 | GW56: 0 | GY56: 0 | GZ56: 0
A57: 014.386-00 | B57: 2022/0029282-001 | C57: G | D57: 2022/0029282 | E57: EUV7153 | F57: 01/04/2026 | G57: 30/04/2026 | H57: EDUARDO MARSURA DOS SANTOS | I57: EDUARDO MARSURA DOS SANTOS | J57: NORMAL | K57: EMEF | L57: =CONTINUA!BV57 -> 44 | M57: =CONTINUA!BW57 -> 0 | O57: 6020.2022/0029282-4 | P57: 0 | Q57: 36 | S57: 13 | U57: 0 | V57: 0 | W57: 36 | Y57: 13 | AA57: 0 | AB57: 0 | AC57: 36 | AE57: 13 | AG57: 0 | AH57: 0 | AI57: 36 | AK57: 13 | AM57: 0 | AN57: 0 | AO57: 36 | AQ57: 13 | AS57: 0 | AT57: 0 | AU57: 36 | AW57: 13 | AY57: 0 | AZ57: 0 | BA57: 36 | BC57: 13 | BE57: 0 | BF57: 0 | BG57: 36 | BI57: 13 | BK57: 0 | BL57: 0 | BM57: 36 | BO57: 13 | BQ57: 0 | BR57: 0 | BS57: 36 | BU57: 13 | BW57: 0 | BX57: 0 | BY57: 36 | CA57: 13 | CC57: 0 | CD57: 0 | CE57: 36 | CG57: 13 | CI57: 0 | CJ57: 0 | CK57: 36 | CM57: 13 | CO57: 0 | CP57: 0 | CQ57: 36 | CS57: 13 | CU57: 0 | CV57: 0 | CW57: 36 | CY57: 13 | DA57: 0 | DB57: 0 | DC57: 36 | DE57: 13 | DG57: 0 | DH57: 0 | DI57: 36 | DK57: 13 | DM57: 0 | DN57: 0 | DO57: 36 | DQ57: 13 | DS57: 0 | DT57: 0 | DU57: 36 | DW57: 13 | DY57: 0 | DZ57: 0 | EA57: 36 | EC57: 13 | EE57: 0 | EF57: 0 | EG57: 36 | EI57: 13 | EK57: 0 | EL57: 0 | EM57: 36 | EO57: 13 | EQ57: 0 | ER57: 0 | ES57: 36 | EU57: 13 | EW57: 0 | EX57: 0 | EY57: 36 | FA57: 13 | FC57: 0 | FD57: 0 | FE57: 36 | FG57: 13 | FI57: 0 | FJ57: 0 | FK57: 36 | FM57: 13 | FO57: 0 | FP57: 0 | FQ57: 36 | FS57: 13 | FU57: 0 | FV57: 0 | FW57: 36 | FY57: 13 | GA57: 0 | GB57: 0 | GC57: 36 | GE57: 13 | GG57: 0 | GH57: 0 | GI57: 36 | GK57: 13 | GM57: 0 | GN57: 0 | GO57: 36 | GQ57: 13 | GS57: 0 | GT57: 0 | GU57: 36 | GW57: 13 | GY57: 0 | GZ57: 0
A58: 014.386-00 | B58: 2022/0029282-001 | C58: G | D58: 2022/0029282 | E58: EUV7153 | F58: 01/04/2026 | G58: 30/04/2026 | H58: EDUARDO MARSURA DOS SANTOS | I58: EDUARDO MARSURA DOS SANTOS | J58: NORMAL | K58: EMEE | L58: =CONTINUA!BV58 -> 0 | M58: =CONTINUA!BW58 -> 0 | O58: 6020.2022/0029282-4 | P58: 0 | Q58: 0 | S58: 0 | U58: 0 | V58: 0 | W58: 0 | Y58: 0 | AA58: 0 | AB58: 0 | AC58: 0 | AE58: 0 | AG58: 0 | AH58: 0 | AI58: 0 | AK58: 0 | AM58: 0 | AN58: 0 | AO58: 0 | AQ58: 0 | AS58: 0 | AT58: 0 | AU58: 0 | AW58: 0 | AY58: 0 | AZ58: 0 | BA58: 0 | BC58: 0 | BE58: 0 | BF58: 0 | BG58: 0 | BI58: 0 | BK58: 0 | BL58: 0 | BM58: 0 | BO58: 0 | BQ58: 0 | BR58: 0 | BS58: 0 | BU58: 0 | BW58: 0 | BX58: 0 | BY58: 0 | CA58: 0 | CC58: 0 | CD58: 0 | CE58: 0 | CG58: 0 | CI58: 0 | CJ58: 0 | CK58: 0 | CM58: 0 | CO58: 0 | CP58: 0 | CQ58: 0 | CS58: 0 | CU58: 0 | CV58: 0 | CW58: 0 | CY58: 0 | DA58: 0 | DB58: 0 | DC58: 0 | DE58: 0 | DG58: 0 | DH58: 0 | DI58: 0 | DK58: 0 | DM58: 0 | DN58: 0 | DO58: 0 | DQ58: 0 | DS58: 0 | DT58: 0 | DU58: 0 | DW58: 0 | DY58: 0 | DZ58: 0 | EA58: 0 | EC58: 0 | EE58: 0 | EF58: 0 | EG58: 0 | EI58: 0 | EK58: 0 | EL58: 0 | EM58: 0 | EO58: 0 | EQ58: 0 | ER58: 0 | ES58: 0 | EU58: 0 | EW58: 0 | EX58: 0 | EY58: 0 | FA58: 0 | FC58: 0 | FD58: 0 | FE58: 0 | FG58: 0 | FI58: 0 | FJ58: 0 | FK58: 0 | FM58: 0 | FO58: 0 | FP58: 0 | FQ58: 0 | FS58: 0 | FU58: 0 | FV58: 0 | FW58: 0 | FY58: 0 | GA58: 0 | GB58: 0 | GC58: 0 | GE58: 0 | GG58: 0 | GH58: 0 | GI58: 0 | GK58: 0 | GM58: 0 | GN58: 0 | GO58: 0 | GQ58: 0 | GS58: 0 | GT58: 0 | GU58: 0 | GW58: 0 | GY58: 0 | GZ58: 0
A59: 014.386-00 | B59: 2022/0029282-001 | C59: G | D59: 2022/0029282 | E59: EUV7153 | F59: 01/04/2026 | G59: 30/04/2026 | H59: EDUARDO MARSURA DOS SANTOS | I59: EDUARDO MARSURA DOS SANTOS | J59: NORMAL | K59: CEI | L59: =CONTINUA!BV59 -> 0 | M59: =CONTINUA!BW59 -> 0 | O59: 6020.2022/0029282-4 | P59: 0 | Q59: 0 | S59: 0 | U59: 0 | V59: 0 | W59: 0 | Y59: 0 | AA59: 0 | AB59: 0 | AC59: 0 | AE59: 0 | AG59: 0 | AH59: 0 | AI59: 0 | AK59: 0 | AM59: 0 | AN59: 0 | AO59: 0 | AQ59: 0 | AS59: 0 | AT59: 0 | AU59: 0 | AW59: 0 | AY59: 0 | AZ59: 0 | BA59: 0 | BC59: 0 | BE59: 0 | BF59: 0 | BG59: 0 | BI59: 0 | BK59: 0 | BL59: 0 | BM59: 0 | BO59: 0 | BQ59: 0 | BR59: 0 | BS59: 0 | BU59: 0 | BW59: 0 | BX59: 0 | BY59: 0 | CA59: 0 | CC59: 0 | CD59: 0 | CE59: 0 | CG59: 0 | CI59: 0 | CJ59: 0 | CK59: 0 | CM59: 0 | CO59: 0 | CP59: 0 | CQ59: 0 | CS59: 0 | CU59: 0 | CV59: 0 | CW59: 0 | CY59: 0 | DA59: 0 | DB59: 0 | DC59: 0 | DE59: 0 | DG59: 0 | DH59: 0 | DI59: 0 | DK59: 0 | DM59: 0 | DN59: 0 | DO59: 0 | DQ59: 0 | DS59: 0 | DT59: 0 | DU59: 0 | DW59: 0 | DY59: 0 | DZ59: 0 | EA59: 0 | EC59: 0 | EE59: 0 | EF59: 0 | EG59: 0 | EI59: 0 | EK59: 0 | EL59: 0 | EM59: 0 | EO59: 0 | EQ59: 0 | ER59: 0 | ES59: 0 | EU59: 0 | EW59: 0 | EX59: 0 | EY59: 0 | FA59: 0 | FC59: 0 | FD59: 0 | FE59: 0 | FG59: 0 | FI59: 0 | FJ59: 0 | FK59: 0 | FM59: 0 | FO59: 0 | FP59: 0 | FQ59: 0 | FS59: 0 | FU59: 0 | FV59: 0 | FW59: 0 | FY59: 0 | GA59: 0 | GB59: 0 | GC59: 0 | GE59: 0 | GG59: 0 | GH59: 0 | GI59: 0 | GK59: 0 | GM59: 0 | GN59: 0 | GO59: 0 | GQ59: 0 | GS59: 0 | GT59: 0 | GU59: 0 | GW59: 0 | GY59: 0 | GZ59: 0
A60: 014.386-00 | B60: 2022/0029282-001 | C60: G | D60: 2022/0029282 | E60: EUV7153 | F60: 01/04/2026 | G60: 30/04/2026 | H60: EDUARDO MARSURA DOS SANTOS | I60: EDUARDO MARSURA DOS SANTOS | J60: NORMAL | K60: CCA | L60: =CONTINUA!BV60 -> 0 | M60: =CONTINUA!BW60 -> 0 | O60: 6020.2022/0029282-4 | P60: 0 | Q60: 0 | S60: 0 | U60: 0 | V60: 0 | W60: 0 | Y60: 0 | AA60: 0 | AB60: 0 | AC60: 0 | AE60: 0 | AG60: 0 | AH60: 0 | AI60: 0 | AK60: 0 | AM60: 0 | AN60: 0 | AO60: 0 | AQ60: 0 | AS60: 0 | AT60: 0 | AU60: 0 | AW60: 0 | AY60: 0 | AZ60: 0 | BA60: 0 | BC60: 0 | BE60: 0 | BF60: 0 | BG60: 0 | BI60: 0 | BK60: 0 | BL60: 0 | BM60: 0 | BO60: 0 | BQ60: 0 | BR60: 0 | BS60: 0 | BU60: 0 | BW60: 0 | BX60: 0 | BY60: 0 | CA60: 0 | CC60: 0 | CD60: 0 | CE60: 0 | CG60: 0 | CI60: 0 | CJ60: 0 | CK60: 0 | CM60: 0 | CO60: 0 | CP60: 0 | CQ60: 0 | CS60: 0 | CU60: 0 | CV60: 0 | CW60: 0 | CY60: 0 | DA60: 0 | DB60: 0 | DC60: 0 | DE60: 0 | DG60: 0 | DH60: 0 | DI60: 0 | DK60: 0 | DM60: 0 | DN60: 0 | DO60: 0 | DQ60: 0 | DS60: 0 | DT60: 0 | DU60: 0 | DW60: 0 | DY60: 0 | DZ60: 0 | EA60: 0 | EC60: 0 | EE60: 0 | EF60: 0 | EG60: 0 | EI60: 0 | EK60: 0 | EL60: 0 | EM60: 0 | EO60: 0 | EQ60: 0 | ER60: 0 | ES60: 0 | EU60: 0 | EW60: 0 | EX60: 0 | EY60: 0 | FA60: 0 | FC60: 0 | FD60: 0 | FE60: 0 | FG60: 0 | FI60: 0 | FJ60: 0 | FK60: 0 | FM60: 0 | FO60: 0 | FP60: 0 | FQ60: 0 | FS60: 0 | FU60: 0 | FV60: 0 | FW60: 0 | FY60: 0 | GA60: 0 | GB60: 0 | GC60: 0 | GE60: 0 | GG60: 0 | GH60: 0 | GI60: 0 | GK60: 0 | GM60: 0 | GN60: 0 | GO60: 0 | GQ60: 0 | GS60: 0 | GT60: 0 | GU60: 0 | GW60: 0 | GY60: 0 | GZ60: 0
A61: 019.568-00 | B61: 2022/0032072-001 | C61: 1 | D61: 2022/0032072 | E61: CZX8751 | F61: 01/04/2026 | G61: 30/04/2026 | H61: EDUARDO ROMUALDO | I61: EDUARDO ROMUALDO | J61: NORMAL | K61: EMEI | L61: =CONTINUA!BV61 -> 0 | M61: =CONTINUA!BW61 -> 0 | O61: 6020.2022/0032072-0 | P61: 0 | Q61: 7 | S61: 0 | U61: 0 | V61: 0 | W61: 7 | Y61: 0 | AA61: 0 | AB61: 0 | AC61: 7 | AE61: 0 | AG61: 0 | AH61: 0 | AI61: 7 | AK61: 0 | AM61: 0 | AN61: 0 | AO61: 7 | AQ61: 0 | AS61: 0 | AT61: 0 | AU61: 7 | AW61: 0 | AY61: 0 | AZ61: 0 | BA61: 7 | BC61: 0 | BE61: 0 | BF61: 0 | BG61: 7 | BI61: 0 | BK61: 0 | BL61: 0 | BM61: 7 | BO61: 0 | BQ61: 0 | BR61: 0 | BS61: 7 | BU61: 0 | BW61: 0 | BX61: 0 | BY61: 7 | CA61: 0 | CC61: 0 | CD61: 0 | CE61: 7 | CG61: 0 | CI61: 0 | CJ61: 0 | CK61: 7 | CM61: 0 | CO61: 0 | CP61: 0 | CQ61: 7 | CS61: 0 | CU61: 0 | CV61: 0 | CW61: 7 | CY61: 0 | DA61: 0 | DB61: 0 | DC61: 7 | DE61: 0 | DG61: 0 | DH61: 0 | DI61: 7 | DK61: 0 | DM61: 0 | DN61: 0 | DO61: 7 | DQ61: 0 | DS61: 0 | DT61: 0 | DU61: 7 | DW61: 0 | DY61: 0 | DZ61: 0 | EA61: 7 | EC61: 0 | EE61: 0 | EF61: 0 | EG61: 7 | EI61: 0 | EK61: 0 | EL61: 0 | EM61: 7 | EO61: 0 | EQ61: 0 | ER61: 0 | ES61: 7 | EU61: 0 | EW61: 0 | EX61: 0 | EY61: 7 | FA61: 0 | FC61: 0 | FD61: 0 | FE61: 7 | FG61: 0 | FI61: 0 | FJ61: 0 | FK61: 7 | FM61: 0 | FO61: 0 | FP61: 0 | FQ61: 7 | FS61: 0 | FU61: 0 | FV61: 0 | FW61: 7 | FY61: 0 | GA61: 0 | GB61: 0 | GC61: 7 | GE61: 0 | GG61: 0 | GH61: 0 | GI61: 7 | GK61: 0 | GM61: 0 | GN61: 0 | GO61: 7 | GQ61: 0 | GS61: 0 | GT61: 0 | GU61: 7 | GW61: 0 | GY61: 0 | GZ61: 0
A62: 019.568-00 | B62: 2022/0032072-001 | C62: G | D62: 2022/0032072 | E62: CZX8751 | F62: 01/04/2026 | G62: 30/04/2026 | H62: EDUARDO ROMUALDO | I62: EDUARDO ROMUALDO | J62: NORMAL | K62: EMEF | L62: =CONTINUA!BV62 -> 0 | M62: =CONTINUA!BW62 -> 0 | O62: 6020.2022/0032072-0 | P62: 0 | Q62: 32 | S62: 2 | U62: 0 | V62: 0 | W62: 32 | Y62: 2 | AA62: 0 | AB62: 0 | AC62: 32 | AE62: 2 | AG62: 0 | AH62: 0 | AI62: 32 | AK62: 2 | AM62: 0 | AN62: 0 | AO62: 32 | AQ62: 2 | AS62: 0 | AT62: 0 | AU62: 32 | AW62: 2 | AY62: 0 | AZ62: 0 | BA62: 32 | BC62: 2 | BE62: 0 | BF62: 0 | BG62: 32 | BI62: 2 | BK62: 0 | BL62: 0 | BM62: 32 | BO62: 2 | BQ62: 0 | BR62: 0 | BS62: 32 | BU62: 2 | BW62: 0 | BX62: 0 | BY62: 32 | CA62: 2 | CC62: 0 | CD62: 0 | CE62: 32 | CG62: 2 | CI62: 0 | CJ62: 0 | CK62: 32 | CM62: 2 | CO62: 0 | CP62: 0 | CQ62: 32 | CS62: 2 | CU62: 0 | CV62: 0 | CW62: 32 | CY62: 2 | DA62: 0 | DB62: 0 | DC62: 32 | DE62: 2 | DG62: 0 | DH62: 0 | DI62: 32 | DK62: 2 | DM62: 0 | DN62: 0 | DO62: 32 | DQ62: 2 | DS62: 0 | DT62: 0 | DU62: 32 | DW62: 2 | DY62: 0 | DZ62: 0 | EA62: 32 | EC62: 2 | EE62: 0 | EF62: 0 | EG62: 32 | EI62: 2 | EK62: 0 | EL62: 0 | EM62: 32 | EO62: 2 | EQ62: 0 | ER62: 0 | ES62: 32 | EU62: 2 | EW62: 0 | EX62: 0 | EY62: 32 | FA62: 2 | FC62: 0 | FD62: 0 | FE62: 32 | FG62: 2 | FI62: 0 | FJ62: 0 | FK62: 32 | FM62: 2 | FO62: 0 | FP62: 0 | FQ62: 32 | FS62: 2 | FU62: 0 | FV62: 0 | FW62: 32 | FY62: 2 | GA62: 0 | GB62: 0 | GC62: 32 | GE62: 2 | GG62: 0 | GH62: 0 | GI62: 32 | GK62: 2 | GM62: 0 | GN62: 0 | GO62: 32 | GQ62: 2 | GS62: 0 | GT62: 0 | GU62: 32 | GW62: 2 | GY62: 0 | GZ62: 0
A63: 019.568-00 | B63: 2022/0032072-001 | C63: G | D63: 2022/0032072 | E63: CZX8751 | F63: 01/04/2026 | G63: 30/04/2026 | H63: EDUARDO ROMUALDO | I63: EDUARDO ROMUALDO | J63: NORMAL | K63: EMEE | L63: =CONTINUA!BV63 -> 0 | M63: =CONTINUA!BW63 -> 0 | O63: 6020.2022/0032072-0 | P63: 0 | Q63: 0 | S63: 0 | U63: 0 | V63: 0 | W63: 0 | Y63: 0 | AA63: 0 | AB63: 0 | AC63: 0 | AE63: 0 | AG63: 0 | AH63: 0 | AI63: 0 | AK63: 0 | AM63: 0 | AN63: 0 | AO63: 0 | AQ63: 0 | AS63: 0 | AT63: 0 | AU63: 0 | AW63: 0 | AY63: 0 | AZ63: 0 | BA63: 0 | BC63: 0 | BE63: 0 | BF63: 0 | BG63: 0 | BI63: 0 | BK63: 0 | BL63: 0 | BM63: 0 | BO63: 0 | BQ63: 0 | BR63: 0 | BS63: 0 | BU63: 0 | BW63: 0 | BX63: 0 | BY63: 0 | CA63: 0 | CC63: 0 | CD63: 0 | CE63: 0 | CG63: 0 | CI63: 0 | CJ63: 0 | CK63: 0 | CM63: 0 | CO63: 0 | CP63: 0 | CQ63: 0 | CS63: 0 | CU63: 0 | CV63: 0 | CW63: 0 | CY63: 0 | DA63: 0 | DB63: 0 | DC63: 0 | DE63: 0 | DG63: 0 | DH63: 0 | DI63: 0 | DK63: 0 | DM63: 0 | DN63: 0 | DO63: 0 | DQ63: 0 | DS63: 0 | DT63: 0 | DU63: 0 | DW63: 0 | DY63: 0 | DZ63: 0 | EA63: 0 | EC63: 0 | EE63: 0 | EF63: 0 | EG63: 0 | EI63: 0 | EK63: 0 | EL63: 0 | EM63: 0 | EO63: 0 | EQ63: 0 | ER63: 0 | ES63: 0 | EU63: 0 | EW63: 0 | EX63: 0 | EY63: 0 | FA63: 0 | FC63: 0 | FD63: 0 | FE63: 0 | FG63: 0 | FI63: 0 | FJ63: 0 | FK63: 0 | FM63: 0 | FO63: 0 | FP63: 0 | FQ63: 0 | FS63: 0 | FU63: 0 | FV63: 0 | FW63: 0 | FY63: 0 | GA63: 0 | GB63: 0 | GC63: 0 | GE63: 0 | GG63: 0 | GH63: 0 | GI63: 0 | GK63: 0 | GM63: 0 | GN63: 0 | GO63: 0 | GQ63: 0 | GS63: 0 | GT63: 0 | GU63: 0 | GW63: 0 | GY63: 0 | GZ63: 0
A64: 019.568-00 | B64: 2022/0032072-001 | C64: G | D64: 2022/0032072 | E64: CZX8751 | F64: 01/04/2026 | G64: 30/04/2026 | H64: EDUARDO ROMUALDO | I64: EDUARDO ROMUALDO | J64: NORMAL | K64: CEI | L64: =CONTINUA!BV64 -> 0 | M64: =CONTINUA!BW64 -> 0 | O64: 6020.2022/0032072-0 | P64: 0 | Q64: 0 | S64: 0 | U64: 0 | V64: 0 | W64: 0 | Y64: 0 | AA64: 0 | AB64: 0 | AC64: 0 | AE64: 0 | AG64: 0 | AH64: 0 | AI64: 0 | AK64: 0 | AM64: 0 | AN64: 0 | AO64: 0 | AQ64: 0 | AS64: 0 | AT64: 0 | AU64: 0 | AW64: 0 | AY64: 0 | AZ64: 0 | BA64: 0 | BC64: 0 | BE64: 0 | BF64: 0 | BG64: 0 | BI64: 0 | BK64: 0 | BL64: 0 | BM64: 0 | BO64: 0 | BQ64: 0 | BR64: 0 | BS64: 0 | BU64: 0 | BW64: 0 | BX64: 0 | BY64: 0 | CA64: 0 | CC64: 0 | CD64: 0 | CE64: 0 | CG64: 0 | CI64: 0 | CJ64: 0 | CK64: 0 | CM64: 0 | CO64: 0 | CP64: 0 | CQ64: 0 | CS64: 0 | CU64: 0 | CV64: 0 | CW64: 0 | CY64: 0 | DA64: 0 | DB64: 0 | DC64: 0 | DE64: 0 | DG64: 0 | DH64: 0 | DI64: 0 | DK64: 0 | DM64: 0 | DN64: 0 | DO64: 0 | DQ64: 0 | DS64: 0 | DT64: 0 | DU64: 0 | DW64: 0 | DY64: 0 | DZ64: 0 | EA64: 0 | EC64: 0 | EE64: 0 | EF64: 0 | EG64: 0 | EI64: 0 | EK64: 0 | EL64: 0 | EM64: 0 | EO64: 0 | EQ64: 0 | ER64: 0 | ES64: 0 | EU64: 0 | EW64: 0 | EX64: 0 | EY64: 0 | FA64: 0 | FC64: 0 | FD64: 0 | FE64: 0 | FG64: 0 | FI64: 0 | FJ64: 0 | FK64: 0 | FM64: 0 | FO64: 0 | FP64: 0 | FQ64: 0 | FS64: 0 | FU64: 0 | FV64: 0 | FW64: 0 | FY64: 0 | GA64: 0 | GB64: 0 | GC64: 0 | GE64: 0 | GG64: 0 | GH64: 0 | GI64: 0 | GK64: 0 | GM64: 0 | GN64: 0 | GO64: 0 | GQ64: 0 | GS64: 0 | GT64: 0 | GU64: 0 | GW64: 0 | GY64: 0 | GZ64: 0
A65: 019.568-00 | B65: 2022/0032072-001 | C65: G | D65: 2022/0032072 | E65: CZX8751 | F65: 01/04/2026 | G65: 30/04/2026 | H65: EDUARDO ROMUALDO | I65: EDUARDO ROMUALDO | J65: NORMAL | K65: CCA | L65: =CONTINUA!BV65 -> 0 | M65: =CONTINUA!BW65 -> 0 | O65: 6020.2022/0032072-0 | P65: 0 | Q65: 0 | S65: 0 | U65: 0 | V65: 0 | W65: 0 | Y65: 0 | AA65: 0 | AB65: 0 | AC65: 0 | AE65: 0 | AG65: 0 | AH65: 0 | AI65: 0 | AK65: 0 | AM65: 0 | AN65: 0 | AO65: 0 | AQ65: 0 | AS65: 0 | AT65: 0 | AU65: 0 | AW65: 0 | AY65: 0 | AZ65: 0 | BA65: 0 | BC65: 0 | BE65: 0 | BF65: 0 | BG65: 0 | BI65: 0 | BK65: 0 | BL65: 0 | BM65: 0 | BO65: 0 | BQ65: 0 | BR65: 0 | BS65: 0 | BU65: 0 | BW65: 0 | BX65: 0 | BY65: 0 | CA65: 0 | CC65: 0 | CD65: 0 | CE65: 0 | CG65: 0 | CI65: 0 | CJ65: 0 | CK65: 0 | CM65: 0 | CO65: 0 | CP65: 0 | CQ65: 0 | CS65: 0 | CU65: 0 | CV65: 0 | CW65: 0 | CY65: 0 | DA65: 0 | DB65: 0 | DC65: 0 | DE65: 0 | DG65: 0 | DH65: 0 | DI65: 0 | DK65: 0 | DM65: 0 | DN65: 0 | DO65: 0 | DQ65: 0 | DS65: 0 | DT65: 0 | DU65: 0 | DW65: 0 | DY65: 0 | DZ65: 0 | EA65: 0 | EC65: 0 | EE65: 0 | EF65: 0 | EG65: 0 | EI65: 0 | EK65: 0 | EL65: 0 | EM65: 0 | EO65: 0 | EQ65: 0 | ER65: 0 | ES65: 0 | EU65: 0 | EW65: 0 | EX65: 0 | EY65: 0 | FA65: 0 | FC65: 0 | FD65: 0 | FE65: 0 | FG65: 0 | FI65: 0 | FJ65: 0 | FK65: 0 | FM65: 0 | FO65: 0 | FP65: 0 | FQ65: 0 | FS65: 0 | FU65: 0 | FV65: 0 | FW65: 0 | FY65: 0 | GA65: 0 | GB65: 0 | GC65: 0 | GE65: 0 | GG65: 0 | GH65: 0 | GI65: 0 | GK65: 0 | GM65: 0 | GN65: 0 | GO65: 0 | GQ65: 0 | GS65: 0 | GT65: 0 | GU65: 0 | GW65: 0 | GY65: 0 | GZ65: 0
A66: 018.052-00 | B66: 2022/0029586-001 | C66: 1 | D66: 2022/0029586 | E66: FTG7519 | F66: 01/04/2026 | G66: 30/04/2026 | H66: ELIANA PEREIRA SILVA DE FARIA | I66: ELIANA PEREIRA SILVA DE FARIA | J66: NORMAL | K66: EMEI | L66: =CONTINUA!BV66 -> 0 | M66: =CONTINUA!BW66 -> 0 | O66: 6020.2022/0029586-6 | P66: 0 | Q66: 0 | S66: 0 | U66: 0 | V66: 0 | W66: 0 | Y66: 0 | AA66: 0 | AB66: 0 | AC66: 0 | AE66: 0 | AG66: 0 | AH66: 0 | AI66: 0 | AK66: 0 | AM66: 0 | AN66: 0 | AO66: 0 | AQ66: 0 | AS66: 0 | AT66: 0 | AU66: 0 | AW66: 0 | AY66: 0 | AZ66: 0 | BA66: 0 | BC66: 0 | BE66: 0 | BF66: 0 | BG66: 0 | BI66: 0 | BK66: 0 | BL66: 0 | BM66: 0 | BO66: 0 | BQ66: 0 | BR66: 0 | BS66: 0 | BU66: 0 | BW66: 0 | BX66: 0 | BY66: 0 | CA66: 0 | CC66: 0 | CD66: 0 | CE66: 0 | CG66: 0 | CI66: 0 | CJ66: 0 | CK66: 0 | CM66: 0 | CO66: 0 | CP66: 0 | CQ66: 0 | CS66: 0 | CU66: 0 | CV66: 0 | CW66: 0 | CY66: 0 | DA66: 0 | DB66: 0 | DC66: 0 | DE66: 0 | DG66: 0 | DH66: 0 | DI66: 0 | DK66: 0 | DM66: 0 | DN66: 0 | DO66: 0 | DQ66: 0 | DS66: 0 | DT66: 0 | DU66: 0 | DW66: 0 | DY66: 0 | DZ66: 0 | EA66: 0 | EC66: 0 | EE66: 0 | EF66: 0 | EG66: 0 | EI66: 0 | EK66: 0 | EL66: 0 | EM66: 0 | EO66: 0 | EQ66: 0 | ER66: 0 | ES66: 0 | EU66: 0 | EW66: 0 | EX66: 0 | EY66: 0 | FA66: 0 | FC66: 0 | FD66: 0 | FE66: 0 | FG66: 0 | FI66: 0 | FJ66: 0 | FK66: 0 | FM66: 0 | FO66: 0 | FP66: 0 | FQ66: 0 | FS66: 0 | FU66: 0 | FV66: 0 | FW66: 0 | FY66: 0 | GA66: 0 | GB66: 0 | GC66: 0 | GE66: 0 | GG66: 0 | GH66: 0 | GI66: 0 | GK66: 0 | GM66: 0 | GN66: 0 | GO66: 0 | GQ66: 0 | GS66: 0 | GT66: 0 | GU66: 0 | GW66: 0 | GY66: 0 | GZ66: 0
A67: 018.052-00 | B67: 2022/0029586-001 | C67: G | D67: 2022/0029586 | E67: FTG7519 | F67: 01/04/2026 | G67: 30/04/2026 | H67: ELIANA PEREIRA SILVA DE FARIA | I67: ELIANA PEREIRA SILVA DE FARIA | J67: NORMAL | K67: EMEF | L67: =CONTINUA!BV67 -> 0 | M67: =CONTINUA!BW67 -> 0 | O67: 6020.2022/0029586-6 | P67: 0 | Q67: 32 | S67: 2 | U67: 0 | V67: 0 | W67: 32 | Y67: 2 | AA67: 0 | AB67: 0 | AC67: 32 | AE67: 2 | AG67: 0 | AH67: 0 | AI67: 32 | AK67: 2 | AM67: 0 | AN67: 0 | AO67: 32 | AQ67: 2 | AS67: 0 | AT67: 0 | AU67: 32 | AW67: 2 | AY67: 0 | AZ67: 0 | BA67: 32 | BC67: 2 | BE67: 0 | BF67: 0 | BG67: 32 | BI67: 2 | BK67: 0 | BL67: 0 | BM67: 32 | BO67: 2 | BQ67: 0 | BR67: 0 | BS67: 32 | BU67: 2 | BW67: 0 | BX67: 0 | BY67: 32 | CA67: 2 | CC67: 0 | CD67: 0 | CE67: 32 | CG67: 2 | CI67: 0 | CJ67: 0 | CK67: 32 | CM67: 2 | CO67: 0 | CP67: 0 | CQ67: 32 | CS67: 2 | CU67: 0 | CV67: 0 | CW67: 32 | CY67: 2 | DA67: 0 | DB67: 0 | DC67: 32 | DE67: 2 | DG67: 0 | DH67: 0 | DI67: 32 | DK67: 2 | DM67: 0 | DN67: 0 | DO67: 32 | DQ67: 2 | DS67: 0 | DT67: 0 | DU67: 32 | DW67: 2 | DY67: 0 | DZ67: 0 | EA67: 32 | EC67: 2 | EE67: 0 | EF67: 0 | EG67: 32 | EI67: 2 | EK67: 0 | EL67: 0 | EM67: 32 | EO67: 2 | EQ67: 0 | ER67: 0 | ES67: 32 | EU67: 2 | EW67: 0 | EX67: 0 | EY67: 32 | FA67: 2 | FC67: 0 | FD67: 0 | FE67: 32 | FG67: 2 | FI67: 0 | FJ67: 0 | FK67: 32 | FM67: 2 | FO67: 0 | FP67: 0 | FQ67: 32 | FS67: 2 | FU67: 0 | FV67: 0 | FW67: 32 | FY67: 2 | GA67: 0 | GB67: 0 | GC67: 32 | GE67: 2 | GG67: 0 | GH67: 0 | GI67: 32 | GK67: 2 | GM67: 0 | GN67: 0 | GO67: 32 | GQ67: 2 | GS67: 0 | GT67: 0 | GU67: 32 | GW67: 2 | GY67: 0 | GZ67: 0
A68: 018.052-00 | B68: 2022/0029586-001 | C68: G | D68: 2022/0029586 | E68: FTG7519 | F68: 01/04/2026 | G68: 30/04/2026 | H68: ELIANA PEREIRA SILVA DE FARIA | I68: ELIANA PEREIRA SILVA DE FARIA | J68: NORMAL | K68: EMEE | L68: =CONTINUA!BV68 -> 0 | M68: =CONTINUA!BW68 -> 0 | O68: 6020.2022/0029586-6 | P68: 0 | Q68: 0 | S68: 0 | U68: 0 | V68: 0 | W68: 0 | Y68: 0 | AA68: 0 | AB68: 0 | AC68: 0 | AE68: 0 | AG68: 0 | AH68: 0 | AI68: 0 | AK68: 0 | AM68: 0 | AN68: 0 | AO68: 0 | AQ68: 0 | AS68: 0 | AT68: 0 | AU68: 0 | AW68: 0 | AY68: 0 | AZ68: 0 | BA68: 0 | BC68: 0 | BE68: 0 | BF68: 0 | BG68: 0 | BI68: 0 | BK68: 0 | BL68: 0 | BM68: 0 | BO68: 0 | BQ68: 0 | BR68: 0 | BS68: 0 | BU68: 0 | BW68: 0 | BX68: 0 | BY68: 0 | CA68: 0 | CC68: 0 | CD68: 0 | CE68: 0 | CG68: 0 | CI68: 0 | CJ68: 0 | CK68: 0 | CM68: 0 | CO68: 0 | CP68: 0 | CQ68: 0 | CS68: 0 | CU68: 0 | CV68: 0 | CW68: 0 | CY68: 0 | DA68: 0 | DB68: 0 | DC68: 0 | DE68: 0 | DG68: 0 | DH68: 0 | DI68: 0 | DK68: 0 | DM68: 0 | DN68: 0 | DO68: 0 | DQ68: 0 | DS68: 0 | DT68: 0 | DU68: 0 | DW68: 0 | DY68: 0 | DZ68: 0 | EA68: 0 | EC68: 0 | EE68: 0 | EF68: 0 | EG68: 0 | EI68: 0 | EK68: 0 | EL68: 0 | EM68: 0 | EO68: 0 | EQ68: 0 | ER68: 0 | ES68: 0 | EU68: 0 | EW68: 0 | EX68: 0 | EY68: 0 | FA68: 0 | FC68: 0 | FD68: 0 | FE68: 0 | FG68: 0 | FI68: 0 | FJ68: 0 | FK68: 0 | FM68: 0 | FO68: 0 | FP68: 0 | FQ68: 0 | FS68: 0 | FU68: 0 | FV68: 0 | FW68: 0 | FY68: 0 | GA68: 0 | GB68: 0 | GC68: 0 | GE68: 0 | GG68: 0 | GH68: 0 | GI68: 0 | GK68: 0 | GM68: 0 | GN68: 0 | GO68: 0 | GQ68: 0 | GS68: 0 | GT68: 0 | GU68: 0 | GW68: 0 | GY68: 0 | GZ68: 0
A69: 018.052-00 | B69: 2022/0029586-001 | C69: G | D69: 2022/0029586 | E69: FTG7519 | F69: 01/04/2026 | G69: 30/04/2026 | H69: ELIANA PEREIRA SILVA DE FARIA | I69: ELIANA PEREIRA SILVA DE FARIA | J69: NORMAL | K69: CEI | L69: =CONTINUA!BV69 -> 0 | M69: =CONTINUA!BW69 -> 0 | O69: 6020.2022/0029586-6 | P69: 0 | Q69: 0 | S69: 0 | U69: 0 | V69: 0 | W69: 0 | Y69: 0 | AA69: 0 | AB69: 0 | AC69: 0 | AE69: 0 | AG69: 0 | AH69: 0 | AI69: 0 | AK69: 0 | AM69: 0 | AN69: 0 | AO69: 0 | AQ69: 0 | AS69: 0 | AT69: 0 | AU69: 0 | AW69: 0 | AY69: 0 | AZ69: 0 | BA69: 0 | BC69: 0 | BE69: 0 | BF69: 0 | BG69: 0 | BI69: 0 | BK69: 0 | BL69: 0 | BM69: 0 | BO69: 0 | BQ69: 0 | BR69: 0 | BS69: 0 | BU69: 0 | BW69: 0 | BX69: 0 | BY69: 0 | CA69: 0 | CC69: 0 | CD69: 0 | CE69: 0 | CG69: 0 | CI69: 0 | CJ69: 0 | CK69: 0 | CM69: 0 | CO69: 0 | CP69: 0 | CQ69: 0 | CS69: 0 | CU69: 0 | CV69: 0 | CW69: 0 | CY69: 0 | DA69: 0 | DB69: 0 | DC69: 0 | DE69: 0 | DG69: 0 | DH69: 0 | DI69: 0 | DK69: 0 | DM69: 0 | DN69: 0 | DO69: 0 | DQ69: 0 | DS69: 0 | DT69: 0 | DU69: 0 | DW69: 0 | DY69: 0 | DZ69: 0 | EA69: 0 | EC69: 0 | EE69: 0 | EF69: 0 | EG69: 0 | EI69: 0 | EK69: 0 | EL69: 0 | EM69: 0 | EO69: 0 | EQ69: 0 | ER69: 0 | ES69: 0 | EU69: 0 | EW69: 0 | EX69: 0 | EY69: 0 | FA69: 0 | FC69: 0 | FD69: 0 | FE69: 0 | FG69: 0 | FI69: 0 | FJ69: 0 | FK69: 0 | FM69: 0 | FO69: 0 | FP69: 0 | FQ69: 0 | FS69: 0 | FU69: 0 | FV69: 0 | FW69: 0 | FY69: 0 | GA69: 0 | GB69: 0 | GC69: 0 | GE69: 0 | GG69: 0 | GH69: 0 | GI69: 0 | GK69: 0 | GM69: 0 | GN69: 0 | GO69: 0 | GQ69: 0 | GS69: 0 | GT69: 0 | GU69: 0 | GW69: 0 | GY69: 0 | GZ69: 0
A70: 018.052-00 | B70: 2022/0029586-001 | C70: G | D70: 2022/0029586 | E70: FTG7519 | F70: 01/04/2026 | G70: 30/04/2026 | H70: ELIANA PEREIRA SILVA DE FARIA | I70: ELIANA PEREIRA SILVA DE FARIA | J70: NORMAL | K70: CCA | L70: =CONTINUA!BV70 -> 0 | M70: =CONTINUA!BW70 -> 0 | O70: 6020.2022/0029586-6 | P70: 0 | Q70: 0 | S70: 0 | U70: 0 | V70: 0 | W70: 0 | Y70: 0 | AA70: 0 | AB70: 0 | AC70: 0 | AE70: 0 | AG70: 0 | AH70: 0 | AI70: 0 | AK70: 0 | AM70: 0 | AN70: 0 | AO70: 0 | AQ70: 0 | AS70: 0 | AT70: 0 | AU70: 0 | AW70: 0 | AY70: 0 | AZ70: 0 | BA70: 0 | BC70: 0 | BE70: 0 | BF70: 0 | BG70: 0 | BI70: 0 | BK70: 0 | BL70: 0 | BM70: 0 | BO70: 0 | BQ70: 0 | BR70: 0 | BS70: 0 | BU70: 0 | BW70: 0 | BX70: 0 | BY70: 0 | CA70: 0 | CC70: 0 | CD70: 0 | CE70: 0 | CG70: 0 | CI70: 0 | CJ70: 0 | CK70: 0 | CM70: 0 | CO70: 0 | CP70: 0 | CQ70: 0 | CS70: 0 | CU70: 0 | CV70: 0 | CW70: 0 | CY70: 0 | DA70: 0 | DB70: 0 | DC70: 0 | DE70: 0 | DG70: 0 | DH70: 0 | DI70: 0 | DK70: 0 | DM70: 0 | DN70: 0 | DO70: 0 | DQ70: 0 | DS70: 0 | DT70: 0 | DU70: 0 | DW70: 0 | DY70: 0 | DZ70: 0 | EA70: 0 | EC70: 0 | EE70: 0 | EF70: 0 | EG70: 0 | EI70: 0 | EK70: 0 | EL70: 0 | EM70: 0 | EO70: 0 | EQ70: 0 | ER70: 0 | ES70: 0 | EU70: 0 | EW70: 0 | EX70: 0 | EY70: 0 | FA70: 0 | FC70: 0 | FD70: 0 | FE70: 0 | FG70: 0 | FI70: 0 | FJ70: 0 | FK70: 0 | FM70: 0 | FO70: 0 | FP70: 0 | FQ70: 0 | FS70: 0 | FU70: 0 | FV70: 0 | FW70: 0 | FY70: 0 | GA70: 0 | GB70: 0 | GC70: 0 | GE70: 0 | GG70: 0 | GH70: 0 | GI70: 0 | GK70: 0 | GM70: 0 | GN70: 0 | GO70: 0 | GQ70: 0 | GS70: 0 | GT70: 0 | GU70: 0 | GW70: 0 | GY70: 0 | GZ70: 0
A71: 019.232-00 | B71: 2022/0036886-001 | C71: 4 | D71: 2022/0036886 | E71: CZX8905 | F71: 01/04/2026 | G71: 30/04/2026 | H71: ELISABETE NASCIMENTO | I71: ELISABETE NASCIMENTO | J71: NORMAL | K71: EMEI | L71: =CONTINUA!BV71 -> 0 | M71: =CONTINUA!BW71 -> 0 | O71: 6020.2022/0036886-3 | P71: 0 | Q71: 0 | S71: 0 | U71: 0 | V71: 0 | W71: 0 | Y71: 0 | AA71: 0 | AB71: 0 | AC71: 0 | AE71: 0 | AG71: 0 | AH71: 0 | AI71: 0 | AK71: 0 | AM71: 0 | AN71: 0 | AO71: 0 | AQ71: 0 | AS71: 0 | AT71: 0 | AU71: 0 | AW71: 0 | AY71: 0 | AZ71: 0 | BA71: 0 | BC71: 0 | BE71: 0 | BF71: 0 | BG71: 0 | BI71: 0 | BK71: 0 | BL71: 0 | BM71: 0 | BO71: 0 | BQ71: 0 | BR71: 0 | BS71: 0 | BU71: 0 | BW71: 0 | BX71: 0 | BY71: 0 | CA71: 0 | CC71: 0 | CD71: 0 | CE71: 0 | CG71: 0 | CI71: 0 | CJ71: 0 | CK71: 0 | CM71: 0 | CO71: 0 | CP71: 0 | CQ71: 0 | CS71: 0 | CU71: 0 | CV71: 0 | CW71: 0 | CY71: 0 | DA71: 0 | DB71: 0 | DC71: 0 | DE71: 0 | DG71: 0 | DH71: 0 | DI71: 0 | DK71: 0 | DM71: 0 | DN71: 0 | DO71: 0 | DQ71: 0 | DS71: 0 | DT71: 0 | DU71: 0 | DW71: 0 | DY71: 0 | DZ71: 0 | EA71: 0 | EC71: 0 | EE71: 0 | EF71: 0 | EG71: 0 | EI71: 0 | EK71: 0 | EL71: 0 | EM71: 0 | EO71: 0 | EQ71: 0 | ER71: 0 | ES71: 0 | EU71: 0 | EW71: 0 | EX71: 0 | EY71: 0 | FA71: 0 | FC71: 0 | FD71: 0 | FE71: 0 | FG71: 0 | FI71: 0 | FJ71: 0 | FK71: 0 | FM71: 0 | FO71: 0 | FP71: 0 | FQ71: 0 | FS71: 0 | FU71: 0 | FV71: 0 | FW71: 0 | FY71: 0 | GA71: 0 | GB71: 0 | GC71: 0 | GE71: 0 | GG71: 0 | GH71: 0 | GI71: 0 | GK71: 0 | GM71: 0 | GN71: 0 | GO71: 0 | GQ71: 0 | GS71: 0 | GT71: 0 | GU71: 0 | GW71: 0 | GY71: 0 | GZ71: 0
A72: 019.232-00 | B72: 2022/0036886-001 | C72: GE | D72: 2022/0036886 | E72: CZX8905 | F72: 01/04/2026 | G72: 30/04/2026 | H72: ELISABETE NASCIMENTO | I72: ELISABETE NASCIMENTO | J72: NORMAL | K72: EMEF | L72: =CONTINUA!BV72 -> 0 | M72: =CONTINUA!BW72 -> 0 | O72: 6020.2022/0036886-3 | P72: 0 | Q72: 6 | S72: 4 | U72: 0 | V72: 0 | W72: 6 | Y72: 4 | AA72: 0 | AB72: 0 | AC72: 6 | AE72: 4 | AG72: 0 | AH72: 0 | AI72: 6 | AK72: 4 | AM72: 0 | AN72: 0 | AO72: 6 | AQ72: 4 | AS72: 0 | AT72: 0 | AU72: 6 | AW72: 4 | AY72: 0 | AZ72: 0 | BA72: 6 | BC72: 4 | BE72: 0 | BF72: 0 | BG72: 6 | BI72: 4 | BK72: 0 | BL72: 0 | BM72: 6 | BO72: 4 | BQ72: 0 | BR72: 0 | BS72: 6 | BU72: 4 | BW72: 0 | BX72: 0 | BY72: 6 | CA72: 4 | CC72: 0 | CD72: 0 | CE72: 6 | CG72: 4 | CI72: 0 | CJ72: 0 | CK72: 6 | CM72: 4 | CO72: 0 | CP72: 0 | CQ72: 6 | CS72: 4 | CU72: 0 | CV72: 0 | CW72: 6 | CY72: 4 | DA72: 0 | DB72: 0 | DC72: 6 | DE72: 4 | DG72: 0 | DH72: 0 | DI72: 6 | DK72: 4 | DM72: 0 | DN72: 0 | DO72: 6 | DQ72: 4 | DS72: 0 | DT72: 0 | DU72: 6 | DW72: 4 | DY72: 0 | DZ72: 0 | EA72: 6 | EC72: 4 | EE72: 0 | EF72: 0 | EG72: 6 | EI72: 4 | EK72: 0 | EL72: 0 | EM72: 6 | EO72: 4 | EQ72: 0 | ER72: 0 | ES72: 6 | EU72: 4 | EW72: 0 | EX72: 0 | EY72: 6 | FA72: 4 | FC72: 0 | FD72: 0 | FE72: 6 | FG72: 4 | FI72: 0 | FJ72: 0 | FK72: 6 | FM72: 4 | FO72: 0 | FP72: 0 | FQ72: 6 | FS72: 4 | FU72: 0 | FV72: 0 | FW72: 6 | FY72: 4 | GA72: 0 | GB72: 0 | GC72: 6 | GE72: 4 | GG72: 0 | GH72: 0 | GI72: 6 | GK72: 4 | GM72: 0 | GN72: 0 | GO72: 6 | GQ72: 4 | GS72: 0 | GT72: 0 | GU72: 6 | GW72: 4 | GY72: 0 | GZ72: 0
A73: 019.232-00 | B73: 2022/0036886-001 | C73: GE | D73: 2022/0036886 | E73: CZX8905 | F73: 01/04/2026 | G73: 30/04/2026 | H73: ELISABETE NASCIMENTO | I73: ELISABETE NASCIMENTO | J73: NORMAL | K73: EMEE | L73: =CONTINUA!BV73 -> 0 | M73: =CONTINUA!BW73 -> 0 | O73: 6020.2022/0036886-3 | P73: 0 | Q73: 0 | S73: 0 | U73: 0 | V73: 0 | W73: 0 | Y73: 0 | AA73: 0 | AB73: 0 | AC73: 0 | AE73: 0 | AG73: 0 | AH73: 0 | AI73: 0 | AK73: 0 | AM73: 0 | AN73: 0 | AO73: 0 | AQ73: 0 | AS73: 0 | AT73: 0 | AU73: 0 | AW73: 0 | AY73: 0 | AZ73: 0 | BA73: 0 | BC73: 0 | BE73: 0 | BF73: 0 | BG73: 0 | BI73: 0 | BK73: 0 | BL73: 0 | BM73: 0 | BO73: 0 | BQ73: 0 | BR73: 0 | BS73: 0 | BU73: 0 | BW73: 0 | BX73: 0 | BY73: 0 | CA73: 0 | CC73: 0 | CD73: 0 | CE73: 0 | CG73: 0 | CI73: 0 | CJ73: 0 | CK73: 0 | CM73: 0 | CO73: 0 | CP73: 0 | CQ73: 0 | CS73: 0 | CU73: 0 | CV73: 0 | CW73: 0 | CY73: 0 | DA73: 0 | DB73: 0 | DC73: 0 | DE73: 0 | DG73: 0 | DH73: 0 | DI73: 0 | DK73: 0 | DM73: 0 | DN73: 0 | DO73: 0 | DQ73: 0 | DS73: 0 | DT73: 0 | DU73: 0 | DW73: 0 | DY73: 0 | DZ73: 0 | EA73: 0 | EC73: 0 | EE73: 0 | EF73: 0 | EG73: 0 | EI73: 0 | EK73: 0 | EL73: 0 | EM73: 0 | EO73: 0 | EQ73: 0 | ER73: 0 | ES73: 0 | EU73: 0 | EW73: 0 | EX73: 0 | EY73: 0 | FA73: 0 | FC73: 0 | FD73: 0 | FE73: 0 | FG73: 0 | FI73: 0 | FJ73: 0 | FK73: 0 | FM73: 0 | FO73: 0 | FP73: 0 | FQ73: 0 | FS73: 0 | FU73: 0 | FV73: 0 | FW73: 0 | FY73: 0 | GA73: 0 | GB73: 0 | GC73: 0 | GE73: 0 | GG73: 0 | GH73: 0 | GI73: 0 | GK73: 0 | GM73: 0 | GN73: 0 | GO73: 0 | GQ73: 0 | GS73: 0 | GT73: 0 | GU73: 0 | GW73: 0 | GY73: 0 | GZ73: 0
A74: 019.232-00 | B74: 2022/0036886-001 | C74: GE | D74: 2022/0036886 | E74: CZX8905 | F74: 01/04/2026 | G74: 30/04/2026 | H74: ELISABETE NASCIMENTO | I74: ELISABETE NASCIMENTO | J74: NORMAL | K74: CEI | L74: =CONTINUA!BV74 -> 0 | M74: =CONTINUA!BW74 -> 0 | O74: 6020.2022/0036886-3 | P74: 0 | Q74: 0 | S74: 0 | U74: 0 | V74: 0 | W74: 0 | Y74: 0 | AA74: 0 | AB74: 0 | AC74: 0 | AE74: 0 | AG74: 0 | AH74: 0 | AI74: 0 | AK74: 0 | AM74: 0 | AN74: 0 | AO74: 0 | AQ74: 0 | AS74: 0 | AT74: 0 | AU74: 0 | AW74: 0 | AY74: 0 | AZ74: 0 | BA74: 0 | BC74: 0 | BE74: 0 | BF74: 0 | BG74: 0 | BI74: 0 | BK74: 0 | BL74: 0 | BM74: 0 | BO74: 0 | BQ74: 0 | BR74: 0 | BS74: 0 | BU74: 0 | BW74: 0 | BX74: 0 | BY74: 0 | CA74: 0 | CC74: 0 | CD74: 0 | CE74: 0 | CG74: 0 | CI74: 0 | CJ74: 0 | CK74: 0 | CM74: 0 | CO74: 0 | CP74: 0 | CQ74: 0 | CS74: 0 | CU74: 0 | CV74: 0 | CW74: 0 | CY74: 0 | DA74: 0 | DB74: 0 | DC74: 0 | DE74: 0 | DG74: 0 | DH74: 0 | DI74: 0 | DK74: 0 | DM74: 0 | DN74: 0 | DO74: 0 | DQ74: 0 | DS74: 0 | DT74: 0 | DU74: 0 | DW74: 0 | DY74: 0 | DZ74: 0 | EA74: 0 | EC74: 0 | EE74: 0 | EF74: 0 | EG74: 0 | EI74: 0 | EK74: 0 | EL74: 0 | EM74: 0 | EO74: 0 | EQ74: 0 | ER74: 0 | ES74: 0 | EU74: 0 | EW74: 0 | EX74: 0 | EY74: 0 | FA74: 0 | FC74: 0 | FD74: 0 | FE74: 0 | FG74: 0 | FI74: 0 | FJ74: 0 | FK74: 0 | FM74: 0 | FO74: 0 | FP74: 0 | FQ74: 0 | FS74: 0 | FU74: 0 | FV74: 0 | FW74: 0 | FY74: 0 | GA74: 0 | GB74: 0 | GC74: 0 | GE74: 0 | GG74: 0 | GH74: 0 | GI74: 0 | GK74: 0 | GM74: 0 | GN74: 0 | GO74: 0 | GQ74: 0 | GS74: 0 | GT74: 0 | GU74: 0 | GW74: 0 | GY74: 0 | GZ74: 0
A75: 019.232-00 | B75: 2022/0036886-001 | C75: GE | D75: 2022/0036886 | E75: CZX8905 | F75: 01/04/2026 | G75: 30/04/2026 | H75: ELISABETE NASCIMENTO | I75: ELISABETE NASCIMENTO | J75: NORMAL | K75: CCA | L75: =CONTINUA!BV75 -> 0 | M75: =CONTINUA!BW75 -> 0 | O75: 6020.2022/0036886-3 | P75: 0 | Q75: 0 | S75: 0 | U75: 0 | V75: 0 | W75: 0 | Y75: 0 | AA75: 0 | AB75: 0 | AC75: 0 | AE75: 0 | AG75: 0 | AH75: 0 | AI75: 0 | AK75: 0 | AM75: 0 | AN75: 0 | AO75: 0 | AQ75: 0 | AS75: 0 | AT75: 0 | AU75: 0 | AW75: 0 | AY75: 0 | AZ75: 0 | BA75: 0 | BC75: 0 | BE75: 0 | BF75: 0 | BG75: 0 | BI75: 0 | BK75: 0 | BL75: 0 | BM75: 0 | BO75: 0 | BQ75: 0 | BR75: 0 | BS75: 0 | BU75: 0 | BW75: 0 | BX75: 0 | BY75: 0 | CA75: 0 | CC75: 0 | CD75: 0 | CE75: 0 | CG75: 0 | CI75: 0 | CJ75: 0 | CK75: 0 | CM75: 0 | CO75: 0 | CP75: 0 | CQ75: 0 | CS75: 0 | CU75: 0 | CV75: 0 | CW75: 0 | CY75: 0 | DA75: 0 | DB75: 0 | DC75: 0 | DE75: 0 | DG75: 0 | DH75: 0 | DI75: 0 | DK75: 0 | DM75: 0 | DN75: 0 | DO75: 0 | DQ75: 0 | DS75: 0 | DT75: 0 | DU75: 0 | DW75: 0 | DY75: 0 | DZ75: 0 | EA75: 0 | EC75: 0 | EE75: 0 | EF75: 0 | EG75: 0 | EI75: 0 | EK75: 0 | EL75: 0 | EM75: 0 | EO75: 0 | EQ75: 0 | ER75: 0 | ES75: 0 | EU75: 0 | EW75: 0 | EX75: 0 | EY75: 0 | FA75: 0 | FC75: 0 | FD75: 0 | FE75: 0 | FG75: 0 | FI75: 0 | FJ75: 0 | FK75: 0 | FM75: 0 | FO75: 0 | FP75: 0 | FQ75: 0 | FS75: 0 | FU75: 0 | FV75: 0 | FW75: 0 | FY75: 0 | GA75: 0 | GB75: 0 | GC75: 0 | GE75: 0 | GG75: 0 | GH75: 0 | GI75: 0 | GK75: 0 | GM75: 0 | GN75: 0 | GO75: 0 | GQ75: 0 | GS75: 0 | GT75: 0 | GU75: 0 | GW75: 0 | GY75: 0 | GZ75: 0
A76: 037.047-00 | B76: 2023/0026583-001 | C76: 1 | D76: 2023/0026583 | E76: DTD2868 | F76: 01/04/2026 | G76: 30/04/2026 | H76: ERIK BRASIL DE VASCONCELOS | I76: ERIK BRASIL DE VASCONCELOS | J76: NORMAL | K76: EMEI | L76: =CONTINUA!BV76 -> 0 | M76: =CONTINUA!BW76 -> 0 | O76: 6020.2023/0026583-7 | P76: 0 | Q76: 0 | S76: 0 | U76: 0 | V76: 0 | W76: 0 | Y76: 0 | AA76: 0 | AB76: 0 | AC76: 0 | AE76: 0 | AG76: 0 | AH76: 0 | AI76: 0 | AK76: 0 | AM76: 0 | AN76: 0 | AO76: 0 | AQ76: 0 | AS76: 0 | AT76: 0 | AU76: 0 | AW76: 0 | AY76: 0 | AZ76: 0 | BA76: 0 | BC76: 0 | BE76: 0 | BF76: 0 | BG76: 0 | BI76: 0 | BK76: 0 | BL76: 0 | BM76: 0 | BO76: 0 | BQ76: 0 | BR76: 0 | BS76: 0 | BU76: 0 | BW76: 0 | BX76: 0 | BY76: 0 | CA76: 0 | CC76: 0 | CD76: 0 | CE76: 0 | CG76: 0 | CI76: 0 | CJ76: 0 | CK76: 0 | CM76: 0 | CO76: 0 | CP76: 0 | CQ76: 0 | CS76: 0 | CU76: 0 | CV76: 0 | CW76: 0 | CY76: 0 | DA76: 0 | DB76: 0 | DC76: 0 | DE76: 0 | DG76: 0 | DH76: 0 | DI76: 0 | DK76: 0 | DM76: 0 | DN76: 0 | DO76: 0 | DQ76: 0 | DS76: 0 | DT76: 0 | DU76: 0 | DW76: 0 | DY76: 0 | DZ76: 0 | EA76: 0 | EC76: 0 | EE76: 0 | EF76: 0 | EG76: 0 | EI76: 0 | EK76: 0 | EL76: 0 | EM76: 0 | EO76: 0 | EQ76: 0 | ER76: 0 | ES76: 0 | EU76: 0 | EW76: 0 | EX76: 0 | EY76: 0 | FA76: 0 | FC76: 0 | FD76: 0 | FE76: 0 | FG76: 0 | FI76: 0 | FJ76: 0 | FK76: 0 | FM76: 0 | FO76: 0 | FP76: 0 | FQ76: 0 | FS76: 0 | FU76: 0 | FV76: 0 | FW76: 0 | FY76: 0 | GA76: 0 | GB76: 0 | GC76: 0 | GE76: 0 | GG76: 0 | GH76: 0 | GI76: 0 | GK76: 0 | GM76: 0 | GN76: 0 | GO76: 0 | GQ76: 0 | GS76: 0 | GT76: 0 | GU76: 0 | GW76: 0 | GY76: 0 | GZ76: 0
A77: 037.047-00 | B77: 2023/0026583-001 | C77: G | D77: 2023/0026583 | E77: DTD2868 | F77: 01/04/2026 | G77: 30/04/2026 | H77: ERIK BRASIL DE VASCONCELOS | I77: ERIK BRASIL DE VASCONCELOS | J77: NORMAL | K77: EMEF | L77: =CONTINUA!BV77 -> 32 | M77: =CONTINUA!BW77 -> 0 | O77: 6020.2023/0026583-7 | P77: 0 | Q77: 49 | S77: 11 | U77: 0 | V77: 0 | W77: 49 | Y77: 11 | AA77: 0 | AB77: 0 | AC77: 49 | AE77: 11 | AG77: 0 | AH77: 0 | AI77: 49 | AK77: 11 | AM77: 0 | AN77: 0 | AO77: 49 | AQ77: 11 | AS77: 0 | AT77: 0 | AU77: 49 | AW77: 11 | AY77: 0 | AZ77: 0 | BA77: 49 | BC77: 11 | BE77: 0 | BF77: 0 | BG77: 49 | BI77: 11 | BK77: 0 | BL77: 0 | BM77: 49 | BO77: 11 | BQ77: 0 | BR77: 0 | BS77: 49 | BU77: 11 | BW77: 0 | BX77: 0 | BY77: 49 | CA77: 11 | CC77: 0 | CD77: 0 | CE77: 49 | CG77: 11 | CI77: 0 | CJ77: 0 | CK77: 49 | CM77: 11 | CO77: 0 | CP77: 0 | CQ77: 49 | CS77: 11 | CU77: 0 | CV77: 0 | CW77: 49 | CY77: 11 | DA77: 0 | DB77: 0 | DC77: 49 | DE77: 11 | DG77: 0 | DH77: 0 | DI77: 49 | DK77: 11 | DM77: 0 | DN77: 0 | DO77: 49 | DQ77: 11 | DS77: 0 | DT77: 0 | DU77: 49 | DW77: 11 | DY77: 0 | DZ77: 0 | EA77: 49 | EC77: 11 | EE77: 0 | EF77: 0 | EG77: 49 | EI77: 11 | EK77: 0 | EL77: 0 | EM77: 49 | EO77: 11 | EQ77: 0 | ER77: 0 | ES77: 49 | EU77: 11 | EW77: 0 | EX77: 0 | EY77: 49 | FA77: 11 | FC77: 0 | FD77: 0 | FE77: 49 | FG77: 11 | FI77: 0 | FJ77: 0 | FK77: 49 | FM77: 11 | FO77: 0 | FP77: 0 | FQ77: 49 | FS77: 11 | FU77: 0 | FV77: 0 | FW77: 49 | FY77: 11 | GA77: 0 | GB77: 0 | GC77: 49 | GE77: 11 | GG77: 0 | GH77: 0 | GI77: 49 | GK77: 11 | GM77: 0 | GN77: 0 | GO77: 49 | GQ77: 11 | GS77: 0 | GT77: 0 | GU77: 49 | GW77: 11 | GY77: 0 | GZ77: 0
A78: 037.047-00 | B78: 2023/0026583-001 | C78: G | D78: 2023/0026583 | E78: DTD2868 | F78: 01/04/2026 | G78: 30/04/2026 | H78: ERIK BRASIL DE VASCONCELOS | I78: ERIK BRASIL DE VASCONCELOS | J78: NORMAL | K78: EMEE | L78: =CONTINUA!BV78 -> 0 | M78: =CONTINUA!BW78 -> 0 | O78: 6020.2023/0026583-7 | P78: 0 | Q78: 0 | S78: 0 | U78: 0 | V78: 0 | W78: 0 | Y78: 0 | AA78: 0 | AB78: 0 | AC78: 0 | AE78: 0 | AG78: 0 | AH78: 0 | AI78: 0 | AK78: 0 | AM78: 0 | AN78: 0 | AO78: 0 | AQ78: 0 | AS78: 0 | AT78: 0 | AU78: 0 | AW78: 0 | AY78: 0 | AZ78: 0 | BA78: 0 | BC78: 0 | BE78: 0 | BF78: 0 | BG78: 0 | BI78: 0 | BK78: 0 | BL78: 0 | BM78: 0 | BO78: 0 | BQ78: 0 | BR78: 0 | BS78: 0 | BU78: 0 | BW78: 0 | BX78: 0 | BY78: 0 | CA78: 0 | CC78: 0 | CD78: 0 | CE78: 0 | CG78: 0 | CI78: 0 | CJ78: 0 | CK78: 0 | CM78: 0 | CO78: 0 | CP78: 0 | CQ78: 0 | CS78: 0 | CU78: 0 | CV78: 0 | CW78: 0 | CY78: 0 | DA78: 0 | DB78: 0 | DC78: 0 | DE78: 0 | DG78: 0 | DH78: 0 | DI78: 0 | DK78: 0 | DM78: 0 | DN78: 0 | DO78: 0 | DQ78: 0 | DS78: 0 | DT78: 0 | DU78: 0 | DW78: 0 | DY78: 0 | DZ78: 0 | EA78: 0 | EC78: 0 | EE78: 0 | EF78: 0 | EG78: 0 | EI78: 0 | EK78: 0 | EL78: 0 | EM78: 0 | EO78: 0 | EQ78: 0 | ER78: 0 | ES78: 0 | EU78: 0 | EW78: 0 | EX78: 0 | EY78: 0 | FA78: 0 | FC78: 0 | FD78: 0 | FE78: 0 | FG78: 0 | FI78: 0 | FJ78: 0 | FK78: 0 | FM78: 0 | FO78: 0 | FP78: 0 | FQ78: 0 | FS78: 0 | FU78: 0 | FV78: 0 | FW78: 0 | FY78: 0 | GA78: 0 | GB78: 0 | GC78: 0 | GE78: 0 | GG78: 0 | GH78: 0 | GI78: 0 | GK78: 0 | GM78: 0 | GN78: 0 | GO78: 0 | GQ78: 0 | GS78: 0 | GT78: 0 | GU78: 0 | GW78: 0 | GY78: 0 | GZ78: 0
A79: 037.047-00 | B79: 2023/0026583-001 | C79: G | D79: 2023/0026583 | E79: DTD2868 | F79: 01/04/2026 | G79: 30/04/2026 | H79: ERIK BRASIL DE VASCONCELOS | I79: ERIK BRASIL DE VASCONCELOS | J79: NORMAL | K79: CEI | L79: =CONTINUA!BV79 -> 0 | M79: =CONTINUA!BW79 -> 0 | O79: 6020.2023/0026583-7 | P79: 0 | Q79: 0 | S79: 0 | U79: 0 | V79: 0 | W79: 0 | Y79: 0 | AA79: 0 | AB79: 0 | AC79: 0 | AE79: 0 | AG79: 0 | AH79: 0 | AI79: 0 | AK79: 0 | AM79: 0 | AN79: 0 | AO79: 0 | AQ79: 0 | AS79: 0 | AT79: 0 | AU79: 0 | AW79: 0 | AY79: 0 | AZ79: 0 | BA79: 0 | BC79: 0 | BE79: 0 | BF79: 0 | BG79: 0 | BI79: 0 | BK79: 0 | BL79: 0 | BM79: 0 | BO79: 0 | BQ79: 0 | BR79: 0 | BS79: 0 | BU79: 0 | BW79: 0 | BX79: 0 | BY79: 0 | CA79: 0 | CC79: 0 | CD79: 0 | CE79: 0 | CG79: 0 | CI79: 0 | CJ79: 0 | CK79: 0 | CM79: 0 | CO79: 0 | CP79: 0 | CQ79: 0 | CS79: 0 | CU79: 0 | CV79: 0 | CW79: 0 | CY79: 0 | DA79: 0 | DB79: 0 | DC79: 0 | DE79: 0 | DG79: 0 | DH79: 0 | DI79: 0 | DK79: 0 | DM79: 0 | DN79: 0 | DO79: 0 | DQ79: 0 | DS79: 0 | DT79: 0 | DU79: 0 | DW79: 0 | DY79: 0 | DZ79: 0 | EA79: 0 | EC79: 0 | EE79: 0 | EF79: 0 | EG79: 0 | EI79: 0 | EK79: 0 | EL79: 0 | EM79: 0 | EO79: 0 | EQ79: 0 | ER79: 0 | ES79: 0 | EU79: 0 | EW79: 0 | EX79: 0 | EY79: 0 | FA79: 0 | FC79: 0 | FD79: 0 | FE79: 0 | FG79: 0 | FI79: 0 | FJ79: 0 | FK79: 0 | FM79: 0 | FO79: 0 | FP79: 0 | FQ79: 0 | FS79: 0 | FU79: 0 | FV79: 0 | FW79: 0 | FY79: 0 | GA79: 0 | GB79: 0 | GC79: 0 | GE79: 0 | GG79: 0 | GH79: 0 | GI79: 0 | GK79: 0 | GM79: 0 | GN79: 0 | GO79: 0 | GQ79: 0 | GS79: 0 | GT79: 0 | GU79: 0 | GW79: 0 | GY79: 0 | GZ79: 0
A80: 037.047-00 | B80: 2023/0026583-001 | C80: G | D80: 2023/0026583 | E80: DTD2868 | F80: 01/04/2026 | G80: 30/04/2026 | H80: ERIK BRASIL DE VASCONCELOS | I80: ERIK BRASIL DE VASCONCELOS | J80: NORMAL | K80: CCA | L80: =CONTINUA!BV80 -> 0 | M80: =CONTINUA!BW80 -> 0 | O80: 6020.2023/0026583-7 | P80: 0 | Q80: 0 | S80: 0 | U80: 0 | V80: 0 | W80: 0 | Y80: 0 | AA80: 0 | AB80: 0 | AC80: 0 | AE80: 0 | AG80: 0 | AH80: 0 | AI80: 0 | AK80: 0 | AM80: 0 | AN80: 0 | AO80: 0 | AQ80: 0 | AS80: 0 | AT80: 0 | AU80: 0 | AW80: 0 | AY80: 0 | AZ80: 0 | BA80: 0 | BC80: 0 | BE80: 0 | BF80: 0 | BG80: 0 | BI80: 0 | BK80: 0 | BL80: 0 | BM80: 0 | BO80: 0 | BQ80: 0 | BR80: 0 | BS80: 0 | BU80: 0 | BW80: 0 | BX80: 0 | BY80: 0 | CA80: 0 | CC80: 0 | CD80: 0 | CE80: 0 | CG80: 0 | CI80: 0 | CJ80: 0 | CK80: 0 | CM80: 0 | CO80: 0 | CP80: 0 | CQ80: 0 | CS80: 0 | CU80: 0 | CV80: 0 | CW80: 0 | CY80: 0 | DA80: 0 | DB80: 0 | DC80: 0 | DE80: 0 | DG80: 0 | DH80: 0 | DI80: 0 | DK80: 0 | DM80: 0 | DN80: 0 | DO80: 0 | DQ80: 0 | DS80: 0 | DT80: 0 | DU80: 0 | DW80: 0 | DY80: 0 | DZ80: 0 | EA80: 0 | EC80: 0 | EE80: 0 | EF80: 0 | EG80: 0 | EI80: 0 | EK80: 0 | EL80: 0 | EM80: 0 | EO80: 0 | EQ80: 0 | ER80: 0 | ES80: 0 | EU80: 0 | EW80: 0 | EX80: 0 | EY80: 0 | FA80: 0 | FC80: 0 | FD80: 0 | FE80: 0 | FG80: 0 | FI80: 0 | FJ80: 0 | FK80: 0 | FM80: 0 | FO80: 0 | FP80: 0 | FQ80: 0 | FS80: 0 | FU80: 0 | FV80: 0 | FW80: 0 | FY80: 0 | GA80: 0 | GB80: 0 | GC80: 0 | GE80: 0 | GG80: 0 | GH80: 0 | GI80: 0 | GK80: 0 | GM80: 0 | GN80: 0 | GO80: 0 | GQ80: 0 | GS80: 0 | GT80: 0 | GU80: 0 | GW80: 0 | GY80: 0 | GZ80: 0
A81: 021.099-00 | B81: 2023/0025327-001 | C81: 1 | D81: 2023/0025327 | E81: DTB5538 | F81: 01/04/2026 | G81: 30/04/2026 | H81: GERALDO CONCEICAO DA SILVA | I81: GERALDO CONCEICAO DA SILVA | J81: NORMAL | K81: EMEI | L81: =CONTINUA!BV81 -> 0 | M81: =CONTINUA!BW81 -> 0 | O81: 6020.2023/0025327-8 | P81: 0 | Q81: 0 | S81: 0 | U81: 0 | V81: 0 | W81: 0 | Y81: 0 | AA81: 0 | AB81: 0 | AC81: 0 | AE81: 0 | AG81: 0 | AH81: 0 | AI81: 0 | AK81: 0 | AM81: 0 | AN81: 0 | AO81: 0 | AQ81: 0 | AS81: 0 | AT81: 0 | AU81: 0 | AW81: 0 | AY81: 0 | AZ81: 0 | BA81: 0 | BC81: 0 | BE81: 0 | BF81: 0 | BG81: 0 | BI81: 0 | BK81: 0 | BL81: 0 | BM81: 0 | BO81: 0 | BQ81: 0 | BR81: 0 | BS81: 0 | BU81: 0 | BW81: 0 | BX81: 0 | BY81: 0 | CA81: 0 | CC81: 0 | CD81: 0 | CE81: 0 | CG81: 0 | CI81: 0 | CJ81: 0 | CK81: 0 | CM81: 0 | CO81: 0 | CP81: 0 | CQ81: 0 | CS81: 0 | CU81: 0 | CV81: 0 | CW81: 0 | CY81: 0 | DA81: 0 | DB81: 0 | DC81: 0 | DE81: 0 | DG81: 0 | DH81: 0 | DI81: 0 | DK81: 0 | DM81: 0 | DN81: 0 | DO81: 0 | DQ81: 0 | DS81: 0 | DT81: 0 | DU81: 0 | DW81: 0 | DY81: 0 | DZ81: 0 | EA81: 0 | EC81: 0 | EE81: 0 | EF81: 0 | EG81: 0 | EI81: 0 | EK81: 0 | EL81: 0 | EM81: 0 | EO81: 0 | EQ81: 0 | ER81: 0 | ES81: 0 | EU81: 0 | EW81: 0 | EX81: 0 | EY81: 0 | FA81: 0 | FC81: 0 | FD81: 0 | FE81: 0 | FG81: 0 | FI81: 0 | FJ81: 0 | FK81: 0 | FM81: 0 | FO81: 0 | FP81: 0 | FQ81: 0 | FS81: 0 | FU81: 0 | FV81: 0 | FW81: 0 | FY81: 0 | GA81: 0 | GB81: 0 | GC81: 0 | GE81: 0 | GG81: 0 | GH81: 0 | GI81: 0 | GK81: 0 | GM81: 0 | GN81: 0 | GO81: 0 | GQ81: 0 | GS81: 0 | GT81: 0 | GU81: 0 | GW81: 0 | GY81: 0 | GZ81: 0
A82: 021.099-00 | B82: 2023/0025327-001 | C82: G | D82: 2023/0025327 | E82: DTB5538 | F82: 01/04/2026 | G82: 30/04/2026 | H82: GERALDO CONCEICAO DA SILVA | I82: GERALDO CONCEICAO DA SILVA | J82: NORMAL | K82: EMEF | L82: =CONTINUA!BV82 -> 0 | M82: =CONTINUA!BW82 -> 0 | O82: 6020.2023/0025327-8 | P82: 0 | Q82: 38 | S82: 8 | U82: 0 | V82: 0 | W82: 38 | Y82: 8 | AA82: 0 | AB82: 0 | AC82: 38 | AE82: 8 | AG82: 0 | AH82: 0 | AI82: 38 | AK82: 8 | AM82: 0 | AN82: 0 | AO82: 38 | AQ82: 8 | AS82: 0 | AT82: 0 | AU82: 38 | AW82: 8 | AY82: 0 | AZ82: 0 | BA82: 38 | BC82: 8 | BE82: 0 | BF82: 0 | BG82: 38 | BI82: 8 | BK82: 0 | BL82: 0 | BM82: 38 | BO82: 8 | BQ82: 0 | BR82: 0 | BS82: 38 | BU82: 8 | BW82: 0 | BX82: 0 | BY82: 38 | CA82: 8 | CC82: 0 | CD82: 0 | CE82: 38 | CG82: 8 | CI82: 0 | CJ82: 0 | CK82: 38 | CM82: 8 | CO82: 0 | CP82: 0 | CQ82: 38 | CS82: 8 | CU82: 0 | CV82: 0 | CW82: 38 | CY82: 8 | DA82: 0 | DB82: 0 | DC82: 38 | DE82: 8 | DG82: 0 | DH82: 0 | DI82: 38 | DK82: 8 | DM82: 0 | DN82: 0 | DO82: 38 | DQ82: 8 | DS82: 0 | DT82: 0 | DU82: 38 | DW82: 8 | DY82: 0 | DZ82: 0 | EA82: 38 | EC82: 8 | EE82: 0 | EF82: 0 | EG82: 38 | EI82: 8 | EK82: 0 | EL82: 0 | EM82: 38 | EO82: 8 | EQ82: 0 | ER82: 0 | ES82: 38 | EU82: 8 | EW82: 0 | EX82: 0 | EY82: 38 | FA82: 8 | FC82: 0 | FD82: 0 | FE82: 38 | FG82: 8 | FI82: 0 | FJ82: 0 | FK82: 38 | FM82: 8 | FO82: 0 | FP82: 0 | FQ82: 38 | FS82: 8 | FU82: 0 | FV82: 0 | FW82: 38 | FY82: 8 | GA82: 0 | GB82: 0 | GC82: 38 | GE82: 8 | GG82: 0 | GH82: 0 | GI82: 38 | GK82: 8 | GM82: 0 | GN82: 0 | GO82: 38 | GQ82: 8 | GS82: 0 | GT82: 0 | GU82: 38 | GW82: 8 | GY82: 0 | GZ82: 0
A83: 021.099-00 | B83: 2023/0025327-001 | C83: G | D83: 2023/0025327 | E83: DTB5538 | F83: 01/04/2026 | G83: 30/04/2026 | H83: GERALDO CONCEICAO DA SILVA | I83: GERALDO CONCEICAO DA SILVA | J83: NORMAL | K83: EMEE | L83: =CONTINUA!BV83 -> 0 | M83: =CONTINUA!BW83 -> 0 | O83: 6020.2023/0025327-8 | P83: 0 | Q83: 0 | S83: 0 | U83: 0 | V83: 0 | W83: 0 | Y83: 0 | AA83: 0 | AB83: 0 | AC83: 0 | AE83: 0 | AG83: 0 | AH83: 0 | AI83: 0 | AK83: 0 | AM83: 0 | AN83: 0 | AO83: 0 | AQ83: 0 | AS83: 0 | AT83: 0 | AU83: 0 | AW83: 0 | AY83: 0 | AZ83: 0 | BA83: 0 | BC83: 0 | BE83: 0 | BF83: 0 | BG83: 0 | BI83: 0 | BK83: 0 | BL83: 0 | BM83: 0 | BO83: 0 | BQ83: 0 | BR83: 0 | BS83: 0 | BU83: 0 | BW83: 0 | BX83: 0 | BY83: 0 | CA83: 0 | CC83: 0 | CD83: 0 | CE83: 0 | CG83: 0 | CI83: 0 | CJ83: 0 | CK83: 0 | CM83: 0 | CO83: 0 | CP83: 0 | CQ83: 0 | CS83: 0 | CU83: 0 | CV83: 0 | CW83: 0 | CY83: 0 | DA83: 0 | DB83: 0 | DC83: 0 | DE83: 0 | DG83: 0 | DH83: 0 | DI83: 0 | DK83: 0 | DM83: 0 | DN83: 0 | DO83: 0 | DQ83: 0 | DS83: 0 | DT83: 0 | DU83: 0 | DW83: 0 | DY83: 0 | DZ83: 0 | EA83: 0 | EC83: 0 | EE83: 0 | EF83: 0 | EG83: 0 | EI83: 0 | EK83: 0 | EL83: 0 | EM83: 0 | EO83: 0 | EQ83: 0 | ER83: 0 | ES83: 0 | EU83: 0 | EW83: 0 | EX83: 0 | EY83: 0 | FA83: 0 | FC83: 0 | FD83: 0 | FE83: 0 | FG83: 0 | FI83: 0 | FJ83: 0 | FK83: 0 | FM83: 0 | FO83: 0 | FP83: 0 | FQ83: 0 | FS83: 0 | FU83: 0 | FV83: 0 | FW83: 0 | FY83: 0 | GA83: 0 | GB83: 0 | GC83: 0 | GE83: 0 | GG83: 0 | GH83: 0 | GI83: 0 | GK83: 0 | GM83: 0 | GN83: 0 | GO83: 0 | GQ83: 0 | GS83: 0 | GT83: 0 | GU83: 0 | GW83: 0 | GY83: 0 | GZ83: 0
A84: 021.099-00 | B84: 2023/0025327-001 | C84: G | D84: 2023/0025327 | E84: DTB5538 | F84: 01/04/2026 | G84: 30/04/2026 | H84: GERALDO CONCEICAO DA SILVA | I84: GERALDO CONCEICAO DA SILVA | J84: NORMAL | K84: CEI | L84: =CONTINUA!BV84 -> 0 | M84: =CONTINUA!BW84 -> 0 | O84: 6020.2023/0025327-8 | P84: 0 | Q84: 0 | S84: 0 | U84: 0 | V84: 0 | W84: 0 | Y84: 0 | AA84: 0 | AB84: 0 | AC84: 0 | AE84: 0 | AG84: 0 | AH84: 0 | AI84: 0 | AK84: 0 | AM84: 0 | AN84: 0 | AO84: 0 | AQ84: 0 | AS84: 0 | AT84: 0 | AU84: 0 | AW84: 0 | AY84: 0 | AZ84: 0 | BA84: 0 | BC84: 0 | BE84: 0 | BF84: 0 | BG84: 0 | BI84: 0 | BK84: 0 | BL84: 0 | BM84: 0 | BO84: 0 | BQ84: 0 | BR84: 0 | BS84: 0 | BU84: 0 | BW84: 0 | BX84: 0 | BY84: 0 | CA84: 0 | CC84: 0 | CD84: 0 | CE84: 0 | CG84: 0 | CI84: 0 | CJ84: 0 | CK84: 0 | CM84: 0 | CO84: 0 | CP84: 0 | CQ84: 0 | CS84: 0 | CU84: 0 | CV84: 0 | CW84: 0 | CY84: 0 | DA84: 0 | DB84: 0 | DC84: 0 | DE84: 0 | DG84: 0 | DH84: 0 | DI84: 0 | DK84: 0 | DM84: 0 | DN84: 0 | DO84: 0 | DQ84: 0 | DS84: 0 | DT84: 0 | DU84: 0 | DW84: 0 | DY84: 0 | DZ84: 0 | EA84: 0 | EC84: 0 | EE84: 0 | EF84: 0 | EG84: 0 | EI84: 0 | EK84: 0 | EL84: 0 | EM84: 0 | EO84: 0 | EQ84: 0 | ER84: 0 | ES84: 0 | EU84: 0 | EW84: 0 | EX84: 0 | EY84: 0 | FA84: 0 | FC84: 0 | FD84: 0 | FE84: 0 | FG84: 0 | FI84: 0 | FJ84: 0 | FK84: 0 | FM84: 0 | FO84: 0 | FP84: 0 | FQ84: 0 | FS84: 0 | FU84: 0 | FV84: 0 | FW84: 0 | FY84: 0 | GA84: 0 | GB84: 0 | GC84: 0 | GE84: 0 | GG84: 0 | GH84: 0 | GI84: 0 | GK84: 0 | GM84: 0 | GN84: 0 | GO84: 0 | GQ84: 0 | GS84: 0 | GT84: 0 | GU84: 0 | GW84: 0 | GY84: 0 | GZ84: 0
A85: 021.099-00 | B85: 2023/0025327-001 | C85: G | D85: 2023/0025327 | E85: DTB5538 | F85: 01/04/2026 | G85: 30/04/2026 | H85: GERALDO CONCEICAO DA SILVA | I85: GERALDO CONCEICAO DA SILVA | J85: NORMAL | K85: CCA | L85: =CONTINUA!BV85 -> 0 | M85: =CONTINUA!BW85 -> 0 | O85: 6020.2023/0025327-8 | P85: 0 | Q85: 0 | S85: 0 | U85: 0 | V85: 0 | W85: 0 | Y85: 0 | AA85: 0 | AB85: 0 | AC85: 0 | AE85: 0 | AG85: 0 | AH85: 0 | AI85: 0 | AK85: 0 | AM85: 0 | AN85: 0 | AO85: 0 | AQ85: 0 | AS85: 0 | AT85: 0 | AU85: 0 | AW85: 0 | AY85: 0 | AZ85: 0 | BA85: 0 | BC85: 0 | BE85: 0 | BF85: 0 | BG85: 0 | BI85: 0 | BK85: 0 | BL85: 0 | BM85: 0 | BO85: 0 | BQ85: 0 | BR85: 0 | BS85: 0 | BU85: 0 | BW85: 0 | BX85: 0 | BY85: 0 | CA85: 0 | CC85: 0 | CD85: 0 | CE85: 0 | CG85: 0 | CI85: 0 | CJ85: 0 | CK85: 0 | CM85: 0 | CO85: 0 | CP85: 0 | CQ85: 0 | CS85: 0 | CU85: 0 | CV85: 0 | CW85: 0 | CY85: 0 | DA85: 0 | DB85: 0 | DC85: 0 | DE85: 0 | DG85: 0 | DH85: 0 | DI85: 0 | DK85: 0 | DM85: 0 | DN85: 0 | DO85: 0 | DQ85: 0 | DS85: 0 | DT85: 0 | DU85: 0 | DW85: 0 | DY85: 0 | DZ85: 0 | EA85: 0 | EC85: 0 | EE85: 0 | EF85: 0 | EG85: 0 | EI85: 0 | EK85: 0 | EL85: 0 | EM85: 0 | EO85: 0 | EQ85: 0 | ER85: 0 | ES85: 0 | EU85: 0 | EW85: 0 | EX85: 0 | EY85: 0 | FA85: 0 | FC85: 0 | FD85: 0 | FE85: 0 | FG85: 0 | FI85: 0 | FJ85: 0 | FK85: 0 | FM85: 0 | FO85: 0 | FP85: 0 | FQ85: 0 | FS85: 0 | FU85: 0 | FV85: 0 | FW85: 0 | FY85: 0 | GA85: 0 | GB85: 0 | GC85: 0 | GE85: 0 | GG85: 0 | GH85: 0 | GI85: 0 | GK85: 0 | GM85: 0 | GN85: 0 | GO85: 0 | GQ85: 0 | GS85: 0 | GT85: 0 | GU85: 0 | GW85: 0 | GY85: 0 | GZ85: 0
A86: 031.735-00 | B86: 2022/0031049-001 | C86: 2 | D86: 2022/0031049 | E86: DTD9110 | F86: 01/04/2026 | G86: 30/04/2026 | H86: GETRAN SANTOS | I86: GETRAN SANTOS | J86: ADAPTADO | K86: EMEI | L86: =CONTINUA!BV86 -> 0 | M86: =CONTINUA!BW86 -> 0 | O86: 6020.2022/0031049-0 | P86: 0 | Q86: 2 | R86: 0 | S86: 0 | T86: 0 | U86: 0 | V86: 0 | W86: 2 | X86: 0 | Y86: 0 | Z86: 0 | AA86: 0 | AB86: 0 | AC86: 2 | AD86: 0 | AE86: 0 | AF86: 0 | AG86: 0 | AH86: 0 | AI86: 2 | AJ86: 0 | AK86: 0 | AL86: 0 | AM86: 0 | AN86: 0 | AO86: 2 | AP86: 0 | AQ86: 0 | AR86: 0 | AS86: 0 | AT86: 0 | AU86: 2 | AV86: 0 | AW86: 0 | AX86: 0 | AY86: 0 | AZ86: 0 | BA86: 2 | BB86: 0 | BC86: 0 | BD86: 0 | BE86: 0 | BF86: 0 | BG86: 2 | BH86: 0 | BI86: 0 | BJ86: 0 | BK86: 0 | BL86: 0 | BM86: 2 | BN86: 0 | BO86: 0 | BP86: 0 | BQ86: 0 | BR86: 0 | BS86: 2 | BT86: 0 | BU86: 0 | BV86: 0 | BW86: 0 | BX86: 0 | BY86: 2 | BZ86: 0 | CA86: 0 | CB86: 0 | CC86: 0 | CD86: 0 | CE86: 2 | CF86: 0 | CG86: 0 | CH86: 0 | CI86: 0 | CJ86: 0 | CK86: 2 | CL86: 0 | CM86: 0 | CN86: 0 | CO86: 0 | CP86: 0 | CQ86: 2 | CR86: 0 | CS86: 0 | CT86: 0 | CU86: 0 | CV86: 0 | CW86: 2 | CX86: 0 | CY86: 0 | CZ86: 0 | DA86: 0 | DB86: 0 | DC86: 2 | DD86: 0 | DE86: 0 | DF86: 0 | DG86: 0 | DH86: 0 | DI86: 2 | DJ86: 0 | DK86: 0 | DL86: 0 | DM86: 0 | DN86: 0 | DO86: 2 | DP86: 0 | DQ86: 0 | DR86: 0 | DS86: 0 | DT86: 0 | DU86: 2 | DV86: 0 | DW86: 0 | DX86: 0 | DY86: 0 | DZ86: 0 | EA86: 2 | EB86: 0 | EC86: 0 | ED86: 0 | EE86: 0 | EF86: 0 | EG86: 2 | EH86: 0 | EI86: 0 | EJ86: 0 | EK86: 0 | EL86: 0 | EM86: 2 | EN86: 0 | EO86: 0 | EP86: 0 | EQ86: 0 | ER86: 0 | ES86: 2 | ET86: 0 | EU86: 0 | EV86: 0 | EW86: 0 | EX86: 0 | EY86: 2 | EZ86: 0 | FA86: 0 | FB86: 0 | FC86: 0 | FD86: 0 | FE86: 2 | FF86: 0 | FG86: 0 | FH86: 0 | FI86: 0 | FJ86: 0 | FK86: 2 | FL86: 0 | FM86: 0 | FN86: 0 | FO86: 0 | FP86: 0 | FQ86: 2 | FR86: 0 | FS86: 0 | FT86: 0 | FU86: 0 | FV86: 0 | FW86: 2 | FX86: 0 | FY86: 0 | FZ86: 0 | GA86: 0 | GB86: 0 | GC86: 2 | GD86: 0 | GE86: 0 | GF86: 0 | GG86: 0 | GH86: 0 | GI86: 2 | GJ86: 0 | GK86: 0 | GL86: 0 | GM86: 0 | GN86: 0 | GO86: 2 | GP86: 0 | GQ86: 0 | GR86: 0 | GS86: 0 | GT86: 0 | GU86: 2 | GV86: 0 | GW86: 0 | GX86: 0 | GY86: 0 | GZ86: 0
A87: 031.735-00 | B87: 2022/0031049-001 | C87: G | D87: 2022/0031049 | E87: DTD9110 | F87: 01/04/2026 | G87: 30/04/2026 | H87: GETRAN SANTOS | I87: GETRAN SANTOS | J87: ADAPTADO | K87: EMEF | L87: =CONTINUA!BV87 -> 8 | M87: =CONTINUA!BW87 -> 0 | O87: 6020.2022/0031049-0 | P87: 0 | Q87: 13 | R87: 3 | S87: 2 | T87: 1 | U87: 0 | V87: 0 | W87: 13 | X87: 3 | Y87: 2 | Z87: 1 | AA87: 0 | AB87: 0 | AC87: 13 | AD87: 3 | AE87: 2 | AF87: 1 | AG87: 0 | AH87: 0 | AI87: 13 | AJ87: 3 | AK87: 2 | AL87: 1 | AM87: 0 | AN87: 0 | AO87: 13 | AP87: 3 | AQ87: 2 | AR87: 1 | AS87: 0 | AT87: 0 | AU87: 13 | AV87: 3 | AW87: 2 | AX87: 1 | AY87: 0 | AZ87: 0 | BA87: 13 | BB87: 3 | BC87: 2 | BD87: 1 | BE87: 0 | BF87: 0 | BG87: 13 | BH87: 3 | BI87: 2 | BJ87: 1 | BK87: 0 | BL87: 0 | BM87: 13 | BN87: 3 | BO87: 2 | BP87: 1 | BQ87: 0 | BR87: 0 | BS87: 13 | BT87: 3 | BU87: 2 | BV87: 1 | BW87: 0 | BX87: 0 | BY87: 13 | BZ87: 3 | CA87: 2 | CB87: 1 | CC87: 0 | CD87: 0 | CE87: 13 | CF87: 3 | CG87: 2 | CH87: 1 | CI87: 0 | CJ87: 0 | CK87: 13 | CL87: 3 | CM87: 2 | CN87: 1 | CO87: 0 | CP87: 0 | CQ87: 13 | CR87: 3 | CS87: 2 | CT87: 1 | CU87: 0 | CV87: 0 | CW87: 13 | CX87: 3 | CY87: 2 | CZ87: 1 | DA87: 0 | DB87: 0 | DC87: 13 | DD87: 3 | DE87: 2 | DF87: 1 | DG87: 0 | DH87: 0 | DI87: 13 | DJ87: 3 | DK87: 2 | DL87: 1 | DM87: 0 | DN87: 0 | DO87: 13 | DP87: 3 | DQ87: 2 | DR87: 1 | DS87: 0 | DT87: 0 | DU87: 13 | DV87: 3 | DW87: 2 | DX87: 1 | DY87: 0 | DZ87: 0 | EA87: 13 | EB87: 3 | EC87: 2 | ED87: 1 | EE87: 0 | EF87: 0 | EG87: 13 | EH87: 3 | EI87: 2 | EJ87: 1 | EK87: 0 | EL87: 0 | EM87: 13 | EN87: 3 | EO87: 2 | EP87: 1 | EQ87: 0 | ER87: 0 | ES87: 13 | ET87: 3 | EU87: 2 | EV87: 1 | EW87: 0 | EX87: 0 | EY87: 13 | EZ87: 3 | FA87: 2 | FB87: 1 | FC87: 0 | FD87: 0 | FE87: 13 | FF87: 3 | FG87: 2 | FH87: 1 | FI87: 0 | FJ87: 0 | FK87: 13 | FL87: 3 | FM87: 2 | FN87: 1 | FO87: 0 | FP87: 0 | FQ87: 13 | FR87: 3 | FS87: 2 | FT87: 1 | FU87: 0 | FV87: 0 | FW87: 13 | FX87: 3 | FY87: 2 | FZ87: 1 | GA87: 0 | GB87: 0 | GC87: 13 | GD87: 3 | GE87: 2 | GF87: 1 | GG87: 0 | GH87: 0 | GI87: 13 | GJ87: 3 | GK87: 2 | GL87: 1 | GM87: 0 | GN87: 0 | GO87: 13 | GP87: 3 | GQ87: 2 | GR87: 1 | GS87: 0 | GT87: 0 | GU87: 13 | GV87: 3 | GW87: 2 | GX87: 1 | GY87: 0 | GZ87: 0
A88: 031.735-00 | B88: 2022/0031049-001 | C88: G | D88: 2022/0031049 | E88: DTD9110 | F88: 01/04/2026 | G88: 30/04/2026 | H88: GETRAN SANTOS | I88: GETRAN SANTOS | J88: ADAPTADO | K88: EMEE | L88: =CONTINUA!BV88 -> 0 | M88: =CONTINUA!BW88 -> 0 | O88: 6020.2022/0031049-0 | P88: 0 | Q88: 0 | R88: 0 | S88: 0 | T88: 0 | U88: 0 | V88: 0 | W88: 0 | X88: 0 | Y88: 0 | Z88: 0 | AA88: 0 | AB88: 0 | AC88: 0 | AD88: 0 | AE88: 0 | AF88: 0 | AG88: 0 | AH88: 0 | AI88: 0 | AJ88: 0 | AK88: 0 | AL88: 0 | AM88: 0 | AN88: 0 | AO88: 0 | AP88: 0 | AQ88: 0 | AR88: 0 | AS88: 0 | AT88: 0 | AU88: 0 | AV88: 0 | AW88: 0 | AX88: 0 | AY88: 0 | AZ88: 0 | BA88: 0 | BB88: 0 | BC88: 0 | BD88: 0 | BE88: 0 | BF88: 0 | BG88: 0 | BH88: 0 | BI88: 0 | BJ88: 0 | BK88: 0 | BL88: 0 | BM88: 0 | BN88: 0 | BO88: 0 | BP88: 0 | BQ88: 0 | BR88: 0 | BS88: 0 | BT88: 0 | BU88: 0 | BV88: 0 | BW88: 0 | BX88: 0 | BY88: 0 | BZ88: 0 | CA88: 0 | CB88: 0 | CC88: 0 | CD88: 0 | CE88: 0 | CF88: 0 | CG88: 0 | CH88: 0 | CI88: 0 | CJ88: 0 | CK88: 0 | CL88: 0 | CM88: 0 | CN88: 0 | CO88: 0 | CP88: 0 | CQ88: 0 | CR88: 0 | CS88: 0 | CT88: 0 | CU88: 0 | CV88: 0 | CW88: 0 | CX88: 0 | CY88: 0 | CZ88: 0 | DA88: 0 | DB88: 0 | DC88: 0 | DD88: 0 | DE88: 0 | DF88: 0 | DG88: 0 | DH88: 0 | DI88: 0 | DJ88: 0 | DK88: 0 | DL88: 0 | DM88: 0 | DN88: 0 | DO88: 0 | DP88: 0 | DQ88: 0 | DR88: 0 | DS88: 0 | DT88: 0 | DU88: 0 | DV88: 0 | DW88: 0 | DX88: 0 | DY88: 0 | DZ88: 0 | EA88: 0 | EB88: 0 | EC88: 0 | ED88: 0 | EE88: 0 | EF88: 0 | EG88: 0 | EH88: 0 | EI88: 0 | EJ88: 0 | EK88: 0 | EL88: 0 | EM88: 0 | EN88: 0 | EO88: 0 | EP88: 0 | EQ88: 0 | ER88: 0 | ES88: 0 | ET88: 0 | EU88: 0 | EV88: 0 | EW88: 0 | EX88: 0 | EY88: 0 | EZ88: 0 | FA88: 0 | FB88: 0 | FC88: 0 | FD88: 0 | FE88: 0 | FF88: 0 | FG88: 0 | FH88: 0 | FI88: 0 | FJ88: 0 | FK88: 0 | FL88: 0 | FM88: 0 | FN88: 0 | FO88: 0 | FP88: 0 | FQ88: 0 | FR88: 0 | FS88: 0 | FT88: 0 | FU88: 0 | FV88: 0 | FW88: 0 | FX88: 0 | FY88: 0 | FZ88: 0 | GA88: 0 | GB88: 0 | GC88: 0 | GD88: 0 | GE88: 0 | GF88: 0 | GG88: 0 | GH88: 0 | GI88: 0 | GJ88: 0 | GK88: 0 | GL88: 0 | GM88: 0 | GN88: 0 | GO88: 0 | GP88: 0 | GQ88: 0 | GR88: 0 | GS88: 0 | GT88: 0 | GU88: 0 | GV88: 0 | GW88: 0 | GX88: 0 | GY88: 0 | GZ88: 0
A89: 031.735-00 | B89: 2022/0031049-001 | C89: G | D89: 2022/0031049 | E89: DTD9110 | F89: 01/04/2026 | G89: 30/04/2026 | H89: GETRAN SANTOS | I89: GETRAN SANTOS | J89: ADAPTADO | K89: CEI | L89: =CONTINUA!BV89 -> 0 | M89: =CONTINUA!BW89 -> 0 | O89: 6020.2022/0031049-0 | P89: 0 | Q89: 0 | R89: 0 | S89: 0 | T89: 0 | U89: 0 | V89: 0 | W89: 0 | X89: 0 | Y89: 0 | Z89: 0 | AA89: 0 | AB89: 0 | AC89: 0 | AD89: 0 | AE89: 0 | AF89: 0 | AG89: 0 | AH89: 0 | AI89: 0 | AJ89: 0 | AK89: 0 | AL89: 0 | AM89: 0 | AN89: 0 | AO89: 0 | AP89: 0 | AQ89: 0 | AR89: 0 | AS89: 0 | AT89: 0 | AU89: 0 | AV89: 0 | AW89: 0 | AX89: 0 | AY89: 0 | AZ89: 0 | BA89: 0 | BB89: 0 | BC89: 0 | BD89: 0 | BE89: 0 | BF89: 0 | BG89: 0 | BH89: 0 | BI89: 0 | BJ89: 0 | BK89: 0 | BL89: 0 | BM89: 0 | BN89: 0 | BO89: 0 | BP89: 0 | BQ89: 0 | BR89: 0 | BS89: 0 | BT89: 0 | BU89: 0 | BV89: 0 | BW89: 0 | BX89: 0 | BY89: 0 | BZ89: 0 | CA89: 0 | CB89: 0 | CC89: 0 | CD89: 0 | CE89: 0 | CF89: 0 | CG89: 0 | CH89: 0 | CI89: 0 | CJ89: 0 | CK89: 0 | CL89: 0 | CM89: 0 | CN89: 0 | CO89: 0 | CP89: 0 | CQ89: 0 | CR89: 0 | CS89: 0 | CT89: 0 | CU89: 0 | CV89: 0 | CW89: 0 | CX89: 0 | CY89: 0 | CZ89: 0 | DA89: 0 | DB89: 0 | DC89: 0 | DD89: 0 | DE89: 0 | DF89: 0 | DG89: 0 | DH89: 0 | DI89: 0 | DJ89: 0 | DK89: 0 | DL89: 0 | DM89: 0 | DN89: 0 | DO89: 0 | DP89: 0 | DQ89: 0 | DR89: 0 | DS89: 0 | DT89: 0 | DU89: 0 | DV89: 0 | DW89: 0 | DX89: 0 | DY89: 0 | DZ89: 0 | EA89: 0 | EB89: 0 | EC89: 0 | ED89: 0 | EE89: 0 | EF89: 0 | EG89: 0 | EH89: 0 | EI89: 0 | EJ89: 0 | EK89: 0 | EL89: 0 | EM89: 0 | EN89: 0 | EO89: 0 | EP89: 0 | EQ89: 0 | ER89: 0 | ES89: 0 | ET89: 0 | EU89: 0 | EV89: 0 | EW89: 0 | EX89: 0 | EY89: 0 | EZ89: 0 | FA89: 0 | FB89: 0 | FC89: 0 | FD89: 0 | FE89: 0 | FF89: 0 | FG89: 0 | FH89: 0 | FI89: 0 | FJ89: 0 | FK89: 0 | FL89: 0 | FM89: 0 | FN89: 0 | FO89: 0 | FP89: 0 | FQ89: 0 | FR89: 0 | FS89: 0 | FT89: 0 | FU89: 0 | FV89: 0 | FW89: 0 | FX89: 0 | FY89: 0 | FZ89: 0 | GA89: 0 | GB89: 0 | GC89: 0 | GD89: 0 | GE89: 0 | GF89: 0 | GG89: 0 | GH89: 0 | GI89: 0 | GJ89: 0 | GK89: 0 | GL89: 0 | GM89: 0 | GN89: 0 | GO89: 0 | GP89: 0 | GQ89: 0 | GR89: 0 | GS89: 0 | GT89: 0 | GU89: 0 | GV89: 0 | GW89: 0 | GX89: 0 | GY89: 0 | GZ89: 0
A90: 031.735-00 | B90: 2022/0031049-001 | C90: G | D90: 2022/0031049 | E90: DTD9110 | F90: 01/04/2026 | G90: 30/04/2026 | H90: GETRAN SANTOS | I90: GETRAN SANTOS | J90: ADAPTADO | K90: CCA | L90: =CONTINUA!BV90 -> 0 | M90: =CONTINUA!BW90 -> 0 | O90: 6020.2022/0031049-0 | P90: 0 | Q90: 0 | R90: 0 | S90: 0 | T90: 0 | U90: 0 | V90: 0 | W90: 0 | X90: 0 | Y90: 0 | Z90: 0 | AA90: 0 | AB90: 0 | AC90: 0 | AD90: 0 | AE90: 0 | AF90: 0 | AG90: 0 | AH90: 0 | AI90: 0 | AJ90: 0 | AK90: 0 | AL90: 0 | AM90: 0 | AN90: 0 | AO90: 0 | AP90: 0 | AQ90: 0 | AR90: 0 | AS90: 0 | AT90: 0 | AU90: 0 | AV90: 0 | AW90: 0 | AX90: 0 | AY90: 0 | AZ90: 0 | BA90: 0 | BB90: 0 | BC90: 0 | BD90: 0 | BE90: 0 | BF90: 0 | BG90: 0 | BH90: 0 | BI90: 0 | BJ90: 0 | BK90: 0 | BL90: 0 | BM90: 0 | BN90: 0 | BO90: 0 | BP90: 0 | BQ90: 0 | BR90: 0 | BS90: 0 | BT90: 0 | BU90: 0 | BV90: 0 | BW90: 0 | BX90: 0 | BY90: 0 | BZ90: 0 | CA90: 0 | CB90: 0 | CC90: 0 | CD90: 0 | CE90: 0 | CF90: 0 | CG90: 0 | CH90: 0 | CI90: 0 | CJ90: 0 | CK90: 0 | CL90: 0 | CM90: 0 | CN90: 0 | CO90: 0 | CP90: 0 | CQ90: 0 | CR90: 0 | CS90: 0 | CT90: 0 | CU90: 0 | CV90: 0 | CW90: 0 | CX90: 0 | CY90: 0 | CZ90: 0 | DA90: 0 | DB90: 0 | DC90: 0 | DD90: 0 | DE90: 0 | DF90: 0 | DG90: 0 | DH90: 0 | DI90: 0 | DJ90: 0 | DK90: 0 | DL90: 0 | DM90: 0 | DN90: 0 | DO90: 0 | DP90: 0 | DQ90: 0 | DR90: 0 | DS90: 0 | DT90: 0 | DU90: 0 | DV90: 0 | DW90: 0 | DX90: 0 | DY90: 0 | DZ90: 0 | EA90: 0 | EB90: 0 | EC90: 0 | ED90: 0 | EE90: 0 | EF90: 0 | EG90: 0 | EH90: 0 | EI90: 0 | EJ90: 0 | EK90: 0 | EL90: 0 | EM90: 0 | EN90: 0 | EO90: 0 | EP90: 0 | EQ90: 0 | ER90: 0 | ES90: 0 | ET90: 0 | EU90: 0 | EV90: 0 | EW90: 0 | EX90: 0 | EY90: 0 | EZ90: 0 | FA90: 0 | FB90: 0 | FC90: 0 | FD90: 0 | FE90: 0 | FF90: 0 | FG90: 0 | FH90: 0 | FI90: 0 | FJ90: 0 | FK90: 0 | FL90: 0 | FM90: 0 | FN90: 0 | FO90: 0 | FP90: 0 | FQ90: 0 | FR90: 0 | FS90: 0 | FT90: 0 | FU90: 0 | FV90: 0 | FW90: 0 | FX90: 0 | FY90: 0 | FZ90: 0 | GA90: 0 | GB90: 0 | GC90: 0 | GD90: 0 | GE90: 0 | GF90: 0 | GG90: 0 | GH90: 0 | GI90: 0 | GJ90: 0 | GK90: 0 | GL90: 0 | GM90: 0 | GN90: 0 | GO90: 0 | GP90: 0 | GQ90: 0 | GR90: 0 | GS90: 0 | GT90: 0 | GU90: 0 | GV90: 0 | GW90: 0 | GX90: 0 | GY90: 0 | GZ90: 0
A91: 017.928-00 | B91: 2023/0026599-001 | C91: 1 | D91: 2023/0026599 | E91: DZX5134 | F91: 01/04/2026 | G91: 30/04/2026 | H91: GILMAR RIBEIRO LEAL | I91: GILMAR RIBEIRO LEAL | J91: NORMAL | K91: EMEI | L91: =CONTINUA!BV91 -> 0 | M91: =CONTINUA!BW91 -> 0 | O91: 6020.2023/0026599-3 | P91: 0 | Q91: 45 | S91: 0 | U91: 0 | V91: 0 | W91: 45 | Y91: 0 | AA91: 0 | AB91: 0 | AC91: 45 | AE91: 0 | AG91: 0 | AH91: 0 | AI91: 45 | AK91: 0 | AM91: 0 | AN91: 0 | AO91: 45 | AQ91: 0 | AS91: 0 | AT91: 0 | AU91: 45 | AW91: 0 | AY91: 0 | AZ91: 0 | BA91: 45 | BC91: 0 | BE91: 0 | BF91: 0 | BG91: 45 | BI91: 0 | BK91: 0 | BL91: 0 | BM91: 45 | BO91: 0 | BQ91: 0 | BR91: 0 | BS91: 45 | BU91: 0 | BW91: 0 | BX91: 0 | BY91: 45 | CA91: 0 | CC91: 0 | CD91: 0 | CE91: 45 | CG91: 0 | CI91: 0 | CJ91: 0 | CK91: 45 | CM91: 0 | CO91: 0 | CP91: 0 | CQ91: 45 | CS91: 0 | CU91: 0 | CV91: 0 | CW91: 45 | CY91: 0 | DA91: 0 | DB91: 0 | DC91: 45 | DE91: 0 | DG91: 0 | DH91: 0 | DI91: 45 | DK91: 0 | DM91: 0 | DN91: 0 | DO91: 45 | DQ91: 0 | DS91: 0 | DT91: 0 | DU91: 45 | DW91: 0 | DY91: 0 | DZ91: 0 | EA91: 45 | EC91: 0 | EE91: 0 | EF91: 0 | EG91: 45 | EI91: 0 | EK91: 0 | EL91: 0 | EM91: 45 | EO91: 0 | EQ91: 0 | ER91: 0 | ES91: 45 | EU91: 0 | EW91: 0 | EX91: 0 | EY91: 45 | FA91: 0 | FC91: 0 | FD91: 0 | FE91: 45 | FG91: 0 | FI91: 0 | FJ91: 0 | FK91: 45 | FM91: 0 | FO91: 0 | FP91: 0 | FQ91: 45 | FS91: 0 | FU91: 0 | FV91: 0 | FW91: 45 | FY91: 0 | GA91: 0 | GB91: 0 | GC91: 45 | GE91: 0 | GG91: 0 | GH91: 0 | GI91: 45 | GK91: 0 | GM91: 0 | GN91: 0 | GO91: 45 | GQ91: 0 | GS91: 0 | GT91: 0 | GU91: 45 | GW91: 0 | GY91: 0 | GZ91: 0
A92: 017.928-00 | B92: 2023/0026599-001 | C92: G | D92: 2023/0026599 | E92: DZX5134 | F92: 01/04/2026 | G92: 30/04/2026 | H92: GILMAR RIBEIRO LEAL | I92: GILMAR RIBEIRO LEAL | J92: NORMAL | K92: EMEF | L92: =CONTINUA!BV92 -> 0 | M92: =CONTINUA!BW92 -> 0 | O92: 6020.2023/0026599-3 | P92: 0 | Q92: 0 | S92: 0 | U92: 0 | V92: 0 | W92: 0 | Y92: 0 | AA92: 0 | AB92: 0 | AC92: 0 | AE92: 0 | AG92: 0 | AH92: 0 | AI92: 0 | AK92: 0 | AM92: 0 | AN92: 0 | AO92: 0 | AQ92: 0 | AS92: 0 | AT92: 0 | AU92: 0 | AW92: 0 | AY92: 0 | AZ92: 0 | BA92: 0 | BC92: 0 | BE92: 0 | BF92: 0 | BG92: 0 | BI92: 0 | BK92: 0 | BL92: 0 | BM92: 0 | BO92: 0 | BQ92: 0 | BR92: 0 | BS92: 0 | BU92: 0 | BW92: 0 | BX92: 0 | BY92: 0 | CA92: 0 | CC92: 0 | CD92: 0 | CE92: 0 | CG92: 0 | CI92: 0 | CJ92: 0 | CK92: 0 | CM92: 0 | CO92: 0 | CP92: 0 | CQ92: 0 | CS92: 0 | CU92: 0 | CV92: 0 | CW92: 0 | CY92: 0 | DA92: 0 | DB92: 0 | DC92: 0 | DE92: 0 | DG92: 0 | DH92: 0 | DI92: 0 | DK92: 0 | DM92: 0 | DN92: 0 | DO92: 0 | DQ92: 0 | DS92: 0 | DT92: 0 | DU92: 0 | DW92: 0 | DY92: 0 | DZ92: 0 | EA92: 0 | EC92: 0 | EE92: 0 | EF92: 0 | EG92: 0 | EI92: 0 | EK92: 0 | EL92: 0 | EM92: 0 | EO92: 0 | EQ92: 0 | ER92: 0 | ES92: 0 | EU92: 0 | EW92: 0 | EX92: 0 | EY92: 0 | FA92: 0 | FC92: 0 | FD92: 0 | FE92: 0 | FG92: 0 | FI92: 0 | FJ92: 0 | FK92: 0 | FM92: 0 | FO92: 0 | FP92: 0 | FQ92: 0 | FS92: 0 | FU92: 0 | FV92: 0 | FW92: 0 | FY92: 0 | GA92: 0 | GB92: 0 | GC92: 0 | GE92: 0 | GG92: 0 | GH92: 0 | GI92: 0 | GK92: 0 | GM92: 0 | GN92: 0 | GO92: 0 | GQ92: 0 | GS92: 0 | GT92: 0 | GU92: 0 | GW92: 0 | GY92: 0 | GZ92: 0
A93: 017.928-00 | B93: 2023/0026599-001 | C93: G | D93: 2023/0026599 | E93: DZX5134 | F93: 01/04/2026 | G93: 30/04/2026 | H93: GILMAR RIBEIRO LEAL | I93: GILMAR RIBEIRO LEAL | J93: NORMAL | K93: EMEE | L93: =CONTINUA!BV93 -> 0 | M93: =CONTINUA!BW93 -> 0 | O93: 6020.2023/0026599-3 | P93: 0 | Q93: 0 | S93: 0 | U93: 0 | V93: 0 | W93: 0 | Y93: 0 | AA93: 0 | AB93: 0 | AC93: 0 | AE93: 0 | AG93: 0 | AH93: 0 | AI93: 0 | AK93: 0 | AM93: 0 | AN93: 0 | AO93: 0 | AQ93: 0 | AS93: 0 | AT93: 0 | AU93: 0 | AW93: 0 | AY93: 0 | AZ93: 0 | BA93: 0 | BC93: 0 | BE93: 0 | BF93: 0 | BG93: 0 | BI93: 0 | BK93: 0 | BL93: 0 | BM93: 0 | BO93: 0 | BQ93: 0 | BR93: 0 | BS93: 0 | BU93: 0 | BW93: 0 | BX93: 0 | BY93: 0 | CA93: 0 | CC93: 0 | CD93: 0 | CE93: 0 | CG93: 0 | CI93: 0 | CJ93: 0 | CK93: 0 | CM93: 0 | CO93: 0 | CP93: 0 | CQ93: 0 | CS93: 0 | CU93: 0 | CV93: 0 | CW93: 0 | CY93: 0 | DA93: 0 | DB93: 0 | DC93: 0 | DE93: 0 | DG93: 0 | DH93: 0 | DI93: 0 | DK93: 0 | DM93: 0 | DN93: 0 | DO93: 0 | DQ93: 0 | DS93: 0 | DT93: 0 | DU93: 0 | DW93: 0 | DY93: 0 | DZ93: 0 | EA93: 0 | EC93: 0 | EE93: 0 | EF93: 0 | EG93: 0 | EI93: 0 | EK93: 0 | EL93: 0 | EM93: 0 | EO93: 0 | EQ93: 0 | ER93: 0 | ES93: 0 | EU93: 0 | EW93: 0 | EX93: 0 | EY93: 0 | FA93: 0 | FC93: 0 | FD93: 0 | FE93: 0 | FG93: 0 | FI93: 0 | FJ93: 0 | FK93: 0 | FM93: 0 | FO93: 0 | FP93: 0 | FQ93: 0 | FS93: 0 | FU93: 0 | FV93: 0 | FW93: 0 | FY93: 0 | GA93: 0 | GB93: 0 | GC93: 0 | GE93: 0 | GG93: 0 | GH93: 0 | GI93: 0 | GK93: 0 | GM93: 0 | GN93: 0 | GO93: 0 | GQ93: 0 | GS93: 0 | GT93: 0 | GU93: 0 | GW93: 0 | GY93: 0 | GZ93: 0
A94: 017.928-00 | B94: 2023/0026599-001 | C94: G | D94: 2023/0026599 | E94: DZX5134 | F94: 01/04/2026 | G94: 30/04/2026 | H94: GILMAR RIBEIRO LEAL | I94: GILMAR RIBEIRO LEAL | J94: NORMAL | K94: CEI | L94: =CONTINUA!BV94 -> 0 | M94: =CONTINUA!BW94 -> 0 | O94: 6020.2023/0026599-3 | P94: 0 | Q94: 0 | S94: 0 | U94: 0 | V94: 0 | W94: 0 | Y94: 0 | AA94: 0 | AB94: 0 | AC94: 0 | AE94: 0 | AG94: 0 | AH94: 0 | AI94: 0 | AK94: 0 | AM94: 0 | AN94: 0 | AO94: 0 | AQ94: 0 | AS94: 0 | AT94: 0 | AU94: 0 | AW94: 0 | AY94: 0 | AZ94: 0 | BA94: 0 | BC94: 0 | BE94: 0 | BF94: 0 | BG94: 0 | BI94: 0 | BK94: 0 | BL94: 0 | BM94: 0 | BO94: 0 | BQ94: 0 | BR94: 0 | BS94: 0 | BU94: 0 | BW94: 0 | BX94: 0 | BY94: 0 | CA94: 0 | CC94: 0 | CD94: 0 | CE94: 0 | CG94: 0 | CI94: 0 | CJ94: 0 | CK94: 0 | CM94: 0 | CO94: 0 | CP94: 0 | CQ94: 0 | CS94: 0 | CU94: 0 | CV94: 0 | CW94: 0 | CY94: 0 | DA94: 0 | DB94: 0 | DC94: 0 | DE94: 0 | DG94: 0 | DH94: 0 | DI94: 0 | DK94: 0 | DM94: 0 | DN94: 0 | DO94: 0 | DQ94: 0 | DS94: 0 | DT94: 0 | DU94: 0 | DW94: 0 | DY94: 0 | DZ94: 0 | EA94: 0 | EC94: 0 | EE94: 0 | EF94: 0 | EG94: 0 | EI94: 0 | EK94: 0 | EL94: 0 | EM94: 0 | EO94: 0 | EQ94: 0 | ER94: 0 | ES94: 0 | EU94: 0 | EW94: 0 | EX94: 0 | EY94: 0 | FA94: 0 | FC94: 0 | FD94: 0 | FE94: 0 | FG94: 0 | FI94: 0 | FJ94: 0 | FK94: 0 | FM94: 0 | FO94: 0 | FP94: 0 | FQ94: 0 | FS94: 0 | FU94: 0 | FV94: 0 | FW94: 0 | FY94: 0 | GA94: 0 | GB94: 0 | GC94: 0 | GE94: 0 | GG94: 0 | GH94: 0 | GI94: 0 | GK94: 0 | GM94: 0 | GN94: 0 | GO94: 0 | GQ94: 0 | GS94: 0 | GT94: 0 | GU94: 0 | GW94: 0 | GY94: 0 | GZ94: 0
A95: 017.928-00 | B95: 2023/0026599-001 | C95: G | D95: 2023/0026599 | E95: DZX5134 | F95: 01/04/2026 | G95: 30/04/2026 | H95: GILMAR RIBEIRO LEAL | I95: GILMAR RIBEIRO LEAL | J95: NORMAL | K95: CCA | L95: =CONTINUA!BV95 -> 0 | M95: =CONTINUA!BW95 -> 0 | O95: 6020.2023/0026599-3 | P95: 0 | Q95: 0 | S95: 0 | U95: 0 | V95: 0 | W95: 0 | Y95: 0 | AA95: 0 | AB95: 0 | AC95: 0 | AE95: 0 | AG95: 0 | AH95: 0 | AI95: 0 | AK95: 0 | AM95: 0 | AN95: 0 | AO95: 0 | AQ95: 0 | AS95: 0 | AT95: 0 | AU95: 0 | AW95: 0 | AY95: 0 | AZ95: 0 | BA95: 0 | BC95: 0 | BE95: 0 | BF95: 0 | BG95: 0 | BI95: 0 | BK95: 0 | BL95: 0 | BM95: 0 | BO95: 0 | BQ95: 0 | BR95: 0 | BS95: 0 | BU95: 0 | BW95: 0 | BX95: 0 | BY95: 0 | CA95: 0 | CC95: 0 | CD95: 0 | CE95: 0 | CG95: 0 | CI95: 0 | CJ95: 0 | CK95: 0 | CM95: 0 | CO95: 0 | CP95: 0 | CQ95: 0 | CS95: 0 | CU95: 0 | CV95: 0 | CW95: 0 | CY95: 0 | DA95: 0 | DB95: 0 | DC95: 0 | DE95: 0 | DG95: 0 | DH95: 0 | DI95: 0 | DK95: 0 | DM95: 0 | DN95: 0 | DO95: 0 | DQ95: 0 | DS95: 0 | DT95: 0 | DU95: 0 | DW95: 0 | DY95: 0 | DZ95: 0 | EA95: 0 | EC95: 0 | EE95: 0 | EF95: 0 | EG95: 0 | EI95: 0 | EK95: 0 | EL95: 0 | EM95: 0 | EO95: 0 | EQ95: 0 | ER95: 0 | ES95: 0 | EU95: 0 | EW95: 0 | EX95: 0 | EY95: 0 | FA95: 0 | FC95: 0 | FD95: 0 | FE95: 0 | FG95: 0 | FI95: 0 | FJ95: 0 | FK95: 0 | FM95: 0 | FO95: 0 | FP95: 0 | FQ95: 0 | FS95: 0 | FU95: 0 | FV95: 0 | FW95: 0 | FY95: 0 | GA95: 0 | GB95: 0 | GC95: 0 | GE95: 0 | GG95: 0 | GH95: 0 | GI95: 0 | GK95: 0 | GM95: 0 | GN95: 0 | GO95: 0 | GQ95: 0 | GS95: 0 | GT95: 0 | GU95: 0 | GW95: 0 | GY95: 0 | GZ95: 0
A96: 040.333-00 | B96: 2022/0024483-001 | C96: 1 | D96: 2022/0024483 | E96: EXO0054 | F96: 01/04/2026 | G96: 30/04/2026 | H96: GISELE BRITO DE MATOS MALAQUIAS | I96: GISELE BRITO DE MATOS MALAQUIAS | J96: NORMAL | K96: EMEI | L96: =CONTINUA!BV96 -> 0 | M96: =CONTINUA!BW96 -> 0 | O96: 6020.2022/0024483-8 | P96: 0 | Q96: 19 | S96: 0 | U96: 0 | V96: 0 | W96: 19 | Y96: 0 | AA96: 0 | AB96: 0 | AC96: 19 | AE96: 0 | AG96: 0 | AH96: 0 | AI96: 19 | AK96: 0 | AM96: 0 | AN96: 0 | AO96: 19 | AQ96: 0 | AS96: 0 | AT96: 0 | AU96: 19 | AW96: 0 | AY96: 0 | AZ96: 0 | BA96: 19 | BC96: 0 | BE96: 0 | BF96: 0 | BG96: 19 | BI96: 0 | BK96: 0 | BL96: 0 | BM96: 19 | BO96: 0 | BQ96: 0 | BR96: 0 | BS96: 19 | BU96: 0 | BW96: 0 | BX96: 0 | BY96: 19 | CA96: 0 | CC96: 0 | CD96: 0 | CE96: 19 | CG96: 0 | CI96: 0 | CJ96: 0 | CK96: 19 | CM96: 0 | CO96: 0 | CP96: 0 | CQ96: 19 | CS96: 0 | CU96: 0 | CV96: 0 | CW96: 19 | CY96: 0 | DA96: 0 | DB96: 0 | DC96: 19 | DE96: 0 | DG96: 0 | DH96: 0 | DI96: 19 | DK96: 0 | DM96: 0 | DN96: 0 | DO96: 19 | DQ96: 0 | DS96: 0 | DT96: 0 | DU96: 19 | DW96: 0 | DY96: 0 | DZ96: 0 | EA96: 19 | EC96: 0 | EE96: 0 | EF96: 0 | EG96: 19 | EI96: 0 | EK96: 0 | EL96: 0 | EM96: 19 | EO96: 0 | EQ96: 0 | ER96: 0 | ES96: 19 | EU96: 0 | EW96: 0 | EX96: 0 | EY96: 19 | FA96: 0 | FC96: 0 | FD96: 0 | FE96: 19 | FG96: 0 | FI96: 0 | FJ96: 0 | FK96: 19 | FM96: 0 | FO96: 0 | FP96: 0 | FQ96: 19 | FS96: 0 | FU96: 0 | FV96: 0 | FW96: 19 | FY96: 0 | GA96: 0 | GB96: 0 | GC96: 19 | GE96: 0 | GG96: 0 | GH96: 0 | GI96: 19 | GK96: 0 | GM96: 0 | GN96: 0 | GO96: 19 | GQ96: 0 | GS96: 0 | GT96: 0 | GU96: 19 | GW96: 0 | GY96: 0 | GZ96: 0
A97: 040.333-00 | B97: 2022/0024483-001 | C97: G | D97: 2022/0024483 | E97: EXO0054 | F97: 01/04/2026 | G97: 30/04/2026 | H97: GISELE BRITO DE MATOS MALAQUIAS | I97: GISELE BRITO DE MATOS MALAQUIAS | J97: NORMAL | K97: EMEF | L97: =CONTINUA!BV97 -> 8 | M97: =CONTINUA!BW97 -> 0 | O97: 6020.2022/0024483-8 | P97: 0 | Q97: 17 | S97: 0 | U97: 0 | V97: 0 | W97: 17 | Y97: 0 | AA97: 0 | AB97: 0 | AC97: 17 | AE97: 0 | AG97: 0 | AH97: 0 | AI97: 17 | AK97: 0 | AM97: 0 | AN97: 0 | AO97: 17 | AQ97: 0 | AS97: 0 | AT97: 0 | AU97: 17 | AW97: 0 | AY97: 0 | AZ97: 0 | BA97: 17 | BC97: 0 | BE97: 0 | BF97: 0 | BG97: 17 | BI97: 0 | BK97: 0 | BL97: 0 | BM97: 17 | BO97: 0 | BQ97: 0 | BR97: 0 | BS97: 17 | BU97: 0 | BW97: 0 | BX97: 0 | BY97: 17 | CA97: 0 | CC97: 0 | CD97: 0 | CE97: 17 | CG97: 0 | CI97: 0 | CJ97: 0 | CK97: 17 | CM97: 0 | CO97: 0 | CP97: 0 | CQ97: 17 | CS97: 0 | CU97: 0 | CV97: 0 | CW97: 17 | CY97: 0 | DA97: 0 | DB97: 0 | DC97: 17 | DE97: 0 | DG97: 0 | DH97: 0 | DI97: 17 | DK97: 0 | DM97: 0 | DN97: 0 | DO97: 17 | DQ97: 0 | DS97: 0 | DT97: 0 | DU97: 17 | DW97: 0 | DY97: 0 | DZ97: 0 | EA97: 17 | EC97: 0 | EE97: 0 | EF97: 0 | EG97: 17 | EI97: 0 | EK97: 0 | EL97: 0 | EM97: 17 | EO97: 0 | EQ97: 0 | ER97: 0 | ES97: 17 | EU97: 0 | EW97: 0 | EX97: 0 | EY97: 17 | FA97: 0 | FC97: 0 | FD97: 0 | FE97: 17 | FG97: 0 | FI97: 0 | FJ97: 0 | FK97: 17 | FM97: 0 | FO97: 0 | FP97: 0 | FQ97: 17 | FS97: 0 | FU97: 0 | FV97: 0 | FW97: 17 | FY97: 0 | GA97: 0 | GB97: 0 | GC97: 17 | GE97: 0 | GG97: 0 | GH97: 0 | GI97: 17 | GK97: 0 | GM97: 0 | GN97: 0 | GO97: 17 | GQ97: 0 | GS97: 0 | GT97: 0 | GU97: 17 | GW97: 0 | GY97: 0 | GZ97: 0
A98: 040.333-00 | B98: 2022/0024483-001 | C98: G | D98: 2022/0024483 | E98: EXO0054 | F98: 01/04/2026 | G98: 30/04/2026 | H98: GISELE BRITO DE MATOS MALAQUIAS | I98: GISELE BRITO DE MATOS MALAQUIAS | J98: NORMAL | K98: EMEE | L98: =CONTINUA!BV98 -> 0 | M98: =CONTINUA!BW98 -> 0 | O98: 6020.2022/0024483-8 | P98: 0 | Q98: 0 | S98: 0 | U98: 0 | V98: 0 | W98: 0 | Y98: 0 | AA98: 0 | AB98: 0 | AC98: 0 | AE98: 0 | AG98: 0 | AH98: 0 | AI98: 0 | AK98: 0 | AM98: 0 | AN98: 0 | AO98: 0 | AQ98: 0 | AS98: 0 | AT98: 0 | AU98: 0 | AW98: 0 | AY98: 0 | AZ98: 0 | BA98: 0 | BC98: 0 | BE98: 0 | BF98: 0 | BG98: 0 | BI98: 0 | BK98: 0 | BL98: 0 | BM98: 0 | BO98: 0 | BQ98: 0 | BR98: 0 | BS98: 0 | BU98: 0 | BW98: 0 | BX98: 0 | BY98: 0 | CA98: 0 | CC98: 0 | CD98: 0 | CE98: 0 | CG98: 0 | CI98: 0 | CJ98: 0 | CK98: 0 | CM98: 0 | CO98: 0 | CP98: 0 | CQ98: 0 | CS98: 0 | CU98: 0 | CV98: 0 | CW98: 0 | CY98: 0 | DA98: 0 | DB98: 0 | DC98: 0 | DE98: 0 | DG98: 0 | DH98: 0 | DI98: 0 | DK98: 0 | DM98: 0 | DN98: 0 | DO98: 0 | DQ98: 0 | DS98: 0 | DT98: 0 | DU98: 0 | DW98: 0 | DY98: 0 | DZ98: 0 | EA98: 0 | EC98: 0 | EE98: 0 | EF98: 0 | EG98: 0 | EI98: 0 | EK98: 0 | EL98: 0 | EM98: 0 | EO98: 0 | EQ98: 0 | ER98: 0 | ES98: 0 | EU98: 0 | EW98: 0 | EX98: 0 | EY98: 0 | FA98: 0 | FC98: 0 | FD98: 0 | FE98: 0 | FG98: 0 | FI98: 0 | FJ98: 0 | FK98: 0 | FM98: 0 | FO98: 0 | FP98: 0 | FQ98: 0 | FS98: 0 | FU98: 0 | FV98: 0 | FW98: 0 | FY98: 0 | GA98: 0 | GB98: 0 | GC98: 0 | GE98: 0 | GG98: 0 | GH98: 0 | GI98: 0 | GK98: 0 | GM98: 0 | GN98: 0 | GO98: 0 | GQ98: 0 | GS98: 0 | GT98: 0 | GU98: 0 | GW98: 0 | GY98: 0 | GZ98: 0
A99: 040.333-00 | B99: 2022/0024483-001 | C99: G | D99: 2022/0024483 | E99: EXO0054 | F99: 01/04/2026 | G99: 30/04/2026 | H99: GISELE BRITO DE MATOS MALAQUIAS | I99: GISELE BRITO DE MATOS MALAQUIAS | J99: NORMAL | K99: CEI | L99: =CONTINUA!BV99 -> 0 | M99: =CONTINUA!BW99 -> 0 | O99: 6020.2022/0024483-8 | P99: 0 | Q99: 0 | S99: 0 | U99: 0 | V99: 0 | W99: 0 | Y99: 0 | AA99: 0 | AB99: 0 | AC99: 0 | AE99: 0 | AG99: 0 | AH99: 0 | AI99: 0 | AK99: 0 | AM99: 0 | AN99: 0 | AO99: 0 | AQ99: 0 | AS99: 0 | AT99: 0 | AU99: 0 | AW99: 0 | AY99: 0 | AZ99: 0 | BA99: 0 | BC99: 0 | BE99: 0 | BF99: 0 | BG99: 0 | BI99: 0 | BK99: 0 | BL99: 0 | BM99: 0 | BO99: 0 | BQ99: 0 | BR99: 0 | BS99: 0 | BU99: 0 | BW99: 0 | BX99: 0 | BY99: 0 | CA99: 0 | CC99: 0 | CD99: 0 | CE99: 0 | CG99: 0 | CI99: 0 | CJ99: 0 | CK99: 0 | CM99: 0 | CO99: 0 | CP99: 0 | CQ99: 0 | CS99: 0 | CU99: 0 | CV99: 0 | CW99: 0 | CY99: 0 | DA99: 0 | DB99: 0 | DC99: 0 | DE99: 0 | DG99: 0 | DH99: 0 | DI99: 0 | DK99: 0 | DM99: 0 | DN99: 0 | DO99: 0 | DQ99: 0 | DS99: 0 | DT99: 0 | DU99: 0 | DW99: 0 | DY99: 0 | DZ99: 0 | EA99: 0 | EC99: 0 | EE99: 0 | EF99: 0 | EG99: 0 | EI99: 0 | EK99: 0 | EL99: 0 | EM99: 0 | EO99: 0 | EQ99: 0 | ER99: 0 | ES99: 0 | EU99: 0 | EW99: 0 | EX99: 0 | EY99: 0 | FA99: 0 | FC99: 0 | FD99: 0 | FE99: 0 | FG99: 0 | FI99: 0 | FJ99: 0 | FK99: 0 | FM99: 0 | FO99: 0 | FP99: 0 | FQ99: 0 | FS99: 0 | FU99: 0 | FV99: 0 | FW99: 0 | FY99: 0 | GA99: 0 | GB99: 0 | GC99: 0 | GE99: 0 | GG99: 0 | GH99: 0 | GI99: 0 | GK99: 0 | GM99: 0 | GN99: 0 | GO99: 0 | GQ99: 0 | GS99: 0 | GT99: 0 | GU99: 0 | GW99: 0 | GY99: 0 | GZ99: 0
A100: 040.333-00 | B100: 2022/0024483-001 | C100: G | D100: 2022/0024483 | E100: EXO0054 | F100: 01/04/2026 | G100: 30/04/2026 | H100: GISELE BRITO DE MATOS MALAQUIAS | I100: GISELE BRITO DE MATOS MALAQUIAS | J100: NORMAL | K100: CCA | L100: =CONTINUA!BV100 -> 0 | M100: =CONTINUA!BW100 -> 0 | O100: 6020.2022/0024483-8 | P100: 0 | Q100: 0 | S100: 0 | U100: 0 | V100: 0 | W100: 0 | Y100: 0 | AA100: 0 | AB100: 0 | AC100: 0 | AE100: 0 | AG100: 0 | AH100: 0 | AI100: 0 | AK100: 0 | AM100: 0 | AN100: 0 | AO100: 0 | AQ100: 0 | AS100: 0 | AT100: 0 | AU100: 0 | AW100: 0 | AY100: 0 | AZ100: 0 | BA100: 0 | BC100: 0 | BE100: 0 | BF100: 0 | BG100: 0 | BI100: 0 | BK100: 0 | BL100: 0 | BM100: 0 | BO100: 0 | BQ100: 0 | BR100: 0 | BS100: 0 | BU100: 0 | BW100: 0 | BX100: 0 | BY100: 0 | CA100: 0 | CC100: 0 | CD100: 0 | CE100: 0 | CG100: 0 | CI100: 0 | CJ100: 0 | CK100: 0 | CM100: 0 | CO100: 0 | CP100: 0 | CQ100: 0 | CS100: 0 | CU100: 0 | CV100: 0 | CW100: 0 | CY100: 0 | DA100: 0 | DB100: 0 | DC100: 0 | DE100: 0 | DG100: 0 | DH100: 0 | DI100: 0 | DK100: 0 | DM100: 0 | DN100: 0 | DO100: 0 | DQ100: 0 | DS100: 0 | DT100: 0 | DU100: 0 | DW100: 0 | DY100: 0 | DZ100: 0 | EA100: 0 | EC100: 0 | EE100: 0 | EF100: 0 | EG100: 0 | EI100: 0 | EK100: 0 | EL100: 0 | EM100: 0 | EO100: 0 | EQ100: 0 | ER100: 0 | ES100: 0 | EU100: 0 | EW100: 0 | EX100: 0 | EY100: 0 | FA100: 0 | FC100: 0 | FD100: 0 | FE100: 0 | FG100: 0 | FI100: 0 | FJ100: 0 | FK100: 0 | FM100: 0 | FO100: 0 | FP100: 0 | FQ100: 0 | FS100: 0 | FU100: 0 | FV100: 0 | FW100: 0 | FY100: 0 | GA100: 0 | GB100: 0 | GC100: 0 | GE100: 0 | GG100: 0 | GH100: 0 | GI100: 0 | GK100: 0 | GM100: 0 | GN100: 0 | GO100: 0 | GQ100: 0 | GS100: 0 | GT100: 0 | GU100: 0 | GW100: 0 | GY100: 0 | GZ100: 0
...

Sheet APELIDOS
A1: CREDENCIADO | B1: APELIDO
A2: COOP DE TR DA CAP DE SP - COOPER CAPITAL | B2: COOPER CAPITAL
A3: COOP DE TRANSP ESC DA Z SUL DE SP - COOPERTRES | B3: COOPERTRES
A4: COOP DE TRANSP ESC DA Z SUL DE SP - COOPERTRES | B4: COOPERTRES
A5: COOP DE TRANSP ESC DA Z SUL DE SP - COOPERTRES | B5: COOPERTRES
A6: COOP DE TRANSP ESC DA Z SUL DE SP - COOPERTRES | B6: COOPERTRES
A7: COOP DE TRANSP ESC DA Z SUL DE SP - COOPERTRES | B7: COOPERTRES
A8: COOP DE TRANSP ESC DA Z SUL DE SP - COOPERTRES | B8: COOPERTRES
A9: COOP DE TRANSP ESC NORTE SAO PAULO - COOPERNORTE | B9: COOPERNORTE
A10: COOP DE TRANSP ESC NORTE SAO PAULO - COOPERNORTE | B10: COOPERNORTE
A11: COOP DE TRANSP ESC NORTE SAO PAULO - COOPERNORTE | B11: COOPERNORTE
A12: COOP TRANSP ESC CAP SOC COOPERCAPS | B12: COOPERCAPS
... A3867: VIA LUZ TRANSPORTES DE PASSAGEIROS LTDA - EPP | B3867: VIA LUZ

Sheet CONTINUA
A1: ='APONTAMENTO CREDENCIAMENTO'!A1 -> Guaianases | G1: ='BASE C'!E4 -> ABRIL | I1: APONTAMENTO CREDENCIAMENTO
G2: 01/06 a 30/06/2025
B3: =A3+1 -> 1 | C3: 3 | D3: 3 | F3: =D3+1 -> 4 | G3: 5 | H3: =G3+1 -> 6 | I3: =H3+1 -> 7 | J3: =I3+1 -> 8 | K3: =J3+1 -> 9
A4: CRMC | B4: OS | C4: DRE | D4: CONTRATO | E4: PLACA | F4: PERÍODO | H4: EMPRESA | I4: NOME CONDUTOR | J4: TIPO DE VEÍCULO (NORMAL, ADAPTADO) | K4: TIPO DE ATENDIMENTO | L4: =F5 -> 46113 | N4: =L4+1 -> 46114 | P4: =N4+1 -> 46115 | R4: =P4+1 -> 46116 | T4: =R4+1 -> 46117 | V4: =T4+1 -> 46118 | X4: =V4+1 -> 46119 | Z4: =X4+1 -> 46120 | AB4: =Z4+1 -> 46121 | AD4: =AB4+1 -> 46122 | AF4: =AD4+1 -> 46123 | AH4: =AF4+1 -> 46124 | AJ4: =AH4+1 -> 46125 | AL4: =AJ4+1 -> 46126 | AN4: =AL4+1 -> 46127 | AP4: =AN4+1 -> 46128 | AR4: =AP4+1 -> 46129 | AT4: =AR4+1 -> 46130 | AV4: =AT4+1 -> 46131 | AX4: =AV4+1 -> 46132 | AZ4: =AX4+1 -> 46133 | BB4: =AZ4+1 -> 46134 | BD4: =BB4+1 -> 46135 | BF4: =BD4+1 -> 46136 | BH4: =BF4+1 -> 46137 | BJ4: =BH4+1 -> 46138 | BL4: =BJ4+1 -> 46139 | BN4: =BL4+1 -> 46140 | BP4: =BN4+1 -> 46141 | BR4: =BP4+1 -> 46142 | BV4: TOTAL GERAL REG | BW4: TOTAL GERAL CAD
F5: ='VALORES TABELA'!$B$11 -> 46113 | G5: ='VALORES TABELA'!$C$11 -> 46142 | L5: Cont N CAD | M5: Cont CAD | N5: Cont N CAD | O5: Cont CAD | P5: Cont N CAD | Q5: Cont CAD | R5: Cont N CAD | S5: Cont CAD | T5: Cont N CAD | U5: Cont CAD | V5: Cont N CAD | W5: Cont CAD | X5: Cont N CAD | Y5: Cont CAD | Z5: Cont N CAD | AA5: Cont CAD | AB5: Cont N CAD | AC5: Cont CAD | AD5: Cont N CAD | AE5: Cont CAD | AF5: Cont N CAD | AG5: Cont CAD | AH5: Cont N CAD | AI5: Cont CAD | AJ5: Cont N CAD | AK5: Cont CAD | AL5: Cont N CAD | AM5: Cont CAD | AN5: Cont N CAD | AO5: Cont CAD | AP5: Cont N CAD | AQ5: Cont CAD | AR5: Cont N CAD | AS5: Cont CAD | AT5: Cont N CAD | AU5: Cont CAD | AV5: Cont N CAD | AW5: Cont CAD | AX5: Cont N CAD | AY5: Cont CAD | AZ5: Cont N CAD | BA5: Cont CAD | BB5: Cont N CAD | BC5: Cont CAD | BD5: Cont N CAD | BE5: Cont CAD | BG5: Cont CAD | BH5: Cont N CAD | BJ5: Cont N CAD | BK5: Cont CAD | BL5: Cont N CAD | BM5: Cont CAD | BN5: Cont N CAD | BO5: Cont CAD | BP5: Cont N CAD | BQ5: Cont CAD | BR5: Cont N CAD | BS5: Cont CAD | BT5: Cont N CAD | BU5: Cont CAD
A6: 019.832-00 | B6: 2022/0031800-001 | C6: 1 | D6: 2022/0031800 | E6: DJB1584 | F6: 01/04/2026 | G6: 30/04/2026 | H6: AJENIAS PEREIRA | I6: AJENIAS PEREIRA | J6: NORMAL | K6: EMEI | L6: 0 | M6: 0 | N6: 0 | O6: 0 | P6: 0 | Q6: 0 | V6: 0 | W6: 0 | X6: 0 | Y6: 0 | Z6: 0 | AA6: 0 | AB6: 0 | AC6: 0 | AD6: 0 | AE6: 0 | AJ6: 0 | AK6: 0 | AL6: 0 | AM6: 0 | AN6: 0 | AO6: 0 | AP6: 0 | AQ6: 0 | AR6: 0 | AS6: 0 | AX6: 0 | AY6: 0 | AZ6: 0 | BA6: 0 | BB6: 0 | BC6: 0 | BD6: 0 | BE6: 0 | BF6: 0 | BG6: 0 | BL6: 0 | BM6: 0 | BN6: 0 | BO6: 0 | BP6: 0 | BQ6: 0 | BR6: 0 | BS6: 0 | BV6: =L6+N6+P6+R6+T6+V6+X6+Z6+AB6+AD6+AF6+AH6+AJ6+AL6+AN6+AP6+AR6+AT6+AV6+AX6+AZ6+BB6+BD6+BF6+BH6+BJ6+BL6+BN6+BP6+BR6+BT6 -> 0 | BW6: =M6+O6+Q6+S6+U6+W6+Y6+AA6+AC6+AE6+AG6+AI6+AK6+AM6+AO6+AQ6+AS6+AU6+AW6+AY6+BA6+BC6+BE6+BG6+BI6+BK6+BM6+BO6+BQ6+BS6+BU6 -> 0
A7: 019.832-00 | B7: 2022/0031800-001 | C7: G | D7: 2022/0031800 | E7: DJB1584 | F7: 01/04/2026 | G7: 30/04/2026 | H7: AJENIAS PEREIRA | I7: AJENIAS PEREIRA | J7: NORMAL | K7: EMEF | L7: 0 | M7: 0 | N7: 0 | O7: 0 | P7: 0 | Q7: 0 | V7: 0 | W7: 0 | X7: 0 | Y7: 0 | Z7: 0 | AA7: 0 | AB7: 0 | AC7: 0 | AD7: 0 | AE7: 0 | AJ7: 0 | AK7: 0 | AL7: 0 | AM7: 0 | AN7: 0 | AO7: 0 | AP7: 0 | AQ7: 0 | AR7: 0 | AS7: 0 | AX7: 0 | AY7: 0 | AZ7: 0 | BA7: 0 | BB7: 0 | BC7: 0 | BD7: 0 | BE7: 0 | BF7: 0 | BG7: 0 | BL7: 0 | BM7: 0 | BN7: 0 | BO7: 0 | BP7: 0 | BQ7: 0 | BR7: 0 | BS7: 0 | BV7: =L7+N7+P7+R7+T7+V7+X7+Z7+AB7+AD7+AF7+AH7+AJ7+AL7+AN7+AP7+AR7+AT7+AV7+AX7+AZ7+BB7+BD7+BF7+BH7+BJ7+BL7+BN7+BP7+BR7+BT7 -> 0 | BW7: =M7+O7+Q7+S7+U7+W7+Y7+AA7+AC7+AE7+AG7+AI7+AK7+AM7+AO7+AQ7+AS7+AU7+AW7+AY7+BA7+BC7+BE7+BG7+BI7+BK7+BM7+BO7+BQ7+BS7+BU7 -> 0
A8: 019.832-00 | B8: 2022/0031800-001 | C8: G | D8: 2022/0031800 | E8: DJB1584 | F8: 01/04/2026 | G8: 30/04/2026 | H8: AJENIAS PEREIRA | I8: AJENIAS PEREIRA | J8: NORMAL | K8: EMEE | L8: 0 | M8: 0 | N8: 0 | O8: 0 | P8: 0 | Q8: 0 | V8: 0 | W8: 0 | X8: 0 | Y8: 0 | Z8: 0 | AA8: 0 | AB8: 0 | AC8: 0 | AD8: 0 | AE8: 0 | AJ8: 0 | AK8: 0 | AL8: 0 | AM8: 0 | AN8: 0 | AO8: 0 | AP8: 0 | AQ8: 0 | AR8: 0 | AS8: 0 | AX8: 0 | AY8: 0 | AZ8: 0 | BA8: 0 | BB8: 0 | BC8: 0 | BD8: 0 | BE8: 0 | BF8: 0 | BG8: 0 | BL8: 0 | BM8: 0 | BN8: 0 | BO8: 0 | BP8: 0 | BQ8: 0 | BR8: 0 | BS8: 0 | BV8: =L8+N8+P8+R8+T8+V8+X8+Z8+AB8+AD8+AF8+AH8+AJ8+AL8+AN8+AP8+AR8+AT8+AV8+AX8+AZ8+BB8+BD8+BF8+BH8+BJ8+BL8+BN8+BP8+BR8+BT8 -> 0 | BW8: =M8+O8+Q8+S8+U8+W8+Y8+AA8+AC8+AE8+AG8+AI8+AK8+AM8+AO8+AQ8+AS8+AU8+AW8+AY8+BA8+BC8+BE8+BG8+BI8+BK8+BM8+BO8+BQ8+BS8+BU8 -> 0
A9: 019.832-00 | B9: 2022/0031800-001 | C9: G | D9: 2022/0031800 | E9: DJB1584 | F9: 01/04/2026 | G9: 30/04/2026 | H9: AJENIAS PEREIRA | I9: AJENIAS PEREIRA | J9: NORMAL | K9: CEI | L9: 0 | M9: 0 | N9: 0 | O9: 0 | P9: 0 | Q9: 0 | V9: 0 | W9: 0 | X9: 0 | Y9: 0 | Z9: 0 | AA9: 0 | AB9: 0 | AC9: 0 | AD9: 0 | AE9: 0 | AJ9: 0 | AK9: 0 | AL9: 0 | AM9: 0 | AN9: 0 | AO9: 0 | AP9: 0 | AQ9: 0 | AR9: 0 | AS9: 0 | AX9: 0 | AY9: 0 | AZ9: 0 | BA9: 0 | BB9: 0 | BC9: 0 | BD9: 0 | BE9: 0 | BF9: 0 | BG9: 0 | BL9: 0 | BM9: 0 | BN9: 0 | BO9: 0 | BP9: 0 | BQ9: 0 | BR9: 0 | BS9: 0 | BV9: =L9+N9+P9+R9+T9+V9+X9+Z9+AB9+AD9+AF9+AH9+AJ9+AL9+AN9+AP9+AR9+AT9+AV9+AX9+AZ9+BB9+BD9+BF9+BH9+BJ9+BL9+BN9+BP9+BR9+BT9 -> 0 | BW9: =M9+O9+Q9+S9+U9+W9+Y9+AA9+AC9+AE9+AG9+AI9+AK9+AM9+AO9+AQ9+AS9+AU9+AW9+AY9+BA9+BC9+BE9+BG9+BI9+BK9+BM9+BO9+BQ9+BS9+BU9 -> 0
A10: 019.832-00 | B10: 2022/0031800-001 | C10: G | D10: 2022/0031800 | E10: DJB1584 | F10: 01/04/2026 | G10: 30/04/2026 | H10: AJENIAS PEREIRA | I10: AJENIAS PEREIRA | J10: NORMAL | K10: CCA | L10: 0 | M10: 0 | N10: 0 | O10: 0 | P10: 0 | Q10: 0 | V10: 0 | W10: 0 | X10: 0 | Y10: 0 | Z10: 0 | AA10: 0 | AB10: 0 | AC10: 0 | AD10: 0 | AE10: 0 | AJ10: 0 | AK10: 0 | AL10: 0 | AM10: 0 | AN10: 0 | AO10: 0 | AP10: 0 | AQ10: 0 | AR10: 0 | AS10: 0 | AX10: 0 | AY10: 0 | AZ10: 0 | BA10: 0 | BB10: 0 | BC10: 0 | BD10: 0 | BE10: 0 | BF10: 0 | BG10: 0 | BL10: 0 | BM10: 0 | BN10: 0 | BO10: 0 | BP10: 0 | BQ10: 0 | BR10: 0 | BS10: 0 | BV10: =L10+N10+P10+R10+T10+V10+X10+Z10+AB10+AD10+AF10+AH10+AJ10+AL10+AN10+AP10+AR10+AT10+AV10+AX10+AZ10+BB10+BD10+BF10+BH10+BJ10+BL10+BN10+BP10+BR10+BT10 -> 0 | BW10: =M10+O10+Q10+S10+U10+W10+Y10+AA10+AC10+AE10+AG10+AI10+AK10+AM10+AO10+AQ10+AS10+AU10+AW10+AY10+BA10+BC10+BE10+BG10+BI10+BK10+BM10+BO10+BQ10+BS10+BU10 -> 0
A11: 017.554-00 | B11: 2022/0029218-001 | C11: 1 | D11: 2022/0029218 | E11: CZX5065 | F11: 01/04/2026 | G11: 30/04/2026 | H11: ALTAIR ELIAS CARNEIRO | I11: ALTAIR ELIAS CARNEIRO | J11: NORMAL | K11: EMEI | L11: 0 | M11: 0 | N11: 0 | O11: 0 | P11: 0 | Q11: 0 | V11: 0 | W11: 0 | X11: 0 | Y11: 0 | Z11: 0 | AA11: 0 | AB11: 0 | AC11: 0 | AD11: 0 | AE11: 0 | AJ11: 0 | AK11: 0 | AL11: 0 | AM11: 0 | AN11: 0 | AO11: 0 | AP11: 0 | AQ11: 0 | AR11: 0 | AS11: 0 | AX11: 0 | AY11: 0 | AZ11: 0 | BA11: 0 | BB11: 0 | BC11: 0 | BD11: 0 | BE11: 0 | BF11: 0 | BG11: 0 | BL11: 0 | BM11: 0 | BN11: 0 | BO11: 0 | BP11: 0 | BQ11: 0 | BR11: 0 | BS11: 0 | BV11: =L11+N11+P11+R11+T11+V11+X11+Z11+AB11+AD11+AF11+AH11+AJ11+AL11+AN11+AP11+AR11+AT11+AV11+AX11+AZ11+BB11+BD11+BF11+BH11+BJ11+BL11+BN11+BP11+BR11+BT11 -> 0 | BW11: =M11+O11+Q11+S11+U11+W11+Y11+AA11+AC11+AE11+AG11+AI11+AK11+AM11+AO11+AQ11+AS11+AU11+AW11+AY11+BA11+BC11+BE11+BG11+BI11+BK11+BM11+BO11+BQ11+BS11+BU11 -> 0
A12: 017.554-00 | B12: 2022/0029218-001 | C12: G | D12: 2022/0029218 | E12: CZX5065 | F12: 01/04/2026 | G12: 30/04/2026 | H12: ALTAIR ELIAS CARNEIRO | I12: ALTAIR ELIAS CARNEIRO | J12: NORMAL | K12: EMEF | L12: 0 | M12: 0 | N12: 0 | O12: 0 | P12: 0 | Q12: 0 | V12: 0 | W12: 0 | X12: 0 | Y12: 0 | Z12: 0 | AA12: 0 | AB12: 0 | AC12: 0 | AD12: 0 | AE12: 0 | AJ12: 0 | AK12: 0 | AL12: 0 | AM12: 0 | AN12: 0 | AO12: 0 | AP12: 0 | AQ12: 0 | AR12: 0 | AS12: 0 | AX12: 0 | AY12: 0 | AZ12: 0 | BA12: 0 | BB12: 0 | BC12: 0 | BD12: 0 | BE12: 0 | BF12: 0 | BG12: 0 | BL12: 0 | BM12: 0 | BN12: 0 | BO12: 0 | BP12: 0 | BQ12: 0 | BR12: 0 | BS12: 0 | BV12: =L12+N12+P12+R12+T12+V12+X12+Z12+AB12+AD12+AF12+AH12+AJ12+AL12+AN12+AP12+AR12+AT12+AV12+AX12+AZ12+BB12+BD12+BF12+BH12+BJ12+BL12+BN12+BP12+BR12+BT12 -> 0 | BW12: =M12+O12+Q12+S12+U12+W12+Y12+AA12+AC12+AE12+AG12+AI12+AK12+AM12+AO12+AQ12+AS12+AU12+AW12+AY12+BA12+BC12+BE12+BG12+BI12+BK12+BM12+BO12+BQ12+BS12+BU12 -> 0
A13: 017.554-00 | B13: 2022/0029218-001 | C13: G | D13: 2022/0029218 | E13: CZX5065 | F13: 01/04/2026 | G13: 30/04/2026 | H13: ALTAIR ELIAS CARNEIRO | I13: ALTAIR ELIAS CARNEIRO | J13: NORMAL | K13: EMEE | L13: 0 | M13: 0 | N13: 0 | O13: 0 | P13: 0 | Q13: 0 | V13: 0 | W13: 0 | X13: 0 | Y13: 0 | Z13: 0 | AA13: 0 | AB13: 0 | AC13: 0 | AD13: 0 | AE13: 0 | AJ13: 0 | AK13: 0 | AL13: 0 | AM13: 0 | AN13: 0 | AO13: 0 | AP13: 0 | AQ13: 0 | AR13: 0 | AS13: 0 | AX13: 0 | AY13: 0 | AZ13: 0 | BA13: 0 | BB13: 0 | BC13: 0 | BD13: 0 | BE13: 0 | BF13: 0 | BG13: 0 | BL13: 0 | BM13: 0 | BN13: 0 | BO13: 0 | BP13: 0 | BQ13: 0 | BR13: 0 | BS13: 0 | BV13: =L13+N13+P13+R13+T13+V13+X13+Z13+AB13+AD13+AF13+AH13+AJ13+AL13+AN13+AP13+AR13+AT13+AV13+AX13+AZ13+BB13+BD13+BF13+BH13+BJ13+BL13+BN13+BP13+BR13+BT13 -> 0 | BW13: =M13+O13+Q13+S13+U13+W13+Y13+AA13+AC13+AE13+AG13+AI13+AK13+AM13+AO13+AQ13+AS13+AU13+AW13+AY13+BA13+BC13+BE13+BG13+BI13+BK13+BM13+BO13+BQ13+BS13+BU13 -> 0
A14: 017.554-00 | B14: 2022/0029218-001 | C14: G | D14: 2022/0029218 | E14: CZX5065 | F14: 01/04/2026 | G14: 30/04/2026 | H14: ALTAIR ELIAS CARNEIRO | I14: ALTAIR ELIAS CARNEIRO | J14: NORMAL | K14: CEI | L14: 0 | M14: 0 | N14: 0 | O14: 0 | P14: 0 | Q14: 0 | V14: 0 | W14: 0 | X14: 0 | Y14: 0 | Z14: 0 | AA14: 0 | AB14: 0 | AC14: 0 | AD14: 0 | AE14: 0 | AJ14: 0 | AK14: 0 | AL14: 0 | AM14: 0 | AN14: 0 | AO14: 0 | AP14: 0 | AQ14: 0 | AR14: 0 | AS14: 0 | AX14: 0 | AY14: 0 | AZ14: 0 | BA14: 0 | BB14: 0 | BC14: 0 | BD14: 0 | BE14: 0 | BF14: 0 | BG14: 0 | BL14: 0 | BM14: 0 | BN14: 0 | BO14: 0 | BP14: 0 | BQ14: 0 | BR14: 0 | BS14: 0 | BV14: =L14+N14+P14+R14+T14+V14+X14+Z14+AB14+AD14+AF14+AH14+AJ14+AL14+AN14+AP14+AR14+AT14+AV14+AX14+AZ14+BB14+BD14+BF14+BH14+BJ14+BL14+BN14+BP14+BR14+BT14 -> 0 | BW14: =M14+O14+Q14+S14+U14+W14+Y14+AA14+AC14+AE14+AG14+AI14+AK14+AM14+AO14+AQ14+AS14+AU14+AW14+AY14+BA14+BC14+BE14+BG14+BI14+BK14+BM14+BO14+BQ14+BS14+BU14 -> 0
A15: 017.554-00 | B15: 2022/0029218-001 | C15: G | D15: 2022/0029218 | E15: CZX5065 | F15: 01/04/2026 | G15: 30/04/2026 | H15: ALTAIR ELIAS CARNEIRO | I15: ALTAIR ELIAS CARNEIRO | J15: NORMAL | K15: CCA | L15: 0 | M15: 0 | N15: 0 | O15: 0 | P15: 0 | Q15: 0 | V15: 0 | W15: 0 | X15: 0 | Y15: 0 | Z15: 0 | AA15: 0 | AB15: 0 | AC15: 0 | AD15: 0 | AE15: 0 | AJ15: 0 | AK15: 0 | AL15: 0 | AM15: 0 | AN15: 0 | AO15: 0 | AP15: 0 | AQ15: 0 | AR15: 0 | AS15: 0 | AX15: 0 | AY15: 0 | AZ15: 0 | BA15: 0 | BB15: 0 | BC15: 0 | BD15: 0 | BE15: 0 | BF15: 0 | BG15: 0 | BL15: 0 | BM15: 0 | BN15: 0 | BO15: 0 | BP15: 0 | BQ15: 0 | BR15: 0 | BS15: 0 | BV15: =L15+N15+P15+R15+T15+V15+X15+Z15+AB15+AD15+AF15+AH15+AJ15+AL15+AN15+AP15+AR15+AT15+AV15+AX15+AZ15+BB15+BD15+BF15+BH15+BJ15+BL15+BN15+BP15+BR15+BT15 -> 0 | BW15: =M15+O15+Q15+S15+U15+W15+Y15+AA15+AC15+AE15+AG15+AI15+AK15+AM15+AO15+AQ15+AS15+AU15+AW15+AY15+BA15+BC15+BE15+BG15+BI15+BK15+BM15+BO15+BQ15+BS15+BU15 -> 0
A16: 001.119-00 | B16: 2023/0026116-001 | C16: 1 | D16: 2023/0026116 | E16: DTD4303 | F16: 01/04/2026 | G16: 30/04/2026 | H16: ANTONIO ROBERTO GOMES | I16: ANTONIO ROBERTO GOMES | J16: NORMAL | K16: EMEI | L16: 0 | M16: 0 | N16: 0 | O16: 0 | P16: 0 | Q16: 0 | V16: 0 | W16: 0 | X16: 0 | Y16: 0 | Z16: 0 | AA16: 0 | AB16: 0 | AC16: 0 | AD16: 0 | AE16: 0 | AJ16: 0 | AK16: 0 | AL16: 0 | AM16: 0 | AN16: 0 | AO16: 0 | AP16: 0 | AQ16: 0 | AR16: 0 | AS16: 0 | AX16: 0 | AY16: 0 | AZ16: 0 | BA16: 0 | BB16: 0 | BC16: 0 | BD16: 0 | BE16: 0 | BF16: 0 | BG16: 0 | BL16: 0 | BM16: 0 | BN16: 0 | BO16: 0 | BP16: 0 | BQ16: 0 | BR16: 0 | BS16: 0 | BV16: =L16+N16+P16+R16+T16+V16+X16+Z16+AB16+AD16+AF16+AH16+AJ16+AL16+AN16+AP16+AR16+AT16+AV16+AX16+AZ16+BB16+BD16+BF16+BH16+BJ16+BL16+BN16+BP16+BR16+BT16 -> 0 | BW16: =M16+O16+Q16+S16+U16+W16+Y16+AA16+AC16+AE16+AG16+AI16+AK16+AM16+AO16+AQ16+AS16+AU16+AW16+AY16+BA16+BC16+BE16+BG16+BI16+BK16+BM16+BO16+BQ16+BS16+BU16 -> 0
A17: 001.119-00 | B17: 2023/0026116-001 | C17: G | D17: 2023/0026116 | E17: DTD4303 | F17: 01/04/2026 | G17: 30/04/2026 | H17: ANTONIO ROBERTO GOMES | I17: ANTONIO ROBERTO GOMES | J17: NORMAL | K17: EMEF | L17: 0 | M17: 0 | N17: 0 | O17: 0 | P17: 0 | Q17: 0 | V17: 6 | W17: 0 | X17: 0 | Y17: 0 | Z17: 0 | AA17: 0 | AB17: 0 | AC17: 0 | AD17: 0 | AE17: 0 | AJ17: 6 | AK17: 0 | AL17: 0 | AM17: 0 | AN17: 0 | AO17: 0 | AP17: 0 | AQ17: 0 | AR17: 0 | AS17: 0 | AX17: 6 | AY17: 0 | AZ17: 0 | BA17: 0 | BB17: 0 | BC17: 0 | BD17: 0 | BE17: 0 | BF17: 0 | BG17: 0 | BL17: 6 | BM17: 0 | BN17: 0 | BO17: 0 | BP17: 0 | BQ17: 0 | BR17: 0 | BS17: 0 | BV17: =L17+N17+P17+R17+T17+V17+X17+Z17+AB17+AD17+AF17+AH17+AJ17+AL17+AN17+AP17+AR17+AT17+AV17+AX17+AZ17+BB17+BD17+BF17+BH17+BJ17+BL17+BN17+BP17+BR17+BT17 -> 24 | BW17: =M17+O17+Q17+S17+U17+W17+Y17+AA17+AC17+AE17+AG17+AI17+AK17+AM17+AO17+AQ17+AS17+AU17+AW17+AY17+BA17+BC17+BE17+BG17+BI17+BK17+BM17+BO17+BQ17+BS17+BU17 -> 0
A18: 001.119-00 | B18: 2023/0026116-001 | C18: G | D18: 2023/0026116 | E18: DTD4303 | F18: 01/04/2026 | G18: 30/04/2026 | H18: ANTONIO ROBERTO GOMES | I18: ANTONIO ROBERTO GOMES | J18: NORMAL | K18: EMEE | L18: 0 | M18: 0 | N18: 0 | O18: 0 | P18: 0 | Q18: 0 | V18: 0 | W18: 0 | X18: 0 | Y18: 0 | Z18: 0 | AA18: 0 | AB18: 0 | AC18: 0 | AD18: 0 | AE18: 0 | AJ18: 0 | AK18: 0 | AL18: 0 | AM18: 0 | AN18: 0 | AO18: 0 | AP18: 0 | AQ18: 0 | AR18: 0 | AS18: 0 | AX18: 0 | AY18: 0 | AZ18: 0 | BA18: 0 | BB18: 0 | BC18: 0 | BD18: 0 | BE18: 0 | BF18: 0 | BG18: 0 | BL18: 0 | BM18: 0 | BN18: 0 | BO18: 0 | BP18: 0 | BQ18: 0 | BR18: 0 | BS18: 0 | BV18: =L18+N18+P18+R18+T18+V18+X18+Z18+AB18+AD18+AF18+AH18+AJ18+AL18+AN18+AP18+AR18+AT18+AV18+AX18+AZ18+BB18+BD18+BF18+BH18+BJ18+BL18+BN18+BP18+BR18+BT18 -> 0 | BW18: =M18+O18+Q18+S18+U18+W18+Y18+AA18+AC18+AE18+AG18+AI18+AK18+AM18+AO18+AQ18+AS18+AU18+AW18+AY18+BA18+BC18+BE18+BG18+BI18+BK18+BM18+BO18+BQ18+BS18+BU18 -> 0
A19: 001.119-00 | B19: 2023/0026116-001 | C19: G | D19: 2023/0026116 | E19: DTD4303 | F19: 01/04/2026 | G19: 30/04/2026 | H19: ANTONIO ROBERTO GOMES | I19: ANTONIO ROBERTO GOMES | J19: NORMAL | K19: CEI | L19: 0 | M19: 0 | N19: 0 | O19: 0 | P19: 0 | Q19: 0 | V19: 0 | W19: 0 | X19: 0 | Y19: 0 | Z19: 0 | AA19: 0 | AB19: 0 | AC19: 0 | AD19: 0 | AE19: 0 | AJ19: 0 | AK19: 0 | AL19: 0 | AM19: 0 | AN19: 0 | AO19: 0 | AP19: 0 | AQ19: 0 | AR19: 0 | AS19: 0 | AX19: 0 | AY19: 0 | AZ19: 0 | BA19: 0 | BB19: 0 | BC19: 0 | BD19: 0 | BE19: 0 | BF19: 0 | BG19: 0 | BL19: 0 | BM19: 0 | BN19: 0 | BO19: 0 | BP19: 0 | BQ19: 0 | BR19: 0 | BS19: 0 | BV19: =L19+N19+P19+R19+T19+V19+X19+Z19+AB19+AD19+AF19+AH19+AJ19+AL19+AN19+AP19+AR19+AT19+AV19+AX19+AZ19+BB19+BD19+BF19+BH19+BJ19+BL19+BN19+BP19+BR19+BT19 -> 0 | BW19: =M19+O19+Q19+S19+U19+W19+Y19+AA19+AC19+AE19+AG19+AI19+AK19+AM19+AO19+AQ19+AS19+AU19+AW19+AY19+BA19+BC19+BE19+BG19+BI19+BK19+BM19+BO19+BQ19+BS19+BU19 -> 0
A20: 001.119-00 | B20: 2023/0026116-001 | C20: G | D20: 2023/0026116 | E20: DTD4303 | F20: 01/04/2026 | G20: 30/04/2026 | H20: ANTONIO ROBERTO GOMES | I20: ANTONIO ROBERTO GOMES | J20: NORMAL | K20: CCA | L20: 0 | M20: 0 | N20: 0 | O20: 0 | P20: 0 | Q20: 0 | V20: 0 | W20: 0 | X20: 0 | Y20: 0 | Z20: 0 | AA20: 0 | AB20: 0 | AC20: 0 | AD20: 0 | AE20: 0 | AJ20: 0 | AK20: 0 | AL20: 0 | AM20: 0 | AN20: 0 | AO20: 0 | AP20: 0 | AQ20: 0 | AR20: 0 | AS20: 0 | AX20: 0 | AY20: 0 | AZ20: 0 | BA20: 0 | BB20: 0 | BC20: 0 | BD20: 0 | BE20: 0 | BF20: 0 | BG20: 0 | BL20: 0 | BM20: 0 | BN20: 0 | BO20: 0 | BP20: 0 | BQ20: 0 | BR20: 0 | BS20: 0 | BV20: =L20+N20+P20+R20+T20+V20+X20+Z20+AB20+AD20+AF20+AH20+AJ20+AL20+AN20+AP20+AR20+AT20+AV20+AX20+AZ20+BB20+BD20+BF20+BH20+BJ20+BL20+BN20+BP20+BR20+BT20 -> 0 | BW20: =M20+O20+Q20+S20+U20+W20+Y20+AA20+AC20+AE20+AG20+AI20+AK20+AM20+AO20+AQ20+AS20+AU20+AW20+AY20+BA20+BC20+BE20+BG20+BI20+BK20+BM20+BO20+BQ20+BS20+BU20 -> 0
A21: 034.861-00 | B21: 2022/0033315-001A | C21: 1 | D21: 2022/0033315 | E21: FQH5J83 | F21: 01/04/2026 | G21: 30/04/2026 | H21: BRUNO EDUARDO BARBOSA | I21: BRUNO EDUARDO BARBOSA | J21: NORMAL | K21: EMEI | L21: 0 | M21: 0 | N21: 0 | O21: 0 | P21: 0 | Q21: 0 | V21: 0 | W21: 0 | X21: 0 | Y21: 0 | Z21: 0 | AA21: 0 | AB21: 0 | AC21: 0 | AD21: 0 | AE21: 0 | AJ21: 0 | AK21: 0 | AL21: 0 | AM21: 0 | AN21: 0 | AO21: 0 | AP21: 0 | AQ21: 0 | AR21: 0 | AS21: 0 | AX21: 0 | AY21: 0 | AZ21: 0 | BA21: 0 | BB21: 0 | BC21: 0 | BD21: 0 | BE21: 0 | BF21: 0 | BG21: 0 | BL21: 0 | BM21: 0 | BN21: 0 | BO21: 0 | BP21: 0 | BQ21: 0 | BR21: 0 | BS21: 0 | BV21: =L21+N21+P21+R21+T21+V21+X21+Z21+AB21+AD21+AF21+AH21+AJ21+AL21+AN21+AP21+AR21+AT21+AV21+AX21+AZ21+BB21+BD21+BF21+BH21+BJ21+BL21+BN21+BP21+BR21+BT21 -> 0 | BW21: =M21+O21+Q21+S21+U21+W21+Y21+AA21+AC21+AE21+AG21+AI21+AK21+AM21+AO21+AQ21+AS21+AU21+AW21+AY21+BA21+BC21+BE21+BG21+BI21+BK21+BM21+BO21+BQ21+BS21+BU21 -> 0
A22: 034.861-00 | B22: 2022/0033315-001A | C22: G | D22: 2022/0033315 | E22: FQH5J83 | F22: 01/04/2026 | G22: 30/04/2026 | H22: BRUNO EDUARDO BARBOSA | I22: BRUNO EDUARDO BARBOSA | J22: NORMAL | K22: EMEF | L22: 0 | M22: 0 | N22: 0 | O22: 0 | P22: 0 | Q22: 0 | V22: 4 | W22: 0 | X22: 0 | Y22: 0 | Z22: 0 | AA22: 0 | AB22: 0 | AC22: 0 | AD22: 0 | AE22: 0 | AJ22: 4 | AK22: 0 | AL22: 0 | AM22: 0 | AN22: 0 | AO22: 0 | AP22: 0 | AQ22: 0 | AR22: 0 | AS22: 0 | AX22: 4 | AY22: 0 | AZ22: 0 | BA22: 0 | BB22: 0 | BC22: 0 | BD22: 0 | BE22: 0 | BF22: 0 | BG22: 0 | BL22: 4 | BM22: 0 | BN22: 0 | BO22: 0 | BP22: 0 | BQ22: 0 | BR22: 0 | BS22: 0 | BV22: =L22+N22+P22+R22+T22+V22+X22+Z22+AB22+AD22+AF22+AH22+AJ22+AL22+AN22+AP22+AR22+AT22+AV22+AX22+AZ22+BB22+BD22+BF22+BH22+BJ22+BL22+BN22+BP22+BR22+BT22 -> 16 | BW22: =M22+O22+Q22+S22+U22+W22+Y22+AA22+AC22+AE22+AG22+AI22+AK22+AM22+AO22+AQ22+AS22+AU22+AW22+AY22+BA22+BC22+BE22+BG22+BI22+BK22+BM22+BO22+BQ22+BS22+BU22 -> 0
A23: 034.861-00 | B23: 2022/0033315-001A | C23: G | D23: 2022/0033315 | E23: FQH5J83 | F23: 01/04/2026 | G23: 30/04/2026 | H23: BRUNO EDUARDO BARBOSA | I23: BRUNO EDUARDO BARBOSA | J23: NORMAL | K23: EMEE | L23: 0 | M23: 0 | N23: 0 | O23: 0 | P23: 0 | Q23: 0 | V23: 0 | W23: 0 | X23: 0 | Y23: 0 | Z23: 0 | AA23: 0 | AB23: 0 | AC23: 0 | AD23: 0 | AE23: 0 | AJ23: 0 | AK23: 0 | AL23: 0 | AM23: 0 | AN23: 0 | AO23: 0 | AP23: 0 | AQ23: 0 | AR23: 0 | AS23: 0 | AX23: 0 | AY23: 0 | AZ23: 0 | BA23: 0 | BB23: 0 | BC23: 0 | BD23: 0 | BE23: 0 | BF23: 0 | BG23: 0 | BL23: 0 | BM23: 0 | BN23: 0 | BO23: 0 | BP23: 0 | BQ23: 0 | BR23: 0 | BS23: 0 | BV23: =L23+N23+P23+R23+T23+V23+X23+Z23+AB23+AD23+AF23+AH23+AJ23+AL23+AN23+AP23+AR23+AT23+AV23+AX23+AZ23+BB23+BD23+BF23+BH23+BJ23+BL23+BN23+BP23+BR23+BT23 -> 0 | BW23: =M23+O23+Q23+S23+U23+W23+Y23+AA23+AC23+AE23+AG23+AI23+AK23+AM23+AO23+AQ23+AS23+AU23+AW23+AY23+BA23+BC23+BE23+BG23+BI23+BK23+BM23+BO23+BQ23+BS23+BU23 -> 0
A24: 034.861-00 | B24: 2022/0033315-001A | C24: G | D24: 2022/0033315 | E24: FQH5J83 | F24: 01/04/2026 | G24: 30/04/2026 | H24: BRUNO EDUARDO BARBOSA | I24: BRUNO EDUARDO BARBOSA | J24: NORMAL | K24: CEI | L24: 0 | M24: 0 | N24: 0 | O24: 0 | P24: 0 | Q24: 0 | V24: 0 | W24: 0 | X24: 0 | Y24: 0 | Z24: 0 | AA24: 0 | AB24: 0 | AC24: 0 | AD24: 0 | AE24: 0 | AJ24: 0 | AK24: 0 | AL24: 0 | AM24: 0 | AN24: 0 | AO24: 0 | AP24: 0 | AQ24: 0 | AR24: 0 | AS24: 0 | AX24: 0 | AY24: 0 | AZ24: 0 | BA24: 0 | BB24: 0 | BC24: 0 | BD24: 0 | BE24: 0 | BF24: 0 | BG24: 0 | BL24: 0 | BM24: 0 | BN24: 0 | BO24: 0 | BP24: 0 | BQ24: 0 | BR24: 0 | BS24: 0 | BV24: =L24+N24+P24+R24+T24+V24+X24+Z24+AB24+AD24+AF24+AH24+AJ24+AL24+AN24+AP24+AR24+AT24+AV24+AX24+AZ24+BB24+BD24+BF24+BH24+BJ24+BL24+BN24+BP24+BR24+BT24 -> 0 | BW24: =M24+O24+Q24+S24+U24+W24+Y24+AA24+AC24+AE24+AG24+AI24+AK24+AM24+AO24+AQ24+AS24+AU24+AW24+AY24+BA24+BC24+BE24+BG24+BI24+BK24+BM24+BO24+BQ24+BS24+BU24 -> 0
A25: 034.861-00 | B25: 2022/0033315-001A | C25: G | D25: 2022/0033315 | E25: FQH5J83 | F25: 01/04/2026 | G25: 30/04/2026 | H25: BRUNO EDUARDO BARBOSA | I25: BRUNO EDUARDO BARBOSA | J25: NORMAL | K25: CCA | L25: 0 | M25: 0 | N25: 0 | O25: 0 | P25: 0 | Q25: 0 | V25: 0 | W25: 0 | X25: 0 | Y25: 0 | Z25: 0 | AA25: 0 | AB25: 0 | AC25: 0 | AD25: 0 | AE25: 0 | AJ25: 0 | AK25: 0 | AL25: 0 | AM25: 0 | AN25: 0 | AO25: 0 | AP25: 0 | AQ25: 0 | AR25: 0 | AS25: 0 | AX25: 0 | AY25: 0 | AZ25: 0 | BA25: 0 | BB25: 0 | BC25: 0 | BD25: 0 | BE25: 0 | BF25: 0 | BG25: 0 | BL25: 0 | BM25: 0 | BN25: 0 | BO25: 0 | BP25: 0 | BQ25: 0 | BR25: 0 | BS25: 0 | BV25: =L25+N25+P25+R25+T25+V25+X25+Z25+AB25+AD25+AF25+AH25+AJ25+AL25+AN25+AP25+AR25+AT25+AV25+AX25+AZ25+BB25+BD25+BF25+BH25+BJ25+BL25+BN25+BP25+BR25+BT25 -> 0 | BW25: =M25+O25+Q25+S25+U25+W25+Y25+AA25+AC25+AE25+AG25+AI25+AK25+AM25+AO25+AQ25+AS25+AU25+AW25+AY25+BA25+BC25+BE25+BG25+BI25+BK25+BM25+BO25+BQ25+BS25+BU25 -> 0
A26: 020.989-00 | B26: 2022/0034309-001B | C26: 2 | D26: 2022/0034309 | E26: FRC8739 | F26: 01/04/2026 | G26: 30/04/2026 | H26: CARLOS ALBERTO DE ARAUJO | I26: CARLOS ALBERTO DE ARAUJO | J26: ADAPTADO | K26: EMEI | L26: 0 | M26: 0 | N26: 0 | O26: 0 | P26: 0 | Q26: 0 | V26: 0 | W26: 0 | X26: 0 | Y26: 0 | Z26: 0 | AA26: 0 | AB26: 0 | AC26: 0 | AD26: 0 | AE26: 0 | AJ26: 0 | AK26: 0 | AL26: 0 | AM26: 0 | AN26: 0 | AO26: 0 | AP26: 0 | AQ26: 0 | AR26: 0 | AS26: 0 | AX26: 0 | AY26: 0 | AZ26: 0 | BA26: 0 | BB26: 0 | BC26: 0 | BD26: 0 | BE26: 0 | BF26: 0 | BG26: 0 | BL26: 0 | BM26: 0 | BN26: 0 | BO26: 0 | BP26: 0 | BQ26: 0 | BR26: 0 | BS26: 0 | BV26: =L26+N26+P26+R26+T26+V26+X26+Z26+AB26+AD26+AF26+AH26+AJ26+AL26+AN26+AP26+AR26+AT26+AV26+AX26+AZ26+BB26+BD26+BF26+BH26+BJ26+BL26+BN26+BP26+BR26+BT26 -> 0 | BW26: =M26+O26+Q26+S26+U26+W26+Y26+AA26+AC26+AE26+AG26+AI26+AK26+AM26+AO26+AQ26+AS26+AU26+AW26+AY26+BA26+BC26+BE26+BG26+BI26+BK26+BM26+BO26+BQ26+BS26+BU26 -> 0
A27: 020.989-00 | B27: 2022/0034309-001B | C27: G | D27: 2022/0034309 | E27: FRC8739 | F27: 01/04/2026 | G27: 30/04/2026 | H27: CARLOS ALBERTO DE ARAUJO | I27: CARLOS ALBERTO DE ARAUJO | J27: ADAPTADO | K27: EMEF | L27: 0 | M27: 0 | N27: 0 | O27: 0 | P27: 0 | Q27: 0 | V27: 0 | W27: 0 | X27: 0 | Y27: 0 | Z27: 0 | AA27: 0 | AB27: 0 | AC27: 0 | AD27: 0 | AE27: 0 | AJ27: 0 | AK27: 0 | AL27: 0 | AM27: 0 | AN27: 0 | AO27: 0 | AP27: 0 | AQ27: 0 | AR27: 0 | AS27: 0 | AX27: 0 | AY27: 0 | AZ27: 0 | BA27: 0 | BB27: 0 | BC27: 0 | BD27: 0 | BE27: 0 | BF27: 0 | BG27: 0 | BL27: 0 | BM27: 0 | BN27: 0 | BO27: 0 | BP27: 0 | BQ27: 0 | BR27: 0 | BS27: 0 | BV27: =L27+N27+P27+R27+T27+V27+X27+Z27+AB27+AD27+AF27+AH27+AJ27+AL27+AN27+AP27+AR27+AT27+AV27+AX27+AZ27+BB27+BD27+BF27+BH27+BJ27+BL27+BN27+BP27+BR27+BT27 -> 0 | BW27: =M27+O27+Q27+S27+U27+W27+Y27+AA27+AC27+AE27+AG27+AI27+AK27+AM27+AO27+AQ27+AS27+AU27+AW27+AY27+BA27+BC27+BE27+BG27+BI27+BK27+BM27+BO27+BQ27+BS27+BU27 -> 0
A28: 020.989-00 | B28: 2022/0034309-001B | C28: G | D28: 2022/0034309 | E28: FRC8739 | F28: 01/04/2026 | G28: 30/04/2026 | H28: CARLOS ALBERTO DE ARAUJO | I28: CARLOS ALBERTO DE ARAUJO | J28: ADAPTADO | K28: EMEE | L28: 0 | M28: 0 | N28: 0 | O28: 0 | P28: 0 | Q28: 0 | V28: 0 | W28: 0 | X28: 0 | Y28: 0 | Z28: 0 | AA28: 0 | AB28: 0 | AC28: 0 | AD28: 0 | AE28: 0 | AJ28: 0 | AK28: 0 | AL28: 0 | AM28: 0 | AN28: 0 | AO28: 0 | AP28: 0 | AQ28: 0 | AR28: 0 | AS28: 0 | AX28: 0 | AY28: 0 | AZ28: 0 | BA28: 0 | BB28: 0 | BC28: 0 | BD28: 0 | BE28: 0 | BF28: 0 | BG28: 0 | BL28: 0 | BM28: 0 | BN28: 0 | BO28: 0 | BP28: 0 | BQ28: 0 | BR28: 0 | BS28: 0 | BV28: =L28+N28+P28+R28+T28+V28+X28+Z28+AB28+AD28+AF28+AH28+AJ28+AL28+AN28+AP28+AR28+AT28+AV28+AX28+AZ28+BB28+BD28+BF28+BH28+BJ28+BL28+BN28+BP28+BR28+BT28 -> 0 | BW28: =M28+O28+Q28+S28+U28+W28+Y28+AA28+AC28+AE28+AG28+AI28+AK28+AM28+AO28+AQ28+AS28+AU28+AW28+AY28+BA28+BC28+BE28+BG28+BI28+BK28+BM28+BO28+BQ28+BS28+BU28 -> 0
A29: 020.989-00 | B29: 2022/0034309-001B | C29: G | D29: 2022/0034309 | E29: FRC8739 | F29: 01/04/2026 | G29: 30/04/2026 | H29: CARLOS ALBERTO DE ARAUJO | I29: CARLOS ALBERTO DE ARAUJO | J29: ADAPTADO | K29: CEI | L29: 0 | M29: 0 | N29: 0 | O29: 0 | P29: 0 | Q29: 0 | V29: 0 | W29: 0 | X29: 0 | Y29: 0 | Z29: 0 | AA29: 0 | AB29: 0 | AC29: 0 | AD29: 0 | AE29: 0 | AJ29: 0 | AK29: 0 | AL29: 0 | AM29: 0 | AN29: 0 | AO29: 0 | AP29: 0 | AQ29: 0 | AR29: 0 | AS29: 0 | AX29: 0 | AY29: 0 | AZ29: 0 | BA29: 0 | BB29: 0 | BC29: 0 | BD29: 0 | BE29: 0 | BF29: 0 | BG29: 0 | BL29: 0 | BM29: 0 | BN29: 0 | BO29: 0 | BP29: 0 | BQ29: 0 | BR29: 0 | BS29: 0 | BV29: =L29+N29+P29+R29+T29+V29+X29+Z29+AB29+AD29+AF29+AH29+AJ29+AL29+AN29+AP29+AR29+AT29+AV29+AX29+AZ29+BB29+BD29+BF29+BH29+BJ29+BL29+BN29+BP29+BR29+BT29 -> 0 | BW29: =M29+O29+Q29+S29+U29+W29+Y29+AA29+AC29+AE29+AG29+AI29+AK29+AM29+AO29+AQ29+AS29+AU29+AW29+AY29+BA29+BC29+BE29+BG29+BI29+BK29+BM29+BO29+BQ29+BS29+BU29 -> 0
A30: 020.989-00 | B30: 2022/0034309-001B | C30: G | D30: 2022/0034309 | E30: FRC8739 | F30: 01/04/2026 | G30: 30/04/2026 | H30: CARLOS ALBERTO DE ARAUJO | I30: CARLOS ALBERTO DE ARAUJO | J30: ADAPTADO | K30: CCA | L30: 0 | M30: 0 | N30: 0 | O30: 0 | P30: 0 | Q30: 0 | V30: 0 | W30: 0 | X30: 0 | Y30: 0 | Z30: 0 | AA30: 0 | AB30: 0 | AC30: 0 | AD30: 0 | AE30: 0 | AJ30: 0 | AK30: 0 | AL30: 0 | AM30: 0 | AN30: 0 | AO30: 0 | AP30: 0 | AQ30: 0 | AR30: 0 | AS30: 0 | AX30: 0 | AY30: 0 | AZ30: 0 | BA30: 0 | BB30: 0 | BC30: 0 | BD30: 0 | BE30: 0 | BF30: 0 | BG30: 0 | BL30: 0 | BM30: 0 | BN30: 0 | BO30: 0 | BP30: 0 | BQ30: 0 | BR30: 0 | BS30: 0 | BV30: =L30+N30+P30+R30+T30+V30+X30+Z30+AB30+AD30+AF30+AH30+AJ30+AL30+AN30+AP30+AR30+AT30+AV30+AX30+AZ30+BB30+BD30+BF30+BH30+BJ30+BL30+BN30+BP30+BR30+BT30 -> 0 | BW30: =M30+O30+Q30+S30+U30+W30+Y30+AA30+AC30+AE30+AG30+AI30+AK30+AM30+AO30+AQ30+AS30+AU30+AW30+AY30+BA30+BC30+BE30+BG30+BI30+BK30+BM30+BO30+BQ30+BS30+BU30 -> 0
A31: 017.507-00 | B31: 2022/0032326-001 | C31: 2 | D31: 2022/0032326 | E31: ECT4953 | F31: 01/04/2026 | G31: 30/04/2026 | H31: CARLOS GONCALVES DOS SANTOS | I31: CARLOS GONCALVES DOS SANTOS | J31: ADAPTADO | K31: EMEI | L31: 0 | M31: 0 | N31: 0 | O31: 0 | P31: 0 | Q31: 0 | V31: 0 | W31: 1 | X31: 0 | Y31: 0 | Z31: 0 | AA31: 0 | AB31: 0 | AC31: 0 | AD31: 0 | AE31: 0 | AJ31: 0 | AK31: 1 | AL31: 0 | AM31: 0 | AN31: 0 | AO31: 0 | AP31: 0 | AQ31: 0 | AR31: 0 | AS31: 0 | AX31: 0 | AY31: 1 | AZ31: 0 | BA31: 0 | BB31: 0 | BC31: 0 | BD31: 0 | BE31: 0 | BF31: 0 | BG31: 0 | BL31: 0 | BM31: 1 | BN31: 0 | BO31: 0 | BP31: 0 | BQ31: 0 | BR31: 0 | BS31: 0 | BV31: =L31+N31+P31+R31+T31+V31+X31+Z31+AB31+AD31+AF31+AH31+AJ31+AL31+AN31+AP31+AR31+AT31+AV31+AX31+AZ31+BB31+BD31+BF31+BH31+BJ31+BL31+BN31+BP31+BR31+BT31 -> 0 | BW31: =M31+O31+Q31+S31+U31+W31+Y31+AA31+AC31+AE31+AG31+AI31+AK31+AM31+AO31+AQ31+AS31+AU31+AW31+AY31+BA31+BC31+BE31+BG31+BI31+BK31+BM31+BO31+BQ31+BS31+BU31 -> 4
A32: 017.507-00 | B32: 2022/0032326-001 | C32: G | D32: 2022/0032326 | E32: ECT4953 | F32: 01/04/2026 | G32: 30/04/2026 | H32: CARLOS GONCALVES DOS SANTOS | I32: CARLOS GONCALVES DOS SANTOS | J32: ADAPTADO | K32: EMEF | L32: 0 | M32: 0 | N32: 0 | O32: 0 | P32: 0 | Q32: 0 | V32: 3 | W32: 0 | X32: 0 | Y32: 0 | Z32: 0 | AA32: 0 | AB32: 0 | AC32: 0 | AD32: 0 | AE32: 0 | AJ32: 3 | AK32: 0 | AL32: 0 | AM32: 0 | AN32: 0 | AO32: 0 | AP32: 0 | AQ32: 0 | AR32: 0 | AS32: 0 | AX32: 3 | AY32: 0 | AZ32: 0 | BA32: 0 | BB32: 0 | BC32: 0 | BD32: 0 | BE32: 0 | BF32: 0 | BG32: 0 | BL32: 3 | BM32: 0 | BN32: 0 | BO32: 0 | BP32: 0 | BQ32: 0 | BR32: 0 | BS32: 0 | BV32: =L32+N32+P32+R32+T32+V32+X32+Z32+AB32+AD32+AF32+AH32+AJ32+AL32+AN32+AP32+AR32+AT32+AV32+AX32+AZ32+BB32+BD32+BF32+BH32+BJ32+BL32+BN32+BP32+BR32+BT32 -> 12 | BW32: =M32+O32+Q32+S32+U32+W32+Y32+AA32+AC32+AE32+AG32+AI32+AK32+AM32+AO32+AQ32+AS32+AU32+AW32+AY32+BA32+BC32+BE32+BG32+BI32+BK32+BM32+BO32+BQ32+BS32+BU32 -> 0
A33: 017.507-00 | B33: 2022/0032326-001 | C33: G | D33: 2022/0032326 | E33: ECT4953 | F33: 01/04/2026 | G33: 30/04/2026 | H33: CARLOS GONCALVES DOS SANTOS | I33: CARLOS GONCALVES DOS SANTOS | J33: ADAPTADO | K33: EMEE | L33: 0 | M33: 0 | N33: 0 | O33: 0 | P33: 0 | Q33: 0 | V33: 0 | W33: 0 | X33: 0 | Y33: 0 | Z33: 0 | AA33: 0 | AB33: 0 | AC33: 0 | AD33: 0 | AE33: 0 | AJ33: 0 | AK33: 0 | AL33: 0 | AM33: 0 | AN33: 0 | AO33: 0 | AP33: 0 | AQ33: 0 | AR33: 0 | AS33: 0 | AX33: 0 | AY33: 0 | AZ33: 0 | BA33: 0 | BB33: 0 | BC33: 0 | BD33: 0 | BE33: 0 | BF33: 0 | BG33: 0 | BL33: 0 | BM33: 0 | BN33: 0 | BO33: 0 | BP33: 0 | BQ33: 0 | BR33: 0 | BS33: 0 | BV33: =L33+N33+P33+R33+T33+V33+X33+Z33+AB33+AD33+AF33+AH33+AJ33+AL33+AN33+AP33+AR33+AT33+AV33+AX33+AZ33+BB33+BD33+BF33+BH33+BJ33+BL33+BN33+BP33+BR33+BT33 -> 0 | BW33: =M33+O33+Q33+S33+U33+W33+Y33+AA33+AC33+AE33+AG33+AI33+AK33+AM33+AO33+AQ33+AS33+AU33+AW33+AY33+BA33+BC33+BE33+BG33+BI33+BK33+BM33+BO33+BQ33+BS33+BU33 -> 0
A34: 017.507-00 | B34: 2022/0032326-001 | C34: G | D34: 2022/0032326 | E34: ECT4953 | F34: 01/04/2026 | G34: 30/04/2026 | H34: CARLOS GONCALVES DOS SANTOS | I34: CARLOS GONCALVES DOS SANTOS | J34: ADAPTADO | K34: CEI | L34: 0 | M34: 0 | N34: 0 | O34: 0 | P34: 0 | Q34: 0 | V34: 0 | W34: 0 | X34: 0 | Y34: 0 | Z34: 0 | AA34: 0 | AB34: 0 | AC34: 0 | AD34: 0 | AE34: 0 | AJ34: 0 | AK34: 0 | AL34: 0 | AM34: 0 | AN34: 0 | AO34: 0 | AP34: 0 | AQ34: 0 | AR34: 0 | AS34: 0 | AX34: 0 | AY34: 0 | AZ34: 0 | BA34: 0 | BB34: 0 | BC34: 0 | BD34: 0 | BE34: 0 | BF34: 0 | BG34: 0 | BL34: 0 | BM34: 0 | BN34: 0 | BO34: 0 | BP34: 0 | BQ34: 0 | BR34: 0 | BS34: 0 | BV34: =L34+N34+P34+R34+T34+V34+X34+Z34+AB34+AD34+AF34+AH34+AJ34+AL34+AN34+AP34+AR34+AT34+AV34+AX34+AZ34+BB34+BD34+BF34+BH34+BJ34+BL34+BN34+BP34+BR34+BT34 -> 0 | BW34: =M34+O34+Q34+S34+U34+W34+Y34+AA34+AC34+AE34+AG34+AI34+AK34+AM34+AO34+AQ34+AS34+AU34+AW34+AY34+BA34+BC34+BE34+BG34+BI34+BK34+BM34+BO34+BQ34+BS34+BU34 -> 0
