Workbook
Name \a: #REF!
Name \a: #REF!
Name \p: #REF!
Name \p: #REF!
Name _______xlnm.Print_Titles: #REF!
Name _______xlnm_Print_Titles: NA()
Name ______xlnm._FilterDatabase: "#ref!"
Name ______xlnm.Print_Titles: #REF!
Name ______xlnm__FilterDatabase: "#ref!"
Name ______xlnm_Print_Titles: NA()
Name _____xlfn_BAHTTEXT: NA()
Name _____xlfn_SUMIFS: NA()
Name _____xlnm._FilterDatabase: "#ref!"
Name _____xlnm.Print_Titles: #REF!
Name _____xlnm__FilterDatabase: "#ref!"
Name _____xlnm_Print_Titles: NA()
Name ____xlfn_BAHTTEXT: NA()
Name ____xlfn_SUMIFS: NA()
Name ____xlnm._FilterDatabase: "#ref!"
Name ____xlnm.Print_Titles: #REF!
Name ____xlnm__FilterDatabase: "#ref!"
Name ____xlnm_Print_Titles: NA()
Name ___xlfn_BAHTTEXT: NA()
Name ___xlfn_SUMIFS: NA()
Name ___xlnm._FilterDatabase: "#ref!"
Name ___xlnm.Print_Titles: #REF!
Name ___xlnm__FilterDatabase: "#ref!"
Name ___xlnm_Print_Titles: NA()
Name __TAB3688: #REF!
Name __xlfn_BAHTTEXT: NA()
Name __xlfn_SUMIFS: NA()
Name __xlnm._FilterDatabase: "#ref!"
Name __xlnm.Print_Titles: #REF!
Name __xlnm__FilterDatabase: "#ref!"
Name __xlnm_Print_Titles: NA()
Name _TAB3688: #REF!
Name _TAB3688: #REF!
Name a: #REF!
Name abr: #REF!
Name abr: #REF!
Name abril: #REF!
Name ACRESCENTAR: #REF!
Name ADAPTADO: '[1]APONTAMENTO CREDENCIAMENTO'!#REF!
Name ADAPTADO: 'APONTAMENTO CREDENCIAMENTO'!$FH$7:$GM$7
Name AGOSTO: #REF!
Name AI: #REF!
Name AI: #REF!
Name AII: #REF!
Name AII: #REF!
Name AK: #REF!
Name AK: #REF!
Name AL: #REF!
Name AL: #REF!
Name AMPLIAR: #REF!
Name AMPLIAR: #REF!
Name ApagaAtesteFis: 'ATESTE-LIQ-FIS'!$A$4:$K$3908
Name ApagaBaseC: 'BASE C'!$A$11:$N$4950
Name ApagaDadosA: 'APONTAMENTO CREDENCIAMENTO'!$Q$6:$EL$2822
Name ApagaDadosC: CONTINUA!$L$6:$BU$2883
Name ApagarDadosDigitados: #REF!

Sheet APONTAMENTO CREDENCIAMENTO
A1: Freguesia / Brasilândia | G1: ='BASE C'!E4 -> ABRIL | I1: APONTAMENTO CREDENCIAMENTO | EL1: ATENÇÃO
G2: 01/06 a 30/06/2025
A3: 1 | B3: =A3+1 -> 2 | C3: =B3+1 -> 3 | D3: 1 | E3: =D3+1 -> 2 | F3: =E3+1 -> 3 | G3: =F3+1 -> 4 | H3: =G3+1 -> 5 | I3: =H3+1 -> 6 | J3: =I3+1 -> 7 | K3: =J3+1 -> 8 | L3: =K3+1 -> 9 | M3: =L3+1 -> 10 | N3: 10 | O3: =N3+1 -> 11 | P3: 13 | Q3: =P3+1 -> 14 | R3: =Q3+1 -> 15 | S3: =R3+1 -> 16 | T3: =S3+1 -> 17 | U3: =T3+1 -> 18 | V3: =U3+1 -> 19 | W3: =V3+1 -> 20 | X3: =W3+1 -> 21 | ... EL3: =EK3+1 -> 139 | EM3: 140 | EN3: =EM3+1 -> 141 | EO3: =EN3+1 -> 142 | EP3: =EO3+1 -> 143 | EQ3: =EP3+1 -> 144 | ER3: =EQ3+1 -> 145 | ES3: =ER3+1 -> 146 | ET3: =ES3+1 -> 147 | EU3: =ET3+1 -> 148 | ... FD3: =FC3+1 -> 157 | FF3: =FD3+1 -> 158 | FH3: =FF3+1 -> 159 | FI3: =FH3+1 -> 160 | FJ3: =FI3+1 -> 161 | FL3: =FJ3+1 -> 162 | FM3: =FL3+1 -> 163 | FN3: =FM3+1 -> 164 | FO3: =FN3+1 -> 165 | FP3: =FO3+1 -> 166 | FQ3: =FP3+1 -> 167 | FR3: =FQ3+1 -> 168 | FS3: =FR3+1 -> 169 | FT3: =FS3+1 -> 170 | ... ID3: =IC3+1 -> 232
A4: CRMC | B4: OS | C4: DRE | D4: CONTRATO | E4: PLACA | F4: PERÍODO | H4: EMPRESA | I4: NOME CONDUTOR | J4: TIPO DE VEÍCULO (NORMAL, ADAPTADO) | K4: TIPO DE ATENDIMENTO | L4: TOTAL CONT REG | M4: TOTAL CONT CAD | N4: KM ADICIONAL | O4: SEI | P4: Tipo Optante | Q4: =F5 -> 01/04/2026 | U4: =Q4+1 -> 46114 | Y4: =U4+1 -> 46115 | AC4: =Y4+1 -> 46116 | AG4: =AC4+1 -> 46117 | AK4: =AG4+1 -> 46118 | AO4: =AK4+1 -> 46119 | AS4: =AO4+1 -> 46120 | AW4: =AS4+1 -> 46121 | BA4: =AW4+1 -> 46122 | BE4: =BA4+1 -> 46123 | BI4: =BE4+1 -> 46124 | BM4: =BI4+1 -> 46125 | BQ4: =BM4+1 -> 46126 | BU4: =BQ4+1 -> 46127 | BY4: =BU4+1 -> 46128 | CC4: =BY4+1 -> 46129 | CG4: =CC4+1 -> 46130 | CK4: =CG4+1 -> 46131 | CO4: =CK4+1 -> 46132 | CS4: =CO4+1 -> 46133 | CW4: =CS4+1 -> 46134 | DA4: =CW4+1 -> 46135 | DE4: =DA4+1 -> 46136 | DI4: =DE4+1 -> 46137 | DM4: =DI4+1 -> 46138 | DQ4: =DM4+1 -> 46139 | DU4: =DQ4+1 -> 46140 | DY4: =DU4+1 -> 46141 | EC4: =DY4+1 -> 46142 | EK4: FALTAS - APONTAR AS DATAS | EL4: OBSERVAÇÕES ALUNO PRESENCIAL COLUNAS FINAIS | EM4: Ajuste positivo | EN4: Ajuste negativo | EO4: Desconto faltas | EP4: TOTAL ALUNOS N CAD(30 DIAS) | EQ4: TOTAL ALUNOS N CAD(MENOS DE 30 DIAS) | ER4: TOTAL ALUNOS ATIV.COMPL. N CAD | ES4: TOTAL ALUNOS CAD (30 DIAS) | ET4: TOTAL ALUNOS CAD (MENOS DE 30 DIAS) | EU4: TOTAL ALUNOS ATIV.COMPL. CAD | EV4: TOTAL GERAL | EW4: Contratos Especiais (Valor fixo) | EX4: Valor total alunos presenciais (30 dias) | EY4: Ativ.Complementar Continuada | EZ4: Valor alunos presenciais (menos de 30 dias) | FA4: Saida de alunos ao longo do mês | FB4: CCA | FC4: Valor km adicional | FD4: Outros apontamentos | FF4: VALOR ATESTE | FH4: 30 | FI4: =FH4-1 -> 29 | FJ4: =FI4-1 -> 28 | FL4: =FJ4-1 -> 27 | FM4: =FL4-1 -> 26 | FN4: =FM4-1 -> 25 | FO4: =FN4-1 -> 24 | FP4: =FO4-1 -> 23 | FQ4: =FP4-1 -> 22 | FR4: =FQ4-1 -> 21 | FS4: =FR4-1 -> 20 | FT4: =FS4-1 -> 19 | ... GL4: =GK4-1 -> 1 | GM4: 1 | GN4: Multa Contratual | GO4: CÁLCULO | GP4: DIAS | GQ4: 29 | GR4: =GQ4-1 -> 28 | GS4: =GR4-1 -> 27 | GT4: =GS4-1 -> 26 | GU4: =GT4-1 -> 25 | GV4: =GU4-1 -> 24 | GW4: =GV4-1 -> 23 | GX4: =GW4-1 -> 22 | GY4: =GX4-1 -> 21 | ... HS4: =HR4-1 -> 1 | HZ4: VALOR ATESTE | IB4: Ajuste positivo | IC4: Ajuste negativo | ID4: Desconto faltas
F5: 01/04/2026 | G5: 30/04/2026 | Q5: N CAD presencial | R5: CAD | S5: AT. COMPL. N CAD | T5: AT. COMPL. CAD | U5: N CAD presencial | V5: CAD | W5: AT. COMPL. N CAD | X5: AT. COMPL. CAD | Y5: N CAD presencial | Z5: CAD | AA5: AT. COMPL. N CAD | AB5: AT. COMPL. CAD | AC5: N CAD presencial | AD5: CAD | AE5: AT. COMPL. N CAD | AF5: AT. COMPL. CAD | AG5: N CAD presencial | AH5: CAD | AI5: AT. COMPL. N CAD | AJ5: AT. COMPL. CAD | AK5: N CAD presencial | AL5: CAD | AM5: AT. COMPL. N CAD | AN5: AT. COMPL. CAD | AO5: N CAD presencial | AP5: CAD | AQ5: AT. COMPL. N CAD | AR5: AT. COMPL. CAD | AS5: N CAD presencial | AT5: CAD | AU5: AT. COMPL. N CAD | AV5: AT. COMPL. CAD | AW5: N CAD presencial | AX5: CAD | AY5: AT. COMPL. N CAD | AZ5: AT. COMPL. CAD | BA5: N CAD presencial | BB5: CAD | BC5: AT. COMPL. N CAD | BD5: AT. COMPL. CAD | BE5: N CAD presencial | BF5: CAD | BG5: AT. COMPL. N CAD | BH5: AT. COMPL. CAD | BI5: N CAD presencial | BJ5: CAD | BK5: AT. COMPL. N CAD | BL5: AT. COMPL. CAD | BM5: N CAD presencial | BN5: CAD | BO5: AT. COMPL. N CAD | BP5: AT. COMPL. CAD | BQ5: N CAD presencial | BR5: CAD | BS5: AT. COMPL. N CAD | BT5: AT. COMPL. CAD | BU5: N CAD presencial | BV5: CAD | BW5: AT. COMPL. N CAD | BX5: AT. COMPL. CAD | BY5: N CAD presencial | BZ5: CAD | CA5: AT. COMPL. N CAD | CB5: AT. COMPL. CAD | CC5: N CAD presencial | CD5: CAD | CE5: AT. COMPL. N CAD | CF5: AT. COMPL. CAD | CG5: N CAD presencial | CH5: CAD | CI5: AT. COMPL. N CAD | CJ5: AT. COMPL. CAD | CK5: N CAD presencial | CL5: CAD | CM5: AT. COMPL. N CAD | CN5: AT. COMPL. CAD | CO5: N CAD presencial | CP5: CAD | CQ5: AT. COMPL. N CAD | CR5: AT. COMPL. CAD | CS5: N CAD presencial | CT5: CAD | CU5: AT. COMPL. N CAD | CV5: AT. COMPL. CAD | CW5: N CAD presencial | CX5: CAD | CY5: AT. COMPL. N CAD | CZ5: AT. COMPL. CAD | DA5: N CAD presencial | DB5: CAD | DC5: AT. COMPL. N CAD | DD5: AT. COMPL. CAD | DE5: N CAD presencial | DF5: CAD | DG5: AT. COMPL. N CAD | DH5: AT. COMPL. CAD | DI5: N CAD presencial | DJ5: CAD | DK5: AT. COMPL. N CAD | DL5: AT. COMPL. CAD | DM5: N CAD presencial | DN5: CAD | DO5: AT. COMPL. N CAD | DP5: AT. COMPL. CAD | DQ5: N CAD presencial | DR5: CAD | DS5: AT. COMPL. N CAD | DT5: AT. COMPL. CAD | DU5: N CAD presencial | DV5: CAD | DW5: AT. COMPL. N CAD | DX5: AT. COMPL. CAD | DY5: N CAD presencial | DZ5: CAD | EA5: AT. COMPL. N CAD | EB5: AT. COMPL. CAD | EC5: N CAD presencial | ED5: CAD | EE5: AT. COMPL. N CAD | EF5: AT. COMPL. CAD | EG5: N CAD presencial | EH5: CAD | EI5: AT. COMPL. N CAD | EJ5: AT. COMPL. CAD
A6: 029.007-00 | B6: 2025/0018729-001 | C6: 1 | D6: 2025/0018729 | E6: DTE1882 | F6: 01/04/2026 | G6: 30/04/2026 | H6: 25.292.508 CLAUDIA COSTA BORCA | I6: CLAUDIA COSTA BORCA | J6: NORMAL | K6: EMEI | L6: =CONTINUA!BV6 -> 0 | M6: =CONTINUA!BW6 -> 0 | O6: 6020.2025/0018729-5 | P6: O | EP6: =Q6 -> 0 | EQ6: =U6+Y6+AC6+AG6+AK6+AO6+AS6+AW6+BA6+BE6+BI6+BM6+BQ6+BU6+BY6+CC6+CG6+CK6+CO6+CS6+CW6+DA6+DE6+DI6+DM6+DQ6+DU6+DY6+EC6+EG6 -> 0 | ER6: =S6+W6+AA6+AE6+AI6+AM6+AQ6+AU6+AY6+BC6+BG6+BK6+BO6+BS6+BW6+CA6+CE6+CI6+CM6+CQ6+CU6+CY6+DC6+DG6+DK6+DO6+DS6+DW6+EA6+EE6+EI6 -> 0 | ES6: =R6 -> 0 | ET6: =V6+Z6+AD6+AH6+AL6+AP6+AT6+AX6+BB6+BF6+BJ6+BN6+BR6+BV6+BZ6+CD6+CH6+CL6+CP6+CT6+CX6+DB6+DF6+DJ6+DN6+DR6+DV6+DZ6+ED6+EH6 -> 0 | EU6: =T6+X6+AB6+AF6+AJ6+AN6+AR6+AV6+AZ6+BD6+BH6+BL6+BP6+BT6+BX6+CB6+CF6+CJ6+CN6+CR6+CV6+CZ6+DD6+DH6+DL6+DP6+DT6+DX6+EB6+EF6+EJ6 -> 0 | EV6: =EP6+EQ6+ES6+ET6+ER6+EU6 -> 0 | EW6: =IF(C6=4,IF(MAX(Q6:EJ8)>0,(Especiall/30*(IF(($G6-$F6)=($G$5-$F$5),30,IF(DAY($G6)=31,($G6-$F6),($G6-$F6)+1)))),0),0) -> 0 | EX6: =FH6 -> 0 | EY6: =(L6*regular)+(M6*Cadeirantee) -> 0 | EZ6: =SUMIF(FI6:GM6,">0") -> 603.527 | FA6: =SUMIF(FI6:GM6,"<0")+SUMIF(GQ6:HS6,"<0") -> -218.297 | FB6: 0 | FC6: =N6*km*'VALORES TABELA'!$B$13 -> 0 | FD6: =GO6 -> 0 | FF6: =(EW6+EW7+EW8+EW9+EX6+EX7+EX8+EX9+EY6+EY7+EY8+EY9+EY10+EZ6+EZ7+EZ8+EZ9+FA6+FA7+FA8+FA9+FC6+FC7+FC8+FC9+IB6-IC6-ID6+FD6+FD7+FD8+FD9+FB10) -> 880.27038 | FH6: =IF(C6=4,FH36,IF(C6=3,+L62,IF(C6=2,+L50+K69,IF(C6=1,IF(J20<=15,+FH53,IF(J20>=16,+FH78)))))) -> 0 | FI6: =IF(C6=4,SUM(U6+U7+U8+W6+W7+W8)*Percapita/30*FI$4+(V6+V7+V8+X6+X7+X8)*Cadeirante/30*FI$4,IF(C6=3,IF(U9+W9=10,Fixo/30*FI$4+(U6+U7+U8+W6+W7+W8)*Percapita/30*FI$4+(V9+X9)*Cadeirante/30*FI$4,IF(U9+W9<=9,(U9+W9)*Crechee/30*FI$4)+(V9+X9)*Cadeirante/30*FI$4+(U6+U7+U8+W6+W7+W8)*Percapita/30*FI$4)+IF(U9+W9>=11,Fixo/30*FI$4+(U9+W9-10)*Crechee/30*FI$4,0),IF(C6=2,IF(V6+V7+V8+V9+X6+X7+X8+X9=1,Cadeirante/30*FI$4,IF(V6+V7+V8+V9+X6+X7+X8+X9=2,Fixo/30*FI$4,IF(V6+V7+V8+V9+X6+X7+X8+X9>2,Fixo/30*FI$4+(V6+V7+V8+V9+X6+X7+X8+X9-2)*Cadeirante/30*FI$4)))+(U6+U7+U8+W6+W7+W8)*Percapita/30*FI$4+(U9+W9)*Crechee/30*FI$4,IF(C6=1,IF(U6+U7+U8+V6+V7+V8+W6+W7+W8+X6+X7+X8<=15,(U6+U7+U8+W6+W7+W8)*Percapita/30*FI$4,IF(U6+U7+U8+V6+V7+V8+W6+W7+W8+X6+X7+X8>=16,Fixo/30*FI$4+(U6+U7+U8+V6+V7+V8+W6+W7+W8+X6+X7-16)*Percapita/30*FI$4)))))) -> 0 | FJ6: =IF(C6=4,SUM(Y6+Y7+Y8+AA6+AA7+AA8)*Percapita/30*FJ$4+(Z6+Z7+Z8+AB6+AB7+AB8)*Cadeirante/30*FJ$4,IF(C6=3,IF(Y9+AA9=10,Fixo/30*FJ$4+(Y6+Y7+Y8+AA6+AA7+AA8)*Percapita/30*FJ$4+(Z9+AB9)*Cadeirante/30*FJ$4,IF(Y9+AA9<=9,(Y9+AA9)*Crechee/30*FJ$4)+(Z9+AB9)*Cadeirante/30*FJ$4+(Y6+Y7+Y8+AA6+AA7+AA8)*Percapita/30*FJ$4)+IF(Y9+AA9>=11,Fixo/30*FJ$4+(Y9+AA9-10)*Crechee/30*FJ$4,0),IF(C6=2,IF(Z6+Z7+Z8+Z9+AB6+AB7+AB8+AB9=1,Cadeirante/30*FJ$4,IF(Z6+Z7+Z8+Z9+AB6+AB7+AB8+AB9=2,Fixo/30*FJ$4,IF(Z6+Z7+Z8+Z9+AB6+AB7+AB8+AB9>2,Fixo/30*FJ$4+(Z6+Z7+Z8+Z9+AB6+AB7+AB8+AB9-2)*Cadeirante/30*FJ$4)))+(Y6+Y7+Y8+AA6+AA7+AA8)*Percapita/30*FJ$4+(Y9+AA9)*Crechee/30*FJ$4,IF(C6=1,IF(Y6+Y7+Y8+Z6+Z7+Z8+AA6+AA7+AA8+AB6+AB7+AB8<=15,(Y6+Y7+Y8+AA6+AA7+AA8)*Percapita/30*FJ$4,IF(Y6+Y7+Y8+Z6+Z7+Z8+AA6+AA7+AA8+AB6+AB7+AB8>=16,Fixo/30*FJ$4+(Y6+Y7+Y8+Z6+Z7+Z8+AA6+AA7+AA8+AB6+AB7-16)*Percapita/30*FJ$4)))))) -> 0 | FL6: =IF(C6=4,SUM(AC6+AC7+AC8+AE6+AE7+AE8)*Percapita/30*FL$4+(AD6+AD7+AD8+AF6+AF7+AF8)*Cadeirante/30*FL$4,IF(C6=3,IF(AC9+AE9=10,Fixo/30*FL$4+(AC6+AC7+AC8+AE6+AE7+AE8)*Percapita/30*FL$4+(AD9+AF9)*Cadeirante/30*FL$4,IF(AC9+AE9<=9,(AC9+AE9)*Crechee/30*FL$4)+(AD9+AF9)*Cadeirante/30*FL$4+(AC6+AC7+AC8+AE6+AE7+AE8)*Percapita/30*FL$4)+IF(AC9+AE9>=11,Fixo/30*FL$4+(AC9+AE9-10)*Crechee/30*FL$4,0),IF(C6=2,IF(AD6+AD7+AD8+AD9+AF6+AF7+AF8+AF9=1,Cadeirante/30*FL$4,IF(AD6+AD7+AD8+AD9+AF6+AF7+AF8+AF9=2,Fixo/30*FL$4,IF(AD6+AD7+AD8+AD9+AF6+AF7+AF8+AF9>2,Fixo/30*FL$4+(AD6+AD7+AD8+AD9+AF6+AF7+AF8+AF9-2)*Cadeirante/30*FL$4)))+(AC6+AC7+AC8+AE6+AE7+AE8)*Percapita/30*FL$4+(AC9+AE9)*Crechee/30*FL$4,IF(C6=1,IF(AC6+AC7+AC8+AD6+AD7+AD8+AE6+AE7+AE8+AF6+AF7+AF8<=15,(AC6+AC7+AC8+AE6+AE7+AE8)*Percapita/30*FL$4,IF(AC6+AC7+AC8+AD6+AD7+AD8+AE6+AE7+AE8+AF6+AF7+AF8>=16,Fixo/30*FL$4+(AC6+AC7+AC8+AD6+AD7+AD8+AE6+AE7+AE8+AF6+AF7-16)*Percapita/30*FL$4)))))) -> 0 | FM6: =IF(C6=4,SUM(AG6+AG7+AG8+AI6+AI7+AI8)*Percapita/30*FM$4+(AH6+AH7+AH8+AJ6+AJ7+AJ8)*Cadeirante/30*FM$4,IF(C6=3,IF(AG9+AI9=10,Fixo/30*FM$4+(AG6+AG7+AG8+AI6+AI7+AI8)*Percapita/30*FM$4+(AH9+AJ9)*Cadeirante/30*FM$4,IF(AG9+AI9<=9,(AG9+AI9)*Crechee/30*FM$4)+(AH9+AJ9)*Cadeirante/30*FM$4+(AG6+AG7+AG8+AI6+AI7+AI8)*Percapita/30*FM$4)+IF(AG9+AI9>=11,Fixo/30*FM$4+(AG9+AI9-10)*Crechee/30*FM$4,0),IF(C6=2,IF(AH6+AH7+AH8+AH9+AJ6+AJ7+AJ8+AJ9=1,Cadeirante/30*FM$4,IF(AH6+AH7+AH8+AH9+AJ6+AJ7+AJ8+AJ9=2,Fixo/30*FM$4,IF(AH6+AH7+AH8+AH9+AJ6+AJ7+AJ8+AJ9>2,Fixo/30*FM$4+(AH6+AH7+AH8+AH9+AJ6+AJ7+AJ8+AJ9-2)*Cadeirante/30*FM$4)))+(AG6+AG7+AG8+AI6+AI7+AI8)*Percapita/30*FM$4+(AG9+AI9)*Crechee/30*FM$4,IF(C6=1,IF(AG6+AG7+AG8+AH6+AH7+AH8+AI6+AI7+AI8+AJ6+AJ7+AJ8<=15,(AG6+AG7+AG8+AI6+AI7+AI8)*Percapita/30*FM$4,IF(AG6+AG7+AG8+AH6+AH7+AH8+AI6+AI7+AI8+AJ6+AJ7+AJ8>=16,Fixo/30*FM$4+(AG6+AG7+AG8+AH6+AH7+AH8+AI6+AI7+AI8+AJ6+AJ7-16)*Percapita/30*FM$4)))))) -> 0 | FN6: =IF(C6=4,SUM(AK6+AK7+AK8+AM6+AM7+AM8)*Percapita/30*FN$4+(AL6+AL7+AL8+AN6+AN7+AN8)*Cadeirante/30*FN$4,IF(C6=3,IF(AK9+AM9=10,Fixo/30*FN$4+(AK6+AK7+AK8+AM6+AM7+AM8)*Percapita/30*FN$4+(AL9+AN9)*Cadeirante/30*FN$4,IF(AK9+AM9<=9,(AK9+AM9)*Crechee/30*FN$4)+(AL9+AN9)*Cadeirante/30*FN$4+(AK6+AK7+AK8+AM6+AM7+AM8)*Percapita/30*FN$4)+IF(AK9+AM9>=11,Fixo/30*FN$4+(AK9+AM9-10)*Crechee/30*FN$4,0),IF(C6=2,IF(AL6+AL7+AL8+AL9+AN6+AN7+AN8+AN9=1,Cadeirante/30*FN$4,IF(AL6+AL7+AL8+AL9+AN6+AN7+AN8+AN9=2,Fixo/30*FN$4,IF(AL6+AL7+AL8+AL9+AN6+AN7+AN8+AN9>2,Fixo/30*FN$4+(AL6+AL7+AL8+AL9+AN6+AN7+AN8+AN9-2)*Cadeirante/30*FN$4)))+(AK6+AK7+AK8+AM6+AM7+AM8)*Percapita/30*FN$4+(AK9+AM9)*Crechee/30*FN$4,IF(C6=1,IF(AK6+AK7+AK8+AL6+AL7+AL8+AM6+AM7+AM8+AN6+AN7+AN8<=15,(AK6+AK7+AK8+AM6+AM7+AM8)*Percapita/30*FN$4,IF(AK6+AK7+AK8+AL6+AL7+AL8+AM6+AM7+AM8+AN6+AN7+AN8>=16,Fixo/30*FN$4+(AK6+AK7+AK8+AL6+AL7+AL8+AM6+AM7+AM8+AN6+AN7-16)*Percapita/30*FN$4)))))) -> 0 | FO6: =IF(C6=4,SUM(AO6+AO7+AO8+AQ6+AQ7+AQ8)*Percapita/30*FO$4+(AP6+AP7+AP8+AR6+AR7+AR8)*Cadeirante/30*FO$4,IF(C6=3,IF(AO9+AQ9=10,Fixo/30*FO$4+(AO6+AO7+AO8+AQ6+AQ7+AQ8)*Percapita/30*FO$4+(AP9+AR9)*Cadeirante/30*FO$4,IF(AO9+AQ9<=9,(AO9+AQ9)*Crechee/30*FO$4)+(AP9+AR9)*Cadeirante/30*FO$4+(AO6+AO7+AO8+AQ6+AQ7+AQ8)*Percapita/30*FO$4)+IF(AO9+AQ9>=11,Fixo/30*FO$4+(AO9+AQ9-10)*Crechee/30*FO$4,0),IF(C6=2,IF(AP6+AP7+AP8+AP9+AR6+AR7+AR8+AR9=1,Cadeirante/30*FO$4,IF(AP6+AP7+AP8+AP9+AR6+AR7+AR8+AR9=2,Fixo/30*FO$4,IF(AP6+AP7+AP8+AP9+AR6+AR7+AR8+AR9>2,Fixo/30*FO$4+(AP6+AP7+AP8+AP9+AR6+AR7+AR8+AR9-2)*Cadeirante/30*FO$4)))+(AO6+AO7+AO8+AQ6+AQ7+AQ8)*Percapita/30*FO$4+(AO9+AQ9)*Crechee/30*FO$4,IF(C6=1,IF(AO6+AO7+AO8+AP6+AP7+AP8+AQ6+AQ7+AQ8+AR6+AR7+AR8<=15,(AO6+AO7+AO8+AQ6+AQ7+AQ8)*Percapita/30*FO$4,IF(AO6+AO7+AO8+AP6+AP7+AP8+AQ6+AQ7+AQ8+AR6+AR7+AR8>=16,Fixo/30*FO$4+(AO6+AO7+AO8+AP6+AP7+AP8+AQ6+AQ7+AQ8+AR6+AR7-16)*Percapita/30*FO$4)))))) -> 308.184 | FP6: =IF(C6=4,SUM(AS6+AS7+AS8+AU6+AU7+AU8)*Percapita/30*FP$4+(AT6+AT7+AT8+AV6+AV7+AV8)*Cadeirante/30*FP$4,IF(C6=3,IF(AS9+AU9=10,Fixo/30*FP$4+(AS6+AS7+AS8+AU6+AU7+AU8)*Percapita/30*FP$4+(AT9+AV9)*Cadeirante/30*FP$4,IF(AS9+AU9<=9,(AS9+AU9)*Crechee/30*FP$4)+(AT9+AV9)*Cadeirante/30*FP$4+(AS6+AS7+AS8+AU6+AU7+AU8)*Percapita/30*FP$4)+IF(AS9+AU9>=11,Fixo/30*FP$4+(AS9+AU9-10)*Crechee/30*FP$4,0),IF(C6=2,IF(AT6+AT7+AT8+AT9+AV6+AV7+AV8+AV9=1,Cadeirante/30*FP$4,IF(AT6+AT7+AT8+AT9+AV6+AV7+AV8+AV9=2,Fixo/30*FP$4,IF(AT6+AT7+AT8+AT9+AV6+AV7+AV8+AV9>2,Fixo/30*FP$4+(AT6+AT7+AT8+AT9+AV6+AV7+AV8+AV9-2)*Cadeirante/30*FP$4)))+(AS6+AS7+AS8+AU6+AU7+AU8)*Percapita/30*FP$4+(AS9+AU9)*Crechee/30*FP$4,IF(C6=1,IF(AS6+AS7+AS8+AT6+AT7+AT8+AU6+AU7+AU8+AV6+AV7+AV8<=15,(AS6+AS7+AS8+AU6+AU7+AU8)*Percapita/30*FP$4,IF(AS6+AS7+AS8+AT6+AT7+AT8+AU6+AU7+AU8+AV6+AV7+AV8>=16,Fixo/30*FP$4+(AS6+AS7+AS8+AT6+AT7+AT8+AU6+AU7+AU8+AV6+AV7-16)*Percapita/30*FP$4)))))) -> 295.343 | FQ6: =IF(C6=4,SUM(AW6+AW7+AW8+AY6+AY7+AY8)*Percapita/30*FQ$4+(AX6+AX7+AX8+AZ6+AZ7+AZ8)*Cadeirante/30*FQ$4,IF(C6=3,IF(AW9+AY9=10,Fixo/30*FQ$4+(AW6+AW7+AW8+AY6+AY7+AY8)*Percapita/30*FQ$4+(AX9+AZ9)*Cadeirante/30*FQ$4,IF(AW9+AY9<=9,(AW9+AY9)*Crechee/30*FQ$4)+(AX9+AZ9)*Cadeirante/30*FQ$4+(AW6+AW7+AW8+AY6+AY7+AY8)*Percapita/30*FQ$4)+IF(AW9+AY9>=11,Fixo/30*FQ$4+(AW9+AY9-10)*Crechee/30*FQ$4,0),IF(C6=2,IF(AX6+AX7+AX8+AX9+AZ6+AZ7+AZ8+AZ9=1,Cadeirante/30*FQ$4,IF(AX6+AX7+AX8+AX9+AZ6+AZ7+AZ8+AZ9=2,Fixo/30*FQ$4,IF(AX6+AX7+AX8+AX9+AZ6+AZ7+AZ8+AZ9>2,Fixo/30*FQ$4+(AX6+AX7+AX8+AX9+AZ6+AZ7+AZ8+AZ9-2)*Cadeirante/30*FQ$4)))+(AW6+AW7+AW8+AY6+AY7+AY8)*Percapita/30*FQ$4+(AW9+AY9)*Crechee/30*FQ$4,IF(C6=1,IF(AW6+AW7+AW8+AX6+AX7+AX8+AY6+AY7+AY8+AZ6+AZ7+AZ8<=15,(AW6+AW7+AW8+AY6+AY7+AY8)*Percapita/30*FQ$4,IF(AW6+AW7+AW8+AX6+AX7+AX8+AY6+AY7+AY8+AZ6+AZ7+AZ8>=16,Fixo/30*FQ$4+(AW6+AW7+AW8+AX6+AX7+AX8+AY6+AY7+AY8+AZ6+AZ7-16)*Percapita/30*FQ$4)))))) -> 0 | FR6: =IF(C6=4,SUM(BA6+BA7+BA8+BC6+BC7+BC8)*Percapita/30*FR$4+(BB6+BB7+BB8+BD6+BD7+BD8)*Cadeirante/30*FR$4,IF(C6=3,IF(BA9+BC9=10,Fixo/30*FR$4+(BA6+BA7+BA8+BC6+BC7+BC8)*Percapita/30*FR$4+(BB9+BD9)*Cadeirante/30*FR$4,IF(BA9+BC9<=9,(BA9+BC9)*Crechee/30*FR$4)+(BB9+BD9)*Cadeirante/30*FR$4+(BA6+BA7+BA8+BC6+BC7+BC8)*Percapita/30*FR$4)+IF(BA9+BC9>=11,Fixo/30*FR$4+(BA9+BC9-10)*Crechee/30*FR$4,0),IF(C6=2,IF(BB6+BB7+BB8+BB9+BD6+BD7+BD8+BD9=1,Cadeirante/30*FR$4,IF(BB6+BB7+BB8+BB9+BD6+BD7+BD8+BD9=2,Fixo/30*FR$4,IF(BB6+BB7+BB8+BB9+BD6+BD7+BD8+BD9>2,Fixo/30*FR$4+(BB6+BB7+BB8+BB9+BD6+BD7+BD8+BD9-2)*Cadeirante/30*FR$4)))+(BA6+BA7+BA8+BC6+BC7+BC8)*Percapita/30*FR$4+(BA9+BC9)*Crechee/30*FR$4,IF(C6=1,IF(BA6+BA7+BA8+BB6+BB7+BB8+BC6+BC7+BC8+BD6+BD7+BD8<=15,(BA6+BA7+BA8+BC6+BC7+BC8)*Percapita/30*FR$4,IF(BA6+BA7+BA8+BB6+BB7+BB8+BC6+BC7+BC8+BD6+BD7+BD8>=16,Fixo/30*FR$4+(BA6+BA7+BA8+BB6+BB7+BB8+BC6+BC7+BC8+BD6+BD7-16)*Percapita/30*FR$4)))))) -> 0 | FS6: =IF(C6=4,SUM(BE6+BE7+BE8+BG6+BG7+BG8)*Percapita/30*FS$4+(BF6+BF7+BF8+BH6+BH7+BH8)*Cadeirante/30*FS$4,IF(C6=3,IF(BE9+BG9=10,Fixo/30*FS$4+(BE6+BE7+BE8+BG6+BG7+BG8)*Percapita/30*FS$4+(BF9+BH9)*Cadeirante/30*FS$4,IF(BE9+BG9<=9,(BE9+BG9)*Crechee/30*FS$4)+(BF9+BH9)*Cadeirante/30*FS$4+(BE6+BE7+BE8+BG6+BG7+BG8)*Percapita/30*FS$4)+IF(BE9+BG9>=11,Fixo/30*FS$4+(BE9+BG9-10)*Crechee/30*FS$4,0),IF(C6=2,IF(BF6+BF7+BF8+BF9+BH6+BH7+BH8+BH9=1,Cadeirante/30*FS$4,IF(BF6+BF7+BF8+BF9+BH6+BH7+BH8+BH9=2,Fixo/30*FS$4,IF(BF6+BF7+BF8+BF9+BH6+BH7+BH8+BH9>2,Fixo/30*FS$4+(BF6+BF7+BF8+BF9+BH6+BH7+BH8+BH9-2)*Cadeirante/30*FS$4)))+(BE6+BE7+BE8+BG6+BG7+BG8)*Percapita/30*FS$4+(BE9+BG9)*Crechee/30*FS$4,IF(C6=1,IF(BE6+BE7+BE8+BF6+BF7+BF8+BG6+BG7+BG8+BH6+BH7+BH8<=15,(BE6+BE7+BE8+BG6+BG7+BG8)*Percapita/30*FS$4,IF(BE6+BE7+BE8+BF6+BF7+BF8+BG6+BG7+BG8+BH6+BH7+BH8>=16,Fixo/30*FS$4+(BE6+BE7+BE8+BF6+BF7+BF8+BG6+BG7+BG8+BH6+BH7-16)*Percapita/30*FS$4)))))) -> 0 | FT6: =IF(C6=4,SUM(BI6+BI7+BI8+BK6+BK7+BK8)*Percapita/30*FT$4+(BJ6+BJ7+BJ8+BL6+BL7+BL8)*Cadeirante/30*FT$4,IF(C6=3,IF(BI9+BK9=10,Fixo/30*FT$4+(BI6+BI7+BI8+BK6+BK7+BK8)*Percapita/30*FT$4+(BJ9+BL9)*Cadeirante/30*FT$4,IF(BI9+BK9<=9,(BI9+BK9)*Crechee/30*FT$4)+(BJ9+BL9)*Cadeirante/30*FT$4+(BI6+BI7+BI8+BK6+BK7+BK8)*Percapita/30*FT$4)+IF(BI9+BK9>=11,Fixo/30*FT$4+(BI9+BK9-10)*Crechee/30*FT$4,0),IF(C6=2,IF(BJ6+BJ7+BJ8+BJ9+BL6+BL7+BL8+BL9=1,Cadeirante/30*FT$4,IF(BJ6+BJ7+BJ8+BJ9+BL6+BL7+BL8+BL9=2,Fixo/30*FT$4,IF(BJ6+BJ7+BJ8+BJ9+BL6+BL7+BL8+BL9>2,Fixo/30*FT$4+(BJ6+BJ7+BJ8+BJ9+BL6+BL7+BL8+BL9-2)*Cadeirante/30*FT$4)))+(BI6+BI7+BI8+BK6+BK7+BK8)*Percapita/30*FT$4+(BI9+BK9)*Crechee/30*FT$4,IF(C6=1,IF(BI6+BI7+BI8+BJ6+BJ7+BJ8+BK6+BK7+BK8+BL6+BL7+BL8<=15,(BI6+BI7+BI8+BK6+BK7+BK8)*Percapita/30*FT$4,IF(BI6+BI7+BI8+BJ6+BJ7+BJ8+BK6+BK7+BK8+BL6+BL7+BL8>=16,Fixo/30*FT$4+(BI6+BI7+BI8+BJ6+BJ7+BJ8+BK6+BK7+BK8+BL6+BL7-16)*Percapita/30*FT$4)))))) -> 0 | FU6: =IF(C6=4,SUM(BM6+BM7+BM8+BO6+BO7+BO8)*Percapita/30*FU$4+(BN6+BN7+BN8+BP6+BP7+BP8)*Cadeirante/30*FU$4,IF(C6=3,IF(BM9+BO9=10,Fixo/30*FU$4+(BM6+BM7+BM8+BO6+BO7+BO8)*Percapita/30*FU$4+(BN9+BP9)*Cadeirante/30*FU$4,IF(BM9+BO9<=9,(BM9+BO9)*Crechee/30*FU$4)+(BN9+BP9)*Cadeirante/30*FU$4+(BM6+BM7+BM8+BO6+BO7+BO8)*Percapita/30*FU$4)+IF(BM9+BO9>=11,Fixo/30*FU$4+(BM9+BO9-10)*Crechee/30*FU$4,0),IF(C6=2,IF(BN6+BN7+BN8+BN9+BP6+BP7+BP8+BP9=1,Cadeirante/30*FU$4,IF(BN6+BN7+BN8+BN9+BP6+BP7+BP8+BP9=2,Fixo/30*FU$4,IF(BN6+BN7+BN8+BN9+BP6+BP7+BP8+BP9>2,Fixo/30*FU$4+(BN6+BN7+BN8+BN9+BP6+BP7+BP8+BP9-2)*Cadeirante/30*FU$4)))+(BM6+BM7+BM8+BO6+BO7+BO8)*Percapita/30*FU$4+(BM9+BO9)*Crechee/30*FU$4,IF(C6=1,IF(BM6+BM7+BM8+BN6+BN7+BN8+BO6+BO7+BO8+BP6+BP7+BP8<=15,(BM6+BM7+BM8+BO6+BO7+BO8)*Percapita/30*FU$4,IF(BM6+BM7+BM8+BN6+BN7+BN8+BO6+BO7+BO8+BP6+BP7+BP8>=16,Fixo/30*FU$4+(BM6+BM7+BM8+BN6+BN7+BN8+BO6+BO7+BO8+BP6+BP7-16)*Percapita/30*FU$4)))))) -> 0 | FV6: =IF(C6=4,SUM(BQ6+BQ7+BQ8+BS6+BS7+BS8)*Percapita/30*FV$4+(BR6+BR7+BR8+BT6+BT7+BT8)*Cadeirante/30*FV$4,IF(C6=3,IF(BQ9+BS9=10,Fixo/30*FV$4+(BQ6+BQ7+BQ8+BS6+BS7+BS8)*Percapita/30*FV$4+(BR9+BT9)*Cadeirante/30*FV$4,IF(BQ9+BS9<=9,(BQ9+BS9)*Crechee/30*FV$4)+(BR9+BT9)*Cadeirante/30*FV$4+(BQ6+BQ7+BQ8+BS6+BS7+BS8)*Percapita/30*FV$4)+IF(BQ9+BS9>=11,Fixo/30*FV$4+(BQ9+BS9-10)*Crechee/30*FV$4,0),IF(C6=2,IF(BR6+BR7+BR8+BR9+BT6+BT7+BT8+BT9=1,Cadeirante/30*FV$4,IF(BR6+BR7+BR8+BR9+BT6+BT7+BT8+BT9=2,Fixo/30*FV$4,IF(BR6+BR7+BR8+BR9+BT6+BT7+BT8+BT9>2,Fixo/30*FV$4+(BR6+BR7+BR8+BR9+BT6+BT7+BT8+BT9-2)*Cadeirante/30*FV$4)))+(BQ6+BQ7+BQ8+BS6+BS7+BS8)*Percapita/30*FV$4+(BQ9+BS9)*Crechee/30*FV$4,IF(C6=1,IF(BQ6+BQ7+BQ8+BR6+BR7+BR8+BS6+BS7+BS8+BT6+BT7+BT8<=15,(BQ6+BQ7+BQ8+BS6+BS7+BS8)*Percapita/30*FV$4,IF(BQ6+BQ7+BQ8+BR6+BR7+BR8+BS6+BS7+BS8+BT6+BT7+BT8>=16,Fixo/30*FV$4+(BQ6+BQ7+BQ8+BR6+BR7+BR8+BS6+BS7+BS8+BT6+BT7-16)*Percapita/30*FV$4)))))) -> -218.297 | FW6: =IF(C6=4,SUM(BU6+BU7+BU8+BW6+BW7+BW8)*Percapita/30*FW$4+(BV6+BV7+BV8+BX6+BX7+BX8)*Cadeirante/30*FW$4,IF(C6=3,IF(BU9+BW9=10,Fixo/30*FW$4+(BU6+BU7+BU8+BW6+BW7+BW8)*Percapita/30*FW$4+(BV9+BX9)*Cadeirante/30*FW$4,IF(BU9+BW9<=9,(BU9+BW9)*Crechee/30*FW$4)+(BV9+BX9)*Cadeirante/30*FW$4+(BU6+BU7+BU8+BW6+BW7+BW8)*Percapita/30*FW$4)+IF(BU9+BW9>=11,Fixo/30*FW$4+(BU9+BW9-10)*Crechee/30*FW$4,0),IF(C6=2,IF(BV6+BV7+BV8+BV9+BX6+BX7+BX8+BX9=1,Cadeirante/30*FW$4,IF(BV6+BV7+BV8+BV9+BX6+BX7+BX8+BX9=2,Fixo/30*FW$4,IF(BV6+BV7+BV8+BV9+BX6+BX7+BX8+BX9>2,Fixo/30*FW$4+(BV6+BV7+BV8+BV9+BX6+BX7+BX8+BX9-2)*Cadeirante/30*FW$4)))+(BU6+BU7+BU8+BW6+BW7+BW8)*Percapita/30*FW$4+(BU9+BW9)*Crechee/30*FW$4,IF(C6=1,IF(BU6+BU7+BU8+BV6+BV7+BV8+BW6+BW7+BW8+BX6+BX7+BX8<=15,(BU6+BU7+BU8+BW6+BW7+BW8)*Percapita/30*FW$4,IF(BU6+BU7+BU8+BV6+BV7+BV8+BW6+BW7+BW8+BX6+BX7+BX8>=16,Fixo/30*FW$4+(BU6+BU7+BU8+BV6+BV7+BV8+BW6+BW7+BW8+BX6+BX7-16)*Percapita/30*FW$4)))))) -> 0 | FX6: =IF(C6=4,SUM(BY6+BY7+BY8+CA6+CA7+CA8)*Percapita/30*FX$4+(BZ6+BZ7+BZ8+CB6+CB7+CB8)*Cadeirante/30*FX$4,IF(C6=3,IF(BY9+CA9=10,Fixo/30*FX$4+(BY6+BY7+BY8+CA6+CA7+CA8)*Percapita/30*FX$4+(BZ9+CB9)*Cadeirante/30*FX$4,IF(BY9+CA9<=9,(BY9+CA9)*Crechee/30*FX$4)+(BZ9+CB9)*Cadeirante/30*FX$4+(BY6+BY7+BY8+CA6+CA7+CA8)*Percapita/30*FX$4)+IF(BY9+CA9>=11,Fixo/30*FX$4+(BY9+CA9-10)*Crechee/30*FX$4,0),IF(C6=2,IF(BZ6+BZ7+BZ8+BZ9+CB6+CB7+CB8+CB9=1,Cadeirante/30*FX$4,IF(BZ6+BZ7+BZ8+BZ9+CB6+CB7+CB8+CB9=2,Fixo/30*FX$4,IF(BZ6+BZ7+BZ8+BZ9+CB6+CB7+CB8+CB9>2,Fixo/30*FX$4+(BZ6+BZ7+BZ8+BZ9+CB6+CB7+CB8+CB9-2)*Cadeirante/30*FX$4)))+(BY6+BY7+BY8+CA6+CA7+CA8)*Percapita/30*FX$4+(BY9+CA9)*Crechee/30*FX$4,IF(C6=1,IF(BY6+BY7+BY8+BZ6+BZ7+BZ8+CA6+CA7+CA8+CB6+CB7+CB8<=15,(BY6+BY7+BY8+CA6+CA7+CA8)*Percapita/30*FX$4,IF(BY6+BY7+BY8+BZ6+BZ7+BZ8+CA6+CA7+CA8+CB6+CB7+CB8>=16,Fixo/30*FX$4+(BY6+BY7+BY8+BZ6+BZ7+BZ8+CA6+CA7+CA8+CB6+CB7-16)*Percapita/30*FX$4)))))) -> 0 | FY6: =IF(C6=4,SUM(CC6+CC7+CC8+CE6+CE7+CE8)*Percapita/30*FY$4+(CD6+CD7+CD8+CF6+CF7+CF8)*Cadeirante/30*FY$4,IF(C6=3,IF(CC9+CE9=10,Fixo/30*FY$4+(CC6+CC7+CC8+CE6+CE7+CE8)*Percapita/30*FY$4+(CD9+CF9)*Cadeirante/30*FY$4,IF(CC9+CE9<=9,(CC9+CE9)*Crechee/30*FY$4)+(CD9+CF9)*Cadeirante/30*FY$4+(CC6+CC7+CC8+CE6+CE7+CE8)*Percapita/30*FY$4)+IF(CC9+CE9>=11,Fixo/30*FY$4+(CC9+CE9-10)*Crechee/30*FY$4,0),IF(C6=2,IF(CD6+CD7+CD8+CD9+CF6+CF7+CF8+CF9=1,Cadeirante/30*FY$4,IF(CD6+CD7+CD8+CD9+CF6+CF7+CF8+CF9=2,Fixo/30*FY$4,IF(CD6+CD7+CD8+CD9+CF6+CF7+CF8+CF9>2,Fixo/30*FY$4+(CD6+CD7+CD8+CD9+CF6+CF7+CF8+CF9-2)*Cadeirante/30*FY$4)))+(CC6+CC7+CC8+CE6+CE7+CE8)*Percapita/30*FY$4+(CC9+CE9)*Crechee/30*FY$4,IF(C6=1,IF(CC6+CC7+CC8+CD6+CD7+CD8+CE6+CE7+CE8+CF6+CF7+CF8<=15,(CC6+CC7+CC8+CE6+CE7+CE8)*Percapita/30*FY$4,IF(CC6+CC7+CC8+CD6+CD7+CD8+CE6+CE7+CE8+CF6+CF7+CF8>=16,Fixo/30*FY$4+(CC6+CC7+CC8+CD6+CD7+CD8+CE6+CE7+CE8+CF6+CF7-16)*Percapita/30*FY$4)))))) -> 0 | FZ6: =IF(C6=4,SUM(CG6+CG7+CG8+CI6+CI7+CI8)*Percapita/30*FZ$4+(CH6+CH7+CH8+CJ6+CJ7+CJ8)*Cadeirante/30*FZ$4,IF(C6=3,IF(CG9+CI9=10,Fixo/30*FZ$4+(CG6+CG7+CG8+CI6+CI7+CI8)*Percapita/30*FZ$4+(CH9+CJ9)*Cadeirante/30*FZ$4,IF(CG9+CI9<=9,(CG9+CI9)*Crechee/30*FZ$4)+(CH9+CJ9)*Cadeirante/30*FZ$4+(CG6+CG7+CG8+CI6+CI7+CI8)*Percapita/30*FZ$4)+IF(CG9+CI9>=11,Fixo/30*FZ$4+(CG9+CI9-10)*Crechee/30*FZ$4,0),IF(C6=2,IF(CH6+CH7+CH8+CH9+CJ6+CJ7+CJ8+CJ9=1,Cadeirante/30*FZ$4,IF(CH6+CH7+CH8+CH9+CJ6+CJ7+CJ8+CJ9=2,Fixo/30*FZ$4,IF(CH6+CH7+CH8+CH9+CJ6+CJ7+CJ8+CJ9>2,Fixo/30*FZ$4+(CH6+CH7+CH8+CH9+CJ6+CJ7+CJ8+CJ9-2)*Cadeirante/30*FZ$4)))+(CG6+CG7+CG8+CI6+CI7+CI8)*Percapita/30*FZ$4+(CG9+CI9)*Crechee/30*FZ$4,IF(C6=1,IF(CG6+CG7+CG8+CH6+CH7+CH8+CI6+CI7+CI8+CJ6+CJ7+CJ8<=15,(CG6+CG7+CG8+CI6+CI7+CI8)*Percapita/30*FZ$4,IF(CG6+CG7+CG8+CH6+CH7+CH8+CI6+CI7+CI8+CJ6+CJ7+CJ8>=16,Fixo/30*FZ$4+(CG6+CG7+CG8+CH6+CH7+CH8+CI6+CI7+CI8+CJ6+CJ7-16)*Percapita/30*FZ$4)))))) -> 0 | GA6: =IF(C6=4,SUM(CK6+CK7+CK8+CM6+CM7+CM8)*Percapita/30*GA$4+(CL6+CL7+CL8+CN6+CN7+CN8)*Cadeirante/30*GA$4,IF(C6=3,IF(CK9+CM9=10,Fixo/30*GA$4+(CK6+CK7+CK8+CM6+CM7+CM8)*Percapita/30*GA$4+(CL9+CN9)*Cadeirante/30*GA$4,IF(CK9+CM9<=9,(CK9+CM9)*Crechee/30*GA$4)+(CL9+CN9)*Cadeirante/30*GA$4+(CK6+CK7+CK8+CM6+CM7+CM8)*Percapita/30*GA$4)+IF(CK9+CM9>=11,Fixo/30*GA$4+(CK9+CM9-10)*Crechee/30*GA$4,0),IF(C6=2,IF(CL6+CL7+CL8+CL9+CN6+CN7+CN8+CN9=1,Cadeirante/30*GA$4,IF(CL6+CL7+CL8+CL9+CN6+CN7+CN8+CN9=2,Fixo/30*GA$4,IF(CL6+CL7+CL8+CL9+CN6+CN7+CN8+CN9>2,Fixo/30*GA$4+(CL6+CL7+CL8+CL9+CN6+CN7+CN8+CN9-2)*Cadeirante/30*GA$4)))+(CK6+CK7+CK8+CM6+CM7+CM8)*Percapita/30*GA$4+(CK9+CM9)*Crechee/30*GA$4,IF(C6=1,IF(CK6+CK7+CK8+CL6+CL7+CL8+CM6+CM7+CM8+CN6+CN7+CN8<=15,(CK6+CK7+CK8+CM6+CM7+CM8)*Percapita/30*GA$4,IF(CK6+CK7+CK8+CL6+CL7+CL8+CM6+CM7+CM8+CN6+CN7+CN8>=16,Fixo/30*GA$4+(CK6+CK7+CK8+CL6+CL7+CL8+CM6+CM7+CM8+CN6+CN7-16)*Percapita/30*GA$4)))))) -> 0 | GB6: =IF(C6=4,SUM(CO6+CO7+CO8+CQ6+CQ7+CQ8)*Percapita/30*GB$4+(CP6+CP7+CP8+CR6+CR7+CR8)*Cadeirante/30*GB$4,IF(C6=3,IF(CO9+CQ9=10,Fixo/30*GB$4+(CO6+CO7+CO8+CQ6+CQ7+CQ8)*Percapita/30*GB$4+(CP9+CR9)*Cadeirante/30*GB$4,IF(CO9+CQ9<=9,(CO9+CQ9)*Crechee/30*GB$4)+(CP9+CR9)*Cadeirante/30*GB$4+(CO6+CO7+CO8+CQ6+CQ7+CQ8)*Percapita/30*GB$4)+IF(CO9+CQ9>=11,Fixo/30*GB$4+(CO9+CQ9-10)*Crechee/30*GB$4,0),IF(C6=2,IF(CP6+CP7+CP8+CP9+CR6+CR7+CR8+CR9=1,Cadeirante/30*GB$4,IF(CP6+CP7+CP8+CP9+CR6+CR7+CR8+CR9=2,Fixo/30*GB$4,IF(CP6+CP7+CP8+CP9+CR6+CR7+CR8+CR9>2,Fixo/30*GB$4+(CP6+CP7+CP8+CP9+CR6+CR7+CR8+CR9-2)*Cadeirante/30*GB$4)))+(CO6+CO7+CO8+CQ6+CQ7+CQ8)*Percapita/30*GB$4+(CO9+CQ9)*Crechee/30*GB$4,IF(C6=1,IF(CO6+CO7+CO8+CP6+CP7+CP8+CQ6+CQ7+CQ8+CR6+CR7+CR8<=15,(CO6+CO7+CO8+CQ6+CQ7+CQ8)*Percapita/30*GB$4,IF(CO6+CO7+CO8+CP6+CP7+CP8+CQ6+CQ7+CQ8+CR6+CR7+CR8>=16,Fixo/30*GB$4+(CO6+CO7+CO8+CP6+CP7+CP8+CQ6+CQ7+CQ8+CR6+CR7-16)*Percapita/30*GB$4)))))) -> 0 | GC6: =IF(C6=4,SUM(CS6+CS7+CS8+CU6+CU7+CU8)*Percapita/30*GC$4+(CT6+CT7+CT8+CV6+CV7+CV8)*Cadeirante/30*GC$4,IF(C6=3,IF(CS9+CU9=10,Fixo/30*GC$4+(CS6+CS7+CS8+CU6+CU7+CU8)*Percapita/30*GC$4+(CT9+CV9)*Cadeirante/30*GC$4,IF(CS9+CU9<=9,(CS9+CU9)*Crechee/30*GC$4)+(CT9+CV9)*Cadeirante/30*GC$4+(CS6+CS7+CS8+CU6+CU7+CU8)*Percapita/30*GC$4)+IF(CS9+CU9>=11,Fixo/30*GC$4+(CS9+CU9-10)*Crechee/30*GC$4,0),IF(C6=2,IF(CT6+CT7+CT8+CT9+CV6+CV7+CV8+CV9=1,Cadeirante/30*GC$4,IF(CT6+CT7+CT8+CT9+CV6+CV7+CV8+CV9=2,Fixo/30*GC$4,IF(CT6+CT7+CT8+CT9+CV6+CV7+CV8+CV9>2,Fixo/30*GC$4+(CT6+CT7+CT8+CT9+CV6+CV7+CV8+CV9-2)*Cadeirante/30*GC$4)))+(CS6+CS7+CS8+CU6+CU7+CU8)*Percapita/30*GC$4+(CS9+CU9)*Crechee/30*GC$4,IF(C6=1,IF(CS6+CS7+CS8+CT6+CT7+CT8+CU6+CU7+CU8+CV6+CV7+CV8<=15,(CS6+CS7+CS8+CU6+CU7+CU8)*Percapita/30*GC$4,IF(CS6+CS7+CS8+CT6+CT7+CT8+CU6+CU7+CU8+CV6+CV7+CV8>=16,Fixo/30*GC$4+(CS6+CS7+CS8+CT6+CT7+CT8+CU6+CU7+CU8+CV6+CV7-16)*Percapita/30*GC$4)))))) -> 0 | GD6: =IF(C6=4,SUM(CW6+CW7+CW8+CY6+CY7+CY8)*Percapita/30*GD$4+(CX6+CX7+CX8+CZ6+CZ7+CZ8)*Cadeirante/30*GD$4,IF(C6=3,IF(CW9+CY9=10,Fixo/30*GD$4+(CW6+CW7+CW8+CY6+CY7+CY8)*Percapita/30*GD$4+(CX9+CZ9)*Cadeirante/30*GD$4,IF(CW9+CY9<=9,(CW9+CY9)*Crechee/30*GD$4)+(CX9+CZ9)*Cadeirante/30*GD$4+(CW6+CW7+CW8+CY6+CY7+CY8)*Percapita/30*GD$4)+IF(CW9+CY9>=11,Fixo/30*GD$4+(CW9+CY9-10)*Crechee/30*GD$4,0),IF(C6=2,IF(CX6+CX7+CX8+CX9+CZ6+CZ7+CZ8+CZ9=1,Cadeirante/30*GD$4,IF(CX6+CX7+CX8+CX9+CZ6+CZ7+CZ8+CZ9=2,Fixo/30*GD$4,IF(CX6+CX7+CX8+CX9+CZ6+CZ7+CZ8+CZ9>2,Fixo/30*GD$4+(CX6+CX7+CX8+CX9+CZ6+CZ7+CZ8+CZ9-2)*Cadeirante/30*GD$4)))+(CW6+CW7+CW8+CY6+CY7+CY8)*Percapita/30*GD$4+(CW9+CY9)*Crechee/30*GD$4,IF(C6=1,IF(CW6+CW7+CW8+CX6+CX7+CX8+CY6+CY7+CY8+CZ6+CZ7+CZ8<=15,(CW6+CW7+CW8+CY6+CY7+CY8)*Percapita/30*GD$4,IF(CW6+CW7+CW8+CX6+CX7+CX8+CY6+CY7+CY8+CZ6+CZ7+CZ8>=16,Fixo/30*GD$4+(CW6+CW7+CW8+CX6+CX7+CX8+CY6+CY7+CY8+CZ6+CZ7-16)*Percapita/30*GD$4)))))) -> 0 | GE6: =IF(C6=4,SUM(DA6+DA7+DA8+DC6+DC7+DC8)*Percapita/30*GE$4+(DB6+DB7+DB8+DD6+DD7+DD8)*Cadeirante/30*GE$4,IF(C6=3,IF(DA9+DC9=10,Fixo/30*GE$4+(DA6+DA7+DA8+DC6+DC7+DC8)*Percapita/30*GE$4+(DB9+DD9)*Cadeirante/30*GE$4,IF(DA9+DC9<=9,(DA9+DC9)*Crechee/30*GE$4)+(DB9+DD9)*Cadeirante/30*GE$4+(DA6+DA7+DA8+DC6+DC7+DC8)*Percapita/30*GE$4)+IF(DA9+DC9>=11,Fixo/30*GE$4+(DA9+DC9-10)*Crechee/30*GE$4,0),IF(C6=2,IF(DB6+DB7+DB8+DB9+DD6+DD7+DD8+DD9=1,Cadeirante/30*GE$4,IF(DB6+DB7+DB8+DB9+DD6+DD7+DD8+DD9=2,Fixo/30*GE$4,IF(DB6+DB7+DB8+DB9+DD6+DD7+DD8+DD9>2,Fixo/30*GE$4+(DB6+DB7+DB8+DB9+DD6+DD7+DD8+DD9-2)*Cadeirante/30*GE$4)))+(DA6+DA7+DA8+DC6+DC7+DC8)*Percapita/30*GE$4+(DA9+DC9)*Crechee/30*GE$4,IF(C6=1,IF(DA6+DA7+DA8+DB6+DB7+DB8+DC6+DC7+DC8+DD6+DD7+DD8<=15,(DA6+DA7+DA8+DC6+DC7+DC8)*Percapita/30*GE$4,IF(DA6+DA7+DA8+DB6+DB7+DB8+DC6+DC7+DC8+DD6+DD7+DD8>=16,Fixo/30*GE$4+(DA6+DA7+DA8+DB6+DB7+DB8+DC6+DC7+DC8+DD6+DD7-16)*Percapita/30*GE$4)))))) -> 0 | GF6: =IF(C6=4,SUM(DE6+DE7+DE8+DG6+DG7+DG8)*Percapita/30*GF$4+(DF6+DF7+DF8+DH6+DH7+DH8)*Cadeirante/30*GF$4,IF(C6=3,IF(DE9+DG9=10,Fixo/30*GF$4+(DE6+DE7+DE8+DG6+DG7+DG8)*Percapita/30*GF$4+(DF9+DH9)*Cadeirante/30*GF$4,IF(DE9+DG9<=9,(DE9+DG9)*Crechee/30*GF$4)+(DF9+DH9)*Cadeirante/30*GF$4+(DE6+DE7+DE8+DG6+DG7+DG8)*Percapita/30*GF$4)+IF(DE9+DG9>=11,Fixo/30*GF$4+(DE9+DG9-10)*Crechee/30*GF$4,0),IF(C6=2,IF(DF6+DF7+DF8+DF9+DH6+DH7+DH8+DH9=1,Cadeirante/30*GF$4,IF(DF6+DF7+DF8+DF9+DH6+DH7+DH8+DH9=2,Fixo/30*GF$4,IF(DF6+DF7+DF8+DF9+DH6+DH7+DH8+DH9>2,Fixo/30*GF$4+(DF6+DF7+DF8+DF9+DH6+DH7+DH8+DH9-2)*Cadeirante/30*GF$4)))+(DE6+DE7+DE8+DG6+DG7+DG8)*Percapita/30*GF$4+(DE9+DG9)*Crechee/30*GF$4,IF(C6=1,IF(DE6+DE7+DE8+DF6+DF7+DF8+DG6+DG7+DG8+DH6+DH7+DH8<=15,(DE6+DE7+DE8+DG6+DG7+DG8)*Percapita/30*GF$4,IF(DE6+DE7+DE8+DF6+DF7+DF8+DG6+DG7+DG8+DH6+DH7+DH8>=16,Fixo/30*GF$4+(DE6+DE7+DE8+DF6+DF7+DF8+DG6+DG7+DG8+DH6+DH7-16)*Percapita/30*GF$4)))))) -> 0 | GG6: =IF(C6=4,SUM(DI6+DI7+DI8+DK6+DK7+DK8)*Percapita/30*GG$4+(DJ6+DJ7+DJ8+DL6+DL7+DL8)*Cadeirante/30*GG$4,IF(C6=3,IF(DI9+DK9=10,Fixo/30*GG$4+(DI6+DI7+DI8+DK6+DK7+DK8)*Percapita/30*GG$4+(DJ9+DL9)*Cadeirante/30*GG$4,IF(DI9+DK9<=9,(DI9+DK9)*Crechee/30*GG$4)+(DJ9+DL9)*Cadeirante/30*GG$4+(DI6+DI7+DI8+DK6+DK7+DK8)*Percapita/30*GG$4)+IF(DI9+DK9>=11,Fixo/30*GG$4+(DI9+DK9-10)*Crechee/30*GG$4,0),IF(C6=2,IF(DJ6+DJ7+DJ8+DJ9+DL6+DL7+DL8+DL9=1,Cadeirante/30*GG$4,IF(DJ6+DJ7+DJ8+DJ9+DL6+DL7+DL8+DL9=2,Fixo/30*GG$4,IF(DJ6+DJ7+DJ8+DJ9+DL6+DL7+DL8+DL9>2,Fixo/30*GG$4+(DJ6+DJ7+DJ8+DJ9+DL6+DL7+DL8+DL9-2)*Cadeirante/30*GG$4)))+(DI6+DI7+DI8+DK6+DK7+DK8)*Percapita/30*GG$4+(DI9+DK9)*Crechee/30*GG$4,IF(C6=1,IF(DI6+DI7+DI8+DJ6+DJ7+DJ8+DK6+DK7+DK8+DL6+DL7+DL8<=15,(DI6+DI7+DI8+DK6+DK7+DK8)*Percapita/30*GG$4,IF(DI6+DI7+DI8+DJ6+DJ7+DJ8+DK6+DK7+DK8+DL6+DL7+DL8>=16,Fixo/30*GG$4+(DI6+DI7+DI8+DJ6+DJ7+DJ8+DK6+DK7+DK8+DL6+DL7-16)*Percapita/30*GG$4)))))) -> 0 | GH6: =IF(C6=4,SUM(DM6+DM7+DM8+DO6+DO7+DO8)*Percapita/30*GH$4+(DN6+DN7+DN8+DP6+DP7+DP8)*Cadeirante/30*GH$4,IF(C6=3,IF(DM9+DO9=10,Fixo/30*GH$4+(DM6+DM7+DM8+DO6+DO7+DO8)*Percapita/30*GH$4+(DN9+DP9)*Cadeirante/30*GH$4,IF(DM9+DO9<=9,(DM9+DO9)*Crechee/30*GH$4)+(DN9+DP9)*Cadeirante/30*GH$4+(DM6+DM7+DM8+DO6+DO7+DO8)*Percapita/30*GH$4)+IF(DM9+DO9>=11,Fixo/30*GH$4+(DM9+DO9-10)*Crechee/30*GH$4,0),IF(C6=2,IF(DN6+DN7+DN8+DN9+DP6+DP7+DP8+DP9=1,Cadeirante/30*GH$4,IF(DN6+DN7+DN8+DN9+DP6+DP7+DP8+DP9=2,Fixo/30*GH$4,IF(DN6+DN7+DN8+DN9+DP6+DP7+DP8+DP9>2,Fixo/30*GH$4+(DN6+DN7+DN8+DN9+DP6+DP7+DP8+DP9-2)*Cadeirante/30*GH$4)))+(DM6+DM7+DM8+DO6+DO7+DO8)*Percapita/30*GH$4+(DM9+DO9)*Crechee/30*GH$4,IF(C6=1,IF(DM6+DM7+DM8+DN6+DN7+DN8+DO6+DO7+DO8+DP6+DP7+DP8<=15,(DM6+DM7+DM8+DO6+DO7+DO8)*Percapita/30*GH$4,IF(DM6+DM7+DM8+DN6+DN7+DN8+DO6+DO7+DO8+DP6+DP7+DP8>=16,Fixo/30*GH$4+(DM6+DM7+DM8+DN6+DN7+DN8+DO6+DO7+DO8+DP6+DP7-16)*Percapita/30*GH$4)))))) -> 0 | GI6: =IF(C6=4,SUM(DQ6+DQ7+DQ8+DS6+DS7+DS8)*Percapita/30*GI$4+(DR6+DR7+DR8+DT6+DT7+DT8)*Cadeirante/30*GI$4,IF(C6=3,IF(DQ9+DS9=10,Fixo/30*GI$4+(DQ6+DQ7+DQ8+DS6+DS7+DS8)*Percapita/30*GI$4+(DR9+DT9)*Cadeirante/30*GI$4,IF(DQ9+DS9<=9,(DQ9+DS9)*Crechee/30*GI$4)+(DR9+DT9)*Cadeirante/30*GI$4+(DQ6+DQ7+DQ8+DS6+DS7+DS8)*Percapita/30*GI$4)+IF(DQ9+DS9>=11,Fixo/30*GI$4+(DQ9+DS9-10)*Crechee/30*GI$4,0),IF(C6=2,IF(DR6+DR7+DR8+DR9+DT6+DT7+DT8+DT9=1,Cadeirante/30*GI$4,IF(DR6+DR7+DR8+DR9+DT6+DT7+DT8+DT9=2,Fixo/30*GI$4,IF(DR6+DR7+DR8+DR9+DT6+DT7+DT8+DT9>2,Fixo/30*GI$4+(DR6+DR7+DR8+DR9+DT6+DT7+DT8+DT9-2)*Cadeirante/30*GI$4)))+(DQ6+DQ7+DQ8+DS6+DS7+DS8)*Percapita/30*GI$4+(DQ9+DS9)*Crechee/30*GI$4,IF(C6=1,IF(DQ6+DQ7+DQ8+DR6+DR7+DR8+DS6+DS7+DS8+DT6+DT7+DT8<=15,(DQ6+DQ7+DQ8+DS6+DS7+DS8)*Percapita/30*GI$4,IF(DQ6+DQ7+DQ8+DR6+DR7+DR8+DS6+DS7+DS8+DT6+DT7+DT8>=16,Fixo/30*GI$4+(DQ6+DQ7+DQ8+DR6+DR7+DR8+DS6+DS7+DS8+DT6+DT7-16)*Percapita/30*GI$4)))))) -> 0 | GJ6: =IF(C6=4,SUM(DU6+DU7+DU8+DW6+DW7+DW8)*Percapita/30*GJ$4+(DV6+DV7+DV8+DX6+DX7+DX8)*Cadeirante/30*GJ$4,IF(C6=3,IF(DU9+DW9=10,Fixo/30*GJ$4+(DU6+DU7+DU8+DW6+DW7+DW8)*Percapita/30*GJ$4+(DV9+DX9)*Cadeirante/30*GJ$4,IF(DU9+DW9<=9,(DU9+DW9)*Crechee/30*GJ$4)+(DV9+DX9)*Cadeirante/30*GJ$4+(DU6+DU7+DU8+DW6+DW7+DW8)*Percapita/30*GJ$4)+IF(DU9+DW9>=11,Fixo/30*GJ$4+(DU9+DW9-10)*Crechee/30*GJ$4,0),IF(C6=2,IF(DV6+DV7+DV8+DV9+DX6+DX7+DX8+DX9=1,Cadeirante/30*GJ$4,IF(DV6+DV7+DV8+DV9+DX6+DX7+DX8+DX9=2,Fixo/30*GJ$4,IF(DV6+DV7+DV8+DV9+DX6+DX7+DX8+DX9>2,Fixo/30*GJ$4+(DV6+DV7+DV8+DV9+DX6+DX7+DX8+DX9-2)*Cadeirante/30*GJ$4)))+(DU6+DU7+DU8+DW6+DW7+DW8)*Percapita/30*GJ$4+(DU9+DW9)*Crechee/30*GJ$4,IF(C6=1,IF(DU6+DU7+DU8+DV6+DV7+DV8+DW6+DW7+DW8+DX6+DX7+DX8<=15,(DU6+DU7+DU8+DW6+DW7+DW8)*Percapita/30*GJ$4,IF(DU6+DU7+DU8+DV6+DV7+DV8+DW6+DW7+DW8+DX6+DX7+DX8>=16,Fixo/30*GJ$4+(DU6+DU7+DU8+DV6+DV7+DV8+DW6+DW7+DW8+DX6+DX7-16)*Percapita/30*GJ$4)))))) -> 0 | GK6: =IF(C6=4,SUM(DY6+DY7+DY8+EA6+EA7+EA8)*Percapita/30*GK$4+(DZ6+DZ7+DZ8+EB6+EB7+EB8)*Cadeirante/30*GK$4,IF(C6=3,IF(DY9+EA9=10,Fixo/30*GK$4+(DY6+DY7+DY8+EA6+EA7+EA8)*Percapita/30*GK$4+(DZ9+EB9)*Cadeirante/30*GK$4,IF(DY9+EA9<=9,(DY9+EA9)*Crechee/30*GK$4)+(DZ9+EB9)*Cadeirante/30*GK$4+(DY6+DY7+DY8+EA6+EA7+EA8)*Percapita/30*GK$4)+IF(DY9+EA9>=11,Fixo/30*GK$4+(DY9+EA9-10)*Crechee/30*GK$4,0),IF(C6=2,IF(DZ6+DZ7+DZ8+DZ9+EB6+EB7+EB8+EB9=1,Cadeirante/30*GK$4,IF(DZ6+DZ7+DZ8+DZ9+EB6+EB7+EB8+EB9=2,Fixo/30*GK$4,IF(DZ6+DZ7+DZ8+DZ9+EB6+EB7+EB8+EB9>2,Fixo/30*GK$4+(DZ6+DZ7+DZ8+DZ9+EB6+EB7+EB8+EB9-2)*Cadeirante/30*GK$4)))+(DY6+DY7+DY8+EA6+EA7+EA8)*Percapita/30*GK$4+(DY9+EA9)*Crechee/30*GK$4,IF(C6=1,IF(DY6+DY7+DY8+DZ6+DZ7+DZ8+EA6+EA7+EA8+EB6+EB7+EB8<=15,(DY6+DY7+DY8+EA6+EA7+EA8)*Percapita/30*GK$4,IF(DY6+DY7+DY8+DZ6+DZ7+DZ8+EA6+EA7+EA8+EB6+EB7+EB8>=16,Fixo/30*GK$4+(DY6+DY7+DY8+DZ6+DZ7+DZ8+EA6+EA7+EA8+EB6+EB7-16)*Percapita/30*GK$4)))))) -> 0 | GL6: =IF(C6=4,SUM(EC6+EC7+EC8+EE6+EE7+EE8)*Percapita/30*GL$4+(ED6+ED7+ED8+EF6+EF7+EF8)*Cadeirante/30*GL$4,IF(C6=3,IF(EC9+EE9=10,Fixo/30*GL$4+(EC6+EC7+EC8+EE6+EE7+EE8)*Percapita/30*GL$4+(ED9+EF9)*Cadeirante/30*GL$4,IF(EC9+EE9<=9,(EC9+EE9)*Crechee/30*GL$4)+(ED9+EF9)*Cadeirante/30*GL$4+(EC6+EC7+EC8+EE6+EE7+EE8)*Percapita/30*GL$4)+IF(EC9+EE9>=11,Fixo/30*GL$4+(EC9+EE9-10)*Crechee/30*GL$4,0),IF(C6=2,IF(ED6+ED7+ED8+ED9+EF6+EF7+EF8+EF9=1,Cadeirante/30*GL$4,IF(ED6+ED7+ED8+ED9+EF6+EF7+EF8+EF9=2,Fixo/30*GL$4,IF(ED6+ED7+ED8+ED9+EF6+EF7+EF8+EF9>2,Fixo/30*GL$4+(ED6+ED7+ED8+ED9+EF6+EF7+EF8+EF9-2)*Cadeirante/30*GL$4)))+(EC6+EC7+EC8+EE6+EE7+EE8)*Percapita/30*GL$4+(EC9+EE9)*Crechee/30*GL$4,IF(C6=1,IF(EC6+EC7+EC8+ED6+ED7+ED8+EE6+EE7+EE8+EF6+EF7+EF8<=15,(EC6+EC7+EC8+EE6+EE7+EE8)*Percapita/30*GL$4,IF(EC6+EC7+EC8+ED6+ED7+ED8+EE6+EE7+EE8+EF6+EF7+EF8>=16,Fixo/30*GL$4+(EC6+EC7+EC8+ED6+ED7+ED8+EE6+EE7+EE8+EF6+EF7-16)*Percapita/30*GL$4)))))) -> 0 | GM6: =IF(C6=4,SUM(EG6+EG7+EG8+EI6+EI7+EI8)*Percapita/30*GM$4+(EH6+EH7+EH8+EJ6+EJ7+EJ8)*Cadeirante/30*GM$4,IF(C6=3,IF(EG9+EI9=10,Fixo/30*GM$4+(EG6+EG7+EG8+EI6+EI7+EI8)*Percapita/30*GM$4+(EH9+EJ9)*Cadeirante/30*GM$4,IF(EG9+EI9<=9,(EG9+EI9)*Crechee/30*GM$4)+(EH9+EJ9)*Cadeirante/30*GM$4+(EG6+EG7+EG8+EI6+EI7+EI8)*Percapita/30*GM$4)+IF(EG9+EI9>=11,Fixo/30*GM$4+(EG9+EI9-10)*Crechee/30*GM$4,0),IF(C6=2,IF(EH6+EH7+EH8+EH9+EJ6+EJ7+EJ8+EJ9=1,Cadeirante/30*GM$4,IF(EH6+EH7+EH8+EH9+EJ6+EJ7+EJ8+EJ9=2,Fixo/30*GM$4,IF(EH6+EH7+EH8+EH9+EJ6+EJ7+EJ8+EJ9>2,Fixo/30*GM$4+(EH6+EH7+EH8+EH9+EJ6+EJ7+EJ8+EJ9-2)*Cadeirante/30*GM$4)))+(EG6+EG7+EG8+EI6+EI7+EI8)*Percapita/30*GM$4+(EG9+EI9)*Crechee/30*GM$4,IF(C6=1,IF(EG6+EG7+EG8+EH6+EH7+EH8+EI6+EI7+EI8+EJ6+EJ7+EJ8<=15,(EG6+EG7+EG8+EI6+EI7+EI8)*Percapita/30*GM$4,IF(EG6+EG7+EG8+EH6+EH7+EH8+EI6+EI7+EI8+EJ6+EJ7+EJ8>=16,Fixo/30*GM$4+(EG6+EG7+EG8+EH6+EH7+EH8+EI6+EI7+EI8+EJ6+EJ7-16)*Percapita/30*GM$4)))))) -> 0 | GO6: =IF(J6="ADAPTADO",T6*Cadeirante/30*GP6+S6*Percapita/30*GP6,IF(J6="NORMAL",(S6+T6)*Percapita/30*GP6,IF(J6="CRECHE",0)))*-1 -> 0 | GQ6: =SUMIF(V6:V9,"<0")*Cadeirante/30*GQ$4+SUMIF(X6:X9,"<0")*Cadeirante/30*GQ$4 -> 0 | GR6: =SUMIF(Z6:Z9,"<0")*Cadeirante/30*GR$4+SUMIF(AB6:AB9,"<0")*Cadeirante/30*GR$4 -> 0 | GS6: =SUMIF(AD6:AD9,"<0")*Cadeirante/30*GS$4+SUMIF(AF6:AF9,"<0")*Cadeirante/30*GS$4 -> 0 | GT6: =SUMIF(AH6:AH9,"<0")*Cadeirante/30*GT$4+SUMIF(AJ6:AJ9,"<0")*Cadeirante/30*GT$4 -> 0 | GU6: =SUMIF(AL6:AL9,"<0")*Cadeirante/30*GU$4+SUMIF(AN6:AN9,"<0")*Cadeirante/30*GU$4 -> 0 | GV6: =SUMIF(AP6:AP9,"<0")*Cadeirante/30*GV$4+SUMIF(AR6:AR9,"<0")*Cadeirante/30*GV$4 -> 0 | GW6: =SUMIF(AT6:AT9,"<0")*Cadeirante/30*GW$4+SUMIF(AV6:AV9,"<0")*Cadeirante/30*GW$4 -> 0 | GX6: =SUMIF(AX6:AX9,"<0")*Cadeirante/30*GX$4+SUMIF(AZ6:AZ9,"<0")*Cadeirante/30*GX$4 -> 0 | GY6: =SUMIF(BB6:BB9,"<0")*Cadeirante/30*GY$4+SUMIF(BD6:BD9,"<0")*Cadeirante/30*GY$4 -> 0 | GZ6: =SUMIF(BF6:BF9,"<0")*Cadeirante/30*GZ$4+SUMIF(BH6:BH9,"<0")*Cadeirante/30*GZ$4 -> 0 | HA6: =SUMIF(BJ6:BJ9,"<0")*Cadeirante/30*HA$4+SUMIF(BL6:BL9,"<0")*Cadeirante/30*HA$4 -> 0 | HB6: =SUMIF(BN6:BN9,"<0")*Cadeirante/30*HB$4+SUMIF(BP6:BP9,"<0")*Cadeirante/30*HB$4 -> 0 | HC6: =SUMIF(BR6:BR9,"<0")*Cadeirante/30*HC$4+SUMIF(BT6:BT9,"<0")*Cadeirante/30*HC$4 -> 0 | HD6: =SUMIF(BV6:BV9,"<0")*Cadeirante/30*HD$4+SUMIF(BX6:BX9,"<0")*Cadeirante/30*HD$4 -> 0 | HE6: =SUMIF(BZ6:BZ9,"<0")*Cadeirante/30*HE$4+SUMIF(CB6:CB9,"<0")*Cadeirante/30*HE$4 -> 0 | HF6: =SUMIF(CD6:CD9,"<0")*Cadeirante/30*HF$4+SUMIF(CF6:CF9,"<0")*Cadeirante/30*HF$4 -> 0 | HG6: =SUMIF(CH6:CH9,"<0")*Cadeirante/30*HG$4+SUMIF(CJ6:CJ9,"<0")*Cadeirante/30*HG$4 -> 0 | HH6: =SUMIF(CL6:CL9,"<0")*Cadeirante/30*HH$4+SUMIF(CN6:CN9,"<0")*Cadeirante/30*HH$4 -> 0 | HI6: =SUMIF(CP6:CP9,"<0")*Cadeirante/30*HI$4+SUMIF(CR6:CR9,"<0")*Cadeirante/30*HI$4 -> 0 | HJ6: =SUMIF(CT6:CT9,"<0")*Cadeirante/30*HJ$4+SUMIF(CV6:CV9,"<0")*Cadeirante/30*HJ$4 -> 0 | HK6: =SUMIF(CX6:CX9,"<0")*Cadeirante/30*HK$4+SUMIF(CZ6:CZ9,"<0")*Cadeirante/30*HK$4 -> 0 | HL6: =SUMIF(DB6:DB9,"<0")*Cadeirante/30*HL$4+SUMIF(DD6:DD9,"<0")*Cadeirante/30*HL$4 -> 0 | HM6: =SUMIF(DF6:DF9,"<0")*Cadeirante/30*HM$4+SUMIF(DH6:DH9,"<0")*Cadeirante/30*HM$4 -> 0 | HN6: =SUMIF(DJ6:DJ9,"<0")*Cadeirante/30*HN$4+SUMIF(DL6:DL9,"<0")*Cadeirante/30*HN$4 -> 0 | HO6: =SUMIF(DN6:DN9,"<0")*Cadeirante/30*HO$4+SUMIF(DP6:DP9,"<0")*Cadeirante/30*HO$4 -> 0 | HP6: =SUMIF(DR6:DR9,"<0")*Cadeirante/30*HP$4+SUMIF(DT6:DT9,"<0")*Cadeirante/30*HP$4 -> 0 | HQ6: =SUMIF(DV6:DV9,"<0")*Cadeirante/30*HQ$4+SUMIF(DX6:DX9,"<0")*Cadeirante/30*HQ$4 -> 0 | HR6: =SUMIF(DZ6:DZ9,"<0")*Cadeirante/30*HR$4+SUMIF(EB6:EB9,"<0")*Cadeirante/30*HR$4 -> 0 | HS6: =SUMIF(ED6:ED9,"<0")*Cadeirante/30*HS$4+SUMIF(EF6:EF9,"<0")*Cadeirante/30*HS$4 -> 0 | HZ6: 17629.31 | IB6: =IF(ISTEXT(EM6), VALUE(EM6), EM6) -> 0 | IC6: =IF(ISTEXT(EN6), VALUE(EN6), EN6) -> 0 | ID6: =IF(ISTEXT(EO6), VALUE(EO6), EO6) -> 0 | IE6: =HZ6=FF6 -> FALSE
A7: 029.007-00 | B7: 2025/0018729-001 | C7: FBE | D7: 2025/0018729 | E7: DTE1882 | F7: 01/04/2026 | G7: 30/04/2026 | H7: 25.292.508 CLAUDIA COSTA BORCA | I7: CLAUDIA COSTA BORCA | J7: NORMAL | K7: EMEF | L7: =CONTINUA!BV7 -> 43 | M7: =CONTINUA!BW7 -> 1 | O7: 6020.2025/0018729-5 | P7: O | AO7: 1 | AS7: 1 | BQ7: -1 | EP7: =Q7 -> 0 | EQ7: =U7+Y7+AC7+AG7+AK7+AO7+AS7+AW7+BA7+BE7+BI7+BM7+BQ7+BU7+BY7+CC7+CG7+CK7+CO7+CS7+CW7+DA7+DE7+DI7+DM7+DQ7+DU7+DY7+EC7+EG7 -> 1 | ER7: =S7+W7+AA7+AE7+AI7+AM7+AQ7+AU7+AY7+BC7+BG7+BK7+BO7+BS7+BW7+CA7+CE7+CI7+CM7+CQ7+CU7+CY7+DC7+DG7+DK7+DO7+DS7+DW7+EA7+EE7+EI7 -> 0 | ES7: =R7 -> 0 | ET7: =V7+Z7+AD7+AH7+AL7+AP7+AT7+AX7+BB7+BF7+BJ7+BN7+BR7+BV7+BZ7+CD7+CH7+CL7+CP7+CT7+CX7+DB7+DF7+DJ7+DN7+DR7+DV7+DZ7+ED7+EH7 -> 0 | EU7: =T7+X7+AB7+AF7+AJ7+AN7+AR7+AV7+AZ7+BD7+BH7+BL7+BP7+BT7+BX7+CB7+CF7+CJ7+CN7+CR7+CV7+CZ7+DD7+DH7+DL7+DP7+DT7+DX7+EB7+EF7+EJ7 -> 0 | EV7: =EP7+EQ7+ES7+ET7+ER7+EU7 -> 1 | EX7: =FH7 -> 0 | EY7: =(L7*regular)+(M7*Cadeirantee) -> 470.72038 | EZ7: =SUMIF(FI7:GM7,">0") -> 0 | FA7: =SUMIF(FI7:GM7,"<0")+SUMIF(GQ7:HS7,"<0") -> 0 | FB7: 0 | FC7: =N7*km*'VALORES TABELA'!$B$13 -> 0 | FD7: =GO7 -> 0 | GO7: =IF(J7="ADAPTADO",T7*Cadeirante/30*GP7+S7*Percapita/30*GP7,IF(J7="NORMAL",(S7+T7)*Percapita/30*GP7,IF(J7="CRECHE",0)))*-1 -> 0 | IB7: =IF(ISTEXT(EM7), VALUE(EM7), EM7) -> 0 | IC7: =IF(ISTEXT(EN7), VALUE(EN7), EN7) -> 0 | ID7: =IF(ISTEXT(EO7), VALUE(EO7), EO7) -> 0
A8: 029.007-00 | B8: 2025/0018729-001 | C8: FB | D8: 2025/0018729 | E8: DTE1882 | F8: 01/04/2026 | G8: 30/04/2026 | H8: 25.292.508 CLAUDIA COSTA BORCA | I8: CLAUDIA COSTA BORCA | J8: NORMAL | K8: EMEE | L8: =CONTINUA!BV8 -> 0 | M8: =CONTINUA!BW8 -> 0 | O8: 6020.2025/0018729-5 | P8: O | Q8: 8 | S8: 2 | EP8: =Q8 -> 8 | EQ8: =U8+Y8+AC8+AG8+AK8+AO8+AS8+AW8+BA8+BE8+BI8+BM8+BQ8+BU8+BY8+CC8+CG8+CK8+CO8+CS8+CW8+DA8+DE8+DI8+DM8+DQ8+DU8+DY8+EC8+EG8 -> 0 | ER8: =S8+W8+AA8+AE8+AI8+AM8+AQ8+AU8+AY8+BC8+BG8+BK8+BO8+BS8+BW8+CA8+CE8+CI8+CM8+CQ8+CU8+CY8+DC8+DG8+DK8+DO8+DS8+DW8+EA8+EE8+EI8 -> 2 | ES8: =R8 -> 0 | ET8: =V8+Z8+AD8+AH8+AL8+AP8+AT8+AX8+BB8+BF8+BJ8+BN8+BR8+BV8+BZ8+CD8+CH8+CL8+CP8+CT8+CX8+DB8+DF8+DJ8+DN8+DR8+DV8+DZ8+ED8+EH8 -> 0 | EU8: =T8+X8+AB8+AF8+AJ8+AN8+AR8+AV8+AZ8+BD8+BH8+BL8+BP8+BT8+BX8+CB8+CF8+CJ8+CN8+CR8+CV8+CZ8+DD8+DH8+DL8+DP8+DT8+DX8+EB8+EF8+EJ8 -> 0 | EV8: =EP8+EQ8+ES8+ET8+ER8+EU8 -> 10 | EX8: =FH8 -> 0 | EY8: =(L8*regular)+(M8*Cadeirantee) -> 0 | EZ8: =SUMIF(FI8:GM8,">0") -> 0 | FA8: =SUMIF(FI8:GM8,"<0")+SUMIF(GQ8:HS8,"<0") -> 0 | FB8: 0 | FC8: =N8*km*'VALORES TABELA'!$B$13 -> 0 | FD8: =GO8 -> 0 | GO8: =IF(J8="ADAPTADO",T8*Cadeirante/30*GP8+S8*Percapita/30*GP8,IF(J8="NORMAL",(S8+T8)*Percapita/30*GP8,IF(J8="CRECHE",0)))*-1 -> 0 | IB8: =IF(ISTEXT(EM8), VALUE(EM8), EM8) -> 0 | IC8: =IF(ISTEXT(EN8), VALUE(EN8), EN8) -> 0 | ID8: =IF(ISTEXT(EO8), VALUE(EO8), EO8) -> 0
A9: 029.007-00 | B9: 2025/0018729-001 | C9: FB | D9: 2025/0018729 | E9: DTE1882 | F9: 01/04/2026 | G9: 30/04/2026 | H9: 25.292.508 CLAUDIA COSTA BORCA | I9: CLAUDIA COSTA BORCA | J9: NORMAL | K9: CEI | L9: =CONTINUA!BV9 -> 0 | M9: =CONTINUA!BW9 -> 0 | N9: 1 | O9: 6020.2025/0018729-5 | P9: O | EP9: =Q9 -> 0 | EQ9: =U9+Y9+AC9+AG9+AK9+AO9+AS9+AW9+BA9+BE9+BI9+BM9+BQ9+BU9+BY9+CC9+CG9+CK9+CO9+CS9+CW9+DA9+DE9+DI9+DM9+DQ9+DU9+DY9+EC9+EG9 -> 0 | ER9: =S9+W9+AA9+AE9+AI9+AM9+AQ9+AU9+AY9+BC9+BG9+BK9+BO9+BS9+BW9+CA9+CE9+CI9+CM9+CQ9+CU9+CY9+DC9+DG9+DK9+DO9+DS9+DW9+EA9+EE9+EI9 -> 0 | ES9: =R9 -> 0 | ET9: =V9+Z9+AD9+AH9+AL9+AP9+AT9+AX9+BB9+BF9+BJ9+BN9+BR9+BV9+BZ9+CD9+CH9+CL9+CP9+CT9+CX9+DB9+DF9+DJ9+DN9+DR9+DV9+DZ9+ED9+EH9 -> 0 | EU9: =T9+X9+AB9+AF9+AJ9+AN9+AR9+AV9+AZ9+BD9+BH9+BL9+BP9+BT9+BX9+CB9+CF9+CJ9+CN9+CR9+CV9+CZ9+DD9+DH9+DL9+DP9+DT9+DX9+EB9+EF9+EJ9 -> 0 | EV9: =EP9+EQ9+ES9+ET9+ER9+EU9 -> 0 | EX9: =FH9 -> 0 | EY9: =(L9*regular)+(M9*Cadeirantee) -> 0 | EZ9: =SUMIF(FI9:GM9,">0") -> 0 | FA9: =SUMIF(FI9:GM9,"<0")+SUMIF(GQ9:HS9,"<0") -> 0 | FB9: 0 | FC9: =N9*km*'VALORES TABELA'!$B$13 -> 24.32 | FD9: =GO9 -> 0 | GO9: =IF(J9="ADAPTADO",T9*Cadeirante/30*GP9+S9*Percapita/30*GP9,IF(J9="NORMAL",(S9+T9)*Percapita/30*GP9,IF(J9="CRECHE",0)))*-1 -> 0 | IB9: =IF(ISTEXT(EM9), VALUE(EM9), EM9) -> 0 | IC9: =IF(ISTEXT(EN9), VALUE(EN9), EN9) -> 0 | ID9: =IF(ISTEXT(EO9), VALUE(EO9), EO9) -> 0
A10: 029.007-00 | B10: 2025/0018729-001 | C10: FB | D10: 2025/0018729 | E10: DTE1882 | F10: 01/04/2026 | G10: 30/04/2026 | H10: 25.292.508 CLAUDIA COSTA BORCA | I10: CLAUDIA COSTA BORCA | J10: NORMAL | K10: CCA | L10: =CONTINUA!BV10 -> 0 | M10: =CONTINUA!BW10 -> 0 | O10: 6020.2025/0018729-5 | P10: O | EP10: =Q10 -> 0 | EQ10: =U10+Y10+AC10+AG10+AK10+AO10+AS10+AW10+BA10+BE10+BI10+BM10+BQ10+BU10+BY10+CC10+CG10+CK10+CO10+CS10+CW10+DA10+DE10+DI10+DM10+DQ10+DU10+DY10+EC10+EG10 -> 0 | ER10: =S10+W10+AA10+AE10+AI10+AM10+AQ10+AU10+AY10+BC10+BG10+BK10+BO10+BS10+BW10+CA10+CE10+CI10+CM10+CQ10+CU10+CY10+DC10+DG10+DK10+DO10+DS10+DW10+EA10+EE10+EI10 -> 0 | ES10: =R10 -> 0 | ET10: =V10+Z10+AD10+AH10+AL10+AP10+AT10+AX10+BB10+BF10+BJ10+BN10+BR10+BV10+BZ10+CD10+CH10+CL10+CP10+CT10+CX10+DB10+DF10+DJ10+DN10+DR10+DV10+DZ10+ED10+EH10 -> 0 | EU10: =T10+X10+AB10+AF10+AJ10+AN10+AR10+AV10+AZ10+BD10+BH10+BL10+BP10+BT10+BX10+CB10+CF10+CJ10+CN10+CR10+CV10+CZ10+DD10+DH10+DL10+DP10+DT10+DX10+EB10+EF10+EJ10 -> 0 | EV10: =EP10+EQ10+ES10+ET10+ER10+EU10 -> 0 | EX10: 0 | EY10: 0 | EZ10: 0 | FA10: 0 | FB10: =SUM(FH10:GL10)/2 -> 0 | FC10: =N10*km*'VALORES TABELA'!$B$13 -> 0 | FD10: =GO10 -> 0 | FH10: =((Q10+S10)*Percapita)+((R10+T10)*Cadeirante) -> 0 | FI10: =((U10+W10)*Percapita/30*FI$4)+((V10+X10)*Cadeirante/30*FI$4) -> 0 | FJ10: =((Y10+AA10)*Percapita/30*FJ$4)+((Z10+AB10)*Cadeirante/30*FJ$4) -> 0 | FL10: =((AC10+AE10)*Percapita/30*FL$4)+((AD10+AF10)*Cadeirante/30*FL$4) -> 0 | FM10: =((AG10+AI10)*Percapita/30*FM$4)+((AH10+AJ10)*Cadeirante/30*FM$4) -> 0 | FN10: =((AK10+AM10)*Percapita/30*FN$4)+((AL10+AN10)*Cadeirante/30*FN$4) -> 0 | FO10: =((AO10+AQ10)*Percapita/30*FO$4)+((AP10+AR10)*Cadeirante/30*FO$4) -> 0 | FP10: =((AS10+AU10)*Percapita/30*FP$4)+((AT10+AV10)*Cadeirante/30*FP$4) -> 0 | FQ10: =((AW10+AY10)*Percapita/30*FQ$4)+((AX10+AZ10)*Cadeirante/30*FQ$4) -> 0 | FR10: =((BA10+BC10)*Percapita/30*FR$4)+((BB10+BD10)*Cadeirante/30*FR$4) -> 0 | FS10: =((BE10+BG10)*Percapita/30*FS$4)+((BF10+BH10)*Cadeirante/30*FS$4) -> 0 | FT10: =((BI10+BK10)*Percapita/30*FT$4)+((BJ10+BL10)*Cadeirante/30*FT$4) -> 0 | FU10: =((BM10+BO10)*Percapita/30*FU$4)+((BN10+BP10)*Cadeirante/30*FU$4) -> 0 | FV10: =((BQ10+BS10)*Percapita/30*FV$4)+((BR10+BT10)*Cadeirante/30*FV$4) -> 0 | FW10: =((BU10+BW10)*Percapita/30*FW$4)+((BV10+BX10)*Cadeirante/30*FW$4) -> 0 | FX10: =((BY10+CA10)*Percapita/30*FX$4)+((BZ10+CB10)*Cadeirante/30*FX$4) -> 0 | FY10: =((CC10+CE10)*Percapita/30*FY$4)+((CD10+CF10)*Cadeirante/30*FY$4) -> 0 | FZ10: =((CG10+CI10)*Percapita/30*FZ$4)+((CI10+CK10)*Cadeirante/30*FZ$4) -> 0 | GA10: =((CK10+CM10)*Percapita/30*GA$4)+((CL10+CN10)*Cadeirante/30*GA$4) -> 0 | GB10: =((CO10+CQ10)*Percapita/30*GB$4)+((CP10+CR10)*Cadeirante/30*GB$4) -> 0 | GC10: =((CS10+CU10)*Percapita/30*GC$4)+((CT10+CV10)*Cadeirante/30*GC$4) -> 0 | GD10: =((CW10+CY10)*Percapita/30*GD$4)+((CX10+CZ10)*Cadeirante/30*GD$4) -> 0 | GE10: =((DA10+DC10)*Percapita/30*GE$4)+((DB10+DD10)*Cadeirante/30*GE$4) -> 0 | GF10: =((DE10+DG10)*Percapita/30*GF$4)+((DF10+DH10)*Cadeirante/30*GF$4) -> 0 | GG10: =((DI10+DK10)*Percapita/30*GG$4)+((DJ10+DL10)*Cadeirante/30*GG$4) -> 0 | GH10: =((DM10+DO10)*Percapita/30*GH$4)+((DN10+DP10)*Cadeirante/30*GH$4) -> 0 | GI10: =((DQ10+DS10)*Percapita/30*GI$4)+((DR10+DT10)*Cadeirante/30*GI$4) -> 0 | GJ10: =((DU10+DW10)*Percapita/30*GJ$4)+((DV10+DX10)*Cadeirante/30*GJ$4) -> 0 | GK10: =((DY10+EA10)*Percapita/30*GK$4)+((DZ10+EB10)*Cadeirante/30*GK$4) -> 0 | GL10: =((EC10+EE10)*Percapita/30*GL$4)+((ED10+EF10)*Cadeirante/30*GL$4) -> 0 | GM10: =((EG10+EI10)*Percapita)+((EH10+EJ10)*Cadeirante) -> 0 | GO10: =IF(J10="ADAPTADO",T10*Cadeirante/30*GP10+S10*Percapita/30*GP10,IF(J10="NORMAL",(S10+T10)*Percapita/30*GP10,IF(J10="CRECHE",0)))*-1 -> 0 | IB10: =IF(ISTEXT(EM10), VALUE(EM10), EM10) -> 0 | IC10: =IF(ISTEXT(EN10), VALUE(EN10), EN10) -> 0 | ID10: =IF(ISTEXT(EO10), VALUE(EO10), EO10) -> 0
I12: valores acumulados de apontamento serviços do dia 01/04/2026
I13: Não cadeirante presencial (EMEI, EMEF,EMEE) | J13: =Q6+Q7+Q8 -> 8
I14: Não cadeirante at compl (EMEI, EMEF,EMEE) | J14: =+S6+S7+S8 -> 2 | L14: Calculo valores Remuneracao Servicos para COLUNAS teg Reg. Fixo e teg Reg. Percapita
I15: cadeirante (EMEI, EMEF, EMEE) | J15: =+R6+R7+R8 -> 0 | L15: Regular | M15: Pecapta | N15: Fixo | Q15: Tabela Modalidade x Bancada x Pagamento x Condicao
I16: Cadeirante Atendimento compl (EMEI, EMEF, EMEE) | J16: =+T6+T7+T8 -> 0 | L16: <=15 | M16: =IF(J21<=15,J21*J28,0) -> 3852.3 | O16: =SUM(M16:N18) -> 1540.92
I17: cadeirante (EMEI, EMEF,EMEE, CEI) + Cadeirante Atendimento compl (EMEI, EMEF, EMEE, CEi) | J17: =R6+R7+R8+R9+T6+T7+T8+T9 -> 0 | L17: =16 | N17: =IF(J21>15,J27) -> FALSE | Q17: 15
I18: cadeirante (EMEI, EMEF, EMEE) + Cadeirante Atendimento compl (EMEI, EMEF, EMEE) | J18: =(R6+R7+R8+T6+T7+T8) -> 0 | L18: >16 | M18: =(J21-16)*J28 -> -2311.38 | Q18: 16
I19: Não cadeirante presencial (CEI) + Não cadeirante at compl (CEI) | J19: =(Q9+S9) -> 0
I20: Não cadeirante presencial e at compl (EMEI, EMEF,EMEE) + cadeirante presencial e at compl (EMEI, EMEF,EMEE) | J20: =J13+J15+J14+J16 -> 10
I21: Não cadeirante presencial + at compl (EMEI, EMEF,EMEE) | J21: =SUM(J13+J14) -> 10
I22: km | J22: =SUM(N6:N10) -> 1
I23: Continua não cadeirante | J23: =SUM(CONTINUA!L6:L10) -> 1
I24: Continua Cadeirante | J24: =SUM(CONTINUA!M6:M10) -> 1
I26: Tabela continua_valor, km_valor e Tabela Modalidade x Bancada x Pagamento x Condicao Valor
I27: Fixo (7492,52) /30*30 | J27: =Fixo/30*FH$4 -> 7492.52
I28: Percapita/30*FH$4 | J28: =Percapita/30*FH$4 -> 385.23
I29: Cadeirante/30*FH$4 | J29: =Cadeirante/30*FH$4 -> 2043.65
I30: Crechee/30*FH$4 | J30: =Crechee/30*FH$4 -> 621.14
I31: Fixo Especial | J31: 11465.63
I32: km | J32: 1.28
I33: Continua não cadeirante | J33: 9.64
I34: Continua Cadeirante | J34: 56.2
I37: Regular | J37: Pecapta | K37: Fixo
I38: <=15 | J38: =J21*J28 -> 3852.3
I39: <=15 | K39: =J27 -> 7492.52 | L39: =IF(C6=1,IF(J20<=15,J38,IF(J20>=16,J40+K39))) -> 3852.3
I40: >16 | J40: =(J20-16)*J28 -> -2311.38
I47: Acessivel | J47: Pecapta | K47: Fixo
I48: 1 aluno | L48: =IF(J17>2,K49) -> FALSE | FN48: =-2 -> -2
I49: 2 alunos | K49: =J27+J50 -> 3405.22 | L49: =IF(J17=2,J27,F22) -> 0 | M49: 1
I50: +3 alunos | J50: =(J17-2)*J29 -> -4087.3 | L50: =IF(J17=1,J29,+F38) -> 0 | M50: 2
I52: Acessivel | J52: Pecapta | K52: Fixo
I53: 1 aluno | J53: =IF(J17=M49,J29,0) -> 0
I54: 2 alunos | K54: =IF(J17>=M50,J27,0) -> 0 | L54: =SUM(J53:K55) -> 0
I55: +3 alunos | J55: =IF(J17>M50,(J17-M50)*J29,0) -> 0
I57: duvida entrou CEI e segundo d Walter não deveria
I60: Creche | J60: Pecapta | K60: Fixo
I61: <=9 | J61: =J19*J30 -> 0 | L61: =IF(J19<=9,+J61) -> 0
L62: =IF(J19=10,J27) -> FALSE | M62: 9
I63: >=11 | J63: =(J19-10)*J30 -> -6211.4 | K63: =J27+J63 -> 1281.12 | L63: =IF(J19>=11,+K63,0) -> 0 | M63: 10
I64: Acessivel | J64: Pecapta | K64: Fixo
I65: ate 9 alunos | J65: =IF(J19<=M62,J30*J19,0) -> 0
I66: 10 alunos | K66: =IF(J19>=M63,J27,0) -> 0 | L66: =SUM(J65:K67) -> 0
I67: +11 alunos | J67: =IF(J19>M63,(J19-M63)*J30,0) -> 0
I72: Especial
I73: Fixo | J73: Percapta - Regular | K73: Percapta - Acessivel
I75: =+J31 -> 11465.63 | J75: =+J21*J28 -> 3852.3 | K75: =+J17*J29 -> 0 | L75: =SUM(I75:K75) -> 15317.93
I78: =IF((J13+J15+J14+J16)>=1,J31,0) -> 11465.63 | J78: =IF((J13+J14)>=1,(J13+J14)*J28,0) -> 3852.3 | K78: =IF((J15+J16)>=1,(J15+J16)*J29,0) -> 0 | L78: =SUM(I78:K78) -> 15317.93
I84: km
I85: Fixo
I86: <=6 KM
I87: >=6 KM | L87: =IF(J22>0,J22*J32,0) -> 1.28
I91: CONTINUA | J91: REGULAR/ N cadeirante | K91: CADEIRANTE
I92: Fixo | J92: PERCAPTA
I94: 2,4% DO VALOR | J94: =IF(J23>0,J23*J33,0) -> 9.64 | K94: =IF(J24>0,J24*J34,0) -> 56.2 | L94: =SUM(J94:K94) -> 65.84

Sheet APELIDOS
A1: CREDENCIADO | B1: APELIDO
A2: COOP DE TR DA CAP DE SP - COOPER CAPITAL | B2: COOPER CAPITAL
A3: COOP DE TRANSP ESC DA Z SUL DE SP - COOPERTRES | B3: COOPERTRES
A4: COOP DE TRANSP ESC DA Z SUL DE SP - COOPERTRES | B4: COOPERTRES
A5: COOP DE TRANSP ESC DA Z SUL DE SP - COOPERTRES | B5: COOPERTRES
A6: COOP DE TRANSP ESC DA Z SUL DE SP - COOPERTRES | B6: COOPERTRES
A7: COOP DE TRANSP ESC DA Z SUL DE SP - COOPERTRES | B7: COOPERTRES
A8: COOP DE TRANSP ESC DA Z SUL DE SP - COOPERTRES | B8: COOPERTRES
A9: COOP DE TRANSP ESC NORTE SAO PAULO - COOPERNORTE | B9: COOPERNORTE
A10: COOP DE TRANSP ESC NORTE SAO PAULO - COOPERNORTE | B10: COOPERNORTE
A11: COOP DE TRANSP ESC NORTE SAO PAULO - COOPERNORTE | B11: COOPERNORTE
A12: COOP TRANSP ESC CAP SOC COOPERCAPS | B12: COOPERCAPS
... A3867: VIA LUZ TRANSPORTES DE PASSAGEIROS LTDA - EPP | B3867: VIA LUZ

Sheet VALORES TABELA
A1: Descrição | B1: Atual | D1: Anterior COM AUMENTO 4,91 | F1: Anterior ANTES DO AUMENTO | J1: 2428.8 | K1: 0 | M1: Faixa 1
A2: Percapita | B2: 385.23 | D2: 350.21 | F2: 333.82 | J2: 2826.65 | K2: 0.075 | L2: 182.16 | M2: Faixa 2
A3: Fixo | B3: 7492.52 | D3: 6811.38 | F3: 6492.53 | J3: 3751.05 | K3: 0.15 | L3: 394.16 | M3: Faixa 3
A4: Cadeirante | B4: 2043.65 | D4: 2043.65 | F4: 1947.98 | J4: 4664.68 | K4: 0.225 | L4: 675.49 | M4: Faixa 4
A5: Crechee | B5: 621.14 | D5: 564.67 | F5: 538.24 | J5: 999999999 | K5: 0.275 | L5: 908.73 | M5: Faixa 5
A6: Especiall | B6: 11465.63 | D6: 10423.3 | F6: 9935.37 | J6: 5000 | K6: 7350 | L6: 978.62 | M6: 0.133145
A7: Km | B7: 1.28 | D7: 1.16 | F7: 1.08
A8: 2,5% Regular | B8: 9.64 | D8: 8.75525 | F8: 8.35 | J8: IR 2026
A9: 2,5% Cadeirantee | B9: 56.200375 | D9: 51.09125 | F9: 48.7
A11: Periodo de Operação | B11: 46113 | C11: 46142
A13: DIAS LETIVOS | B13: =VLOOKUP(B11,A24:B34,2) -> 19
A16: Optante
A17: Cooperativa | B17: 0.015 | E17: a digitar
A18: Outros | B18: 0.024
A22: Dias Letivos
A23: 46023 | B23: 0
A24: 46054 | B24: 16
A25: 46082 | B25: 22
A26: 46113 | B26: 19
A27: 46143 | B27: 20
A28: 46174 | B28: 20
A29: 46204
A30: 46235
A31: 46266
A32: 46296
A33: 46327
A34: 46357
A37: Previsao de Crédito | B37: 46171
A40: Retenção INSS
A41: indice A | B41: 0.2
A42: indice B | B42: 0.11
A44: retençao
A45: indice A | B45: 0.2
A46: indice B | B46: 0.025
A50: Nova Base | B50: 0.6
A54: Nova base de cálculo IRRF | D54: Descrição
A55: Valor base | B55: % Retenção | C55: Desconto
A56: 2428.8 | B56: 0 | C56: 0 | D56: Até 2.428,80
A57: 2826.65 | B57: 0.075 | C57: 182.16 | D57: De 2.428,81 até 2.826,65
A58: 3751.05 | B58: 0.15 | C58: 394.16 | D58: De 2.826,66 até 3.751,05
A59: 4664.68 | B59: 0.225 | C59: 675.49 | D59: De 3.751,06 até 4.664,68
A60: 4664.69 | B60: 0.275 | C60: 908.73 | D60: Acima de 4.664,68

Sheet CONTINUA
A1: ='APONTAMENTO CREDENCIAMENTO'!A1 -> Freguesia / Brasilândia | G1: ='BASE C'!E4 -> ABRIL | I1: APONTAMENTO CREDENCIAMENTO
G2: 01/06 a 30/06/2025
B3: =A3+1 -> 1 | C3: 3 | D3: 3 | F3: =D3+1 -> 4 | G3: 5 | H3: =G3+1 -> 6 | I3: =H3+1 -> 7 | J3: =I3+1 -> 8 | K3: =J3+1 -> 9
A4: CRMC | B4: OS | C4: DRE | D4: CONTRATO | E4: PLACA | F4: PERÍODO | H4: EMPRESA | I4: NOME CONDUTOR | J4: TIPO DE VEÍCULO (NORMAL, ADAPTADO) | K4: TIPO DE ATENDIMENTO | L4: =F5 -> 46113 | N4: =L4+1 -> 46114 | P4: =N4+1 -> 46115 | R4: =P4+1 -> 46116 | T4: =R4+1 -> 46117 | V4: =T4+1 -> 46118 | X4: =V4+1 -> 46119 | Z4: =X4+1 -> 46120 | AB4: =Z4+1 -> 46121 | AD4: =AB4+1 -> 46122 | AF4: =AD4+1 -> 46123 | AH4: =AF4+1 -> 46124 | AJ4: =AH4+1 -> 46125 | AL4: =AJ4+1 -> 46126 | AN4: =AL4+1 -> 46127 | AP4: =AN4+1 -> 46128 | AR4: =AP4+1 -> 46129 | AT4: =AR4+1 -> 46130 | AV4: =AT4+1 -> 46131 | AX4: =AV4+1 -> 46132 | AZ4: =AX4+1 -> 46133 | BB4: =AZ4+1 -> 46134 | BD4: =BB4+1 -> 46135 | BF4: =BD4+1 -> 46136 | BH4: =BF4+1 -> 46137 | BJ4: =BH4+1 -> 46138 | BL4: =BJ4+1 -> 46139 | BN4: =BL4+1 -> 46140 | BP4: =BN4+1 -> 46141 | BR4: =BP4+1 -> 46142 | BV4: TOTAL GERAL REG | BW4: TOTAL GERAL CAD
F5: ='VALORES TABELA'!$B$11 -> 46113 | G5: ='VALORES TABELA'!$C$11 -> 46142 | L5: Cont N CAD | M5: Cont CAD | N5: Cont N CAD | O5: Cont CAD | P5: Cont N CAD | Q5: Cont CAD | R5: Cont N CAD | S5: Cont CAD | T5: Cont N CAD | U5: Cont CAD | V5: Cont N CAD | W5: Cont CAD | X5: Cont N CAD | Y5: Cont CAD | Z5: Cont N CAD | AA5: Cont CAD | AB5: Cont N CAD | AC5: Cont CAD | AD5: Cont N CAD | AE5: Cont CAD | AF5: Cont N CAD | AG5: Cont CAD | AH5: Cont N CAD | AI5: Cont CAD | AJ5: Cont N CAD | AK5: Cont CAD | AL5: Cont N CAD | AM5: Cont CAD | AN5: Cont N CAD | AO5: Cont CAD | AP5: Cont N CAD | AQ5: Cont CAD | AR5: Cont N CAD | AS5: Cont CAD | AT5: Cont N CAD | AU5: Cont CAD | AV5: Cont N CAD | AW5: Cont CAD | AX5: Cont N CAD | AY5: Cont CAD | AZ5: Cont N CAD | BA5: Cont CAD | BB5: Cont N CAD | BC5: Cont CAD | BD5: Cont N CAD | BE5: Cont CAD | BG5: Cont CAD | BH5: Cont N CAD | BJ5: Cont N CAD | BK5: Cont CAD | BL5: Cont N CAD | BM5: Cont CAD | BN5: Cont N CAD | BO5: Cont CAD | BP5: Cont N CAD | BQ5: Cont CAD | BR5: Cont N CAD | BS5: Cont CAD | BT5: Cont N CAD | BU5: Cont CAD
A6: 029.007-00 | B6: 2025/0018729-001 | C6: 1 | D6: 2025/0018729 | E6: DTE1882 | F6: 01/04/2026 | G6: 30/04/2026 | H6: 25.292.508 CLAUDIA COSTA BORCA | I6: CLAUDIA COSTA BORCA | J6: NORMAL | K6: EMEI | BV6: =L6+N6+P6+R6+T6+V6+X6+Z6+AB6+AD6+AF6+AH6+AJ6+AL6+AN6+AP6+AR6+AT6+AV6+AX6+AZ6+BB6+BD6+BF6+BH6+BJ6+BL6+BN6+BP6+BR6+BT6 -> 0 | BW6: =M6+O6+Q6+S6+U6+W6+Y6+AA6+AC6+AE6+AG6+AI6+AK6+AM6+AO6+AQ6+AS6+AU6+AW6+AY6+BA6+BC6+BE6+BG6+BI6+BK6+BM6+BO6+BQ6+BS6+BU6 -> 0
A7: 029.007-00 | B7: 2025/0018729-001 | C7: FB | D7: 2025/0018729 | E7: DTE1882 | F7: 01/04/2026 | G7: 30/04/2026 | H7: 25.292.508 CLAUDIA COSTA BORCA | I7: CLAUDIA COSTA BORCA | J7: NORMAL | K7: EMEF | L7: 1 | M7: 1 | Z7: 1 | AB7: 1 | AD7: 3 | AN7: 4 | AP7: 4 | AR7: 4 | BB7: 4 | BD7: 4 | BF7: 4 | BL7: 4 | BN7: 1 | BP7: 4 | BR7: 4 | BV7: =L7+N7+P7+R7+T7+V7+X7+Z7+AB7+AD7+AF7+AH7+AJ7+AL7+AN7+AP7+AR7+AT7+AV7+AX7+AZ7+BB7+BD7+BF7+BH7+BJ7+BL7+BN7+BP7+BR7+BT7 -> 43 | BW7: =M7+O7+Q7+S7+U7+W7+Y7+AA7+AC7+AE7+AG7+AI7+AK7+AM7+AO7+AQ7+AS7+AU7+AW7+AY7+BA7+BC7+BE7+BG7+BI7+BK7+BM7+BO7+BQ7+BS7+BU7 -> 1
A8: 029.007-00 | B8: 2025/0018729-001 | C8: FB | D8: 2025/0018729 | E8: DTE1882 | F8: 01/04/2026 | G8: 30/04/2026 | H8: 25.292.508 CLAUDIA COSTA BORCA | I8: CLAUDIA COSTA BORCA | J8: NORMAL | K8: EMEE | BV8: =L8+N8+P8+R8+T8+V8+X8+Z8+AB8+AD8+AF8+AH8+AJ8+AL8+AN8+AP8+AR8+AT8+AV8+AX8+AZ8+BB8+BD8+BF8+BH8+BJ8+BL8+BN8+BP8+BR8+BT8 -> 0 | BW8: =M8+O8+Q8+S8+U8+W8+Y8+AA8+AC8+AE8+AG8+AI8+AK8+AM8+AO8+AQ8+AS8+AU8+AW8+AY8+BA8+BC8+BE8+BG8+BI8+BK8+BM8+BO8+BQ8+BS8+BU8 -> 0
A9: 029.007-00 | B9: 2025/0018729-001 | C9: FB | D9: 2025/0018729 | E9: DTE1882 | F9: 01/04/2026 | G9: 30/04/2026 | H9: 25.292.508 CLAUDIA COSTA BORCA | I9: CLAUDIA COSTA BORCA | J9: NORMAL | K9: CEI | BV9: =L9+N9+P9+R9+T9+V9+X9+Z9+AB9+AD9+AF9+AH9+AJ9+AL9+AN9+AP9+AR9+AT9+AV9+AX9+AZ9+BB9+BD9+BF9+BH9+BJ9+BL9+BN9+BP9+BR9+BT9 -> 0 | BW9: =M9+O9+Q9+S9+U9+W9+Y9+AA9+AC9+AE9+AG9+AI9+AK9+AM9+AO9+AQ9+AS9+AU9+AW9+AY9+BA9+BC9+BE9+BG9+BI9+BK9+BM9+BO9+BQ9+BS9+BU9 -> 0
A10: 029.007-00 | B10: 2025/0018729-001 | C10: FB | D10: 2025/0018729 | E10: DTE1882 | F10: 01/04/2026 | G10: 30/04/2026 | H10: 25.292.508 CLAUDIA COSTA BORCA | I10: CLAUDIA COSTA BORCA | J10: NORMAL | K10: CCA | BV10: =L10+N10+P10+R10+T10+V10+X10+Z10+AB10+AD10+AF10+AH10+AJ10+AL10+AN10+AP10+AR10+AT10+AV10+AX10+AZ10+BB10+BD10+BF10+BH10+BJ10+BL10+BN10+BP10+BR10+BT10 -> 0 | BW10: =M10+O10+Q10+S10+U10+W10+Y10+AA10+AC10+AE10+AG10+AI10+AK10+AM10+AO10+AQ10+AS10+AU10+AW10+AY10+BA10+BC10+BE10+BG10+BI10+BK10+BM10+BO10+BQ10+BS10+BU10 -> 0

Sheet BASE C
A1: Base de Calculo para as Demais Planilhas | E1: APELIDO: | F1: =IFERROR(VLOOKUP(D4,APELIDOS!A:B,2,FALSE),D4) -> #N/A
A2: DRE | C2: =UPPER(MID('APONTAMENTO CREDENCIAMENTO'!C7,1,2)) -> FB | D2: =UPPER('APONTAMENTO CREDENCIAMENTO'!A1) -> FREGUESIA / BRASILÂNDIA | I2: Período Inicial | J2: Período Final | N2: PERÍODO REALIZAÇÃO | P2: FERIADOS | Q2: Obs: Digitar feriados apenas quando forem entre 2ª e 6ª feira
A3: Contrato | B3: 2026/0016071 | D3: Empresa: | E3: Mês | H3: Veículo | I3: =N3 -> 01/04/2026 | J3: =O3 -> 30/04/2026 | K3: Periodo Operacional | N3: ='APONTAMENTO CREDENCIAMENTO'!F5 -> 01/04/2026 | O3: ='APONTAMENTO CREDENCIAMENTO'!G5 -> 30/04/2026
A4: Período | B4: =I3 -> 01/04/2026 | C4: =J3 -> 30/04/2026 | D4: =D10 -> #N/A | E4: =UPPER(TEXT(B4,"MMMM")) -> ABRIL
A5: Crédito | B5: 45868
A6: Tipo | B6: não e processado por tipo segundo o thiago | R6: Legenda
A7: IR | B7: =IF(N10="C",'VALORES TABELA'!B17,IF(N10="N",'VALORES TABELA'!B18,0)) -> #N/A
A8: Apenas para Cooperativas (1,5%)
A9: Quantidade | B9: Quantidade | C9: CRMC | D9: =VLOOKUP($C9,'APONTAMENTO CREDENCIAMENTO'!$A:$J,8,0) -> EMPRESA | E9: =VLOOKUP($C9,'APONTAMENTO CREDENCIAMENTO'!$A:$J,9,0) -> NOME CONDUTOR | F9: =VLOOKUP($C9,'APONTAMENTO CREDENCIAMENTO'!$A:$P,15,0) -> SEI | G9: =VLOOKUP($C9,'APONTAMENTO CREDENCIAMENTO'!$A:$P,4,0) -> CONTRATO | H9: Placa | I9: TIPO DE VEÍCULO (NORMAL, ADAPTADO) | K9: =VLOOKUP($C9,'APONTAMENTO CREDENCIAMENTO'!$A:$J,6,0) -> PERÍODO | M9: =MID(D9,1,3) -> EMP | N9: =VLOOKUP($C9,'APONTAMENTO CREDENCIAMENTO'!$A:$P,16,0) -> Tipo Optante
A10: 1 | B10: 1 | C10: 006.336-00 | D10: =VLOOKUP($C10,'APONTAMENTO CREDENCIAMENTO'!$A:$J,8,0) -> #N/A | E10: =VLOOKUP($C10,'APONTAMENTO CREDENCIAMENTO'!$A:$J,9,0) -> #N/A | F10: =VLOOKUP($C10,'APONTAMENTO CREDENCIAMENTO'!$A:$P,15,0) -> #N/A | G10: =VLOOKUP($C10,'APONTAMENTO CREDENCIAMENTO'!$A:$P,4,0) -> #N/A | H10: =VLOOKUP($C10,'APONTAMENTO CREDENCIAMENTO'!$A:$P,5,0) -> #N/A | I10: =IF(VLOOKUP($C10,'APONTAMENTO CREDENCIAMENTO'!$A:$J,10,0)="NORMAL","NORMAL","ADAPTADO") -> #N/A | J10: =VLOOKUP($C10,'APONTAMENTO CREDENCIAMENTO'!$A:$EL,142,0) -> #N/A | K10: =VLOOKUP($C10,'APONTAMENTO CREDENCIAMENTO'!$A:$J,6,0) -> #N/A | L10: =VLOOKUP($C10,'APONTAMENTO CREDENCIAMENTO'!$A:$J,7,0) -> #N/A | M10: =MID(D10,1,3) -> #N/A | N10: =VLOOKUP($C10,'APONTAMENTO CREDENCIAMENTO'!$A:$P,16,0) -> #N/A

Sheet DEMO C
B9: DADOS DO CONTRATO LICITADO
A10: CONTRATO Nº | D10: Tipo de Operação | F10: Km/dia | G10: Total Alunos | H10: Mês base | I10: D.R.E
A11: ='BASE C'!B3 -> 2026/0016071 | F11: ='EMPRESA C'!G16 -> 0 | G11: ='EMPRESA C'!H16+'EMPRESA C'!I16+'EMPRESA C'!J16+'EMPRESA C'!K16+'EMPRESA C'!L16+'EMPRESA C'!M16 -> 0 | H11: ='BASE C'!E4 -> ABRIL | I11: ='BASE C'!D2 -> FREGUESIA / BRASILÂNDIA
A12: Nome do Contratado | F12: CNPJ | H12: Período
A13: ='BASE C'!D4 -> #N/A | F13: =VLOOKUP(A11,ProcRel1!E2:G5000,3,FALSE) -> 65.425.834/0001-94 | H13: ='BASE C'!B4 -> 01/04/2026 | I13: ='BASE C'!C4 -> 30/04/2026
F14: Processo SEI! | H14: Previsão de Crédito
F15: =VLOOKUP(A11,'APONTAMENTO CREDENCIAMENTO'!D1:EL3845,12,FALSE) -> #N/A | H15: ='VALORES TABELA'!B37 -> 46171
B17: DEMONSTRATIVO DE PAGAMENTO
A19: Descrição | H19: Valor ( em Reais )
A20: ( A ) | B20: ='EMPRESA C'!N13 -> Contratos Especiais (Valor fixo) | H20: ='EMPRESA C'!N16 -> 0
A21: ( B ) | B21: ='EMPRESA C'!O13 -> Valor total alunos presenciais (30 dias) | H21: ='EMPRESA C'!O16 -> 0
A22: ( C ) | B22: ='EMPRESA C'!P13 -> Ativ.Complementar Continuada | H22: ='EMPRESA C'!P16 -> 0
A23: ( D ) | B23: ='APONTAMENTO CREDENCIAMENTO'!EZ4 -> Valor alunos presenciais (menos de 30 dias) | H23: ='EMPRESA C'!Q16 -> 0
A24: ( E ) | B24: ='EMPRESA C'!R13 -> Saida de alunos ao longo do mês | H24: ='EMPRESA C'!R16 -> 0
A25: ( F ) | B25: CCA | H25: ='EMPRESA C'!S16 -> 0
A26: ( G ) | B26: ='APONTAMENTO CREDENCIAMENTO'!FC4 -> Valor km adicional | H26: ='EMPRESA C'!T16 -> 0
A27: ( H ) | B27: ='APONTAMENTO CREDENCIAMENTO'!EM4 -> Ajuste positivo | H27: ='EMPRESA C'!U16 -> 0
A28: ( I ) | B28: ='EMPRESA C'!V13 -> Ajuste negativo | H28: ='EMPRESA C'!V16 -> 0
A29: ( J ) | B29: ='EMPRESA C'!W13 -> Desconto faltas | H29: ='EMPRESA C'!W16 -> 0
A30: ( L ) | B30: ='APONTAMENTO CREDENCIAMENTO'!FD4 -> Outros apontamentos | H30: ='EMPRESA C'!X16 -> 0
A31: ( M ) | B31: Desconto por multa Contratual - Enquadramento | H31: ='EMPRESA C'!Y16 -> 0
A32: ( N ) | B32: Remuneração Bruta ( A+B+C+D+E+F+I+J) - (G+H ) | H32: ='EMPRESA C'!Z16 -> 0
A33: ( O ) | B33: Imposto de Renda Retido na Fonte | H33: ='EMPRESA C'!AB16 -> #N/A
A34: ( P ) | B34: Remuneração Líquida ( J-K-L ) | H34: =H32-H33 -> #N/A
A35: OBS FIN: | B35: =VLOOKUP(A11,'APONTAMENTO CREDENCIAMENTO'!D1:EL3845,138,FALSE) -> #N/A
A37: OBS DRE: | B37: =VLOOKUP(A11,'APONTAMENTO CREDENCIAMENTO'!D1:EL3845,139,FALSE) -> #N/A
B39: Declaro pelo presente, estar de acordo com as informações e valores aqui demonstrados, cujo crédito será efetuado na conta corrente por mim indicada, operando-se a quitação plena, geral e irrestrita, no ato da efetivação do crédito referenciado.
B43: São Paulo,______/______/______ Assinatura do Contratado__________________________________
A45: Documentos necessários para liquidação
A46: Enviar os documentos na ordem informada abaixo em um único arquivo PDF.
A47: 1 - Demonstrativo assinado.
A48: 2 - Nota fiscal referente ao valor bruto.
A49: 3 - Guia do INSS e comprovante de pagamento referente a competência: | G49: =$H$13+1-1 -> 46113
A50: 4 - Guia do ISS (ou DAS em caso de optante pelo SIMPLES) e comprovante de pagamento ref. a competência: | I50: =G49 -> 46113
A51: 5 - Guia do FGTS e comprovante de pagamento referente a competência: | G51: =G49 -> 46113
A52: 6 - Relatório do FGTS digital.
A53: Informações importantes
B54: Link Cadin: | E54: http://www3.prefeitura.sp.gov.br/cadin/Pesq_Deb.aspx
B55: Link para consulta de pagamento: | E55: http://sfemp.prefeitura.sp.gov.br/cons_pagto.aspx
A56: Para declaração de IRRF, favor utilizarem este CNPJ - Secretaria Municipal da Fazenda (Fonte Pagadora) 46.392.130/0003-80
B57: Link Informe de rendimentos IR: | E57: https://sofconsulta.prefeitura.sp.gov.br/ir
A58: Para emissão das notas fiscais, favor utilizarem este CNPJ - Secretaria Municipal de Mobilidade e Transp. 46.392.155/0001-11
B59: Obs. O número do seu processo SEI! encontra-se na parte superior do demonstrativo

Sheet ATESTE-LIQ-FIS
A1: Contrato | C1: CPF | D1: Valor Bruto | E1: RetenCAo de INSS | F1: RetenCAo Sest/ Senat | G1: Base de CAlculo IR 2026 | H1: IR Retido | I1: NOVA BASE | J1: IR NORMAL | K1: IR ACUMULA
B2: SEI
I3: =IF(C3=C2,(D3+D2)*'VALORES TABELA'!$B$50-E2,D3*'VALORES TABELA'!$B$50) -> 0 | J3: =IF(($G3-E3)<='VALORES TABELA'!$A$56,0,IF(($G3-$E3)<='VALORES TABELA'!$A$57,($G3-$E3)*'VALORES TABELA'!$B$57-'VALORES TABELA'!$C$57,IF(($G3-$E3)<='VALORES TABELA'!$A$58,($G3-$E3)*'VALORES TABELA'!$B$58-'VALORES TABELA'!$C$58,IF(($G3-$E3)<='VALORES TABELA'!$A$59,($G3-$E3)*'VALORES TABELA'!$B$59-'VALORES TABELA'!$C$59,($G3-$E3)*'VALORES TABELA'!$B$60-'VALORES TABELA'!$C$60)))) -> 0 | K3: =IF(($I3-$E3)<='VALORES TABELA'!$A$56,0,IF(($I3-$E3)<='VALORES TABELA'!$A$57,($I3-$E3)*'VALORES TABELA'!$B$57-'VALORES TABELA'!$C$57,IF(($I3-$E3)<='VALORES TABELA'!$A$58,($I3-$E3)*'VALORES TABELA'!$B$58-'VALORES TABELA'!$C$58,IF(($I3-$E3)<='VALORES TABELA'!$A$59,($I3-$E3)*'VALORES TABELA'!$B$59-'VALORES TABELA'!$C$59,($I3-$E3)*'VALORES TABELA'!$B$60-'VALORES TABELA'!$C$60))))-J2 -> 0
A4: 2024/0058910 | B4: 6020.2024/0058910-3 | C4: 32.437.112/0001-09 | D4: =SUMIF('APONTAMENTO CREDENCIAMENTO'!$D$5:$D$3847,$A4,'APONTAMENTO CREDENCIAMENTO'!$FF$5:$FF$3847) -> 0 | E4: =IF(D4=0,0,IF(D4*0.2*0.11>607.2,607.2,IF(D4<42377.92,D4*0.2*0.11,IF(D4*0.2*0.11>932.31,932.31)))) -> 0 | F4: =$D4*'VALORES TABELA'!$B$45*'VALORES TABELA'!$B$46 -> 0 | G4: =D4*60% -> 0 | H4: =_xlfn.LET(_xlpm.base,G4,_xlpm.bruto,E4+G4,_xlpm.ir_normal,IF(_xlpm.base<='VALORES TABELA'!$J$1,'VALORES TABELA'!$K$1,IF(_xlpm.base<='VALORES TABELA'!$J$2,_xlpm.base*'VALORES TABELA'!$K$2-'VALORES TABELA'!$L$2,IF(_xlpm.base<='VALORES TABELA'!$J$3,_xlpm.base*'VALORES TABELA'!$K$3-'VALORES TABELA'!$L$3,IF(_xlpm.base<='VALORES TABELA'!$J$4,_xlpm.base*'VALORES TABELA'!$K$4-'VALORES TABELA'!$L$4,_xlpm.base*'VALORES TABELA'!$K$5-'VALORES TABELA'!$L$5)))),_xlpm.redutor,IF(_xlpm.bruto<='VALORES TABELA'!$J$6,_xlpm.ir_normal,IF(_xlpm.bruto<='VALORES TABELA'!$K$6,MIN(_xlpm.ir_normal,'VALORES TABELA'!$L$6-'VALORES TABELA'!$M$6*_xlpm.bruto),0)),TRUNC(MAX(0,_xlpm.ir_normal-_xlpm.redutor),2)) -> 0 | I4: =IF($C4=$C3,($D4+$D3)*'VALORES TABELA'!$B$50-$E3,$D4*'VALORES TABELA'!$B$50) -> 0 | J4: =IF(($G4-E4)<='VALORES TABELA'!$A$56,0,IF(($G4-$E4)<='VALORES TABELA'!$A$57,($G4-$E4)*'VALORES TABELA'!$B$57-'VALORES TABELA'!$C$57,IF(($G4-$E4)<='VALORES TABELA'!$A$58,($G4-$E4)*'VALORES TABELA'!$B$58-'VALORES TABELA'!$C$58,IF(($G4-$E4)<='VALORES TABELA'!$A$59,($G4-$E4)*'VALORES TABELA'!$B$59-'VALORES TABELA'!$C$59,($G4-$E4)*'VALORES TABELA'!$B$60-'VALORES TABELA'!$C$60)))) -> 0 | K4: =IF(($I4-$E4)<='VALORES TABELA'!$A$56,0,IF(($I4-$E4)<='VALORES TABELA'!$A$57,($I4-$E4)*'VALORES TABELA'!$B$57-'VALORES TABELA'!$C$57,IF(($I4-$E4)<='VALORES TABELA'!$A$58,($I4-$E4)*'VALORES TABELA'!$B$58-'VALORES TABELA'!$C$58,IF(($I4-$E4)<='VALORES TABELA'!$A$59,($I4-$E4)*'VALORES TABELA'!$B$59-'VALORES TABELA'!$C$59,($I4-$E4)*'VALORES TABELA'!$B$60-'VALORES TABELA'!$C$60))))-J3 -> 0
A5: 2023/0009598 | B5: 6020.2023/0009598-2 | C5: 32.437.112/0001-09 | D5: =SUMIF('APONTAMENTO CREDENCIAMENTO'!$D$5:$D$3847,$A5,'APONTAMENTO CREDENCIAMENTO'!$FF$5:$FF$3847) -> 0 | E5: =IF(D5=0,0,IF(D5*0.2*0.11>607.2,607.2,IF(D5<42377.92,D5*0.2*0.11,IF(D5*0.2*0.11>932.31,932.31)))) -> 0 | F5: =$D5*'VALORES TABELA'!$B$45*'VALORES TABELA'!$B$46 -> 0 | G5: =D5*60% -> 0 | H5: =_xlfn.LET(_xlpm.base,G5,_xlpm.bruto,E5+G5,_xlpm.ir_normal,IF(_xlpm.base<='VALORES TABELA'!$J$1,'VALORES TABELA'!$K$1,IF(_xlpm.base<='VALORES TABELA'!$J$2,_xlpm.base*'VALORES TABELA'!$K$2-'VALORES TABELA'!$L$2,IF(_xlpm.base<='VALORES TABELA'!$J$3,_xlpm.base*'VALORES TABELA'!$K$3-'VALORES TABELA'!$L$3,IF(_xlpm.base<='VALORES TABELA'!$J$4,_xlpm.base*'VALORES TABELA'!$K$4-'VALORES TABELA'!$L$4,_xlpm.base*'VALORES TABELA'!$K$5-'VALORES TABELA'!$L$5)))),_xlpm.redutor,IF(_xlpm.bruto<='VALORES TABELA'!$J$6,_xlpm.ir_normal,IF(_xlpm.bruto<='VALORES TABELA'!$K$6,MIN(_xlpm.ir_normal,'VALORES TABELA'!$L$6-'VALORES TABELA'!$M$6*_xlpm.bruto),0)),TRUNC(MAX(0,_xlpm.ir_normal-_xlpm.redutor),2)) -> 0 | I5: =IF($C5=$C4,($D5+$D4)*'VALORES TABELA'!$B$50-$E4,$D5*'VALORES TABELA'!$B$50) -> 0 | J5: =IF(($G5-E5)<='VALORES TABELA'!$A$56,0,IF(($G5-$E5)<='VALORES TABELA'!$A$57,($G5-$E5)*'VALORES TABELA'!$B$57-'VALORES TABELA'!$C$57,IF(($G5-$E5)<='VALORES TABELA'!$A$58,($G5-$E5)*'VALORES TABELA'!$B$58-'VALORES TABELA'!$C$58,IF(($G5-$E5)<='VALORES TABELA'!$A$59,($G5-$E5)*'VALORES TABELA'!$B$59-'VALORES TABELA'!$C$59,($G5-$E5)*'VALORES TABELA'!$B$60-'VALORES TABELA'!$C$60)))) -> 0 | K5: =IF(($I5-$E5)<='VALORES TABELA'!$A$56,0,IF(($I5-$E5)<='VALORES TABELA'!$A$57,($I5-$E5)*'VALORES TABELA'!$B$57-'VALORES TABELA'!$C$57,IF(($I5-$E5)<='VALORES TABELA'!$A$58,($I5-$E5)*'VALORES TABELA'!$B$58-'VALORES TABELA'!$C$58,IF(($I5-$E5)<='VALORES TABELA'!$A$59,($I5-$E5)*'VALORES TABELA'!$B$59-'VALORES TABELA'!$C$59,($I5-$E5)*'VALORES TABELA'!$B$60-'VALORES TABELA'!$C$60))))-J4 -> 0
A6: 2023/0019748 | B6: 6020.2023/0019748-3 | C6: 25.147.022/0001-00 | D6: =SUMIF('APONTAMENTO CREDENCIAMENTO'!$D$5:$D$3847,$A6,'APONTAMENTO CREDENCIAMENTO'!$FF$5:$FF$3847) -> 0 | E6: =IF(D6=0,0,IF(D6*0.2*0.11>607.2,607.2,IF(D6<42377.92,D6*0.2*0.11,IF(D6*0.2*0.11>932.31,932.31)))) -> 0 | F6: =$D6*'VALORES TABELA'!$B$45*'VALORES TABELA'!$B$46 -> 0 | G6: =D6*60% -> 0 | H6: =_xlfn.LET(_xlpm.base,G6,_xlpm.bruto,E6+G6,_xlpm.ir_normal,IF(_xlpm.base<='VALORES TABELA'!$J$1,'VALORES TABELA'!$K$1,IF(_xlpm.base<='VALORES TABELA'!$J$2,_xlpm.base*'VALORES TABELA'!$K$2-'VALORES TABELA'!$L$2,IF(_xlpm.base<='VALORES TABELA'!$J$3,_xlpm.base*'VALORES TABELA'!$K$3-'VALORES TABELA'!$L$3,IF(_xlpm.base<='VALORES TABELA'!$J$4,_xlpm.base*'VALORES TABELA'!$K$4-'VALORES TABELA'!$L$4,_xlpm.base*'VALORES TABELA'!$K$5-'VALORES TABELA'!$L$5)))),_xlpm.redutor,IF(_xlpm.bruto<='VALORES TABELA'!$J$6,_xlpm.ir_normal,IF(_xlpm.bruto<='VALORES TABELA'!$K$6,MIN(_xlpm.ir_normal,'VALORES TABELA'!$L$6-'VALORES TABELA'!$M$6*_xlpm.bruto),0)),TRUNC(MAX(0,_xlpm.ir_normal-_xlpm.redutor),2)) -> 0 | I6: =IF($C6=$C5,($D6+$D5)*'VALORES TABELA'!$B$50-$E5,$D6*'VALORES TABELA'!$B$50) -> 0 | J6: =IF(($G6-E6)<='VALORES TABELA'!$A$56,0,IF(($G6-$E6)<='VALORES TABELA'!$A$57,($G6-$E6)*'VALORES TABELA'!$B$57-'VALORES TABELA'!$C$57,IF(($G6-$E6)<='VALORES TABELA'!$A$58,($G6-$E6)*'VALORES TABELA'!$B$58-'VALORES TABELA'!$C$58,IF(($G6-$E6)<='VALORES TABELA'!$A$59,($G6-$E6)*'VALORES TABELA'!$B$59-'VALORES TABELA'!$C$59,($G6-$E6)*'VALORES TABELA'!$B$60-'VALORES TABELA'!$C$60)))) -> 0 | K6: =IF(($I6-$E6)<='VALORES TABELA'!$A$56,0,IF(($I6-$E6)<='VALORES TABELA'!$A$57,($I6-$E6)*'VALORES TABELA'!$B$57-'VALORES TABELA'!$C$57,IF(($I6-$E6)<='VALORES TABELA'!$A$58,($I6-$E6)*'VALORES TABELA'!$B$58-'VALORES TABELA'!$C$58,IF(($I6-$E6)<='VALORES TABELA'!$A$59,($I6-$E6)*'VALORES TABELA'!$B$59-'VALORES TABELA'!$C$59,($I6-$E6)*'VALORES TABELA'!$B$60-'VALORES TABELA'!$C$60))))-J5 -> 0
A7: 2023/0034391 | B7: 6020.2023/0034391-9 | C7: 43.874.830/0001-50 | D7: =SUMIF('APONTAMENTO CREDENCIAMENTO'!$D$5:$D$3847,$A7,'APONTAMENTO CREDENCIAMENTO'!$FF$5:$FF$3847) -> 0 | E7: =IF(D7=0,0,IF(D7*0.2*0.11>607.2,607.2,IF(D7<42377.92,D7*0.2*0.11,IF(D7*0.2*0.11>932.31,932.31)))) -> 0 | F7: =$D7*'VALORES TABELA'!$B$45*'VALORES TABELA'!$B$46 -> 0 | G7: =D7*60% -> 0 | H7: =_xlfn.LET(_xlpm.base,G7,_xlpm.bruto,E7+G7,_xlpm.ir_normal,IF(_xlpm.base<='VALORES TABELA'!$J$1,'VALORES TABELA'!$K$1,IF(_xlpm.base<='VALORES TABELA'!$J$2,_xlpm.base*'VALORES TABELA'!$K$2-'VALORES TABELA'!$L$2,IF(_xlpm.base<='VALORES TABELA'!$J$3,_xlpm.base*'VALORES TABELA'!$K$3-'VALORES TABELA'!$L$3,IF(_xlpm.base<='VALORES TABELA'!$J$4,_xlpm.base*'VALORES TABELA'!$K$4-'VALORES TABELA'!$L$4,_xlpm.base*'VALORES TABELA'!$K$5-'VALORES TABELA'!$L$5)))),_xlpm.redutor,IF(_xlpm.bruto<='VALORES TABELA'!$J$6,_xlpm.ir_normal,IF(_xlpm.bruto<='VALORES TABELA'!$K$6,MIN(_xlpm.ir_normal,'VALORES TABELA'!$L$6-'VALORES TABELA'!$M$6*_xlpm.bruto),0)),TRUNC(MAX(0,_xlpm.ir_normal-_xlpm.redutor),2)) -> 0 | I7: =IF($C7=$C6,($D7+$D6)*'VALORES TABELA'!$B$50-$E6,$D7*'VALORES TABELA'!$B$50) -> 0 | J7: =IF(($G7-E7)<='VALORES TABELA'!$A$56,0,IF(($G7-$E7)<='VALORES TABELA'!$A$57,($G7-$E7)*'VALORES TABELA'!$B$57-'VALORES TABELA'!$C$57,IF(($G7-$E7)<='VALORES TABELA'!$A$58,($G7-$E7)*'VALORES TABELA'!$B$58-'VALORES TABELA'!$C$58,IF(($G7-$E7)<='VALORES TABELA'!$A$59,($G7-$E7)*'VALORES TABELA'!$B$59-'VALORES TABELA'!$C$59,($G7-$E7)*'VALORES TABELA'!$B$60-'VALORES TABELA'!$C$60)))) -> 0 | K7: =IF(($I7-$E7)<='VALORES TABELA'!$A$56,0,IF(($I7-$E7)<='VALORES TABELA'!$A$57,($I7-$E7)*'VALORES TABELA'!$B$57-'VALORES TABELA'!$C$57,IF(($I7-$E7)<='VALORES TABELA'!$A$58,($I7-$E7)*'VALORES TABELA'!$B$58-'VALORES TABELA'!$C$58,IF(($I7-$E7)<='VALORES TABELA'!$A$59,($I7-$E7)*'VALORES TABELA'!$B$59-'VALORES TABELA'!$C$59,($I7-$E7)*'VALORES TABELA'!$B$60-'VALORES TABELA'!$C$60))))-J6 -> 0
A8: 2022/0054095 | B8: 6020.2022/0054095-0 | C8: 43.874.830/0001-50 | D8: =SUMIF('APONTAMENTO CREDENCIAMENTO'!$D$5:$D$3847,$A8,'APONTAMENTO CREDENCIAMENTO'!$FF$5:$FF$3847) -> 0 | E8: =IF(D8=0,0,IF(D8*0.2*0.11>607.2,607.2,IF(D8<42377.92,D8*0.2*0.11,IF(D8*0.2*0.11>932.31,932.31)))) -> 0 | F8: =$D8*'VALORES TABELA'!$B$45*'VALORES TABELA'!$B$46 -> 0 | G8: =D8*60% -> 0 | H8: =_xlfn.LET(_xlpm.base,G8,_xlpm.bruto,E8+G8,_xlpm.ir_normal,IF(_xlpm.base<='VALORES TABELA'!$J$1,'VALORES TABELA'!$K$1,IF(_xlpm.base<='VALORES TABELA'!$J$2,_xlpm.base*'VALORES TABELA'!$K$2-'VALORES TABELA'!$L$2,IF(_xlpm.base<='VALORES TABELA'!$J$3,_xlpm.base*'VALORES TABELA'!$K$3-'VALORES TABELA'!$L$3,IF(_xlpm.base<='VALORES TABELA'!$J$4,_xlpm.base*'VALORES TABELA'!$K$4-'VALORES TABELA'!$L$4,_xlpm.base*'VALORES TABELA'!$K$5-'VALORES TABELA'!$L$5)))),_xlpm.redutor,IF(_xlpm.bruto<='VALORES TABELA'!$J$6,_xlpm.ir_normal,IF(_xlpm.bruto<='VALORES TABELA'!$K$6,MIN(_xlpm.ir_normal,'VALORES TABELA'!$L$6-'VALORES TABELA'!$M$6*_xlpm.bruto),0)),TRUNC(MAX(0,_xlpm.ir_normal-_xlpm.redutor),2)) -> 0 | I8: =IF($C8=$C7,($D8+$D7)*'VALORES TABELA'!$B$50-$E7,$D8*'VALORES TABELA'!$B$50) -> 0 | J8: =IF(($G8-E8)<='VALORES TABELA'!$A$56,0,IF(($G8-$E8)<='VALORES TABELA'!$A$57,($G8-$E8)*'VALORES TABELA'!$B$57-'VALORES TABELA'!$C$57,IF(($G8-$E8)<='VALORES TABELA'!$A$58,($G8-$E8)*'VALORES TABELA'!$B$58-'VALORES TABELA'!$C$58,IF(($G8-$E8)<='VALORES TABELA'!$A$59,($G8-$E8)*'VALORES TABELA'!$B$59-'VALORES TABELA'!$C$59,($G8-$E8)*'VALORES TABELA'!$B$60-'VALORES TABELA'!$C$60)))) -> 0 | K8: =IF(($I8-$E8)<='VALORES TABELA'!$A$56,0,IF(($I8-$E8)<='VALORES TABELA'!$A$57,($I8-$E8)*'VALORES TABELA'!$B$57-'VALORES TABELA'!$C$57,IF(($I8-$E8)<='VALORES TABELA'!$A$58,($I8-$E8)*'VALORES TABELA'!$B$58-'VALORES TABELA'!$C$58,IF(($I8-$E8)<='VALORES TABELA'!$A$59,($I8-$E8)*'VALORES TABELA'!$B$59-'VALORES TABELA'!$C$59,($I8-$E8)*'VALORES TABELA'!$B$60-'VALORES TABELA'!$C$60))))-J7 -> 0
A9: 2023/0082114 | B9: 6020.2023/0082114-4 | C9: 43.874.830/0001-50 | D9: =SUMIF('APONTAMENTO CREDENCIAMENTO'!$D$5:$D$3847,$A9,'APONTAMENTO CREDENCIAMENTO'!$FF$5:$FF$3847) -> 0 | E9: =IF(D9=0,0,IF(D9*0.2*0.11>607.2,607.2,IF(D9<42377.92,D9*0.2*0.11,IF(D9*0.2*0.11>932.31,932.31)))) -> 0 | F9: =$D9*'VALORES TABELA'!$B$45*'VALORES TABELA'!$B$46 -> 0 | G9: =D9*60% -> 0 | H9: =_xlfn.LET(_xlpm.base,G9,_xlpm.bruto,E9+G9,_xlpm.ir_normal,IF(_xlpm.base<='VALORES TABELA'!$J$1,'VALORES TABELA'!$K$1,IF(_xlpm.base<='VALORES TABELA'!$J$2,_xlpm.base*'VALORES TABELA'!$K$2-'VALORES TABELA'!$L$2,IF(_xlpm.base<='VALORES TABELA'!$J$3,_xlpm.base*'VALORES TABELA'!$K$3-'VALORES TABELA'!$L$3,IF(_xlpm.base<='VALORES TABELA'!$J$4,_xlpm.base*'VALORES TABELA'!$K$4-'VALORES TABELA'!$L$4,_xlpm.base*'VALORES TABELA'!$K$5-'VALORES TABELA'!$L$5)))),_xlpm.redutor,IF(_xlpm.bruto<='VALORES TABELA'!$J$6,_xlpm.ir_normal,IF(_xlpm.bruto<='VALORES TABELA'!$K$6,MIN(_xlpm.ir_normal,'VALORES TABELA'!$L$6-'VALORES TABELA'!$M$6*_xlpm.bruto),0)),TRUNC(MAX(0,_xlpm.ir_normal-_xlpm.redutor),2)) -> 0 | I9: =IF($C9=$C8,($D9+$D8)*'VALORES TABELA'!$B$50-$E8,$D9*'VALORES TABELA'!$B$50) -> 0 | J9: =IF(($G9-E9)<='VALORES TABELA'!$A$56,0,IF(($G9-$E9)<='VALORES TABELA'!$A$57,($G9-$E9)*'VALORES TABELA'!$B$57-'VALORES TABELA'!$C$57,IF(($G9-$E9)<='VALORES TABELA'!$A$58,($G9-$E9)*'VALORES TABELA'!$B$58-'VALORES TABELA'!$C$58,IF(($G9-$E9)<='VALORES TABELA'!$A$59,($G9-$E9)*'VALORES TABELA'!$B$59-'VALORES TABELA'!$C$59,($G9-$E9)*'VALORES TABELA'!$B$60-'VALORES TABELA'!$C$60)))) -> 0 | K9: =IF(($I9-$E9)<='VALORES TABELA'!$A$56,0,IF(($I9-$E9)<='VALORES TABELA'!$A$57,($I9-$E9)*'VALORES TABELA'!$B$57-'VALORES TABELA'!$C$57,IF(($I9-$E9)<='VALORES TABELA'!$A$58,($I9-$E9)*'VALORES TABELA'!$B$58-'VALORES TABELA'!$C$58,IF(($I9-$E9)<='VALORES TABELA'!$A$59,($I9-$E9)*'VALORES TABELA'!$B$59-'VALORES TABELA'!$C$59,($I9-$E9)*'VALORES TABELA'!$B$60-'VALORES TABELA'!$C$60))))-J8 -> 0
A10: 2022/0034911 | B10: 6020.2022/0034911-7 | C10: 30.950.404/0001-07 | D10: =SUMIF('APONTAMENTO CREDENCIAMENTO'!$D$5:$D$3847,$A10,'APONTAMENTO CREDENCIAMENTO'!$FF$5:$FF$3847) -> 0 | E10: =IF(D10=0,0,IF(D10*0.2*0.11>607.2,607.2,IF(D10<42377.92,D10*0.2*0.11,IF(D10*0.2*0.11>932.31,932.31)))) -> 0 | F10: =$D10*'VALORES TABELA'!$B$45*'VALORES TABELA'!$B$46 -> 0 | G10: =D10*60% -> 0 | H10: =_xlfn.LET(_xlpm.base,G10,_xlpm.bruto,E10+G10,_xlpm.ir_normal,IF(_xlpm.base<='VALORES TABELA'!$J$1,'VALORES TABELA'!$K$1,IF(_xlpm.base<='VALORES TABELA'!$J$2,_xlpm.base*'VALORES TABELA'!$K$2-'VALORES TABELA'!$L$2,IF(_xlpm.base<='VALORES TABELA'!$J$3,_xlpm.base*'VALORES TABELA'!$K$3-'VALORES TABELA'!$L$3,IF(_xlpm.base<='VALORES TABELA'!$J$4,_xlpm.base*'VALORES TABELA'!$K$4-'VALORES TABELA'!$L$4,_xlpm.base*'VALORES TABELA'!$K$5-'VALORES TABELA'!$L$5)))),_xlpm.redutor,IF(_xlpm.bruto<='VALORES TABELA'!$J$6,_xlpm.ir_normal,IF(_xlpm.bruto<='VALORES TABELA'!$K$6,MIN(_xlpm.ir_normal,'VALORES TABELA'!$L$6-'VALORES TABELA'!$M$6*_xlpm.bruto),0)),TRUNC(MAX(0,_xlpm.ir_normal-_xlpm.redutor),2)) -> 0 | I10: =IF($C10=$C9,($D10+$D9)*'VALORES TABELA'!$B$50-$E9,$D10*'VALORES TABELA'!$B$50) -> 0 | J10: =IF(($G10-E10)<='VALORES TABELA'!$A$56,0,IF(($G10-$E10)<='VALORES TABELA'!$A$57,($G10-$E10)*'VALORES TABELA'!$B$57-'VALORES TABELA'!$C$57,IF(($G10-$E10)<='VALORES TABELA'!$A$58,($G10-$E10)*'VALORES TABELA'!$B$58-'VALORES TABELA'!$C$58,IF(($G10-$E10)<='VALORES TABELA'!$A$59,($G10-$E10)*'VALORES TABELA'!$B$59-'VALORES TABELA'!$C$59,($G10-$E10)*'VALORES TABELA'!$B$60-'VALORES TABELA'!$C$60)))) -> 0 | K10: =IF(($I10-$E10)<='VALORES TABELA'!$A$56,0,IF(($I10-$E10)<='VALORES TABELA'!$A$57,($I10-$E10)*'VALORES TABELA'!$B$57-'VALORES TABELA'!$C$57,IF(($I10-$E10)<='VALORES TABELA'!$A$58,($I10-$E10)*'VALORES TABELA'!$B$58-'VALORES TABELA'!$C$58,IF(($I10-$E10)<='VALORES TABELA'!$A$59,($I10-$E10)*'VALORES TABELA'!$B$59-'VALORES TABELA'!$C$59,($I10-$E10)*'VALORES TABELA'!$B$60-'VALORES TABELA'!$C$60))))-J9 -> 0
A11: 2022/0034297 | B11: 6020.2022/0034297-0 | C11: 14.287.748/0001-21 | D11: =SUMIF('APONTAMENTO CREDENCIAMENTO'!$D$5:$D$3847,$A11,'APONTAMENTO CREDENCIAMENTO'!$FF$5:$FF$3847) -> 0 | E11: =IF(D11=0,0,IF(D11*0.2*0.11>607.2,607.2,IF(D11<42377.92,D11*0.2*0.11,IF(D11*0.2*0.11>932.31,932.31)))) -> 0 | F11: =$D11*'VALORES TABELA'!$B$45*'VALORES TABELA'!$B$46 -> 0 | G11: =D11*60% -> 0 | H11: =_xlfn.LET(_xlpm.base,G11,_xlpm.bruto,E11+G11,_xlpm.ir_normal,IF(_xlpm.base<='VALORES TABELA'!$J$1,'VALORES TABELA'!$K$1,IF(_xlpm.base<='VALORES TABELA'!$J$2,_xlpm.base*'VALORES TABELA'!$K$2-'VALORES TABELA'!$L$2,IF(_xlpm.base<='VALORES TABELA'!$J$3,_xlpm.base*'VALORES TABELA'!$K$3-'VALORES TABELA'!$L$3,IF(_xlpm.base<='VALORES TABELA'!$J$4,_xlpm.base*'VALORES TABELA'!$K$4-'VALORES TABELA'!$L$4,_xlpm.base*'VALORES TABELA'!$K$5-'VALORES TABELA'!$L$5)))),_xlpm.redutor,IF(_xlpm.bruto<='VALORES TABELA'!$J$6,_xlpm.ir_normal,IF(_xlpm.bruto<='VALORES TABELA'!$K$6,MIN(_xlpm.ir_normal,'VALORES TABELA'!$L$6-'VALORES TABELA'!$M$6*_xlpm.bruto),0)),TRUNC(MAX(0,_xlpm.ir_normal-_xlpm.redutor),2)) -> 0 | I11: =IF($C11=$C10,($D11+$D10)*'VALORES TABELA'!$B$50-$E10,$D11*'VALORES TABELA'!$B$50) -> 0 | J11: =IF(($G11-E11)<='VALORES TABELA'!$A$56,0,IF(($G11-$E11)<='VALORES TABELA'!$A$57,($G11-$E11)*'VALORES TABELA'!$B$57-'VALORES TABELA'!$C$57,IF(($G11-$E11)<='VALORES TABELA'!$A$58,($G11-$E11)*'VALORES TABELA'!$B$58-'VALORES TABELA'!$C$58,IF(($G11-$E11)<='VALORES TABELA'!$A$59,($G11-$E11)*'VALORES TABELA'!$B$59-'VALORES TABELA'!$C$59,($G11-$E11)*'VALORES TABELA'!$B$60-'VALORES TABELA'!$C$60)))) -> 0 | K11: =IF(($I11-$E11)<='VALORES TABELA'!$A$56,0,IF(($I11-$E11)<='VALORES TABELA'!$A$57,($I11-$E11)*'VALORES TABELA'!$B$57-'VALORES TABELA'!$C$57,IF(($I11-$E11)<='VALORES TABELA'!$A$58,($I11-$E11)*'VALORES TABELA'!$B$58-'VALORES TABELA'!$C$58,IF(($I11-$E11)<='VALORES TABELA'!$A$59,($I11-$E11)*'VALORES TABELA'!$B$59-'VALORES TABELA'!$C$59,($I11-$E11)*'VALORES TABELA'!$B$60-'VALORES TABELA'!$C$60))))-J10 -> 0
A12: 2024/0016666 | B12: 6020.2024/0016666-0 | C12: 97.524.274/0001-11 | D12: =SUMIF('APONTAMENTO CREDENCIAMENTO'!$D$5:$D$3847,$A12,'APONTAMENTO CREDENCIAMENTO'!$FF$5:$FF$3847) -> 0 | E12: =IF(D12=0,0,IF(D12*0.2*0.11>607.2,607.2,IF(D12<42377.92,D12*0.2*0.11,IF(D12*0.2*0.11>932.31,932.31)))) -> 0 | F12: =$D12*'VALORES TABELA'!$B$45*'VALORES TABELA'!$B$46 -> 0 | G12: =D12*60% -> 0 | H12: =_xlfn.LET(_xlpm.base,G12,_xlpm.bruto,E12+G12,_xlpm.ir_normal,IF(_xlpm.base<='VALORES TABELA'!$J$1,'VALORES TABELA'!$K$1,IF(_xlpm.base<='VALORES TABELA'!$J$2,_xlpm.base*'VALORES TABELA'!$K$2-'VALORES TABELA'!$L$2,IF(_xlpm.base<='VALORES TABELA'!$J$3,_xlpm.base*'VALORES TABELA'!$K$3-'VALORES TABELA'!$L$3,IF(_xlpm.base<='VALORES TABELA'!$J$4,_xlpm.base*'VALORES TABELA'!$K$4-'VALORES TABELA'!$L$4,_xlpm.base*'VALORES TABELA'!$K$5-'VALORES TABELA'!$L$5)))),_xlpm.redutor,IF(_xlpm.bruto<='VALORES TABELA'!$J$6,_xlpm.ir_normal,IF(_xlpm.bruto<='VALORES TABELA'!$K$6,MIN(_xlpm.ir_normal,'VALORES TABELA'!$L$6-'VALORES TABELA'!$M$6*_xlpm.bruto),0)),TRUNC(MAX(0,_xlpm.ir_normal-_xlpm.redutor),2)) -> 0 | I12: =IF($C12=$C11,($D12+$D11)*'VALORES TABELA'!$B$50-$E11,$D12*'VALORES TABELA'!$B$50) -> 0 | J12: =IF(($G12-E12)<='VALORES TABELA'!$A$56,0,IF(($G12-$E12)<='VALORES TABELA'!$A$57,($G12-$E12)*'VALORES TABELA'!$B$57-'VALORES TABELA'!$C$57,IF(($G12-$E12)<='VALORES TABELA'!$A$58,($G12-$E12)*'VALORES TABELA'!$B$58-'VALORES TABELA'!$C$58,IF(($G12-$E12)<='VALORES TABELA'!$A$59,($G12-$E12)*'VALORES TABELA'!$B$59-'VALORES TABELA'!$C$59,($G12-$E12)*'VALORES TABELA'!$B$60-'VALORES TABELA'!$C$60)))) -> 0 | K12: =IF(($I12-$E12)<='VALORES TABELA'!$A$56,0,IF(($I12-$E12)<='VALORES TABELA'!$A$57,($I12-$E12)*'VALORES TABELA'!$B$57-'VALORES TABELA'!$C$57,IF(($I12-$E12)<='VALORES TABELA'!$A$58,($I12-$E12)*'VALORES TABELA'!$B$58-'VALORES TABELA'!$C$58,IF(($I12-$E12)<='VALORES TABELA'!$A$59,($I12-$E12)*'VALORES TABELA'!$B$59-'VALORES TABELA'!$C$59,($I12-$E12)*'VALORES TABELA'!$B$60-'VALORES TABELA'!$C$60))))-J11 -> 0
A13: 2023/0010767 | B13: 6020.2023/0010767-0 | C13: 31.534.583/0001-64 | D13: =SUMIF('APONTAMENTO CREDENCIAMENTO'!$D$5:$D$3847,$A13,'APONTAMENTO CREDENCIAMENTO'!$FF$5:$FF$3847) -> 0 | E13: =IF(D13=0,0,IF(D13*0.2*0.11>607.2,607.2,IF(D13<42377.92,D13*0.2*0.11,IF(D13*0.2*0.11>932.31,932.31)))) -> 0 | F13: =$D13*'VALORES TABELA'!$B$45*'VALORES TABELA'!$B$46 -> 0 | G13: =D13*60% -> 0 | H13: =_xlfn.LET(_xlpm.base,G13,_xlpm.bruto,E13+G13,_xlpm.ir_normal,IF(_xlpm.base<='VALORES TABELA'!$J$1,'VALORES TABELA'!$K$1,IF(_xlpm.base<='VALORES TABELA'!$J$2,_xlpm.base*'VALORES TABELA'!$K$2-'VALORES TABELA'!$L$2,IF(_xlpm.base<='VALORES TABELA'!$J$3,_xlpm.base*'VALORES TABELA'!$K$3-'VALORES TABELA'!$L$3,IF(_xlpm.base<='VALORES TABELA'!$J$4,_xlpm.base*'VALORES TABELA'!$K$4-'VALORES TABELA'!$L$4,_xlpm.base*'VALORES TABELA'!$K$5-'VALORES TABELA'!$L$5)))),_xlpm.redutor,IF(_xlpm.bruto<='VALORES TABELA'!$J$6,_xlpm.ir_normal,IF(_xlpm.bruto<='VALORES TABELA'!$K$6,MIN(_xlpm.ir_normal,'VALORES TABELA'!$L$6-'VALORES TABELA'!$M$6*_xlpm.bruto),0)),TRUNC(MAX(0,_xlpm.ir_normal-_xlpm.redutor),2)) -> 0 | I13: =IF($C13=$C12,($D13+$D12)*'VALORES TABELA'!$B$50-$E12,$D13*'VALORES TABELA'!$B$50) -> 0 | J13: =IF(($G13-E13)<='VALORES TABELA'!$A$56,0,IF(($G13-$E13)<='VALORES TABELA'!$A$57,($G13-$E13)*'VALORES TABELA'!$B$57-'VALORES TABELA'!$C$57,IF(($G13-$E13)<='VALORES TABELA'!$A$58,($G13-$E13)*'VALORES TABELA'!$B$58-'VALORES TABELA'!$C$58,IF(($G13-$E13)<='VALORES TABELA'!$A$59,($G13-$E13)*'VALORES TABELA'!$B$59-'VALORES TABELA'!$C$59,($G13-$E13)*'VALORES TABELA'!$B$60-'VALORES TABELA'!$C$60)))) -> 0 | K13: =IF(($I13-$E13)<='VALORES TABELA'!$A$56,0,IF(($I13-$E13)<='VALORES TABELA'!$A$57,($I13-$E13)*'VALORES TABELA'!$B$57-'VALORES TABELA'!$C$57,IF(($I13-$E13)<='VALORES TABELA'!$A$58,($I13-$E13)*'VALORES TABELA'!$B$58-'VALORES TABELA'!$C$58,IF(($I13-$E13)<='VALORES TABELA'!$A$59,($I13-$E13)*'VALORES TABELA'!$B$59-'VALORES TABELA'!$C$59,($I13-$E13)*'VALORES TABELA'!$B$60-'VALORES TABELA'!$C$60))))-J12 -> 0
A14: 2025/0001782 | B14: 6020.2025/0001782-9 | C14: 22.618.510/0001-60 | D14: =SUMIF('APONTAMENTO CREDENCIAMENTO'!$D$5:$D$3847,$A14,'APONTAMENTO CREDENCIAMENTO'!$FF$5:$FF$3847) -> 0 | E14: =IF(D14=0,0,IF(D14*0.2*0.11>607.2,607.2,IF(D14<42377.92,D14*0.2*0.11,IF(D14*0.2*0.11>932.31,932.31)))) -> 0 | F14: =$D14*'VALORES TABELA'!$B$45*'VALORES TABELA'!$B$46 -> 0 | G14: =D14*60% -> 0 | H14: =_xlfn.LET(_xlpm.base,G14,_xlpm.bruto,E14+G14,_xlpm.ir_normal,IF(_xlpm.base<='VALORES TABELA'!$J$1,'VALORES TABELA'!$K$1,IF(_xlpm.base<='VALORES TABELA'!$J$2,_xlpm.base*'VALORES TABELA'!$K$2-'VALORES TABELA'!$L$2,IF(_xlpm.base<='VALORES TABELA'!$J$3,_xlpm.base*'VALORES TABELA'!$K$3-'VALORES TABELA'!$L$3,IF(_xlpm.base<='VALORES TABELA'!$J$4,_xlpm.base*'VALORES TABELA'!$K$4-'VALORES TABELA'!$L$4,_xlpm.base*'VALORES TABELA'!$K$5-'VALORES TABELA'!$L$5)))),_xlpm.redutor,IF(_xlpm.bruto<='VALORES TABELA'!$J$6,_xlpm.ir_normal,IF(_xlpm.bruto<='VALORES TABELA'!$K$6,MIN(_xlpm.ir_normal,'VALORES TABELA'!$L$6-'VALORES TABELA'!$M$6*_xlpm.bruto),0)),TRUNC(MAX(0,_xlpm.ir_normal-_xlpm.redutor),2)) -> 0 | I14: =IF($C14=$C13,($D14+$D13)*'VALORES TABELA'!$B$50-$E13,$D14*'VALORES TABELA'!$B$50) -> 0 | J14: =IF(($G14-E14)<='VALORES TABELA'!$A$56,0,IF(($G14-$E14)<='VALORES TABELA'!$A$57,($G14-$E14)*'VALORES TABELA'!$B$57-'VALORES TABELA'!$C$57,IF(($G14-$E14)<='VALORES TABELA'!$A$58,($G14-$E14)*'VALORES TABELA'!$B$58-'VALORES TABELA'!$C$58,IF(($G14-$E14)<='VALORES TABELA'!$A$59,($G14-$E14)*'VALORES TABELA'!$B$59-'VALORES TABELA'!$C$59,($G14-$E14)*'VALORES TABELA'!$B$60-'VALORES TABELA'!$C$60)))) -> 0 | K14: =IF(($I14-$E14)<='VALORES TABELA'!$A$56,0,IF(($I14-$E14)<='VALORES TABELA'!$A$57,($I14-$E14)*'VALORES TABELA'!$B$57-'VALORES TABELA'!$C$57,IF(($I14-$E14)<='VALORES TABELA'!$A$58,($I14-$E14)*'VALORES TABELA'!$B$58-'VALORES TABELA'!$C$58,IF(($I14-$E14)<='VALORES TABELA'!$A$59,($I14-$E14)*'VALORES TABELA'!$B$59-'VALORES TABELA'!$C$59,($I14-$E14)*'VALORES TABELA'!$B$60-'VALORES TABELA'!$C$60))))-J13 -> 0

Sheet DEMO FIS
B9: DADOS DO CONTRATO LICITADO
A10: CONTRATO Nº | C10: CRMC | D10: Placas | F10: Km/mês | G10: Alunos/Mês | H10: Mês base | I10: D.R.E
A11: ='BASE C'!B3 -> 2026/0016071 | C11: =VLOOKUP(A11,ProcRel!A1:C5000,3,0) -> 006.336-00 | D11: =VLOOKUP(A11,'APONTAMENTO CREDENCIAMENTO'!$D$6:$D$3847,1,FALSE) -> #N/A | F11: =SUMIF('APONTAMENTO CREDENCIAMENTO'!D$5:D$4950,A11,'APONTAMENTO CREDENCIAMENTO'!N$5:N$4950) -> 0 | G11: ='EMPRESA C'!H16+'EMPRESA C'!I16+'EMPRESA C'!J16+'EMPRESA C'!K16+'EMPRESA C'!L16+'EMPRESA C'!M16 -> 0 | H11: ='BASE C'!E4 -> ABRIL | I11: ='BASE C'!D2 -> FREGUESIA / BRASILÂNDIA
A12: Nome do Contratado | F12: CPF | H12: Período
A13: =VLOOKUP(A11,'APONTAMENTO CREDENCIAMENTO'!D1:J4950,6,FALSE) -> #N/A | F13: =VLOOKUP(A11,ProcRel1!E2:G5000,3,FALSE) -> 65.425.834/0001-94 | H13: ='BASE C'!B4 -> 01/04/2026 | I13: ='BASE C'!C4 -> 30/04/2026
F14: Processo SEI! | H14: Previsão de Crédito
F15: =VLOOKUP(A11,'APONTAMENTO CREDENCIAMENTO'!D1:O3845,12,FALSE) -> #N/A | H15: ='VALORES TABELA'!B37 -> 46171
B17: DEMONSTRATIVO DE PAGAMENTO
A19: Descrição | H19: Valor ( em Reais )
A20: ( A ) | B20: Remuneração Fixa integral | I20: =VLOOKUP(A11,'APONTAMENTO CREDENCIAMENTO'!$D$6:$EW$3847,150,FALSE) -> #N/A
A21: ( B ) | B21: Remuneração transporte alunos presenciais | I21: =SUMIF('APONTAMENTO CREDENCIAMENTO'!D$5:D$4950,A11,'APONTAMENTO CREDENCIAMENTO'!EX$5:EX$4950) -> 0
A22: ( C ) | B22: Remuneração CCA | I22: =SUMIF('APONTAMENTO CREDENCIAMENTO'!D5:D4950,A11,'APONTAMENTO CREDENCIAMENTO'!FB5:FB4950) -> 0
A23: ( D ) | B23: Remuneração transporte alunos presenciais valor proporconial (menos de 30 dias) | I23: =SUMIF('APONTAMENTO CREDENCIAMENTO'!D5:D4950,A11,'APONTAMENTO CREDENCIAMENTO'!EZ5:EZ4950) -> 0
A24: ( E ) | B24: Saida de Alunos ao longo do mês | I24: =SUMIF('APONTAMENTO CREDENCIAMENTO'!D5:D4950,A11,'APONTAMENTO CREDENCIAMENTO'!FA5:FA4950) -> 0
A25: ( F ) | B25: Remuneração Variável Medida km adicional | I25: =SUMIF('APONTAMENTO CREDENCIAMENTO'!D5:D4950,A11,'APONTAMENTO CREDENCIAMENTO'!FC5:FC4950) -> 0
A26: ( G ) | B26: Ajuste positivo | I26: =VLOOKUP(A11,'APONTAMENTO CREDENCIAMENTO'!D5:ID4950,230,0) -> #N/A
A27: ( H ) | B27: Ajustes Negativos | I27: =VLOOKUP(A11,'APONTAMENTO CREDENCIAMENTO'!D5:ID4950,231,0)*-1 -> #N/A
A28: ( I ) | B28: Descontos por Faltas | I28: =VLOOKUP(A11,'APONTAMENTO CREDENCIAMENTO'!D5:ID4950,232,0)*-1 -> #N/A
A29: ( J ) | B29: Atividade Complementar Continuada | E29: =SUMIF('APONTAMENTO CREDENCIAMENTO'!D5:D4950,A11,'APONTAMENTO CREDENCIAMENTO'!L5:L4950) -> 0 | F29: Regular | G29: =SUMIF('APONTAMENTO CREDENCIAMENTO'!D5:D4950,A11,'APONTAMENTO CREDENCIAMENTO'!M5:M4950) -> 0 | H29: Cadeirante | I29: =SUMIF('APONTAMENTO CREDENCIAMENTO'!D5:D4950,A11,'APONTAMENTO CREDENCIAMENTO'!EY5:EY4950) -> 0
A30: ( K ) | B30: Outros Apontamentos | I30: =SUMIF('APONTAMENTO CREDENCIAMENTO'!D5:D4950,A11,'APONTAMENTO CREDENCIAMENTO'!FD5:FD4950) -> 0
A31: ( L ) | B31: Remuneração bruta (A+B+C+D+E+F+G+H+I) - (H-J) | I31: =(I20+I21+I22+I23+I24+I25+I26+I27+I28+I29+I30) -> #N/A
A32: ( M ) | B32: INSS 11% | I32: =VLOOKUP(A11,'ATESTE-LIQ-FIS'!A4:K3908,5,0)*-1 -> #N/A
A33: ( N ) | B33: SEST/SENAT 2,5% | I33: =VLOOKUP(A11,'ATESTE-LIQ-FIS'!A4:K3908,6,0)*-1 -> #N/A
A34: ( O ) | B34: Imposto de Renda Retido na Fonte | I34: =-MIN('Cálculo IRRF -Jan.2026'!D33:F33) -> #N/A
A35: ( P ) | B35: Desconto por Multa Contratual - Enquadramento | I35: 0
A36: ( Q ) | B36: Remuneração Líquida (L-M-N-O-P) | I36: =SUM(H31:I35) -> #N/A
A37: OBS FIN: | B37: =VLOOKUP(A11,'APONTAMENTO CREDENCIAMENTO'!D1:EL3845,138,FALSE) -> #N/A
A39: OBS DRE: | B39: =VLOOKUP(A11,'APONTAMENTO CREDENCIAMENTO'!D1:EL3845,139,FALSE) -> #N/A
B42: São Paulo,______/______/______ Assinatura do Contratado__________________________________
A44: N CAD PRES | C44: AT COMP N CAD PRES | E44: CAD PRES | G44: AT COMP CAD PRES | I44: TOTAL
A45: =SUMIF('APONTAMENTO CREDENCIAMENTO'!D5:D4950,A11,'APONTAMENTO CREDENCIAMENTO'!EP5:EP4950) -> 0 | C45: =SUMIF('APONTAMENTO CREDENCIAMENTO'!D5:D4950,A11,'APONTAMENTO CREDENCIAMENTO'!ER5:ER4950) -> 0 | E45: =SUMIF('APONTAMENTO CREDENCIAMENTO'!D5:D4950,A11,'APONTAMENTO CREDENCIAMENTO'!ES5:ES4950) -> 0 | G45: =SUMIF('APONTAMENTO CREDENCIAMENTO'!D5:D4950,A11,'APONTAMENTO CREDENCIAMENTO'!EU5:EU4950) -> 0 | I45: =SUM(A45:H45) -> 0
B47: São Paulo,______/______/______ Assinatura do Responsável na D.R.E__________________________________
A49: Documentos necessários para liquidação
A50: Enviar os documentos na ordem informada abaixo em um único arquivo PDF.
A51: 1 - Demonstrativo assinado.
A52: 2 - Nota fiscal referente ao valor bruto.
A53: 3 - Guia do INSS e comprovante de pagamento referente a competência: | G53: =$H$13+1-1 -> 46113
A54: 4 - Guia do FGTS e comprovante de pagamento referente a competência: | G54: =G53 -> 46113
A55: 5 - Relatório do FGTS digital.
A56: Informações importantes
B57: Link Cadin: | E57: http://www3.prefeitura.sp.gov.br/cadin/Pesq_Deb.aspx
B58: Link para consulta de pagamento: | E58: http://sfemp.prefeitura.sp.gov.br/cons_pagto.aspx
A59: Para declaração de IRRF, favor utilizarem este CNPJ - Secretaria Municipal da Fazenda (Fonte Pagadora) 46.392.130/0003-80
B60: Link Informe de rendimentos IR: | E60: https://sofconsulta.prefeitura.sp.gov.br/ir
A61: Para emissão das notas fiscais, favor utilizarem este CNPJ - Secretaria Municipal de Mobilidade e Transp. 46.392.155/0001-11
B62: Obs. O número do seu processo SEI! encontra-se na parte superior do demonstrativo

Sheet EMPRESA C
B7: Demonstrativo de Pagamento: | G7: ='BASE C'!D10 -> #N/A
B9: Contrato : | D9: ='BASE C'!B3 -> 2026/0016071 | G9: CE: | H9: ='APONTAMENTO CREDENCIAMENTO'!A1 -> Freguesia / Brasilândia
D10: Mês: | E10: ='BASE C'!E4 -> ABRIL | G10: Período | H10: ='BASE C'!N3 -> 01/04/2026 | I10: à | J10: ='BASE C'!O3 -> 30/04/2026
A12: NOME CONDUTOR | B12: OPERAÇÃO DO CONDUTOR | D12: CRMC | E12: VEICULO | G12: Operação/ Mês | N12: Valores/Mês | Y12: multa | Z12: Valor Bruto | AA12: Base de Cálculo IR | AB12: IR | AC12: Valor Liquido
G13: KM ADICIONAL | H13: TOTAL ALUNOS N CAD PRESENCIAIS (30 DIAS) | I13: TOTAL ALUNOS N CAD PRESENCIAIS ( MENOS DE 30 DIAS) | J13: TOTAL ALUNOS ATIV.COMPL. N CAD | K13: TOTAL ALUNOS CAD PRESENCIAIS (30 DIAS) | L13: TOTAL ALUNOS CAD PRESENCIAIS (MENOS DE 30 DIAS | M13: TOTAL ALUNOS ATIV.COMPL. CAD | N13: Contratos Especiais (Valor fixo) | O13: ='APONTAMENTO CREDENCIAMENTO'!EX4 -> Valor total alunos presenciais (30 dias) | P13: ='APONTAMENTO CREDENCIAMENTO'!EY4 -> Ativ.Complementar Continuada | Q13: ='APONTAMENTO CREDENCIAMENTO'!EZ4 -> Valor alunos presenciais (menos de 30 dias) | R13: ='APONTAMENTO CREDENCIAMENTO'!FA4 -> Saida de alunos ao longo do mês | S13: CCA | T13: ='APONTAMENTO CREDENCIAMENTO'!FC4 -> Valor km adicional | U13: Ajuste positivo | V13: Ajuste negativo | W13: Desconto faltas | X13: Recesso escolar desconto de 10 dias nas atividades complementares
A14: =VLOOKUP(D14,'BASE C'!$C$10:$E$5000,3,0) -> #N/A | B14: =VLOOKUP(D14,'APONTAMENTO CREDENCIAMENTO'!$A$6:$F$3848,6,0) -> #N/A | C14: =VLOOKUP(D14,'APONTAMENTO CREDENCIAMENTO'!$A$6:$G$3848,7,0) -> #N/A | D14: ='BASE C'!C10 -> 006.336-00 | E14: ='BASE C'!H10 -> #N/A | G14: =SUMIF('APONTAMENTO CREDENCIAMENTO'!$A$6:$A$3848,'EMPRESA C'!D14,'APONTAMENTO CREDENCIAMENTO'!$N$6:$N$3848) -> 0 | H14: =SUMIF('APONTAMENTO CREDENCIAMENTO'!$A$6:$A$3848,'EMPRESA C'!D14,'APONTAMENTO CREDENCIAMENTO'!$EP$6:$EP$3848) -> 0 | I14: =SUMIF('APONTAMENTO CREDENCIAMENTO'!$A$6:$A$3848,'EMPRESA C'!D14,'APONTAMENTO CREDENCIAMENTO'!$EQ$6:$EQ$3848) -> 0 | J14: =SUMIF('APONTAMENTO CREDENCIAMENTO'!$A$6:$A$3848,'EMPRESA C'!D14,'APONTAMENTO CREDENCIAMENTO'!$ER$6:$ER$3848) -> 0 | K14: =SUMIF('APONTAMENTO CREDENCIAMENTO'!$A$6:$A$3848,'EMPRESA C'!D14,'APONTAMENTO CREDENCIAMENTO'!$ES$6:$ES$3848) -> 0 | L14: =SUMIF('APONTAMENTO CREDENCIAMENTO'!$A$6:$A$3848,'EMPRESA C'!D14,'APONTAMENTO CREDENCIAMENTO'!$ET$6:$ET$3848) -> 0 | M14: =SUMIF('APONTAMENTO CREDENCIAMENTO'!$A$6:$A$3848,'EMPRESA C'!D14,'APONTAMENTO CREDENCIAMENTO'!$EU$6:$EU$3848) -> 0 | N14: =SUMIF('APONTAMENTO CREDENCIAMENTO'!$A$6:$A$3848,'EMPRESA C'!D14,'APONTAMENTO CREDENCIAMENTO'!$EW$6:$EW$3848) -> 0 | O14: =SUMIF('APONTAMENTO CREDENCIAMENTO'!$A$6:$A$3848,'EMPRESA C'!D14,'APONTAMENTO CREDENCIAMENTO'!$EX$6:$EX$3848) -> 0 | P14: =SUMIF('APONTAMENTO CREDENCIAMENTO'!$A$5:$A$3848,'EMPRESA C'!D14,'APONTAMENTO CREDENCIAMENTO'!$EY$5:$EY$3848) -> 0 | Q14: =SUMIF('APONTAMENTO CREDENCIAMENTO'!$A$5:$A$3848,'EMPRESA C'!D14,'APONTAMENTO CREDENCIAMENTO'!$EZ$5:$EZ$3848) -> 0 | R14: =SUMIF('APONTAMENTO CREDENCIAMENTO'!$A$5:$A$3848,'EMPRESA C'!D14,'APONTAMENTO CREDENCIAMENTO'!$FA$5:$FA$3848) -> 0 | S14: =SUMIF('APONTAMENTO CREDENCIAMENTO'!$A$5:$A$3848,'EMPRESA C'!D14,'APONTAMENTO CREDENCIAMENTO'!$FB$5:$FB$3848) -> 0 | T14: =SUMIF('APONTAMENTO CREDENCIAMENTO'!$A$5:$A$3848,'EMPRESA C'!D14,'APONTAMENTO CREDENCIAMENTO'!$FC$5:$FC$3848) -> 0 | U14: =SUMIF('APONTAMENTO CREDENCIAMENTO'!$A$5:$A$3848,'EMPRESA C'!D14,'APONTAMENTO CREDENCIAMENTO'!$IB$5:$IB$3848) -> 0 | V14: =SUMIF('APONTAMENTO CREDENCIAMENTO'!$A$5:$A$3848,'EMPRESA C'!D14,'APONTAMENTO CREDENCIAMENTO'!$IC$5:$IC$3848)*-1 -> 0 | W14: =SUMIF('APONTAMENTO CREDENCIAMENTO'!$A$5:$A$3848,'EMPRESA C'!D14,'APONTAMENTO CREDENCIAMENTO'!$ID$5:$ID$3848)*-1 -> 0 | X14: =SUMIF('APONTAMENTO CREDENCIAMENTO'!$A$5:$A$3848,'EMPRESA C'!D14,'APONTAMENTO CREDENCIAMENTO'!$FD$5:$FD$3848) -> 0 | Y14: =SUMIF('APONTAMENTO CREDENCIAMENTO'!$A$5:$A$3848,'EMPRESA C'!D14,'APONTAMENTO CREDENCIAMENTO'!$GN$5:$GN$3848)*-1 -> 0 | Z14: =(N14+O14+P14+Q14+R14+S14+T14+U14+V14+W14+X14+Y14) -> 0 | AA14: =Z14 -> 0 | AB14: =AA14*'BASE C'!B$7 -> #N/A | AC14: =AA14-AB14 -> #N/A
G16: =SUM(G14:G15) -> 0 | H16: =SUM(H14:H15) -> 0 | I16: =SUM(I14:I15) -> 0 | J16: =SUM(J14:J15) -> 0 | K16: =SUM(K14:K15) -> 0 | L16: =SUM(L14:L15) -> 0 | M16: =SUM(M14:M15) -> 0 | N16: =SUM(N14:N15) -> 0 | ... AC16: =SUM(AC14:AC15) -> #N/A
G18: Atestado pela CE através da planilha de compromisso a pagar - processo de pagamento

Sheet ATESTADO C
Z1: =VLOOKUP(A14,#REF!,27,0) -> #REF!
B10: ATESTADO DE PRESTAÇÃO DE SERVIÇOS
A13: CONTRATO | B13: EMPRESA | E13: Mês base | G13: Período | M13: C.E.
A14: ='BASE C'!B3 -> 2026/0016071 | B14: ='BASE C'!D4 -> #N/A | E14: ='BASE C'!E4 -> ABRIL | J14: ='EMPRESA C'!H10 -> 01/04/2026 | K14: a | L14: ='BASE C'!C4 -> 30/04/2026 | M14: ='BASE C'!C2 -> FB
E16: CREDENCIAMENTO | L16: OBSERVAÇÕES
A17: NOME CONDUTOR | B17: CRMC | C17: PLACA | D17: KM ADICIONAL | E17: TOTAL ALUNOS N CAD PRESENCIAIS (30 DIAS) | F17: TOTAL ALUNOS N CAD PRESENCIAIS ( MENOS DE 30 DIAS) | G17: TOTAL ALUNOS ATIV.COMPL. N CAD | H17: TOTAL ALUNOS CAD PRESENCIAIS (30 DIAS) | I17: TOTAL ALUNOS CAD PRESENCIAIS (MENOS DE 30 DIAS | J17: TOTAL ALUNOS ATIV.COMPL. CAD | K17: TOTAL GERAL
A18: =VLOOKUP(B18,'BASE C'!$C$10:$E$5000,3,0) -> #N/A | B18: ='BASE C'!C10 -> 006.336-00 | C18: ='BASE C'!H10 -> #N/A | D18: =SUMIF('APONTAMENTO CREDENCIAMENTO'!$A$6:$A$3848,'ATESTADO C'!B18,'APONTAMENTO CREDENCIAMENTO'!$N$6:$N$3848) -> 0 | E18: =SUMIF('APONTAMENTO CREDENCIAMENTO'!$A$6:$A$3848,'ATESTADO C'!B18,'APONTAMENTO CREDENCIAMENTO'!$EP$6:$EP$3848) -> 0 | F18: =SUMIF('APONTAMENTO CREDENCIAMENTO'!$A$6:$A$3848,'ATESTADO C'!B18,'APONTAMENTO CREDENCIAMENTO'!$EQ$6:$EQ$3848) -> 0 | G18: =SUMIF('APONTAMENTO CREDENCIAMENTO'!$A$6:$A$3848,'ATESTADO C'!B18,'APONTAMENTO CREDENCIAMENTO'!$ER$6:$ER$3848) -> 0 | H18: =SUMIF('APONTAMENTO CREDENCIAMENTO'!$A$6:$A$3848,'ATESTADO C'!B18,'APONTAMENTO CREDENCIAMENTO'!$ES$6:$ES$3848) -> 0 | I18: =SUMIF('APONTAMENTO CREDENCIAMENTO'!$A$6:$A$3848,'ATESTADO C'!B18,'APONTAMENTO CREDENCIAMENTO'!$ET$6:$ET$3848) -> 0 | J18: =SUMIF('APONTAMENTO CREDENCIAMENTO'!$A$6:$A$3848,'ATESTADO C'!B18,'APONTAMENTO CREDENCIAMENTO'!$EU$6:$EU$3848) -> 0 | K18: =E18+F18+H18+I18+G18+J18 -> 0 | L18: =CONCATENATE(VLOOKUP(B18,'APONTAMENTO CREDENCIAMENTO'!$A$6:$EK$3848,141,0)," - ",VLOOKUP(B18,'APONTAMENTO CREDENCIAMENTO'!$A$6:$EL$3848,142,0)) -> #N/A
A20: Diretor da DRE | D20: Responsável pelo Ateste do Serviço na DRE | L20: Responsável pelo TEG na DRE
A21: Nome: | D21: Nome: | L21: Nome:
A22: RF: | D22: RF: | L22: RF:
A23: Cargo: | D23: Cargo: | L23: Cargo:

Sheet Planilha1

Sheet ProcRel
A1: 2025/0018729 | B1: 25.292.508 CLAUDIA COSTA BORCA | C1: 029.007-00
A2: 2022/0025069 | B2: ANTOGRA TRANSPORTE E LOGISTICA EIRELI - ME | C2: 051.992-00
A3: 2022/0026693 | B3: COOPER-X - COOP. SERV. TRANSP. ESCOLAR SP | C3: 046.762-00
A4: 2022/0026745 | B4: LUIGI TRANSPORTES ESCOLARES LTDA - ME | C4: 032.433-00
A5: 2022/0026751 | B5: KAUA TRANSPORTE ESCOLAR S/S LTDA - ME | C5: 007.633-01
A6: 2022/0026934 | B6: DORGIVAL TRANSPORTE ESCOLAR LTDA | C6: 022.565-00
A7: 2022/0027035 | B7: CLAUDIA GOMES FREITAS TOLEDO EIRELI - ME | C7: 038.336-00
A8: 2022/0027035 | B8: CLAUDIA GOMES FREITAS TOLEDO EIRELI - ME | C8: 051.941-00
A9: 2022/0027240 | B9: TRANSESCOLAR LOPES COELHO LTDA - ME | C9: 011.644-00
A10: 2022/0027740 | B10: WELL TRANSPORTE ESCOLAR LTDA - ME | C10: 046.640-00
A11: 2022/0027919 | B11: ROBERTO HERNANDES TRANSPORTES LTDA | C11: 048.347-00
A12: 2022/0028862 | B12: F.A.C.E TRANSPORTES ESCOLARES LTDA - ME | C12: 049.882-00
... A148: 2026/0016071 | B148: LUANETO TRANSPORTE ESCOLAR LTDA | C148: 006.336-00

Sheet ProcRel1
E1: Termo_de_adesao | F1: SEI | G1: CNPJ_CPF
E2: 2025/0018729 | F2: 6020.2025/0018729-5 | G2: 25.292.508/0001-31
E3: 2025/0037122 | F3: 6020.2025/0037122-3 | G3: 60.676.117/0001-11
E4: 2025/0039901 | F4: 6020.2025/0039901-2 | G4: 61.246.494/0001-83
E5: 2025/0068352 | F5: 6020.2025/0068352-7 | G5: 63.673.349/0001-04
E6: 2025/0037287 | F6: 6020.2025/0037287-4 | G6: 19.578.216/0001-67
E7: 2025/0040147 | F7: 6020.2025/0040147-5 | G7: 60.661.528/0001-33
E8: 2025/0010904 | F8: 6020.2025/0010904-9 | G8: 15.537.940/0001-91
E9: 2023/0030066 | F9: 6020.2023/0030066-7 | G9: 15.537.940/0001-91
E10: 2022/0036627 | F10: 6020.2022/0036627-5 | G10: 15.537.940/0001-91
E11: 2025/0040165 | F11: 6020.2025/0040165-3 | G11: 52.595.342/0001-03
E12: 2023/0019642 | F12: 6020.2023/0019642-8 | G12: 23.668.295/0001-74
... E149: 2022/0032075 | F149: 6020.2022/0032075-5 | G149: 16.731.558/0001-87

Sheet ATESTE-LIQ
A1: CONTRATO | B1: LIQUIDAÇÃO | C1: EMPENHO | D1: PA | E1: NF | F1: VALOR | G1: PER. REALIZAÇÃO | J1: LIQUIDADO | K1: IR | L1: EMPRESA | M1: LIQUIDAÇÃO | N1: SOF | O1: CONF | P1: RESERVA | Q1: SUB | R1: EL | S1: REFERÊNCIA | T1: PA | U1: TOTAL | V1: SETEMBRO | W1: EMPENHO | AA1: HISTÓRICO / ANEXO | AB1: NOME | AC1: CONFERÊNCIA | AD1: ANO
A2: 2025/0018729 | C2: =W2 -> 0 | D2: =VLOOKUP(A2,'APONTAMENTO CREDENCIAMENTO'!$D$6:$P$2821,12,0) -> 6020.2025/0018729-5 | F2: =SUMIF('APONTAMENTO CREDENCIAMENTO'!$D$6:$D$2821,'ATESTE-LIQ'!A2,'APONTAMENTO CREDENCIAMENTO'!$FF$6:$FF$2821) -> 880.27038 | G2: =VLOOKUP(A2,'APONTAMENTO CREDENCIAMENTO'!$D$6:$G$2821,3,0) -> 01/04/2026 | H2: =VLOOKUP(A2,'APONTAMENTO CREDENCIAMENTO'!$D$6:$G$2821,4,0) -> 30/04/2026 | I2: =CONCATENATE("PE - Pagto. Doc(s): ",E2," - Contrato nº ",A2) -> PE - Pagto. Doc(s): - Contrato nº 2025/0018729 | J2: =F2 -> 880.27038 | K2: 0 | L2: =VLOOKUP(A2,'APONTAMENTO CREDENCIAMENTO'!$D$6:$P$2821,5,0) -> 25.292.508 CLAUDIA COSTA BORCA | T2: =D2 -> 6020.2025/0018729-5 | U2: =F2 -> 880.27038 | V2: =U2 -> 880.27038 | AA2: =CONCATENATE("Prestação de Serviço e Transpor. Escolar Gratuito - TEG n. ",A2," - DRE - " &'BASE C'!$C$2) -> Prestação de Serviço e Transpor. Escolar Gratuito - TEG n. 2025/0018729 - DRE - FB | AB2: =L2 -> 25.292.508 CLAUDIA COSTA BORCA
A3: 2022/0025069 | C3: =W3 -> 0 | D3: =VLOOKUP(A3,'APONTAMENTO CREDENCIAMENTO'!$D$6:$P$2821,12,0) -> #N/A | F3: =SUMIF('APONTAMENTO CREDENCIAMENTO'!$D$6:$D$2821,'ATESTE-LIQ'!A3,'APONTAMENTO CREDENCIAMENTO'!$FF$6:$FF$2821) -> 0 | G3: =VLOOKUP(A3,'APONTAMENTO CREDENCIAMENTO'!$D$6:$G$2821,3,0) -> #N/A | H3: =VLOOKUP(A3,'APONTAMENTO CREDENCIAMENTO'!$D$6:$G$2821,4,0) -> #N/A | I3: =CONCATENATE("PE - Pagto. Doc(s): ",E3," - Contrato nº ",A3) -> PE - Pagto. Doc(s): - Contrato nº 2022/0025069 | J3: =F3 -> 0 | K3: 0 | L3: =VLOOKUP(A3,'APONTAMENTO CREDENCIAMENTO'!$D$6:$P$2821,5,0) -> #N/A | T3: =D3 -> #N/A | U3: =F3 -> 0 | V3: =U3 -> 0 | AA3: =CONCATENATE("Prestação de Serviço e Transpor. Escolar Gratuito - TEG n. ",A3," - DRE - " &'BASE C'!$C$2) -> Prestação de Serviço e Transpor. Escolar Gratuito - TEG n. 2022/0025069 - DRE - FB | AB3: =L3 -> #N/A
A4: 2022/0026693 | C4: =W4 -> 0 | D4: =VLOOKUP(A4,'APONTAMENTO CREDENCIAMENTO'!$D$6:$P$2821,12,0) -> #N/A | F4: =SUMIF('APONTAMENTO CREDENCIAMENTO'!$D$6:$D$2821,'ATESTE-LIQ'!A4,'APONTAMENTO CREDENCIAMENTO'!$FF$6:$FF$2821) -> 0 | G4: =VLOOKUP(A4,'APONTAMENTO CREDENCIAMENTO'!$D$6:$G$2821,3,0) -> #N/A | H4: =VLOOKUP(A4,'APONTAMENTO CREDENCIAMENTO'!$D$6:$G$2821,4,0) -> #N/A | I4: =CONCATENATE("PE - Pagto. Doc(s): ",E4," - Contrato nº ",A4) -> PE - Pagto. Doc(s): - Contrato nº 2022/0026693 | J4: =F4 -> 0 | K4: 0 | L4: =VLOOKUP(A4,'APONTAMENTO CREDENCIAMENTO'!$D$6:$P$2821,5,0) -> #N/A | T4: =D4 -> #N/A | U4: =F4 -> 0 | V4: =U4 -> 0 | AA4: =CONCATENATE("Prestação de Serviço e Transpor. Escolar Gratuito - TEG n. ",A4," - DRE - " &'BASE C'!$C$2) -> Prestação de Serviço e Transpor. Escolar Gratuito - TEG n. 2022/0026693 - DRE - FB | AB4: =L4 -> #N/A
A5: 2022/0026745 | C5: =W5 -> 0 | D5: =VLOOKUP(A5,'APONTAMENTO CREDENCIAMENTO'!$D$6:$P$2821,12,0) -> #N/A | F5: =SUMIF('APONTAMENTO CREDENCIAMENTO'!$D$6:$D$2821,'ATESTE-LIQ'!A5,'APONTAMENTO CREDENCIAMENTO'!$FF$6:$FF$2821) -> 0 | G5: =VLOOKUP(A5,'APONTAMENTO CREDENCIAMENTO'!$D$6:$G$2821,3,0) -> #N/A | H5: =VLOOKUP(A5,'APONTAMENTO CREDENCIAMENTO'!$D$6:$G$2821,4,0) -> #N/A | I5: =CONCATENATE("PE - Pagto. Doc(s): ",E5," - Contrato nº ",A5) -> PE - Pagto. Doc(s): - Contrato nº 2022/0026745 | J5: =F5 -> 0 | K5: 0 | L5: =VLOOKUP(A5,'APONTAMENTO CREDENCIAMENTO'!$D$6:$P$2821,5,0) -> #N/A | T5: =D5 -> #N/A | U5: =F5 -> 0 | V5: =U5 -> 0 | AA5: =CONCATENATE("Prestação de Serviço e Transpor. Escolar Gratuito - TEG n. ",A5," - DRE - " &'BASE C'!$C$2) -> Prestação de Serviço e Transpor. Escolar Gratuito - TEG n. 2022/0026745 - DRE - FB | AB5: =L5 -> #N/A
A6: 2022/0026751 | C6: =W6 -> 0 | D6: =VLOOKUP(A6,'APONTAMENTO CREDENCIAMENTO'!$D$6:$P$2821,12,0) -> #N/A | F6: =SUMIF('APONTAMENTO CREDENCIAMENTO'!$D$6:$D$2821,'ATESTE-LIQ'!A6,'APONTAMENTO CREDENCIAMENTO'!$FF$6:$FF$2821) -> 0 | G6: =VLOOKUP(A6,'APONTAMENTO CREDENCIAMENTO'!$D$6:$G$2821,3,0) -> #N/A | H6: =VLOOKUP(A6,'APONTAMENTO CREDENCIAMENTO'!$D$6:$G$2821,4,0) -> #N/A | I6: =CONCATENATE("PE - Pagto. Doc(s): ",E6," - Contrato nº ",A6) -> PE - Pagto. Doc(s): - Contrato nº 2022/0026751 | J6: =F6 -> 0 | K6: 0 | L6: =VLOOKUP(A6,'APONTAMENTO CREDENCIAMENTO'!$D$6:$P$2821,5,0) -> #N/A | T6: =D6 -> #N/A | U6: =F6 -> 0 | V6: =U6 -> 0 | AA6: =CONCATENATE("Prestação de Serviço e Transpor. Escolar Gratuito - TEG n. ",A6," - DRE - " &'BASE C'!$C$2) -> Prestação de Serviço e Transpor. Escolar Gratuito - TEG n. 2022/0026751 - DRE - FB | AB6: =L6 -> #N/A
A7: 2022/0026934 | C7: =W7 -> 0 | D7: =VLOOKUP(A7,'APONTAMENTO CREDENCIAMENTO'!$D$6:$P$2821,12,0) -> #N/A | F7: =SUMIF('APONTAMENTO CREDENCIAMENTO'!$D$6:$D$2821,'ATESTE-LIQ'!A7,'APONTAMENTO CREDENCIAMENTO'!$FF$6:$FF$2821) -> 0 | G7: =VLOOKUP(A7,'APONTAMENTO CREDENCIAMENTO'!$D$6:$G$2821,3,0) -> #N/A | H7: =VLOOKUP(A7,'APONTAMENTO CREDENCIAMENTO'!$D$6:$G$2821,4,0) -> #N/A | I7: =CONCATENATE("PE - Pagto. Doc(s): ",E7," - Contrato nº ",A7) -> PE - Pagto. Doc(s): - Contrato nº 2022/0026934 | J7: =F7 -> 0 | K7: 0 | L7: =VLOOKUP(A7,'APONTAMENTO CREDENCIAMENTO'!$D$6:$P$2821,5,0) -> #N/A | T7: =D7 -> #N/A | U7: =F7 -> 0 | V7: =U7 -> 0 | AA7: =CONCATENATE("Prestação de Serviço e Transpor. Escolar Gratuito - TEG n. ",A7," - DRE - " &'BASE C'!$C$2) -> Prestação de Serviço e Transpor. Escolar Gratuito - TEG n. 2022/0026934 - DRE - FB | AB7: =L7 -> #N/A
A8: 2022/0027035 | C8: =W8 -> 0 | D8: =VLOOKUP(A8,'APONTAMENTO CREDENCIAMENTO'!$D$6:$P$2821,12,0) -> #N/A | F8: =SUMIF('APONTAMENTO CREDENCIAMENTO'!$D$6:$D$2821,'ATESTE-LIQ'!A8,'APONTAMENTO CREDENCIAMENTO'!$FF$6:$FF$2821) -> 0 | G8: =VLOOKUP(A8,'APONTAMENTO CREDENCIAMENTO'!$D$6:$G$2821,3,0) -> #N/A | H8: =VLOOKUP(A8,'APONTAMENTO CREDENCIAMENTO'!$D$6:$G$2821,4,0) -> #N/A | I8: =CONCATENATE("PE - Pagto. Doc(s): ",E8," - Contrato nº ",A8) -> PE - Pagto. Doc(s): - Contrato nº 2022/0027035 | J8: =F8 -> 0 | K8: 0 | L8: =VLOOKUP(A8,'APONTAMENTO CREDENCIAMENTO'!$D$6:$P$2821,5,0) -> #N/A | T8: =D8 -> #N/A | U8: =F8 -> 0 | V8: =U8 -> 0 | AA8: =CONCATENATE("Prestação de Serviço e Transpor. Escolar Gratuito - TEG n. ",A8," - DRE - " &'BASE C'!$C$2) -> Prestação de Serviço e Transpor. Escolar Gratuito - TEG n. 2022/0027035 - DRE - FB | AB8: =L8 -> #N/A
A9: 2022/0027240 | C9: =W9 -> 0 | D9: =VLOOKUP(A9,'APONTAMENTO CREDENCIAMENTO'!$D$6:$P$2821,12,0) -> #N/A | F9: =SUMIF('APONTAMENTO CREDENCIAMENTO'!$D$6:$D$2821,'ATESTE-LIQ'!A9,'APONTAMENTO CREDENCIAMENTO'!$FF$6:$FF$2821) -> 0 | G9: =VLOOKUP(A9,'APONTAMENTO CREDENCIAMENTO'!$D$6:$G$2821,3,0) -> #N/A | H9: =VLOOKUP(A9,'APONTAMENTO CREDENCIAMENTO'!$D$6:$G$2821,4,0) -> #N/A | I9: =CONCATENATE("PE - Pagto. Doc(s): ",E9," - Contrato nº ",A9) -> PE - Pagto. Doc(s): - Contrato nº 2022/0027240 | J9: =F9 -> 0 | K9: 0 | L9: =VLOOKUP(A9,'APONTAMENTO CREDENCIAMENTO'!$D$6:$P$2821,5,0) -> #N/A | T9: =D9 -> #N/A | U9: =F9 -> 0 | V9: =U9 -> 0 | AA9: =CONCATENATE("Prestação de Serviço e Transpor. Escolar Gratuito - TEG n. ",A9," - DRE - " &'BASE C'!$C$2) -> Prestação de Serviço e Transpor. Escolar Gratuito - TEG n. 2022/0027240 - DRE - FB | AB9: =L9 -> #N/A
A10: 2022/0027740 | C10: =W10 -> 0 | D10: =VLOOKUP(A10,'APONTAMENTO CREDENCIAMENTO'!$D$6:$P$2821,12,0) -> #N/A | F10: =SUMIF('APONTAMENTO CREDENCIAMENTO'!$D$6:$D$2821,'ATESTE-LIQ'!A10,'APONTAMENTO CREDENCIAMENTO'!$FF$6:$FF$2821) -> 0 | G10: =VLOOKUP(A10,'APONTAMENTO CREDENCIAMENTO'!$D$6:$G$2821,3,0) -> #N/A | H10: =VLOOKUP(A10,'APONTAMENTO CREDENCIAMENTO'!$D$6:$G$2821,4,0) -> #N/A | I10: =CONCATENATE("PE - Pagto. Doc(s): ",E10," - Contrato nº ",A10) -> PE - Pagto. Doc(s): - Contrato nº 2022/0027740 | J10: =F10 -> 0 | K10: 0 | L10: =VLOOKUP(A10,'APONTAMENTO CREDENCIAMENTO'!$D$6:$P$2821,5,0) -> #N/A | T10: =D10 -> #N/A | U10: =F10 -> 0 | V10: =U10 -> 0 | AA10: =CONCATENATE("Prestação de Serviço e Transpor. Escolar Gratuito - TEG n. ",A10," - DRE - " &'BASE C'!$C$2) -> Prestação de Serviço e Transpor. Escolar Gratuito - TEG n. 2022/0027740 - DRE - FB | AB10: =L10 -> #N/A
A11: 2022/0027919 | C11: =W11 -> 0 | D11: =VLOOKUP(A11,'APONTAMENTO CREDENCIAMENTO'!$D$6:$P$2821,12,0) -> #N/A | F11: =SUMIF('APONTAMENTO CREDENCIAMENTO'!$D$6:$D$2821,'ATESTE-LIQ'!A11,'APONTAMENTO CREDENCIAMENTO'!$FF$6:$FF$2821) -> 0 | G11: =VLOOKUP(A11,'APONTAMENTO CREDENCIAMENTO'!$D$6:$G$2821,3,0) -> #N/A | H11: =VLOOKUP(A11,'APONTAMENTO CREDENCIAMENTO'!$D$6:$G$2821,4,0) -> #N/A | I11: =CONCATENATE("PE - Pagto. Doc(s): ",E11," - Contrato nº ",A11) -> PE - Pagto. Doc(s): - Contrato nº 2022/0027919 | J11: =F11 -> 0 | K11: 0 | L11: =VLOOKUP(A11,'APONTAMENTO CREDENCIAMENTO'!$D$6:$P$2821,5,0) -> #N/A | T11: =D11 -> #N/A | U11: =F11 -> 0 | V11: =U11 -> 0 | AA11: =CONCATENATE("Prestação de Serviço e Transpor. Escolar Gratuito - TEG n. ",A11," - DRE - " &'BASE C'!$C$2) -> Prestação de Serviço e Transpor. Escolar Gratuito - TEG n. 2022/0027919 - DRE - FB | AB11: =L11 -> #N/A
A12: 2022/0028862 | C12: =W12 -> 0 | D12: =VLOOKUP(A12,'APONTAMENTO CREDENCIAMENTO'!$D$6:$P$2821,12,0) -> #N/A | F12: =SUMIF('APONTAMENTO CREDENCIAMENTO'!$D$6:$D$2821,'ATESTE-LIQ'!A12,'APONTAMENTO CREDENCIAMENTO'!$FF$6:$FF$2821) -> 0 | G12: =VLOOKUP(A12,'APONTAMENTO CREDENCIAMENTO'!$D$6:$G$2821,3,0) -> #N/A | H12: =VLOOKUP(A12,'APONTAMENTO CREDENCIAMENTO'!$D$6:$G$2821,4,0) -> #N/A | I12: =CONCATENATE("PE - Pagto. Doc(s): ",E12," - Contrato nº ",A12) -> PE - Pagto. Doc(s): - Contrato nº 2022/0028862 | J12: =F12 -> 0 | K12: 0 | L12: =VLOOKUP(A12,'APONTAMENTO CREDENCIAMENTO'!$D$6:$P$2821,5,0) -> #N/A | T12: =D12 -> #N/A | U12: =F12 -> 0 | V12: =U12 -> 0 | AA12: =CONCATENATE("Prestação de Serviço e Transpor. Escolar Gratuito - TEG n. ",A12," - DRE - " &'BASE C'!$C$2) -> Prestação de Serviço e Transpor. Escolar Gratuito - TEG n. 2022/0028862 - DRE - FB | AB12: =L12 -> #N/A
A13: 2022/0028892 | C13: =W13 -> 0 | D13: =VLOOKUP(A13,'APONTAMENTO CREDENCIAMENTO'!$D$6:$P$2821,12,0) -> #N/A | F13: =SUMIF('APONTAMENTO CREDENCIAMENTO'!$D$6:$D$2821,'ATESTE-LIQ'!A13,'APONTAMENTO CREDENCIAMENTO'!$FF$6:$FF$2821) -> 0 | G13: =VLOOKUP(A13,'APONTAMENTO CREDENCIAMENTO'!$D$6:$G$2821,3,0) -> #N/A | H13: =VLOOKUP(A13,'APONTAMENTO CREDENCIAMENTO'!$D$6:$G$2821,4,0) -> #N/A | I13: =CONCATENATE("PE - Pagto. Doc(s): ",E13," - Contrato nº ",A13) -> PE - Pagto. Doc(s): - Contrato nº 2022/0028892 | J13: =F13 -> 0 | K13: 0 | L13: =VLOOKUP(A13,'APONTAMENTO CREDENCIAMENTO'!$D$6:$P$2821,5,0) -> #N/A | T13: =D13 -> #N/A | U13: =F13 -> 0 | V13: =U13 -> 0 | AA13: =CONCATENATE("Prestação de Serviço e Transpor. Escolar Gratuito - TEG n. ",A13," - DRE - " &'BASE C'!$C$2) -> Prestação de Serviço e Transpor. Escolar Gratuito - TEG n. 2022/0028892 - DRE - FB | AB13: =L13 -> #N/A
... A94: 2026/0016071 | C94: =W94 -> 0 | D94: =VLOOKUP(A94,'APONTAMENTO CREDENCIAMENTO'!$D$6:$P$2821,12,0) -> #N/A | F94: =SUMIF('APONTAMENTO CREDENCIAMENTO'!$D$6:$D$2821,'ATESTE-LIQ'!A94,'APONTAMENTO CREDENCIAMENTO'!$FF$6:$FF$2821) -> 0 | G94: =VLOOKUP(A94,'APONTAMENTO CREDENCIAMENTO'!$D$6:$G$2821,3,0) -> #N/A | H94: =VLOOKUP(A94,'APONTAMENTO CREDENCIAMENTO'!$D$6:$G$2821,4,0) -> #N/A | I94: =CONCATENATE("PE - Pagto. Doc(s): ",E94," - Contrato nº ",A94) -> PE - Pagto. Doc(s): - Contrato nº 2026/0016071 | J94: =F94 -> 0 | K94: 0 | L94: =VLOOKUP(A94,'APONTAMENTO CREDENCIAMENTO'!$D$6:$P$2821,5,0) -> #N/A | T94: =D94 -> #N/A | U94: =F94 -> 0 | V94: =U94 -> 0 | AA94: =CONCATENATE("Prestação de Serviço e Transpor. Escolar Gratuito - TEG n. ",A94," - DRE - " &'BASE C'!$C$2) -> Prestação de Serviço e Transpor. Escolar Gratuito - TEG n. 2026/0016071 - DRE - FB | AB94: =L94 -> #N/A
F96: =SUM(F2:F95) -> 880.27038 | J96: =SUM(J2:J95) -> 880.27038

Sheet REVISAO
A1: pdf2 | B1: limpeza de variaveis com erro
A2: PDF3 | B2: mudança salar com wtemp
B3: mudança pasta gravacao pdf criando o subdiretorio da dre
B4: mudança verificando se deve gerar pdf
A6: pdf4 | B6: mudou sai para xlsx
A8: pdf5 | B8: muda a formula do contrato especial
B9: =especial/30 * (=SE(($G6-$F6)=($G$5-$F$5);30;($G6-$F6)+1))
A11: 45978 | B11: corrige erro - não encontrou apelido
A13: 01/dez/ processamento por pf e pj e colocar filtro na emissão de demonstrativo
A14: 45993 | B14: checagem antecipada se tem alguma planilha com problema ou não encontrada

Sheet Plan1

Sheet Cálculo IRRF -Jan.2026
B2: SUBSECRETARIA DO TESOURO MUNICIPAL DEPARTAMENTO DE CONTADORIA DIVISAO DE CONTABILIDADE DE RECEITAS E DE IMPOSTO DE RENDA
C5: PLANILHA PARA SIMULAÇÃO DE CÁLCULO DO IRRF
C6: VIGÊNCIA A PARTIR DE 1º DE JANEIRO/2026 | H6: Contrato
C8: São editáveis apenas os campos destacados em cinza | H8: ='BASE C'!B3 -> 2026/0016071
C10: Rendimentos tributáveis
C11: Pagamentos anteriores | D11: =VLOOKUP(H8,'ATESTE-LIQ-FIS'!A:D,4,0)*60% -> #N/A
C12: Pagamento da NLP atual
C13: Rendimentos tributáveis Acumulado¹ | D13: =SUM(D11:D12) -> #N/A
C15: ¹ O fato gerador do IR é o pagamento. O cálculo deve considerar os valores com base na previsão de pagamento dentro de um mesmo mês.
C17: Retenção anterior
C18: Valor(es) retido(s) em NLP(s) anterior(es)
C20: Informações para simulação do cálculo do IRRF
C22: Deduções Legais
C23: Previdência oficial | D23: =VLOOKUP(H8,'ATESTE-LIQ-FIS'!A:E,5,0) -> #N/A
C24: Dependentes (quantidade) | D24: 0
D25: =D24*189.59 -> 0
C26: Pensão alimentícia | D26: 0
C27: Outras Deduções Previdência Privada, Funpresp, FAPI e Parcela isenta de aposentadoria, reserva remunerada, reforma e pensão para declarante com 65 anos ou mais, caso não tenha sido deduzida dos rendimentos tributáveis. Carne-Leão: Livro Caixa. | D27: 0
C29: Desconto simplicado (Dedução 25% s/ 1ª Faixa) | D29: 607.2
C31: Por Deduções Legais | E31: Por Desconto Simplificado ²
C32: Valor da retencão acumulada | D32: ='IR Deduções Legais-Maio.2025'!F30 -> #N/A | E32: Valor da retencão acumulada | F32: ='IR Desc. Simplificado-Maio.2025'!F30 -> #N/A
C33: Valor a reter na NLP atual | D33: =D32-D18 -> #N/A | E33: Valor a reter na NLP atual | F33: =F32-D18 -> #N/A
C35: Melhor opção para o IRRF
C36: =IF(D32<F32,"Deduções Legais","Desconto Simplificado") -> #N/A | D36: =TRUNC(SMALL(D32:F32,1),2) -> #N/A
C37: Valor a reter na NLP atual | D37: =TRUNC(IF(F32<=D32,F33,D33),2) -> #N/A
C39: Observações:
C41: • A apuração do imposto é realizada com base na opção entre as deduções legais ou o desconto simplificado, adotando-se a alternativa mais vantajosa ao contribuinte.
C42: • O cálculo já contempla a isenção e a redução do Imposto de Renda estabelecidas na Lei nº 15.270, de 26 de novembro de 2025.
C44: RENDIMENTOS TRIBUTÁVEIS SUJEITOS AO AJUSTE MENSAL | E44: REDUÇÃO DO IMPOSTO DE RENDA
C45: De | D45: Até | E45: Regra
C46: 0 | D46: 5000 | E46: até R$ 312,89 (de modo que o imposto devido seja zero)
C47: 5000.01 | D47: 7350 | E47: R$ 978,62 - (0,133145 x rendimentos tributáveis sujeitos à incidência mensal) (de modo que a redução do imposto seja decrescente linearmente até zerar para rendimentos a partir de R$ 7.350,00)
C48: Vigente a partir do mês de janeiro do ano-calendário de 2026. Lei nº 15.270, de 26 de novembro de 2025
C50: Acima de R$ 7.350,00 não haverá redução no imposto devido.
C52: Tabela Progressiva
C53: Base de Cálculo (R$) | D53: Alíquota (%) | E53: Parcela a Deduzir do IR (R$)
C54: Até 2.428,80 | D54: 0 | E54: 0
C55: De 2.428,81 até 2.826,65 | D55: 7.5 | E55: 182.16
C56: De 2.826,66 até 3.751,05 | D56: 15 | E56: 394.16
C57: De 3.751,06 até 4.664,68 | D57: 22.5 | E57: 675.49
C58: Acima de 4.664,68 | D58: 27.5 | E58: 908.73
C59: Vigente a partir do mês de maio do ano-calendário de 2025 (Lei nº 11.482, de 31 de maio de 2007)

Sheet IR Deduções Legais-Maio.2025
B2: Base Contribuição Previdenciária:
B3: ='Cálculo IRRF -Jan.2026'!D13 -> #N/A
B10: Total de Contribuição | F10: ='Cálculo IRRF -Jan.2026'!D23 -> #N/A
B13: Base Imposto de Renda
B14: Quantidade de Dependentes | E14: ='Cálculo IRRF -Jan.2026'!D24 -> 0
B15: Dedução por dependente | E15: 189.59 | H15: Total das Deduções: | I15: =F10+I17+I18+(E14*E15) -> #N/A
B16: Valor da Base | E16: =B3-I17-I18-F10-(E14*E15) -> #N/A
H17: Pensão | I17: ='Cálculo IRRF -Jan.2026'!D26 -> 0
B18: Inicial | C18: Final | D18: Alíquota | E18: Dedução | F18: Valor | H18: Outras Deduções | I18: ='Cálculo IRRF -Jan.2026'!D27 -> 0
B19: 0 | C19: 2428.8 | D19: 0 | E19: 0 | F19: 0
B20: 2428.81 | C20: 2826.65 | D20: 0.075 | E20: 182.16 | F20: =TRUNC(IF(AND($E$16>B20,$E$16<C20),$E$16*D20-E20,0),2) -> #N/A
B21: 2826.66 | C21: 3751.05 | D21: 0.15 | E21: 394.16 | F21: =TRUNC(IF(AND($E$16>B21,$E$16<C21),$E$16*D21-E21,0),2) -> #N/A
B22: 3751.06 | C22: 4664.68 | D22: 0.225 | E22: 675.49 | F22: =TRUNC(IF(AND($E$16>B22,$E$16<C22),$E$16*D22-E22,0),2) -> #N/A
B23: 4664.69 | C23: 9999999 | D23: 0.275 | E23: 908.73 | F23: =TRUNC(IF(AND($E$16>B23,$E$16<C23),$E$16*D23-E23,0),2) -> #N/A
B24: Total Desconto de IR | F24: =SUM(F19:F23) -> #N/A
B26: Calculo considerando a regra de Isenção até R$ 5.000,00 | F26: =IF(B3<=C50,0,F24) -> #N/A
B28: Calculo do imposto considerando a redução sobre rendimentos tributaveis entre R$ 5.000,01 e R$ 7.350,00 | F28: =IF(AND($B$3>C50,$B$3<=C51),F24-E39,IF($B$3<=C50,F26,F24)) -> #N/A
B30: Valor do IR apurado a ser retido considerando isenção e redução | F30: =MIN(F24,F26,F28) -> #N/A
B32: CÁLCULO REDUÇÃO DE IR
B34: Rendimento tributavel acumulado | C34: =IF(B3>7350,7350,B3) -> #N/A
B35: Fator Multiplicador do Rendimento Tributável | C35: 0.133145
B36: Valor Fixo de redução | C36: 978.62
B38: Valor Fixo de redução | C38: rendimentos tributáveis sujeitos à incidência mensal (bruto) | D38: Fator Multiplicador | E38: Valor da reduçao
B39: 978.62 | C39: =C34 -> #N/A | D39: 0.133145 | E39: =TRUNC(B39-(C39*D39),2) -> #N/A
B42: Valor do IR aplicando a tabela progressiva | C42: =F24 -> #N/A
B43: Valor da reduçao do IR | C43: =E39 -> #N/A
B44: Valor da retençao do IR acumulada Faixa de redução R$ 5.000,01 a R$ 7.350,00 | C44: =C42-C43 -> #N/A
B47: LEI Nº 15.270, DE 26 DE NOVEMBRO DE 2025
B48: RENDIMENTOS TRIBUTÁVEIS SUJEITOS AO AJUSTE MENSAL | D48: REDUÇÃO DO IMPOSTO DE RENDA
B49: De | C49: Até | D49: Regra
B50: 0 | C50: 5000 | D50: até R$ 312,89 (de modo que o imposto devido seja zero)
B51: 5000.01 | C51: 7350 | D51: R$ 978,62 - (0,133145 x rendimentos tributáveis sujeitos à incidência mensal) (de modo que a redução do imposto seja decrescente linearmente até zerar para rendimentos a partir de R$ 7.350,00)

Sheet IR Desc. Simplificado-Maio.2025
B2: Base Contribuição Previdenciária:
B3: ='Cálculo IRRF -Jan.2026'!D13 -> #N/A
B10: Total de Contribuição | F10: ='Cálculo IRRF -Jan.2026'!D23 -> #N/A
B13: Base Imposto de Renda (MODO SIMPLIFICADO)
B14: Remuneração | E14: =B3 -> #N/A
B15: Dedução 25% s/ 1ª Faixa | E15: 607.2
B16: Valor da Base | E16: ='Cálculo IRRF -Jan.2026'!D13-'Cálculo IRRF -Jan.2026'!D29 -> #N/A
B18: Inicial | C18: Final | D18: Alíquota | E18: Dedução | F18: Valor
B19: 0 | C19: 2428.8 | D19: 0 | E19: 0 | F19: 0
B20: 2428.81 | C20: 2826.65 | D20: 0.075 | E20: 182.16 | F20: =IF(AND($E$16>B20,$E$16<C20),TRUNC($E$16*D20,2)-E20,0) -> #N/A
B21: 2826.66 | C21: 3751.05 | D21: 0.15 | E21: 394.16 | F21: =IF(AND($E$16>B21,$E$16<C21),TRUNC($E$16*D21,2)-E21,0) -> #N/A
B22: 3751.06 | C22: 4664.68 | D22: 0.225 | E22: 675.49 | F22: =IF(AND($E$16>B22,$E$16<C22),TRUNC($E$16*D22,2)-E22,0) -> #N/A
B23: 4664.69 | C23: 9999999 | D23: 0.275 | E23: 908.73 | F23: =IF(AND($E$16>B23,$E$16<C23),TRUNC($E$16*D23,2)-E23,0) -> #N/A
B24: Total Desconto de IR | F24: =SUM(F19:F23) -> #N/A
B26: Calculo considerando a regra de Isenção até R$ 5.000,00 | F26: =IF($B$3<=$C$50,0,$F$24) -> #N/A
B28: Calculo do imposto considerando a redução sobre rendimentos tributaveis entre R$ 5.000,01 e R$ 7.350,00 | F28: =IF(AND($B$3>C50,$B$3<=C51),F24-E39,IF($B$3<=C50,F26,F24)) -> #N/A
B30: Valor do IR apurado a ser retido considerando isenção e redução | F30: =MIN(F24,F26,F28) -> #N/A
B32: CÁLCULO REDUÇÃO DE IR
B34: Rendimento tributavel acumulado | C34: =IF($B$3>7350,7350,$B$3) -> #N/A
B35: Fator Multiplicador do Rendimento Tributável | C35: 0.133145
B36: Valor Fixo de redução | C36: 978.62
B38: Valor Fixo de redução | C38: rendimentos tributáveis sujeitos à incidência mensal (bruto) | D38: Fator Multiplicador | E38: Valor da reduçao
B39: 978.62 | C39: =$B$3 -> #N/A | D39: 0.133145 | E39: =TRUNC($B$39-($C$39*$D$39),2) -> #N/A
B42: Valor do IR aplicando a tabela progressiva | C42: =$F$24 -> #N/A
B43: Valor da reduçao do IR | C43: =$E$39 -> #N/A
B44: Valor da retençao do IR acumulada Faixa de redução R$ 5.000,01 a R$ 7.350,00 | C44: =$C$42-$C$43 -> #N/A
B47: LEI Nº 15.270, DE 26 DE NOVEMBRO DE 2025
B48: RENDIMENTOS TRIBUTÁVEIS SUJEITOS AO AJUSTE MENSAL | D48: REDUÇÃO DO IMPOSTO DE RENDA
B49: De | C49: Até | D49: Regra
B50: 0 | C50: 5000 | D50: até R$ 312,89 (de modo que o imposto devido seja zero)
B51: 5000.01 | C51: 7350 | D51: R$ 978,62 - (0,133145 x rendimentos tributáveis sujeitos à incidência mensal) (de modo que a redução do imposto seja decrescente linearmente até zerar para rendimentos a partir de R$ 7.350,00)
