Workbook
Name \a: #REF!
Name \a: #REF!
Name \p: #REF!
Name \p: #REF!
Name _______xlnm.Print_Titles: #REF!
Name _______xlnm_Print_Titles: NA()
Name ______xlnm._FilterDatabase: "#ref!"
Name ______xlnm.Print_Titles: #REF!
Name ______xlnm__FilterDatabase: "#ref!"
Name ______xlnm_Print_Titles: NA()
Name _____xlfn_BAHTTEXT: NA()
Name _____xlfn_SUMIFS: NA()
Name _____xlnm._FilterDatabase: "#ref!"
Name _____xlnm.Print_Titles: #REF!
Name _____xlnm__FilterDatabase: "#ref!"
Name _____xlnm_Print_Titles: NA()
Name ____xlfn_BAHTTEXT: NA()
Name ____xlfn_SUMIFS: NA()
Name ____xlnm._FilterDatabase: "#ref!"
Name ____xlnm.Print_Titles: #REF!
Name ____xlnm__FilterDatabase: "#ref!"
Name ____xlnm_Print_Titles: NA()
Name ___xlfn_BAHTTEXT: NA()
Name ___xlfn_SUMIFS: NA()
Name ___xlnm._FilterDatabase: "#ref!"
Name ___xlnm.Print_Titles: #REF!
Name ___xlnm__FilterDatabase: "#ref!"
Name ___xlnm_Print_Titles: NA()
Name __TAB3688: #REF!
Name __xlfn_BAHTTEXT: NA()
Name __xlfn_SUMIFS: NA()
Name __xlnm._FilterDatabase: "#ref!"
Name __xlnm.Print_Titles: #REF!
Name __xlnm__FilterDatabase: "#ref!"
Name __xlnm_Print_Titles: NA()
Name _TAB3688: #REF!
Name _TAB3688: #REF!
Name a: #REF!
Name abr: #REF!
Name abr: #REF!
Name abril: #REF!
Name ACRESCENTAR: #REF!
Name ADAPTADO: '[1]APONTAMENTO CREDENCIAMENTO'!#REF!
Name ADAPTADO: 'APONTAMENTO CREDENCIAMENTO'!$FF$7:$GJ$7
Name AGOSTO: #REF!
Name AI: #REF!
Name AI: #REF!
Name AII: #REF!
Name AII: #REF!
Name AK: #REF!
Name AK: #REF!
Name AL: #REF!
Name AL: #REF!
Name AMPLIAR: #REF!
Name AMPLIAR: #REF!
Name ApagaAtesteFis: 'ATESTE-LIQ-FIS'!$A$4:$K$3908
Name ApagaBaseC: 'BASE C'!$A$11:$N$4950
Name ApagaDadosA: 'APONTAMENTO CREDENCIAMENTO'!$Q$6:$EL$3994
Name ApagaDadosC: CONTINUA!$L$6:$BU$4012
Name ApagarDadosDigitados: #REF!

Sheet APONTAMENTO CREDENCIAMENTO
A1: Butantã | G1: ='BASE C'!E4 -> ABRIL | I1: APONTAMENTO CREDENCIAMENTO | EL1: ATENÇÃO
G2: 01/06 a 30/06/2025
A3: 1 | B3: =A3+1 -> 2 | C3: =B3+1 -> 3 | D3: 1 | E3: =D3+1 -> 2 | F3: =E3+1 -> 3 | G3: =F3+1 -> 4 | H3: =G3+1 -> 5 | I3: =H3+1 -> 6 | J3: =I3+1 -> 7 | K3: =J3+1 -> 8 | L3: =K3+1 -> 9 | M3: =L3+1 -> 10 | N3: 10 | O3: =N3+1 -> 11 | P3: 13 | Q3: =P3+1 -> 14 | R3: =Q3+1 -> 15 | S3: =R3+1 -> 16 | T3: =S3+1 -> 17 | U3: =T3+1 -> 18 | V3: =U3+1 -> 19 | W3: =V3+1 -> 20 | X3: =W3+1 -> 21 | ... EL3: =EK3+1 -> 139 | EM3: 140 | EN3: =EM3+1 -> 141 | EO3: =EN3+1 -> 142 | EP3: =EO3+1 -> 143 | EQ3: =EP3+1 -> 144 | ER3: =EQ3+1 -> 145 | ES3: =ER3+1 -> 146 | ET3: =ES3+1 -> 147 | EU3: =ET3+1 -> 148 | ... IA3: =HZ3+1 -> 232
A4: CRMC | B4: OS | C4: DRE | D4: CONTRATO | E4: PLACA | F4: PERÍODO | H4: EMPRESA | I4: NOME CONDUTOR | J4: TIPO DE VEÍCULO (NORMAL, ADAPTADO) | K4: TIPO DE ATENDIMENTO | L4: TOTAL CONT REG | M4: TOTAL CONT CAD | N4: KM ADICIONAL | O4: SEI | P4: Tipo Optante | Q4: =F5 -> 01/04/2026 | U4: =Q4+1 -> 46114 | Y4: =U4+1 -> 46115 | AC4: =Y4+1 -> 46116 | AG4: =AC4+1 -> 46117 | AK4: =AG4+1 -> 46118 | AO4: =AK4+1 -> 46119 | AS4: =AO4+1 -> 46120 | AW4: =AS4+1 -> 46121 | BA4: =AW4+1 -> 46122 | BE4: =BA4+1 -> 46123 | BI4: =BE4+1 -> 46124 | BM4: =BI4+1 -> 46125 | BQ4: =BM4+1 -> 46126 | BU4: =BQ4+1 -> 46127 | BY4: =BU4+1 -> 46128 | CC4: =BY4+1 -> 46129 | CG4: =CC4+1 -> 46130 | CK4: =CG4+1 -> 46131 | CO4: =CK4+1 -> 46132 | CS4: =CO4+1 -> 46133 | CW4: =CS4+1 -> 46134 | DA4: =CW4+1 -> 46135 | DE4: =DA4+1 -> 46136 | DI4: =DE4+1 -> 46137 | DM4: =DI4+1 -> 46138 | DQ4: =DM4+1 -> 46139 | DU4: =DQ4+1 -> 46140 | DY4: =DU4+1 -> 46141 | EC4: =DY4+1 -> 46142 | EK4: FALTAS - APONTAR AS DATAS | EL4: OBSERVAÇÕES ALUNO PRESENCIAL COLUNAS FINAIS | EM4: Ajuste positivo | EN4: Ajuste negativo | EO4: Desconto faltas | EP4: TOTAL ALUNOS N CAD(30 DIAS) | EQ4: TOTAL ALUNOS N CAD(MENOS DE 30 DIAS) | ER4: TOTAL ALUNOS ATIV.COMPL. N CAD | ES4: TOTAL ALUNOS CAD (30 DIAS) | ET4: TOTAL ALUNOS CAD (MENOS DE 30 DIAS) | EU4: TOTAL ALUNOS ATIV.COMPL. CAD | EV4: TOTAL GERAL | EW4: Contratos Especiais (Valor fixo) | EX4: Valor total alunos presenciais (30 dias) | EY4: Ativ.Complementar Continuada | EZ4: Valor alunos presenciais (menos de 30 dias) | FA4: Saida de alunos ao longo do mês | FB4: CCA | FC4: Valor km adicional | FD4: Outros apontamentos | FE4: VALOR ATESTE | FF4: 30 | FG4: =FF4-1 -> 29 | FH4: =FG4-1 -> 28 | FI4: =FH4-1 -> 27 | FJ4: =FI4-1 -> 26 | FK4: =FJ4-1 -> 25 | FL4: =FK4-1 -> 24 | FM4: =FL4-1 -> 23 | FN4: =FM4-1 -> 22 | ... GI4: =GH4-1 -> 1 | GJ4: 1 | GK4: Multa Contratual | GL4: CÁLCULO | GM4: DIAS | GN4: 29 | GO4: =GN4-1 -> 28 | GP4: =GO4-1 -> 27 | GQ4: =GP4-1 -> 26 | GR4: =GQ4-1 -> 25 | GS4: =GR4-1 -> 24 | GT4: =GS4-1 -> 23 | GU4: =GT4-1 -> 22 | GV4: =GU4-1 -> 21 | ... HP4: =HO4-1 -> 1 | HW4: VALOR ATESTE | HY4: Ajuste positivo | HZ4: Ajuste negativo | IA4: Desconto faltas
F5: 01/04/2026 | G5: 30/04/2026 | Q5: N CAD presencial | R5: CAD | S5: AT. COMPL. N CAD | T5: AT. COMPL. CAD | U5: N CAD presencial | V5: CAD | W5: AT. COMPL. N CAD | X5: AT. COMPL. CAD | Y5: N CAD presencial | Z5: CAD | AA5: AT. COMPL. N CAD | AB5: AT. COMPL. CAD | AC5: N CAD presencial | AD5: CAD | AE5: AT. COMPL. N CAD | AF5: AT. COMPL. CAD | AG5: N CAD presencial | AH5: CAD | AI5: AT. COMPL. N CAD | AJ5: AT. COMPL. CAD | AK5: N CAD presencial | AL5: CAD | AM5: AT. COMPL. N CAD | AN5: AT. COMPL. CAD | AO5: N CAD presencial | AP5: CAD | AQ5: AT. COMPL. N CAD | AR5: AT. COMPL. CAD | AS5: N CAD presencial | AT5: CAD | AU5: AT. COMPL. N CAD | AV5: AT. COMPL. CAD | AW5: N CAD presencial | AX5: CAD | AY5: AT. COMPL. N CAD | AZ5: AT. COMPL. CAD | BA5: N CAD presencial | BB5: CAD | BC5: AT. COMPL. N CAD | BD5: AT. COMPL. CAD | BE5: N CAD presencial | BF5: CAD | BG5: AT. COMPL. N CAD | BH5: AT. COMPL. CAD | BI5: N CAD presencial | BJ5: CAD | BK5: AT. COMPL. N CAD | BL5: AT. COMPL. CAD | BM5: N CAD presencial | BN5: CAD | BO5: AT. COMPL. N CAD | BP5: AT. COMPL. CAD | BQ5: N CAD presencial | BR5: CAD | BS5: AT. COMPL. N CAD | BT5: AT. COMPL. CAD | BU5: N CAD presencial | BV5: CAD | BW5: AT. COMPL. N CAD | BX5: AT. COMPL. CAD | BY5: N CAD presencial | BZ5: CAD | CA5: AT. COMPL. N CAD | CB5: AT. COMPL. CAD | CC5: N CAD presencial | CD5: CAD | CE5: AT. COMPL. N CAD | CF5: AT. COMPL. CAD | CG5: N CAD presencial | CH5: CAD | CI5: AT. COMPL. N CAD | CJ5: AT. COMPL. CAD | CK5: N CAD presencial | CL5: CAD | CM5: AT. COMPL. N CAD | CN5: AT. COMPL. CAD | CO5: N CAD presencial | CP5: CAD | CQ5: AT. COMPL. N CAD | CR5: AT. COMPL. CAD | CS5: N CAD presencial | CT5: CAD | CU5: AT. COMPL. N CAD | CV5: AT. COMPL. CAD | CW5: N CAD presencial | CX5: CAD | CY5: AT. COMPL. N CAD | CZ5: AT. COMPL. CAD | DA5: N CAD presencial | DB5: CAD | DC5: AT. COMPL. N CAD | DD5: AT. COMPL. CAD | DE5: N CAD presencial | DF5: CAD | DG5: AT. COMPL. N CAD | DH5: AT. COMPL. CAD | DI5: N CAD presencial | DJ5: CAD | DK5: AT. COMPL. N CAD | DL5: AT. COMPL. CAD | DM5: N CAD presencial | DN5: CAD | DO5: AT. COMPL. N CAD | DP5: AT. COMPL. CAD | DQ5: N CAD presencial | DR5: CAD | DS5: AT. COMPL. N CAD | DT5: AT. COMPL. CAD | DU5: N CAD presencial | DV5: CAD | DW5: AT. COMPL. N CAD | DX5: AT. COMPL. CAD | DY5: N CAD presencial | DZ5: CAD | EA5: AT. COMPL. N CAD | EB5: AT. COMPL. CAD | EC5: N CAD presencial | ED5: CAD | EE5: AT. COMPL. N CAD | EF5: AT. COMPL. CAD | EG5: N CAD presencial | EH5: CAD | EI5: AT. COMPL. N CAD | EJ5: AT. COMPL. CAD
A6: 028.293-00 | B6: 2024/0058910-001 | C6: 1 | D6: 2024/0058910 | E6: EFV2108 | F6: 01/04/2026 | G6: 30/04/2026 | H6: A.C.G. TRANSPORTE ESCOLAR LTDA | I6: ANDREIA PEREIRA DA SILVA | J6: NORMAL | K6: EMEI | L6: =CONTINUA!BV6 -> 0 | M6: =CONTINUA!BW6 -> 0 | O6: 6020.2024/0058910-3 | P6: O | EP6: =Q6 -> 0 | EQ6: =U6+Y6+AC6+AG6+AK6+AO6+AS6+AW6+BA6+BE6+BI6+BM6+BQ6+BU6+BY6+CC6+CG6+CK6+CO6+CS6+CW6+DA6+DE6+DI6+DM6+DQ6+DU6+DY6+EC6+EG6 -> 0 | ER6: =S6+W6+AA6+AE6+AI6+AM6+AQ6+AU6+AY6+BC6+BG6+BK6+BO6+BS6+BW6+CA6+CE6+CI6+CM6+CQ6+CU6+CY6+DC6+DG6+DK6+DO6+DS6+DW6+EA6+EE6+EI6 -> 0 | ES6: =R6 -> 0 | ET6: =V6+Z6+AD6+AH6+AL6+AP6+AT6+AX6+BB6+BF6+BJ6+BN6+BR6+BV6+BZ6+CD6+CH6+CL6+CP6+CT6+CX6+DB6+DF6+DJ6+DN6+DR6+DV6+DZ6+ED6+EH6 -> 0 | EU6: =T6+X6+AB6+AF6+AJ6+AN6+AR6+AV6+AZ6+BD6+BH6+BL6+BP6+BT6+BX6+CB6+CF6+CJ6+CN6+CR6+CV6+CZ6+DD6+DH6+DL6+DP6+DT6+DX6+EB6+EF6+EJ6 -> 0 | EV6: =EP6+EQ6+ES6+ET6+ER6+EU6 -> 0 | EW6: =IF(C6=4,IF(MAX(Q6:EJ8)>0,(Especiall/30*(IF(($G6-$F6)=($G$5-$F$5),30,IF(DAY($G6)=31,($G6-$F6),($G6-$F6)+1)))),0),0) -> 0 | EX6: =FF6 -> 20205.11 | EY6: =(L6*regular)+(M6*Cadeirantee) -> 0 | EZ6: =SUMIF(FG6:GJ6,">0") -> 295.343 | FA6: =SUMIF(FG6:GJ6,"<0")+SUMIF(GN6:HP6,"<0") -> 0 | FB6: 0 | FC6: =N6*km*'VALORES TABELA'!$B$13 -> 0 | FD6: =GL6 -> 0 | FE6: =(EW6+EW7+EW8+EW9+EX6+EX7+EX8+EX9+EY6+EY7+EY8+EY9+EY10+EZ6+EZ7+EZ8+EZ9+FA6+FA7+FA8+FA9+FC6+FC7+FC8+FC9+HY6-HZ6-IA6+FD6+FD7+FD8+FD9+FB10) -> 20943.893 | FF6: =IF(C6=4,SUM(Q6+Q7+Q8+S6+S7+S8)*Percapita/30*FF$4+(R6+R7+R8+T6+T7+T8)*Cadeirante/30*FF$4,IF(C6=3,IF(Q9+S9=10,Fixo/30*FF$4+(Q6+Q7+Q8+S6+S7+S8)*Percapita/30*FF$4+(R9+T9)*Cadeirante/30*FF$4,IF(Q9+S9<=9,(Q9+S9)*Crechee/30*FF$4)+(R9+T9)*Cadeirante/30*FF$4+(Q6+Q7+Q8+S6+S7+S8)*Percapita/30*FF$4)+IF(Q9+S9>=11,Fixo/30*FF$4+(Q9+S9-10)*Crechee/30*FF$4,0),IF(C6=2,IF(R6+R7+R8+R9+T6+T7+T8+T9=1,Cadeirante/30*FF$4,IF(R6+R7+R8+R9+T6+T7+T8+T9=2,Fixo/30*FF$4,IF(R6+R7+R8+R9+T6+T7+T8+T9>2,Fixo/30*FF$4+(R6+R7+R8+R9+T6+T7+T8+T9-2)*Cadeirante/30*FF$4)))+(Q6+Q7+Q8+S6+S7+S8)*Percapita/30*FF$4+(Q9+S9)*Crechee/30*FF$4,IF(C6=1,IF(Q6+Q7+Q8+R6+R7+R8+S6+S7+S8+T6+T7+T8<=15,(Q6+Q7+Q8+S6+S7+S8)*Percapita/30*FF$4,IF(Q6+Q7+Q8+R6+R7+R8+S6+S7+S8+T6+T7+T8>=16,Fixo/30*FF$4+(Q6+Q7+Q8+R6+R7+R8+S6+S7+S8+T6+T7-16)*Percapita/30*FF$4)))))) -> 20205.11 | FG6: =IF(C6=4,SUM(U6+U7+U8+W6+W7+W8)*Percapita/30*FG$4+(V6+V7+V8+X6+X7+X8)*Cadeirante/30*FG$4,IF(C6=3,IF(U9+W9=10,Fixo/30*FG$4+(U6+U7+U8+W6+W7+W8)*Percapita/30*FG$4+(V9+X9)*Cadeirante/30*FG$4,IF(U9+W9<=9,(U9+W9)*Crechee/30*FG$4)+(V9+X9)*Cadeirante/30*FG$4+(U6+U7+U8+W6+W7+W8)*Percapita/30*FG$4)+IF(U9+W9>=11,Fixo/30*FG$4+(U9+W9-10)*Crechee/30*FG$4,0),IF(C6=2,IF(V6+V7+V8+V9+X6+X7+X8+X9=1,Cadeirante/30*FG$4,IF(V6+V7+V8+V9+X6+X7+X8+X9=2,Fixo/30*FG$4,IF(V6+V7+V8+V9+X6+X7+X8+X9>2,Fixo/30*FG$4+(V6+V7+V8+V9+X6+X7+X8+X9-2)*Cadeirante/30*FG$4)))+(U6+U7+U8+W6+W7+W8)*Percapita/30*FG$4+(U9+W9)*Crechee/30*FG$4,IF(C6=1,IF(U6+U7+U8+V6+V7+V8+W6+W7+W8+X6+X7+X8<=15,(U6+U7+U8+W6+W7+W8)*Percapita/30*FG$4,IF(U6+U7+U8+V6+V7+V8+W6+W7+W8+X6+X7+X8>=16,Fixo/30*FG$4+(U6+U7+U8+V6+V7+V8+W6+W7+W8+X6+X7-16)*Percapita/30*FG$4)))))) -> 0 | FH6: =IF(C6=4,SUM(Y6+Y7+Y8+AA6+AA7+AA8)*Percapita/30*FH$4+(Z6+Z7+Z8+AB6+AB7+AB8)*Cadeirante/30*FH$4,IF(C6=3,IF(Y9+AA9=10,Fixo/30*FH$4+(Y6+Y7+Y8+AA6+AA7+AA8)*Percapita/30*FH$4+(Z9+AB9)*Cadeirante/30*FH$4,IF(Y9+AA9<=9,(Y9+AA9)*Crechee/30*FH$4)+(Z9+AB9)*Cadeirante/30*FH$4+(Y6+Y7+Y8+AA6+AA7+AA8)*Percapita/30*FH$4)+IF(Y9+AA9>=11,Fixo/30*FH$4+(Y9+AA9-10)*Crechee/30*FH$4,0),IF(C6=2,IF(Z6+Z7+Z8+Z9+AB6+AB7+AB8+AB9=1,Cadeirante/30*FH$4,IF(Z6+Z7+Z8+Z9+AB6+AB7+AB8+AB9=2,Fixo/30*FH$4,IF(Z6+Z7+Z8+Z9+AB6+AB7+AB8+AB9>2,Fixo/30*FH$4+(Z6+Z7+Z8+Z9+AB6+AB7+AB8+AB9-2)*Cadeirante/30*FH$4)))+(Y6+Y7+Y8+AA6+AA7+AA8)*Percapita/30*FH$4+(Y9+AA9)*Crechee/30*FH$4,IF(C6=1,IF(Y6+Y7+Y8+Z6+Z7+Z8+AA6+AA7+AA8+AB6+AB7+AB8<=15,(Y6+Y7+Y8+AA6+AA7+AA8)*Percapita/30*FH$4,IF(Y6+Y7+Y8+Z6+Z7+Z8+AA6+AA7+AA8+AB6+AB7+AB8>=16,Fixo/30*FH$4+(Y6+Y7+Y8+Z6+Z7+Z8+AA6+AA7+AA8+AB6+AB7-16)*Percapita/30*FH$4)))))) -> 0 | FI6: =IF(C6=4,SUM(AC6+AC7+AC8+AE6+AE7+AE8)*Percapita/30*FI$4+(AD6+AD7+AD8+AF6+AF7+AF8)*Cadeirante/30*FI$4,IF(C6=3,IF(AC9+AE9=10,Fixo/30*FI$4+(AC6+AC7+AC8+AE6+AE7+AE8)*Percapita/30*FI$4+(AD9+AF9)*Cadeirante/30*FI$4,IF(AC9+AE9<=9,(AC9+AE9)*Crechee/30*FI$4)+(AD9+AF9)*Cadeirante/30*FI$4+(AC6+AC7+AC8+AE6+AE7+AE8)*Percapita/30*FI$4)+IF(AC9+AE9>=11,Fixo/30*FI$4+(AC9+AE9-10)*Crechee/30*FI$4,0),IF(C6=2,IF(AD6+AD7+AD8+AD9+AF6+AF7+AF8+AF9=1,Cadeirante/30*FI$4,IF(AD6+AD7+AD8+AD9+AF6+AF7+AF8+AF9=2,Fixo/30*FI$4,IF(AD6+AD7+AD8+AD9+AF6+AF7+AF8+AF9>2,Fixo/30*FI$4+(AD6+AD7+AD8+AD9+AF6+AF7+AF8+AF9-2)*Cadeirante/30*FI$4)))+(AC6+AC7+AC8+AE6+AE7+AE8)*Percapita/30*FI$4+(AC9+AE9)*Crechee/30*FI$4,IF(C6=1,IF(AC6+AC7+AC8+AD6+AD7+AD8+AE6+AE7+AE8+AF6+AF7+AF8<=15,(AC6+AC7+AC8+AE6+AE7+AE8)*Percapita/30*FI$4,IF(AC6+AC7+AC8+AD6+AD7+AD8+AE6+AE7+AE8+AF6+AF7+AF8>=16,Fixo/30*FI$4+(AC6+AC7+AC8+AD6+AD7+AD8+AE6+AE7+AE8+AF6+AF7-16)*Percapita/30*FI$4)))))) -> 0 | FJ6: =IF(C6=4,SUM(AG6+AG7+AG8+AI6+AI7+AI8)*Percapita/30*FJ$4+(AH6+AH7+AH8+AJ6+AJ7+AJ8)*Cadeirante/30*FJ$4,IF(C6=3,IF(AG9+AI9=10,Fixo/30*FJ$4+(AG6+AG7+AG8+AI6+AI7+AI8)*Percapita/30*FJ$4+(AH9+AJ9)*Cadeirante/30*FJ$4,IF(AG9+AI9<=9,(AG9+AI9)*Crechee/30*FJ$4)+(AH9+AJ9)*Cadeirante/30*FJ$4+(AG6+AG7+AG8+AI6+AI7+AI8)*Percapita/30*FJ$4)+IF(AG9+AI9>=11,Fixo/30*FJ$4+(AG9+AI9-10)*Crechee/30*FJ$4,0),IF(C6=2,IF(AH6+AH7+AH8+AH9+AJ6+AJ7+AJ8+AJ9=1,Cadeirante/30*FJ$4,IF(AH6+AH7+AH8+AH9+AJ6+AJ7+AJ8+AJ9=2,Fixo/30*FJ$4,IF(AH6+AH7+AH8+AH9+AJ6+AJ7+AJ8+AJ9>2,Fixo/30*FJ$4+(AH6+AH7+AH8+AH9+AJ6+AJ7+AJ8+AJ9-2)*Cadeirante/30*FJ$4)))+(AG6+AG7+AG8+AI6+AI7+AI8)*Percapita/30*FJ$4+(AG9+AI9)*Crechee/30*FJ$4,IF(C6=1,IF(AG6+AG7+AG8+AH6+AH7+AH8+AI6+AI7+AI8+AJ6+AJ7+AJ8<=15,(AG6+AG7+AG8+AI6+AI7+AI8)*Percapita/30*FJ$4,IF(AG6+AG7+AG8+AH6+AH7+AH8+AI6+AI7+AI8+AJ6+AJ7+AJ8>=16,Fixo/30*FJ$4+(AG6+AG7+AG8+AH6+AH7+AH8+AI6+AI7+AI8+AJ6+AJ7-16)*Percapita/30*FJ$4)))))) -> 0 | FK6: =IF(C6=4,SUM(AK6+AK7+AK8+AM6+AM7+AM8)*Percapita/30*FK$4+(AL6+AL7+AL8+AN6+AN7+AN8)*Cadeirante/30*FK$4,IF(C6=3,IF(AK9+AM9=10,Fixo/30*FK$4+(AK6+AK7+AK8+AM6+AM7+AM8)*Percapita/30*FK$4+(AL9+AN9)*Cadeirante/30*FK$4,IF(AK9+AM9<=9,(AK9+AM9)*Crechee/30*FK$4)+(AL9+AN9)*Cadeirante/30*FK$4+(AK6+AK7+AK8+AM6+AM7+AM8)*Percapita/30*FK$4)+IF(AK9+AM9>=11,Fixo/30*FK$4+(AK9+AM9-10)*Crechee/30*FK$4,0),IF(C6=2,IF(AL6+AL7+AL8+AL9+AN6+AN7+AN8+AN9=1,Cadeirante/30*FK$4,IF(AL6+AL7+AL8+AL9+AN6+AN7+AN8+AN9=2,Fixo/30*FK$4,IF(AL6+AL7+AL8+AL9+AN6+AN7+AN8+AN9>2,Fixo/30*FK$4+(AL6+AL7+AL8+AL9+AN6+AN7+AN8+AN9-2)*Cadeirante/30*FK$4)))+(AK6+AK7+AK8+AM6+AM7+AM8)*Percapita/30*FK$4+(AK9+AM9)*Crechee/30*FK$4,IF(C6=1,IF(AK6+AK7+AK8+AL6+AL7+AL8+AM6+AM7+AM8+AN6+AN7+AN8<=15,(AK6+AK7+AK8+AM6+AM7+AM8)*Percapita/30*FK$4,IF(AK6+AK7+AK8+AL6+AL7+AL8+AM6+AM7+AM8+AN6+AN7+AN8>=16,Fixo/30*FK$4+(AK6+AK7+AK8+AL6+AL7+AL8+AM6+AM7+AM8+AN6+AN7-16)*Percapita/30*FK$4)))))) -> 0 | FL6: =IF(C6=4,SUM(AO6+AO7+AO8+AQ6+AQ7+AQ8)*Percapita/30*FL$4+(AP6+AP7+AP8+AR6+AR7+AR8)*Cadeirante/30*FL$4,IF(C6=3,IF(AO9+AQ9=10,Fixo/30*FL$4+(AO6+AO7+AO8+AQ6+AQ7+AQ8)*Percapita/30*FL$4+(AP9+AR9)*Cadeirante/30*FL$4,IF(AO9+AQ9<=9,(AO9+AQ9)*Crechee/30*FL$4)+(AP9+AR9)*Cadeirante/30*FL$4+(AO6+AO7+AO8+AQ6+AQ7+AQ8)*Percapita/30*FL$4)+IF(AO9+AQ9>=11,Fixo/30*FL$4+(AO9+AQ9-10)*Crechee/30*FL$4,0),IF(C6=2,IF(AP6+AP7+AP8+AP9+AR6+AR7+AR8+AR9=1,Cadeirante/30*FL$4,IF(AP6+AP7+AP8+AP9+AR6+AR7+AR8+AR9=2,Fixo/30*FL$4,IF(AP6+AP7+AP8+AP9+AR6+AR7+AR8+AR9>2,Fixo/30*FL$4+(AP6+AP7+AP8+AP9+AR6+AR7+AR8+AR9-2)*Cadeirante/30*FL$4)))+(AO6+AO7+AO8+AQ6+AQ7+AQ8)*Percapita/30*FL$4+(AO9+AQ9)*Crechee/30*FL$4,IF(C6=1,IF(AO6+AO7+AO8+AP6+AP7+AP8+AQ6+AQ7+AQ8+AR6+AR7+AR8<=15,(AO6+AO7+AO8+AQ6+AQ7+AQ8)*Percapita/30*FL$4,IF(AO6+AO7+AO8+AP6+AP7+AP8+AQ6+AQ7+AQ8+AR6+AR7+AR8>=16,Fixo/30*FL$4+(AO6+AO7+AO8+AP6+AP7+AP8+AQ6+AQ7+AQ8+AR6+AR7-16)*Percapita/30*FL$4)))))) -> 0 | FM6: =IF(C6=4,SUM(AS6+AS7+AS8+AU6+AU7+AU8)*Percapita/30*FM$4+(AT6+AT7+AT8+AV6+AV7+AV8)*Cadeirante/30*FM$4,IF(C6=3,IF(AS9+AU9=10,Fixo/30*FM$4+(AS6+AS7+AS8+AU6+AU7+AU8)*Percapita/30*FM$4+(AT9+AV9)*Cadeirante/30*FM$4,IF(AS9+AU9<=9,(AS9+AU9)*Crechee/30*FM$4)+(AT9+AV9)*Cadeirante/30*FM$4+(AS6+AS7+AS8+AU6+AU7+AU8)*Percapita/30*FM$4)+IF(AS9+AU9>=11,Fixo/30*FM$4+(AS9+AU9-10)*Crechee/30*FM$4,0),IF(C6=2,IF(AT6+AT7+AT8+AT9+AV6+AV7+AV8+AV9=1,Cadeirante/30*FM$4,IF(AT6+AT7+AT8+AT9+AV6+AV7+AV8+AV9=2,Fixo/30*FM$4,IF(AT6+AT7+AT8+AT9+AV6+AV7+AV8+AV9>2,Fixo/30*FM$4+(AT6+AT7+AT8+AT9+AV6+AV7+AV8+AV9-2)*Cadeirante/30*FM$4)))+(AS6+AS7+AS8+AU6+AU7+AU8)*Percapita/30*FM$4+(AS9+AU9)*Crechee/30*FM$4,IF(C6=1,IF(AS6+AS7+AS8+AT6+AT7+AT8+AU6+AU7+AU8+AV6+AV7+AV8<=15,(AS6+AS7+AS8+AU6+AU7+AU8)*Percapita/30*FM$4,IF(AS6+AS7+AS8+AT6+AT7+AT8+AU6+AU7+AU8+AV6+AV7+AV8>=16,Fixo/30*FM$4+(AS6+AS7+AS8+AT6+AT7+AT8+AU6+AU7+AU8+AV6+AV7-16)*Percapita/30*FM$4)))))) -> 0 | FN6: =IF(C6=4,SUM(AW6+AW7+AW8+AY6+AY7+AY8)*Percapita/30*FN$4+(AX6+AX7+AX8+AZ6+AZ7+AZ8)*Cadeirante/30*FN$4,IF(C6=3,IF(AW9+AY9=10,Fixo/30*FN$4+(AW6+AW7+AW8+AY6+AY7+AY8)*Percapita/30*FN$4+(AX9+AZ9)*Cadeirante/30*FN$4,IF(AW9+AY9<=9,(AW9+AY9)*Crechee/30*FN$4)+(AX9+AZ9)*Cadeirante/30*FN$4+(AW6+AW7+AW8+AY6+AY7+AY8)*Percapita/30*FN$4)+IF(AW9+AY9>=11,Fixo/30*FN$4+(AW9+AY9-10)*Crechee/30*FN$4,0),IF(C6=2,IF(AX6+AX7+AX8+AX9+AZ6+AZ7+AZ8+AZ9=1,Cadeirante/30*FN$4,IF(AX6+AX7+AX8+AX9+AZ6+AZ7+AZ8+AZ9=2,Fixo/30*FN$4,IF(AX6+AX7+AX8+AX9+AZ6+AZ7+AZ8+AZ9>2,Fixo/30*FN$4+(AX6+AX7+AX8+AX9+AZ6+AZ7+AZ8+AZ9-2)*Cadeirante/30*FN$4)))+(AW6+AW7+AW8+AY6+AY7+AY8)*Percapita/30*FN$4+(AW9+AY9)*Crechee/30*FN$4,IF(C6=1,IF(AW6+AW7+AW8+AX6+AX7+AX8+AY6+AY7+AY8+AZ6+AZ7+AZ8<=15,(AW6+AW7+AW8+AY6+AY7+AY8)*Percapita/30*FN$4,IF(AW6+AW7+AW8+AX6+AX7+AX8+AY6+AY7+AY8+AZ6+AZ7+AZ8>=16,Fixo/30*FN$4+(AW6+AW7+AW8+AX6+AX7+AX8+AY6+AY7+AY8+AZ6+AZ7-16)*Percapita/30*FN$4)))))) -> 0 | FO6: =IF(C6=4,SUM(BA6+BA7+BA8+BC6+BC7+BC8)*Percapita/30*FO$4+(BB6+BB7+BB8+BD6+BD7+BD8)*Cadeirante/30*FO$4,IF(C6=3,IF(BA9+BC9=10,Fixo/30*FO$4+(BA6+BA7+BA8+BC6+BC7+BC8)*Percapita/30*FO$4+(BB9+BD9)*Cadeirante/30*FO$4,IF(BA9+BC9<=9,(BA9+BC9)*Crechee/30*FO$4)+(BB9+BD9)*Cadeirante/30*FO$4+(BA6+BA7+BA8+BC6+BC7+BC8)*Percapita/30*FO$4)+IF(BA9+BC9>=11,Fixo/30*FO$4+(BA9+BC9-10)*Crechee/30*FO$4,0),IF(C6=2,IF(BB6+BB7+BB8+BB9+BD6+BD7+BD8+BD9=1,Cadeirante/30*FO$4,IF(BB6+BB7+BB8+BB9+BD6+BD7+BD8+BD9=2,Fixo/30*FO$4,IF(BB6+BB7+BB8+BB9+BD6+BD7+BD8+BD9>2,Fixo/30*FO$4+(BB6+BB7+BB8+BB9+BD6+BD7+BD8+BD9-2)*Cadeirante/30*FO$4)))+(BA6+BA7+BA8+BC6+BC7+BC8)*Percapita/30*FO$4+(BA9+BC9)*Crechee/30*FO$4,IF(C6=1,IF(BA6+BA7+BA8+BB6+BB7+BB8+BC6+BC7+BC8+BD6+BD7+BD8<=15,(BA6+BA7+BA8+BC6+BC7+BC8)*Percapita/30*FO$4,IF(BA6+BA7+BA8+BB6+BB7+BB8+BC6+BC7+BC8+BD6+BD7+BD8>=16,Fixo/30*FO$4+(BA6+BA7+BA8+BB6+BB7+BB8+BC6+BC7+BC8+BD6+BD7-16)*Percapita/30*FO$4)))))) -> 0 | FP6: =IF(C6=4,SUM(BE6+BE7+BE8+BG6+BG7+BG8)*Percapita/30*FP$4+(BF6+BF7+BF8+BH6+BH7+BH8)*Cadeirante/30*FP$4,IF(C6=3,IF(BE9+BG9=10,Fixo/30*FP$4+(BE6+BE7+BE8+BG6+BG7+BG8)*Percapita/30*FP$4+(BF9+BH9)*Cadeirante/30*FP$4,IF(BE9+BG9<=9,(BE9+BG9)*Crechee/30*FP$4)+(BF9+BH9)*Cadeirante/30*FP$4+(BE6+BE7+BE8+BG6+BG7+BG8)*Percapita/30*FP$4)+IF(BE9+BG9>=11,Fixo/30*FP$4+(BE9+BG9-10)*Crechee/30*FP$4,0),IF(C6=2,IF(BF6+BF7+BF8+BF9+BH6+BH7+BH8+BH9=1,Cadeirante/30*FP$4,IF(BF6+BF7+BF8+BF9+BH6+BH7+BH8+BH9=2,Fixo/30*FP$4,IF(BF6+BF7+BF8+BF9+BH6+BH7+BH8+BH9>2,Fixo/30*FP$4+(BF6+BF7+BF8+BF9+BH6+BH7+BH8+BH9-2)*Cadeirante/30*FP$4)))+(BE6+BE7+BE8+BG6+BG7+BG8)*Percapita/30*FP$4+(BE9+BG9)*Crechee/30*FP$4,IF(C6=1,IF(BE6+BE7+BE8+BF6+BF7+BF8+BG6+BG7+BG8+BH6+BH7+BH8<=15,(BE6+BE7+BE8+BG6+BG7+BG8)*Percapita/30*FP$4,IF(BE6+BE7+BE8+BF6+BF7+BF8+BG6+BG7+BG8+BH6+BH7+BH8>=16,Fixo/30*FP$4+(BE6+BE7+BE8+BF6+BF7+BF8+BG6+BG7+BG8+BH6+BH7-16)*Percapita/30*FP$4)))))) -> 0 | FQ6: =IF(C6=4,SUM(BI6+BI7+BI8+BK6+BK7+BK8)*Percapita/30*FQ$4+(BJ6+BJ7+BJ8+BL6+BL7+BL8)*Cadeirante/30*FQ$4,IF(C6=3,IF(BI9+BK9=10,Fixo/30*FQ$4+(BI6+BI7+BI8+BK6+BK7+BK8)*Percapita/30*FQ$4+(BJ9+BL9)*Cadeirante/30*FQ$4,IF(BI9+BK9<=9,(BI9+BK9)*Crechee/30*FQ$4)+(BJ9+BL9)*Cadeirante/30*FQ$4+(BI6+BI7+BI8+BK6+BK7+BK8)*Percapita/30*FQ$4)+IF(BI9+BK9>=11,Fixo/30*FQ$4+(BI9+BK9-10)*Crechee/30*FQ$4,0),IF(C6=2,IF(BJ6+BJ7+BJ8+BJ9+BL6+BL7+BL8+BL9=1,Cadeirante/30*FQ$4,IF(BJ6+BJ7+BJ8+BJ9+BL6+BL7+BL8+BL9=2,Fixo/30*FQ$4,IF(BJ6+BJ7+BJ8+BJ9+BL6+BL7+BL8+BL9>2,Fixo/30*FQ$4+(BJ6+BJ7+BJ8+BJ9+BL6+BL7+BL8+BL9-2)*Cadeirante/30*FQ$4)))+(BI6+BI7+BI8+BK6+BK7+BK8)*Percapita/30*FQ$4+(BI9+BK9)*Crechee/30*FQ$4,IF(C6=1,IF(BI6+BI7+BI8+BJ6+BJ7+BJ8+BK6+BK7+BK8+BL6+BL7+BL8<=15,(BI6+BI7+BI8+BK6+BK7+BK8)*Percapita/30*FQ$4,IF(BI6+BI7+BI8+BJ6+BJ7+BJ8+BK6+BK7+BK8+BL6+BL7+BL8>=16,Fixo/30*FQ$4+(BI6+BI7+BI8+BJ6+BJ7+BJ8+BK6+BK7+BK8+BL6+BL7-16)*Percapita/30*FQ$4)))))) -> 0 | FR6: =IF(C6=4,SUM(BM6+BM7+BM8+BO6+BO7+BO8)*Percapita/30*FR$4+(BN6+BN7+BN8+BP6+BP7+BP8)*Cadeirante/30*FR$4,IF(C6=3,IF(BM9+BO9=10,Fixo/30*FR$4+(BM6+BM7+BM8+BO6+BO7+BO8)*Percapita/30*FR$4+(BN9+BP9)*Cadeirante/30*FR$4,IF(BM9+BO9<=9,(BM9+BO9)*Crechee/30*FR$4)+(BN9+BP9)*Cadeirante/30*FR$4+(BM6+BM7+BM8+BO6+BO7+BO8)*Percapita/30*FR$4)+IF(BM9+BO9>=11,Fixo/30*FR$4+(BM9+BO9-10)*Crechee/30*FR$4,0),IF(C6=2,IF(BN6+BN7+BN8+BN9+BP6+BP7+BP8+BP9=1,Cadeirante/30*FR$4,IF(BN6+BN7+BN8+BN9+BP6+BP7+BP8+BP9=2,Fixo/30*FR$4,IF(BN6+BN7+BN8+BN9+BP6+BP7+BP8+BP9>2,Fixo/30*FR$4+(BN6+BN7+BN8+BN9+BP6+BP7+BP8+BP9-2)*Cadeirante/30*FR$4)))+(BM6+BM7+BM8+BO6+BO7+BO8)*Percapita/30*FR$4+(BM9+BO9)*Crechee/30*FR$4,IF(C6=1,IF(BM6+BM7+BM8+BN6+BN7+BN8+BO6+BO7+BO8+BP6+BP7+BP8<=15,(BM6+BM7+BM8+BO6+BO7+BO8)*Percapita/30*FR$4,IF(BM6+BM7+BM8+BN6+BN7+BN8+BO6+BO7+BO8+BP6+BP7+BP8>=16,Fixo/30*FR$4+(BM6+BM7+BM8+BN6+BN7+BN8+BO6+BO7+BO8+BP6+BP7-16)*Percapita/30*FR$4)))))) -> 0 | FS6: =IF(C6=4,SUM(BQ6+BQ7+BQ8+BS6+BS7+BS8)*Percapita/30*FS$4+(BR6+BR7+BR8+BT6+BT7+BT8)*Cadeirante/30*FS$4,IF(C6=3,IF(BQ9+BS9=10,Fixo/30*FS$4+(BQ6+BQ7+BQ8+BS6+BS7+BS8)*Percapita/30*FS$4+(BR9+BT9)*Cadeirante/30*FS$4,IF(BQ9+BS9<=9,(BQ9+BS9)*Crechee/30*FS$4)+(BR9+BT9)*Cadeirante/30*FS$4+(BQ6+BQ7+BQ8+BS6+BS7+BS8)*Percapita/30*FS$4)+IF(BQ9+BS9>=11,Fixo/30*FS$4+(BQ9+BS9-10)*Crechee/30*FS$4,0),IF(C6=2,IF(BR6+BR7+BR8+BR9+BT6+BT7+BT8+BT9=1,Cadeirante/30*FS$4,IF(BR6+BR7+BR8+BR9+BT6+BT7+BT8+BT9=2,Fixo/30*FS$4,IF(BR6+BR7+BR8+BR9+BT6+BT7+BT8+BT9>2,Fixo/30*FS$4+(BR6+BR7+BR8+BR9+BT6+BT7+BT8+BT9-2)*Cadeirante/30*FS$4)))+(BQ6+BQ7+BQ8+BS6+BS7+BS8)*Percapita/30*FS$4+(BQ9+BS9)*Crechee/30*FS$4,IF(C6=1,IF(BQ6+BQ7+BQ8+BR6+BR7+BR8+BS6+BS7+BS8+BT6+BT7+BT8<=15,(BQ6+BQ7+BQ8+BS6+BS7+BS8)*Percapita/30*FS$4,IF(BQ6+BQ7+BQ8+BR6+BR7+BR8+BS6+BS7+BS8+BT6+BT7+BT8>=16,Fixo/30*FS$4+(BQ6+BQ7+BQ8+BR6+BR7+BR8+BS6+BS7+BS8+BT6+BT7-16)*Percapita/30*FS$4)))))) -> 0 | FT6: =IF(C6=4,SUM(BU6+BU7+BU8+BW6+BW7+BW8)*Percapita/30*FT$4+(BV6+BV7+BV8+BX6+BX7+BX8)*Cadeirante/30*FT$4,IF(C6=3,IF(BU9+BW9=10,Fixo/30*FT$4+(BU6+BU7+BU8+BW6+BW7+BW8)*Percapita/30*FT$4+(BV9+BX9)*Cadeirante/30*FT$4,IF(BU9+BW9<=9,(BU9+BW9)*Crechee/30*FT$4)+(BV9+BX9)*Cadeirante/30*FT$4+(BU6+BU7+BU8+BW6+BW7+BW8)*Percapita/30*FT$4)+IF(BU9+BW9>=11,Fixo/30*FT$4+(BU9+BW9-10)*Crechee/30*FT$4,0),IF(C6=2,IF(BV6+BV7+BV8+BV9+BX6+BX7+BX8+BX9=1,Cadeirante/30*FT$4,IF(BV6+BV7+BV8+BV9+BX6+BX7+BX8+BX9=2,Fixo/30*FT$4,IF(BV6+BV7+BV8+BV9+BX6+BX7+BX8+BX9>2,Fixo/30*FT$4+(BV6+BV7+BV8+BV9+BX6+BX7+BX8+BX9-2)*Cadeirante/30*FT$4)))+(BU6+BU7+BU8+BW6+BW7+BW8)*Percapita/30*FT$4+(BU9+BW9)*Crechee/30*FT$4,IF(C6=1,IF(BU6+BU7+BU8+BV6+BV7+BV8+BW6+BW7+BW8+BX6+BX7+BX8<=15,(BU6+BU7+BU8+BW6+BW7+BW8)*Percapita/30*FT$4,IF(BU6+BU7+BU8+BV6+BV7+BV8+BW6+BW7+BW8+BX6+BX7+BX8>=16,Fixo/30*FT$4+(BU6+BU7+BU8+BV6+BV7+BV8+BW6+BW7+BW8+BX6+BX7-16)*Percapita/30*FT$4)))))) -> 0 | FU6: =IF(C6=4,SUM(BY6+BY7+BY8+CA6+CA7+CA8)*Percapita/30*FU$4+(BZ6+BZ7+BZ8+CB6+CB7+CB8)*Cadeirante/30*FU$4,IF(C6=3,IF(BY9+CA9=10,Fixo/30*FU$4+(BY6+BY7+BY8+CA6+CA7+CA8)*Percapita/30*FU$4+(BZ9+CB9)*Cadeirante/30*FU$4,IF(BY9+CA9<=9,(BY9+CA9)*Crechee/30*FU$4)+(BZ9+CB9)*Cadeirante/30*FU$4+(BY6+BY7+BY8+CA6+CA7+CA8)*Percapita/30*FU$4)+IF(BY9+CA9>=11,Fixo/30*FU$4+(BY9+CA9-10)*Crechee/30*FU$4,0),IF(C6=2,IF(BZ6+BZ7+BZ8+BZ9+CB6+CB7+CB8+CB9=1,Cadeirante/30*FU$4,IF(BZ6+BZ7+BZ8+BZ9+CB6+CB7+CB8+CB9=2,Fixo/30*FU$4,IF(BZ6+BZ7+BZ8+BZ9+CB6+CB7+CB8+CB9>2,Fixo/30*FU$4+(BZ6+BZ7+BZ8+BZ9+CB6+CB7+CB8+CB9-2)*Cadeirante/30*FU$4)))+(BY6+BY7+BY8+CA6+CA7+CA8)*Percapita/30*FU$4+(BY9+CA9)*Crechee/30*FU$4,IF(C6=1,IF(BY6+BY7+BY8+BZ6+BZ7+BZ8+CA6+CA7+CA8+CB6+CB7+CB8<=15,(BY6+BY7+BY8+CA6+CA7+CA8)*Percapita/30*FU$4,IF(BY6+BY7+BY8+BZ6+BZ7+BZ8+CA6+CA7+CA8+CB6+CB7+CB8>=16,Fixo/30*FU$4+(BY6+BY7+BY8+BZ6+BZ7+BZ8+CA6+CA7+CA8+CB6+CB7-16)*Percapita/30*FU$4)))))) -> 0 | FV6: =IF(C6=4,SUM(CC6+CC7+CC8+CE6+CE7+CE8)*Percapita/30*FV$4+(CD6+CD7+CD8+CF6+CF7+CF8)*Cadeirante/30*FV$4,IF(C6=3,IF(CC9+CE9=10,Fixo/30*FV$4+(CC6+CC7+CC8+CE6+CE7+CE8)*Percapita/30*FV$4+(CD9+CF9)*Cadeirante/30*FV$4,IF(CC9+CE9<=9,(CC9+CE9)*Crechee/30*FV$4)+(CD9+CF9)*Cadeirante/30*FV$4+(CC6+CC7+CC8+CE6+CE7+CE8)*Percapita/30*FV$4)+IF(CC9+CE9>=11,Fixo/30*FV$4+(CC9+CE9-10)*Crechee/30*FV$4,0),IF(C6=2,IF(CD6+CD7+CD8+CD9+CF6+CF7+CF8+CF9=1,Cadeirante/30*FV$4,IF(CD6+CD7+CD8+CD9+CF6+CF7+CF8+CF9=2,Fixo/30*FV$4,IF(CD6+CD7+CD8+CD9+CF6+CF7+CF8+CF9>2,Fixo/30*FV$4+(CD6+CD7+CD8+CD9+CF6+CF7+CF8+CF9-2)*Cadeirante/30*FV$4)))+(CC6+CC7+CC8+CE6+CE7+CE8)*Percapita/30*FV$4+(CC9+CE9)*Crechee/30*FV$4,IF(C6=1,IF(CC6+CC7+CC8+CD6+CD7+CD8+CE6+CE7+CE8+CF6+CF7+CF8<=15,(CC6+CC7+CC8+CE6+CE7+CE8)*Percapita/30*FV$4,IF(CC6+CC7+CC8+CD6+CD7+CD8+CE6+CE7+CE8+CF6+CF7+CF8>=16,Fixo/30*FV$4+(CC6+CC7+CC8+CD6+CD7+CD8+CE6+CE7+CE8+CF6+CF7-16)*Percapita/30*FV$4)))))) -> 179.774 | FW6: =IF(C6=4,SUM(CG6+CG7+CG8+CI6+CI7+CI8)*Percapita/30*FW$4+(CH6+CH7+CH8+CJ6+CJ7+CJ8)*Cadeirante/30*FW$4,IF(C6=3,IF(CG9+CI9=10,Fixo/30*FW$4+(CG6+CG7+CG8+CI6+CI7+CI8)*Percapita/30*FW$4+(CH9+CJ9)*Cadeirante/30*FW$4,IF(CG9+CI9<=9,(CG9+CI9)*Crechee/30*FW$4)+(CH9+CJ9)*Cadeirante/30*FW$4+(CG6+CG7+CG8+CI6+CI7+CI8)*Percapita/30*FW$4)+IF(CG9+CI9>=11,Fixo/30*FW$4+(CG9+CI9-10)*Crechee/30*FW$4,0),IF(C6=2,IF(CH6+CH7+CH8+CH9+CJ6+CJ7+CJ8+CJ9=1,Cadeirante/30*FW$4,IF(CH6+CH7+CH8+CH9+CJ6+CJ7+CJ8+CJ9=2,Fixo/30*FW$4,IF(CH6+CH7+CH8+CH9+CJ6+CJ7+CJ8+CJ9>2,Fixo/30*FW$4+(CH6+CH7+CH8+CH9+CJ6+CJ7+CJ8+CJ9-2)*Cadeirante/30*FW$4)))+(CG6+CG7+CG8+CI6+CI7+CI8)*Percapita/30*FW$4+(CG9+CI9)*Crechee/30*FW$4,IF(C6=1,IF(CG6+CG7+CG8+CH6+CH7+CH8+CI6+CI7+CI8+CJ6+CJ7+CJ8<=15,(CG6+CG7+CG8+CI6+CI7+CI8)*Percapita/30*FW$4,IF(CG6+CG7+CG8+CH6+CH7+CH8+CI6+CI7+CI8+CJ6+CJ7+CJ8>=16,Fixo/30*FW$4+(CG6+CG7+CG8+CH6+CH7+CH8+CI6+CI7+CI8+CJ6+CJ7-16)*Percapita/30*FW$4)))))) -> 0 | FX6: =IF(C6=4,SUM(CK6+CK7+CK8+CM6+CM7+CM8)*Percapita/30*FX$4+(CL6+CL7+CL8+CN6+CN7+CN8)*Cadeirante/30*FX$4,IF(C6=3,IF(CK9+CM9=10,Fixo/30*FX$4+(CK6+CK7+CK8+CM6+CM7+CM8)*Percapita/30*FX$4+(CL9+CN9)*Cadeirante/30*FX$4,IF(CK9+CM9<=9,(CK9+CM9)*Crechee/30*FX$4)+(CL9+CN9)*Cadeirante/30*FX$4+(CK6+CK7+CK8+CM6+CM7+CM8)*Percapita/30*FX$4)+IF(CK9+CM9>=11,Fixo/30*FX$4+(CK9+CM9-10)*Crechee/30*FX$4,0),IF(C6=2,IF(CL6+CL7+CL8+CL9+CN6+CN7+CN8+CN9=1,Cadeirante/30*FX$4,IF(CL6+CL7+CL8+CL9+CN6+CN7+CN8+CN9=2,Fixo/30*FX$4,IF(CL6+CL7+CL8+CL9+CN6+CN7+CN8+CN9>2,Fixo/30*FX$4+(CL6+CL7+CL8+CL9+CN6+CN7+CN8+CN9-2)*Cadeirante/30*FX$4)))+(CK6+CK7+CK8+CM6+CM7+CM8)*Percapita/30*FX$4+(CK9+CM9)*Crechee/30*FX$4,IF(C6=1,IF(CK6+CK7+CK8+CL6+CL7+CL8+CM6+CM7+CM8+CN6+CN7+CN8<=15,(CK6+CK7+CK8+CM6+CM7+CM8)*Percapita/30*FX$4,IF(CK6+CK7+CK8+CL6+CL7+CL8+CM6+CM7+CM8+CN6+CN7+CN8>=16,Fixo/30*FX$4+(CK6+CK7+CK8+CL6+CL7+CL8+CM6+CM7+CM8+CN6+CN7-16)*Percapita/30*FX$4)))))) -> 0 | FY6: =IF(C6=4,SUM(CO6+CO7+CO8+CQ6+CQ7+CQ8)*Percapita/30*FY$4+(CP6+CP7+CP8+CR6+CR7+CR8)*Cadeirante/30*FY$4,IF(C6=3,IF(CO9+CQ9=10,Fixo/30*FY$4+(CO6+CO7+CO8+CQ6+CQ7+CQ8)*Percapita/30*FY$4+(CP9+CR9)*Cadeirante/30*FY$4,IF(CO9+CQ9<=9,(CO9+CQ9)*Crechee/30*FY$4)+(CP9+CR9)*Cadeirante/30*FY$4+(CO6+CO7+CO8+CQ6+CQ7+CQ8)*Percapita/30*FY$4)+IF(CO9+CQ9>=11,Fixo/30*FY$4+(CO9+CQ9-10)*Crechee/30*FY$4,0),IF(C6=2,IF(CP6+CP7+CP8+CP9+CR6+CR7+CR8+CR9=1,Cadeirante/30*FY$4,IF(CP6+CP7+CP8+CP9+CR6+CR7+CR8+CR9=2,Fixo/30*FY$4,IF(CP6+CP7+CP8+CP9+CR6+CR7+CR8+CR9>2,Fixo/30*FY$4+(CP6+CP7+CP8+CP9+CR6+CR7+CR8+CR9-2)*Cadeirante/30*FY$4)))+(CO6+CO7+CO8+CQ6+CQ7+CQ8)*Percapita/30*FY$4+(CO9+CQ9)*Crechee/30*FY$4,IF(C6=1,IF(CO6+CO7+CO8+CP6+CP7+CP8+CQ6+CQ7+CQ8+CR6+CR7+CR8<=15,(CO6+CO7+CO8+CQ6+CQ7+CQ8)*Percapita/30*FY$4,IF(CO6+CO7+CO8+CP6+CP7+CP8+CQ6+CQ7+CQ8+CR6+CR7+CR8>=16,Fixo/30*FY$4+(CO6+CO7+CO8+CP6+CP7+CP8+CQ6+CQ7+CQ8+CR6+CR7-16)*Percapita/30*FY$4)))))) -> 0 | FZ6: =IF(C6=4,SUM(CS6+CS7+CS8+CU6+CU7+CU8)*Percapita/30*FZ$4+(CT6+CT7+CT8+CV6+CV7+CV8)*Cadeirante/30*FZ$4,IF(C6=3,IF(CS9+CU9=10,Fixo/30*FZ$4+(CS6+CS7+CS8+CU6+CU7+CU8)*Percapita/30*FZ$4+(CT9+CV9)*Cadeirante/30*FZ$4,IF(CS9+CU9<=9,(CS9+CU9)*Crechee/30*FZ$4)+(CT9+CV9)*Cadeirante/30*FZ$4+(CS6+CS7+CS8+CU6+CU7+CU8)*Percapita/30*FZ$4)+IF(CS9+CU9>=11,Fixo/30*FZ$4+(CS9+CU9-10)*Crechee/30*FZ$4,0),IF(C6=2,IF(CT6+CT7+CT8+CT9+CV6+CV7+CV8+CV9=1,Cadeirante/30*FZ$4,IF(CT6+CT7+CT8+CT9+CV6+CV7+CV8+CV9=2,Fixo/30*FZ$4,IF(CT6+CT7+CT8+CT9+CV6+CV7+CV8+CV9>2,Fixo/30*FZ$4+(CT6+CT7+CT8+CT9+CV6+CV7+CV8+CV9-2)*Cadeirante/30*FZ$4)))+(CS6+CS7+CS8+CU6+CU7+CU8)*Percapita/30*FZ$4+(CS9+CU9)*Crechee/30*FZ$4,IF(C6=1,IF(CS6+CS7+CS8+CT6+CT7+CT8+CU6+CU7+CU8+CV6+CV7+CV8<=15,(CS6+CS7+CS8+CU6+CU7+CU8)*Percapita/30*FZ$4,IF(CS6+CS7+CS8+CT6+CT7+CT8+CU6+CU7+CU8+CV6+CV7+CV8>=16,Fixo/30*FZ$4+(CS6+CS7+CS8+CT6+CT7+CT8+CU6+CU7+CU8+CV6+CV7-16)*Percapita/30*FZ$4)))))) -> 0 | GA6: =IF(C6=4,SUM(CW6+CW7+CW8+CY6+CY7+CY8)*Percapita/30*GA$4+(CX6+CX7+CX8+CZ6+CZ7+CZ8)*Cadeirante/30*GA$4,IF(C6=3,IF(CW9+CY9=10,Fixo/30*GA$4+(CW6+CW7+CW8+CY6+CY7+CY8)*Percapita/30*GA$4+(CX9+CZ9)*Cadeirante/30*GA$4,IF(CW9+CY9<=9,(CW9+CY9)*Crechee/30*GA$4)+(CX9+CZ9)*Cadeirante/30*GA$4+(CW6+CW7+CW8+CY6+CY7+CY8)*Percapita/30*GA$4)+IF(CW9+CY9>=11,Fixo/30*GA$4+(CW9+CY9-10)*Crechee/30*GA$4,0),IF(C6=2,IF(CX6+CX7+CX8+CX9+CZ6+CZ7+CZ8+CZ9=1,Cadeirante/30*GA$4,IF(CX6+CX7+CX8+CX9+CZ6+CZ7+CZ8+CZ9=2,Fixo/30*GA$4,IF(CX6+CX7+CX8+CX9+CZ6+CZ7+CZ8+CZ9>2,Fixo/30*GA$4+(CX6+CX7+CX8+CX9+CZ6+CZ7+CZ8+CZ9-2)*Cadeirante/30*GA$4)))+(CW6+CW7+CW8+CY6+CY7+CY8)*Percapita/30*GA$4+(CW9+CY9)*Crechee/30*GA$4,IF(C6=1,IF(CW6+CW7+CW8+CX6+CX7+CX8+CY6+CY7+CY8+CZ6+CZ7+CZ8<=15,(CW6+CW7+CW8+CY6+CY7+CY8)*Percapita/30*GA$4,IF(CW6+CW7+CW8+CX6+CX7+CX8+CY6+CY7+CY8+CZ6+CZ7+CZ8>=16,Fixo/30*GA$4+(CW6+CW7+CW8+CX6+CX7+CX8+CY6+CY7+CY8+CZ6+CZ7-16)*Percapita/30*GA$4)))))) -> 115.569 | GB6: =IF(C6=4,SUM(DA6+DA7+DA8+DC6+DC7+DC8)*Percapita/30*GB$4+(DB6+DB7+DB8+DD6+DD7+DD8)*Cadeirante/30*GB$4,IF(C6=3,IF(DA9+DC9=10,Fixo/30*GB$4+(DA6+DA7+DA8+DC6+DC7+DC8)*Percapita/30*GB$4+(DB9+DD9)*Cadeirante/30*GB$4,IF(DA9+DC9<=9,(DA9+DC9)*Crechee/30*GB$4)+(DB9+DD9)*Cadeirante/30*GB$4+(DA6+DA7+DA8+DC6+DC7+DC8)*Percapita/30*GB$4)+IF(DA9+DC9>=11,Fixo/30*GB$4+(DA9+DC9-10)*Crechee/30*GB$4,0),IF(C6=2,IF(DB6+DB7+DB8+DB9+DD6+DD7+DD8+DD9=1,Cadeirante/30*GB$4,IF(DB6+DB7+DB8+DB9+DD6+DD7+DD8+DD9=2,Fixo/30*GB$4,IF(DB6+DB7+DB8+DB9+DD6+DD7+DD8+DD9>2,Fixo/30*GB$4+(DB6+DB7+DB8+DB9+DD6+DD7+DD8+DD9-2)*Cadeirante/30*GB$4)))+(DA6+DA7+DA8+DC6+DC7+DC8)*Percapita/30*GB$4+(DA9+DC9)*Crechee/30*GB$4,IF(C6=1,IF(DA6+DA7+DA8+DB6+DB7+DB8+DC6+DC7+DC8+DD6+DD7+DD8<=15,(DA6+DA7+DA8+DC6+DC7+DC8)*Percapita/30*GB$4,IF(DA6+DA7+DA8+DB6+DB7+DB8+DC6+DC7+DC8+DD6+DD7+DD8>=16,Fixo/30*GB$4+(DA6+DA7+DA8+DB6+DB7+DB8+DC6+DC7+DC8+DD6+DD7-16)*Percapita/30*GB$4)))))) -> 0 | GC6: =IF(C6=4,SUM(DE6+DE7+DE8+DG6+DG7+DG8)*Percapita/30*GC$4+(DF6+DF7+DF8+DH6+DH7+DH8)*Cadeirante/30*GC$4,IF(C6=3,IF(DE9+DG9=10,Fixo/30*GC$4+(DE6+DE7+DE8+DG6+DG7+DG8)*Percapita/30*GC$4+(DF9+DH9)*Cadeirante/30*GC$4,IF(DE9+DG9<=9,(DE9+DG9)*Crechee/30*GC$4)+(DF9+DH9)*Cadeirante/30*GC$4+(DE6+DE7+DE8+DG6+DG7+DG8)*Percapita/30*GC$4)+IF(DE9+DG9>=11,Fixo/30*GC$4+(DE9+DG9-10)*Crechee/30*GC$4,0),IF(C6=2,IF(DF6+DF7+DF8+DF9+DH6+DH7+DH8+DH9=1,Cadeirante/30*GC$4,IF(DF6+DF7+DF8+DF9+DH6+DH7+DH8+DH9=2,Fixo/30*GC$4,IF(DF6+DF7+DF8+DF9+DH6+DH7+DH8+DH9>2,Fixo/30*GC$4+(DF6+DF7+DF8+DF9+DH6+DH7+DH8+DH9-2)*Cadeirante/30*GC$4)))+(DE6+DE7+DE8+DG6+DG7+DG8)*Percapita/30*GC$4+(DE9+DG9)*Crechee/30*GC$4,IF(C6=1,IF(DE6+DE7+DE8+DF6+DF7+DF8+DG6+DG7+DG8+DH6+DH7+DH8<=15,(DE6+DE7+DE8+DG6+DG7+DG8)*Percapita/30*GC$4,IF(DE6+DE7+DE8+DF6+DF7+DF8+DG6+DG7+DG8+DH6+DH7+DH8>=16,Fixo/30*GC$4+(DE6+DE7+DE8+DF6+DF7+DF8+DG6+DG7+DG8+DH6+DH7-16)*Percapita/30*GC$4)))))) -> 0 | GD6: =IF(C6=4,SUM(DI6+DI7+DI8+DK6+DK7+DK8)*Percapita/30*GD$4+(DJ6+DJ7+DJ8+DL6+DL7+DL8)*Cadeirante/30*GD$4,IF(C6=3,IF(DI9+DK9=10,Fixo/30*GD$4+(DI6+DI7+DI8+DK6+DK7+DK8)*Percapita/30*GD$4+(DJ9+DL9)*Cadeirante/30*GD$4,IF(DI9+DK9<=9,(DI9+DK9)*Crechee/30*GD$4)+(DJ9+DL9)*Cadeirante/30*GD$4+(DI6+DI7+DI8+DK6+DK7+DK8)*Percapita/30*GD$4)+IF(DI9+DK9>=11,Fixo/30*GD$4+(DI9+DK9-10)*Crechee/30*GD$4,0),IF(C6=2,IF(DJ6+DJ7+DJ8+DJ9+DL6+DL7+DL8+DL9=1,Cadeirante/30*GD$4,IF(DJ6+DJ7+DJ8+DJ9+DL6+DL7+DL8+DL9=2,Fixo/30*GD$4,IF(DJ6+DJ7+DJ8+DJ9+DL6+DL7+DL8+DL9>2,Fixo/30*GD$4+(DJ6+DJ7+DJ8+DJ9+DL6+DL7+DL8+DL9-2)*Cadeirante/30*GD$4)))+(DI6+DI7+DI8+DK6+DK7+DK8)*Percapita/30*GD$4+(DI9+DK9)*Crechee/30*GD$4,IF(C6=1,IF(DI6+DI7+DI8+DJ6+DJ7+DJ8+DK6+DK7+DK8+DL6+DL7+DL8<=15,(DI6+DI7+DI8+DK6+DK7+DK8)*Percapita/30*GD$4,IF(DI6+DI7+DI8+DJ6+DJ7+DJ8+DK6+DK7+DK8+DL6+DL7+DL8>=16,Fixo/30*GD$4+(DI6+DI7+DI8+DJ6+DJ7+DJ8+DK6+DK7+DK8+DL6+DL7-16)*Percapita/30*GD$4)))))) -> 0 | GE6: =IF(C6=4,SUM(DM6+DM7+DM8+DO6+DO7+DO8)*Percapita/30*GE$4+(DN6+DN7+DN8+DP6+DP7+DP8)*Cadeirante/30*GE$4,IF(C6=3,IF(DM9+DO9=10,Fixo/30*GE$4+(DM6+DM7+DM8+DO6+DO7+DO8)*Percapita/30*GE$4+(DN9+DP9)*Cadeirante/30*GE$4,IF(DM9+DO9<=9,(DM9+DO9)*Crechee/30*GE$4)+(DN9+DP9)*Cadeirante/30*GE$4+(DM6+DM7+DM8+DO6+DO7+DO8)*Percapita/30*GE$4)+IF(DM9+DO9>=11,Fixo/30*GE$4+(DM9+DO9-10)*Crechee/30*GE$4,0),IF(C6=2,IF(DN6+DN7+DN8+DN9+DP6+DP7+DP8+DP9=1,Cadeirante/30*GE$4,IF(DN6+DN7+DN8+DN9+DP6+DP7+DP8+DP9=2,Fixo/30*GE$4,IF(DN6+DN7+DN8+DN9+DP6+DP7+DP8+DP9>2,Fixo/30*GE$4+(DN6+DN7+DN8+DN9+DP6+DP7+DP8+DP9-2)*Cadeirante/30*GE$4)))+(DM6+DM7+DM8+DO6+DO7+DO8)*Percapita/30*GE$4+(DM9+DO9)*Crechee/30*GE$4,IF(C6=1,IF(DM6+DM7+DM8+DN6+DN7+DN8+DO6+DO7+DO8+DP6+DP7+DP8<=15,(DM6+DM7+DM8+DO6+DO7+DO8)*Percapita/30*GE$4,IF(DM6+DM7+DM8+DN6+DN7+DN8+DO6+DO7+DO8+DP6+DP7+DP8>=16,Fixo/30*GE$4+(DM6+DM7+DM8+DN6+DN7+DN8+DO6+DO7+DO8+DP6+DP7-16)*Percapita/30*GE$4)))))) -> 0 | GF6: =IF(C6=4,SUM(DQ6+DQ7+DQ8+DS6+DS7+DS8)*Percapita/30*GF$4+(DR6+DR7+DR8+DT6+DT7+DT8)*Cadeirante/30*GF$4,IF(C6=3,IF(DQ9+DS9=10,Fixo/30*GF$4+(DQ6+DQ7+DQ8+DS6+DS7+DS8)*Percapita/30*GF$4+(DR9+DT9)*Cadeirante/30*GF$4,IF(DQ9+DS9<=9,(DQ9+DS9)*Crechee/30*GF$4)+(DR9+DT9)*Cadeirante/30*GF$4+(DQ6+DQ7+DQ8+DS6+DS7+DS8)*Percapita/30*GF$4)+IF(DQ9+DS9>=11,Fixo/30*GF$4+(DQ9+DS9-10)*Crechee/30*GF$4,0),IF(C6=2,IF(DR6+DR7+DR8+DR9+DT6+DT7+DT8+DT9=1,Cadeirante/30*GF$4,IF(DR6+DR7+DR8+DR9+DT6+DT7+DT8+DT9=2,Fixo/30*GF$4,IF(DR6+DR7+DR8+DR9+DT6+DT7+DT8+DT9>2,Fixo/30*GF$4+(DR6+DR7+DR8+DR9+DT6+DT7+DT8+DT9-2)*Cadeirante/30*GF$4)))+(DQ6+DQ7+DQ8+DS6+DS7+DS8)*Percapita/30*GF$4+(DQ9+DS9)*Crechee/30*GF$4,IF(C6=1,IF(DQ6+DQ7+DQ8+DR6+DR7+DR8+DS6+DS7+DS8+DT6+DT7+DT8<=15,(DQ6+DQ7+DQ8+DS6+DS7+DS8)*Percapita/30*GF$4,IF(DQ6+DQ7+DQ8+DR6+DR7+DR8+DS6+DS7+DS8+DT6+DT7+DT8>=16,Fixo/30*GF$4+(DQ6+DQ7+DQ8+DR6+DR7+DR8+DS6+DS7+DS8+DT6+DT7-16)*Percapita/30*GF$4)))))) -> 0 | GG6: =IF(C6=4,SUM(DU6+DU7+DU8+DW6+DW7+DW8)*Percapita/30*GG$4+(DV6+DV7+DV8+DX6+DX7+DX8)*Cadeirante/30*GG$4,IF(C6=3,IF(DU9+DW9=10,Fixo/30*GG$4+(DU6+DU7+DU8+DW6+DW7+DW8)*Percapita/30*GG$4+(DV9+DX9)*Cadeirante/30*GG$4,IF(DU9+DW9<=9,(DU9+DW9)*Crechee/30*GG$4)+(DV9+DX9)*Cadeirante/30*GG$4+(DU6+DU7+DU8+DW6+DW7+DW8)*Percapita/30*GG$4)+IF(DU9+DW9>=11,Fixo/30*GG$4+(DU9+DW9-10)*Crechee/30*GG$4,0),IF(C6=2,IF(DV6+DV7+DV8+DV9+DX6+DX7+DX8+DX9=1,Cadeirante/30*GG$4,IF(DV6+DV7+DV8+DV9+DX6+DX7+DX8+DX9=2,Fixo/30*GG$4,IF(DV6+DV7+DV8+DV9+DX6+DX7+DX8+DX9>2,Fixo/30*GG$4+(DV6+DV7+DV8+DV9+DX6+DX7+DX8+DX9-2)*Cadeirante/30*GG$4)))+(DU6+DU7+DU8+DW6+DW7+DW8)*Percapita/30*GG$4+(DU9+DW9)*Crechee/30*GG$4,IF(C6=1,IF(DU6+DU7+DU8+DV6+DV7+DV8+DW6+DW7+DW8+DX6+DX7+DX8<=15,(DU6+DU7+DU8+DW6+DW7+DW8)*Percapita/30*GG$4,IF(DU6+DU7+DU8+DV6+DV7+DV8+DW6+DW7+DW8+DX6+DX7+DX8>=16,Fixo/30*GG$4+(DU6+DU7+DU8+DV6+DV7+DV8+DW6+DW7+DW8+DX6+DX7-16)*Percapita/30*GG$4)))))) -> 0 | GH6: =IF(C6=4,SUM(DY6+DY7+DY8+EA6+EA7+EA8)*Percapita/30*GH$4+(DZ6+DZ7+DZ8+EB6+EB7+EB8)*Cadeirante/30*GH$4,IF(C6=3,IF(DY9+EA9=10,Fixo/30*GH$4+(DY6+DY7+DY8+EA6+EA7+EA8)*Percapita/30*GH$4+(DZ9+EB9)*Cadeirante/30*GH$4,IF(DY9+EA9<=9,(DY9+EA9)*Crechee/30*GH$4)+(DZ9+EB9)*Cadeirante/30*GH$4+(DY6+DY7+DY8+EA6+EA7+EA8)*Percapita/30*GH$4)+IF(DY9+EA9>=11,Fixo/30*GH$4+(DY9+EA9-10)*Crechee/30*GH$4,0),IF(C6=2,IF(DZ6+DZ7+DZ8+DZ9+EB6+EB7+EB8+EB9=1,Cadeirante/30*GH$4,IF(DZ6+DZ7+DZ8+DZ9+EB6+EB7+EB8+EB9=2,Fixo/30*GH$4,IF(DZ6+DZ7+DZ8+DZ9+EB6+EB7+EB8+EB9>2,Fixo/30*GH$4+(DZ6+DZ7+DZ8+DZ9+EB6+EB7+EB8+EB9-2)*Cadeirante/30*GH$4)))+(DY6+DY7+DY8+EA6+EA7+EA8)*Percapita/30*GH$4+(DY9+EA9)*Crechee/30*GH$4,IF(C6=1,IF(DY6+DY7+DY8+DZ6+DZ7+DZ8+EA6+EA7+EA8+EB6+EB7+EB8<=15,(DY6+DY7+DY8+EA6+EA7+EA8)*Percapita/30*GH$4,IF(DY6+DY7+DY8+DZ6+DZ7+DZ8+EA6+EA7+EA8+EB6+EB7+EB8>=16,Fixo/30*GH$4+(DY6+DY7+DY8+DZ6+DZ7+DZ8+EA6+EA7+EA8+EB6+EB7-16)*Percapita/30*GH$4)))))) -> 0 | GI6: =IF(C6=4,SUM(EC6+EC7+EC8+EE6+EE7+EE8)*Percapita/30*GI$4+(ED6+ED7+ED8+EF6+EF7+EF8)*Cadeirante/30*GI$4,IF(C6=3,IF(EC9+EE9=10,Fixo/30*GI$4+(EC6+EC7+EC8+EE6+EE7+EE8)*Percapita/30*GI$4+(ED9+EF9)*Cadeirante/30*GI$4,IF(EC9+EE9<=9,(EC9+EE9)*Crechee/30*GI$4)+(ED9+EF9)*Cadeirante/30*GI$4+(EC6+EC7+EC8+EE6+EE7+EE8)*Percapita/30*GI$4)+IF(EC9+EE9>=11,Fixo/30*GI$4+(EC9+EE9-10)*Crechee/30*GI$4,0),IF(C6=2,IF(ED6+ED7+ED8+ED9+EF6+EF7+EF8+EF9=1,Cadeirante/30*GI$4,IF(ED6+ED7+ED8+ED9+EF6+EF7+EF8+EF9=2,Fixo/30*GI$4,IF(ED6+ED7+ED8+ED9+EF6+EF7+EF8+EF9>2,Fixo/30*GI$4+(ED6+ED7+ED8+ED9+EF6+EF7+EF8+EF9-2)*Cadeirante/30*GI$4)))+(EC6+EC7+EC8+EE6+EE7+EE8)*Percapita/30*GI$4+(EC9+EE9)*Crechee/30*GI$4,IF(C6=1,IF(EC6+EC7+EC8+ED6+ED7+ED8+EE6+EE7+EE8+EF6+EF7+EF8<=15,(EC6+EC7+EC8+EE6+EE7+EE8)*Percapita/30*GI$4,IF(EC6+EC7+EC8+ED6+ED7+ED8+EE6+EE7+EE8+EF6+EF7+EF8>=16,Fixo/30*GI$4+(EC6+EC7+EC8+ED6+ED7+ED8+EE6+EE7+EE8+EF6+EF7-16)*Percapita/30*GI$4)))))) -> 0 | GJ6: =IF(C6=4,SUM(EG6+EG7+EG8+EI6+EI7+EI8)*Percapita/30*GJ$4+(EH6+EH7+EH8+EJ6+EJ7+EJ8)*Cadeirante/30*GJ$4,IF(C6=3,IF(EG9+EI9=10,Fixo/30*GJ$4+(EG6+EG7+EG8+EI6+EI7+EI8)*Percapita/30*GJ$4+(EH9+EJ9)*Cadeirante/30*GJ$4,IF(EG9+EI9<=9,(EG9+EI9)*Crechee/30*GJ$4)+(EH9+EJ9)*Cadeirante/30*GJ$4+(EG6+EG7+EG8+EI6+EI7+EI8)*Percapita/30*GJ$4)+IF(EG9+EI9>=11,Fixo/30*GJ$4+(EG9+EI9-10)*Crechee/30*GJ$4,0),IF(C6=2,IF(EH6+EH7+EH8+EH9+EJ6+EJ7+EJ8+EJ9=1,Cadeirante/30*GJ$4,IF(EH6+EH7+EH8+EH9+EJ6+EJ7+EJ8+EJ9=2,Fixo/30*GJ$4,IF(EH6+EH7+EH8+EH9+EJ6+EJ7+EJ8+EJ9>2,Fixo/30*GJ$4+(EH6+EH7+EH8+EH9+EJ6+EJ7+EJ8+EJ9-2)*Cadeirante/30*GJ$4)))+(EG6+EG7+EG8+EI6+EI7+EI8)*Percapita/30*GJ$4+(EG9+EI9)*Crechee/30*GJ$4,IF(C6=1,IF(EG6+EG7+EG8+EH6+EH7+EH8+EI6+EI7+EI8+EJ6+EJ7+EJ8<=15,(EG6+EG7+EG8+EI6+EI7+EI8)*Percapita/30*GJ$4,IF(EG6+EG7+EG8+EH6+EH7+EH8+EI6+EI7+EI8+EJ6+EJ7+EJ8>=16,Fixo/30*GJ$4+(EG6+EG7+EG8+EH6+EH7+EH8+EI6+EI7+EI8+EJ6+EJ7-16)*Percapita/30*GJ$4)))))) -> 0 | GL6: =IF(J6="ADAPTADO",T6*Cadeirante/30*GM6+S6*Percapita/30*GM6,IF(J6="NORMAL",(S6+T6)*Percapita/30*GM6,IF(J6="CRECHE",0)))*-1 -> 0 | GN6: =SUMIF(V6:V9,"<0")*Cadeirante/30*GN$4+SUMIF(X6:X9,"<0")*Cadeirante/30*GN$4 -> 0 | GO6: =SUMIF(Z6:Z9,"<0")*Cadeirante/30*GO$4+SUMIF(AB6:AB9,"<0")*Cadeirante/30*GO$4 -> 0 | GP6: =SUMIF(AD6:AD9,"<0")*Cadeirante/30*GP$4+SUMIF(AF6:AF9,"<0")*Cadeirante/30*GP$4 -> 0 | GQ6: =SUMIF(AH6:AH9,"<0")*Cadeirante/30*GQ$4+SUMIF(AJ6:AJ9,"<0")*Cadeirante/30*GQ$4 -> 0 | GR6: =SUMIF(AL6:AL9,"<0")*Cadeirante/30*GR$4+SUMIF(AN6:AN9,"<0")*Cadeirante/30*GR$4 -> 0 | GS6: =SUMIF(AP6:AP9,"<0")*Cadeirante/30*GS$4+SUMIF(AR6:AR9,"<0")*Cadeirante/30*GS$4 -> 0 | GT6: =SUMIF(AT6:AT9,"<0")*Cadeirante/30*GT$4+SUMIF(AV6:AV9,"<0")*Cadeirante/30*GT$4 -> 0 | GU6: =SUMIF(AX6:AX9,"<0")*Cadeirante/30*GU$4+SUMIF(AZ6:AZ9,"<0")*Cadeirante/30*GU$4 -> 0 | GV6: =SUMIF(BB6:BB9,"<0")*Cadeirante/30*GV$4+SUMIF(BD6:BD9,"<0")*Cadeirante/30*GV$4 -> 0 | GW6: =SUMIF(BF6:BF9,"<0")*Cadeirante/30*GW$4+SUMIF(BH6:BH9,"<0")*Cadeirante/30*GW$4 -> 0 | GX6: =SUMIF(BJ6:BJ9,"<0")*Cadeirante/30*GX$4+SUMIF(BL6:BL9,"<0")*Cadeirante/30*GX$4 -> 0 | GY6: =SUMIF(BN6:BN9,"<0")*Cadeirante/30*GY$4+SUMIF(BP6:BP9,"<0")*Cadeirante/30*GY$4 -> 0 | GZ6: =SUMIF(BR6:BR9,"<0")*Cadeirante/30*GZ$4+SUMIF(BT6:BT9,"<0")*Cadeirante/30*GZ$4 -> 0 | HA6: =SUMIF(BV6:BV9,"<0")*Cadeirante/30*HA$4+SUMIF(BX6:BX9,"<0")*Cadeirante/30*HA$4 -> 0 | HB6: =SUMIF(BZ6:BZ9,"<0")*Cadeirante/30*HB$4+SUMIF(CB6:CB9,"<0")*Cadeirante/30*HB$4 -> 0 | HC6: =SUMIF(CD6:CD9,"<0")*Cadeirante/30*HC$4+SUMIF(CF6:CF9,"<0")*Cadeirante/30*HC$4 -> 0 | HD6: =SUMIF(CH6:CH9,"<0")*Cadeirante/30*HD$4+SUMIF(CJ6:CJ9,"<0")*Cadeirante/30*HD$4 -> 0 | HE6: =SUMIF(CL6:CL9,"<0")*Cadeirante/30*HE$4+SUMIF(CN6:CN9,"<0")*Cadeirante/30*HE$4 -> 0 | HF6: =SUMIF(CP6:CP9,"<0")*Cadeirante/30*HF$4+SUMIF(CR6:CR9,"<0")*Cadeirante/30*HF$4 -> 0 | HG6: =SUMIF(CT6:CT9,"<0")*Cadeirante/30*HG$4+SUMIF(CV6:CV9,"<0")*Cadeirante/30*HG$4 -> 0 | HH6: =SUMIF(CX6:CX9,"<0")*Cadeirante/30*HH$4+SUMIF(CZ6:CZ9,"<0")*Cadeirante/30*HH$4 -> 0 | HI6: =SUMIF(DB6:DB9,"<0")*Cadeirante/30*HI$4+SUMIF(DD6:DD9,"<0")*Cadeirante/30*HI$4 -> 0 | HJ6: =SUMIF(DF6:DF9,"<0")*Cadeirante/30*HJ$4+SUMIF(DH6:DH9,"<0")*Cadeirante/30*HJ$4 -> 0 | HK6: =SUMIF(DJ6:DJ9,"<0")*Cadeirante/30*HK$4+SUMIF(DL6:DL9,"<0")*Cadeirante/30*HK$4 -> 0 | HL6: =SUMIF(DN6:DN9,"<0")*Cadeirante/30*HL$4+SUMIF(DP6:DP9,"<0")*Cadeirante/30*HL$4 -> 0 | HM6: =SUMIF(DR6:DR9,"<0")*Cadeirante/30*HM$4+SUMIF(DT6:DT9,"<0")*Cadeirante/30*HM$4 -> 0 | HN6: =SUMIF(DV6:DV9,"<0")*Cadeirante/30*HN$4+SUMIF(DX6:DX9,"<0")*Cadeirante/30*HN$4 -> 0 | HO6: =SUMIF(DZ6:DZ9,"<0")*Cadeirante/30*HO$4+SUMIF(EB6:EB9,"<0")*Cadeirante/30*HO$4 -> 0 | HP6: =SUMIF(ED6:ED9,"<0")*Cadeirante/30*HP$4+SUMIF(EF6:EF9,"<0")*Cadeirante/30*HP$4 -> 0 | HW6: 17629.31 | HY6: =IF(ISTEXT(EM6), VALUE(EM6), EM6) -> 0 | HZ6: =IF(ISTEXT(EN6), VALUE(EN6), EN6) -> 0 | IA6: =IF(ISTEXT(EO6), VALUE(EO6), EO6) -> 0 | IB6: =HW6=FE6 -> FALSE
A7: 028.293-00 | B7: 2024/0058910-001 | C7: BT | D7: 2024/0058910 | E7: EFV2108 | F7: 01/04/2026 | G7: 30/04/2026 | H7: A.C.G. TRANSPORTE ESCOLAR LTDA | I7: ANDREIA PEREIRA DA SILVA | J7: NORMAL | K7: EMEF | L7: =CONTINUA!BV7 -> 46 | M7: =CONTINUA!BW7 -> 0 | O7: 6020.2024/0058910-3 | P7: O | Q7: 49 | CE7: 1 | CY7: 1 | EP7: =Q7 -> 49 | EQ7: =U7+Y7+AC7+AG7+AK7+AO7+AS7+AW7+BA7+BE7+BI7+BM7+BQ7+BU7+BY7+CC7+CG7+CK7+CO7+CS7+CW7+DA7+DE7+DI7+DM7+DQ7+DU7+DY7+EC7+EG7 -> 0 | ER7: =S7+W7+AA7+AE7+AI7+AM7+AQ7+AU7+AY7+BC7+BG7+BK7+BO7+BS7+BW7+CA7+CE7+CI7+CM7+CQ7+CU7+CY7+DC7+DG7+DK7+DO7+DS7+DW7+EA7+EE7+EI7 -> 2 | ES7: =R7 -> 0 | ET7: =V7+Z7+AD7+AH7+AL7+AP7+AT7+AX7+BB7+BF7+BJ7+BN7+BR7+BV7+BZ7+CD7+CH7+CL7+CP7+CT7+CX7+DB7+DF7+DJ7+DN7+DR7+DV7+DZ7+ED7+EH7 -> 0 | EU7: =T7+X7+AB7+AF7+AJ7+AN7+AR7+AV7+AZ7+BD7+BH7+BL7+BP7+BT7+BX7+CB7+CF7+CJ7+CN7+CR7+CV7+CZ7+DD7+DH7+DL7+DP7+DT7+DX7+EB7+EF7+EJ7 -> 0 | EV7: =EP7+EQ7+ES7+ET7+ER7+EU7 -> 51 | EX7: =FF7 -> 0 | EY7: =(L7*regular)+(M7*Cadeirantee) -> 443.44 | EZ7: =SUMIF(FG7:GJ7,">0") -> 0 | FA7: =SUMIF(FG7:GJ7,"<0")+SUMIF(GN7:HP7,"<0") -> 0 | FB7: 0 | FC7: =N7*km*'VALORES TABELA'!$B$13 -> 0 | FD7: =GL7 -> 0 | GL7: =IF(J7="ADAPTADO",T7*Cadeirante/30*GM7+S7*Percapita/30*GM7,IF(J7="NORMAL",(S7+T7)*Percapita/30*GM7,IF(J7="CRECHE",0)))*-1 -> 0 | HY7: =IF(ISTEXT(EM7), VALUE(EM7), EM7) -> 0 | HZ7: =IF(ISTEXT(EN7), VALUE(EN7), EN7) -> 0 | IA7: =IF(ISTEXT(EO7), VALUE(EO7), EO7) -> 0
A8: 028.293-00 | B8: 2024/0058910-001 | C8: BT | D8: 2024/0058910 | E8: EFV2108 | F8: 01/04/2026 | G8: 30/04/2026 | H8: A.C.G. TRANSPORTE ESCOLAR LTDA | I8: ANDREIA PEREIRA DA SILVA | J8: NORMAL | K8: EMEE | L8: =CONTINUA!BV8 -> 0 | M8: =CONTINUA!BW8 -> 0 | O8: 6020.2024/0058910-3 | P8: O | EP8: =Q8 -> 0 | EQ8: =U8+Y8+AC8+AG8+AK8+AO8+AS8+AW8+BA8+BE8+BI8+BM8+BQ8+BU8+BY8+CC8+CG8+CK8+CO8+CS8+CW8+DA8+DE8+DI8+DM8+DQ8+DU8+DY8+EC8+EG8 -> 0 | ER8: =S8+W8+AA8+AE8+AI8+AM8+AQ8+AU8+AY8+BC8+BG8+BK8+BO8+BS8+BW8+CA8+CE8+CI8+CM8+CQ8+CU8+CY8+DC8+DG8+DK8+DO8+DS8+DW8+EA8+EE8+EI8 -> 0 | ES8: =R8 -> 0 | ET8: =V8+Z8+AD8+AH8+AL8+AP8+AT8+AX8+BB8+BF8+BJ8+BN8+BR8+BV8+BZ8+CD8+CH8+CL8+CP8+CT8+CX8+DB8+DF8+DJ8+DN8+DR8+DV8+DZ8+ED8+EH8 -> 0 | EU8: =T8+X8+AB8+AF8+AJ8+AN8+AR8+AV8+AZ8+BD8+BH8+BL8+BP8+BT8+BX8+CB8+CF8+CJ8+CN8+CR8+CV8+CZ8+DD8+DH8+DL8+DP8+DT8+DX8+EB8+EF8+EJ8 -> 0 | EV8: =EP8+EQ8+ES8+ET8+ER8+EU8 -> 0 | EX8: =FF8 -> 0 | EY8: =(L8*regular)+(M8*Cadeirantee) -> 0 | EZ8: =SUMIF(FG8:GJ8,">0") -> 0 | FA8: =SUMIF(FG8:GJ8,"<0")+SUMIF(GN8:HP8,"<0") -> 0 | FB8: 0 | FC8: =N8*km*'VALORES TABELA'!$B$13 -> 0 | FD8: =GL8 -> 0 | GL8: =IF(J8="ADAPTADO",T8*Cadeirante/30*GM8+S8*Percapita/30*GM8,IF(J8="NORMAL",(S8+T8)*Percapita/30*GM8,IF(J8="CRECHE",0)))*-1 -> 0 | HY8: =IF(ISTEXT(EM8), VALUE(EM8), EM8) -> 0 | HZ8: =IF(ISTEXT(EN8), VALUE(EN8), EN8) -> 0 | IA8: =IF(ISTEXT(EO8), VALUE(EO8), EO8) -> 0
A9: 028.293-00 | B9: 2024/0058910-001 | C9: BT | D9: 2024/0058910 | E9: EFV2108 | F9: 01/04/2026 | G9: 30/04/2026 | H9: A.C.G. TRANSPORTE ESCOLAR LTDA | I9: ANDREIA PEREIRA DA SILVA | J9: NORMAL | K9: CEI | L9: =CONTINUA!BV9 -> 0 | M9: =CONTINUA!BW9 -> 0 | O9: 6020.2024/0058910-3 | P9: O | EP9: =Q9 -> 0 | EQ9: =U9+Y9+AC9+AG9+AK9+AO9+AS9+AW9+BA9+BE9+BI9+BM9+BQ9+BU9+BY9+CC9+CG9+CK9+CO9+CS9+CW9+DA9+DE9+DI9+DM9+DQ9+DU9+DY9+EC9+EG9 -> 0 | ER9: =S9+W9+AA9+AE9+AI9+AM9+AQ9+AU9+AY9+BC9+BG9+BK9+BO9+BS9+BW9+CA9+CE9+CI9+CM9+CQ9+CU9+CY9+DC9+DG9+DK9+DO9+DS9+DW9+EA9+EE9+EI9 -> 0 | ES9: =R9 -> 0 | ET9: =V9+Z9+AD9+AH9+AL9+AP9+AT9+AX9+BB9+BF9+BJ9+BN9+BR9+BV9+BZ9+CD9+CH9+CL9+CP9+CT9+CX9+DB9+DF9+DJ9+DN9+DR9+DV9+DZ9+ED9+EH9 -> 0 | EU9: =T9+X9+AB9+AF9+AJ9+AN9+AR9+AV9+AZ9+BD9+BH9+BL9+BP9+BT9+BX9+CB9+CF9+CJ9+CN9+CR9+CV9+CZ9+DD9+DH9+DL9+DP9+DT9+DX9+EB9+EF9+EJ9 -> 0 | EV9: =EP9+EQ9+ES9+ET9+ER9+EU9 -> 0 | EX9: =FF9 -> 0 | EY9: =(L9*regular)+(M9*Cadeirantee) -> 0 | EZ9: =SUMIF(FG9:GJ9,">0") -> 0 | FA9: =SUMIF(FG9:GJ9,"<0")+SUMIF(GN9:HP9,"<0") -> 0 | FB9: 0 | FC9: =N9*km*'VALORES TABELA'!$B$13 -> 0 | FD9: =GL9 -> 0 | GL9: =IF(J9="ADAPTADO",T9*Cadeirante/30*GM9+S9*Percapita/30*GM9,IF(J9="NORMAL",(S9+T9)*Percapita/30*GM9,IF(J9="CRECHE",0)))*-1 -> 0 | HY9: =IF(ISTEXT(EM9), VALUE(EM9), EM9) -> 0 | HZ9: =IF(ISTEXT(EN9), VALUE(EN9), EN9) -> 0 | IA9: =IF(ISTEXT(EO9), VALUE(EO9), EO9) -> 0
A10: 028.293-00 | B10: 2024/0058910-001 | C10: BT | D10: 2024/0058910 | E10: EFV2108 | F10: 01/04/2026 | G10: 30/04/2026 | H10: A.C.G. TRANSPORTE ESCOLAR LTDA | I10: ANDREIA PEREIRA DA SILVA | J10: NORMAL | K10: CCA | L10: =CONTINUA!BV10 -> 0 | M10: =CONTINUA!BW10 -> 0 | O10: 6020.2024/0058910-3 | P10: O | EP10: =Q10 -> 0 | EQ10: =U10+Y10+AC10+AG10+AK10+AO10+AS10+AW10+BA10+BE10+BI10+BM10+BQ10+BU10+BY10+CC10+CG10+CK10+CO10+CS10+CW10+DA10+DE10+DI10+DM10+DQ10+DU10+DY10+EC10+EG10 -> 0 | ER10: =S10+W10+AA10+AE10+AI10+AM10+AQ10+AU10+AY10+BC10+BG10+BK10+BO10+BS10+BW10+CA10+CE10+CI10+CM10+CQ10+CU10+CY10+DC10+DG10+DK10+DO10+DS10+DW10+EA10+EE10+EI10 -> 0 | ES10: =R10 -> 0 | ET10: =V10+Z10+AD10+AH10+AL10+AP10+AT10+AX10+BB10+BF10+BJ10+BN10+BR10+BV10+BZ10+CD10+CH10+CL10+CP10+CT10+CX10+DB10+DF10+DJ10+DN10+DR10+DV10+DZ10+ED10+EH10 -> 0 | EU10: =T10+X10+AB10+AF10+AJ10+AN10+AR10+AV10+AZ10+BD10+BH10+BL10+BP10+BT10+BX10+CB10+CF10+CJ10+CN10+CR10+CV10+CZ10+DD10+DH10+DL10+DP10+DT10+DX10+EB10+EF10+EJ10 -> 0 | EV10: =EP10+EQ10+ES10+ET10+ER10+EU10 -> 0 | EX10: 0 | EY10: 0 | EZ10: 0 | FA10: 0 | FB10: =SUM(FF10:GI10)/2 -> 0 | FC10: =N10*km*'VALORES TABELA'!$B$13 -> 0 | FD10: =GL10 -> 0 | FF10: =((Q10+S10)*Percapita)+((R10+T10)*Cadeirante) -> 0 | FG10: =((U10+W10)*Percapita/30*FG$4)+((V10+X10)*Cadeirante/30*FG$4) -> 0 | FH10: =((Y10+AA10)*Percapita/30*FH$4)+((Z10+AB10)*Cadeirante/30*FH$4) -> 0 | FI10: =((AC10+AE10)*Percapita/30*FI$4)+((AD10+AF10)*Cadeirante/30*FI$4) -> 0 | FJ10: =((AG10+AI10)*Percapita/30*FJ$4)+((AH10+AJ10)*Cadeirante/30*FJ$4) -> 0 | FK10: =((AK10+AM10)*Percapita/30*FK$4)+((AL10+AN10)*Cadeirante/30*FK$4) -> 0 | FL10: =((AO10+AQ10)*Percapita/30*FL$4)+((AP10+AR10)*Cadeirante/30*FL$4) -> 0 | FM10: =((AS10+AU10)*Percapita/30*FM$4)+((AT10+AV10)*Cadeirante/30*FM$4) -> 0 | FN10: =((AW10+AY10)*Percapita/30*FN$4)+((AX10+AZ10)*Cadeirante/30*FN$4) -> 0 | FO10: =((BA10+BC10)*Percapita/30*FO$4)+((BB10+BD10)*Cadeirante/30*FO$4) -> 0 | FP10: =((BE10+BG10)*Percapita/30*FP$4)+((BF10+BH10)*Cadeirante/30*FP$4) -> 0 | FQ10: =((BI10+BK10)*Percapita/30*FQ$4)+((BJ10+BL10)*Cadeirante/30*FQ$4) -> 0 | FR10: =((BM10+BO10)*Percapita/30*FR$4)+((BN10+BP10)*Cadeirante/30*FR$4) -> 0 | FS10: =((BQ10+BS10)*Percapita/30*FS$4)+((BR10+BT10)*Cadeirante/30*FS$4) -> 0 | FT10: =((BU10+BW10)*Percapita/30*FT$4)+((BV10+BX10)*Cadeirante/30*FT$4) -> 0 | FU10: =((BY10+CA10)*Percapita/30*FU$4)+((BZ10+CB10)*Cadeirante/30*FU$4) -> 0 | FV10: =((CC10+CE10)*Percapita/30*FV$4)+((CD10+CF10)*Cadeirante/30*FV$4) -> 0 | FW10: =((CG10+CI10)*Percapita/30*FW$4)+((CI10+CK10)*Cadeirante/30*FW$4) -> 0 | FX10: =((CK10+CM10)*Percapita/30*FX$4)+((CL10+CN10)*Cadeirante/30*FX$4) -> 0 | FY10: =((CO10+CQ10)*Percapita/30*FY$4)+((CP10+CR10)*Cadeirante/30*FY$4) -> 0 | FZ10: =((CS10+CU10)*Percapita/30*FZ$4)+((CT10+CV10)*Cadeirante/30*FZ$4) -> 0 | GA10: =((CW10+CY10)*Percapita/30*GA$4)+((CX10+CZ10)*Cadeirante/30*GA$4) -> 0 | GB10: =((DA10+DC10)*Percapita/30*GB$4)+((DB10+DD10)*Cadeirante/30*GB$4) -> 0 | GC10: =((DE10+DG10)*Percapita/30*GC$4)+((DF10+DH10)*Cadeirante/30*GC$4) -> 0 | GD10: =((DI10+DK10)*Percapita/30*GD$4)+((DJ10+DL10)*Cadeirante/30*GD$4) -> 0 | GE10: =((DM10+DO10)*Percapita/30*GE$4)+((DN10+DP10)*Cadeirante/30*GE$4) -> 0 | GF10: =((DQ10+DS10)*Percapita/30*GF$4)+((DR10+DT10)*Cadeirante/30*GF$4) -> 0 | GG10: =((DU10+DW10)*Percapita/30*GG$4)+((DV10+DX10)*Cadeirante/30*GG$4) -> 0 | GH10: =((DY10+EA10)*Percapita/30*GH$4)+((DZ10+EB10)*Cadeirante/30*GH$4) -> 0 | GI10: =((EC10+EE10)*Percapita/30*GI$4)+((ED10+EF10)*Cadeirante/30*GI$4) -> 0 | GJ10: =((EG10+EI10)*Percapita)+((EH10+EJ10)*Cadeirante) -> 0 | GL10: =IF(J10="ADAPTADO",T10*Cadeirante/30*GM10+S10*Percapita/30*GM10,IF(J10="NORMAL",(S10+T10)*Percapita/30*GM10,IF(J10="CRECHE",0)))*-1 -> 0 | HY10: =IF(ISTEXT(EM10), VALUE(EM10), EM10) -> 0 | HZ10: =IF(ISTEXT(EN10), VALUE(EN10), EN10) -> 0 | IA10: =IF(ISTEXT(EO10), VALUE(EO10), EO10) -> 0
A11: 048.924-00 | B11: 2023/0009598-002B | C11: 1 | D11: 2023/0009598 | E11: EKL2866 | F11: 01/04/2026 | G11: 30/04/2026 | H11: A.C.G. TRANSPORTE ESCOLAR LTDA | I11: JOSE CARLOS FONTELES DA SILVA | J11: NORMAL | K11: EMEI | L11: =CONTINUA!BV11 -> 0 | M11: =CONTINUA!BW11 -> 0 | O11: 6020.2023/0009598-2 | P11: O | EP11: =Q11 -> 0 | EQ11: =U11+Y11+AC11+AG11+AK11+AO11+AS11+AW11+BA11+BE11+BI11+BM11+BQ11+BU11+BY11+CC11+CG11+CK11+CO11+CS11+CW11+DA11+DE11+DI11+DM11+DQ11+DU11+DY11+EC11+EG11 -> 0 | ER11: =S11+W11+AA11+AE11+AI11+AM11+AQ11+AU11+AY11+BC11+BG11+BK11+BO11+BS11+BW11+CA11+CE11+CI11+CM11+CQ11+CU11+CY11+DC11+DG11+DK11+DO11+DS11+DW11+EA11+EE11+EI11 -> 0 | ES11: =R11 -> 0 | ET11: =V11+Z11+AD11+AH11+AL11+AP11+AT11+AX11+BB11+BF11+BJ11+BN11+BR11+BV11+BZ11+CD11+CH11+CL11+CP11+CT11+CX11+DB11+DF11+DJ11+DN11+DR11+DV11+DZ11+ED11+EH11 -> 0 | EU11: =T11+X11+AB11+AF11+AJ11+AN11+AR11+AV11+AZ11+BD11+BH11+BL11+BP11+BT11+BX11+CB11+CF11+CJ11+CN11+CR11+CV11+CZ11+DD11+DH11+DL11+DP11+DT11+DX11+EB11+EF11+EJ11 -> 0 | EV11: =EP11+EQ11+ES11+ET11+ER11+EU11 -> 0 | EW11: =IF(C11=4,IF(MAX(Q11:EJ13)>0,(Especiall/30*(IF(($G11-$F11)=($G$5-$F$5),30,IF(DAY($G11)=31,($G11-$F11),($G11-$F11)+1)))),0),0) -> 0 | EX11: =FF11 -> 19819.88 | EY11: =(L11*regular)+(M11*Cadeirantee) -> 0 | EZ11: =SUMIF(FG11:GJ11,">0") -> 179.774 | FA11: =SUMIF(FG11:GJ11,"<0")+SUMIF(GN11:HP11,"<0") -> 0 | FB11: 0 | FC11: =N11*km*'VALORES TABELA'!$B$13 -> 0 | FD11: =GL11 -> 0 | FE11: =(EW11+EW12+EW13+EW14+EX11+EX12+EX13+EX14+EY11+EY12+EY13+EY14+EY15+EZ11+EZ12+EZ13+EZ14+FA11+FA12+FA13+FA14+FC11+FC12+FC13+FC14+HY11-HZ11-IA11+FD11+FD12+FD13+FD14+FB15) -> 20067.134 | FF11: =IF(C11=4,SUM(Q11+Q12+Q13+S11+S12+S13)*Percapita/30*FF$4+(R11+R12+R13+T11+T12+T13)*Cadeirante/30*FF$4,IF(C11=3,IF(Q14+S14=10,Fixo/30*FF$4+(Q11+Q12+Q13+S11+S12+S13)*Percapita/30*FF$4+(R14+T14)*Cadeirante/30*FF$4,IF(Q14+S14<=9,(Q14+S14)*Crechee/30*FF$4)+(R14+T14)*Cadeirante/30*FF$4+(Q11+Q12+Q13+S11+S12+S13)*Percapita/30*FF$4)+IF(Q14+S14>=11,Fixo/30*FF$4+(Q14+S14-10)*Crechee/30*FF$4,0),IF(C11=2,IF(R11+R12+R13+R14+T11+T12+T13+T14=1,Cadeirante/30*FF$4,IF(R11+R12+R13+R14+T11+T12+T13+T14=2,Fixo/30*FF$4,IF(R11+R12+R13+R14+T11+T12+T13+T14>2,Fixo/30*FF$4+(R11+R12+R13+R14+T11+T12+T13+T14-2)*Cadeirante/30*FF$4)))+(Q11+Q12+Q13+S11+S12+S13)*Percapita/30*FF$4+(Q14+S14)*Crechee/30*FF$4,IF(C11=1,IF(Q11+Q12+Q13+R11+R12+R13+S11+S12+S13+T11+T12+T13<=15,(Q11+Q12+Q13+S11+S12+S13)*Percapita/30*FF$4,IF(Q11+Q12+Q13+R11+R12+R13+S11+S12+S13+T11+T12+T13>=16,Fixo/30*FF$4+(Q11+Q12+Q13+R11+R12+R13+S11+S12+S13+T11+T12-16)*Percapita/30*FF$4)))))) -> 19819.88 | FG11: =IF(C11=4,SUM(U11+U12+U13+W11+W12+W13)*Percapita/30*FG$4+(V11+V12+V13+X11+X12+X13)*Cadeirante/30*FG$4,IF(C11=3,IF(U14+W14=10,Fixo/30*FG$4+(U11+U12+U13+W11+W12+W13)*Percapita/30*FG$4+(V14+X14)*Cadeirante/30*FG$4,IF(U14+W14<=9,(U14+W14)*Crechee/30*FG$4)+(V14+X14)*Cadeirante/30*FG$4+(U11+U12+U13+W11+W12+W13)*Percapita/30*FG$4)+IF(U14+W14>=11,Fixo/30*FG$4+(U14+W14-10)*Crechee/30*FG$4,0),IF(C11=2,IF(V11+V12+V13+V14+X11+X12+X13+X14=1,Cadeirante/30*FG$4,IF(V11+V12+V13+V14+X11+X12+X13+X14=2,Fixo/30*FG$4,IF(V11+V12+V13+V14+X11+X12+X13+X14>2,Fixo/30*FG$4+(V11+V12+V13+V14+X11+X12+X13+X14-2)*Cadeirante/30*FG$4)))+(U11+U12+U13+W11+W12+W13)*Percapita/30*FG$4+(U14+W14)*Crechee/30*FG$4,IF(C11=1,IF(U11+U12+U13+V11+V12+V13+W11+W12+W13+X11+X12+X13<=15,(U11+U12+U13+W11+W12+W13)*Percapita/30*FG$4,IF(U11+U12+U13+V11+V12+V13+W11+W12+W13+X11+X12+X13>=16,Fixo/30*FG$4+(U11+U12+U13+V11+V12+V13+W11+W12+W13+X11+X12-16)*Percapita/30*FG$4)))))) -> 0 | FH11: =IF(C11=4,SUM(Y11+Y12+Y13+AA11+AA12+AA13)*Percapita/30*FH$4+(Z11+Z12+Z13+AB11+AB12+AB13)*Cadeirante/30*FH$4,IF(C11=3,IF(Y14+AA14=10,Fixo/30*FH$4+(Y11+Y12+Y13+AA11+AA12+AA13)*Percapita/30*FH$4+(Z14+AB14)*Cadeirante/30*FH$4,IF(Y14+AA14<=9,(Y14+AA14)*Crechee/30*FH$4)+(Z14+AB14)*Cadeirante/30*FH$4+(Y11+Y12+Y13+AA11+AA12+AA13)*Percapita/30*FH$4)+IF(Y14+AA14>=11,Fixo/30*FH$4+(Y14+AA14-10)*Crechee/30*FH$4,0),IF(C11=2,IF(Z11+Z12+Z13+Z14+AB11+AB12+AB13+AB14=1,Cadeirante/30*FH$4,IF(Z11+Z12+Z13+Z14+AB11+AB12+AB13+AB14=2,Fixo/30*FH$4,IF(Z11+Z12+Z13+Z14+AB11+AB12+AB13+AB14>2,Fixo/30*FH$4+(Z11+Z12+Z13+Z14+AB11+AB12+AB13+AB14-2)*Cadeirante/30*FH$4)))+(Y11+Y12+Y13+AA11+AA12+AA13)*Percapita/30*FH$4+(Y14+AA14)*Crechee/30*FH$4,IF(C11=1,IF(Y11+Y12+Y13+Z11+Z12+Z13+AA11+AA12+AA13+AB11+AB12+AB13<=15,(Y11+Y12+Y13+AA11+AA12+AA13)*Percapita/30*FH$4,IF(Y11+Y12+Y13+Z11+Z12+Z13+AA11+AA12+AA13+AB11+AB12+AB13>=16,Fixo/30*FH$4+(Y11+Y12+Y13+Z11+Z12+Z13+AA11+AA12+AA13+AB11+AB12-16)*Percapita/30*FH$4)))))) -> 0 | FI11: =IF(C11=4,SUM(AC11+AC12+AC13+AE11+AE12+AE13)*Percapita/30*FI$4+(AD11+AD12+AD13+AF11+AF12+AF13)*Cadeirante/30*FI$4,IF(C11=3,IF(AC14+AE14=10,Fixo/30*FI$4+(AC11+AC12+AC13+AE11+AE12+AE13)*Percapita/30*FI$4+(AD14+AF14)*Cadeirante/30*FI$4,IF(AC14+AE14<=9,(AC14+AE14)*Crechee/30*FI$4)+(AD14+AF14)*Cadeirante/30*FI$4+(AC11+AC12+AC13+AE11+AE12+AE13)*Percapita/30*FI$4)+IF(AC14+AE14>=11,Fixo/30*FI$4+(AC14+AE14-10)*Crechee/30*FI$4,0),IF(C11=2,IF(AD11+AD12+AD13+AD14+AF11+AF12+AF13+AF14=1,Cadeirante/30*FI$4,IF(AD11+AD12+AD13+AD14+AF11+AF12+AF13+AF14=2,Fixo/30*FI$4,IF(AD11+AD12+AD13+AD14+AF11+AF12+AF13+AF14>2,Fixo/30*FI$4+(AD11+AD12+AD13+AD14+AF11+AF12+AF13+AF14-2)*Cadeirante/30*FI$4)))+(AC11+AC12+AC13+AE11+AE12+AE13)*Percapita/30*FI$4+(AC14+AE14)*Crechee/30*FI$4,IF(C11=1,IF(AC11+AC12+AC13+AD11+AD12+AD13+AE11+AE12+AE13+AF11+AF12+AF13<=15,(AC11+AC12+AC13+AE11+AE12+AE13)*Percapita/30*FI$4,IF(AC11+AC12+AC13+AD11+AD12+AD13+AE11+AE12+AE13+AF11+AF12+AF13>=16,Fixo/30*FI$4+(AC11+AC12+AC13+AD11+AD12+AD13+AE11+AE12+AE13+AF11+AF12-16)*Percapita/30*FI$4)))))) -> 0 | FJ11: =IF(C11=4,SUM(AG11+AG12+AG13+AI11+AI12+AI13)*Percapita/30*FJ$4+(AH11+AH12+AH13+AJ11+AJ12+AJ13)*Cadeirante/30*FJ$4,IF(C11=3,IF(AG14+AI14=10,Fixo/30*FJ$4+(AG11+AG12+AG13+AI11+AI12+AI13)*Percapita/30*FJ$4+(AH14+AJ14)*Cadeirante/30*FJ$4,IF(AG14+AI14<=9,(AG14+AI14)*Crechee/30*FJ$4)+(AH14+AJ14)*Cadeirante/30*FJ$4+(AG11+AG12+AG13+AI11+AI12+AI13)*Percapita/30*FJ$4)+IF(AG14+AI14>=11,Fixo/30*FJ$4+(AG14+AI14-10)*Crechee/30*FJ$4,0),IF(C11=2,IF(AH11+AH12+AH13+AH14+AJ11+AJ12+AJ13+AJ14=1,Cadeirante/30*FJ$4,IF(AH11+AH12+AH13+AH14+AJ11+AJ12+AJ13+AJ14=2,Fixo/30*FJ$4,IF(AH11+AH12+AH13+AH14+AJ11+AJ12+AJ13+AJ14>2,Fixo/30*FJ$4+(AH11+AH12+AH13+AH14+AJ11+AJ12+AJ13+AJ14-2)*Cadeirante/30*FJ$4)))+(AG11+AG12+AG13+AI11+AI12+AI13)*Percapita/30*FJ$4+(AG14+AI14)*Crechee/30*FJ$4,IF(C11=1,IF(AG11+AG12+AG13+AH11+AH12+AH13+AI11+AI12+AI13+AJ11+AJ12+AJ13<=15,(AG11+AG12+AG13+AI11+AI12+AI13)*Percapita/30*FJ$4,IF(AG11+AG12+AG13+AH11+AH12+AH13+AI11+AI12+AI13+AJ11+AJ12+AJ13>=16,Fixo/30*FJ$4+(AG11+AG12+AG13+AH11+AH12+AH13+AI11+AI12+AI13+AJ11+AJ12-16)*Percapita/30*FJ$4)))))) -> 0 | FK11: =IF(C11=4,SUM(AK11+AK12+AK13+AM11+AM12+AM13)*Percapita/30*FK$4+(AL11+AL12+AL13+AN11+AN12+AN13)*Cadeirante/30*FK$4,IF(C11=3,IF(AK14+AM14=10,Fixo/30*FK$4+(AK11+AK12+AK13+AM11+AM12+AM13)*Percapita/30*FK$4+(AL14+AN14)*Cadeirante/30*FK$4,IF(AK14+AM14<=9,(AK14+AM14)*Crechee/30*FK$4)+(AL14+AN14)*Cadeirante/30*FK$4+(AK11+AK12+AK13+AM11+AM12+AM13)*Percapita/30*FK$4)+IF(AK14+AM14>=11,Fixo/30*FK$4+(AK14+AM14-10)*Crechee/30*FK$4,0),IF(C11=2,IF(AL11+AL12+AL13+AL14+AN11+AN12+AN13+AN14=1,Cadeirante/30*FK$4,IF(AL11+AL12+AL13+AL14+AN11+AN12+AN13+AN14=2,Fixo/30*FK$4,IF(AL11+AL12+AL13+AL14+AN11+AN12+AN13+AN14>2,Fixo/30*FK$4+(AL11+AL12+AL13+AL14+AN11+AN12+AN13+AN14-2)*Cadeirante/30*FK$4)))+(AK11+AK12+AK13+AM11+AM12+AM13)*Percapita/30*FK$4+(AK14+AM14)*Crechee/30*FK$4,IF(C11=1,IF(AK11+AK12+AK13+AL11+AL12+AL13+AM11+AM12+AM13+AN11+AN12+AN13<=15,(AK11+AK12+AK13+AM11+AM12+AM13)*Percapita/30*FK$4,IF(AK11+AK12+AK13+AL11+AL12+AL13+AM11+AM12+AM13+AN11+AN12+AN13>=16,Fixo/30*FK$4+(AK11+AK12+AK13+AL11+AL12+AL13+AM11+AM12+AM13+AN11+AN12-16)*Percapita/30*FK$4)))))) -> 0 | FL11: =IF(C11=4,SUM(AO11+AO12+AO13+AQ11+AQ12+AQ13)*Percapita/30*FL$4+(AP11+AP12+AP13+AR11+AR12+AR13)*Cadeirante/30*FL$4,IF(C11=3,IF(AO14+AQ14=10,Fixo/30*FL$4+(AO11+AO12+AO13+AQ11+AQ12+AQ13)*Percapita/30*FL$4+(AP14+AR14)*Cadeirante/30*FL$4,IF(AO14+AQ14<=9,(AO14+AQ14)*Crechee/30*FL$4)+(AP14+AR14)*Cadeirante/30*FL$4+(AO11+AO12+AO13+AQ11+AQ12+AQ13)*Percapita/30*FL$4)+IF(AO14+AQ14>=11,Fixo/30*FL$4+(AO14+AQ14-10)*Crechee/30*FL$4,0),IF(C11=2,IF(AP11+AP12+AP13+AP14+AR11+AR12+AR13+AR14=1,Cadeirante/30*FL$4,IF(AP11+AP12+AP13+AP14+AR11+AR12+AR13+AR14=2,Fixo/30*FL$4,IF(AP11+AP12+AP13+AP14+AR11+AR12+AR13+AR14>2,Fixo/30*FL$4+(AP11+AP12+AP13+AP14+AR11+AR12+AR13+AR14-2)*Cadeirante/30*FL$4)))+(AO11+AO12+AO13+AQ11+AQ12+AQ13)*Percapita/30*FL$4+(AO14+AQ14)*Crechee/30*FL$4,IF(C11=1,IF(AO11+AO12+AO13+AP11+AP12+AP13+AQ11+AQ12+AQ13+AR11+AR12+AR13<=15,(AO11+AO12+AO13+AQ11+AQ12+AQ13)*Percapita/30*FL$4,IF(AO11+AO12+AO13+AP11+AP12+AP13+AQ11+AQ12+AQ13+AR11+AR12+AR13>=16,Fixo/30*FL$4+(AO11+AO12+AO13+AP11+AP12+AP13+AQ11+AQ12+AQ13+AR11+AR12-16)*Percapita/30*FL$4)))))) -> 0 | FM11: =IF(C11=4,SUM(AS11+AS12+AS13+AU11+AU12+AU13)*Percapita/30*FM$4+(AT11+AT12+AT13+AV11+AV12+AV13)*Cadeirante/30*FM$4,IF(C11=3,IF(AS14+AU14=10,Fixo/30*FM$4+(AS11+AS12+AS13+AU11+AU12+AU13)*Percapita/30*FM$4+(AT14+AV14)*Cadeirante/30*FM$4,IF(AS14+AU14<=9,(AS14+AU14)*Crechee/30*FM$4)+(AT14+AV14)*Cadeirante/30*FM$4+(AS11+AS12+AS13+AU11+AU12+AU13)*Percapita/30*FM$4)+IF(AS14+AU14>=11,Fixo/30*FM$4+(AS14+AU14-10)*Crechee/30*FM$4,0),IF(C11=2,IF(AT11+AT12+AT13+AT14+AV11+AV12+AV13+AV14=1,Cadeirante/30*FM$4,IF(AT11+AT12+AT13+AT14+AV11+AV12+AV13+AV14=2,Fixo/30*FM$4,IF(AT11+AT12+AT13+AT14+AV11+AV12+AV13+AV14>2,Fixo/30*FM$4+(AT11+AT12+AT13+AT14+AV11+AV12+AV13+AV14-2)*Cadeirante/30*FM$4)))+(AS11+AS12+AS13+AU11+AU12+AU13)*Percapita/30*FM$4+(AS14+AU14)*Crechee/30*FM$4,IF(C11=1,IF(AS11+AS12+AS13+AT11+AT12+AT13+AU11+AU12+AU13+AV11+AV12+AV13<=15,(AS11+AS12+AS13+AU11+AU12+AU13)*Percapita/30*FM$4,IF(AS11+AS12+AS13+AT11+AT12+AT13+AU11+AU12+AU13+AV11+AV12+AV13>=16,Fixo/30*FM$4+(AS11+AS12+AS13+AT11+AT12+AT13+AU11+AU12+AU13+AV11+AV12-16)*Percapita/30*FM$4)))))) -> 0 | FN11: =IF(C11=4,SUM(AW11+AW12+AW13+AY11+AY12+AY13)*Percapita/30*FN$4+(AX11+AX12+AX13+AZ11+AZ12+AZ13)*Cadeirante/30*FN$4,IF(C11=3,IF(AW14+AY14=10,Fixo/30*FN$4+(AW11+AW12+AW13+AY11+AY12+AY13)*Percapita/30*FN$4+(AX14+AZ14)*Cadeirante/30*FN$4,IF(AW14+AY14<=9,(AW14+AY14)*Crechee/30*FN$4)+(AX14+AZ14)*Cadeirante/30*FN$4+(AW11+AW12+AW13+AY11+AY12+AY13)*Percapita/30*FN$4)+IF(AW14+AY14>=11,Fixo/30*FN$4+(AW14+AY14-10)*Crechee/30*FN$4,0),IF(C11=2,IF(AX11+AX12+AX13+AX14+AZ11+AZ12+AZ13+AZ14=1,Cadeirante/30*FN$4,IF(AX11+AX12+AX13+AX14+AZ11+AZ12+AZ13+AZ14=2,Fixo/30*FN$4,IF(AX11+AX12+AX13+AX14+AZ11+AZ12+AZ13+AZ14>2,Fixo/30*FN$4+(AX11+AX12+AX13+AX14+AZ11+AZ12+AZ13+AZ14-2)*Cadeirante/30*FN$4)))+(AW11+AW12+AW13+AY11+AY12+AY13)*Percapita/30*FN$4+(AW14+AY14)*Crechee/30*FN$4,IF(C11=1,IF(AW11+AW12+AW13+AX11+AX12+AX13+AY11+AY12+AY13+AZ11+AZ12+AZ13<=15,(AW11+AW12+AW13+AY11+AY12+AY13)*Percapita/30*FN$4,IF(AW11+AW12+AW13+AX11+AX12+AX13+AY11+AY12+AY13+AZ11+AZ12+AZ13>=16,Fixo/30*FN$4+(AW11+AW12+AW13+AX11+AX12+AX13+AY11+AY12+AY13+AZ11+AZ12-16)*Percapita/30*FN$4)))))) -> 0 | FO11: =IF(C11=4,SUM(BA11+BA12+BA13+BC11+BC12+BC13)*Percapita/30*FO$4+(BB11+BB12+BB13+BD11+BD12+BD13)*Cadeirante/30*FO$4,IF(C11=3,IF(BA14+BC14=10,Fixo/30*FO$4+(BA11+BA12+BA13+BC11+BC12+BC13)*Percapita/30*FO$4+(BB14+BD14)*Cadeirante/30*FO$4,IF(BA14+BC14<=9,(BA14+BC14)*Crechee/30*FO$4)+(BB14+BD14)*Cadeirante/30*FO$4+(BA11+BA12+BA13+BC11+BC12+BC13)*Percapita/30*FO$4)+IF(BA14+BC14>=11,Fixo/30*FO$4+(BA14+BC14-10)*Crechee/30*FO$4,0),IF(C11=2,IF(BB11+BB12+BB13+BB14+BD11+BD12+BD13+BD14=1,Cadeirante/30*FO$4,IF(BB11+BB12+BB13+BB14+BD11+BD12+BD13+BD14=2,Fixo/30*FO$4,IF(BB11+BB12+BB13+BB14+BD11+BD12+BD13+BD14>2,Fixo/30*FO$4+(BB11+BB12+BB13+BB14+BD11+BD12+BD13+BD14-2)*Cadeirante/30*FO$4)))+(BA11+BA12+BA13+BC11+BC12+BC13)*Percapita/30*FO$4+(BA14+BC14)*Crechee/30*FO$4,IF(C11=1,IF(BA11+BA12+BA13+BB11+BB12+BB13+BC11+BC12+BC13+BD11+BD12+BD13<=15,(BA11+BA12+BA13+BC11+BC12+BC13)*Percapita/30*FO$4,IF(BA11+BA12+BA13+BB11+BB12+BB13+BC11+BC12+BC13+BD11+BD12+BD13>=16,Fixo/30*FO$4+(BA11+BA12+BA13+BB11+BB12+BB13+BC11+BC12+BC13+BD11+BD12-16)*Percapita/30*FO$4)))))) -> 0 | FP11: =IF(C11=4,SUM(BE11+BE12+BE13+BG11+BG12+BG13)*Percapita/30*FP$4+(BF11+BF12+BF13+BH11+BH12+BH13)*Cadeirante/30*FP$4,IF(C11=3,IF(BE14+BG14=10,Fixo/30*FP$4+(BE11+BE12+BE13+BG11+BG12+BG13)*Percapita/30*FP$4+(BF14+BH14)*Cadeirante/30*FP$4,IF(BE14+BG14<=9,(BE14+BG14)*Crechee/30*FP$4)+(BF14+BH14)*Cadeirante/30*FP$4+(BE11+BE12+BE13+BG11+BG12+BG13)*Percapita/30*FP$4)+IF(BE14+BG14>=11,Fixo/30*FP$4+(BE14+BG14-10)*Crechee/30*FP$4,0),IF(C11=2,IF(BF11+BF12+BF13+BF14+BH11+BH12+BH13+BH14=1,Cadeirante/30*FP$4,IF(BF11+BF12+BF13+BF14+BH11+BH12+BH13+BH14=2,Fixo/30*FP$4,IF(BF11+BF12+BF13+BF14+BH11+BH12+BH13+BH14>2,Fixo/30*FP$4+(BF11+BF12+BF13+BF14+BH11+BH12+BH13+BH14-2)*Cadeirante/30*FP$4)))+(BE11+BE12+BE13+BG11+BG12+BG13)*Percapita/30*FP$4+(BE14+BG14)*Crechee/30*FP$4,IF(C11=1,IF(BE11+BE12+BE13+BF11+BF12+BF13+BG11+BG12+BG13+BH11+BH12+BH13<=15,(BE11+BE12+BE13+BG11+BG12+BG13)*Percapita/30*FP$4,IF(BE11+BE12+BE13+BF11+BF12+BF13+BG11+BG12+BG13+BH11+BH12+BH13>=16,Fixo/30*FP$4+(BE11+BE12+BE13+BF11+BF12+BF13+BG11+BG12+BG13+BH11+BH12-16)*Percapita/30*FP$4)))))) -> 0 | FQ11: =IF(C11=4,SUM(BI11+BI12+BI13+BK11+BK12+BK13)*Percapita/30*FQ$4+(BJ11+BJ12+BJ13+BL11+BL12+BL13)*Cadeirante/30*FQ$4,IF(C11=3,IF(BI14+BK14=10,Fixo/30*FQ$4+(BI11+BI12+BI13+BK11+BK12+BK13)*Percapita/30*FQ$4+(BJ14+BL14)*Cadeirante/30*FQ$4,IF(BI14+BK14<=9,(BI14+BK14)*Crechee/30*FQ$4)+(BJ14+BL14)*Cadeirante/30*FQ$4+(BI11+BI12+BI13+BK11+BK12+BK13)*Percapita/30*FQ$4)+IF(BI14+BK14>=11,Fixo/30*FQ$4+(BI14+BK14-10)*Crechee/30*FQ$4,0),IF(C11=2,IF(BJ11+BJ12+BJ13+BJ14+BL11+BL12+BL13+BL14=1,Cadeirante/30*FQ$4,IF(BJ11+BJ12+BJ13+BJ14+BL11+BL12+BL13+BL14=2,Fixo/30*FQ$4,IF(BJ11+BJ12+BJ13+BJ14+BL11+BL12+BL13+BL14>2,Fixo/30*FQ$4+(BJ11+BJ12+BJ13+BJ14+BL11+BL12+BL13+BL14-2)*Cadeirante/30*FQ$4)))+(BI11+BI12+BI13+BK11+BK12+BK13)*Percapita/30*FQ$4+(BI14+BK14)*Crechee/30*FQ$4,IF(C11=1,IF(BI11+BI12+BI13+BJ11+BJ12+BJ13+BK11+BK12+BK13+BL11+BL12+BL13<=15,(BI11+BI12+BI13+BK11+BK12+BK13)*Percapita/30*FQ$4,IF(BI11+BI12+BI13+BJ11+BJ12+BJ13+BK11+BK12+BK13+BL11+BL12+BL13>=16,Fixo/30*FQ$4+(BI11+BI12+BI13+BJ11+BJ12+BJ13+BK11+BK12+BK13+BL11+BL12-16)*Percapita/30*FQ$4)))))) -> 0 | FR11: =IF(C11=4,SUM(BM11+BM12+BM13+BO11+BO12+BO13)*Percapita/30*FR$4+(BN11+BN12+BN13+BP11+BP12+BP13)*Cadeirante/30*FR$4,IF(C11=3,IF(BM14+BO14=10,Fixo/30*FR$4+(BM11+BM12+BM13+BO11+BO12+BO13)*Percapita/30*FR$4+(BN14+BP14)*Cadeirante/30*FR$4,IF(BM14+BO14<=9,(BM14+BO14)*Crechee/30*FR$4)+(BN14+BP14)*Cadeirante/30*FR$4+(BM11+BM12+BM13+BO11+BO12+BO13)*Percapita/30*FR$4)+IF(BM14+BO14>=11,Fixo/30*FR$4+(BM14+BO14-10)*Crechee/30*FR$4,0),IF(C11=2,IF(BN11+BN12+BN13+BN14+BP11+BP12+BP13+BP14=1,Cadeirante/30*FR$4,IF(BN11+BN12+BN13+BN14+BP11+BP12+BP13+BP14=2,Fixo/30*FR$4,IF(BN11+BN12+BN13+BN14+BP11+BP12+BP13+BP14>2,Fixo/30*FR$4+(BN11+BN12+BN13+BN14+BP11+BP12+BP13+BP14-2)*Cadeirante/30*FR$4)))+(BM11+BM12+BM13+BO11+BO12+BO13)*Percapita/30*FR$4+(BM14+BO14)*Crechee/30*FR$4,IF(C11=1,IF(BM11+BM12+BM13+BN11+BN12+BN13+BO11+BO12+BO13+BP11+BP12+BP13<=15,(BM11+BM12+BM13+BO11+BO12+BO13)*Percapita/30*FR$4,IF(BM11+BM12+BM13+BN11+BN12+BN13+BO11+BO12+BO13+BP11+BP12+BP13>=16,Fixo/30*FR$4+(BM11+BM12+BM13+BN11+BN12+BN13+BO11+BO12+BO13+BP11+BP12-16)*Percapita/30*FR$4)))))) -> 0 | FS11: =IF(C11=4,SUM(BQ11+BQ12+BQ13+BS11+BS12+BS13)*Percapita/30*FS$4+(BR11+BR12+BR13+BT11+BT12+BT13)*Cadeirante/30*FS$4,IF(C11=3,IF(BQ14+BS14=10,Fixo/30*FS$4+(BQ11+BQ12+BQ13+BS11+BS12+BS13)*Percapita/30*FS$4+(BR14+BT14)*Cadeirante/30*FS$4,IF(BQ14+BS14<=9,(BQ14+BS14)*Crechee/30*FS$4)+(BR14+BT14)*Cadeirante/30*FS$4+(BQ11+BQ12+BQ13+BS11+BS12+BS13)*Percapita/30*FS$4)+IF(BQ14+BS14>=11,Fixo/30*FS$4+(BQ14+BS14-10)*Crechee/30*FS$4,0),IF(C11=2,IF(BR11+BR12+BR13+BR14+BT11+BT12+BT13+BT14=1,Cadeirante/30*FS$4,IF(BR11+BR12+BR13+BR14+BT11+BT12+BT13+BT14=2,Fixo/30*FS$4,IF(BR11+BR12+BR13+BR14+BT11+BT12+BT13+BT14>2,Fixo/30*FS$4+(BR11+BR12+BR13+BR14+BT11+BT12+BT13+BT14-2)*Cadeirante/30*FS$4)))+(BQ11+BQ12+BQ13+BS11+BS12+BS13)*Percapita/30*FS$4+(BQ14+BS14)*Crechee/30*FS$4,IF(C11=1,IF(BQ11+BQ12+BQ13+BR11+BR12+BR13+BS11+BS12+BS13+BT11+BT12+BT13<=15,(BQ11+BQ12+BQ13+BS11+BS12+BS13)*Percapita/30*FS$4,IF(BQ11+BQ12+BQ13+BR11+BR12+BR13+BS11+BS12+BS13+BT11+BT12+BT13>=16,Fixo/30*FS$4+(BQ11+BQ12+BQ13+BR11+BR12+BR13+BS11+BS12+BS13+BT11+BT12-16)*Percapita/30*FS$4)))))) -> 0 | FT11: =IF(C11=4,SUM(BU11+BU12+BU13+BW11+BW12+BW13)*Percapita/30*FT$4+(BV11+BV12+BV13+BX11+BX12+BX13)*Cadeirante/30*FT$4,IF(C11=3,IF(BU14+BW14=10,Fixo/30*FT$4+(BU11+BU12+BU13+BW11+BW12+BW13)*Percapita/30*FT$4+(BV14+BX14)*Cadeirante/30*FT$4,IF(BU14+BW14<=9,(BU14+BW14)*Crechee/30*FT$4)+(BV14+BX14)*Cadeirante/30*FT$4+(BU11+BU12+BU13+BW11+BW12+BW13)*Percapita/30*FT$4)+IF(BU14+BW14>=11,Fixo/30*FT$4+(BU14+BW14-10)*Crechee/30*FT$4,0),IF(C11=2,IF(BV11+BV12+BV13+BV14+BX11+BX12+BX13+BX14=1,Cadeirante/30*FT$4,IF(BV11+BV12+BV13+BV14+BX11+BX12+BX13+BX14=2,Fixo/30*FT$4,IF(BV11+BV12+BV13+BV14+BX11+BX12+BX13+BX14>2,Fixo/30*FT$4+(BV11+BV12+BV13+BV14+BX11+BX12+BX13+BX14-2)*Cadeirante/30*FT$4)))+(BU11+BU12+BU13+BW11+BW12+BW13)*Percapita/30*FT$4+(BU14+BW14)*Crechee/30*FT$4,IF(C11=1,IF(BU11+BU12+BU13+BV11+BV12+BV13+BW11+BW12+BW13+BX11+BX12+BX13<=15,(BU11+BU12+BU13+BW11+BW12+BW13)*Percapita/30*FT$4,IF(BU11+BU12+BU13+BV11+BV12+BV13+BW11+BW12+BW13+BX11+BX12+BX13>=16,Fixo/30*FT$4+(BU11+BU12+BU13+BV11+BV12+BV13+BW11+BW12+BW13+BX11+BX12-16)*Percapita/30*FT$4)))))) -> 0 | FU11: =IF(C11=4,SUM(BY11+BY12+BY13+CA11+CA12+CA13)*Percapita/30*FU$4+(BZ11+BZ12+BZ13+CB11+CB12+CB13)*Cadeirante/30*FU$4,IF(C11=3,IF(BY14+CA14=10,Fixo/30*FU$4+(BY11+BY12+BY13+CA11+CA12+CA13)*Percapita/30*FU$4+(BZ14+CB14)*Cadeirante/30*FU$4,IF(BY14+CA14<=9,(BY14+CA14)*Crechee/30*FU$4)+(BZ14+CB14)*Cadeirante/30*FU$4+(BY11+BY12+BY13+CA11+CA12+CA13)*Percapita/30*FU$4)+IF(BY14+CA14>=11,Fixo/30*FU$4+(BY14+CA14-10)*Crechee/30*FU$4,0),IF(C11=2,IF(BZ11+BZ12+BZ13+BZ14+CB11+CB12+CB13+CB14=1,Cadeirante/30*FU$4,IF(BZ11+BZ12+BZ13+BZ14+CB11+CB12+CB13+CB14=2,Fixo/30*FU$4,IF(BZ11+BZ12+BZ13+BZ14+CB11+CB12+CB13+CB14>2,Fixo/30*FU$4+(BZ11+BZ12+BZ13+BZ14+CB11+CB12+CB13+CB14-2)*Cadeirante/30*FU$4)))+(BY11+BY12+BY13+CA11+CA12+CA13)*Percapita/30*FU$4+(BY14+CA14)*Crechee/30*FU$4,IF(C11=1,IF(BY11+BY12+BY13+BZ11+BZ12+BZ13+CA11+CA12+CA13+CB11+CB12+CB13<=15,(BY11+BY12+BY13+CA11+CA12+CA13)*Percapita/30*FU$4,IF(BY11+BY12+BY13+BZ11+BZ12+BZ13+CA11+CA12+CA13+CB11+CB12+CB13>=16,Fixo/30*FU$4+(BY11+BY12+BY13+BZ11+BZ12+BZ13+CA11+CA12+CA13+CB11+CB12-16)*Percapita/30*FU$4)))))) -> 0 | FV11: =IF(C11=4,SUM(CC11+CC12+CC13+CE11+CE12+CE13)*Percapita/30*FV$4+(CD11+CD12+CD13+CF11+CF12+CF13)*Cadeirante/30*FV$4,IF(C11=3,IF(CC14+CE14=10,Fixo/30*FV$4+(CC11+CC12+CC13+CE11+CE12+CE13)*Percapita/30*FV$4+(CD14+CF14)*Cadeirante/30*FV$4,IF(CC14+CE14<=9,(CC14+CE14)*Crechee/30*FV$4)+(CD14+CF14)*Cadeirante/30*FV$4+(CC11+CC12+CC13+CE11+CE12+CE13)*Percapita/30*FV$4)+IF(CC14+CE14>=11,Fixo/30*FV$4+(CC14+CE14-10)*Crechee/30*FV$4,0),IF(C11=2,IF(CD11+CD12+CD13+CD14+CF11+CF12+CF13+CF14=1,Cadeirante/30*FV$4,IF(CD11+CD12+CD13+CD14+CF11+CF12+CF13+CF14=2,Fixo/30*FV$4,IF(CD11+CD12+CD13+CD14+CF11+CF12+CF13+CF14>2,Fixo/30*FV$4+(CD11+CD12+CD13+CD14+CF11+CF12+CF13+CF14-2)*Cadeirante/30*FV$4)))+(CC11+CC12+CC13+CE11+CE12+CE13)*Percapita/30*FV$4+(CC14+CE14)*Crechee/30*FV$4,IF(C11=1,IF(CC11+CC12+CC13+CD11+CD12+CD13+CE11+CE12+CE13+CF11+CF12+CF13<=15,(CC11+CC12+CC13+CE11+CE12+CE13)*Percapita/30*FV$4,IF(CC11+CC12+CC13+CD11+CD12+CD13+CE11+CE12+CE13+CF11+CF12+CF13>=16,Fixo/30*FV$4+(CC11+CC12+CC13+CD11+CD12+CD13+CE11+CE12+CE13+CF11+CF12-16)*Percapita/30*FV$4)))))) -> 179.774 | FW11: =IF(C11=4,SUM(CG11+CG12+CG13+CI11+CI12+CI13)*Percapita/30*FW$4+(CH11+CH12+CH13+CJ11+CJ12+CJ13)*Cadeirante/30*FW$4,IF(C11=3,IF(CG14+CI14=10,Fixo/30*FW$4+(CG11+CG12+CG13+CI11+CI12+CI13)*Percapita/30*FW$4+(CH14+CJ14)*Cadeirante/30*FW$4,IF(CG14+CI14<=9,(CG14+CI14)*Crechee/30*FW$4)+(CH14+CJ14)*Cadeirante/30*FW$4+(CG11+CG12+CG13+CI11+CI12+CI13)*Percapita/30*FW$4)+IF(CG14+CI14>=11,Fixo/30*FW$4+(CG14+CI14-10)*Crechee/30*FW$4,0),IF(C11=2,IF(CH11+CH12+CH13+CH14+CJ11+CJ12+CJ13+CJ14=1,Cadeirante/30*FW$4,IF(CH11+CH12+CH13+CH14+CJ11+CJ12+CJ13+CJ14=2,Fixo/30*FW$4,IF(CH11+CH12+CH13+CH14+CJ11+CJ12+CJ13+CJ14>2,Fixo/30*FW$4+(CH11+CH12+CH13+CH14+CJ11+CJ12+CJ13+CJ14-2)*Cadeirante/30*FW$4)))+(CG11+CG12+CG13+CI11+CI12+CI13)*Percapita/30*FW$4+(CG14+CI14)*Crechee/30*FW$4,IF(C11=1,IF(CG11+CG12+CG13+CH11+CH12+CH13+CI11+CI12+CI13+CJ11+CJ12+CJ13<=15,(CG11+CG12+CG13+CI11+CI12+CI13)*Percapita/30*FW$4,IF(CG11+CG12+CG13+CH11+CH12+CH13+CI11+CI12+CI13+CJ11+CJ12+CJ13>=16,Fixo/30*FW$4+(CG11+CG12+CG13+CH11+CH12+CH13+CI11+CI12+CI13+CJ11+CJ12-16)*Percapita/30*FW$4)))))) -> 0 | FX11: =IF(C11=4,SUM(CK11+CK12+CK13+CM11+CM12+CM13)*Percapita/30*FX$4+(CL11+CL12+CL13+CN11+CN12+CN13)*Cadeirante/30*FX$4,IF(C11=3,IF(CK14+CM14=10,Fixo/30*FX$4+(CK11+CK12+CK13+CM11+CM12+CM13)*Percapita/30*FX$4+(CL14+CN14)*Cadeirante/30*FX$4,IF(CK14+CM14<=9,(CK14+CM14)*Crechee/30*FX$4)+(CL14+CN14)*Cadeirante/30*FX$4+(CK11+CK12+CK13+CM11+CM12+CM13)*Percapita/30*FX$4)+IF(CK14+CM14>=11,Fixo/30*FX$4+(CK14+CM14-10)*Crechee/30*FX$4,0),IF(C11=2,IF(CL11+CL12+CL13+CL14+CN11+CN12+CN13+CN14=1,Cadeirante/30*FX$4,IF(CL11+CL12+CL13+CL14+CN11+CN12+CN13+CN14=2,Fixo/30*FX$4,IF(CL11+CL12+CL13+CL14+CN11+CN12+CN13+CN14>2,Fixo/30*FX$4+(CL11+CL12+CL13+CL14+CN11+CN12+CN13+CN14-2)*Cadeirante/30*FX$4)))+(CK11+CK12+CK13+CM11+CM12+CM13)*Percapita/30*FX$4+(CK14+CM14)*Crechee/30*FX$4,IF(C11=1,IF(CK11+CK12+CK13+CL11+CL12+CL13+CM11+CM12+CM13+CN11+CN12+CN13<=15,(CK11+CK12+CK13+CM11+CM12+CM13)*Percapita/30*FX$4,IF(CK11+CK12+CK13+CL11+CL12+CL13+CM11+CM12+CM13+CN11+CN12+CN13>=16,Fixo/30*FX$4+(CK11+CK12+CK13+CL11+CL12+CL13+CM11+CM12+CM13+CN11+CN12-16)*Percapita/30*FX$4)))))) -> 0 | FY11: =IF(C11=4,SUM(CO11+CO12+CO13+CQ11+CQ12+CQ13)*Percapita/30*FY$4+(CP11+CP12+CP13+CR11+CR12+CR13)*Cadeirante/30*FY$4,IF(C11=3,IF(CO14+CQ14=10,Fixo/30*FY$4+(CO11+CO12+CO13+CQ11+CQ12+CQ13)*Percapita/30*FY$4+(CP14+CR14)*Cadeirante/30*FY$4,IF(CO14+CQ14<=9,(CO14+CQ14)*Crechee/30*FY$4)+(CP14+CR14)*Cadeirante/30*FY$4+(CO11+CO12+CO13+CQ11+CQ12+CQ13)*Percapita/30*FY$4)+IF(CO14+CQ14>=11,Fixo/30*FY$4+(CO14+CQ14-10)*Crechee/30*FY$4,0),IF(C11=2,IF(CP11+CP12+CP13+CP14+CR11+CR12+CR13+CR14=1,Cadeirante/30*FY$4,IF(CP11+CP12+CP13+CP14+CR11+CR12+CR13+CR14=2,Fixo/30*FY$4,IF(CP11+CP12+CP13+CP14+CR11+CR12+CR13+CR14>2,Fixo/30*FY$4+(CP11+CP12+CP13+CP14+CR11+CR12+CR13+CR14-2)*Cadeirante/30*FY$4)))+(CO11+CO12+CO13+CQ11+CQ12+CQ13)*Percapita/30*FY$4+(CO14+CQ14)*Crechee/30*FY$4,IF(C11=1,IF(CO11+CO12+CO13+CP11+CP12+CP13+CQ11+CQ12+CQ13+CR11+CR12+CR13<=15,(CO11+CO12+CO13+CQ11+CQ12+CQ13)*Percapita/30*FY$4,IF(CO11+CO12+CO13+CP11+CP12+CP13+CQ11+CQ12+CQ13+CR11+CR12+CR13>=16,Fixo/30*FY$4+(CO11+CO12+CO13+CP11+CP12+CP13+CQ11+CQ12+CQ13+CR11+CR12-16)*Percapita/30*FY$4)))))) -> 0 | FZ11: =IF(C11=4,SUM(CS11+CS12+CS13+CU11+CU12+CU13)*Percapita/30*FZ$4+(CT11+CT12+CT13+CV11+CV12+CV13)*Cadeirante/30*FZ$4,IF(C11=3,IF(CS14+CU14=10,Fixo/30*FZ$4+(CS11+CS12+CS13+CU11+CU12+CU13)*Percapita/30*FZ$4+(CT14+CV14)*Cadeirante/30*FZ$4,IF(CS14+CU14<=9,(CS14+CU14)*Crechee/30*FZ$4)+(CT14+CV14)*Cadeirante/30*FZ$4+(CS11+CS12+CS13+CU11+CU12+CU13)*Percapita/30*FZ$4)+IF(CS14+CU14>=11,Fixo/30*FZ$4+(CS14+CU14-10)*Crechee/30*FZ$4,0),IF(C11=2,IF(CT11+CT12+CT13+CT14+CV11+CV12+CV13+CV14=1,Cadeirante/30*FZ$4,IF(CT11+CT12+CT13+CT14+CV11+CV12+CV13+CV14=2,Fixo/30*FZ$4,IF(CT11+CT12+CT13+CT14+CV11+CV12+CV13+CV14>2,Fixo/30*FZ$4+(CT11+CT12+CT13+CT14+CV11+CV12+CV13+CV14-2)*Cadeirante/30*FZ$4)))+(CS11+CS12+CS13+CU11+CU12+CU13)*Percapita/30*FZ$4+(CS14+CU14)*Crechee/30*FZ$4,IF(C11=1,IF(CS11+CS12+CS13+CT11+CT12+CT13+CU11+CU12+CU13+CV11+CV12+CV13<=15,(CS11+CS12+CS13+CU11+CU12+CU13)*Percapita/30*FZ$4,IF(CS11+CS12+CS13+CT11+CT12+CT13+CU11+CU12+CU13+CV11+CV12+CV13>=16,Fixo/30*FZ$4+(CS11+CS12+CS13+CT11+CT12+CT13+CU11+CU12+CU13+CV11+CV12-16)*Percapita/30*FZ$4)))))) -> 0 | GA11: =IF(C11=4,SUM(CW11+CW12+CW13+CY11+CY12+CY13)*Percapita/30*GA$4+(CX11+CX12+CX13+CZ11+CZ12+CZ13)*Cadeirante/30*GA$4,IF(C11=3,IF(CW14+CY14=10,Fixo/30*GA$4+(CW11+CW12+CW13+CY11+CY12+CY13)*Percapita/30*GA$4+(CX14+CZ14)*Cadeirante/30*GA$4,IF(CW14+CY14<=9,(CW14+CY14)*Crechee/30*GA$4)+(CX14+CZ14)*Cadeirante/30*GA$4+(CW11+CW12+CW13+CY11+CY12+CY13)*Percapita/30*GA$4)+IF(CW14+CY14>=11,Fixo/30*GA$4+(CW14+CY14-10)*Crechee/30*GA$4,0),IF(C11=2,IF(CX11+CX12+CX13+CX14+CZ11+CZ12+CZ13+CZ14=1,Cadeirante/30*GA$4,IF(CX11+CX12+CX13+CX14+CZ11+CZ12+CZ13+CZ14=2,Fixo/30*GA$4,IF(CX11+CX12+CX13+CX14+CZ11+CZ12+CZ13+CZ14>2,Fixo/30*GA$4+(CX11+CX12+CX13+CX14+CZ11+CZ12+CZ13+CZ14-2)*Cadeirante/30*GA$4)))+(CW11+CW12+CW13+CY11+CY12+CY13)*Percapita/30*GA$4+(CW14+CY14)*Crechee/30*GA$4,IF(C11=1,IF(CW11+CW12+CW13+CX11+CX12+CX13+CY11+CY12+CY13+CZ11+CZ12+CZ13<=15,(CW11+CW12+CW13+CY11+CY12+CY13)*Percapita/30*GA$4,IF(CW11+CW12+CW13+CX11+CX12+CX13+CY11+CY12+CY13+CZ11+CZ12+CZ13>=16,Fixo/30*GA$4+(CW11+CW12+CW13+CX11+CX12+CX13+CY11+CY12+CY13+CZ11+CZ12-16)*Percapita/30*GA$4)))))) -> 0 | GB11: =IF(C11=4,SUM(DA11+DA12+DA13+DC11+DC12+DC13)*Percapita/30*GB$4+(DB11+DB12+DB13+DD11+DD12+DD13)*Cadeirante/30*GB$4,IF(C11=3,IF(DA14+DC14=10,Fixo/30*GB$4+(DA11+DA12+DA13+DC11+DC12+DC13)*Percapita/30*GB$4+(DB14+DD14)*Cadeirante/30*GB$4,IF(DA14+DC14<=9,(DA14+DC14)*Crechee/30*GB$4)+(DB14+DD14)*Cadeirante/30*GB$4+(DA11+DA12+DA13+DC11+DC12+DC13)*Percapita/30*GB$4)+IF(DA14+DC14>=11,Fixo/30*GB$4+(DA14+DC14-10)*Crechee/30*GB$4,0),IF(C11=2,IF(DB11+DB12+DB13+DB14+DD11+DD12+DD13+DD14=1,Cadeirante/30*GB$4,IF(DB11+DB12+DB13+DB14+DD11+DD12+DD13+DD14=2,Fixo/30*GB$4,IF(DB11+DB12+DB13+DB14+DD11+DD12+DD13+DD14>2,Fixo/30*GB$4+(DB11+DB12+DB13+DB14+DD11+DD12+DD13+DD14-2)*Cadeirante/30*GB$4)))+(DA11+DA12+DA13+DC11+DC12+DC13)*Percapita/30*GB$4+(DA14+DC14)*Crechee/30*GB$4,IF(C11=1,IF(DA11+DA12+DA13+DB11+DB12+DB13+DC11+DC12+DC13+DD11+DD12+DD13<=15,(DA11+DA12+DA13+DC11+DC12+DC13)*Percapita/30*GB$4,IF(DA11+DA12+DA13+DB11+DB12+DB13+DC11+DC12+DC13+DD11+DD12+DD13>=16,Fixo/30*GB$4+(DA11+DA12+DA13+DB11+DB12+DB13+DC11+DC12+DC13+DD11+DD12-16)*Percapita/30*GB$4)))))) -> 0 | GC11: =IF(C11=4,SUM(DE11+DE12+DE13+DG11+DG12+DG13)*Percapita/30*GC$4+(DF11+DF12+DF13+DH11+DH12+DH13)*Cadeirante/30*GC$4,IF(C11=3,IF(DE14+DG14=10,Fixo/30*GC$4+(DE11+DE12+DE13+DG11+DG12+DG13)*Percapita/30*GC$4+(DF14+DH14)*Cadeirante/30*GC$4,IF(DE14+DG14<=9,(DE14+DG14)*Crechee/30*GC$4)+(DF14+DH14)*Cadeirante/30*GC$4+(DE11+DE12+DE13+DG11+DG12+DG13)*Percapita/30*GC$4)+IF(DE14+DG14>=11,Fixo/30*GC$4+(DE14+DG14-10)*Crechee/30*GC$4,0),IF(C11=2,IF(DF11+DF12+DF13+DF14+DH11+DH12+DH13+DH14=1,Cadeirante/30*GC$4,IF(DF11+DF12+DF13+DF14+DH11+DH12+DH13+DH14=2,Fixo/30*GC$4,IF(DF11+DF12+DF13+DF14+DH11+DH12+DH13+DH14>2,Fixo/30*GC$4+(DF11+DF12+DF13+DF14+DH11+DH12+DH13+DH14-2)*Cadeirante/30*GC$4)))+(DE11+DE12+DE13+DG11+DG12+DG13)*Percapita/30*GC$4+(DE14+DG14)*Crechee/30*GC$4,IF(C11=1,IF(DE11+DE12+DE13+DF11+DF12+DF13+DG11+DG12+DG13+DH11+DH12+DH13<=15,(DE11+DE12+DE13+DG11+DG12+DG13)*Percapita/30*GC$4,IF(DE11+DE12+DE13+DF11+DF12+DF13+DG11+DG12+DG13+DH11+DH12+DH13>=16,Fixo/30*GC$4+(DE11+DE12+DE13+DF11+DF12+DF13+DG11+DG12+DG13+DH11+DH12-16)*Percapita/30*GC$4)))))) -> 0 | GD11: =IF(C11=4,SUM(DI11+DI12+DI13+DK11+DK12+DK13)*Percapita/30*GD$4+(DJ11+DJ12+DJ13+DL11+DL12+DL13)*Cadeirante/30*GD$4,IF(C11=3,IF(DI14+DK14=10,Fixo/30*GD$4+(DI11+DI12+DI13+DK11+DK12+DK13)*Percapita/30*GD$4+(DJ14+DL14)*Cadeirante/30*GD$4,IF(DI14+DK14<=9,(DI14+DK14)*Crechee/30*GD$4)+(DJ14+DL14)*Cadeirante/30*GD$4+(DI11+DI12+DI13+DK11+DK12+DK13)*Percapita/30*GD$4)+IF(DI14+DK14>=11,Fixo/30*GD$4+(DI14+DK14-10)*Crechee/30*GD$4,0),IF(C11=2,IF(DJ11+DJ12+DJ13+DJ14+DL11+DL12+DL13+DL14=1,Cadeirante/30*GD$4,IF(DJ11+DJ12+DJ13+DJ14+DL11+DL12+DL13+DL14=2,Fixo/30*GD$4,IF(DJ11+DJ12+DJ13+DJ14+DL11+DL12+DL13+DL14>2,Fixo/30*GD$4+(DJ11+DJ12+DJ13+DJ14+DL11+DL12+DL13+DL14-2)*Cadeirante/30*GD$4)))+(DI11+DI12+DI13+DK11+DK12+DK13)*Percapita/30*GD$4+(DI14+DK14)*Crechee/30*GD$4,IF(C11=1,IF(DI11+DI12+DI13+DJ11+DJ12+DJ13+DK11+DK12+DK13+DL11+DL12+DL13<=15,(DI11+DI12+DI13+DK11+DK12+DK13)*Percapita/30*GD$4,IF(DI11+DI12+DI13+DJ11+DJ12+DJ13+DK11+DK12+DK13+DL11+DL12+DL13>=16,Fixo/30*GD$4+(DI11+DI12+DI13+DJ11+DJ12+DJ13+DK11+DK12+DK13+DL11+DL12-16)*Percapita/30*GD$4)))))) -> 0 | GE11: =IF(C11=4,SUM(DM11+DM12+DM13+DO11+DO12+DO13)*Percapita/30*GE$4+(DN11+DN12+DN13+DP11+DP12+DP13)*Cadeirante/30*GE$4,IF(C11=3,IF(DM14+DO14=10,Fixo/30*GE$4+(DM11+DM12+DM13+DO11+DO12+DO13)*Percapita/30*GE$4+(DN14+DP14)*Cadeirante/30*GE$4,IF(DM14+DO14<=9,(DM14+DO14)*Crechee/30*GE$4)+(DN14+DP14)*Cadeirante/30*GE$4+(DM11+DM12+DM13+DO11+DO12+DO13)*Percapita/30*GE$4)+IF(DM14+DO14>=11,Fixo/30*GE$4+(DM14+DO14-10)*Crechee/30*GE$4,0),IF(C11=2,IF(DN11+DN12+DN13+DN14+DP11+DP12+DP13+DP14=1,Cadeirante/30*GE$4,IF(DN11+DN12+DN13+DN14+DP11+DP12+DP13+DP14=2,Fixo/30*GE$4,IF(DN11+DN12+DN13+DN14+DP11+DP12+DP13+DP14>2,Fixo/30*GE$4+(DN11+DN12+DN13+DN14+DP11+DP12+DP13+DP14-2)*Cadeirante/30*GE$4)))+(DM11+DM12+DM13+DO11+DO12+DO13)*Percapita/30*GE$4+(DM14+DO14)*Crechee/30*GE$4,IF(C11=1,IF(DM11+DM12+DM13+DN11+DN12+DN13+DO11+DO12+DO13+DP11+DP12+DP13<=15,(DM11+DM12+DM13+DO11+DO12+DO13)*Percapita/30*GE$4,IF(DM11+DM12+DM13+DN11+DN12+DN13+DO11+DO12+DO13+DP11+DP12+DP13>=16,Fixo/30*GE$4+(DM11+DM12+DM13+DN11+DN12+DN13+DO11+DO12+DO13+DP11+DP12-16)*Percapita/30*GE$4)))))) -> 0 | GF11: =IF(C11=4,SUM(DQ11+DQ12+DQ13+DS11+DS12+DS13)*Percapita/30*GF$4+(DR11+DR12+DR13+DT11+DT12+DT13)*Cadeirante/30*GF$4,IF(C11=3,IF(DQ14+DS14=10,Fixo/30*GF$4+(DQ11+DQ12+DQ13+DS11+DS12+DS13)*Percapita/30*GF$4+(DR14+DT14)*Cadeirante/30*GF$4,IF(DQ14+DS14<=9,(DQ14+DS14)*Crechee/30*GF$4)+(DR14+DT14)*Cadeirante/30*GF$4+(DQ11+DQ12+DQ13+DS11+DS12+DS13)*Percapita/30*GF$4)+IF(DQ14+DS14>=11,Fixo/30*GF$4+(DQ14+DS14-10)*Crechee/30*GF$4,0),IF(C11=2,IF(DR11+DR12+DR13+DR14+DT11+DT12+DT13+DT14=1,Cadeirante/30*GF$4,IF(DR11+DR12+DR13+DR14+DT11+DT12+DT13+DT14=2,Fixo/30*GF$4,IF(DR11+DR12+DR13+DR14+DT11+DT12+DT13+DT14>2,Fixo/30*GF$4+(DR11+DR12+DR13+DR14+DT11+DT12+DT13+DT14-2)*Cadeirante/30*GF$4)))+(DQ11+DQ12+DQ13+DS11+DS12+DS13)*Percapita/30*GF$4+(DQ14+DS14)*Crechee/30*GF$4,IF(C11=1,IF(DQ11+DQ12+DQ13+DR11+DR12+DR13+DS11+DS12+DS13+DT11+DT12+DT13<=15,(DQ11+DQ12+DQ13+DS11+DS12+DS13)*Percapita/30*GF$4,IF(DQ11+DQ12+DQ13+DR11+DR12+DR13+DS11+DS12+DS13+DT11+DT12+DT13>=16,Fixo/30*GF$4+(DQ11+DQ12+DQ13+DR11+DR12+DR13+DS11+DS12+DS13+DT11+DT12-16)*Percapita/30*GF$4)))))) -> 0 | GG11: =IF(C11=4,SUM(DU11+DU12+DU13+DW11+DW12+DW13)*Percapita/30*GG$4+(DV11+DV12+DV13+DX11+DX12+DX13)*Cadeirante/30*GG$4,IF(C11=3,IF(DU14+DW14=10,Fixo/30*GG$4+(DU11+DU12+DU13+DW11+DW12+DW13)*Percapita/30*GG$4+(DV14+DX14)*Cadeirante/30*GG$4,IF(DU14+DW14<=9,(DU14+DW14)*Crechee/30*GG$4)+(DV14+DX14)*Cadeirante/30*GG$4+(DU11+DU12+DU13+DW11+DW12+DW13)*Percapita/30*GG$4)+IF(DU14+DW14>=11,Fixo/30*GG$4+(DU14+DW14-10)*Crechee/30*GG$4,0),IF(C11=2,IF(DV11+DV12+DV13+DV14+DX11+DX12+DX13+DX14=1,Cadeirante/30*GG$4,IF(DV11+DV12+DV13+DV14+DX11+DX12+DX13+DX14=2,Fixo/30*GG$4,IF(DV11+DV12+DV13+DV14+DX11+DX12+DX13+DX14>2,Fixo/30*GG$4+(DV11+DV12+DV13+DV14+DX11+DX12+DX13+DX14-2)*Cadeirante/30*GG$4)))+(DU11+DU12+DU13+DW11+DW12+DW13)*Percapita/30*GG$4+(DU14+DW14)*Crechee/30*GG$4,IF(C11=1,IF(DU11+DU12+DU13+DV11+DV12+DV13+DW11+DW12+DW13+DX11+DX12+DX13<=15,(DU11+DU12+DU13+DW11+DW12+DW13)*Percapita/30*GG$4,IF(DU11+DU12+DU13+DV11+DV12+DV13+DW11+DW12+DW13+DX11+DX12+DX13>=16,Fixo/30*GG$4+(DU11+DU12+DU13+DV11+DV12+DV13+DW11+DW12+DW13+DX11+DX12-16)*Percapita/30*GG$4)))))) -> 0 | GH11: =IF(C11=4,SUM(DY11+DY12+DY13+EA11+EA12+EA13)*Percapita/30*GH$4+(DZ11+DZ12+DZ13+EB11+EB12+EB13)*Cadeirante/30*GH$4,IF(C11=3,IF(DY14+EA14=10,Fixo/30*GH$4+(DY11+DY12+DY13+EA11+EA12+EA13)*Percapita/30*GH$4+(DZ14+EB14)*Cadeirante/30*GH$4,IF(DY14+EA14<=9,(DY14+EA14)*Crechee/30*GH$4)+(DZ14+EB14)*Cadeirante/30*GH$4+(DY11+DY12+DY13+EA11+EA12+EA13)*Percapita/30*GH$4)+IF(DY14+EA14>=11,Fixo/30*GH$4+(DY14+EA14-10)*Crechee/30*GH$4,0),IF(C11=2,IF(DZ11+DZ12+DZ13+DZ14+EB11+EB12+EB13+EB14=1,Cadeirante/30*GH$4,IF(DZ11+DZ12+DZ13+DZ14+EB11+EB12+EB13+EB14=2,Fixo/30*GH$4,IF(DZ11+DZ12+DZ13+DZ14+EB11+EB12+EB13+EB14>2,Fixo/30*GH$4+(DZ11+DZ12+DZ13+DZ14+EB11+EB12+EB13+EB14-2)*Cadeirante/30*GH$4)))+(DY11+DY12+DY13+EA11+EA12+EA13)*Percapita/30*GH$4+(DY14+EA14)*Crechee/30*GH$4,IF(C11=1,IF(DY11+DY12+DY13+DZ11+DZ12+DZ13+EA11+EA12+EA13+EB11+EB12+EB13<=15,(DY11+DY12+DY13+EA11+EA12+EA13)*Percapita/30*GH$4,IF(DY11+DY12+DY13+DZ11+DZ12+DZ13+EA11+EA12+EA13+EB11+EB12+EB13>=16,Fixo/30*GH$4+(DY11+DY12+DY13+DZ11+DZ12+DZ13+EA11+EA12+EA13+EB11+EB12-16)*Percapita/30*GH$4)))))) -> 0 | GI11: =IF(C11=4,SUM(EC11+EC12+EC13+EE11+EE12+EE13)*Percapita/30*GI$4+(ED11+ED12+ED13+EF11+EF12+EF13)*Cadeirante/30*GI$4,IF(C11=3,IF(EC14+EE14=10,Fixo/30*GI$4+(EC11+EC12+EC13+EE11+EE12+EE13)*Percapita/30*GI$4+(ED14+EF14)*Cadeirante/30*GI$4,IF(EC14+EE14<=9,(EC14+EE14)*Crechee/30*GI$4)+(ED14+EF14)*Cadeirante/30*GI$4+(EC11+EC12+EC13+EE11+EE12+EE13)*Percapita/30*GI$4)+IF(EC14+EE14>=11,Fixo/30*GI$4+(EC14+EE14-10)*Crechee/30*GI$4,0),IF(C11=2,IF(ED11+ED12+ED13+ED14+EF11+EF12+EF13+EF14=1,Cadeirante/30*GI$4,IF(ED11+ED12+ED13+ED14+EF11+EF12+EF13+EF14=2,Fixo/30*GI$4,IF(ED11+ED12+ED13+ED14+EF11+EF12+EF13+EF14>2,Fixo/30*GI$4+(ED11+ED12+ED13+ED14+EF11+EF12+EF13+EF14-2)*Cadeirante/30*GI$4)))+(EC11+EC12+EC13+EE11+EE12+EE13)*Percapita/30*GI$4+(EC14+EE14)*Crechee/30*GI$4,IF(C11=1,IF(EC11+EC12+EC13+ED11+ED12+ED13+EE11+EE12+EE13+EF11+EF12+EF13<=15,(EC11+EC12+EC13+EE11+EE12+EE13)*Percapita/30*GI$4,IF(EC11+EC12+EC13+ED11+ED12+ED13+EE11+EE12+EE13+EF11+EF12+EF13>=16,Fixo/30*GI$4+(EC11+EC12+EC13+ED11+ED12+ED13+EE11+EE12+EE13+EF11+EF12-16)*Percapita/30*GI$4)))))) -> 0 | GJ11: =IF(C11=4,SUM(EG11+EG12+EG13+EI11+EI12+EI13)*Percapita/30*GJ$4+(EH11+EH12+EH13+EJ11+EJ12+EJ13)*Cadeirante/30*GJ$4,IF(C11=3,IF(EG14+EI14=10,Fixo/30*GJ$4+(EG11+EG12+EG13+EI11+EI12+EI13)*Percapita/30*GJ$4+(EH14+EJ14)*Cadeirante/30*GJ$4,IF(EG14+EI14<=9,(EG14+EI14)*Crechee/30*GJ$4)+(EH14+EJ14)*Cadeirante/30*GJ$4+(EG11+EG12+EG13+EI11+EI12+EI13)*Percapita/30*GJ$4)+IF(EG14+EI14>=11,Fixo/30*GJ$4+(EG14+EI14-10)*Crechee/30*GJ$4,0),IF(C11=2,IF(EH11+EH12+EH13+EH14+EJ11+EJ12+EJ13+EJ14=1,Cadeirante/30*GJ$4,IF(EH11+EH12+EH13+EH14+EJ11+EJ12+EJ13+EJ14=2,Fixo/30*GJ$4,IF(EH11+EH12+EH13+EH14+EJ11+EJ12+EJ13+EJ14>2,Fixo/30*GJ$4+(EH11+EH12+EH13+EH14+EJ11+EJ12+EJ13+EJ14-2)*Cadeirante/30*GJ$4)))+(EG11+EG12+EG13+EI11+EI12+EI13)*Percapita/30*GJ$4+(EG14+EI14)*Crechee/30*GJ$4,IF(C11=1,IF(EG11+EG12+EG13+EH11+EH12+EH13+EI11+EI12+EI13+EJ11+EJ12+EJ13<=15,(EG11+EG12+EG13+EI11+EI12+EI13)*Percapita/30*GJ$4,IF(EG11+EG12+EG13+EH11+EH12+EH13+EI11+EI12+EI13+EJ11+EJ12+EJ13>=16,Fixo/30*GJ$4+(EG11+EG12+EG13+EH11+EH12+EH13+EI11+EI12+EI13+EJ11+EJ12-16)*Percapita/30*GJ$4)))))) -> 0 | GL11: =IF(J11="ADAPTADO",T11*Cadeirante/30*GM11+S11*Percapita/30*GM11,IF(J11="NORMAL",(S11+T11)*Percapita/30*GM11,IF(J11="CRECHE",0)))*-1 -> 0 | GN11: =SUMIF(V11:V14,"<0")*Cadeirante/30*GN$4+SUMIF(X11:X14,"<0")*Cadeirante/30*GN$4 -> 0 | GO11: =SUMIF(Z11:Z14,"<0")*Cadeirante/30*GO$4+SUMIF(AB11:AB14,"<0")*Cadeirante/30*GO$4 -> 0 | GP11: =SUMIF(AD11:AD14,"<0")*Cadeirante/30*GP$4+SUMIF(AF11:AF14,"<0")*Cadeirante/30*GP$4 -> 0 | GQ11: =SUMIF(AH11:AH14,"<0")*Cadeirante/30*GQ$4+SUMIF(AJ11:AJ14,"<0")*Cadeirante/30*GQ$4 -> 0 | GR11: =SUMIF(AL11:AL14,"<0")*Cadeirante/30*GR$4+SUMIF(AN11:AN14,"<0")*Cadeirante/30*GR$4 -> 0 | GS11: =SUMIF(AP11:AP14,"<0")*Cadeirante/30*GS$4+SUMIF(AR11:AR14,"<0")*Cadeirante/30*GS$4 -> 0 | GT11: =SUMIF(AT11:AT14,"<0")*Cadeirante/30*GT$4+SUMIF(AV11:AV14,"<0")*Cadeirante/30*GT$4 -> 0 | GU11: =SUMIF(AX11:AX14,"<0")*Cadeirante/30*GU$4+SUMIF(AZ11:AZ14,"<0")*Cadeirante/30*GU$4 -> 0 | GV11: =SUMIF(BB11:BB14,"<0")*Cadeirante/30*GV$4+SUMIF(BD11:BD14,"<0")*Cadeirante/30*GV$4 -> 0 | GW11: =SUMIF(BF11:BF14,"<0")*Cadeirante/30*GW$4+SUMIF(BH11:BH14,"<0")*Cadeirante/30*GW$4 -> 0 | GX11: =SUMIF(BJ11:BJ14,"<0")*Cadeirante/30*GX$4+SUMIF(BL11:BL14,"<0")*Cadeirante/30*GX$4 -> 0 | GY11: =SUMIF(BN11:BN14,"<0")*Cadeirante/30*GY$4+SUMIF(BP11:BP14,"<0")*Cadeirante/30*GY$4 -> 0 | GZ11: =SUMIF(BR11:BR14,"<0")*Cadeirante/30*GZ$4+SUMIF(BT11:BT14,"<0")*Cadeirante/30*GZ$4 -> 0 | HA11: =SUMIF(BV11:BV14,"<0")*Cadeirante/30*HA$4+SUMIF(BX11:BX14,"<0")*Cadeirante/30*HA$4 -> 0 | HB11: =SUMIF(BZ11:BZ14,"<0")*Cadeirante/30*HB$4+SUMIF(CB11:CB14,"<0")*Cadeirante/30*HB$4 -> 0 | HC11: =SUMIF(CD11:CD14,"<0")*Cadeirante/30*HC$4+SUMIF(CF11:CF14,"<0")*Cadeirante/30*HC$4 -> 0 | HD11: =SUMIF(CH11:CH14,"<0")*Cadeirante/30*HD$4+SUMIF(CJ11:CJ14,"<0")*Cadeirante/30*HD$4 -> 0 | HE11: =SUMIF(CL11:CL14,"<0")*Cadeirante/30*HE$4+SUMIF(CN11:CN14,"<0")*Cadeirante/30*HE$4 -> 0 | HF11: =SUMIF(CP11:CP14,"<0")*Cadeirante/30*HF$4+SUMIF(CR11:CR14,"<0")*Cadeirante/30*HF$4 -> 0 | HG11: =SUMIF(CT11:CT14,"<0")*Cadeirante/30*HG$4+SUMIF(CV11:CV14,"<0")*Cadeirante/30*HG$4 -> 0 | HH11: =SUMIF(CX11:CX14,"<0")*Cadeirante/30*HH$4+SUMIF(CZ11:CZ14,"<0")*Cadeirante/30*HH$4 -> 0 | HI11: =SUMIF(DB11:DB14,"<0")*Cadeirante/30*HI$4+SUMIF(DD11:DD14,"<0")*Cadeirante/30*HI$4 -> 0 | HJ11: =SUMIF(DF11:DF14,"<0")*Cadeirante/30*HJ$4+SUMIF(DH11:DH14,"<0")*Cadeirante/30*HJ$4 -> 0 | HK11: =SUMIF(DJ11:DJ14,"<0")*Cadeirante/30*HK$4+SUMIF(DL11:DL14,"<0")*Cadeirante/30*HK$4 -> 0 | HL11: =SUMIF(DN11:DN14,"<0")*Cadeirante/30*HL$4+SUMIF(DP11:DP14,"<0")*Cadeirante/30*HL$4 -> 0 | HM11: =SUMIF(DR11:DR14,"<0")*Cadeirante/30*HM$4+SUMIF(DT11:DT14,"<0")*Cadeirante/30*HM$4 -> 0 | HN11: =SUMIF(DV11:DV14,"<0")*Cadeirante/30*HN$4+SUMIF(DX11:DX14,"<0")*Cadeirante/30*HN$4 -> 0 | HO11: =SUMIF(DZ11:DZ14,"<0")*Cadeirante/30*HO$4+SUMIF(EB11:EB14,"<0")*Cadeirante/30*HO$4 -> 0 | HP11: =SUMIF(ED11:ED14,"<0")*Cadeirante/30*HP$4+SUMIF(EF11:EF14,"<0")*Cadeirante/30*HP$4 -> 0 | HW11: 17629.31 | HY11: =IF(ISTEXT(EM11), VALUE(EM11), EM11) -> 0 | HZ11: =IF(ISTEXT(EN11), VALUE(EN11), EN11) -> 0 | IA11: =IF(ISTEXT(EO11), VALUE(EO11), EO11) -> 0 | IB11: =HW11=FE11 -> FALSE
A12: 048.924-00 | B12: 2023/0009598-002B | C12: BT | D12: 2023/0009598 | E12: EKL2866 | F12: 01/04/2026 | G12: 30/04/2026 | H12: A.C.G. TRANSPORTE ESCOLAR LTDA | I12: JOSE CARLOS FONTELES DA SILVA | J12: NORMAL | K12: EMEF | L12: =CONTINUA!BV12 -> 7 | M12: =CONTINUA!BW12 -> 0 | O12: 6020.2023/0009598-2 | P12: O | Q12: 48 | CE12: 1 | EP12: =Q12 -> 48 | EQ12: =U12+Y12+AC12+AG12+AK12+AO12+AS12+AW12+BA12+BE12+BI12+BM12+BQ12+BU12+BY12+CC12+CG12+CK12+CO12+CS12+CW12+DA12+DE12+DI12+DM12+DQ12+DU12+DY12+EC12+EG12 -> 0 | ER12: =S12+W12+AA12+AE12+AI12+AM12+AQ12+AU12+AY12+BC12+BG12+BK12+BO12+BS12+BW12+CA12+CE12+CI12+CM12+CQ12+CU12+CY12+DC12+DG12+DK12+DO12+DS12+DW12+EA12+EE12+EI12 -> 1 | ES12: =R12 -> 0 | ET12: =V12+Z12+AD12+AH12+AL12+AP12+AT12+AX12+BB12+BF12+BJ12+BN12+BR12+BV12+BZ12+CD12+CH12+CL12+CP12+CT12+CX12+DB12+DF12+DJ12+DN12+DR12+DV12+DZ12+ED12+EH12 -> 0 | EU12: =T12+X12+AB12+AF12+AJ12+AN12+AR12+AV12+AZ12+BD12+BH12+BL12+BP12+BT12+BX12+CB12+CF12+CJ12+CN12+CR12+CV12+CZ12+DD12+DH12+DL12+DP12+DT12+DX12+EB12+EF12+EJ12 -> 0 | EV12: =EP12+EQ12+ES12+ET12+ER12+EU12 -> 49 | EX12: =FF12 -> 0 | EY12: =(L12*regular)+(M12*Cadeirantee) -> 67.48 | EZ12: =SUMIF(FG12:GJ12,">0") -> 0 | FA12: =SUMIF(FG12:GJ12,"<0")+SUMIF(GN12:HP12,"<0") -> 0 | FB12: 0 | FC12: =N12*km*'VALORES TABELA'!$B$13 -> 0 | FD12: =GL12 -> 0 | GL12: =IF(J12="ADAPTADO",T12*Cadeirante/30*GM12+S12*Percapita/30*GM12,IF(J12="NORMAL",(S12+T12)*Percapita/30*GM12,IF(J12="CRECHE",0)))*-1 -> 0 | HY12: =IF(ISTEXT(EM12), VALUE(EM12), EM12) -> 0 | HZ12: =IF(ISTEXT(EN12), VALUE(EN12), EN12) -> 0 | IA12: =IF(ISTEXT(EO12), VALUE(EO12), EO12) -> 0
A13: 048.924-00 | B13: 2023/0009598-002B | C13: BT | D13: 2023/0009598 | E13: EKL2866 | F13: 01/04/2026 | G13: 30/04/2026 | H13: A.C.G. TRANSPORTE ESCOLAR LTDA | I13: JOSE CARLOS FONTELES DA SILVA | J13: NORMAL | K13: EMEE | L13: =CONTINUA!BV13 -> 0 | M13: =CONTINUA!BW13 -> 0 | O13: 6020.2023/0009598-2 | P13: O | EP13: =Q13 -> 0 | EQ13: =U13+Y13+AC13+AG13+AK13+AO13+AS13+AW13+BA13+BE13+BI13+BM13+BQ13+BU13+BY13+CC13+CG13+CK13+CO13+CS13+CW13+DA13+DE13+DI13+DM13+DQ13+DU13+DY13+EC13+EG13 -> 0 | ER13: =S13+W13+AA13+AE13+AI13+AM13+AQ13+AU13+AY13+BC13+BG13+BK13+BO13+BS13+BW13+CA13+CE13+CI13+CM13+CQ13+CU13+CY13+DC13+DG13+DK13+DO13+DS13+DW13+EA13+EE13+EI13 -> 0 | ES13: =R13 -> 0 | ET13: =V13+Z13+AD13+AH13+AL13+AP13+AT13+AX13+BB13+BF13+BJ13+BN13+BR13+BV13+BZ13+CD13+CH13+CL13+CP13+CT13+CX13+DB13+DF13+DJ13+DN13+DR13+DV13+DZ13+ED13+EH13 -> 0 | EU13: =T13+X13+AB13+AF13+AJ13+AN13+AR13+AV13+AZ13+BD13+BH13+BL13+BP13+BT13+BX13+CB13+CF13+CJ13+CN13+CR13+CV13+CZ13+DD13+DH13+DL13+DP13+DT13+DX13+EB13+EF13+EJ13 -> 0 | EV13: =EP13+EQ13+ES13+ET13+ER13+EU13 -> 0 | EX13: =FF13 -> 0 | EY13: =(L13*regular)+(M13*Cadeirantee) -> 0 | EZ13: =SUMIF(FG13:GJ13,">0") -> 0 | FA13: =SUMIF(FG13:GJ13,"<0")+SUMIF(GN13:HP13,"<0") -> 0 | FB13: 0 | FC13: =N13*km*'VALORES TABELA'!$B$13 -> 0 | FD13: =GL13 -> 0 | GL13: =IF(J13="ADAPTADO",T13*Cadeirante/30*GM13+S13*Percapita/30*GM13,IF(J13="NORMAL",(S13+T13)*Percapita/30*GM13,IF(J13="CRECHE",0)))*-1 -> 0 | HY13: =IF(ISTEXT(EM13), VALUE(EM13), EM13) -> 0 | HZ13: =IF(ISTEXT(EN13), VALUE(EN13), EN13) -> 0 | IA13: =IF(ISTEXT(EO13), VALUE(EO13), EO13) -> 0
A14: 048.924-00 | B14: 2023/0009598-002B | C14: BT | D14: 2023/0009598 | E14: EKL2866 | F14: 01/04/2026 | G14: 30/04/2026 | H14: A.C.G. TRANSPORTE ESCOLAR LTDA | I14: JOSE CARLOS FONTELES DA SILVA | J14: NORMAL | K14: CEI | L14: =CONTINUA!BV14 -> 0 | M14: =CONTINUA!BW14 -> 0 | O14: 6020.2023/0009598-2 | P14: O | EP14: =Q14 -> 0 | EQ14: =U14+Y14+AC14+AG14+AK14+AO14+AS14+AW14+BA14+BE14+BI14+BM14+BQ14+BU14+BY14+CC14+CG14+CK14+CO14+CS14+CW14+DA14+DE14+DI14+DM14+DQ14+DU14+DY14+EC14+EG14 -> 0 | ER14: =S14+W14+AA14+AE14+AI14+AM14+AQ14+AU14+AY14+BC14+BG14+BK14+BO14+BS14+BW14+CA14+CE14+CI14+CM14+CQ14+CU14+CY14+DC14+DG14+DK14+DO14+DS14+DW14+EA14+EE14+EI14 -> 0 | ES14: =R14 -> 0 | ET14: =V14+Z14+AD14+AH14+AL14+AP14+AT14+AX14+BB14+BF14+BJ14+BN14+BR14+BV14+BZ14+CD14+CH14+CL14+CP14+CT14+CX14+DB14+DF14+DJ14+DN14+DR14+DV14+DZ14+ED14+EH14 -> 0 | EU14: =T14+X14+AB14+AF14+AJ14+AN14+AR14+AV14+AZ14+BD14+BH14+BL14+BP14+BT14+BX14+CB14+CF14+CJ14+CN14+CR14+CV14+CZ14+DD14+DH14+DL14+DP14+DT14+DX14+EB14+EF14+EJ14 -> 0 | EV14: =EP14+EQ14+ES14+ET14+ER14+EU14 -> 0 | EX14: =FF14 -> 0 | EY14: =(L14*regular)+(M14*Cadeirantee) -> 0 | EZ14: =SUMIF(FG14:GJ14,">0") -> 0 | FA14: =SUMIF(FG14:GJ14,"<0")+SUMIF(GN14:HP14,"<0") -> 0 | FB14: 0 | FC14: =N14*km*'VALORES TABELA'!$B$13 -> 0 | FD14: =GL14 -> 0 | GL14: =IF(J14="ADAPTADO",T14*Cadeirante/30*GM14+S14*Percapita/30*GM14,IF(J14="NORMAL",(S14+T14)*Percapita/30*GM14,IF(J14="CRECHE",0)))*-1 -> 0 | HY14: =IF(ISTEXT(EM14), VALUE(EM14), EM14) -> 0 | HZ14: =IF(ISTEXT(EN14), VALUE(EN14), EN14) -> 0 | IA14: =IF(ISTEXT(EO14), VALUE(EO14), EO14) -> 0
A15: 048.924-00 | B15: 2023/0009598-002B | C15: BT | D15: 2023/0009598 | E15: EKL2866 | F15: 01/04/2026 | G15: 30/04/2026 | H15: A.C.G. TRANSPORTE ESCOLAR LTDA | I15: JOSE CARLOS FONTELES DA SILVA | J15: NORMAL | K15: CCA | L15: =CONTINUA!BV15 -> 0 | M15: =CONTINUA!BW15 -> 0 | O15: 6020.2023/0009598-2 | P15: O | EP15: =Q15 -> 0 | EQ15: =U15+Y15+AC15+AG15+AK15+AO15+AS15+AW15+BA15+BE15+BI15+BM15+BQ15+BU15+BY15+CC15+CG15+CK15+CO15+CS15+CW15+DA15+DE15+DI15+DM15+DQ15+DU15+DY15+EC15+EG15 -> 0 | ER15: =S15+W15+AA15+AE15+AI15+AM15+AQ15+AU15+AY15+BC15+BG15+BK15+BO15+BS15+BW15+CA15+CE15+CI15+CM15+CQ15+CU15+CY15+DC15+DG15+DK15+DO15+DS15+DW15+EA15+EE15+EI15 -> 0 | ES15: =R15 -> 0 | ET15: =V15+Z15+AD15+AH15+AL15+AP15+AT15+AX15+BB15+BF15+BJ15+BN15+BR15+BV15+BZ15+CD15+CH15+CL15+CP15+CT15+CX15+DB15+DF15+DJ15+DN15+DR15+DV15+DZ15+ED15+EH15 -> 0 | EU15: =T15+X15+AB15+AF15+AJ15+AN15+AR15+AV15+AZ15+BD15+BH15+BL15+BP15+BT15+BX15+CB15+CF15+CJ15+CN15+CR15+CV15+CZ15+DD15+DH15+DL15+DP15+DT15+DX15+EB15+EF15+EJ15 -> 0 | EV15: =EP15+EQ15+ES15+ET15+ER15+EU15 -> 0 | EX15: 0 | EY15: 0 | EZ15: 0 | FA15: 0 | FB15: =SUM(FF15:GI15)/2 -> 0 | FC15: =N15*km*'VALORES TABELA'!$B$13 -> 0 | FD15: =GL15 -> 0 | FF15: =((Q15+S15)*Percapita)+((R15+T15)*Cadeirante) -> 0 | FG15: =((U15+W15)*Percapita/30*FG$4)+((V15+X15)*Cadeirante/30*FG$4) -> 0 | FH15: =((Y15+AA15)*Percapita/30*FH$4)+((Z15+AB15)*Cadeirante/30*FH$4) -> 0 | FI15: =((AC15+AE15)*Percapita/30*FI$4)+((AD15+AF15)*Cadeirante/30*FI$4) -> 0 | FJ15: =((AG15+AI15)*Percapita/30*FJ$4)+((AH15+AJ15)*Cadeirante/30*FJ$4) -> 0 | FK15: =((AK15+AM15)*Percapita/30*FK$4)+((AL15+AN15)*Cadeirante/30*FK$4) -> 0 | FL15: =((AO15+AQ15)*Percapita/30*FL$4)+((AP15+AR15)*Cadeirante/30*FL$4) -> 0 | FM15: =((AS15+AU15)*Percapita/30*FM$4)+((AT15+AV15)*Cadeirante/30*FM$4) -> 0 | FN15: =((AW15+AY15)*Percapita/30*FN$4)+((AX15+AZ15)*Cadeirante/30*FN$4) -> 0 | FO15: =((BA15+BC15)*Percapita/30*FO$4)+((BB15+BD15)*Cadeirante/30*FO$4) -> 0 | FP15: =((BE15+BG15)*Percapita/30*FP$4)+((BF15+BH15)*Cadeirante/30*FP$4) -> 0 | FQ15: =((BI15+BK15)*Percapita/30*FQ$4)+((BJ15+BL15)*Cadeirante/30*FQ$4) -> 0 | FR15: =((BM15+BO15)*Percapita/30*FR$4)+((BN15+BP15)*Cadeirante/30*FR$4) -> 0 | FS15: =((BQ15+BS15)*Percapita/30*FS$4)+((BR15+BT15)*Cadeirante/30*FS$4) -> 0 | FT15: =((BU15+BW15)*Percapita/30*FT$4)+((BV15+BX15)*Cadeirante/30*FT$4) -> 0 | FU15: =((BY15+CA15)*Percapita/30*FU$4)+((BZ15+CB15)*Cadeirante/30*FU$4) -> 0 | FV15: =((CC15+CE15)*Percapita/30*FV$4)+((CD15+CF15)*Cadeirante/30*FV$4) -> 0 | FW15: =((CG15+CI15)*Percapita/30*FW$4)+((CI15+CK15)*Cadeirante/30*FW$4) -> 0 | FX15: =((CK15+CM15)*Percapita/30*FX$4)+((CL15+CN15)*Cadeirante/30*FX$4) -> 0 | FY15: =((CO15+CQ15)*Percapita/30*FY$4)+((CP15+CR15)*Cadeirante/30*FY$4) -> 0 | FZ15: =((CS15+CU15)*Percapita/30*FZ$4)+((CT15+CV15)*Cadeirante/30*FZ$4) -> 0 | GA15: =((CW15+CY15)*Percapita/30*GA$4)+((CX15+CZ15)*Cadeirante/30*GA$4) -> 0 | GB15: =((DA15+DC15)*Percapita/30*GB$4)+((DB15+DD15)*Cadeirante/30*GB$4) -> 0 | GC15: =((DE15+DG15)*Percapita/30*GC$4)+((DF15+DH15)*Cadeirante/30*GC$4) -> 0 | GD15: =((DI15+DK15)*Percapita/30*GD$4)+((DJ15+DL15)*Cadeirante/30*GD$4) -> 0 | GE15: =((DM15+DO15)*Percapita/30*GE$4)+((DN15+DP15)*Cadeirante/30*GE$4) -> 0 | GF15: =((DQ15+DS15)*Percapita/30*GF$4)+((DR15+DT15)*Cadeirante/30*GF$4) -> 0 | GG15: =((DU15+DW15)*Percapita/30*GG$4)+((DV15+DX15)*Cadeirante/30*GG$4) -> 0 | GH15: =((DY15+EA15)*Percapita/30*GH$4)+((DZ15+EB15)*Cadeirante/30*GH$4) -> 0 | GI15: =((EC15+EE15)*Percapita/30*GI$4)+((ED15+EF15)*Cadeirante/30*GI$4) -> 0 | GJ15: =((EG15+EI15)*Percapita)+((EH15+EJ15)*Cadeirante) -> 0 | GL15: =IF(J15="ADAPTADO",T15*Cadeirante/30*GM15+S15*Percapita/30*GM15,IF(J15="NORMAL",(S15+T15)*Percapita/30*GM15,IF(J15="CRECHE",0)))*-1 -> 0 | HY15: =IF(ISTEXT(EM15), VALUE(EM15), EM15) -> 0 | HZ15: =IF(ISTEXT(EN15), VALUE(EN15), EN15) -> 0 | IA15: =IF(ISTEXT(EO15), VALUE(EO15), EO15) -> 0
A16: 050.754-00 | B16: 2023/0009598-001D | C16: 1 | D16: 2023/0009598 | E16: FQG9125 | F16: 01/04/2026 | G16: 30/04/2026 | H16: A.C.G. TRANSPORTE ESCOLAR LTDA | I16: PAULA CRISTINA DA SILVA | J16: NORMAL | K16: EMEI | L16: =CONTINUA!BV16 -> 0 | M16: =CONTINUA!BW16 -> 0 | O16: 6020.2023/0009598-2 | P16: O | Q16: 52 | EP16: =Q16 -> 52 | EQ16: =U16+Y16+AC16+AG16+AK16+AO16+AS16+AW16+BA16+BE16+BI16+BM16+BQ16+BU16+BY16+CC16+CG16+CK16+CO16+CS16+CW16+DA16+DE16+DI16+DM16+DQ16+DU16+DY16+EC16+EG16 -> 0 | ER16: =S16+W16+AA16+AE16+AI16+AM16+AQ16+AU16+AY16+BC16+BG16+BK16+BO16+BS16+BW16+CA16+CE16+CI16+CM16+CQ16+CU16+CY16+DC16+DG16+DK16+DO16+DS16+DW16+EA16+EE16+EI16 -> 0 | ES16: =R16 -> 0 | ET16: =V16+Z16+AD16+AH16+AL16+AP16+AT16+AX16+BB16+BF16+BJ16+BN16+BR16+BV16+BZ16+CD16+CH16+CL16+CP16+CT16+CX16+DB16+DF16+DJ16+DN16+DR16+DV16+DZ16+ED16+EH16 -> 0 | EU16: =T16+X16+AB16+AF16+AJ16+AN16+AR16+AV16+AZ16+BD16+BH16+BL16+BP16+BT16+BX16+CB16+CF16+CJ16+CN16+CR16+CV16+CZ16+DD16+DH16+DL16+DP16+DT16+DX16+EB16+EF16+EJ16 -> 0 | EV16: =EP16+EQ16+ES16+ET16+ER16+EU16 -> 52 | EW16: =IF(C16=4,IF(MAX(Q16:EJ18)>0,(Especiall/30*(IF(($G16-$F16)=($G$5-$F$5),30,IF(DAY($G16)=31,($G16-$F16),($G16-$F16)+1)))),0),0) -> 0 | EX16: =FF16 -> 21360.8 | EY16: =(L16*regular)+(M16*Cadeirantee) -> 0 | EZ16: =SUMIF(FG16:GJ16,">0") -> 0 | FA16: =SUMIF(FG16:GJ16,"<0")+SUMIF(GN16:HP16,"<0") -> 0 | FB16: 0 | FC16: =N16*km*'VALORES TABELA'!$B$13 -> 0 | FD16: =GL16 -> 0 | FE16: =(EW16+EW17+EW18+EW19+EX16+EX17+EX18+EX19+EY16+EY17+EY18+EY19+EY20+EZ16+EZ17+EZ18+EZ19+FA16+FA17+FA18+FA19+FC16+FC17+FC18+FC19+HY16-HZ16-IA16+FD16+FD17+FD18+FD19+FB20) -> 21360.8 | FF16: =IF(C16=4,SUM(Q16+Q17+Q18+S16+S17+S18)*Percapita/30*FF$4+(R16+R17+R18+T16+T17+T18)*Cadeirante/30*FF$4,IF(C16=3,IF(Q19+S19=10,Fixo/30*FF$4+(Q16+Q17+Q18+S16+S17+S18)*Percapita/30*FF$4+(R19+T19)*Cadeirante/30*FF$4,IF(Q19+S19<=9,(Q19+S19)*Crechee/30*FF$4)+(R19+T19)*Cadeirante/30*FF$4+(Q16+Q17+Q18+S16+S17+S18)*Percapita/30*FF$4)+IF(Q19+S19>=11,Fixo/30*FF$4+(Q19+S19-10)*Crechee/30*FF$4,0),IF(C16=2,IF(R16+R17+R18+R19+T16+T17+T18+T19=1,Cadeirante/30*FF$4,IF(R16+R17+R18+R19+T16+T17+T18+T19=2,Fixo/30*FF$4,IF(R16+R17+R18+R19+T16+T17+T18+T19>2,Fixo/30*FF$4+(R16+R17+R18+R19+T16+T17+T18+T19-2)*Cadeirante/30*FF$4)))+(Q16+Q17+Q18+S16+S17+S18)*Percapita/30*FF$4+(Q19+S19)*Crechee/30*FF$4,IF(C16=1,IF(Q16+Q17+Q18+R16+R17+R18+S16+S17+S18+T16+T17+T18<=15,(Q16+Q17+Q18+S16+S17+S18)*Percapita/30*FF$4,IF(Q16+Q17+Q18+R16+R17+R18+S16+S17+S18+T16+T17+T18>=16,Fixo/30*FF$4+(Q16+Q17+Q18+R16+R17+R18+S16+S17+S18+T16+T17-16)*Percapita/30*FF$4)))))) -> 21360.8 | FG16: =IF(C16=4,SUM(U16+U17+U18+W16+W17+W18)*Percapita/30*FG$4+(V16+V17+V18+X16+X17+X18)*Cadeirante/30*FG$4,IF(C16=3,IF(U19+W19=10,Fixo/30*FG$4+(U16+U17+U18+W16+W17+W18)*Percapita/30*FG$4+(V19+X19)*Cadeirante/30*FG$4,IF(U19+W19<=9,(U19+W19)*Crechee/30*FG$4)+(V19+X19)*Cadeirante/30*FG$4+(U16+U17+U18+W16+W17+W18)*Percapita/30*FG$4)+IF(U19+W19>=11,Fixo/30*FG$4+(U19+W19-10)*Crechee/30*FG$4,0),IF(C16=2,IF(V16+V17+V18+V19+X16+X17+X18+X19=1,Cadeirante/30*FG$4,IF(V16+V17+V18+V19+X16+X17+X18+X19=2,Fixo/30*FG$4,IF(V16+V17+V18+V19+X16+X17+X18+X19>2,Fixo/30*FG$4+(V16+V17+V18+V19+X16+X17+X18+X19-2)*Cadeirante/30*FG$4)))+(U16+U17+U18+W16+W17+W18)*Percapita/30*FG$4+(U19+W19)*Crechee/30*FG$4,IF(C16=1,IF(U16+U17+U18+V16+V17+V18+W16+W17+W18+X16+X17+X18<=15,(U16+U17+U18+W16+W17+W18)*Percapita/30*FG$4,IF(U16+U17+U18+V16+V17+V18+W16+W17+W18+X16+X17+X18>=16,Fixo/30*FG$4+(U16+U17+U18+V16+V17+V18+W16+W17+W18+X16+X17-16)*Percapita/30*FG$4)))))) -> 0 | FH16: =IF(C16=4,SUM(Y16+Y17+Y18+AA16+AA17+AA18)*Percapita/30*FH$4+(Z16+Z17+Z18+AB16+AB17+AB18)*Cadeirante/30*FH$4,IF(C16=3,IF(Y19+AA19=10,Fixo/30*FH$4+(Y16+Y17+Y18+AA16+AA17+AA18)*Percapita/30*FH$4+(Z19+AB19)*Cadeirante/30*FH$4,IF(Y19+AA19<=9,(Y19+AA19)*Crechee/30*FH$4)+(Z19+AB19)*Cadeirante/30*FH$4+(Y16+Y17+Y18+AA16+AA17+AA18)*Percapita/30*FH$4)+IF(Y19+AA19>=11,Fixo/30*FH$4+(Y19+AA19-10)*Crechee/30*FH$4,0),IF(C16=2,IF(Z16+Z17+Z18+Z19+AB16+AB17+AB18+AB19=1,Cadeirante/30*FH$4,IF(Z16+Z17+Z18+Z19+AB16+AB17+AB18+AB19=2,Fixo/30*FH$4,IF(Z16+Z17+Z18+Z19+AB16+AB17+AB18+AB19>2,Fixo/30*FH$4+(Z16+Z17+Z18+Z19+AB16+AB17+AB18+AB19-2)*Cadeirante/30*FH$4)))+(Y16+Y17+Y18+AA16+AA17+AA18)*Percapita/30*FH$4+(Y19+AA19)*Crechee/30*FH$4,IF(C16=1,IF(Y16+Y17+Y18+Z16+Z17+Z18+AA16+AA17+AA18+AB16+AB17+AB18<=15,(Y16+Y17+Y18+AA16+AA17+AA18)*Percapita/30*FH$4,IF(Y16+Y17+Y18+Z16+Z17+Z18+AA16+AA17+AA18+AB16+AB17+AB18>=16,Fixo/30*FH$4+(Y16+Y17+Y18+Z16+Z17+Z18+AA16+AA17+AA18+AB16+AB17-16)*Percapita/30*FH$4)))))) -> 0 | FI16: =IF(C16=4,SUM(AC16+AC17+AC18+AE16+AE17+AE18)*Percapita/30*FI$4+(AD16+AD17+AD18+AF16+AF17+AF18)*Cadeirante/30*FI$4,IF(C16=3,IF(AC19+AE19=10,Fixo/30*FI$4+(AC16+AC17+AC18+AE16+AE17+AE18)*Percapita/30*FI$4+(AD19+AF19)*Cadeirante/30*FI$4,IF(AC19+AE19<=9,(AC19+AE19)*Crechee/30*FI$4)+(AD19+AF19)*Cadeirante/30*FI$4+(AC16+AC17+AC18+AE16+AE17+AE18)*Percapita/30*FI$4)+IF(AC19+AE19>=11,Fixo/30*FI$4+(AC19+AE19-10)*Crechee/30*FI$4,0),IF(C16=2,IF(AD16+AD17+AD18+AD19+AF16+AF17+AF18+AF19=1,Cadeirante/30*FI$4,IF(AD16+AD17+AD18+AD19+AF16+AF17+AF18+AF19=2,Fixo/30*FI$4,IF(AD16+AD17+AD18+AD19+AF16+AF17+AF18+AF19>2,Fixo/30*FI$4+(AD16+AD17+AD18+AD19+AF16+AF17+AF18+AF19-2)*Cadeirante/30*FI$4)))+(AC16+AC17+AC18+AE16+AE17+AE18)*Percapita/30*FI$4+(AC19+AE19)*Crechee/30*FI$4,IF(C16=1,IF(AC16+AC17+AC18+AD16+AD17+AD18+AE16+AE17+AE18+AF16+AF17+AF18<=15,(AC16+AC17+AC18+AE16+AE17+AE18)*Percapita/30*FI$4,IF(AC16+AC17+AC18+AD16+AD17+AD18+AE16+AE17+AE18+AF16+AF17+AF18>=16,Fixo/30*FI$4+(AC16+AC17+AC18+AD16+AD17+AD18+AE16+AE17+AE18+AF16+AF17-16)*Percapita/30*FI$4)))))) -> 0 | FJ16: =IF(C16=4,SUM(AG16+AG17+AG18+AI16+AI17+AI18)*Percapita/30*FJ$4+(AH16+AH17+AH18+AJ16+AJ17+AJ18)*Cadeirante/30*FJ$4,IF(C16=3,IF(AG19+AI19=10,Fixo/30*FJ$4+(AG16+AG17+AG18+AI16+AI17+AI18)*Percapita/30*FJ$4+(AH19+AJ19)*Cadeirante/30*FJ$4,IF(AG19+AI19<=9,(AG19+AI19)*Crechee/30*FJ$4)+(AH19+AJ19)*Cadeirante/30*FJ$4+(AG16+AG17+AG18+AI16+AI17+AI18)*Percapita/30*FJ$4)+IF(AG19+AI19>=11,Fixo/30*FJ$4+(AG19+AI19-10)*Crechee/30*FJ$4,0),IF(C16=2,IF(AH16+AH17+AH18+AH19+AJ16+AJ17+AJ18+AJ19=1,Cadeirante/30*FJ$4,IF(AH16+AH17+AH18+AH19+AJ16+AJ17+AJ18+AJ19=2,Fixo/30*FJ$4,IF(AH16+AH17+AH18+AH19+AJ16+AJ17+AJ18+AJ19>2,Fixo/30*FJ$4+(AH16+AH17+AH18+AH19+AJ16+AJ17+AJ18+AJ19-2)*Cadeirante/30*FJ$4)))+(AG16+AG17+AG18+AI16+AI17+AI18)*Percapita/30*FJ$4+(AG19+AI19)*Crechee/30*FJ$4,IF(C16=1,IF(AG16+AG17+AG18+AH16+AH17+AH18+AI16+AI17+AI18+AJ16+AJ17+AJ18<=15,(AG16+AG17+AG18+AI16+AI17+AI18)*Percapita/30*FJ$4,IF(AG16+AG17+AG18+AH16+AH17+AH18+AI16+AI17+AI18+AJ16+AJ17+AJ18>=16,Fixo/30*FJ$4+(AG16+AG17+AG18+AH16+AH17+AH18+AI16+AI17+AI18+AJ16+AJ17-16)*Percapita/30*FJ$4)))))) -> 0 | FK16: =IF(C16=4,SUM(AK16+AK17+AK18+AM16+AM17+AM18)*Percapita/30*FK$4+(AL16+AL17+AL18+AN16+AN17+AN18)*Cadeirante/30*FK$4,IF(C16=3,IF(AK19+AM19=10,Fixo/30*FK$4+(AK16+AK17+AK18+AM16+AM17+AM18)*Percapita/30*FK$4+(AL19+AN19)*Cadeirante/30*FK$4,IF(AK19+AM19<=9,(AK19+AM19)*Crechee/30*FK$4)+(AL19+AN19)*Cadeirante/30*FK$4+(AK16+AK17+AK18+AM16+AM17+AM18)*Percapita/30*FK$4)+IF(AK19+AM19>=11,Fixo/30*FK$4+(AK19+AM19-10)*Crechee/30*FK$4,0),IF(C16=2,IF(AL16+AL17+AL18+AL19+AN16+AN17+AN18+AN19=1,Cadeirante/30*FK$4,IF(AL16+AL17+AL18+AL19+AN16+AN17+AN18+AN19=2,Fixo/30*FK$4,IF(AL16+AL17+AL18+AL19+AN16+AN17+AN18+AN19>2,Fixo/30*FK$4+(AL16+AL17+AL18+AL19+AN16+AN17+AN18+AN19-2)*Cadeirante/30*FK$4)))+(AK16+AK17+AK18+AM16+AM17+AM18)*Percapita/30*FK$4+(AK19+AM19)*Crechee/30*FK$4,IF(C16=1,IF(AK16+AK17+AK18+AL16+AL17+AL18+AM16+AM17+AM18+AN16+AN17+AN18<=15,(AK16+AK17+AK18+AM16+AM17+AM18)*Percapita/30*FK$4,IF(AK16+AK17+AK18+AL16+AL17+AL18+AM16+AM17+AM18+AN16+AN17+AN18>=16,Fixo/30*FK$4+(AK16+AK17+AK18+AL16+AL17+AL18+AM16+AM17+AM18+AN16+AN17-16)*Percapita/30*FK$4)))))) -> 0 | FL16: =IF(C16=4,SUM(AO16+AO17+AO18+AQ16+AQ17+AQ18)*Percapita/30*FL$4+(AP16+AP17+AP18+AR16+AR17+AR18)*Cadeirante/30*FL$4,IF(C16=3,IF(AO19+AQ19=10,Fixo/30*FL$4+(AO16+AO17+AO18+AQ16+AQ17+AQ18)*Percapita/30*FL$4+(AP19+AR19)*Cadeirante/30*FL$4,IF(AO19+AQ19<=9,(AO19+AQ19)*Crechee/30*FL$4)+(AP19+AR19)*Cadeirante/30*FL$4+(AO16+AO17+AO18+AQ16+AQ17+AQ18)*Percapita/30*FL$4)+IF(AO19+AQ19>=11,Fixo/30*FL$4+(AO19+AQ19-10)*Crechee/30*FL$4,0),IF(C16=2,IF(AP16+AP17+AP18+AP19+AR16+AR17+AR18+AR19=1,Cadeirante/30*FL$4,IF(AP16+AP17+AP18+AP19+AR16+AR17+AR18+AR19=2,Fixo/30*FL$4,IF(AP16+AP17+AP18+AP19+AR16+AR17+AR18+AR19>2,Fixo/30*FL$4+(AP16+AP17+AP18+AP19+AR16+AR17+AR18+AR19-2)*Cadeirante/30*FL$4)))+(AO16+AO17+AO18+AQ16+AQ17+AQ18)*Percapita/30*FL$4+(AO19+AQ19)*Crechee/30*FL$4,IF(C16=1,IF(AO16+AO17+AO18+AP16+AP17+AP18+AQ16+AQ17+AQ18+AR16+AR17+AR18<=15,(AO16+AO17+AO18+AQ16+AQ17+AQ18)*Percapita/30*FL$4,IF(AO16+AO17+AO18+AP16+AP17+AP18+AQ16+AQ17+AQ18+AR16+AR17+AR18>=16,Fixo/30*FL$4+(AO16+AO17+AO18+AP16+AP17+AP18+AQ16+AQ17+AQ18+AR16+AR17-16)*Percapita/30*FL$4)))))) -> 0 | FM16: =IF(C16=4,SUM(AS16+AS17+AS18+AU16+AU17+AU18)*Percapita/30*FM$4+(AT16+AT17+AT18+AV16+AV17+AV18)*Cadeirante/30*FM$4,IF(C16=3,IF(AS19+AU19=10,Fixo/30*FM$4+(AS16+AS17+AS18+AU16+AU17+AU18)*Percapita/30*FM$4+(AT19+AV19)*Cadeirante/30*FM$4,IF(AS19+AU19<=9,(AS19+AU19)*Crechee/30*FM$4)+(AT19+AV19)*Cadeirante/30*FM$4+(AS16+AS17+AS18+AU16+AU17+AU18)*Percapita/30*FM$4)+IF(AS19+AU19>=11,Fixo/30*FM$4+(AS19+AU19-10)*Crechee/30*FM$4,0),IF(C16=2,IF(AT16+AT17+AT18+AT19+AV16+AV17+AV18+AV19=1,Cadeirante/30*FM$4,IF(AT16+AT17+AT18+AT19+AV16+AV17+AV18+AV19=2,Fixo/30*FM$4,IF(AT16+AT17+AT18+AT19+AV16+AV17+AV18+AV19>2,Fixo/30*FM$4+(AT16+AT17+AT18+AT19+AV16+AV17+AV18+AV19-2)*Cadeirante/30*FM$4)))+(AS16+AS17+AS18+AU16+AU17+AU18)*Percapita/30*FM$4+(AS19+AU19)*Crechee/30*FM$4,IF(C16=1,IF(AS16+AS17+AS18+AT16+AT17+AT18+AU16+AU17+AU18+AV16+AV17+AV18<=15,(AS16+AS17+AS18+AU16+AU17+AU18)*Percapita/30*FM$4,IF(AS16+AS17+AS18+AT16+AT17+AT18+AU16+AU17+AU18+AV16+AV17+AV18>=16,Fixo/30*FM$4+(AS16+AS17+AS18+AT16+AT17+AT18+AU16+AU17+AU18+AV16+AV17-16)*Percapita/30*FM$4)))))) -> 0 | FN16: =IF(C16=4,SUM(AW16+AW17+AW18+AY16+AY17+AY18)*Percapita/30*FN$4+(AX16+AX17+AX18+AZ16+AZ17+AZ18)*Cadeirante/30*FN$4,IF(C16=3,IF(AW19+AY19=10,Fixo/30*FN$4+(AW16+AW17+AW18+AY16+AY17+AY18)*Percapita/30*FN$4+(AX19+AZ19)*Cadeirante/30*FN$4,IF(AW19+AY19<=9,(AW19+AY19)*Crechee/30*FN$4)+(AX19+AZ19)*Cadeirante/30*FN$4+(AW16+AW17+AW18+AY16+AY17+AY18)*Percapita/30*FN$4)+IF(AW19+AY19>=11,Fixo/30*FN$4+(AW19+AY19-10)*Crechee/30*FN$4,0),IF(C16=2,IF(AX16+AX17+AX18+AX19+AZ16+AZ17+AZ18+AZ19=1,Cadeirante/30*FN$4,IF(AX16+AX17+AX18+AX19+AZ16+AZ17+AZ18+AZ19=2,Fixo/30*FN$4,IF(AX16+AX17+AX18+AX19+AZ16+AZ17+AZ18+AZ19>2,Fixo/30*FN$4+(AX16+AX17+AX18+AX19+AZ16+AZ17+AZ18+AZ19-2)*Cadeirante/30*FN$4)))+(AW16+AW17+AW18+AY16+AY17+AY18)*Percapita/30*FN$4+(AW19+AY19)*Crechee/30*FN$4,IF(C16=1,IF(AW16+AW17+AW18+AX16+AX17+AX18+AY16+AY17+AY18+AZ16+AZ17+AZ18<=15,(AW16+AW17+AW18+AY16+AY17+AY18)*Percapita/30*FN$4,IF(AW16+AW17+AW18+AX16+AX17+AX18+AY16+AY17+AY18+AZ16+AZ17+AZ18>=16,Fixo/30*FN$4+(AW16+AW17+AW18+AX16+AX17+AX18+AY16+AY17+AY18+AZ16+AZ17-16)*Percapita/30*FN$4)))))) -> 0 | FO16: =IF(C16=4,SUM(BA16+BA17+BA18+BC16+BC17+BC18)*Percapita/30*FO$4+(BB16+BB17+BB18+BD16+BD17+BD18)*Cadeirante/30*FO$4,IF(C16=3,IF(BA19+BC19=10,Fixo/30*FO$4+(BA16+BA17+BA18+BC16+BC17+BC18)*Percapita/30*FO$4+(BB19+BD19)*Cadeirante/30*FO$4,IF(BA19+BC19<=9,(BA19+BC19)*Crechee/30*FO$4)+(BB19+BD19)*Cadeirante/30*FO$4+(BA16+BA17+BA18+BC16+BC17+BC18)*Percapita/30*FO$4)+IF(BA19+BC19>=11,Fixo/30*FO$4+(BA19+BC19-10)*Crechee/30*FO$4,0),IF(C16=2,IF(BB16+BB17+BB18+BB19+BD16+BD17+BD18+BD19=1,Cadeirante/30*FO$4,IF(BB16+BB17+BB18+BB19+BD16+BD17+BD18+BD19=2,Fixo/30*FO$4,IF(BB16+BB17+BB18+BB19+BD16+BD17+BD18+BD19>2,Fixo/30*FO$4+(BB16+BB17+BB18+BB19+BD16+BD17+BD18+BD19-2)*Cadeirante/30*FO$4)))+(BA16+BA17+BA18+BC16+BC17+BC18)*Percapita/30*FO$4+(BA19+BC19)*Crechee/30*FO$4,IF(C16=1,IF(BA16+BA17+BA18+BB16+BB17+BB18+BC16+BC17+BC18+BD16+BD17+BD18<=15,(BA16+BA17+BA18+BC16+BC17+BC18)*Percapita/30*FO$4,IF(BA16+BA17+BA18+BB16+BB17+BB18+BC16+BC17+BC18+BD16+BD17+BD18>=16,Fixo/30*FO$4+(BA16+BA17+BA18+BB16+BB17+BB18+BC16+BC17+BC18+BD16+BD17-16)*Percapita/30*FO$4)))))) -> 0 | FP16: =IF(C16=4,SUM(BE16+BE17+BE18+BG16+BG17+BG18)*Percapita/30*FP$4+(BF16+BF17+BF18+BH16+BH17+BH18)*Cadeirante/30*FP$4,IF(C16=3,IF(BE19+BG19=10,Fixo/30*FP$4+(BE16+BE17+BE18+BG16+BG17+BG18)*Percapita/30*FP$4+(BF19+BH19)*Cadeirante/30*FP$4,IF(BE19+BG19<=9,(BE19+BG19)*Crechee/30*FP$4)+(BF19+BH19)*Cadeirante/30*FP$4+(BE16+BE17+BE18+BG16+BG17+BG18)*Percapita/30*FP$4)+IF(BE19+BG19>=11,Fixo/30*FP$4+(BE19+BG19-10)*Crechee/30*FP$4,0),IF(C16=2,IF(BF16+BF17+BF18+BF19+BH16+BH17+BH18+BH19=1,Cadeirante/30*FP$4,IF(BF16+BF17+BF18+BF19+BH16+BH17+BH18+BH19=2,Fixo/30*FP$4,IF(BF16+BF17+BF18+BF19+BH16+BH17+BH18+BH19>2,Fixo/30*FP$4+(BF16+BF17+BF18+BF19+BH16+BH17+BH18+BH19-2)*Cadeirante/30*FP$4)))+(BE16+BE17+BE18+BG16+BG17+BG18)*Percapita/30*FP$4+(BE19+BG19)*Crechee/30*FP$4,IF(C16=1,IF(BE16+BE17+BE18+BF16+BF17+BF18+BG16+BG17+BG18+BH16+BH17+BH18<=15,(BE16+BE17+BE18+BG16+BG17+BG18)*Percapita/30*FP$4,IF(BE16+BE17+BE18+BF16+BF17+BF18+BG16+BG17+BG18+BH16+BH17+BH18>=16,Fixo/30*FP$4+(BE16+BE17+BE18+BF16+BF17+BF18+BG16+BG17+BG18+BH16+BH17-16)*Percapita/30*FP$4)))))) -> 0 | FQ16: =IF(C16=4,SUM(BI16+BI17+BI18+BK16+BK17+BK18)*Percapita/30*FQ$4+(BJ16+BJ17+BJ18+BL16+BL17+BL18)*Cadeirante/30*FQ$4,IF(C16=3,IF(BI19+BK19=10,Fixo/30*FQ$4+(BI16+BI17+BI18+BK16+BK17+BK18)*Percapita/30*FQ$4+(BJ19+BL19)*Cadeirante/30*FQ$4,IF(BI19+BK19<=9,(BI19+BK19)*Crechee/30*FQ$4)+(BJ19+BL19)*Cadeirante/30*FQ$4+(BI16+BI17+BI18+BK16+BK17+BK18)*Percapita/30*FQ$4)+IF(BI19+BK19>=11,Fixo/30*FQ$4+(BI19+BK19-10)*Crechee/30*FQ$4,0),IF(C16=2,IF(BJ16+BJ17+BJ18+BJ19+BL16+BL17+BL18+BL19=1,Cadeirante/30*FQ$4,IF(BJ16+BJ17+BJ18+BJ19+BL16+BL17+BL18+BL19=2,Fixo/30*FQ$4,IF(BJ16+BJ17+BJ18+BJ19+BL16+BL17+BL18+BL19>2,Fixo/30*FQ$4+(BJ16+BJ17+BJ18+BJ19+BL16+BL17+BL18+BL19-2)*Cadeirante/30*FQ$4)))+(BI16+BI17+BI18+BK16+BK17+BK18)*Percapita/30*FQ$4+(BI19+BK19)*Crechee/30*FQ$4,IF(C16=1,IF(BI16+BI17+BI18+BJ16+BJ17+BJ18+BK16+BK17+BK18+BL16+BL17+BL18<=15,(BI16+BI17+BI18+BK16+BK17+BK18)*Percapita/30*FQ$4,IF(BI16+BI17+BI18+BJ16+BJ17+BJ18+BK16+BK17+BK18+BL16+BL17+BL18>=16,Fixo/30*FQ$4+(BI16+BI17+BI18+BJ16+BJ17+BJ18+BK16+BK17+BK18+BL16+BL17-16)*Percapita/30*FQ$4)))))) -> 0 | FR16: =IF(C16=4,SUM(BM16+BM17+BM18+BO16+BO17+BO18)*Percapita/30*FR$4+(BN16+BN17+BN18+BP16+BP17+BP18)*Cadeirante/30*FR$4,IF(C16=3,IF(BM19+BO19=10,Fixo/30*FR$4+(BM16+BM17+BM18+BO16+BO17+BO18)*Percapita/30*FR$4+(BN19+BP19)*Cadeirante/30*FR$4,IF(BM19+BO19<=9,(BM19+BO19)*Crechee/30*FR$4)+(BN19+BP19)*Cadeirante/30*FR$4+(BM16+BM17+BM18+BO16+BO17+BO18)*Percapita/30*FR$4)+IF(BM19+BO19>=11,Fixo/30*FR$4+(BM19+BO19-10)*Crechee/30*FR$4,0),IF(C16=2,IF(BN16+BN17+BN18+BN19+BP16+BP17+BP18+BP19=1,Cadeirante/30*FR$4,IF(BN16+BN17+BN18+BN19+BP16+BP17+BP18+BP19=2,Fixo/30*FR$4,IF(BN16+BN17+BN18+BN19+BP16+BP17+BP18+BP19>2,Fixo/30*FR$4+(BN16+BN17+BN18+BN19+BP16+BP17+BP18+BP19-2)*Cadeirante/30*FR$4)))+(BM16+BM17+BM18+BO16+BO17+BO18)*Percapita/30*FR$4+(BM19+BO19)*Crechee/30*FR$4,IF(C16=1,IF(BM16+BM17+BM18+BN16+BN17+BN18+BO16+BO17+BO18+BP16+BP17+BP18<=15,(BM16+BM17+BM18+BO16+BO17+BO18)*Percapita/30*FR$4,IF(BM16+BM17+BM18+BN16+BN17+BN18+BO16+BO17+BO18+BP16+BP17+BP18>=16,Fixo/30*FR$4+(BM16+BM17+BM18+BN16+BN17+BN18+BO16+BO17+BO18+BP16+BP17-16)*Percapita/30*FR$4)))))) -> 0 | FS16: =IF(C16=4,SUM(BQ16+BQ17+BQ18+BS16+BS17+BS18)*Percapita/30*FS$4+(BR16+BR17+BR18+BT16+BT17+BT18)*Cadeirante/30*FS$4,IF(C16=3,IF(BQ19+BS19=10,Fixo/30*FS$4+(BQ16+BQ17+BQ18+BS16+BS17+BS18)*Percapita/30*FS$4+(BR19+BT19)*Cadeirante/30*FS$4,IF(BQ19+BS19<=9,(BQ19+BS19)*Crechee/30*FS$4)+(BR19+BT19)*Cadeirante/30*FS$4+(BQ16+BQ17+BQ18+BS16+BS17+BS18)*Percapita/30*FS$4)+IF(BQ19+BS19>=11,Fixo/30*FS$4+(BQ19+BS19-10)*Crechee/30*FS$4,0),IF(C16=2,IF(BR16+BR17+BR18+BR19+BT16+BT17+BT18+BT19=1,Cadeirante/30*FS$4,IF(BR16+BR17+BR18+BR19+BT16+BT17+BT18+BT19=2,Fixo/30*FS$4,IF(BR16+BR17+BR18+BR19+BT16+BT17+BT18+BT19>2,Fixo/30*FS$4+(BR16+BR17+BR18+BR19+BT16+BT17+BT18+BT19-2)*Cadeirante/30*FS$4)))+(BQ16+BQ17+BQ18+BS16+BS17+BS18)*Percapita/30*FS$4+(BQ19+BS19)*Crechee/30*FS$4,IF(C16=1,IF(BQ16+BQ17+BQ18+BR16+BR17+BR18+BS16+BS17+BS18+BT16+BT17+BT18<=15,(BQ16+BQ17+BQ18+BS16+BS17+BS18)*Percapita/30*FS$4,IF(BQ16+BQ17+BQ18+BR16+BR17+BR18+BS16+BS17+BS18+BT16+BT17+BT18>=16,Fixo/30*FS$4+(BQ16+BQ17+BQ18+BR16+BR17+BR18+BS16+BS17+BS18+BT16+BT17-16)*Percapita/30*FS$4)))))) -> 0 | FT16: =IF(C16=4,SUM(BU16+BU17+BU18+BW16+BW17+BW18)*Percapita/30*FT$4+(BV16+BV17+BV18+BX16+BX17+BX18)*Cadeirante/30*FT$4,IF(C16=3,IF(BU19+BW19=10,Fixo/30*FT$4+(BU16+BU17+BU18+BW16+BW17+BW18)*Percapita/30*FT$4+(BV19+BX19)*Cadeirante/30*FT$4,IF(BU19+BW19<=9,(BU19+BW19)*Crechee/30*FT$4)+(BV19+BX19)*Cadeirante/30*FT$4+(BU16+BU17+BU18+BW16+BW17+BW18)*Percapita/30*FT$4)+IF(BU19+BW19>=11,Fixo/30*FT$4+(BU19+BW19-10)*Crechee/30*FT$4,0),IF(C16=2,IF(BV16+BV17+BV18+BV19+BX16+BX17+BX18+BX19=1,Cadeirante/30*FT$4,IF(BV16+BV17+BV18+BV19+BX16+BX17+BX18+BX19=2,Fixo/30*FT$4,IF(BV16+BV17+BV18+BV19+BX16+BX17+BX18+BX19>2,Fixo/30*FT$4+(BV16+BV17+BV18+BV19+BX16+BX17+BX18+BX19-2)*Cadeirante/30*FT$4)))+(BU16+BU17+BU18+BW16+BW17+BW18)*Percapita/30*FT$4+(BU19+BW19)*Crechee/30*FT$4,IF(C16=1,IF(BU16+BU17+BU18+BV16+BV17+BV18+BW16+BW17+BW18+BX16+BX17+BX18<=15,(BU16+BU17+BU18+BW16+BW17+BW18)*Percapita/30*FT$4,IF(BU16+BU17+BU18+BV16+BV17+BV18+BW16+BW17+BW18+BX16+BX17+BX18>=16,Fixo/30*FT$4+(BU16+BU17+BU18+BV16+BV17+BV18+BW16+BW17+BW18+BX16+BX17-16)*Percapita/30*FT$4)))))) -> 0 | FU16: =IF(C16=4,SUM(BY16+BY17+BY18+CA16+CA17+CA18)*Percapita/30*FU$4+(BZ16+BZ17+BZ18+CB16+CB17+CB18)*Cadeirante/30*FU$4,IF(C16=3,IF(BY19+CA19=10,Fixo/30*FU$4+(BY16+BY17+BY18+CA16+CA17+CA18)*Percapita/30*FU$4+(BZ19+CB19)*Cadeirante/30*FU$4,IF(BY19+CA19<=9,(BY19+CA19)*Crechee/30*FU$4)+(BZ19+CB19)*Cadeirante/30*FU$4+(BY16+BY17+BY18+CA16+CA17+CA18)*Percapita/30*FU$4)+IF(BY19+CA19>=11,Fixo/30*FU$4+(BY19+CA19-10)*Crechee/30*FU$4,0),IF(C16=2,IF(BZ16+BZ17+BZ18+BZ19+CB16+CB17+CB18+CB19=1,Cadeirante/30*FU$4,IF(BZ16+BZ17+BZ18+BZ19+CB16+CB17+CB18+CB19=2,Fixo/30*FU$4,IF(BZ16+BZ17+BZ18+BZ19+CB16+CB17+CB18+CB19>2,Fixo/30*FU$4+(BZ16+BZ17+BZ18+BZ19+CB16+CB17+CB18+CB19-2)*Cadeirante/30*FU$4)))+(BY16+BY17+BY18+CA16+CA17+CA18)*Percapita/30*FU$4+(BY19+CA19)*Crechee/30*FU$4,IF(C16=1,IF(BY16+BY17+BY18+BZ16+BZ17+BZ18+CA16+CA17+CA18+CB16+CB17+CB18<=15,(BY16+BY17+BY18+CA16+CA17+CA18)*Percapita/30*FU$4,IF(BY16+BY17+BY18+BZ16+BZ17+BZ18+CA16+CA17+CA18+CB16+CB17+CB18>=16,Fixo/30*FU$4+(BY16+BY17+BY18+BZ16+BZ17+BZ18+CA16+CA17+CA18+CB16+CB17-16)*Percapita/30*FU$4)))))) -> 0 | FV16: =IF(C16=4,SUM(CC16+CC17+CC18+CE16+CE17+CE18)*Percapita/30*FV$4+(CD16+CD17+CD18+CF16+CF17+CF18)*Cadeirante/30*FV$4,IF(C16=3,IF(CC19+CE19=10,Fixo/30*FV$4+(CC16+CC17+CC18+CE16+CE17+CE18)*Percapita/30*FV$4+(CD19+CF19)*Cadeirante/30*FV$4,IF(CC19+CE19<=9,(CC19+CE19)*Crechee/30*FV$4)+(CD19+CF19)*Cadeirante/30*FV$4+(CC16+CC17+CC18+CE16+CE17+CE18)*Percapita/30*FV$4)+IF(CC19+CE19>=11,Fixo/30*FV$4+(CC19+CE19-10)*Crechee/30*FV$4,0),IF(C16=2,IF(CD16+CD17+CD18+CD19+CF16+CF17+CF18+CF19=1,Cadeirante/30*FV$4,IF(CD16+CD17+CD18+CD19+CF16+CF17+CF18+CF19=2,Fixo/30*FV$4,IF(CD16+CD17+CD18+CD19+CF16+CF17+CF18+CF19>2,Fixo/30*FV$4+(CD16+CD17+CD18+CD19+CF16+CF17+CF18+CF19-2)*Cadeirante/30*FV$4)))+(CC16+CC17+CC18+CE16+CE17+CE18)*Percapita/30*FV$4+(CC19+CE19)*Crechee/30*FV$4,IF(C16=1,IF(CC16+CC17+CC18+CD16+CD17+CD18+CE16+CE17+CE18+CF16+CF17+CF18<=15,(CC16+CC17+CC18+CE16+CE17+CE18)*Percapita/30*FV$4,IF(CC16+CC17+CC18+CD16+CD17+CD18+CE16+CE17+CE18+CF16+CF17+CF18>=16,Fixo/30*FV$4+(CC16+CC17+CC18+CD16+CD17+CD18+CE16+CE17+CE18+CF16+CF17-16)*Percapita/30*FV$4)))))) -> 0 | FW16: =IF(C16=4,SUM(CG16+CG17+CG18+CI16+CI17+CI18)*Percapita/30*FW$4+(CH16+CH17+CH18+CJ16+CJ17+CJ18)*Cadeirante/30*FW$4,IF(C16=3,IF(CG19+CI19=10,Fixo/30*FW$4+(CG16+CG17+CG18+CI16+CI17+CI18)*Percapita/30*FW$4+(CH19+CJ19)*Cadeirante/30*FW$4,IF(CG19+CI19<=9,(CG19+CI19)*Crechee/30*FW$4)+(CH19+CJ19)*Cadeirante/30*FW$4+(CG16+CG17+CG18+CI16+CI17+CI18)*Percapita/30*FW$4)+IF(CG19+CI19>=11,Fixo/30*FW$4+(CG19+CI19-10)*Crechee/30*FW$4,0),IF(C16=2,IF(CH16+CH17+CH18+CH19+CJ16+CJ17+CJ18+CJ19=1,Cadeirante/30*FW$4,IF(CH16+CH17+CH18+CH19+CJ16+CJ17+CJ18+CJ19=2,Fixo/30*FW$4,IF(CH16+CH17+CH18+CH19+CJ16+CJ17+CJ18+CJ19>2,Fixo/30*FW$4+(CH16+CH17+CH18+CH19+CJ16+CJ17+CJ18+CJ19-2)*Cadeirante/30*FW$4)))+(CG16+CG17+CG18+CI16+CI17+CI18)*Percapita/30*FW$4+(CG19+CI19)*Crechee/30*FW$4,IF(C16=1,IF(CG16+CG17+CG18+CH16+CH17+CH18+CI16+CI17+CI18+CJ16+CJ17+CJ18<=15,(CG16+CG17+CG18+CI16+CI17+CI18)*Percapita/30*FW$4,IF(CG16+CG17+CG18+CH16+CH17+CH18+CI16+CI17+CI18+CJ16+CJ17+CJ18>=16,Fixo/30*FW$4+(CG16+CG17+CG18+CH16+CH17+CH18+CI16+CI17+CI18+CJ16+CJ17-16)*Percapita/30*FW$4)))))) -> 0 | FX16: =IF(C16=4,SUM(CK16+CK17+CK18+CM16+CM17+CM18)*Percapita/30*FX$4+(CL16+CL17+CL18+CN16+CN17+CN18)*Cadeirante/30*FX$4,IF(C16=3,IF(CK19+CM19=10,Fixo/30*FX$4+(CK16+CK17+CK18+CM16+CM17+CM18)*Percapita/30*FX$4+(CL19+CN19)*Cadeirante/30*FX$4,IF(CK19+CM19<=9,(CK19+CM19)*Crechee/30*FX$4)+(CL19+CN19)*Cadeirante/30*FX$4+(CK16+CK17+CK18+CM16+CM17+CM18)*Percapita/30*FX$4)+IF(CK19+CM19>=11,Fixo/30*FX$4+(CK19+CM19-10)*Crechee/30*FX$4,0),IF(C16=2,IF(CL16+CL17+CL18+CL19+CN16+CN17+CN18+CN19=1,Cadeirante/30*FX$4,IF(CL16+CL17+CL18+CL19+CN16+CN17+CN18+CN19=2,Fixo/30*FX$4,IF(CL16+CL17+CL18+CL19+CN16+CN17+CN18+CN19>2,Fixo/30*FX$4+(CL16+CL17+CL18+CL19+CN16+CN17+CN18+CN19-2)*Cadeirante/30*FX$4)))+(CK16+CK17+CK18+CM16+CM17+CM18)*Percapita/30*FX$4+(CK19+CM19)*Crechee/30*FX$4,IF(C16=1,IF(CK16+CK17+CK18+CL16+CL17+CL18+CM16+CM17+CM18+CN16+CN17+CN18<=15,(CK16+CK17+CK18+CM16+CM17+CM18)*Percapita/30*FX$4,IF(CK16+CK17+CK18+CL16+CL17+CL18+CM16+CM17+CM18+CN16+CN17+CN18>=16,Fixo/30*FX$4+(CK16+CK17+CK18+CL16+CL17+CL18+CM16+CM17+CM18+CN16+CN17-16)*Percapita/30*FX$4)))))) -> 0 | FY16: =IF(C16=4,SUM(CO16+CO17+CO18+CQ16+CQ17+CQ18)*Percapita/30*FY$4+(CP16+CP17+CP18+CR16+CR17+CR18)*Cadeirante/30*FY$4,IF(C16=3,IF(CO19+CQ19=10,Fixo/30*FY$4+(CO16+CO17+CO18+CQ16+CQ17+CQ18)*Percapita/30*FY$4+(CP19+CR19)*Cadeirante/30*FY$4,IF(CO19+CQ19<=9,(CO19+CQ19)*Crechee/30*FY$4)+(CP19+CR19)*Cadeirante/30*FY$4+(CO16+CO17+CO18+CQ16+CQ17+CQ18)*Percapita/30*FY$4)+IF(CO19+CQ19>=11,Fixo/30*FY$4+(CO19+CQ19-10)*Crechee/30*FY$4,0),IF(C16=2,IF(CP16+CP17+CP18+CP19+CR16+CR17+CR18+CR19=1,Cadeirante/30*FY$4,IF(CP16+CP17+CP18+CP19+CR16+CR17+CR18+CR19=2,Fixo/30*FY$4,IF(CP16+CP17+CP18+CP19+CR16+CR17+CR18+CR19>2,Fixo/30*FY$4+(CP16+CP17+CP18+CP19+CR16+CR17+CR18+CR19-2)*Cadeirante/30*FY$4)))+(CO16+CO17+CO18+CQ16+CQ17+CQ18)*Percapita/30*FY$4+(CO19+CQ19)*Crechee/30*FY$4,IF(C16=1,IF(CO16+CO17+CO18+CP16+CP17+CP18+CQ16+CQ17+CQ18+CR16+CR17+CR18<=15,(CO16+CO17+CO18+CQ16+CQ17+CQ18)*Percapita/30*FY$4,IF(CO16+CO17+CO18+CP16+CP17+CP18+CQ16+CQ17+CQ18+CR16+CR17+CR18>=16,Fixo/30*FY$4+(CO16+CO17+CO18+CP16+CP17+CP18+CQ16+CQ17+CQ18+CR16+CR17-16)*Percapita/30*FY$4)))))) -> 0 | FZ16: =IF(C16=4,SUM(CS16+CS17+CS18+CU16+CU17+CU18)*Percapita/30*FZ$4+(CT16+CT17+CT18+CV16+CV17+CV18)*Cadeirante/30*FZ$4,IF(C16=3,IF(CS19+CU19=10,Fixo/30*FZ$4+(CS16+CS17+CS18+CU16+CU17+CU18)*Percapita/30*FZ$4+(CT19+CV19)*Cadeirante/30*FZ$4,IF(CS19+CU19<=9,(CS19+CU19)*Crechee/30*FZ$4)+(CT19+CV19)*Cadeirante/30*FZ$4+(CS16+CS17+CS18+CU16+CU17+CU18)*Percapita/30*FZ$4)+IF(CS19+CU19>=11,Fixo/30*FZ$4+(CS19+CU19-10)*Crechee/30*FZ$4,0),IF(C16=2,IF(CT16+CT17+CT18+CT19+CV16+CV17+CV18+CV19=1,Cadeirante/30*FZ$4,IF(CT16+CT17+CT18+CT19+CV16+CV17+CV18+CV19=2,Fixo/30*FZ$4,IF(CT16+CT17+CT18+CT19+CV16+CV17+CV18+CV19>2,Fixo/30*FZ$4+(CT16+CT17+CT18+CT19+CV16+CV17+CV18+CV19-2)*Cadeirante/30*FZ$4)))+(CS16+CS17+CS18+CU16+CU17+CU18)*Percapita/30*FZ$4+(CS19+CU19)*Crechee/30*FZ$4,IF(C16=1,IF(CS16+CS17+CS18+CT16+CT17+CT18+CU16+CU17+CU18+CV16+CV17+CV18<=15,(CS16+CS17+CS18+CU16+CU17+CU18)*Percapita/30*FZ$4,IF(CS16+CS17+CS18+CT16+CT17+CT18+CU16+CU17+CU18+CV16+CV17+CV18>=16,Fixo/30*FZ$4+(CS16+CS17+CS18+CT16+CT17+CT18+CU16+CU17+CU18+CV16+CV17-16)*Percapita/30*FZ$4)))))) -> 0 | GA16: =IF(C16=4,SUM(CW16+CW17+CW18+CY16+CY17+CY18)*Percapita/30*GA$4+(CX16+CX17+CX18+CZ16+CZ17+CZ18)*Cadeirante/30*GA$4,IF(C16=3,IF(CW19+CY19=10,Fixo/30*GA$4+(CW16+CW17+CW18+CY16+CY17+CY18)*Percapita/30*GA$4+(CX19+CZ19)*Cadeirante/30*GA$4,IF(CW19+CY19<=9,(CW19+CY19)*Crechee/30*GA$4)+(CX19+CZ19)*Cadeirante/30*GA$4+(CW16+CW17+CW18+CY16+CY17+CY18)*Percapita/30*GA$4)+IF(CW19+CY19>=11,Fixo/30*GA$4+(CW19+CY19-10)*Crechee/30*GA$4,0),IF(C16=2,IF(CX16+CX17+CX18+CX19+CZ16+CZ17+CZ18+CZ19=1,Cadeirante/30*GA$4,IF(CX16+CX17+CX18+CX19+CZ16+CZ17+CZ18+CZ19=2,Fixo/30*GA$4,IF(CX16+CX17+CX18+CX19+CZ16+CZ17+CZ18+CZ19>2,Fixo/30*GA$4+(CX16+CX17+CX18+CX19+CZ16+CZ17+CZ18+CZ19-2)*Cadeirante/30*GA$4)))+(CW16+CW17+CW18+CY16+CY17+CY18)*Percapita/30*GA$4+(CW19+CY19)*Crechee/30*GA$4,IF(C16=1,IF(CW16+CW17+CW18+CX16+CX17+CX18+CY16+CY17+CY18+CZ16+CZ17+CZ18<=15,(CW16+CW17+CW18+CY16+CY17+CY18)*Percapita/30*GA$4,IF(CW16+CW17+CW18+CX16+CX17+CX18+CY16+CY17+CY18+CZ16+CZ17+CZ18>=16,Fixo/30*GA$4+(CW16+CW17+CW18+CX16+CX17+CX18+CY16+CY17+CY18+CZ16+CZ17-16)*Percapita/30*GA$4)))))) -> 0 | GB16: =IF(C16=4,SUM(DA16+DA17+DA18+DC16+DC17+DC18)*Percapita/30*GB$4+(DB16+DB17+DB18+DD16+DD17+DD18)*Cadeirante/30*GB$4,IF(C16=3,IF(DA19+DC19=10,Fixo/30*GB$4+(DA16+DA17+DA18+DC16+DC17+DC18)*Percapita/30*GB$4+(DB19+DD19)*Cadeirante/30*GB$4,IF(DA19+DC19<=9,(DA19+DC19)*Crechee/30*GB$4)+(DB19+DD19)*Cadeirante/30*GB$4+(DA16+DA17+DA18+DC16+DC17+DC18)*Percapita/30*GB$4)+IF(DA19+DC19>=11,Fixo/30*GB$4+(DA19+DC19-10)*Crechee/30*GB$4,0),IF(C16=2,IF(DB16+DB17+DB18+DB19+DD16+DD17+DD18+DD19=1,Cadeirante/30*GB$4,IF(DB16+DB17+DB18+DB19+DD16+DD17+DD18+DD19=2,Fixo/30*GB$4,IF(DB16+DB17+DB18+DB19+DD16+DD17+DD18+DD19>2,Fixo/30*GB$4+(DB16+DB17+DB18+DB19+DD16+DD17+DD18+DD19-2)*Cadeirante/30*GB$4)))+(DA16+DA17+DA18+DC16+DC17+DC18)*Percapita/30*GB$4+(DA19+DC19)*Crechee/30*GB$4,IF(C16=1,IF(DA16+DA17+DA18+DB16+DB17+DB18+DC16+DC17+DC18+DD16+DD17+DD18<=15,(DA16+DA17+DA18+DC16+DC17+DC18)*Percapita/30*GB$4,IF(DA16+DA17+DA18+DB16+DB17+DB18+DC16+DC17+DC18+DD16+DD17+DD18>=16,Fixo/30*GB$4+(DA16+DA17+DA18+DB16+DB17+DB18+DC16+DC17+DC18+DD16+DD17-16)*Percapita/30*GB$4)))))) -> 0 | GC16: =IF(C16=4,SUM(DE16+DE17+DE18+DG16+DG17+DG18)*Percapita/30*GC$4+(DF16+DF17+DF18+DH16+DH17+DH18)*Cadeirante/30*GC$4,IF(C16=3,IF(DE19+DG19=10,Fixo/30*GC$4+(DE16+DE17+DE18+DG16+DG17+DG18)*Percapita/30*GC$4+(DF19+DH19)*Cadeirante/30*GC$4,IF(DE19+DG19<=9,(DE19+DG19)*Crechee/30*GC$4)+(DF19+DH19)*Cadeirante/30*GC$4+(DE16+DE17+DE18+DG16+DG17+DG18)*Percapita/30*GC$4)+IF(DE19+DG19>=11,Fixo/30*GC$4+(DE19+DG19-10)*Crechee/30*GC$4,0),IF(C16=2,IF(DF16+DF17+DF18+DF19+DH16+DH17+DH18+DH19=1,Cadeirante/30*GC$4,IF(DF16+DF17+DF18+DF19+DH16+DH17+DH18+DH19=2,Fixo/30*GC$4,IF(DF16+DF17+DF18+DF19+DH16+DH17+DH18+DH19>2,Fixo/30*GC$4+(DF16+DF17+DF18+DF19+DH16+DH17+DH18+DH19-2)*Cadeirante/30*GC$4)))+(DE16+DE17+DE18+DG16+DG17+DG18)*Percapita/30*GC$4+(DE19+DG19)*Crechee/30*GC$4,IF(C16=1,IF(DE16+DE17+DE18+DF16+DF17+DF18+DG16+DG17+DG18+DH16+DH17+DH18<=15,(DE16+DE17+DE18+DG16+DG17+DG18)*Percapita/30*GC$4,IF(DE16+DE17+DE18+DF16+DF17+DF18+DG16+DG17+DG18+DH16+DH17+DH18>=16,Fixo/30*GC$4+(DE16+DE17+DE18+DF16+DF17+DF18+DG16+DG17+DG18+DH16+DH17-16)*Percapita/30*GC$4)))))) -> 0 | GD16: =IF(C16=4,SUM(DI16+DI17+DI18+DK16+DK17+DK18)*Percapita/30*GD$4+(DJ16+DJ17+DJ18+DL16+DL17+DL18)*Cadeirante/30*GD$4,IF(C16=3,IF(DI19+DK19=10,Fixo/30*GD$4+(DI16+DI17+DI18+DK16+DK17+DK18)*Percapita/30*GD$4+(DJ19+DL19)*Cadeirante/30*GD$4,IF(DI19+DK19<=9,(DI19+DK19)*Crechee/30*GD$4)+(DJ19+DL19)*Cadeirante/30*GD$4+(DI16+DI17+DI18+DK16+DK17+DK18)*Percapita/30*GD$4)+IF(DI19+DK19>=11,Fixo/30*GD$4+(DI19+DK19-10)*Crechee/30*GD$4,0),IF(C16=2,IF(DJ16+DJ17+DJ18+DJ19+DL16+DL17+DL18+DL19=1,Cadeirante/30*GD$4,IF(DJ16+DJ17+DJ18+DJ19+DL16+DL17+DL18+DL19=2,Fixo/30*GD$4,IF(DJ16+DJ17+DJ18+DJ19+DL16+DL17+DL18+DL19>2,Fixo/30*GD$4+(DJ16+DJ17+DJ18+DJ19+DL16+DL17+DL18+DL19-2)*Cadeirante/30*GD$4)))+(DI16+DI17+DI18+DK16+DK17+DK18)*Percapita/30*GD$4+(DI19+DK19)*Crechee/30*GD$4,IF(C16=1,IF(DI16+DI17+DI18+DJ16+DJ17+DJ18+DK16+DK17+DK18+DL16+DL17+DL18<=15,(DI16+DI17+DI18+DK16+DK17+DK18)*Percapita/30*GD$4,IF(DI16+DI17+DI18+DJ16+DJ17+DJ18+DK16+DK17+DK18+DL16+DL17+DL18>=16,Fixo/30*GD$4+(DI16+DI17+DI18+DJ16+DJ17+DJ18+DK16+DK17+DK18+DL16+DL17-16)*Percapita/30*GD$4)))))) -> 0 | GE16: =IF(C16=4,SUM(DM16+DM17+DM18+DO16+DO17+DO18)*Percapita/30*GE$4+(DN16+DN17+DN18+DP16+DP17+DP18)*Cadeirante/30*GE$4,IF(C16=3,IF(DM19+DO19=10,Fixo/30*GE$4+(DM16+DM17+DM18+DO16+DO17+DO18)*Percapita/30*GE$4+(DN19+DP19)*Cadeirante/30*GE$4,IF(DM19+DO19<=9,(DM19+DO19)*Crechee/30*GE$4)+(DN19+DP19)*Cadeirante/30*GE$4+(DM16+DM17+DM18+DO16+DO17+DO18)*Percapita/30*GE$4)+IF(DM19+DO19>=11,Fixo/30*GE$4+(DM19+DO19-10)*Crechee/30*GE$4,0),IF(C16=2,IF(DN16+DN17+DN18+DN19+DP16+DP17+DP18+DP19=1,Cadeirante/30*GE$4,IF(DN16+DN17+DN18+DN19+DP16+DP17+DP18+DP19=2,Fixo/30*GE$4,IF(DN16+DN17+DN18+DN19+DP16+DP17+DP18+DP19>2,Fixo/30*GE$4+(DN16+DN17+DN18+DN19+DP16+DP17+DP18+DP19-2)*Cadeirante/30*GE$4)))+(DM16+DM17+DM18+DO16+DO17+DO18)*Percapita/30*GE$4+(DM19+DO19)*Crechee/30*GE$4,IF(C16=1,IF(DM16+DM17+DM18+DN16+DN17+DN18+DO16+DO17+DO18+DP16+DP17+DP18<=15,(DM16+DM17+DM18+DO16+DO17+DO18)*Percapita/30*GE$4,IF(DM16+DM17+DM18+DN16+DN17+DN18+DO16+DO17+DO18+DP16+DP17+DP18>=16,Fixo/30*GE$4+(DM16+DM17+DM18+DN16+DN17+DN18+DO16+DO17+DO18+DP16+DP17-16)*Percapita/30*GE$4)))))) -> 0 | GF16: =IF(C16=4,SUM(DQ16+DQ17+DQ18+DS16+DS17+DS18)*Percapita/30*GF$4+(DR16+DR17+DR18+DT16+DT17+DT18)*Cadeirante/30*GF$4,IF(C16=3,IF(DQ19+DS19=10,Fixo/30*GF$4+(DQ16+DQ17+DQ18+DS16+DS17+DS18)*Percapita/30*GF$4+(DR19+DT19)*Cadeirante/30*GF$4,IF(DQ19+DS19<=9,(DQ19+DS19)*Crechee/30*GF$4)+(DR19+DT19)*Cadeirante/30*GF$4+(DQ16+DQ17+DQ18+DS16+DS17+DS18)*Percapita/30*GF$4)+IF(DQ19+DS19>=11,Fixo/30*GF$4+(DQ19+DS19-10)*Crechee/30*GF$4,0),IF(C16=2,IF(DR16+DR17+DR18+DR19+DT16+DT17+DT18+DT19=1,Cadeirante/30*GF$4,IF(DR16+DR17+DR18+DR19+DT16+DT17+DT18+DT19=2,Fixo/30*GF$4,IF(DR16+DR17+DR18+DR19+DT16+DT17+DT18+DT19>2,Fixo/30*GF$4+(DR16+DR17+DR18+DR19+DT16+DT17+DT18+DT19-2)*Cadeirante/30*GF$4)))+(DQ16+DQ17+DQ18+DS16+DS17+DS18)*Percapita/30*GF$4+(DQ19+DS19)*Crechee/30*GF$4,IF(C16=1,IF(DQ16+DQ17+DQ18+DR16+DR17+DR18+DS16+DS17+DS18+DT16+DT17+DT18<=15,(DQ16+DQ17+DQ18+DS16+DS17+DS18)*Percapita/30*GF$4,IF(DQ16+DQ17+DQ18+DR16+DR17+DR18+DS16+DS17+DS18+DT16+DT17+DT18>=16,Fixo/30*GF$4+(DQ16+DQ17+DQ18+DR16+DR17+DR18+DS16+DS17+DS18+DT16+DT17-16)*Percapita/30*GF$4)))))) -> 0 | GG16: =IF(C16=4,SUM(DU16+DU17+DU18+DW16+DW17+DW18)*Percapita/30*GG$4+(DV16+DV17+DV18+DX16+DX17+DX18)*Cadeirante/30*GG$4,IF(C16=3,IF(DU19+DW19=10,Fixo/30*GG$4+(DU16+DU17+DU18+DW16+DW17+DW18)*Percapita/30*GG$4+(DV19+DX19)*Cadeirante/30*GG$4,IF(DU19+DW19<=9,(DU19+DW19)*Crechee/30*GG$4)+(DV19+DX19)*Cadeirante/30*GG$4+(DU16+DU17+DU18+DW16+DW17+DW18)*Percapita/30*GG$4)+IF(DU19+DW19>=11,Fixo/30*GG$4+(DU19+DW19-10)*Crechee/30*GG$4,0),IF(C16=2,IF(DV16+DV17+DV18+DV19+DX16+DX17+DX18+DX19=1,Cadeirante/30*GG$4,IF(DV16+DV17+DV18+DV19+DX16+DX17+DX18+DX19=2,Fixo/30*GG$4,IF(DV16+DV17+DV18+DV19+DX16+DX17+DX18+DX19>2,Fixo/30*GG$4+(DV16+DV17+DV18+DV19+DX16+DX17+DX18+DX19-2)*Cadeirante/30*GG$4)))+(DU16+DU17+DU18+DW16+DW17+DW18)*Percapita/30*GG$4+(DU19+DW19)*Crechee/30*GG$4,IF(C16=1,IF(DU16+DU17+DU18+DV16+DV17+DV18+DW16+DW17+DW18+DX16+DX17+DX18<=15,(DU16+DU17+DU18+DW16+DW17+DW18)*Percapita/30*GG$4,IF(DU16+DU17+DU18+DV16+DV17+DV18+DW16+DW17+DW18+DX16+DX17+DX18>=16,Fixo/30*GG$4+(DU16+DU17+DU18+DV16+DV17+DV18+DW16+DW17+DW18+DX16+DX17-16)*Percapita/30*GG$4)))))) -> 0 | GH16: =IF(C16=4,SUM(DY16+DY17+DY18+EA16+EA17+EA18)*Percapita/30*GH$4+(DZ16+DZ17+DZ18+EB16+EB17+EB18)*Cadeirante/30*GH$4,IF(C16=3,IF(DY19+EA19=10,Fixo/30*GH$4+(DY16+DY17+DY18+EA16+EA17+EA18)*Percapita/30*GH$4+(DZ19+EB19)*Cadeirante/30*GH$4,IF(DY19+EA19<=9,(DY19+EA19)*Crechee/30*GH$4)+(DZ19+EB19)*Cadeirante/30*GH$4+(DY16+DY17+DY18+EA16+EA17+EA18)*Percapita/30*GH$4)+IF(DY19+EA19>=11,Fixo/30*GH$4+(DY19+EA19-10)*Crechee/30*GH$4,0),IF(C16=2,IF(DZ16+DZ17+DZ18+DZ19+EB16+EB17+EB18+EB19=1,Cadeirante/30*GH$4,IF(DZ16+DZ17+DZ18+DZ19+EB16+EB17+EB18+EB19=2,Fixo/30*GH$4,IF(DZ16+DZ17+DZ18+DZ19+EB16+EB17+EB18+EB19>2,Fixo/30*GH$4+(DZ16+DZ17+DZ18+DZ19+EB16+EB17+EB18+EB19-2)*Cadeirante/30*GH$4)))+(DY16+DY17+DY18+EA16+EA17+EA18)*Percapita/30*GH$4+(DY19+EA19)*Crechee/30*GH$4,IF(C16=1,IF(DY16+DY17+DY18+DZ16+DZ17+DZ18+EA16+EA17+EA18+EB16+EB17+EB18<=15,(DY16+DY17+DY18+EA16+EA17+EA18)*Percapita/30*GH$4,IF(DY16+DY17+DY18+DZ16+DZ17+DZ18+EA16+EA17+EA18+EB16+EB17+EB18>=16,Fixo/30*GH$4+(DY16+DY17+DY18+DZ16+DZ17+DZ18+EA16+EA17+EA18+EB16+EB17-16)*Percapita/30*GH$4)))))) -> 0 | GI16: =IF(C16=4,SUM(EC16+EC17+EC18+EE16+EE17+EE18)*Percapita/30*GI$4+(ED16+ED17+ED18+EF16+EF17+EF18)*Cadeirante/30*GI$4,IF(C16=3,IF(EC19+EE19=10,Fixo/30*GI$4+(EC16+EC17+EC18+EE16+EE17+EE18)*Percapita/30*GI$4+(ED19+EF19)*Cadeirante/30*GI$4,IF(EC19+EE19<=9,(EC19+EE19)*Crechee/30*GI$4)+(ED19+EF19)*Cadeirante/30*GI$4+(EC16+EC17+EC18+EE16+EE17+EE18)*Percapita/30*GI$4)+IF(EC19+EE19>=11,Fixo/30*GI$4+(EC19+EE19-10)*Crechee/30*GI$4,0),IF(C16=2,IF(ED16+ED17+ED18+ED19+EF16+EF17+EF18+EF19=1,Cadeirante/30*GI$4,IF(ED16+ED17+ED18+ED19+EF16+EF17+EF18+EF19=2,Fixo/30*GI$4,IF(ED16+ED17+ED18+ED19+EF16+EF17+EF18+EF19>2,Fixo/30*GI$4+(ED16+ED17+ED18+ED19+EF16+EF17+EF18+EF19-2)*Cadeirante/30*GI$4)))+(EC16+EC17+EC18+EE16+EE17+EE18)*Percapita/30*GI$4+(EC19+EE19)*Crechee/30*GI$4,IF(C16=1,IF(EC16+EC17+EC18+ED16+ED17+ED18+EE16+EE17+EE18+EF16+EF17+EF18<=15,(EC16+EC17+EC18+EE16+EE17+EE18)*Percapita/30*GI$4,IF(EC16+EC17+EC18+ED16+ED17+ED18+EE16+EE17+EE18+EF16+EF17+EF18>=16,Fixo/30*GI$4+(EC16+EC17+EC18+ED16+ED17+ED18+EE16+EE17+EE18+EF16+EF17-16)*Percapita/30*GI$4)))))) -> 0 | GJ16: =IF(C16=4,SUM(EG16+EG17+EG18+EI16+EI17+EI18)*Percapita/30*GJ$4+(EH16+EH17+EH18+EJ16+EJ17+EJ18)*Cadeirante/30*GJ$4,IF(C16=3,IF(EG19+EI19=10,Fixo/30*GJ$4+(EG16+EG17+EG18+EI16+EI17+EI18)*Percapita/30*GJ$4+(EH19+EJ19)*Cadeirante/30*GJ$4,IF(EG19+EI19<=9,(EG19+EI19)*Crechee/30*GJ$4)+(EH19+EJ19)*Cadeirante/30*GJ$4+(EG16+EG17+EG18+EI16+EI17+EI18)*Percapita/30*GJ$4)+IF(EG19+EI19>=11,Fixo/30*GJ$4+(EG19+EI19-10)*Crechee/30*GJ$4,0),IF(C16=2,IF(EH16+EH17+EH18+EH19+EJ16+EJ17+EJ18+EJ19=1,Cadeirante/30*GJ$4,IF(EH16+EH17+EH18+EH19+EJ16+EJ17+EJ18+EJ19=2,Fixo/30*GJ$4,IF(EH16+EH17+EH18+EH19+EJ16+EJ17+EJ18+EJ19>2,Fixo/30*GJ$4+(EH16+EH17+EH18+EH19+EJ16+EJ17+EJ18+EJ19-2)*Cadeirante/30*GJ$4)))+(EG16+EG17+EG18+EI16+EI17+EI18)*Percapita/30*GJ$4+(EG19+EI19)*Crechee/30*GJ$4,IF(C16=1,IF(EG16+EG17+EG18+EH16+EH17+EH18+EI16+EI17+EI18+EJ16+EJ17+EJ18<=15,(EG16+EG17+EG18+EI16+EI17+EI18)*Percapita/30*GJ$4,IF(EG16+EG17+EG18+EH16+EH17+EH18+EI16+EI17+EI18+EJ16+EJ17+EJ18>=16,Fixo/30*GJ$4+(EG16+EG17+EG18+EH16+EH17+EH18+EI16+EI17+EI18+EJ16+EJ17-16)*Percapita/30*GJ$4)))))) -> 0 | GL16: =IF(J16="ADAPTADO",T16*Cadeirante/30*GM16+S16*Percapita/30*GM16,IF(J16="NORMAL",(S16+T16)*Percapita/30*GM16,IF(J16="CRECHE",0)))*-1 -> 0 | GN16: =SUMIF(V16:V19,"<0")*Cadeirante/30*GN$4+SUMIF(X16:X19,"<0")*Cadeirante/30*GN$4 -> 0 | GO16: =SUMIF(Z16:Z19,"<0")*Cadeirante/30*GO$4+SUMIF(AB16:AB19,"<0")*Cadeirante/30*GO$4 -> 0 | GP16: =SUMIF(AD16:AD19,"<0")*Cadeirante/30*GP$4+SUMIF(AF16:AF19,"<0")*Cadeirante/30*GP$4 -> 0 | GQ16: =SUMIF(AH16:AH19,"<0")*Cadeirante/30*GQ$4+SUMIF(AJ16:AJ19,"<0")*Cadeirante/30*GQ$4 -> 0 | GR16: =SUMIF(AL16:AL19,"<0")*Cadeirante/30*GR$4+SUMIF(AN16:AN19,"<0")*Cadeirante/30*GR$4 -> 0 | GS16: =SUMIF(AP16:AP19,"<0")*Cadeirante/30*GS$4+SUMIF(AR16:AR19,"<0")*Cadeirante/30*GS$4 -> 0 | GT16: =SUMIF(AT16:AT19,"<0")*Cadeirante/30*GT$4+SUMIF(AV16:AV19,"<0")*Cadeirante/30*GT$4 -> 0 | GU16: =SUMIF(AX16:AX19,"<0")*Cadeirante/30*GU$4+SUMIF(AZ16:AZ19,"<0")*Cadeirante/30*GU$4 -> 0 | GV16: =SUMIF(BB16:BB19,"<0")*Cadeirante/30*GV$4+SUMIF(BD16:BD19,"<0")*Cadeirante/30*GV$4 -> 0 | GW16: =SUMIF(BF16:BF19,"<0")*Cadeirante/30*GW$4+SUMIF(BH16:BH19,"<0")*Cadeirante/30*GW$4 -> 0 | GX16: =SUMIF(BJ16:BJ19,"<0")*Cadeirante/30*GX$4+SUMIF(BL16:BL19,"<0")*Cadeirante/30*GX$4 -> 0 | GY16: =SUMIF(BN16:BN19,"<0")*Cadeirante/30*GY$4+SUMIF(BP16:BP19,"<0")*Cadeirante/30*GY$4 -> 0 | GZ16: =SUMIF(BR16:BR19,"<0")*Cadeirante/30*GZ$4+SUMIF(BT16:BT19,"<0")*Cadeirante/30*GZ$4 -> 0 | HA16: =SUMIF(BV16:BV19,"<0")*Cadeirante/30*HA$4+SUMIF(BX16:BX19,"<0")*Cadeirante/30*HA$4 -> 0 | HB16: =SUMIF(BZ16:BZ19,"<0")*Cadeirante/30*HB$4+SUMIF(CB16:CB19,"<0")*Cadeirante/30*HB$4 -> 0 | HC16: =SUMIF(CD16:CD19,"<0")*Cadeirante/30*HC$4+SUMIF(CF16:CF19,"<0")*Cadeirante/30*HC$4 -> 0 | HD16: =SUMIF(CH16:CH19,"<0")*Cadeirante/30*HD$4+SUMIF(CJ16:CJ19,"<0")*Cadeirante/30*HD$4 -> 0 | HE16: =SUMIF(CL16:CL19,"<0")*Cadeirante/30*HE$4+SUMIF(CN16:CN19,"<0")*Cadeirante/30*HE$4 -> 0 | HF16: =SUMIF(CP16:CP19,"<0")*Cadeirante/30*HF$4+SUMIF(CR16:CR19,"<0")*Cadeirante/30*HF$4 -> 0 | HG16: =SUMIF(CT16:CT19,"<0")*Cadeirante/30*HG$4+SUMIF(CV16:CV19,"<0")*Cadeirante/30*HG$4 -> 0 | HH16: =SUMIF(CX16:CX19,"<0")*Cadeirante/30*HH$4+SUMIF(CZ16:CZ19,"<0")*Cadeirante/30*HH$4 -> 0 | HI16: =SUMIF(DB16:DB19,"<0")*Cadeirante/30*HI$4+SUMIF(DD16:DD19,"<0")*Cadeirante/30*HI$4 -> 0 | HJ16: =SUMIF(DF16:DF19,"<0")*Cadeirante/30*HJ$4+SUMIF(DH16:DH19,"<0")*Cadeirante/30*HJ$4 -> 0 | HK16: =SUMIF(DJ16:DJ19,"<0")*Cadeirante/30*HK$4+SUMIF(DL16:DL19,"<0")*Cadeirante/30*HK$4 -> 0 | HL16: =SUMIF(DN16:DN19,"<0")*Cadeirante/30*HL$4+SUMIF(DP16:DP19,"<0")*Cadeirante/30*HL$4 -> 0 | HM16: =SUMIF(DR16:DR19,"<0")*Cadeirante/30*HM$4+SUMIF(DT16:DT19,"<0")*Cadeirante/30*HM$4 -> 0 | HN16: =SUMIF(DV16:DV19,"<0")*Cadeirante/30*HN$4+SUMIF(DX16:DX19,"<0")*Cadeirante/30*HN$4 -> 0 | HO16: =SUMIF(DZ16:DZ19,"<0")*Cadeirante/30*HO$4+SUMIF(EB16:EB19,"<0")*Cadeirante/30*HO$4 -> 0 | HP16: =SUMIF(ED16:ED19,"<0")*Cadeirante/30*HP$4+SUMIF(EF16:EF19,"<0")*Cadeirante/30*HP$4 -> 0 | HW16: 17629.31 | HY16: =IF(ISTEXT(EM16), VALUE(EM16), EM16) -> 0 | HZ16: =IF(ISTEXT(EN16), VALUE(EN16), EN16) -> 0 | IA16: =IF(ISTEXT(EO16), VALUE(EO16), EO16) -> 0 | IB16: =HW16=FE16 -> FALSE
A17: 050.754-00 | B17: 2023/0009598-001D | C17: BT | D17: 2023/0009598 | E17: FQG9125 | F17: 01/04/2026 | G17: 30/04/2026 | H17: A.C.G. TRANSPORTE ESCOLAR LTDA | I17: PAULA CRISTINA DA SILVA | J17: NORMAL | K17: EMEF | L17: =CONTINUA!BV17 -> 0 | M17: =CONTINUA!BW17 -> 0 | O17: 6020.2023/0009598-2 | P17: O | EP17: =Q17 -> 0 | EQ17: =U17+Y17+AC17+AG17+AK17+AO17+AS17+AW17+BA17+BE17+BI17+BM17+BQ17+BU17+BY17+CC17+CG17+CK17+CO17+CS17+CW17+DA17+DE17+DI17+DM17+DQ17+DU17+DY17+EC17+EG17 -> 0 | ER17: =S17+W17+AA17+AE17+AI17+AM17+AQ17+AU17+AY17+BC17+BG17+BK17+BO17+BS17+BW17+CA17+CE17+CI17+CM17+CQ17+CU17+CY17+DC17+DG17+DK17+DO17+DS17+DW17+EA17+EE17+EI17 -> 0 | ES17: =R17 -> 0 | ET17: =V17+Z17+AD17+AH17+AL17+AP17+AT17+AX17+BB17+BF17+BJ17+BN17+BR17+BV17+BZ17+CD17+CH17+CL17+CP17+CT17+CX17+DB17+DF17+DJ17+DN17+DR17+DV17+DZ17+ED17+EH17 -> 0 | EU17: =T17+X17+AB17+AF17+AJ17+AN17+AR17+AV17+AZ17+BD17+BH17+BL17+BP17+BT17+BX17+CB17+CF17+CJ17+CN17+CR17+CV17+CZ17+DD17+DH17+DL17+DP17+DT17+DX17+EB17+EF17+EJ17 -> 0 | EV17: =EP17+EQ17+ES17+ET17+ER17+EU17 -> 0 | EX17: =FF17 -> 0 | EY17: =(L17*regular)+(M17*Cadeirantee) -> 0 | EZ17: =SUMIF(FG17:GJ17,">0") -> 0 | FA17: =SUMIF(FG17:GJ17,"<0")+SUMIF(GN17:HP17,"<0") -> 0 | FB17: 0 | FC17: =N17*km*'VALORES TABELA'!$B$13 -> 0 | FD17: =GL17 -> 0 | GL17: =IF(J17="ADAPTADO",T17*Cadeirante/30*GM17+S17*Percapita/30*GM17,IF(J17="NORMAL",(S17+T17)*Percapita/30*GM17,IF(J17="CRECHE",0)))*-1 -> 0 | HY17: =IF(ISTEXT(EM17), VALUE(EM17), EM17) -> 0 | HZ17: =IF(ISTEXT(EN17), VALUE(EN17), EN17) -> 0 | IA17: =IF(ISTEXT(EO17), VALUE(EO17), EO17) -> 0
A18: 050.754-00 | B18: 2023/0009598-001D | C18: BT | D18: 2023/0009598 | E18: FQG9125 | F18: 01/04/2026 | G18: 30/04/2026 | H18: A.C.G. TRANSPORTE ESCOLAR LTDA | I18: PAULA CRISTINA DA SILVA | J18: NORMAL | K18: EMEE | L18: =CONTINUA!BV18 -> 0 | M18: =CONTINUA!BW18 -> 0 | O18: 6020.2023/0009598-2 | P18: O | EP18: =Q18 -> 0 | EQ18: =U18+Y18+AC18+AG18+AK18+AO18+AS18+AW18+BA18+BE18+BI18+BM18+BQ18+BU18+BY18+CC18+CG18+CK18+CO18+CS18+CW18+DA18+DE18+DI18+DM18+DQ18+DU18+DY18+EC18+EG18 -> 0 | ER18: =S18+W18+AA18+AE18+AI18+AM18+AQ18+AU18+AY18+BC18+BG18+BK18+BO18+BS18+BW18+CA18+CE18+CI18+CM18+CQ18+CU18+CY18+DC18+DG18+DK18+DO18+DS18+DW18+EA18+EE18+EI18 -> 0 | ES18: =R18 -> 0 | ET18: =V18+Z18+AD18+AH18+AL18+AP18+AT18+AX18+BB18+BF18+BJ18+BN18+BR18+BV18+BZ18+CD18+CH18+CL18+CP18+CT18+CX18+DB18+DF18+DJ18+DN18+DR18+DV18+DZ18+ED18+EH18 -> 0 | EU18: =T18+X18+AB18+AF18+AJ18+AN18+AR18+AV18+AZ18+BD18+BH18+BL18+BP18+BT18+BX18+CB18+CF18+CJ18+CN18+CR18+CV18+CZ18+DD18+DH18+DL18+DP18+DT18+DX18+EB18+EF18+EJ18 -> 0 | EV18: =EP18+EQ18+ES18+ET18+ER18+EU18 -> 0 | EX18: =FF18 -> 0 | EY18: =(L18*regular)+(M18*Cadeirantee) -> 0 | EZ18: =SUMIF(FG18:GJ18,">0") -> 0 | FA18: =SUMIF(FG18:GJ18,"<0")+SUMIF(GN18:HP18,"<0") -> 0 | FB18: 0 | FC18: =N18*km*'VALORES TABELA'!$B$13 -> 0 | FD18: =GL18 -> 0 | GL18: =IF(J18="ADAPTADO",T18*Cadeirante/30*GM18+S18*Percapita/30*GM18,IF(J18="NORMAL",(S18+T18)*Percapita/30*GM18,IF(J18="CRECHE",0)))*-1 -> 0 | HY18: =IF(ISTEXT(EM18), VALUE(EM18), EM18) -> 0 | HZ18: =IF(ISTEXT(EN18), VALUE(EN18), EN18) -> 0 | IA18: =IF(ISTEXT(EO18), VALUE(EO18), EO18) -> 0
A19: 050.754-00 | B19: 2023/0009598-001D | C19: BT | D19: 2023/0009598 | E19: FQG9125 | F19: 01/04/2026 | G19: 30/04/2026 | H19: A.C.G. TRANSPORTE ESCOLAR LTDA | I19: PAULA CRISTINA DA SILVA | J19: NORMAL | K19: CEI | L19: =CONTINUA!BV19 -> 0 | M19: =CONTINUA!BW19 -> 0 | O19: 6020.2023/0009598-2 | P19: O | EP19: =Q19 -> 0 | EQ19: =U19+Y19+AC19+AG19+AK19+AO19+AS19+AW19+BA19+BE19+BI19+BM19+BQ19+BU19+BY19+CC19+CG19+CK19+CO19+CS19+CW19+DA19+DE19+DI19+DM19+DQ19+DU19+DY19+EC19+EG19 -> 0 | ER19: =S19+W19+AA19+AE19+AI19+AM19+AQ19+AU19+AY19+BC19+BG19+BK19+BO19+BS19+BW19+CA19+CE19+CI19+CM19+CQ19+CU19+CY19+DC19+DG19+DK19+DO19+DS19+DW19+EA19+EE19+EI19 -> 0 | ES19: =R19 -> 0 | ET19: =V19+Z19+AD19+AH19+AL19+AP19+AT19+AX19+BB19+BF19+BJ19+BN19+BR19+BV19+BZ19+CD19+CH19+CL19+CP19+CT19+CX19+DB19+DF19+DJ19+DN19+DR19+DV19+DZ19+ED19+EH19 -> 0 | EU19: =T19+X19+AB19+AF19+AJ19+AN19+AR19+AV19+AZ19+BD19+BH19+BL19+BP19+BT19+BX19+CB19+CF19+CJ19+CN19+CR19+CV19+CZ19+DD19+DH19+DL19+DP19+DT19+DX19+EB19+EF19+EJ19 -> 0 | EV19: =EP19+EQ19+ES19+ET19+ER19+EU19 -> 0 | EX19: =FF19 -> 0 | EY19: =(L19*regular)+(M19*Cadeirantee) -> 0 | EZ19: =SUMIF(FG19:GJ19,">0") -> 0 | FA19: =SUMIF(FG19:GJ19,"<0")+SUMIF(GN19:HP19,"<0") -> 0 | FB19: 0 | FC19: =N19*km*'VALORES TABELA'!$B$13 -> 0 | FD19: =GL19 -> 0 | GL19: =IF(J19="ADAPTADO",T19*Cadeirante/30*GM19+S19*Percapita/30*GM19,IF(J19="NORMAL",(S19+T19)*Percapita/30*GM19,IF(J19="CRECHE",0)))*-1 -> 0 | HY19: =IF(ISTEXT(EM19), VALUE(EM19), EM19) -> 0 | HZ19: =IF(ISTEXT(EN19), VALUE(EN19), EN19) -> 0 | IA19: =IF(ISTEXT(EO19), VALUE(EO19), EO19) -> 0
A20: 050.754-00 | B20: 2023/0009598-001D | C20: BT | D20: 2023/0009598 | E20: FQG9125 | F20: 01/04/2026 | G20: 30/04/2026 | H20: A.C.G. TRANSPORTE ESCOLAR LTDA | I20: PAULA CRISTINA DA SILVA | J20: NORMAL | K20: CCA | L20: =CONTINUA!BV20 -> 0 | M20: =CONTINUA!BW20 -> 0 | O20: 6020.2023/0009598-2 | P20: O | EP20: =Q20 -> 0 | EQ20: =U20+Y20+AC20+AG20+AK20+AO20+AS20+AW20+BA20+BE20+BI20+BM20+BQ20+BU20+BY20+CC20+CG20+CK20+CO20+CS20+CW20+DA20+DE20+DI20+DM20+DQ20+DU20+DY20+EC20+EG20 -> 0 | ER20: =S20+W20+AA20+AE20+AI20+AM20+AQ20+AU20+AY20+BC20+BG20+BK20+BO20+BS20+BW20+CA20+CE20+CI20+CM20+CQ20+CU20+CY20+DC20+DG20+DK20+DO20+DS20+DW20+EA20+EE20+EI20 -> 0 | ES20: =R20 -> 0 | ET20: =V20+Z20+AD20+AH20+AL20+AP20+AT20+AX20+BB20+BF20+BJ20+BN20+BR20+BV20+BZ20+CD20+CH20+CL20+CP20+CT20+CX20+DB20+DF20+DJ20+DN20+DR20+DV20+DZ20+ED20+EH20 -> 0 | EU20: =T20+X20+AB20+AF20+AJ20+AN20+AR20+AV20+AZ20+BD20+BH20+BL20+BP20+BT20+BX20+CB20+CF20+CJ20+CN20+CR20+CV20+CZ20+DD20+DH20+DL20+DP20+DT20+DX20+EB20+EF20+EJ20 -> 0 | EV20: =EP20+EQ20+ES20+ET20+ER20+EU20 -> 0 | EX20: 0 | EY20: 0 | EZ20: 0 | FA20: 0 | FB20: =SUM(FF20:GI20)/2 -> 0 | FC20: =N20*km*'VALORES TABELA'!$B$13 -> 0 | FD20: =GL20 -> 0 | FF20: =((Q20+S20)*Percapita)+((R20+T20)*Cadeirante) -> 0 | FG20: =((U20+W20)*Percapita/30*FG$4)+((V20+X20)*Cadeirante/30*FG$4) -> 0 | FH20: =((Y20+AA20)*Percapita/30*FH$4)+((Z20+AB20)*Cadeirante/30*FH$4) -> 0 | FI20: =((AC20+AE20)*Percapita/30*FI$4)+((AD20+AF20)*Cadeirante/30*FI$4) -> 0 | FJ20: =((AG20+AI20)*Percapita/30*FJ$4)+((AH20+AJ20)*Cadeirante/30*FJ$4) -> 0 | FK20: =((AK20+AM20)*Percapita/30*FK$4)+((AL20+AN20)*Cadeirante/30*FK$4) -> 0 | FL20: =((AO20+AQ20)*Percapita/30*FL$4)+((AP20+AR20)*Cadeirante/30*FL$4) -> 0 | FM20: =((AS20+AU20)*Percapita/30*FM$4)+((AT20+AV20)*Cadeirante/30*FM$4) -> 0 | FN20: =((AW20+AY20)*Percapita/30*FN$4)+((AX20+AZ20)*Cadeirante/30*FN$4) -> 0 | FO20: =((BA20+BC20)*Percapita/30*FO$4)+((BB20+BD20)*Cadeirante/30*FO$4) -> 0 | FP20: =((BE20+BG20)*Percapita/30*FP$4)+((BF20+BH20)*Cadeirante/30*FP$4) -> 0 | FQ20: =((BI20+BK20)*Percapita/30*FQ$4)+((BJ20+BL20)*Cadeirante/30*FQ$4) -> 0 | FR20: =((BM20+BO20)*Percapita/30*FR$4)+((BN20+BP20)*Cadeirante/30*FR$4) -> 0 | FS20: =((BQ20+BS20)*Percapita/30*FS$4)+((BR20+BT20)*Cadeirante/30*FS$4) -> 0 | FT20: =((BU20+BW20)*Percapita/30*FT$4)+((BV20+BX20)*Cadeirante/30*FT$4) -> 0 | FU20: =((BY20+CA20)*Percapita/30*FU$4)+((BZ20+CB20)*Cadeirante/30*FU$4) -> 0 | FV20: =((CC20+CE20)*Percapita/30*FV$4)+((CD20+CF20)*Cadeirante/30*FV$4) -> 0 | FW20: =((CG20+CI20)*Percapita/30*FW$4)+((CI20+CK20)*Cadeirante/30*FW$4) -> 0 | FX20: =((CK20+CM20)*Percapita/30*FX$4)+((CL20+CN20)*Cadeirante/30*FX$4) -> 0 | FY20: =((CO20+CQ20)*Percapita/30*FY$4)+((CP20+CR20)*Cadeirante/30*FY$4) -> 0 | FZ20: =((CS20+CU20)*Percapita/30*FZ$4)+((CT20+CV20)*Cadeirante/30*FZ$4) -> 0 | GA20: =((CW20+CY20)*Percapita/30*GA$4)+((CX20+CZ20)*Cadeirante/30*GA$4) -> 0 | GB20: =((DA20+DC20)*Percapita/30*GB$4)+((DB20+DD20)*Cadeirante/30*GB$4) -> 0 | GC20: =((DE20+DG20)*Percapita/30*GC$4)+((DF20+DH20)*Cadeirante/30*GC$4) -> 0 | GD20: =((DI20+DK20)*Percapita/30*GD$4)+((DJ20+DL20)*Cadeirante/30*GD$4) -> 0 | GE20: =((DM20+DO20)*Percapita/30*GE$4)+((DN20+DP20)*Cadeirante/30*GE$4) -> 0 | GF20: =((DQ20+DS20)*Percapita/30*GF$4)+((DR20+DT20)*Cadeirante/30*GF$4) -> 0 | GG20: =((DU20+DW20)*Percapita/30*GG$4)+((DV20+DX20)*Cadeirante/30*GG$4) -> 0 | GH20: =((DY20+EA20)*Percapita/30*GH$4)+((DZ20+EB20)*Cadeirante/30*GH$4) -> 0 | GI20: =((EC20+EE20)*Percapita/30*GI$4)+((ED20+EF20)*Cadeirante/30*GI$4) -> 0 | GJ20: =((EG20+EI20)*Percapita)+((EH20+EJ20)*Cadeirante) -> 0 | GL20: =IF(J20="ADAPTADO",T20*Cadeirante/30*GM20+S20*Percapita/30*GM20,IF(J20="NORMAL",(S20+T20)*Percapita/30*GM20,IF(J20="CRECHE",0)))*-1 -> 0 | HY20: =IF(ISTEXT(EM20), VALUE(EM20), EM20) -> 0 | HZ20: =IF(ISTEXT(EN20), VALUE(EN20), EN20) -> 0 | IA20: =IF(ISTEXT(EO20), VALUE(EO20), EO20) -> 0
A21: 048.899-00 | B21: 2023/0019748-001A | C21: 1 | D21: 2023/0019748 | E21: CYR9B26 | F21: 01/04/2026 | G21: 30/04/2026 | H21: AME TRANSPORTE LTDA | I21: DORIS BATISTA ELIAS | J21: NORMAL | K21: EMEI | L21: =CONTINUA!BV21 -> 0 | M21: =CONTINUA!BW21 -> 0 | O21: 6020.2023/0019748-3 | P21: O | EP21: =Q21 -> 0 | EQ21: =U21+Y21+AC21+AG21+AK21+AO21+AS21+AW21+BA21+BE21+BI21+BM21+BQ21+BU21+BY21+CC21+CG21+CK21+CO21+CS21+CW21+DA21+DE21+DI21+DM21+DQ21+DU21+DY21+EC21+EG21 -> 0 | ER21: =S21+W21+AA21+AE21+AI21+AM21+AQ21+AU21+AY21+BC21+BG21+BK21+BO21+BS21+BW21+CA21+CE21+CI21+CM21+CQ21+CU21+CY21+DC21+DG21+DK21+DO21+DS21+DW21+EA21+EE21+EI21 -> 0 | ES21: =R21 -> 0 | ET21: =V21+Z21+AD21+AH21+AL21+AP21+AT21+AX21+BB21+BF21+BJ21+BN21+BR21+BV21+BZ21+CD21+CH21+CL21+CP21+CT21+CX21+DB21+DF21+DJ21+DN21+DR21+DV21+DZ21+ED21+EH21 -> 0 | EU21: =T21+X21+AB21+AF21+AJ21+AN21+AR21+AV21+AZ21+BD21+BH21+BL21+BP21+BT21+BX21+CB21+CF21+CJ21+CN21+CR21+CV21+CZ21+DD21+DH21+DL21+DP21+DT21+DX21+EB21+EF21+EJ21 -> 0 | EV21: =EP21+EQ21+ES21+ET21+ER21+EU21 -> 0 | EW21: =IF(C21=4,IF(MAX(Q21:EJ23)>0,(Especiall/30*(IF(($G21-$F21)=($G$5-$F$5),30,IF(DAY($G21)=31,($G21-$F21),($G21-$F21)+1)))),0),0) -> 0 | EX21: =FF21 -> 16738.04 | EY21: =(L21*regular)+(M21*Cadeirantee) -> 0 | EZ21: =SUMIF(FG21:GJ21,">0") -> 25.682 | FA21: =SUMIF(FG21:GJ21,"<0")+SUMIF(GN21:HP21,"<0") -> 0 | FB21: 0 | FC21: =N21*km*'VALORES TABELA'!$B$13 -> 0 | FD21: =GL21 -> 0 | FE21: =(EW21+EW22+EW23+EW24+EX21+EX22+EX23+EX24+EY21+EY22+EY23+EY24+EY25+EZ21+EZ22+EZ23+EZ24+FA21+FA22+FA23+FA24+FC21+FC22+FC23+FC24+HY21-HZ21-IA21+FD21+FD22+FD23+FD24+FB25) -> 16763.722 | FF21: =IF(C21=4,SUM(Q21+Q22+Q23+S21+S22+S23)*Percapita/30*FF$4+(R21+R22+R23+T21+T22+T23)*Cadeirante/30*FF$4,IF(C21=3,IF(Q24+S24=10,Fixo/30*FF$4+(Q21+Q22+Q23+S21+S22+S23)*Percapita/30*FF$4+(R24+T24)*Cadeirante/30*FF$4,IF(Q24+S24<=9,(Q24+S24)*Crechee/30*FF$4)+(R24+T24)*Cadeirante/30*FF$4+(Q21+Q22+Q23+S21+S22+S23)*Percapita/30*FF$4)+IF(Q24+S24>=11,Fixo/30*FF$4+(Q24+S24-10)*Crechee/30*FF$4,0),IF(C21=2,IF(R21+R22+R23+R24+T21+T22+T23+T24=1,Cadeirante/30*FF$4,IF(R21+R22+R23+R24+T21+T22+T23+T24=2,Fixo/30*FF$4,IF(R21+R22+R23+R24+T21+T22+T23+T24>2,Fixo/30*FF$4+(R21+R22+R23+R24+T21+T22+T23+T24-2)*Cadeirante/30*FF$4)))+(Q21+Q22+Q23+S21+S22+S23)*Percapita/30*FF$4+(Q24+S24)*Crechee/30*FF$4,IF(C21=1,IF(Q21+Q22+Q23+R21+R22+R23+S21+S22+S23+T21+T22+T23<=15,(Q21+Q22+Q23+S21+S22+S23)*Percapita/30*FF$4,IF(Q21+Q22+Q23+R21+R22+R23+S21+S22+S23+T21+T22+T23>=16,Fixo/30*FF$4+(Q21+Q22+Q23+R21+R22+R23+S21+S22+S23+T21+T22-16)*Percapita/30*FF$4)))))) -> 16738.04 | FG21: =IF(C21=4,SUM(U21+U22+U23+W21+W22+W23)*Percapita/30*FG$4+(V21+V22+V23+X21+X22+X23)*Cadeirante/30*FG$4,IF(C21=3,IF(U24+W24=10,Fixo/30*FG$4+(U21+U22+U23+W21+W22+W23)*Percapita/30*FG$4+(V24+X24)*Cadeirante/30*FG$4,IF(U24+W24<=9,(U24+W24)*Crechee/30*FG$4)+(V24+X24)*Cadeirante/30*FG$4+(U21+U22+U23+W21+W22+W23)*Percapita/30*FG$4)+IF(U24+W24>=11,Fixo/30*FG$4+(U24+W24-10)*Crechee/30*FG$4,0),IF(C21=2,IF(V21+V22+V23+V24+X21+X22+X23+X24=1,Cadeirante/30*FG$4,IF(V21+V22+V23+V24+X21+X22+X23+X24=2,Fixo/30*FG$4,IF(V21+V22+V23+V24+X21+X22+X23+X24>2,Fixo/30*FG$4+(V21+V22+V23+V24+X21+X22+X23+X24-2)*Cadeirante/30*FG$4)))+(U21+U22+U23+W21+W22+W23)*Percapita/30*FG$4+(U24+W24)*Crechee/30*FG$4,IF(C21=1,IF(U21+U22+U23+V21+V22+V23+W21+W22+W23+X21+X22+X23<=15,(U21+U22+U23+W21+W22+W23)*Percapita/30*FG$4,IF(U21+U22+U23+V21+V22+V23+W21+W22+W23+X21+X22+X23>=16,Fixo/30*FG$4+(U21+U22+U23+V21+V22+V23+W21+W22+W23+X21+X22-16)*Percapita/30*FG$4)))))) -> 0 | FH21: =IF(C21=4,SUM(Y21+Y22+Y23+AA21+AA22+AA23)*Percapita/30*FH$4+(Z21+Z22+Z23+AB21+AB22+AB23)*Cadeirante/30*FH$4,IF(C21=3,IF(Y24+AA24=10,Fixo/30*FH$4+(Y21+Y22+Y23+AA21+AA22+AA23)*Percapita/30*FH$4+(Z24+AB24)*Cadeirante/30*FH$4,IF(Y24+AA24<=9,(Y24+AA24)*Crechee/30*FH$4)+(Z24+AB24)*Cadeirante/30*FH$4+(Y21+Y22+Y23+AA21+AA22+AA23)*Percapita/30*FH$4)+IF(Y24+AA24>=11,Fixo/30*FH$4+(Y24+AA24-10)*Crechee/30*FH$4,0),IF(C21=2,IF(Z21+Z22+Z23+Z24+AB21+AB22+AB23+AB24=1,Cadeirante/30*FH$4,IF(Z21+Z22+Z23+Z24+AB21+AB22+AB23+AB24=2,Fixo/30*FH$4,IF(Z21+Z22+Z23+Z24+AB21+AB22+AB23+AB24>2,Fixo/30*FH$4+(Z21+Z22+Z23+Z24+AB21+AB22+AB23+AB24-2)*Cadeirante/30*FH$4)))+(Y21+Y22+Y23+AA21+AA22+AA23)*Percapita/30*FH$4+(Y24+AA24)*Crechee/30*FH$4,IF(C21=1,IF(Y21+Y22+Y23+Z21+Z22+Z23+AA21+AA22+AA23+AB21+AB22+AB23<=15,(Y21+Y22+Y23+AA21+AA22+AA23)*Percapita/30*FH$4,IF(Y21+Y22+Y23+Z21+Z22+Z23+AA21+AA22+AA23+AB21+AB22+AB23>=16,Fixo/30*FH$4+(Y21+Y22+Y23+Z21+Z22+Z23+AA21+AA22+AA23+AB21+AB22-16)*Percapita/30*FH$4)))))) -> 0 | FI21: =IF(C21=4,SUM(AC21+AC22+AC23+AE21+AE22+AE23)*Percapita/30*FI$4+(AD21+AD22+AD23+AF21+AF22+AF23)*Cadeirante/30*FI$4,IF(C21=3,IF(AC24+AE24=10,Fixo/30*FI$4+(AC21+AC22+AC23+AE21+AE22+AE23)*Percapita/30*FI$4+(AD24+AF24)*Cadeirante/30*FI$4,IF(AC24+AE24<=9,(AC24+AE24)*Crechee/30*FI$4)+(AD24+AF24)*Cadeirante/30*FI$4+(AC21+AC22+AC23+AE21+AE22+AE23)*Percapita/30*FI$4)+IF(AC24+AE24>=11,Fixo/30*FI$4+(AC24+AE24-10)*Crechee/30*FI$4,0),IF(C21=2,IF(AD21+AD22+AD23+AD24+AF21+AF22+AF23+AF24=1,Cadeirante/30*FI$4,IF(AD21+AD22+AD23+AD24+AF21+AF22+AF23+AF24=2,Fixo/30*FI$4,IF(AD21+AD22+AD23+AD24+AF21+AF22+AF23+AF24>2,Fixo/30*FI$4+(AD21+AD22+AD23+AD24+AF21+AF22+AF23+AF24-2)*Cadeirante/30*FI$4)))+(AC21+AC22+AC23+AE21+AE22+AE23)*Percapita/30*FI$4+(AC24+AE24)*Crechee/30*FI$4,IF(C21=1,IF(AC21+AC22+AC23+AD21+AD22+AD23+AE21+AE22+AE23+AF21+AF22+AF23<=15,(AC21+AC22+AC23+AE21+AE22+AE23)*Percapita/30*FI$4,IF(AC21+AC22+AC23+AD21+AD22+AD23+AE21+AE22+AE23+AF21+AF22+AF23>=16,Fixo/30*FI$4+(AC21+AC22+AC23+AD21+AD22+AD23+AE21+AE22+AE23+AF21+AF22-16)*Percapita/30*FI$4)))))) -> 0 | FJ21: =IF(C21=4,SUM(AG21+AG22+AG23+AI21+AI22+AI23)*Percapita/30*FJ$4+(AH21+AH22+AH23+AJ21+AJ22+AJ23)*Cadeirante/30*FJ$4,IF(C21=3,IF(AG24+AI24=10,Fixo/30*FJ$4+(AG21+AG22+AG23+AI21+AI22+AI23)*Percapita/30*FJ$4+(AH24+AJ24)*Cadeirante/30*FJ$4,IF(AG24+AI24<=9,(AG24+AI24)*Crechee/30*FJ$4)+(AH24+AJ24)*Cadeirante/30*FJ$4+(AG21+AG22+AG23+AI21+AI22+AI23)*Percapita/30*FJ$4)+IF(AG24+AI24>=11,Fixo/30*FJ$4+(AG24+AI24-10)*Crechee/30*FJ$4,0),IF(C21=2,IF(AH21+AH22+AH23+AH24+AJ21+AJ22+AJ23+AJ24=1,Cadeirante/30*FJ$4,IF(AH21+AH22+AH23+AH24+AJ21+AJ22+AJ23+AJ24=2,Fixo/30*FJ$4,IF(AH21+AH22+AH23+AH24+AJ21+AJ22+AJ23+AJ24>2,Fixo/30*FJ$4+(AH21+AH22+AH23+AH24+AJ21+AJ22+AJ23+AJ24-2)*Cadeirante/30*FJ$4)))+(AG21+AG22+AG23+AI21+AI22+AI23)*Percapita/30*FJ$4+(AG24+AI24)*Crechee/30*FJ$4,IF(C21=1,IF(AG21+AG22+AG23+AH21+AH22+AH23+AI21+AI22+AI23+AJ21+AJ22+AJ23<=15,(AG21+AG22+AG23+AI21+AI22+AI23)*Percapita/30*FJ$4,IF(AG21+AG22+AG23+AH21+AH22+AH23+AI21+AI22+AI23+AJ21+AJ22+AJ23>=16,Fixo/30*FJ$4+(AG21+AG22+AG23+AH21+AH22+AH23+AI21+AI22+AI23+AJ21+AJ22-16)*Percapita/30*FJ$4)))))) -> 0 | FK21: =IF(C21=4,SUM(AK21+AK22+AK23+AM21+AM22+AM23)*Percapita/30*FK$4+(AL21+AL22+AL23+AN21+AN22+AN23)*Cadeirante/30*FK$4,IF(C21=3,IF(AK24+AM24=10,Fixo/30*FK$4+(AK21+AK22+AK23+AM21+AM22+AM23)*Percapita/30*FK$4+(AL24+AN24)*Cadeirante/30*FK$4,IF(AK24+AM24<=9,(AK24+AM24)*Crechee/30*FK$4)+(AL24+AN24)*Cadeirante/30*FK$4+(AK21+AK22+AK23+AM21+AM22+AM23)*Percapita/30*FK$4)+IF(AK24+AM24>=11,Fixo/30*FK$4+(AK24+AM24-10)*Crechee/30*FK$4,0),IF(C21=2,IF(AL21+AL22+AL23+AL24+AN21+AN22+AN23+AN24=1,Cadeirante/30*FK$4,IF(AL21+AL22+AL23+AL24+AN21+AN22+AN23+AN24=2,Fixo/30*FK$4,IF(AL21+AL22+AL23+AL24+AN21+AN22+AN23+AN24>2,Fixo/30*FK$4+(AL21+AL22+AL23+AL24+AN21+AN22+AN23+AN24-2)*Cadeirante/30*FK$4)))+(AK21+AK22+AK23+AM21+AM22+AM23)*Percapita/30*FK$4+(AK24+AM24)*Crechee/30*FK$4,IF(C21=1,IF(AK21+AK22+AK23+AL21+AL22+AL23+AM21+AM22+AM23+AN21+AN22+AN23<=15,(AK21+AK22+AK23+AM21+AM22+AM23)*Percapita/30*FK$4,IF(AK21+AK22+AK23+AL21+AL22+AL23+AM21+AM22+AM23+AN21+AN22+AN23>=16,Fixo/30*FK$4+(AK21+AK22+AK23+AL21+AL22+AL23+AM21+AM22+AM23+AN21+AN22-16)*Percapita/30*FK$4)))))) -> 0 | FL21: =IF(C21=4,SUM(AO21+AO22+AO23+AQ21+AQ22+AQ23)*Percapita/30*FL$4+(AP21+AP22+AP23+AR21+AR22+AR23)*Cadeirante/30*FL$4,IF(C21=3,IF(AO24+AQ24=10,Fixo/30*FL$4+(AO21+AO22+AO23+AQ21+AQ22+AQ23)*Percapita/30*FL$4+(AP24+AR24)*Cadeirante/30*FL$4,IF(AO24+AQ24<=9,(AO24+AQ24)*Crechee/30*FL$4)+(AP24+AR24)*Cadeirante/30*FL$4+(AO21+AO22+AO23+AQ21+AQ22+AQ23)*Percapita/30*FL$4)+IF(AO24+AQ24>=11,Fixo/30*FL$4+(AO24+AQ24-10)*Crechee/30*FL$4,0),IF(C21=2,IF(AP21+AP22+AP23+AP24+AR21+AR22+AR23+AR24=1,Cadeirante/30*FL$4,IF(AP21+AP22+AP23+AP24+AR21+AR22+AR23+AR24=2,Fixo/30*FL$4,IF(AP21+AP22+AP23+AP24+AR21+AR22+AR23+AR24>2,Fixo/30*FL$4+(AP21+AP22+AP23+AP24+AR21+AR22+AR23+AR24-2)*Cadeirante/30*FL$4)))+(AO21+AO22+AO23+AQ21+AQ22+AQ23)*Percapita/30*FL$4+(AO24+AQ24)*Crechee/30*FL$4,IF(C21=1,IF(AO21+AO22+AO23+AP21+AP22+AP23+AQ21+AQ22+AQ23+AR21+AR22+AR23<=15,(AO21+AO22+AO23+AQ21+AQ22+AQ23)*Percapita/30*FL$4,IF(AO21+AO22+AO23+AP21+AP22+AP23+AQ21+AQ22+AQ23+AR21+AR22+AR23>=16,Fixo/30*FL$4+(AO21+AO22+AO23+AP21+AP22+AP23+AQ21+AQ22+AQ23+AR21+AR22-16)*Percapita/30*FL$4)))))) -> 0 | FM21: =IF(C21=4,SUM(AS21+AS22+AS23+AU21+AU22+AU23)*Percapita/30*FM$4+(AT21+AT22+AT23+AV21+AV22+AV23)*Cadeirante/30*FM$4,IF(C21=3,IF(AS24+AU24=10,Fixo/30*FM$4+(AS21+AS22+AS23+AU21+AU22+AU23)*Percapita/30*FM$4+(AT24+AV24)*Cadeirante/30*FM$4,IF(AS24+AU24<=9,(AS24+AU24)*Crechee/30*FM$4)+(AT24+AV24)*Cadeirante/30*FM$4+(AS21+AS22+AS23+AU21+AU22+AU23)*Percapita/30*FM$4)+IF(AS24+AU24>=11,Fixo/30*FM$4+(AS24+AU24-10)*Crechee/30*FM$4,0),IF(C21=2,IF(AT21+AT22+AT23+AT24+AV21+AV22+AV23+AV24=1,Cadeirante/30*FM$4,IF(AT21+AT22+AT23+AT24+AV21+AV22+AV23+AV24=2,Fixo/30*FM$4,IF(AT21+AT22+AT23+AT24+AV21+AV22+AV23+AV24>2,Fixo/30*FM$4+(AT21+AT22+AT23+AT24+AV21+AV22+AV23+AV24-2)*Cadeirante/30*FM$4)))+(AS21+AS22+AS23+AU21+AU22+AU23)*Percapita/30*FM$4+(AS24+AU24)*Crechee/30*FM$4,IF(C21=1,IF(AS21+AS22+AS23+AT21+AT22+AT23+AU21+AU22+AU23+AV21+AV22+AV23<=15,(AS21+AS22+AS23+AU21+AU22+AU23)*Percapita/30*FM$4,IF(AS21+AS22+AS23+AT21+AT22+AT23+AU21+AU22+AU23+AV21+AV22+AV23>=16,Fixo/30*FM$4+(AS21+AS22+AS23+AT21+AT22+AT23+AU21+AU22+AU23+AV21+AV22-16)*Percapita/30*FM$4)))))) -> 0 | FN21: =IF(C21=4,SUM(AW21+AW22+AW23+AY21+AY22+AY23)*Percapita/30*FN$4+(AX21+AX22+AX23+AZ21+AZ22+AZ23)*Cadeirante/30*FN$4,IF(C21=3,IF(AW24+AY24=10,Fixo/30*FN$4+(AW21+AW22+AW23+AY21+AY22+AY23)*Percapita/30*FN$4+(AX24+AZ24)*Cadeirante/30*FN$4,IF(AW24+AY24<=9,(AW24+AY24)*Crechee/30*FN$4)+(AX24+AZ24)*Cadeirante/30*FN$4+(AW21+AW22+AW23+AY21+AY22+AY23)*Percapita/30*FN$4)+IF(AW24+AY24>=11,Fixo/30*FN$4+(AW24+AY24-10)*Crechee/30*FN$4,0),IF(C21=2,IF(AX21+AX22+AX23+AX24+AZ21+AZ22+AZ23+AZ24=1,Cadeirante/30*FN$4,IF(AX21+AX22+AX23+AX24+AZ21+AZ22+AZ23+AZ24=2,Fixo/30*FN$4,IF(AX21+AX22+AX23+AX24+AZ21+AZ22+AZ23+AZ24>2,Fixo/30*FN$4+(AX21+AX22+AX23+AX24+AZ21+AZ22+AZ23+AZ24-2)*Cadeirante/30*FN$4)))+(AW21+AW22+AW23+AY21+AY22+AY23)*Percapita/30*FN$4+(AW24+AY24)*Crechee/30*FN$4,IF(C21=1,IF(AW21+AW22+AW23+AX21+AX22+AX23+AY21+AY22+AY23+AZ21+AZ22+AZ23<=15,(AW21+AW22+AW23+AY21+AY22+AY23)*Percapita/30*FN$4,IF(AW21+AW22+AW23+AX21+AX22+AX23+AY21+AY22+AY23+AZ21+AZ22+AZ23>=16,Fixo/30*FN$4+(AW21+AW22+AW23+AX21+AX22+AX23+AY21+AY22+AY23+AZ21+AZ22-16)*Percapita/30*FN$4)))))) -> 0 | FO21: =IF(C21=4,SUM(BA21+BA22+BA23+BC21+BC22+BC23)*Percapita/30*FO$4+(BB21+BB22+BB23+BD21+BD22+BD23)*Cadeirante/30*FO$4,IF(C21=3,IF(BA24+BC24=10,Fixo/30*FO$4+(BA21+BA22+BA23+BC21+BC22+BC23)*Percapita/30*FO$4+(BB24+BD24)*Cadeirante/30*FO$4,IF(BA24+BC24<=9,(BA24+BC24)*Crechee/30*FO$4)+(BB24+BD24)*Cadeirante/30*FO$4+(BA21+BA22+BA23+BC21+BC22+BC23)*Percapita/30*FO$4)+IF(BA24+BC24>=11,Fixo/30*FO$4+(BA24+BC24-10)*Crechee/30*FO$4,0),IF(C21=2,IF(BB21+BB22+BB23+BB24+BD21+BD22+BD23+BD24=1,Cadeirante/30*FO$4,IF(BB21+BB22+BB23+BB24+BD21+BD22+BD23+BD24=2,Fixo/30*FO$4,IF(BB21+BB22+BB23+BB24+BD21+BD22+BD23+BD24>2,Fixo/30*FO$4+(BB21+BB22+BB23+BB24+BD21+BD22+BD23+BD24-2)*Cadeirante/30*FO$4)))+(BA21+BA22+BA23+BC21+BC22+BC23)*Percapita/30*FO$4+(BA24+BC24)*Crechee/30*FO$4,IF(C21=1,IF(BA21+BA22+BA23+BB21+BB22+BB23+BC21+BC22+BC23+BD21+BD22+BD23<=15,(BA21+BA22+BA23+BC21+BC22+BC23)*Percapita/30*FO$4,IF(BA21+BA22+BA23+BB21+BB22+BB23+BC21+BC22+BC23+BD21+BD22+BD23>=16,Fixo/30*FO$4+(BA21+BA22+BA23+BB21+BB22+BB23+BC21+BC22+BC23+BD21+BD22-16)*Percapita/30*FO$4)))))) -> 0 | FP21: =IF(C21=4,SUM(BE21+BE22+BE23+BG21+BG22+BG23)*Percapita/30*FP$4+(BF21+BF22+BF23+BH21+BH22+BH23)*Cadeirante/30*FP$4,IF(C21=3,IF(BE24+BG24=10,Fixo/30*FP$4+(BE21+BE22+BE23+BG21+BG22+BG23)*Percapita/30*FP$4+(BF24+BH24)*Cadeirante/30*FP$4,IF(BE24+BG24<=9,(BE24+BG24)*Crechee/30*FP$4)+(BF24+BH24)*Cadeirante/30*FP$4+(BE21+BE22+BE23+BG21+BG22+BG23)*Percapita/30*FP$4)+IF(BE24+BG24>=11,Fixo/30*FP$4+(BE24+BG24-10)*Crechee/30*FP$4,0),IF(C21=2,IF(BF21+BF22+BF23+BF24+BH21+BH22+BH23+BH24=1,Cadeirante/30*FP$4,IF(BF21+BF22+BF23+BF24+BH21+BH22+BH23+BH24=2,Fixo/30*FP$4,IF(BF21+BF22+BF23+BF24+BH21+BH22+BH23+BH24>2,Fixo/30*FP$4+(BF21+BF22+BF23+BF24+BH21+BH22+BH23+BH24-2)*Cadeirante/30*FP$4)))+(BE21+BE22+BE23+BG21+BG22+BG23)*Percapita/30*FP$4+(BE24+BG24)*Crechee/30*FP$4,IF(C21=1,IF(BE21+BE22+BE23+BF21+BF22+BF23+BG21+BG22+BG23+BH21+BH22+BH23<=15,(BE21+BE22+BE23+BG21+BG22+BG23)*Percapita/30*FP$4,IF(BE21+BE22+BE23+BF21+BF22+BF23+BG21+BG22+BG23+BH21+BH22+BH23>=16,Fixo/30*FP$4+(BE21+BE22+BE23+BF21+BF22+BF23+BG21+BG22+BG23+BH21+BH22-16)*Percapita/30*FP$4)))))) -> 0 | FQ21: =IF(C21=4,SUM(BI21+BI22+BI23+BK21+BK22+BK23)*Percapita/30*FQ$4+(BJ21+BJ22+BJ23+BL21+BL22+BL23)*Cadeirante/30*FQ$4,IF(C21=3,IF(BI24+BK24=10,Fixo/30*FQ$4+(BI21+BI22+BI23+BK21+BK22+BK23)*Percapita/30*FQ$4+(BJ24+BL24)*Cadeirante/30*FQ$4,IF(BI24+BK24<=9,(BI24+BK24)*Crechee/30*FQ$4)+(BJ24+BL24)*Cadeirante/30*FQ$4+(BI21+BI22+BI23+BK21+BK22+BK23)*Percapita/30*FQ$4)+IF(BI24+BK24>=11,Fixo/30*FQ$4+(BI24+BK24-10)*Crechee/30*FQ$4,0),IF(C21=2,IF(BJ21+BJ22+BJ23+BJ24+BL21+BL22+BL23+BL24=1,Cadeirante/30*FQ$4,IF(BJ21+BJ22+BJ23+BJ24+BL21+BL22+BL23+BL24=2,Fixo/30*FQ$4,IF(BJ21+BJ22+BJ23+BJ24+BL21+BL22+BL23+BL24>2,Fixo/30*FQ$4+(BJ21+BJ22+BJ23+BJ24+BL21+BL22+BL23+BL24-2)*Cadeirante/30*FQ$4)))+(BI21+BI22+BI23+BK21+BK22+BK23)*Percapita/30*FQ$4+(BI24+BK24)*Crechee/30*FQ$4,IF(C21=1,IF(BI21+BI22+BI23+BJ21+BJ22+BJ23+BK21+BK22+BK23+BL21+BL22+BL23<=15,(BI21+BI22+BI23+BK21+BK22+BK23)*Percapita/30*FQ$4,IF(BI21+BI22+BI23+BJ21+BJ22+BJ23+BK21+BK22+BK23+BL21+BL22+BL23>=16,Fixo/30*FQ$4+(BI21+BI22+BI23+BJ21+BJ22+BJ23+BK21+BK22+BK23+BL21+BL22-16)*Percapita/30*FQ$4)))))) -> 0 | FR21: =IF(C21=4,SUM(BM21+BM22+BM23+BO21+BO22+BO23)*Percapita/30*FR$4+(BN21+BN22+BN23+BP21+BP22+BP23)*Cadeirante/30*FR$4,IF(C21=3,IF(BM24+BO24=10,Fixo/30*FR$4+(BM21+BM22+BM23+BO21+BO22+BO23)*Percapita/30*FR$4+(BN24+BP24)*Cadeirante/30*FR$4,IF(BM24+BO24<=9,(BM24+BO24)*Crechee/30*FR$4)+(BN24+BP24)*Cadeirante/30*FR$4+(BM21+BM22+BM23+BO21+BO22+BO23)*Percapita/30*FR$4)+IF(BM24+BO24>=11,Fixo/30*FR$4+(BM24+BO24-10)*Crechee/30*FR$4,0),IF(C21=2,IF(BN21+BN22+BN23+BN24+BP21+BP22+BP23+BP24=1,Cadeirante/30*FR$4,IF(BN21+BN22+BN23+BN24+BP21+BP22+BP23+BP24=2,Fixo/30*FR$4,IF(BN21+BN22+BN23+BN24+BP21+BP22+BP23+BP24>2,Fixo/30*FR$4+(BN21+BN22+BN23+BN24+BP21+BP22+BP23+BP24-2)*Cadeirante/30*FR$4)))+(BM21+BM22+BM23+BO21+BO22+BO23)*Percapita/30*FR$4+(BM24+BO24)*Crechee/30*FR$4,IF(C21=1,IF(BM21+BM22+BM23+BN21+BN22+BN23+BO21+BO22+BO23+BP21+BP22+BP23<=15,(BM21+BM22+BM23+BO21+BO22+BO23)*Percapita/30*FR$4,IF(BM21+BM22+BM23+BN21+BN22+BN23+BO21+BO22+BO23+BP21+BP22+BP23>=16,Fixo/30*FR$4+(BM21+BM22+BM23+BN21+BN22+BN23+BO21+BO22+BO23+BP21+BP22-16)*Percapita/30*FR$4)))))) -> 0 | FS21: =IF(C21=4,SUM(BQ21+BQ22+BQ23+BS21+BS22+BS23)*Percapita/30*FS$4+(BR21+BR22+BR23+BT21+BT22+BT23)*Cadeirante/30*FS$4,IF(C21=3,IF(BQ24+BS24=10,Fixo/30*FS$4+(BQ21+BQ22+BQ23+BS21+BS22+BS23)*Percapita/30*FS$4+(BR24+BT24)*Cadeirante/30*FS$4,IF(BQ24+BS24<=9,(BQ24+BS24)*Crechee/30*FS$4)+(BR24+BT24)*Cadeirante/30*FS$4+(BQ21+BQ22+BQ23+BS21+BS22+BS23)*Percapita/30*FS$4)+IF(BQ24+BS24>=11,Fixo/30*FS$4+(BQ24+BS24-10)*Crechee/30*FS$4,0),IF(C21=2,IF(BR21+BR22+BR23+BR24+BT21+BT22+BT23+BT24=1,Cadeirante/30*FS$4,IF(BR21+BR22+BR23+BR24+BT21+BT22+BT23+BT24=2,Fixo/30*FS$4,IF(BR21+BR22+BR23+BR24+BT21+BT22+BT23+BT24>2,Fixo/30*FS$4+(BR21+BR22+BR23+BR24+BT21+BT22+BT23+BT24-2)*Cadeirante/30*FS$4)))+(BQ21+BQ22+BQ23+BS21+BS22+BS23)*Percapita/30*FS$4+(BQ24+BS24)*Crechee/30*FS$4,IF(C21=1,IF(BQ21+BQ22+BQ23+BR21+BR22+BR23+BS21+BS22+BS23+BT21+BT22+BT23<=15,(BQ21+BQ22+BQ23+BS21+BS22+BS23)*Percapita/30*FS$4,IF(BQ21+BQ22+BQ23+BR21+BR22+BR23+BS21+BS22+BS23+BT21+BT22+BT23>=16,Fixo/30*FS$4+(BQ21+BQ22+BQ23+BR21+BR22+BR23+BS21+BS22+BS23+BT21+BT22-16)*Percapita/30*FS$4)))))) -> 0 | FT21: =IF(C21=4,SUM(BU21+BU22+BU23+BW21+BW22+BW23)*Percapita/30*FT$4+(BV21+BV22+BV23+BX21+BX22+BX23)*Cadeirante/30*FT$4,IF(C21=3,IF(BU24+BW24=10,Fixo/30*FT$4+(BU21+BU22+BU23+BW21+BW22+BW23)*Percapita/30*FT$4+(BV24+BX24)*Cadeirante/30*FT$4,IF(BU24+BW24<=9,(BU24+BW24)*Crechee/30*FT$4)+(BV24+BX24)*Cadeirante/30*FT$4+(BU21+BU22+BU23+BW21+BW22+BW23)*Percapita/30*FT$4)+IF(BU24+BW24>=11,Fixo/30*FT$4+(BU24+BW24-10)*Crechee/30*FT$4,0),IF(C21=2,IF(BV21+BV22+BV23+BV24+BX21+BX22+BX23+BX24=1,Cadeirante/30*FT$4,IF(BV21+BV22+BV23+BV24+BX21+BX22+BX23+BX24=2,Fixo/30*FT$4,IF(BV21+BV22+BV23+BV24+BX21+BX22+BX23+BX24>2,Fixo/30*FT$4+(BV21+BV22+BV23+BV24+BX21+BX22+BX23+BX24-2)*Cadeirante/30*FT$4)))+(BU21+BU22+BU23+BW21+BW22+BW23)*Percapita/30*FT$4+(BU24+BW24)*Crechee/30*FT$4,IF(C21=1,IF(BU21+BU22+BU23+BV21+BV22+BV23+BW21+BW22+BW23+BX21+BX22+BX23<=15,(BU21+BU22+BU23+BW21+BW22+BW23)*Percapita/30*FT$4,IF(BU21+BU22+BU23+BV21+BV22+BV23+BW21+BW22+BW23+BX21+BX22+BX23>=16,Fixo/30*FT$4+(BU21+BU22+BU23+BV21+BV22+BV23+BW21+BW22+BW23+BX21+BX22-16)*Percapita/30*FT$4)))))) -> 0 | FU21: =IF(C21=4,SUM(BY21+BY22+BY23+CA21+CA22+CA23)*Percapita/30*FU$4+(BZ21+BZ22+BZ23+CB21+CB22+CB23)*Cadeirante/30*FU$4,IF(C21=3,IF(BY24+CA24=10,Fixo/30*FU$4+(BY21+BY22+BY23+CA21+CA22+CA23)*Percapita/30*FU$4+(BZ24+CB24)*Cadeirante/30*FU$4,IF(BY24+CA24<=9,(BY24+CA24)*Crechee/30*FU$4)+(BZ24+CB24)*Cadeirante/30*FU$4+(BY21+BY22+BY23+CA21+CA22+CA23)*Percapita/30*FU$4)+IF(BY24+CA24>=11,Fixo/30*FU$4+(BY24+CA24-10)*Crechee/30*FU$4,0),IF(C21=2,IF(BZ21+BZ22+BZ23+BZ24+CB21+CB22+CB23+CB24=1,Cadeirante/30*FU$4,IF(BZ21+BZ22+BZ23+BZ24+CB21+CB22+CB23+CB24=2,Fixo/30*FU$4,IF(BZ21+BZ22+BZ23+BZ24+CB21+CB22+CB23+CB24>2,Fixo/30*FU$4+(BZ21+BZ22+BZ23+BZ24+CB21+CB22+CB23+CB24-2)*Cadeirante/30*FU$4)))+(BY21+BY22+BY23+CA21+CA22+CA23)*Percapita/30*FU$4+(BY24+CA24)*Crechee/30*FU$4,IF(C21=1,IF(BY21+BY22+BY23+BZ21+BZ22+BZ23+CA21+CA22+CA23+CB21+CB22+CB23<=15,(BY21+BY22+BY23+CA21+CA22+CA23)*Percapita/30*FU$4,IF(BY21+BY22+BY23+BZ21+BZ22+BZ23+CA21+CA22+CA23+CB21+CB22+CB23>=16,Fixo/30*FU$4+(BY21+BY22+BY23+BZ21+BZ22+BZ23+CA21+CA22+CA23+CB21+CB22-16)*Percapita/30*FU$4)))))) -> 0 | FV21: =IF(C21=4,SUM(CC21+CC22+CC23+CE21+CE22+CE23)*Percapita/30*FV$4+(CD21+CD22+CD23+CF21+CF22+CF23)*Cadeirante/30*FV$4,IF(C21=3,IF(CC24+CE24=10,Fixo/30*FV$4+(CC21+CC22+CC23+CE21+CE22+CE23)*Percapita/30*FV$4+(CD24+CF24)*Cadeirante/30*FV$4,IF(CC24+CE24<=9,(CC24+CE24)*Crechee/30*FV$4)+(CD24+CF24)*Cadeirante/30*FV$4+(CC21+CC22+CC23+CE21+CE22+CE23)*Percapita/30*FV$4)+IF(CC24+CE24>=11,Fixo/30*FV$4+(CC24+CE24-10)*Crechee/30*FV$4,0),IF(C21=2,IF(CD21+CD22+CD23+CD24+CF21+CF22+CF23+CF24=1,Cadeirante/30*FV$4,IF(CD21+CD22+CD23+CD24+CF21+CF22+CF23+CF24=2,Fixo/30*FV$4,IF(CD21+CD22+CD23+CD24+CF21+CF22+CF23+CF24>2,Fixo/30*FV$4+(CD21+CD22+CD23+CD24+CF21+CF22+CF23+CF24-2)*Cadeirante/30*FV$4)))+(CC21+CC22+CC23+CE21+CE22+CE23)*Percapita/30*FV$4+(CC24+CE24)*Crechee/30*FV$4,IF(C21=1,IF(CC21+CC22+CC23+CD21+CD22+CD23+CE21+CE22+CE23+CF21+CF22+CF23<=15,(CC21+CC22+CC23+CE21+CE22+CE23)*Percapita/30*FV$4,IF(CC21+CC22+CC23+CD21+CD22+CD23+CE21+CE22+CE23+CF21+CF22+CF23>=16,Fixo/30*FV$4+(CC21+CC22+CC23+CD21+CD22+CD23+CE21+CE22+CE23+CF21+CF22-16)*Percapita/30*FV$4)))))) -> 0 | FW21: =IF(C21=4,SUM(CG21+CG22+CG23+CI21+CI22+CI23)*Percapita/30*FW$4+(CH21+CH22+CH23+CJ21+CJ22+CJ23)*Cadeirante/30*FW$4,IF(C21=3,IF(CG24+CI24=10,Fixo/30*FW$4+(CG21+CG22+CG23+CI21+CI22+CI23)*Percapita/30*FW$4+(CH24+CJ24)*Cadeirante/30*FW$4,IF(CG24+CI24<=9,(CG24+CI24)*Crechee/30*FW$4)+(CH24+CJ24)*Cadeirante/30*FW$4+(CG21+CG22+CG23+CI21+CI22+CI23)*Percapita/30*FW$4)+IF(CG24+CI24>=11,Fixo/30*FW$4+(CG24+CI24-10)*Crechee/30*FW$4,0),IF(C21=2,IF(CH21+CH22+CH23+CH24+CJ21+CJ22+CJ23+CJ24=1,Cadeirante/30*FW$4,IF(CH21+CH22+CH23+CH24+CJ21+CJ22+CJ23+CJ24=2,Fixo/30*FW$4,IF(CH21+CH22+CH23+CH24+CJ21+CJ22+CJ23+CJ24>2,Fixo/30*FW$4+(CH21+CH22+CH23+CH24+CJ21+CJ22+CJ23+CJ24-2)*Cadeirante/30*FW$4)))+(CG21+CG22+CG23+CI21+CI22+CI23)*Percapita/30*FW$4+(CG24+CI24)*Crechee/30*FW$4,IF(C21=1,IF(CG21+CG22+CG23+CH21+CH22+CH23+CI21+CI22+CI23+CJ21+CJ22+CJ23<=15,(CG21+CG22+CG23+CI21+CI22+CI23)*Percapita/30*FW$4,IF(CG21+CG22+CG23+CH21+CH22+CH23+CI21+CI22+CI23+CJ21+CJ22+CJ23>=16,Fixo/30*FW$4+(CG21+CG22+CG23+CH21+CH22+CH23+CI21+CI22+CI23+CJ21+CJ22-16)*Percapita/30*FW$4)))))) -> 0 | FX21: =IF(C21=4,SUM(CK21+CK22+CK23+CM21+CM22+CM23)*Percapita/30*FX$4+(CL21+CL22+CL23+CN21+CN22+CN23)*Cadeirante/30*FX$4,IF(C21=3,IF(CK24+CM24=10,Fixo/30*FX$4+(CK21+CK22+CK23+CM21+CM22+CM23)*Percapita/30*FX$4+(CL24+CN24)*Cadeirante/30*FX$4,IF(CK24+CM24<=9,(CK24+CM24)*Crechee/30*FX$4)+(CL24+CN24)*Cadeirante/30*FX$4+(CK21+CK22+CK23+CM21+CM22+CM23)*Percapita/30*FX$4)+IF(CK24+CM24>=11,Fixo/30*FX$4+(CK24+CM24-10)*Crechee/30*FX$4,0),IF(C21=2,IF(CL21+CL22+CL23+CL24+CN21+CN22+CN23+CN24=1,Cadeirante/30*FX$4,IF(CL21+CL22+CL23+CL24+CN21+CN22+CN23+CN24=2,Fixo/30*FX$4,IF(CL21+CL22+CL23+CL24+CN21+CN22+CN23+CN24>2,Fixo/30*FX$4+(CL21+CL22+CL23+CL24+CN21+CN22+CN23+CN24-2)*Cadeirante/30*FX$4)))+(CK21+CK22+CK23+CM21+CM22+CM23)*Percapita/30*FX$4+(CK24+CM24)*Crechee/30*FX$4,IF(C21=1,IF(CK21+CK22+CK23+CL21+CL22+CL23+CM21+CM22+CM23+CN21+CN22+CN23<=15,(CK21+CK22+CK23+CM21+CM22+CM23)*Percapita/30*FX$4,IF(CK21+CK22+CK23+CL21+CL22+CL23+CM21+CM22+CM23+CN21+CN22+CN23>=16,Fixo/30*FX$4+(CK21+CK22+CK23+CL21+CL22+CL23+CM21+CM22+CM23+CN21+CN22-16)*Percapita/30*FX$4)))))) -> 0 | FY21: =IF(C21=4,SUM(CO21+CO22+CO23+CQ21+CQ22+CQ23)*Percapita/30*FY$4+(CP21+CP22+CP23+CR21+CR22+CR23)*Cadeirante/30*FY$4,IF(C21=3,IF(CO24+CQ24=10,Fixo/30*FY$4+(CO21+CO22+CO23+CQ21+CQ22+CQ23)*Percapita/30*FY$4+(CP24+CR24)*Cadeirante/30*FY$4,IF(CO24+CQ24<=9,(CO24+CQ24)*Crechee/30*FY$4)+(CP24+CR24)*Cadeirante/30*FY$4+(CO21+CO22+CO23+CQ21+CQ22+CQ23)*Percapita/30*FY$4)+IF(CO24+CQ24>=11,Fixo/30*FY$4+(CO24+CQ24-10)*Crechee/30*FY$4,0),IF(C21=2,IF(CP21+CP22+CP23+CP24+CR21+CR22+CR23+CR24=1,Cadeirante/30*FY$4,IF(CP21+CP22+CP23+CP24+CR21+CR22+CR23+CR24=2,Fixo/30*FY$4,IF(CP21+CP22+CP23+CP24+CR21+CR22+CR23+CR24>2,Fixo/30*FY$4+(CP21+CP22+CP23+CP24+CR21+CR22+CR23+CR24-2)*Cadeirante/30*FY$4)))+(CO21+CO22+CO23+CQ21+CQ22+CQ23)*Percapita/30*FY$4+(CO24+CQ24)*Crechee/30*FY$4,IF(C21=1,IF(CO21+CO22+CO23+CP21+CP22+CP23+CQ21+CQ22+CQ23+CR21+CR22+CR23<=15,(CO21+CO22+CO23+CQ21+CQ22+CQ23)*Percapita/30*FY$4,IF(CO21+CO22+CO23+CP21+CP22+CP23+CQ21+CQ22+CQ23+CR21+CR22+CR23>=16,Fixo/30*FY$4+(CO21+CO22+CO23+CP21+CP22+CP23+CQ21+CQ22+CQ23+CR21+CR22-16)*Percapita/30*FY$4)))))) -> 0 | FZ21: =IF(C21=4,SUM(CS21+CS22+CS23+CU21+CU22+CU23)*Percapita/30*FZ$4+(CT21+CT22+CT23+CV21+CV22+CV23)*Cadeirante/30*FZ$4,IF(C21=3,IF(CS24+CU24=10,Fixo/30*FZ$4+(CS21+CS22+CS23+CU21+CU22+CU23)*Percapita/30*FZ$4+(CT24+CV24)*Cadeirante/30*FZ$4,IF(CS24+CU24<=9,(CS24+CU24)*Crechee/30*FZ$4)+(CT24+CV24)*Cadeirante/30*FZ$4+(CS21+CS22+CS23+CU21+CU22+CU23)*Percapita/30*FZ$4)+IF(CS24+CU24>=11,Fixo/30*FZ$4+(CS24+CU24-10)*Crechee/30*FZ$4,0),IF(C21=2,IF(CT21+CT22+CT23+CT24+CV21+CV22+CV23+CV24=1,Cadeirante/30*FZ$4,IF(CT21+CT22+CT23+CT24+CV21+CV22+CV23+CV24=2,Fixo/30*FZ$4,IF(CT21+CT22+CT23+CT24+CV21+CV22+CV23+CV24>2,Fixo/30*FZ$4+(CT21+CT22+CT23+CT24+CV21+CV22+CV23+CV24-2)*Cadeirante/30*FZ$4)))+(CS21+CS22+CS23+CU21+CU22+CU23)*Percapita/30*FZ$4+(CS24+CU24)*Crechee/30*FZ$4,IF(C21=1,IF(CS21+CS22+CS23+CT21+CT22+CT23+CU21+CU22+CU23+CV21+CV22+CV23<=15,(CS21+CS22+CS23+CU21+CU22+CU23)*Percapita/30*FZ$4,IF(CS21+CS22+CS23+CT21+CT22+CT23+CU21+CU22+CU23+CV21+CV22+CV23>=16,Fixo/30*FZ$4+(CS21+CS22+CS23+CT21+CT22+CT23+CU21+CU22+CU23+CV21+CV22-16)*Percapita/30*FZ$4)))))) -> 0 | GA21: =IF(C21=4,SUM(CW21+CW22+CW23+CY21+CY22+CY23)*Percapita/30*GA$4+(CX21+CX22+CX23+CZ21+CZ22+CZ23)*Cadeirante/30*GA$4,IF(C21=3,IF(CW24+CY24=10,Fixo/30*GA$4+(CW21+CW22+CW23+CY21+CY22+CY23)*Percapita/30*GA$4+(CX24+CZ24)*Cadeirante/30*GA$4,IF(CW24+CY24<=9,(CW24+CY24)*Crechee/30*GA$4)+(CX24+CZ24)*Cadeirante/30*GA$4+(CW21+CW22+CW23+CY21+CY22+CY23)*Percapita/30*GA$4)+IF(CW24+CY24>=11,Fixo/30*GA$4+(CW24+CY24-10)*Crechee/30*GA$4,0),IF(C21=2,IF(CX21+CX22+CX23+CX24+CZ21+CZ22+CZ23+CZ24=1,Cadeirante/30*GA$4,IF(CX21+CX22+CX23+CX24+CZ21+CZ22+CZ23+CZ24=2,Fixo/30*GA$4,IF(CX21+CX22+CX23+CX24+CZ21+CZ22+CZ23+CZ24>2,Fixo/30*GA$4+(CX21+CX22+CX23+CX24+CZ21+CZ22+CZ23+CZ24-2)*Cadeirante/30*GA$4)))+(CW21+CW22+CW23+CY21+CY22+CY23)*Percapita/30*GA$4+(CW24+CY24)*Crechee/30*GA$4,IF(C21=1,IF(CW21+CW22+CW23+CX21+CX22+CX23+CY21+CY22+CY23+CZ21+CZ22+CZ23<=15,(CW21+CW22+CW23+CY21+CY22+CY23)*Percapita/30*GA$4,IF(CW21+CW22+CW23+CX21+CX22+CX23+CY21+CY22+CY23+CZ21+CZ22+CZ23>=16,Fixo/30*GA$4+(CW21+CW22+CW23+CX21+CX22+CX23+CY21+CY22+CY23+CZ21+CZ22-16)*Percapita/30*GA$4)))))) -> 0 | GB21: =IF(C21=4,SUM(DA21+DA22+DA23+DC21+DC22+DC23)*Percapita/30*GB$4+(DB21+DB22+DB23+DD21+DD22+DD23)*Cadeirante/30*GB$4,IF(C21=3,IF(DA24+DC24=10,Fixo/30*GB$4+(DA21+DA22+DA23+DC21+DC22+DC23)*Percapita/30*GB$4+(DB24+DD24)*Cadeirante/30*GB$4,IF(DA24+DC24<=9,(DA24+DC24)*Crechee/30*GB$4)+(DB24+DD24)*Cadeirante/30*GB$4+(DA21+DA22+DA23+DC21+DC22+DC23)*Percapita/30*GB$4)+IF(DA24+DC24>=11,Fixo/30*GB$4+(DA24+DC24-10)*Crechee/30*GB$4,0),IF(C21=2,IF(DB21+DB22+DB23+DB24+DD21+DD22+DD23+DD24=1,Cadeirante/30*GB$4,IF(DB21+DB22+DB23+DB24+DD21+DD22+DD23+DD24=2,Fixo/30*GB$4,IF(DB21+DB22+DB23+DB24+DD21+DD22+DD23+DD24>2,Fixo/30*GB$4+(DB21+DB22+DB23+DB24+DD21+DD22+DD23+DD24-2)*Cadeirante/30*GB$4)))+(DA21+DA22+DA23+DC21+DC22+DC23)*Percapita/30*GB$4+(DA24+DC24)*Crechee/30*GB$4,IF(C21=1,IF(DA21+DA22+DA23+DB21+DB22+DB23+DC21+DC22+DC23+DD21+DD22+DD23<=15,(DA21+DA22+DA23+DC21+DC22+DC23)*Percapita/30*GB$4,IF(DA21+DA22+DA23+DB21+DB22+DB23+DC21+DC22+DC23+DD21+DD22+DD23>=16,Fixo/30*GB$4+(DA21+DA22+DA23+DB21+DB22+DB23+DC21+DC22+DC23+DD21+DD22-16)*Percapita/30*GB$4)))))) -> 0 | GC21: =IF(C21=4,SUM(DE21+DE22+DE23+DG21+DG22+DG23)*Percapita/30*GC$4+(DF21+DF22+DF23+DH21+DH22+DH23)*Cadeirante/30*GC$4,IF(C21=3,IF(DE24+DG24=10,Fixo/30*GC$4+(DE21+DE22+DE23+DG21+DG22+DG23)*Percapita/30*GC$4+(DF24+DH24)*Cadeirante/30*GC$4,IF(DE24+DG24<=9,(DE24+DG24)*Crechee/30*GC$4)+(DF24+DH24)*Cadeirante/30*GC$4+(DE21+DE22+DE23+DG21+DG22+DG23)*Percapita/30*GC$4)+IF(DE24+DG24>=11,Fixo/30*GC$4+(DE24+DG24-10)*Crechee/30*GC$4,0),IF(C21=2,IF(DF21+DF22+DF23+DF24+DH21+DH22+DH23+DH24=1,Cadeirante/30*GC$4,IF(DF21+DF22+DF23+DF24+DH21+DH22+DH23+DH24=2,Fixo/30*GC$4,IF(DF21+DF22+DF23+DF24+DH21+DH22+DH23+DH24>2,Fixo/30*GC$4+(DF21+DF22+DF23+DF24+DH21+DH22+DH23+DH24-2)*Cadeirante/30*GC$4)))+(DE21+DE22+DE23+DG21+DG22+DG23)*Percapita/30*GC$4+(DE24+DG24)*Crechee/30*GC$4,IF(C21=1,IF(DE21+DE22+DE23+DF21+DF22+DF23+DG21+DG22+DG23+DH21+DH22+DH23<=15,(DE21+DE22+DE23+DG21+DG22+DG23)*Percapita/30*GC$4,IF(DE21+DE22+DE23+DF21+DF22+DF23+DG21+DG22+DG23+DH21+DH22+DH23>=16,Fixo/30*GC$4+(DE21+DE22+DE23+DF21+DF22+DF23+DG21+DG22+DG23+DH21+DH22-16)*Percapita/30*GC$4)))))) -> 0 | GD21: =IF(C21=4,SUM(DI21+DI22+DI23+DK21+DK22+DK23)*Percapita/30*GD$4+(DJ21+DJ22+DJ23+DL21+DL22+DL23)*Cadeirante/30*GD$4,IF(C21=3,IF(DI24+DK24=10,Fixo/30*GD$4+(DI21+DI22+DI23+DK21+DK22+DK23)*Percapita/30*GD$4+(DJ24+DL24)*Cadeirante/30*GD$4,IF(DI24+DK24<=9,(DI24+DK24)*Crechee/30*GD$4)+(DJ24+DL24)*Cadeirante/30*GD$4+(DI21+DI22+DI23+DK21+DK22+DK23)*Percapita/30*GD$4)+IF(DI24+DK24>=11,Fixo/30*GD$4+(DI24+DK24-10)*Crechee/30*GD$4,0),IF(C21=2,IF(DJ21+DJ22+DJ23+DJ24+DL21+DL22+DL23+DL24=1,Cadeirante/30*GD$4,IF(DJ21+DJ22+DJ23+DJ24+DL21+DL22+DL23+DL24=2,Fixo/30*GD$4,IF(DJ21+DJ22+DJ23+DJ24+DL21+DL22+DL23+DL24>2,Fixo/30*GD$4+(DJ21+DJ22+DJ23+DJ24+DL21+DL22+DL23+DL24-2)*Cadeirante/30*GD$4)))+(DI21+DI22+DI23+DK21+DK22+DK23)*Percapita/30*GD$4+(DI24+DK24)*Crechee/30*GD$4,IF(C21=1,IF(DI21+DI22+DI23+DJ21+DJ22+DJ23+DK21+DK22+DK23+DL21+DL22+DL23<=15,(DI21+DI22+DI23+DK21+DK22+DK23)*Percapita/30*GD$4,IF(DI21+DI22+DI23+DJ21+DJ22+DJ23+DK21+DK22+DK23+DL21+DL22+DL23>=16,Fixo/30*GD$4+(DI21+DI22+DI23+DJ21+DJ22+DJ23+DK21+DK22+DK23+DL21+DL22-16)*Percapita/30*GD$4)))))) -> 0 | GE21: =IF(C21=4,SUM(DM21+DM22+DM23+DO21+DO22+DO23)*Percapita/30*GE$4+(DN21+DN22+DN23+DP21+DP22+DP23)*Cadeirante/30*GE$4,IF(C21=3,IF(DM24+DO24=10,Fixo/30*GE$4+(DM21+DM22+DM23+DO21+DO22+DO23)*Percapita/30*GE$4+(DN24+DP24)*Cadeirante/30*GE$4,IF(DM24+DO24<=9,(DM24+DO24)*Crechee/30*GE$4)+(DN24+DP24)*Cadeirante/30*GE$4+(DM21+DM22+DM23+DO21+DO22+DO23)*Percapita/30*GE$4)+IF(DM24+DO24>=11,Fixo/30*GE$4+(DM24+DO24-10)*Crechee/30*GE$4,0),IF(C21=2,IF(DN21+DN22+DN23+DN24+DP21+DP22+DP23+DP24=1,Cadeirante/30*GE$4,IF(DN21+DN22+DN23+DN24+DP21+DP22+DP23+DP24=2,Fixo/30*GE$4,IF(DN21+DN22+DN23+DN24+DP21+DP22+DP23+DP24>2,Fixo/30*GE$4+(DN21+DN22+DN23+DN24+DP21+DP22+DP23+DP24-2)*Cadeirante/30*GE$4)))+(DM21+DM22+DM23+DO21+DO22+DO23)*Percapita/30*GE$4+(DM24+DO24)*Crechee/30*GE$4,IF(C21=1,IF(DM21+DM22+DM23+DN21+DN22+DN23+DO21+DO22+DO23+DP21+DP22+DP23<=15,(DM21+DM22+DM23+DO21+DO22+DO23)*Percapita/30*GE$4,IF(DM21+DM22+DM23+DN21+DN22+DN23+DO21+DO22+DO23+DP21+DP22+DP23>=16,Fixo/30*GE$4+(DM21+DM22+DM23+DN21+DN22+DN23+DO21+DO22+DO23+DP21+DP22-16)*Percapita/30*GE$4)))))) -> 0 | GF21: =IF(C21=4,SUM(DQ21+DQ22+DQ23+DS21+DS22+DS23)*Percapita/30*GF$4+(DR21+DR22+DR23+DT21+DT22+DT23)*Cadeirante/30*GF$4,IF(C21=3,IF(DQ24+DS24=10,Fixo/30*GF$4+(DQ21+DQ22+DQ23+DS21+DS22+DS23)*Percapita/30*GF$4+(DR24+DT24)*Cadeirante/30*GF$4,IF(DQ24+DS24<=9,(DQ24+DS24)*Crechee/30*GF$4)+(DR24+DT24)*Cadeirante/30*GF$4+(DQ21+DQ22+DQ23+DS21+DS22+DS23)*Percapita/30*GF$4)+IF(DQ24+DS24>=11,Fixo/30*GF$4+(DQ24+DS24-10)*Crechee/30*GF$4,0),IF(C21=2,IF(DR21+DR22+DR23+DR24+DT21+DT22+DT23+DT24=1,Cadeirante/30*GF$4,IF(DR21+DR22+DR23+DR24+DT21+DT22+DT23+DT24=2,Fixo/30*GF$4,IF(DR21+DR22+DR23+DR24+DT21+DT22+DT23+DT24>2,Fixo/30*GF$4+(DR21+DR22+DR23+DR24+DT21+DT22+DT23+DT24-2)*Cadeirante/30*GF$4)))+(DQ21+DQ22+DQ23+DS21+DS22+DS23)*Percapita/30*GF$4+(DQ24+DS24)*Crechee/30*GF$4,IF(C21=1,IF(DQ21+DQ22+DQ23+DR21+DR22+DR23+DS21+DS22+DS23+DT21+DT22+DT23<=15,(DQ21+DQ22+DQ23+DS21+DS22+DS23)*Percapita/30*GF$4,IF(DQ21+DQ22+DQ23+DR21+DR22+DR23+DS21+DS22+DS23+DT21+DT22+DT23>=16,Fixo/30*GF$4+(DQ21+DQ22+DQ23+DR21+DR22+DR23+DS21+DS22+DS23+DT21+DT22-16)*Percapita/30*GF$4)))))) -> 0 | GG21: =IF(C21=4,SUM(DU21+DU22+DU23+DW21+DW22+DW23)*Percapita/30*GG$4+(DV21+DV22+DV23+DX21+DX22+DX23)*Cadeirante/30*GG$4,IF(C21=3,IF(DU24+DW24=10,Fixo/30*GG$4+(DU21+DU22+DU23+DW21+DW22+DW23)*Percapita/30*GG$4+(DV24+DX24)*Cadeirante/30*GG$4,IF(DU24+DW24<=9,(DU24+DW24)*Crechee/30*GG$4)+(DV24+DX24)*Cadeirante/30*GG$4+(DU21+DU22+DU23+DW21+DW22+DW23)*Percapita/30*GG$4)+IF(DU24+DW24>=11,Fixo/30*GG$4+(DU24+DW24-10)*Crechee/30*GG$4,0),IF(C21=2,IF(DV21+DV22+DV23+DV24+DX21+DX22+DX23+DX24=1,Cadeirante/30*GG$4,IF(DV21+DV22+DV23+DV24+DX21+DX22+DX23+DX24=2,Fixo/30*GG$4,IF(DV21+DV22+DV23+DV24+DX21+DX22+DX23+DX24>2,Fixo/30*GG$4+(DV21+DV22+DV23+DV24+DX21+DX22+DX23+DX24-2)*Cadeirante/30*GG$4)))+(DU21+DU22+DU23+DW21+DW22+DW23)*Percapita/30*GG$4+(DU24+DW24)*Crechee/30*GG$4,IF(C21=1,IF(DU21+DU22+DU23+DV21+DV22+DV23+DW21+DW22+DW23+DX21+DX22+DX23<=15,(DU21+DU22+DU23+DW21+DW22+DW23)*Percapita/30*GG$4,IF(DU21+DU22+DU23+DV21+DV22+DV23+DW21+DW22+DW23+DX21+DX22+DX23>=16,Fixo/30*GG$4+(DU21+DU22+DU23+DV21+DV22+DV23+DW21+DW22+DW23+DX21+DX22-16)*Percapita/30*GG$4)))))) -> 0 | GH21: =IF(C21=4,SUM(DY21+DY22+DY23+EA21+EA22+EA23)*Percapita/30*GH$4+(DZ21+DZ22+DZ23+EB21+EB22+EB23)*Cadeirante/30*GH$4,IF(C21=3,IF(DY24+EA24=10,Fixo/30*GH$4+(DY21+DY22+DY23+EA21+EA22+EA23)*Percapita/30*GH$4+(DZ24+EB24)*Cadeirante/30*GH$4,IF(DY24+EA24<=9,(DY24+EA24)*Crechee/30*GH$4)+(DZ24+EB24)*Cadeirante/30*GH$4+(DY21+DY22+DY23+EA21+EA22+EA23)*Percapita/30*GH$4)+IF(DY24+EA24>=11,Fixo/30*GH$4+(DY24+EA24-10)*Crechee/30*GH$4,0),IF(C21=2,IF(DZ21+DZ22+DZ23+DZ24+EB21+EB22+EB23+EB24=1,Cadeirante/30*GH$4,IF(DZ21+DZ22+DZ23+DZ24+EB21+EB22+EB23+EB24=2,Fixo/30*GH$4,IF(DZ21+DZ22+DZ23+DZ24+EB21+EB22+EB23+EB24>2,Fixo/30*GH$4+(DZ21+DZ22+DZ23+DZ24+EB21+EB22+EB23+EB24-2)*Cadeirante/30*GH$4)))+(DY21+DY22+DY23+EA21+EA22+EA23)*Percapita/30*GH$4+(DY24+EA24)*Crechee/30*GH$4,IF(C21=1,IF(DY21+DY22+DY23+DZ21+DZ22+DZ23+EA21+EA22+EA23+EB21+EB22+EB23<=15,(DY21+DY22+DY23+EA21+EA22+EA23)*Percapita/30*GH$4,IF(DY21+DY22+DY23+DZ21+DZ22+DZ23+EA21+EA22+EA23+EB21+EB22+EB23>=16,Fixo/30*GH$4+(DY21+DY22+DY23+DZ21+DZ22+DZ23+EA21+EA22+EA23+EB21+EB22-16)*Percapita/30*GH$4)))))) -> 25.682 | GI21: =IF(C21=4,SUM(EC21+EC22+EC23+EE21+EE22+EE23)*Percapita/30*GI$4+(ED21+ED22+ED23+EF21+EF22+EF23)*Cadeirante/30*GI$4,IF(C21=3,IF(EC24+EE24=10,Fixo/30*GI$4+(EC21+EC22+EC23+EE21+EE22+EE23)*Percapita/30*GI$4+(ED24+EF24)*Cadeirante/30*GI$4,IF(EC24+EE24<=9,(EC24+EE24)*Crechee/30*GI$4)+(ED24+EF24)*Cadeirante/30*GI$4+(EC21+EC22+EC23+EE21+EE22+EE23)*Percapita/30*GI$4)+IF(EC24+EE24>=11,Fixo/30*GI$4+(EC24+EE24-10)*Crechee/30*GI$4,0),IF(C21=2,IF(ED21+ED22+ED23+ED24+EF21+EF22+EF23+EF24=1,Cadeirante/30*GI$4,IF(ED21+ED22+ED23+ED24+EF21+EF22+EF23+EF24=2,Fixo/30*GI$4,IF(ED21+ED22+ED23+ED24+EF21+EF22+EF23+EF24>2,Fixo/30*GI$4+(ED21+ED22+ED23+ED24+EF21+EF22+EF23+EF24-2)*Cadeirante/30*GI$4)))+(EC21+EC22+EC23+EE21+EE22+EE23)*Percapita/30*GI$4+(EC24+EE24)*Crechee/30*GI$4,IF(C21=1,IF(EC21+EC22+EC23+ED21+ED22+ED23+EE21+EE22+EE23+EF21+EF22+EF23<=15,(EC21+EC22+EC23+EE21+EE22+EE23)*Percapita/30*GI$4,IF(EC21+EC22+EC23+ED21+ED22+ED23+EE21+EE22+EE23+EF21+EF22+EF23>=16,Fixo/30*GI$4+(EC21+EC22+EC23+ED21+ED22+ED23+EE21+EE22+EE23+EF21+EF22-16)*Percapita/30*GI$4)))))) -> 0 | GJ21: =IF(C21=4,SUM(EG21+EG22+EG23+EI21+EI22+EI23)*Percapita/30*GJ$4+(EH21+EH22+EH23+EJ21+EJ22+EJ23)*Cadeirante/30*GJ$4,IF(C21=3,IF(EG24+EI24=10,Fixo/30*GJ$4+(EG21+EG22+EG23+EI21+EI22+EI23)*Percapita/30*GJ$4+(EH24+EJ24)*Cadeirante/30*GJ$4,IF(EG24+EI24<=9,(EG24+EI24)*Crechee/30*GJ$4)+(EH24+EJ24)*Cadeirante/30*GJ$4+(EG21+EG22+EG23+EI21+EI22+EI23)*Percapita/30*GJ$4)+IF(EG24+EI24>=11,Fixo/30*GJ$4+(EG24+EI24-10)*Crechee/30*GJ$4,0),IF(C21=2,IF(EH21+EH22+EH23+EH24+EJ21+EJ22+EJ23+EJ24=1,Cadeirante/30*GJ$4,IF(EH21+EH22+EH23+EH24+EJ21+EJ22+EJ23+EJ24=2,Fixo/30*GJ$4,IF(EH21+EH22+EH23+EH24+EJ21+EJ22+EJ23+EJ24>2,Fixo/30*GJ$4+(EH21+EH22+EH23+EH24+EJ21+EJ22+EJ23+EJ24-2)*Cadeirante/30*GJ$4)))+(EG21+EG22+EG23+EI21+EI22+EI23)*Percapita/30*GJ$4+(EG24+EI24)*Crechee/30*GJ$4,IF(C21=1,IF(EG21+EG22+EG23+EH21+EH22+EH23+EI21+EI22+EI23+EJ21+EJ22+EJ23<=15,(EG21+EG22+EG23+EI21+EI22+EI23)*Percapita/30*GJ$4,IF(EG21+EG22+EG23+EH21+EH22+EH23+EI21+EI22+EI23+EJ21+EJ22+EJ23>=16,Fixo/30*GJ$4+(EG21+EG22+EG23+EH21+EH22+EH23+EI21+EI22+EI23+EJ21+EJ22-16)*Percapita/30*GJ$4)))))) -> 0 | GL21: =IF(J21="ADAPTADO",T21*Cadeirante/30*GM21+S21*Percapita/30*GM21,IF(J21="NORMAL",(S21+T21)*Percapita/30*GM21,IF(J21="CRECHE",0)))*-1 -> 0 | GN21: =SUMIF(V21:V24,"<0")*Cadeirante/30*GN$4+SUMIF(X21:X24,"<0")*Cadeirante/30*GN$4 -> 0 | GO21: =SUMIF(Z21:Z24,"<0")*Cadeirante/30*GO$4+SUMIF(AB21:AB24,"<0")*Cadeirante/30*GO$4 -> 0 | GP21: =SUMIF(AD21:AD24,"<0")*Cadeirante/30*GP$4+SUMIF(AF21:AF24,"<0")*Cadeirante/30*GP$4 -> 0 | GQ21: =SUMIF(AH21:AH24,"<0")*Cadeirante/30*GQ$4+SUMIF(AJ21:AJ24,"<0")*Cadeirante/30*GQ$4 -> 0 | GR21: =SUMIF(AL21:AL24,"<0")*Cadeirante/30*GR$4+SUMIF(AN21:AN24,"<0")*Cadeirante/30*GR$4 -> 0 | GS21: =SUMIF(AP21:AP24,"<0")*Cadeirante/30*GS$4+SUMIF(AR21:AR24,"<0")*Cadeirante/30*GS$4 -> 0 | GT21: =SUMIF(AT21:AT24,"<0")*Cadeirante/30*GT$4+SUMIF(AV21:AV24,"<0")*Cadeirante/30*GT$4 -> 0 | GU21: =SUMIF(AX21:AX24,"<0")*Cadeirante/30*GU$4+SUMIF(AZ21:AZ24,"<0")*Cadeirante/30*GU$4 -> 0 | GV21: =SUMIF(BB21:BB24,"<0")*Cadeirante/30*GV$4+SUMIF(BD21:BD24,"<0")*Cadeirante/30*GV$4 -> 0 | GW21: =SUMIF(BF21:BF24,"<0")*Cadeirante/30*GW$4+SUMIF(BH21:BH24,"<0")*Cadeirante/30*GW$4 -> 0 | GX21: =SUMIF(BJ21:BJ24,"<0")*Cadeirante/30*GX$4+SUMIF(BL21:BL24,"<0")*Cadeirante/30*GX$4 -> 0 | GY21: =SUMIF(BN21:BN24,"<0")*Cadeirante/30*GY$4+SUMIF(BP21:BP24,"<0")*Cadeirante/30*GY$4 -> 0 | GZ21: =SUMIF(BR21:BR24,"<0")*Cadeirante/30*GZ$4+SUMIF(BT21:BT24,"<0")*Cadeirante/30*GZ$4 -> 0 | HA21: =SUMIF(BV21:BV24,"<0")*Cadeirante/30*HA$4+SUMIF(BX21:BX24,"<0")*Cadeirante/30*HA$4 -> 0 | HB21: =SUMIF(BZ21:BZ24,"<0")*Cadeirante/30*HB$4+SUMIF(CB21:CB24,"<0")*Cadeirante/30*HB$4 -> 0 | HC21: =SUMIF(CD21:CD24,"<0")*Cadeirante/30*HC$4+SUMIF(CF21:CF24,"<0")*Cadeirante/30*HC$4 -> 0 | HD21: =SUMIF(CH21:CH24,"<0")*Cadeirante/30*HD$4+SUMIF(CJ21:CJ24,"<0")*Cadeirante/30*HD$4 -> 0 | HE21: =SUMIF(CL21:CL24,"<0")*Cadeirante/30*HE$4+SUMIF(CN21:CN24,"<0")*Cadeirante/30*HE$4 -> 0 | HF21: =SUMIF(CP21:CP24,"<0")*Cadeirante/30*HF$4+SUMIF(CR21:CR24,"<0")*Cadeirante/30*HF$4 -> 0 | HG21: =SUMIF(CT21:CT24,"<0")*Cadeirante/30*HG$4+SUMIF(CV21:CV24,"<0")*Cadeirante/30*HG$4 -> 0 | HH21: =SUMIF(CX21:CX24,"<0")*Cadeirante/30*HH$4+SUMIF(CZ21:CZ24,"<0")*Cadeirante/30*HH$4 -> 0 | HI21: =SUMIF(DB21:DB24,"<0")*Cadeirante/30*HI$4+SUMIF(DD21:DD24,"<0")*Cadeirante/30*HI$4 -> 0 | HJ21: =SUMIF(DF21:DF24,"<0")*Cadeirante/30*HJ$4+SUMIF(DH21:DH24,"<0")*Cadeirante/30*HJ$4 -> 0 | HK21: =SUMIF(DJ21:DJ24,"<0")*Cadeirante/30*HK$4+SUMIF(DL21:DL24,"<0")*Cadeirante/30*HK$4 -> 0 | HL21: =SUMIF(DN21:DN24,"<0")*Cadeirante/30*HL$4+SUMIF(DP21:DP24,"<0")*Cadeirante/30*HL$4 -> 0 | HM21: =SUMIF(DR21:DR24,"<0")*Cadeirante/30*HM$4+SUMIF(DT21:DT24,"<0")*Cadeirante/30*HM$4 -> 0 | HN21: =SUMIF(DV21:DV24,"<0")*Cadeirante/30*HN$4+SUMIF(DX21:DX24,"<0")*Cadeirante/30*HN$4 -> 0 | HO21: =SUMIF(DZ21:DZ24,"<0")*Cadeirante/30*HO$4+SUMIF(EB21:EB24,"<0")*Cadeirante/30*HO$4 -> 0 | HP21: =SUMIF(ED21:ED24,"<0")*Cadeirante/30*HP$4+SUMIF(EF21:EF24,"<0")*Cadeirante/30*HP$4 -> 0 | HW21: 17629.31 | HY21: =IF(ISTEXT(EM21), VALUE(EM21), EM21) -> 0 | HZ21: =IF(ISTEXT(EN21), VALUE(EN21), EN21) -> 0 | IA21: =IF(ISTEXT(EO21), VALUE(EO21), EO21) -> 0 | IB21: =HW21=FE21 -> FALSE
A22: 048.899-00 | B22: 2023/0019748-001A | C22: BT | D22: 2023/0019748 | E22: CYR9B26 | F22: 01/04/2026 | G22: 30/04/2026 | H22: AME TRANSPORTE LTDA | I22: DORIS BATISTA ELIAS | J22: NORMAL | K22: EMEF | L22: =CONTINUA!BV22 -> 0 | M22: =CONTINUA!BW22 -> 0 | O22: 6020.2023/0019748-3 | P22: O | Q22: 40 | DY22: 1 | EP22: =Q22 -> 40 | EQ22: =U22+Y22+AC22+AG22+AK22+AO22+AS22+AW22+BA22+BE22+BI22+BM22+BQ22+BU22+BY22+CC22+CG22+CK22+CO22+CS22+CW22+DA22+DE22+DI22+DM22+DQ22+DU22+DY22+EC22+EG22 -> 1 | ER22: =S22+W22+AA22+AE22+AI22+AM22+AQ22+AU22+AY22+BC22+BG22+BK22+BO22+BS22+BW22+CA22+CE22+CI22+CM22+CQ22+CU22+CY22+DC22+DG22+DK22+DO22+DS22+DW22+EA22+EE22+EI22 -> 0 | ES22: =R22 -> 0 | ET22: =V22+Z22+AD22+AH22+AL22+AP22+AT22+AX22+BB22+BF22+BJ22+BN22+BR22+BV22+BZ22+CD22+CH22+CL22+CP22+CT22+CX22+DB22+DF22+DJ22+DN22+DR22+DV22+DZ22+ED22+EH22 -> 0 | EU22: =T22+X22+AB22+AF22+AJ22+AN22+AR22+AV22+AZ22+BD22+BH22+BL22+BP22+BT22+BX22+CB22+CF22+CJ22+CN22+CR22+CV22+CZ22+DD22+DH22+DL22+DP22+DT22+DX22+EB22+EF22+EJ22 -> 0 | EV22: =EP22+EQ22+ES22+ET22+ER22+EU22 -> 41 | EX22: =FF22 -> 0 | EY22: =(L22*regular)+(M22*Cadeirantee) -> 0 | EZ22: =SUMIF(FG22:GJ22,">0") -> 0 | FA22: =SUMIF(FG22:GJ22,"<0")+SUMIF(GN22:HP22,"<0") -> 0 | FB22: 0 | FC22: =N22*km*'VALORES TABELA'!$B$13 -> 0 | FD22: =GL22 -> 0 | GL22: =IF(J22="ADAPTADO",T22*Cadeirante/30*GM22+S22*Percapita/30*GM22,IF(J22="NORMAL",(S22+T22)*Percapita/30*GM22,IF(J22="CRECHE",0)))*-1 -> 0 | HY22: =IF(ISTEXT(EM22), VALUE(EM22), EM22) -> 0 | HZ22: =IF(ISTEXT(EN22), VALUE(EN22), EN22) -> 0 | IA22: =IF(ISTEXT(EO22), VALUE(EO22), EO22) -> 0
A23: 048.899-00 | B23: 2023/0019748-001A | C23: BT | D23: 2023/0019748 | E23: CYR9B26 | F23: 01/04/2026 | G23: 30/04/2026 | H23: AME TRANSPORTE LTDA | I23: DORIS BATISTA ELIAS | J23: NORMAL | K23: EMEE | L23: =CONTINUA!BV23 -> 0 | M23: =CONTINUA!BW23 -> 0 | O23: 6020.2023/0019748-3 | P23: O | EP23: =Q23 -> 0 | EQ23: =U23+Y23+AC23+AG23+AK23+AO23+AS23+AW23+BA23+BE23+BI23+BM23+BQ23+BU23+BY23+CC23+CG23+CK23+CO23+CS23+CW23+DA23+DE23+DI23+DM23+DQ23+DU23+DY23+EC23+EG23 -> 0 | ER23: =S23+W23+AA23+AE23+AI23+AM23+AQ23+AU23+AY23+BC23+BG23+BK23+BO23+BS23+BW23+CA23+CE23+CI23+CM23+CQ23+CU23+CY23+DC23+DG23+DK23+DO23+DS23+DW23+EA23+EE23+EI23 -> 0 | ES23: =R23 -> 0 | ET23: =V23+Z23+AD23+AH23+AL23+AP23+AT23+AX23+BB23+BF23+BJ23+BN23+BR23+BV23+BZ23+CD23+CH23+CL23+CP23+CT23+CX23+DB23+DF23+DJ23+DN23+DR23+DV23+DZ23+ED23+EH23 -> 0 | EU23: =T23+X23+AB23+AF23+AJ23+AN23+AR23+AV23+AZ23+BD23+BH23+BL23+BP23+BT23+BX23+CB23+CF23+CJ23+CN23+CR23+CV23+CZ23+DD23+DH23+DL23+DP23+DT23+DX23+EB23+EF23+EJ23 -> 0 | EV23: =EP23+EQ23+ES23+ET23+ER23+EU23 -> 0 | EX23: =FF23 -> 0 | EY23: =(L23*regular)+(M23*Cadeirantee) -> 0 | EZ23: =SUMIF(FG23:GJ23,">0") -> 0 | FA23: =SUMIF(FG23:GJ23,"<0")+SUMIF(GN23:HP23,"<0") -> 0 | FB23: 0 | FC23: =N23*km*'VALORES TABELA'!$B$13 -> 0 | FD23: =GL23 -> 0 | GL23: =IF(J23="ADAPTADO",T23*Cadeirante/30*GM23+S23*Percapita/30*GM23,IF(J23="NORMAL",(S23+T23)*Percapita/30*GM23,IF(J23="CRECHE",0)))*-1 -> 0 | HY23: =IF(ISTEXT(EM23), VALUE(EM23), EM23) -> 0 | HZ23: =IF(ISTEXT(EN23), VALUE(EN23), EN23) -> 0 | IA23: =IF(ISTEXT(EO23), VALUE(EO23), EO23) -> 0
A24: 048.899-00 | B24: 2023/0019748-001A | C24: BT | D24: 2023/0019748 | E24: CYR9B26 | F24: 01/04/2026 | G24: 30/04/2026 | H24: AME TRANSPORTE LTDA | I24: DORIS BATISTA ELIAS | J24: NORMAL | K24: CEI | L24: =CONTINUA!BV24 -> 0 | M24: =CONTINUA!BW24 -> 0 | O24: 6020.2023/0019748-3 | P24: O | EP24: =Q24 -> 0 | EQ24: =U24+Y24+AC24+AG24+AK24+AO24+AS24+AW24+BA24+BE24+BI24+BM24+BQ24+BU24+BY24+CC24+CG24+CK24+CO24+CS24+CW24+DA24+DE24+DI24+DM24+DQ24+DU24+DY24+EC24+EG24 -> 0 | ER24: =S24+W24+AA24+AE24+AI24+AM24+AQ24+AU24+AY24+BC24+BG24+BK24+BO24+BS24+BW24+CA24+CE24+CI24+CM24+CQ24+CU24+CY24+DC24+DG24+DK24+DO24+DS24+DW24+EA24+EE24+EI24 -> 0 | ES24: =R24 -> 0 | ET24: =V24+Z24+AD24+AH24+AL24+AP24+AT24+AX24+BB24+BF24+BJ24+BN24+BR24+BV24+BZ24+CD24+CH24+CL24+CP24+CT24+CX24+DB24+DF24+DJ24+DN24+DR24+DV24+DZ24+ED24+EH24 -> 0 | EU24: =T24+X24+AB24+AF24+AJ24+AN24+AR24+AV24+AZ24+BD24+BH24+BL24+BP24+BT24+BX24+CB24+CF24+CJ24+CN24+CR24+CV24+CZ24+DD24+DH24+DL24+DP24+DT24+DX24+EB24+EF24+EJ24 -> 0 | EV24: =EP24+EQ24+ES24+ET24+ER24+EU24 -> 0 | EX24: =FF24 -> 0 | EY24: =(L24*regular)+(M24*Cadeirantee) -> 0 | EZ24: =SUMIF(FG24:GJ24,">0") -> 0 | FA24: =SUMIF(FG24:GJ24,"<0")+SUMIF(GN24:HP24,"<0") -> 0 | FB24: 0 | FC24: =N24*km*'VALORES TABELA'!$B$13 -> 0 | FD24: =GL24 -> 0 | GL24: =IF(J24="ADAPTADO",T24*Cadeirante/30*GM24+S24*Percapita/30*GM24,IF(J24="NORMAL",(S24+T24)*Percapita/30*GM24,IF(J24="CRECHE",0)))*-1 -> 0 | HY24: =IF(ISTEXT(EM24), VALUE(EM24), EM24) -> 0 | HZ24: =IF(ISTEXT(EN24), VALUE(EN24), EN24) -> 0 | IA24: =IF(ISTEXT(EO24), VALUE(EO24), EO24) -> 0
A25: 048.899-00 | B25: 2023/0019748-001A | C25: BT | D25: 2023/0019748 | E25: CYR9B26 | F25: 01/04/2026 | G25: 30/04/2026 | H25: AME TRANSPORTE LTDA | I25: DORIS BATISTA ELIAS | J25: NORMAL | K25: CCA | L25: =CONTINUA!BV25 -> 0 | M25: =CONTINUA!BW25 -> 0 | O25: 6020.2023/0019748-3 | P25: O | EP25: =Q25 -> 0 | EQ25: =U25+Y25+AC25+AG25+AK25+AO25+AS25+AW25+BA25+BE25+BI25+BM25+BQ25+BU25+BY25+CC25+CG25+CK25+CO25+CS25+CW25+DA25+DE25+DI25+DM25+DQ25+DU25+DY25+EC25+EG25 -> 0 | ER25: =S25+W25+AA25+AE25+AI25+AM25+AQ25+AU25+AY25+BC25+BG25+BK25+BO25+BS25+BW25+CA25+CE25+CI25+CM25+CQ25+CU25+CY25+DC25+DG25+DK25+DO25+DS25+DW25+EA25+EE25+EI25 -> 0 | ES25: =R25 -> 0 | ET25: =V25+Z25+AD25+AH25+AL25+AP25+AT25+AX25+BB25+BF25+BJ25+BN25+BR25+BV25+BZ25+CD25+CH25+CL25+CP25+CT25+CX25+DB25+DF25+DJ25+DN25+DR25+DV25+DZ25+ED25+EH25 -> 0 | EU25: =T25+X25+AB25+AF25+AJ25+AN25+AR25+AV25+AZ25+BD25+BH25+BL25+BP25+BT25+BX25+CB25+CF25+CJ25+CN25+CR25+CV25+CZ25+DD25+DH25+DL25+DP25+DT25+DX25+EB25+EF25+EJ25 -> 0 | EV25: =EP25+EQ25+ES25+ET25+ER25+EU25 -> 0 | EX25: 0 | EY25: 0 | EZ25: 0 | FA25: 0 | FB25: =SUM(FF25:GI25)/2 -> 0 | FC25: =N25*km*'VALORES TABELA'!$B$13 -> 0 | FD25: =GL25 -> 0 | FF25: =((Q25+S25)*Percapita)+((R25+T25)*Cadeirante) -> 0 | FG25: =((U25+W25)*Percapita/30*FG$4)+((V25+X25)*Cadeirante/30*FG$4) -> 0 | FH25: =((Y25+AA25)*Percapita/30*FH$4)+((Z25+AB25)*Cadeirante/30*FH$4) -> 0 | FI25: =((AC25+AE25)*Percapita/30*FI$4)+((AD25+AF25)*Cadeirante/30*FI$4) -> 0 | FJ25: =((AG25+AI25)*Percapita/30*FJ$4)+((AH25+AJ25)*Cadeirante/30*FJ$4) -> 0 | FK25: =((AK25+AM25)*Percapita/30*FK$4)+((AL25+AN25)*Cadeirante/30*FK$4) -> 0 | FL25: =((AO25+AQ25)*Percapita/30*FL$4)+((AP25+AR25)*Cadeirante/30*FL$4) -> 0 | FM25: =((AS25+AU25)*Percapita/30*FM$4)+((AT25+AV25)*Cadeirante/30*FM$4) -> 0 | FN25: =((AW25+AY25)*Percapita/30*FN$4)+((AX25+AZ25)*Cadeirante/30*FN$4) -> 0 | FO25: =((BA25+BC25)*Percapita/30*FO$4)+((BB25+BD25)*Cadeirante/30*FO$4) -> 0 | FP25: =((BE25+BG25)*Percapita/30*FP$4)+((BF25+BH25)*Cadeirante/30*FP$4) -> 0 | FQ25: =((BI25+BK25)*Percapita/30*FQ$4)+((BJ25+BL25)*Cadeirante/30*FQ$4) -> 0 | FR25: =((BM25+BO25)*Percapita/30*FR$4)+((BN25+BP25)*Cadeirante/30*FR$4) -> 0 | FS25: =((BQ25+BS25)*Percapita/30*FS$4)+((BR25+BT25)*Cadeirante/30*FS$4) -> 0 | FT25: =((BU25+BW25)*Percapita/30*FT$4)+((BV25+BX25)*Cadeirante/30*FT$4) -> 0 | FU25: =((BY25+CA25)*Percapita/30*FU$4)+((BZ25+CB25)*Cadeirante/30*FU$4) -> 0 | FV25: =((CC25+CE25)*Percapita/30*FV$4)+((CD25+CF25)*Cadeirante/30*FV$4) -> 0 | FW25: =((CG25+CI25)*Percapita/30*FW$4)+((CI25+CK25)*Cadeirante/30*FW$4) -> 0 | FX25: =((CK25+CM25)*Percapita/30*FX$4)+((CL25+CN25)*Cadeirante/30*FX$4) -> 0 | FY25: =((CO25+CQ25)*Percapita/30*FY$4)+((CP25+CR25)*Cadeirante/30*FY$4) -> 0 | FZ25: =((CS25+CU25)*Percapita/30*FZ$4)+((CT25+CV25)*Cadeirante/30*FZ$4) -> 0 | GA25: =((CW25+CY25)*Percapita/30*GA$4)+((CX25+CZ25)*Cadeirante/30*GA$4) -> 0 | GB25: =((DA25+DC25)*Percapita/30*GB$4)+((DB25+DD25)*Cadeirante/30*GB$4) -> 0 | GC25: =((DE25+DG25)*Percapita/30*GC$4)+((DF25+DH25)*Cadeirante/30*GC$4) -> 0 | GD25: =((DI25+DK25)*Percapita/30*GD$4)+((DJ25+DL25)*Cadeirante/30*GD$4) -> 0 | GE25: =((DM25+DO25)*Percapita/30*GE$4)+((DN25+DP25)*Cadeirante/30*GE$4) -> 0 | GF25: =((DQ25+DS25)*Percapita/30*GF$4)+((DR25+DT25)*Cadeirante/30*GF$4) -> 0 | GG25: =((DU25+DW25)*Percapita/30*GG$4)+((DV25+DX25)*Cadeirante/30*GG$4) -> 0 | GH25: =((DY25+EA25)*Percapita/30*GH$4)+((DZ25+EB25)*Cadeirante/30*GH$4) -> 0 | GI25: =((EC25+EE25)*Percapita/30*GI$4)+((ED25+EF25)*Cadeirante/30*GI$4) -> 0 | GJ25: =((EG25+EI25)*Percapita)+((EH25+EJ25)*Cadeirante) -> 0 | GL25: =IF(J25="ADAPTADO",T25*Cadeirante/30*GM25+S25*Percapita/30*GM25,IF(J25="NORMAL",(S25+T25)*Percapita/30*GM25,IF(J25="CRECHE",0)))*-1 -> 0 | HY25: =IF(ISTEXT(EM25), VALUE(EM25), EM25) -> 0 | HZ25: =IF(ISTEXT(EN25), VALUE(EN25), EN25) -> 0 | IA25: =IF(ISTEXT(EO25), VALUE(EO25), EO25) -> 0
